Workbook

Sheet ★ぼんぼり戦略表
A2: ぼんぼり | B2: 45870 | C2: =MONTH(B2) -> 8
B3: =B15 -> 45892 | D3: =TEXT(B3, "aaa") -> 土
B4: 目標売上 | C4: =_xlfn.XLOOKUP(D3, B7:B12, C7:C12, "該当なし") -> 0
B6: 7月 曜日毎の目標売上 | D6: 傾向 | G6: 対策考察
B7: 月 | C7: =SUMIFS('2025(¥)'!$AE$22:$AE$104, '2025(¥)'!$AA$22:$AA$104, MONTH($B$2), '2025(¥)'!$AB$22:$AB$104, B7) -> 0 | D7: 意外と売上高め（法人接待 or 週始め会食？） | G7: 週始め利用促進で「月曜だけの一品」など限定打ち出しも有効
B8: 火 | C8: =SUMIFS('2025(¥)'!$AE$22:$AE$104, '2025(¥)'!$AA$22:$AA$104, MONTH($B$2), '2025(¥)'!$AB$22:$AB$104, B8) -> 0 | D8: 平均値付近でやや波あり | G8: 予約状況に応じて割引率の調整やSNSリマインド配信
B9: 水 | C9: =SUMIFS('2025(¥)'!$AE$22:$AE$104, '2025(¥)'!$AA$22:$AA$104, MONTH($B$2), '2025(¥)'!$AB$22:$AB$104, B9) -> 0 | D9: 最も売上が高く安定、大口予約が入りやすい傾向 | G9: コース・飲み放題準備強化／人員厚め配置を検討
B10: 木 | C10: =SUMIFS('2025(¥)'!$AE$22:$AE$104, '2025(¥)'!$AA$22:$AA$104, MONTH($B$2), '2025(¥)'!$AB$22:$AB$104, B10) -> 0 | D10: 週後半に売上が高まる流れ | G10: 平日限定キャンペーン（早割／ワンドリンク付）で集客拡張
B11: 金 | C11: =SUMIFS('2025(¥)'!$AE$22:$AE$104, '2025(¥)'!$AA$22:$AA$104, MONTH($B$2), '2025(¥)'!$AB$22:$AB$104, B11) -> 0 | D11: 週末需要で高水準安定 | G11: 新規客向けにGoogle口コミ促進（来店時カード配布）
B12: 土 | C12: =SUMIFS('2025(¥)'!$AE$22:$AE$104, '2025(¥)'!$AA$22:$AA$104, MONTH($B$2), '2025(¥)'!$AB$22:$AB$104, B12) -> 0 | D12: 週末は思ったよりも苦戦 | G12: 家族・若年層向け投稿（インスタで昼飲み・記念日訴求など）
B15: 45892 | C15: =TEXT(B15, "aaa") -> 土
A16: 日次 | B16: 売上 | C16: =_xlfn.XLOOKUP(B15, '2025(¥)'!F21:F385,'2025(¥)'!J21:J385,"該当なし") -> 114770 | E16: 月次目標売上 | F16: =INDEX('2025(¥)'!I7:I18, MATCH(MONTH(B2), '2025(¥)'!R7:R18, 0)) -> 5034965 | N16: 月 | O16: 傾向分析
B17: 平均目標売上 | C17: =INDEX('2025(¥)'!K7:K18, MATCH(C2, '2025(¥)'!R7:R18, 0)) -> 251748.25 | E17: 月次累計実績売上 | F17: =C22 -> 3248670
B18: 目標売上 | C18: =_xlfn.XLOOKUP(C15, B7:B12, C7:C12, "該当なし") -> 0 | E18: 差額 | F18: =F16-F17 -> 1786295 | N18: 1月 | O18: A: 月初・末が強い（中旬落ち）
B19: 差額 | C19: =C16-C18 -> 114770 | E19: 当月残営業日 | F19: {=(SUMPRODUCT(('2025(¥)'!F21:F385>=B15)*('2025(¥)'!E21:E385=C2)*('2025(¥)'!D21:D385=1)))-1} -> 6 | N19: 2月 | O19: B: 月末にかけて上がる
B20: 達成率 | C20: =IFERROR(C16/C18,0) -> 0 | E20: 今月1日あたりの目標売上 | F20: =IFERROR(F18/F19,0) -> 297715.84 | N20: 3月 | O20: B: 同様に右肩上がり傾向
N21: 4月 | O21: A: 月初も末も強く安定感あり
A22: 月次 | B22: 累積売上 | C22: =_xlfn.XLOOKUP(B15, '2025(¥)'!F21:F385,'2025(¥)'!Q21:Q385,"該当なし") -> 3248670 | N22: 5月 | O22: B: 徐々に上がる
B23: 累積目標売上 | C23: =_xlfn.XLOOKUP(B15, '2025(¥)'!F21:F385,'2025(¥)'!P21:P385,"該当なし") -> 3521812.2 | N23: 分類 | O23: 説明
B24: 差額 | C24: =C22-C23 -> -273142.16 | N24: A: 初・末が強い | O24: 月初・月末の売上が高く、中旬が落ちるパターン
B25: 達成率 | C25: =IFERROR(C22/C23,0) -> 0.92244272 | N25: B: 徐々に上がる | O25: 月初が弱く、末に向かって売上が上がる
N26: C: 平均的 or 中旬強い | O26: 大きな偏りがない or 中旬が強いパターン
A27: 年次 | B27: 累積売上 | C27: =_xlfn.XLOOKUP(B15, '2025(¥)'!F21:F385,'2025(¥)'!V21:V385,"該当なし") -> 45999488
B28: 累積目標売上 | C28: =_xlfn.XLOOKUP(B15, '2025(¥)'!F21:F385,'2025(¥)'!U21:U385,"該当なし") -> 44091043
B29: 差額 | C29: =C27-C28 -> 1908445.1
B30: 達成率 | C30: =IFERROR(C27/C28,0) -> 1.0432842
B32: 年次目標売上 | C32: ='2025(¥)'!G3 -> 72000000
B33: 目標達成までの残額 | C33: =C32-C27 -> 26000512
B34: 今年の残営業日数 | C34: {=(SUMPRODUCT(('2025(¥)'!F21:F385>=B15)*('2025(¥)'!D21:D385=1)))-1} -> 103
B35: 1日あたりの売上額 | C35: =IFERROR(C33/C34,0) -> 252432.15
B36: 年間達成率 | C36: =1-(C33/C32) -> 0.63888178
B38: 2025年7月の情報
B39: 曜日 | C39: 出現回数 | D39: 加重比率 | E39: 曜日別割当額 | F39: 1日あたり目標
B40: 月 | C40: 4 | D40: 0.1193 | E40: 894636 | F40: 223659
B41: 火 | C41: 5 | D41: 0.1404 | E41: 1053371 | F41: 210674
B42: 水 | C42: 5 | D42: 0.2035 | E42: 1526394 | F42: 305279
B43: 木 | C43: 5 | D43: 0.2281 | E43: 1710568 | F43: 342114
B44: 金 | C44: 4 | D44: 0.2189 | E44: 1641933 | F44: 410483
B45: 土 | C45: 4 | D45: 0.0897 | E45: 673097 | F45: 168274
B46: 日 | D46: 0 | E46: 0 | F46: 0
B47: 合計 | C47: =SUM(C40:C46) -> 27 | D47: 1 | E47: ¥7,500,000 ✔ | F47: —
A49: ぼんぼり | B49: 曜日 | C49: 売上 | D49: 平均目標売上 | E49: 曜日繁閑期目標売上 | F49: 差額 | G49: 達成率 | H49: 累積売上 | I49: 累積目標売上 | J49: 差額 | K49: 達成率
B50: =B2 -> 45870 | C50: 316470 | D50: =$C$17 -> 251748.25 | E50: =$C$8 -> 0 | F50: =C50-E50 -> 316470 | G50: =IFERROR(C50/E50,0) -> 0 | H50: =IF(C50=0,0,C50) -> 316470 | I50: =IF(C50=0,0,E50) -> 0 | J50: =H50-I50 -> 316470 | K50: =IFERROR(H50/I50,0) -> 0
B51: =B50+1 -> 45871 | C51: 347600 | D51: =$C$17 -> 251748.25 | E51: =$C$9 -> 0 | F51: =C51-E51 -> 347600 | G51: =IFERROR(C51/E51,0) -> 0 | H51: =IF(C51=0,0,(H50+C51)) -> 664070 | I51: =IF(C51=0,0,(I50+E51)) -> 0 | J51: =H51-I51 -> 664070 | K51: =IFERROR(H51/I51,0) -> 0
B52: =B51+1 -> 45872 | C52: 221970 | D52: =$C$17 -> 251748.25 | E52: =$C$10 -> 0 | F52: =C52-E52 -> 221970 | G52: =IFERROR(C52/E52,0) -> 0 | H52: =IF(C52=0,0,(H51+C52)) -> 886040 | I52: =IF(C52=0,0,(I51+E52)) -> 0 | J52: =H52-I52 -> 886040 | K52: =IFERROR(H52/I52,0) -> 0
B53: =B52+1 -> 45873 | C53: 329910 | D53: =$C$17 -> 251748.25 | E53: =$C$11 -> 0 | F53: =C53-E53 -> 329910 | G53: =IFERROR(C53/E53,0) -> 0 | H53: =IF(C53=0,0,(H52+C53)) -> 1215950 | I53: =IF(C53=0,0,(I52+E53)) -> 0 | J53: =H53-I53 -> 1215950 | K53: =IFERROR(H53/I53,0) -> 0
B54: =B53+1 -> 45874 | C54: 76330 | D54: =$C$17 -> 251748.25 | E54: =$C$12 -> 0 | F54: =C54-E54 -> 76330 | G54: =IFERROR(C54/E54,0) -> 0 | H54: =IF(C54=0,0,(H53+C54)) -> 1292280 | I54: =IF(C54=0,0,(I53+E54)) -> 0 | J54: =H54-I54 -> 1292280 | K54: =IFERROR(H54/I54,0) -> 0
B55: =B54+1 -> 45875 | D55: 0 | F55: =C55-E55 -> 0 | G55: =IFERROR(C55/E55,0) -> 0 | H55: =IF(C55=0,0,(H54+C55)) -> 0 | I55: =IF(C55=0,0,(I54+E55)) -> 0 | J55: =H55-I55 -> 0 | K55: =IFERROR(H55/I55,0) -> 0
B56: =B55+1 -> 45876 | C56: 94600 | D56: =$C$17 -> 251748.25 | E56: =$C$7 -> 0 | F56: =C56-E56 -> 94600 | G56: =IFERROR(C56/E56,0) -> 0 | H56: =IF(C56=0,0,(H55+C56)) -> 94600 | I56: =IF(C56=0,0,(I55+E56)) -> 0 | J56: =H56-I56 -> 94600 | K56: =IFERROR(H56/I56,0) -> 0
B57: =B56+1 -> 45877 | C57: 283650 | D57: =$C$17 -> 251748.25 | E57: =$C$8 -> 0 | F57: =C57-E57 -> 283650 | G57: =IFERROR(C57/E57,0) -> 0 | H57: =IF(C57=0,0,(H56+C57)) -> 378250 | I57: =IF(C57=0,0,(I56+E57)) -> 0 | J57: =H57-I57 -> 378250 | K57: =IFERROR(H57/I57,0) -> 0
B58: =B57+1 -> 45878 | C58: 221610 | D58: =$C$17 -> 251748.25 | E58: =$C$9 -> 0 | F58: =C58-E58 -> 221610 | G58: =IFERROR(C58/E58,0) -> 0 | H58: =IF(C58=0,0,(H57+C58)) -> 599860 | I58: =IF(C58=0,0,(I57+E58)) -> 0 | J58: =H58-I58 -> 599860 | K58: =IFERROR(H58/I58,0) -> 0
B59: =B58+1 -> 45879 | D59: =$C$17 -> 251748.25 | E59: =$C$10 -> 0 | F59: =C59-E59 -> 0 | G59: =IFERROR(C59/E59,0) -> 0 | H59: =IF(C59=0,0,(H58+C59)) -> 0 | I59: =IF(C59=0,0,(I58+E59)) -> 0 | J59: =H59-I59 -> 0 | K59: =IFERROR(H59/I59,0) -> 0
B60: =B59+1 -> 45880 | D60: =$C$17 -> 251748.25 | E60: =$C$11 -> 0 | F60: =C60-E60 -> 0 | G60: =IFERROR(C60/E60,0) -> 0 | H60: =IF(C60=0,0,(H59+C60)) -> 0 | I60: =IF(C60=0,0,(I59+E60)) -> 0 | J60: =H60-I60 -> 0 | K60: =IFERROR(H60/I60,0) -> 0
B61: =B60+1 -> 45881 | D61: =$C$17 -> 251748.25 | E61: =$C$12 -> 0 | F61: =C61-E61 -> 0 | G61: =IFERROR(C61/E61,0) -> 0 | H61: =IF(C61=0,0,(H60+C61)) -> 0 | I61: =IF(C61=0,0,(I60+E61)) -> 0 | J61: =H61-I61 -> 0 | K61: =IFERROR(H61/I61,0) -> 0
B62: =B61+1 -> 45882 | D62: 0 | F62: =C62-E62 -> 0 | G62: =IFERROR(C62/E62,0) -> 0 | H62: =IF(C62=0,0,(H61+C62)) -> 0 | I62: =IF(C62=0,0,(I61+E62)) -> 0 | J62: =H62-I62 -> 0 | K62: =IFERROR(H62/I62,0) -> 0
B63: =B62+1 -> 45883 | D63: =$C$17 -> 251748.25 | E63: =$C$7 -> 0 | F63: =C63-E63 -> 0 | G63: =IFERROR(C63/E63,0) -> 0 | H63: =IF(C63=0,0,(H62+C63)) -> 0 | I63: =IF(C63=0,0,(I62+E63)) -> 0 | J63: =H63-I63 -> 0 | K63: =IFERROR(H63/I63,0) -> 0
B64: =B63+1 -> 45884 | D64: =$C$17 -> 251748.25 | E64: =$C$8 -> 0 | F64: =C64-E64 -> 0 | G64: =IFERROR(C64/E64,0) -> 0 | H64: =IF(C64=0,0,(H63+C64)) -> 0 | I64: =IF(C64=0,0,(I63+E64)) -> 0 | J64: =H64-I64 -> 0 | K64: =IFERROR(H64/I64,0) -> 0
B65: =B64+1 -> 45885 | D65: =$C$17 -> 251748.25 | E65: =$C$9 -> 0 | F65: =C65-E65 -> 0 | G65: =IFERROR(C65/E65,0) -> 0 | H65: =IF(C65=0,0,(H64+C65)) -> 0 | I65: =IF(C65=0,0,(I64+E65)) -> 0 | J65: =H65-I65 -> 0 | K65: =IFERROR(H65/I65,0) -> 0
B66: =B65+1 -> 45886 | D66: =$C$17 -> 251748.25 | E66: =$C$10 -> 0 | F66: =C66-E66 -> 0 | G66: =IFERROR(C66/E66,0) -> 0 | H66: =IF(C66=0,0,(H65+C66)) -> 0 | I66: =IF(C66=0,0,(I65+E66)) -> 0 | J66: =H66-I66 -> 0 | K66: =IFERROR(H66/I66,0) -> 0
B67: =B66+1 -> 45887 | D67: =$C$17 -> 251748.25 | E67: =$C$11 -> 0 | F67: =C67-E67 -> 0 | G67: =IFERROR(C67/E67,0) -> 0 | H67: =IF(C67=0,0,(H66+C67)) -> 0 | I67: =IF(C67=0,0,(I66+E67)) -> 0 | J67: =H67-I67 -> 0 | K67: =IFERROR(H67/I67,0) -> 0
B68: =B67+1 -> 45888 | D68: =$C$17 -> 251748.25 | E68: =$C$12 -> 0 | F68: =C68-E68 -> 0 | G68: =IFERROR(C68/E68,0) -> 0 | H68: =IF(C68=0,0,(H67+C68)) -> 0 | I68: =IF(C68=0,0,(I67+E68)) -> 0 | J68: =H68-I68 -> 0 | K68: =IFERROR(H68/I68,0) -> 0
B69: =B68+1 -> 45889 | D69: 0 | F69: =C69-E69 -> 0 | G69: =IFERROR(C69/E69,0) -> 0 | H69: =IF(C69=0,0,(H68+C69)) -> 0 | I69: =IF(C69=0,0,(I68+E69)) -> 0 | J69: =H69-I69 -> 0 | K69: =IFERROR(H69/I69,0) -> 0
B70: =B69+1 -> 45890 | D70: 0 | F70: =C70-E70 -> 0 | G70: =IFERROR(C70/E70,0) -> 0 | H70: =IF(C70=0,0,(H69+C70)) -> 0 | I70: =IF(C70=0,0,(I69+E70)) -> 0 | J70: =H70-I70 -> 0 | K70: =IFERROR(H70/I70,0) -> 0
B71: =B70+1 -> 45891 | D71: =$C$17 -> 251748.25 | E71: =$C$8 -> 0 | F71: =C71-E71 -> 0 | G71: =IFERROR(C71/E71,0) -> 0 | H71: =IF(C71=0,0,(H70+C71)) -> 0 | I71: =IF(C71=0,0,(I70+E71)) -> 0 | J71: =H71-I71 -> 0 | K71: =IFERROR(H71/I71,0) -> 0
B72: =B71+1 -> 45892 | D72: =$C$17 -> 251748.25 | E72: =$C$9 -> 0 | F72: =C72-E72 -> 0 | G72: =IFERROR(C72/E72,0) -> 0 | H72: =IF(C72=0,0,(H71+C72)) -> 0 | I72: =IF(C72=0,0,(I71+E72)) -> 0 | J72: =H72-I72 -> 0 | K72: =IFERROR(H72/I72,0) -> 0
B73: =B72+1 -> 45893 | D73: =$C$17 -> 251748.25 | E73: =$C$10 -> 0 | F73: =C73-E73 -> 0 | G73: =IFERROR(C73/E73,0) -> 0 | H73: =IF(C73=0,0,(H72+C73)) -> 0 | I73: =IF(C73=0,0,(I72+E73)) -> 0 | J73: =H73-I73 -> 0 | K73: =IFERROR(H73/I73,0) -> 0
B74: =B73+1 -> 45894 | D74: =$C$17 -> 251748.25 | E74: =$C$11 -> 0 | F74: =C74-E74 -> 0 | G74: =IFERROR(C74/E74,0) -> 0 | H74: =IF(C74=0,0,(H73+C74)) -> 0 | I74: =IF(C74=0,0,(I73+E74)) -> 0 | J74: =H74-I74 -> 0 | K74: =IFERROR(H74/I74,0) -> 0
B75: =B74+1 -> 45895 | D75: =$C$17 -> 251748.25 | E75: =$C$12 -> 0 | F75: =C75-E75 -> 0 | G75: =IFERROR(C75/E75,0) -> 0 | H75: =IF(C75=0,0,(H74+C75)) -> 0 | I75: =IF(C75=0,0,(I74+E75)) -> 0 | J75: =H75-I75 -> 0 | K75: =IFERROR(H75/I75,0) -> 0
B76: =B75+1 -> 45896 | D76: 0 | F76: =C76-E76 -> 0 | G76: =IFERROR(C76/E76,0) -> 0 | H76: =IF(C76=0,0,(H75+C76)) -> 0 | I76: =IF(C76=0,0,(I75+E76)) -> 0 | J76: =H76-I76 -> 0 | K76: =IFERROR(H76/I76,0) -> 0
B77: =B76+1 -> 45897 | D77: =$C$17 -> 251748.25 | E77: =$C$7 -> 0 | F77: =C77-E77 -> 0 | G77: =IFERROR(C77/E77,0) -> 0 | H77: =IF(C77=0,0,(H76+C77)) -> 0 | I77: =IF(C77=0,0,(I76+E77)) -> 0 | J77: =H77-I77 -> 0 | K77: =IFERROR(H77/I77,0) -> 0
B78: =B77+1 -> 45898 | D78: =$C$17 -> 251748.25 | E78: =$C$8 -> 0 | F78: =C78-E78 -> 0 | G78: =IFERROR(C78/E78,0) -> 0 | H78: =IF(C78=0,0,(H77+C78)) -> 0 | I78: =IF(C78=0,0,(I77+E78)) -> 0 | J78: =H78-I78 -> 0 | K78: =IFERROR(H78/I78,0) -> 0
B79: =B78+1 -> 45899 | D79: =$C$17 -> 251748.25 | E79: =$C$9 -> 0 | F79: =C79-E79 -> 0 | G79: =IFERROR(C79/E79,0) -> 0 | H79: =IF(C79=0,0,(H78+C79)) -> 0 | I79: =IF(C79=0,0,(I78+E79)) -> 0 | J79: =H79-I79 -> 0 | K79: =IFERROR(H79/I79,0) -> 0
B80: =B79+1 -> 45900 | D80: =$C$17 -> 251748.25 | E80: =$C$10 -> 0 | F80: =C80-E80 -> 0 | G80: =IFERROR(C80/E80,0) -> 0 | H80: =IF(C80=0,0,(H79+C80)) -> 0 | I80: =IF(C80=0,0,(I79+E80)) -> 0 | J80: =H80-I80 -> 0 | K80: =IFERROR(H80/I80,0) -> 0
C81: =SUM(C50:C80) -> 1892140 | D81: =SUM(D50:D80) -> 6545454.5 | E81: =SUM(E50:E80) -> 0
C82: =IFERROR(C81/D81,0) -> 0.28907694 | E82: =E81-F16 -> -5034965

Sheet 2024(¥)
B2: 45292 | E2: ①年間営業日 | G2: ②年間目標売上 | I2: 年間売上％設定 | M2: 年間売上合計 | O2: 年間実質売上 | Q2: 年間利益率 | R2: 年間予想利益額
E3: =SUM(F6:F17) -> 289 | G3: 71220821 | I3: =SUM(AP6:AP17)*100 -> 0.9999996 | K3: =G3*I3 -> 71220793 | M3: =SUM(J20:J385) -> 71220821 | O3: =M3-G3 -> 0 | Q3: 0.21 | R3: =M3*Q3 -> 14956372
B5: 平均日次売上目標額 | E5: 月 | F5: 月次営業日数 | G5: 平均月間売上目標額 | H5: 月次繁閑期%設定 | J5: 月次目標売上 | K5: 日次目標売上 | M5: 月次売上 | N5: 月間差額 | P5: 月次実質% | R5: 1日の売上目標値 参考例 | AO5: =TEXT(K6,"¥0") -> ¥221795
B6: ② ÷ ① | E6: 1月 | F6: =COUNTIF(D20:D50,1) -> 22 | G6: =$B$7*F6 -> 5421654.2 | H6: 0.9 | J6: =G6*H6 -> 4879488.8 | K6: =J6/F6 -> 221794.94 | M6: =SUM(J20:J50) -> 4982374 | N6: =M6-J6 -> 102885.23 | P6: =M6/G6 -> 0.91897672 | R6: 目標売上 | T6: ¥233564 | V6: 0.76 | AO6: =TEXT(K7,"¥0") -> ¥209473 | AP6: =(H6/100)*AQ6 -> 0.0007499997 | AQ6: 0.0833333
B7: =G3/E3 -> 246438.83 | E7: 2月 | F7: =COUNTIF(D51:D79,1) -> 23 | G7: =$B$7*F7 -> 5668093 | H7: 0.85 | J7: =G7*H7 -> 4817879.1 | K7: =J7/F7 -> 209473 | M7: =SUM(J51:J79) -> 5001830 | N7: =M7-J7 -> 183950.93 | P7: =M7/G7 -> 0.88245376 | T7: =T6*V6 -> 177508.64 | AO7: =TEXT(K8,"¥0") -> ¥246439 | AP7: =(H7/100)*AQ7 -> 0.00070833305 | AQ7: 0.0833333
E8: 3月 | F8: =COUNTIF(D80:D110,1) -> 25 | G8: =$B$7*F8 -> 6160970.7 | H8: 1 | J8: =G8*H8 -> 6160970.7 | K8: =J8/F8 -> 246438.83 | M8: =SUM(J80:J110) -> 6460608 | N8: =M8-J8 -> 299637.33 | P8: =M8/G8 -> 1.0486348 | R8: 差額 | T8: =T9-T6 -> 87436 | AO8: =TEXT(K9,"¥0") -> ¥258761 | AP8: =(H8/100)*AQ8 -> 0.000833333 | AQ8: 0.0833333
E9: 4月 | F9: =COUNTIF(D111:D140,1) -> 25 | G9: =$B$7*F9 -> 6160970.7 | H9: 1.05 | J9: =G9*H9 -> 6469019.2 | K9: =J9/F9 -> 258760.77 | M9: =SUM(J111:J140) -> 6676657 | N9: =M9-J9 -> 207637.79 | P9: =M9/G9 -> 1.0837021 | R9: 仮1日売上総合計 | T9: =SUM(V11:V16) -> 321000 | AO9: =TEXT(K10,"¥0") -> ¥246439 | AP9: =(H9/100)*AQ9 -> 0.00087499965 | AQ9: 0.0833333
E10: 5月 | F10: =COUNTIF(D141:D171,1) -> 24 | G10: =$B$7*F10 -> 5914531.8 | H10: 1 | J10: =G10*H10 -> 5914531.8 | K10: =J10/F10 -> 246438.83 | M10: =SUM(J141:J171) -> 6165010 | N10: =M10-J10 -> 250478.15 | P10: =M10/G10 -> 1.0423496 | R10: 項目 | S10: 仮客単価 | T10: 集客数 | V10: 仮1日の売上小計 | AO10: =TEXT(K11,"¥0") -> ¥221795 | AP10: =(H10/100)*AQ10 -> 0.000833333 | AQ10: 0.0833333
E11: 6月 | F11: =COUNTIF(D172:D201,1) -> 25 | G11: =$B$7*F11 -> 6160970.7 | H11: 0.9 | J11: =G11*H11 -> 5544873.6 | K11: =J11/F11 -> 221794.94 | M11: =SUM(J172:J201) -> 5907950 | N11: =M11-J11 -> 363076.39 | P11: =M11/G11 -> 0.95893169 | R11: ランチ | S11: 1100 | T11: 60 | V11: =S11*T11 -> 66000 | AO11: =TEXT(K12,"¥0") -> ¥234117 | AP11: =(H11/100)*AQ11 -> 0.0007499997 | AQ11: 0.0833333
E12: 7月 | F12: =COUNTIF(D202:D232,1) -> 26 | G12: =$B$7*F12 -> 6407409.5 | H12: 0.95 | J12: =G12*H12 -> 6087039 | K12: =J12/F12 -> 234116.89 | M12: =SUM(J202:J232) -> 6522185 | N12: =M12-J12 -> 435145.97 | P12: =M12/G12 -> 1.0179129 | R12: ディナー | S12: 4500 | T12: 20 | V12: =S12*T12 -> 90000 | AO12: =TEXT(K13,"¥0") -> ¥197151 | AP12: =(H12/100)*AQ12 -> 0.00079166635 | AQ12: 0.0833333
E13: 8月 | F13: =COUNTIF(D233:D263,1) -> 22 | G13: =$B$7*F13 -> 5421654.2 | H13: 0.8 | J13: =G13*H13 -> 4337323.4 | K13: =J13/F13 -> 197151.06 | M13: =SUM(J233:J263) -> 4512002 | N13: =M13-J13 -> 174678.64 | P13: =M13/G13 -> 0.8322187 | R13: Party 5500 | S13: 5500 | T13: 30 | V13: =S13*T13 -> 165000 | AO13: =TEXT(K14,"¥0") -> ¥234117 | AP13: =(H13/100)*AQ13 -> 0.0006666664 | AQ13: 0.0833333
E14: 9 月 | F14: =COUNTIF(D264:D293,1) -> 23 | G14: =$B$7*F14 -> 5668093 | H14: 0.95 | J14: =G14*H14 -> 5384688.4 | K14: =J14/F14 -> 234116.89 | M14: =SUM(J264:J293) -> 5425075 | N14: =M14-J14 -> 40386.63 | P14: =M14/G14 -> 0.95712526 | T14: 0 | V14: =S14*T14 -> 0 | AO14: =TEXT(K15,"¥0") -> ¥308049 | AP14: =(H14/100)*AQ14 -> 0.00079166635 | AQ14: 0.0833333
E15: 10月 | F15: =COUNTIF(D294:D324,1) -> 26 | G15: =$B$7*F15 -> 6407409.5 | H15: 1.25 | J15: =G15*H15 -> 8009261.9 | K15: =J15/F15 -> 308048.53 | M15: =SUM(J294:J324) -> 5555530 | N15: =M15-J15 -> -2453731.9 | P15: =M15/G15 -> 0.86704775 | T15: 0 | V15: =S15*T15 -> 0 | AO15: =TEXT(K16,"¥0") -> ¥258761 | AP15: =(H15/100)*AQ15 -> 0.0010416662 | AQ15: 0.0833333
E16: 11月 | F16: =COUNTIF(D325:D354,1) -> 24 | G16: =$B$7*F16 -> 5914531.8 | H16: 1.05 | J16: =G16*H16 -> 6210258.4 | K16: =J16/F16 -> 258760.77 | M16: =SUM(J325:J354) -> 6112150 | N16: =M16-J16 -> -98108.44 | P16: =M16/G16 -> 1.0334123 | T16: 0 | V16: =S16*T16 -> 0 | AO16: =TEXT(K17,"¥0") -> ¥320370 | AP16: =(H16/100)*AQ16 -> 0.00087499965 | AQ16: 0.0833333
E17: 12月 | F17: =COUNTIF(D355:D385,1) -> 24 | G17: =$B$7*F17 -> 5914531.8 | H17: 1.3 | J17: =G17*H17 -> 7688891.4 | K17: =J17/F17 -> 320370.48 | M17: =SUM(J355:J385) -> 7899450 | N17: =M17-J17 -> 210558.6 | P17: =M17/G17 -> 1.3356002 | AP17: =(H17/100)*AQ17 -> 0.0010833329 | AQ17: 0.0833333
E19: 月 | F19: 日程 | G19: 曜日 | H19: 休店日理由 | J19: Daily売上入力 | L19: 目標売上 KPI | M19: 日次実質売上 | N19: 実質% | P19: 月次目標売上 | Q19: 月次実質売上 | R19: 月次差額(勝率) | S19: 月次実質% | U19: 年次目標売上 | V19: 年次実質売上 | W19: 年次差額(勝率) | X19: 年次実質% | AC19: 月 | AD19: 曜日 | AE19: 平均売上 | AF19: 曜日回数 | AH19: 曜日合計額 | AI19: 加重比率
C20: 1 | D20: 0 | E20: =TEXT(AA20,"m") -> 1 | F20: =B2 -> 45292 | G20: =TEXT(AS20,"ddd") -> Mon | H20: 元旦 | J20: 0 | L20: =IF(D20=0,0,$K$6) -> 0 | M20: =IF(D20=0,0,J20-L20) -> 0 | N20: =IFERROR(J20/L20,"0%") -> 0% | P20: =IF(D20=0,0,$K$6) -> 0 | Q20: =IF(D20=0,0,$J$20) -> 0 | R20: =IF(D20=0,0,Q20-P20) -> 0 | S20: =IFERROR(Q20/P20,"0%") -> 0% | U20: =IF(D20=0,0,$L$20) -> 0 | V20: =IF(D20=0,0,$J$20) -> 0 | W20: =IF(D20=0,0,V20-U20) -> 0 | X20: =IFERROR(V20/U20,"0%") -> 0% | Z20: =B2 -> 45292 | AA20: =B2 -> 45292 | AB20: 45292 | AC20: 1 | AD20: 月 | AE20: =IFERROR(AVERAGEIFS(J20:J50,D20:D50,1,G20:G50,"mon"),0) -> 253025 | AF20: =COUNTIFS(D20:D50,1,G20:G50,"Mon") -> 4 | AG20: =SUMIFS(J20:J50,D20:D50,1,G20:G50,"mon") -> 1012100 | AH20: =AE20*AF20 -> 1012100 | AI20: =AH20/$M$6 -> 0.2031361 | AJ20: =SUM(AI20:AI26) -> 1 | AS20: =B2 -> 45292
C21: =C20+1 -> 2 | D21: 0 | E21: =TEXT(AA21,"m") -> 1 | F21: =F20+1 -> 45293 | G21: =TEXT(AS21,"ddd") -> Tue | H21: 休み | J21: 0 | L21: =IF(D21=0,0,$K$6) -> 0 | M21: =IF(D21=0,0,J21-L21) -> 0 | N21: =IFERROR(J21/L21,"0%") -> 0% | P21: =IF(D21=0,0,SUM($L$20:L21)) -> 0 | Q21: =IF(D21=0,0,SUM($J$20:J21)) -> 0 | R21: =IF(D21=0,0,Q21-P21) -> 0 | S21: =IFERROR(Q21/P21,"0%") -> 0% | U21: =IF(D21=0,0,SUM($L$20:L21)) -> 0 | V21: =IF(D21=0,0,SUM($J$20:J21)) -> 0 | W21: =IF(D21=0,0,V21-U21) -> 0 | X21: =IFERROR(V21/U21,"0%") -> 0% | Z21: =Z20+1 -> 45293 | AA21: =AA20+1 -> 45293 | AB21: 45293 | AC21: 1 | AD21: 火 | AE21: =IFERROR(AVERAGEIFS(J20:J50,D20:D50,1,G20:G50,"tue"),0) -> 214411 | AF21: =COUNTIFS(D20:D50,1,G20:G50,"Tue") -> 4 | AH21: =AE21*AF21 -> 857644 | AI21: =AH21/$M$6 -> 0.17213561 | AS21: =AS20+1 -> 45293
C22: =C21+1 -> 3 | D22: 0 | E22: =TEXT(AA22,"m") -> 1 | F22: =F21+1 -> 45294 | G22: =TEXT(AS22,"ddd") -> Wed | H22: 休み | J22: 0 | L22: =IF(D22=0,0,$K$6) -> 0 | M22: =IF(D22=0,0,J22-L22) -> 0 | N22: =IFERROR(J22/L22,"0%") -> 0% | P22: =IF(D22=0,0,SUM($L$20:L22)) -> 0 | Q22: =IF(D22=0,0,SUM($J$20:J22)) -> 0 | R22: =IF(D22=0,0,Q22-P22) -> 0 | S22: =IFERROR(Q22/P22,"0%") -> 0% | U22: =IF(D22=0,0,SUM($L$20:L22)) -> 0 | V22: =IF(D22=0,0,SUM($J$20:J22)) -> 0 | W22: =IF(D22=0,0,V22-U22) -> 0 | X22: =IFERROR(V22/U22,"0%") -> 0% | Z22: =Z21+1 -> 45294 | AA22: =AA21+1 -> 45294 | AB22: 45294 | AC22: 1 | AD22: 水 | AE22: =IFERROR(AVERAGEIFS(J20:J50,D20:D50,1,G20:G50,"wed"),0) -> 241500 | AF22: =COUNTIFS(D20:D50,1,G20:G50,"wed") -> 4 | AH22: =AE22*AF22 -> 966000 | AI22: =AH22/$M$6 -> 0.19388348 | AS22: =AS21+1 -> 45294
C23: =C22+1 -> 4 | D23: 0 | E23: =TEXT(AA23,"m") -> 1 | F23: =F22+1 -> 45295 | G23: =TEXT(AS23,"ddd") -> Thu | H23: 祝日 | J23: 0 | L23: =IF(D23=0,0,$K$6) -> 0 | M23: =IF(D23=0,0,J23-L23) -> 0 | N23: =IFERROR(J23/L23,"0%") -> 0% | P23: =IF(D23=0,0,SUM($L$20:L23)) -> 0 | Q23: =IF(D23=0,0,SUM($J$20:J23)) -> 0 | R23: =IF(D23=0,0,Q23-P23) -> 0 | S23: =IFERROR(Q23/P23,"0%") -> 0% | U23: =IF(D23=0,0,SUM($L$20:L23)) -> 0 | V23: =IF(D23=0,0,SUM($J$20:J23)) -> 0 | W23: =IF(D23=0,0,V23-U23) -> 0 | X23: =IFERROR(V23/U23,"0%") -> 0% | Z23: =Z22+1 -> 45295 | AA23: =AA22+1 -> 45295 | AB23: 45295 | AC23: 1 | AD23: 木 | AE23: =IFERROR(AVERAGEIFS(J20:J50,D20:D50,1,G20:G50,"thu"),0) -> 223706.67 | AF23: =COUNTIFS(D20:D50,1,G20:G50,"thu") -> 3 | AH23: =AE23*AF23 -> 671120 | AI23: =AH23/$M$6 -> 0.13469884 | AS23: =AS22+1 -> 45295
C24: =C23+1 -> 5 | D24: 1 | E24: =TEXT(AA24,"m") -> 1 | F24: =F23+1 -> 45296 | G24: =TEXT(AS24,"ddd") -> Fri | J24: 365950 | L24: =IF(D24=0,0,$K$6) -> 221794.94 | M24: =IF(D24=0,0,J24-L24) -> 144155.06 | N24: =IFERROR(J24/L24,"0%") -> 1.6499474 | P24: =IF(D24=0,0,SUM($L$20:L24)) -> 221794.94 | Q24: =IF(D24=0,0,SUM($J$20:J24)) -> 365950 | R24: =IF(D24=0,0,Q24-P24) -> 144155.06 | S24: =IFERROR(Q24/P24,"0%") -> 1.6499474 | U24: =IF(D24=0,0,SUM($L$20:L24)) -> 221794.94 | V24: =IF(D24=0,0,SUM($J$20:J24)) -> 365950 | W24: =IF(D24=0,0,V24-U24) -> 144155.06 | X24: =IFERROR(V24/U24,"0%") -> 1.6499474 | Z24: =Z23+1 -> 45296 | AA24: =AA23+1 -> 45296 | AB24: 45296 | AC24: 1 | AD24: 金 | AE24: =IFERROR(AVERAGEIFS(J20:J50,D20:D50,1,G20:G50,"fri"),0) -> 292927.5 | AF24: =COUNTIFS(D20:D50,1,G20:G50,"fri") -> 4 | AH24: =AE24*AF24 -> 1171710 | AI24: =AH24/$M$6 -> 0.23517102 | AS24: =AS23+1 -> 45296
C25: =C24+1 -> 6 | D25: 0 | E25: =TEXT(AA25,"m") -> 1 | F25: =F24+1 -> 45297 | G25: =TEXT(AS25,"ddd") -> Sat | J25: 0 | L25: =IF(D25=0,0,$K$6) -> 0 | M25: =IF(D25=0,0,J25-L25) -> 0 | N25: =IFERROR(J25/L25,"0%") -> 0% | P25: =IF(D25=0,0,SUM($L$20:L25)) -> 0 | Q25: =IF(D25=0,0,SUM($J$20:J25)) -> 0 | R25: =IF(D25=0,0,Q25-P25) -> 0 | S25: =IFERROR(Q25/P25,"0%") -> 0% | U25: =IF(D25=0,0,SUM($L$20:L25)) -> 0 | V25: =IF(D25=0,0,SUM($J$20:J25)) -> 0 | W25: =IF(D25=0,0,V25-U25) -> 0 | X25: =IFERROR(V25/U25,"0%") -> 0% | Z25: =Z24+1 -> 45297 | AA25: =AA24+1 -> 45297 | AB25: 45297 | AC25: 1 | AD25: 土 | AE25: =IFERROR(AVERAGEIFS(J20:J50,D20:D50,1,G20:G50,"sat"),0) -> 101266.67 | AF25: =COUNTIFS(D20:D50,1,G20:G50,"sat") -> 3 | AH25: =AE25*AF25 -> 303800 | AI25: =AH25/$M$6 -> 0.060974949 | AS25: =AS24+1 -> 45297
C26: =C25+1 -> 7 | D26: 0 | E26: =TEXT(AA26,"m") -> 1 | F26: =F25+1 -> 45298 | G26: =TEXT(AS26,"ddd") -> Sun | H26: 日曜日 | J26: 0 | L26: =IF(D26=0,0,$K$6) -> 0 | M26: =IF(D26=0,0,J26-L26) -> 0 | N26: =IFERROR(J26/L26,"0%") -> 0% | P26: =IF(D26=0,0,SUM($L$20:L26)) -> 0 | Q26: =IF(D26=0,0,SUM($J$20:J26)) -> 0 | R26: =IF(D26=0,0,Q26-P26) -> 0 | S26: =IFERROR(Q26/P26,"0%") -> 0% | U26: =IF(D26=0,0,SUM($L$20:L26)) -> 0 | V26: =IF(D26=0,0,SUM($J$20:J26)) -> 0 | W26: =IF(D26=0,0,V26-U26) -> 0 | X26: =IFERROR(V26/U26,"0%") -> 0% | Z26: =Z25+1 -> 45298 | AA26: =AA25+1 -> 45298 | AB26: 45298 | AC26: 1 | AD26: 日 | AE26: =IFERROR(AVERAGEIFS(J20:J50,D20:D50,1,G20:G50,"sun"),0) -> 0 | AF26: =IFERROR(COUNTIFS(D20:D50,1,G20:G50,"sun"),0) -> 0 | AH26: =AE26*AF26 -> 0 | AI26: =AH26/$M$6 -> 0 | AS26: =AS25+1 -> 45298
C27: =C26+1 -> 8 | D27: 1 | E27: =TEXT(AA27,"m") -> 1 | F27: =F26+1 -> 45299 | G27: =TEXT(AS27,"ddd") -> Mon | J27: 250000 | L27: =IF(D27=0,0,$K$6) -> 221794.94 | M27: =IF(D27=0,0,J27-L27) -> 28205.056 | N27: =IFERROR(J27/L27,"0%") -> 1.1271673 | P27: =IF(D27=0,0,SUM($L$20:L27)) -> 443589.89 | Q27: =IF(D27=0,0,SUM($J$20:J27)) -> 615950 | R27: =IF(D27=0,0,Q27-P27) -> 172360.11 | S27: =IFERROR(Q27/P27,"0%") -> 1.3885573 | U27: =IF(D27=0,0,SUM($L$20:L27)) -> 443589.89 | V27: =IF(D27=0,0,SUM($J$20:J27)) -> 615950 | W27: =IF(D27=0,0,V27-U27) -> 172360.11 | X27: =IFERROR(V27/U27,"0%") -> 1.3885573 | Z27: =Z26+1 -> 45299 | AA27: =AA26+1 -> 45299 | AB27: 45299 | AC27: 2 | AD27: 月 | AE27: =AVERAGEIFS(J51:J79,D51:D79,1,G51:G79,"mon") -> 231250 | AF27: =COUNTIFS(D51:D79,1,G51:G79,"Mon") -> 3 | AH27: =AE27*AF27 -> 693750 | AI27: =AH27/$M$7 -> 0.13869924 | AJ27: =SUM(AI27:AI33) -> 1 | AK27: 51〜79 | AS27: =AS26+1 -> 45299
C28: =C27+1 -> 9 | D28: 1 | E28: =TEXT(AA28,"m") -> 1 | F28: =F27+1 -> 45300 | G28: =TEXT(AS28,"ddd") -> Tue | J28: 143850 | L28: =IF(D28=0,0,$K$6) -> 221794.94 | M28: =IF(D28=0,0,J28-L28) -> -77944.944 | N28: =IFERROR(J28/L28,"0%") -> 0.64857204 | P28: =IF(D28=0,0,SUM($L$20:L28)) -> 665384.83 | Q28: =IF(D28=0,0,SUM($J$20:J28)) -> 759800 | R28: =IF(D28=0,0,Q28-P28) -> 94415.167 | S28: =IFERROR(Q28/P28,"0%") -> 1.1418956 | U28: =IF(D28=0,0,SUM($L$20:L28)) -> 665384.83 | V28: =IF(D28=0,0,SUM($J$20:J28)) -> 759800 | W28: =IF(D28=0,0,V28-U28) -> 94415.167 | X28: =IFERROR(V28/U28,"0%") -> 1.1418956 | Z28: =Z27+1 -> 45300 | AA28: =AA27+1 -> 45300 | AB28: 45300 | AC28: 2 | AD28: 火 | AE28: =AVERAGEIFS(J51:J79,D51:D79,1,G51:G79,"tue") -> 214245 | AF28: =COUNTIFS(D51:D79,1,G51:G79,"tue") -> 4 | AH28: =AE28*AF28 -> 856980 | AI28: =AH28/$M$7 -> 0.17133329 | AS28: =AS27+1 -> 45300
C29: =C28+1 -> 10 | D29: 1 | E29: =TEXT(AA29,"m") -> 1 | F29: =F28+1 -> 45301 | G29: =TEXT(AS29,"ddd") -> Wed | J29: 331400 | L29: =IF(D29=0,0,$K$6) -> 221794.94 | M29: =IF(D29=0,0,J29-L29) -> 109605.06 | N29: =IFERROR(J29/L29,"0%") -> 1.4941729 | P29: =IF(D29=0,0,SUM($L$20:L29)) -> 887179.78 | Q29: =IF(D29=0,0,SUM($J$20:J29)) -> 1091200 | R29: =IF(D29=0,0,Q29-P29) -> 204020.22 | S29: =IFERROR(Q29/P29,"0%") -> 1.2299649 | U29: =IF(D29=0,0,SUM($L$20:L29)) -> 887179.78 | V29: =IF(D29=0,0,SUM($J$20:J29)) -> 1091200 | W29: =IF(D29=0,0,V29-U29) -> 204020.22 | X29: =IFERROR(V29/U29,"0%") -> 1.2299649 | Z29: =Z28+1 -> 45301 | AA29: =AA28+1 -> 45301 | AB29: 45301 | AC29: 2 | AD29: 水 | AE29: =AVERAGEIFS(J51:J79,D51:D79,1,G51:G79,"wed") -> 221717.5 | AF29: =COUNTIFS(D51:D79,1,G51:G79,"wed") -> 4 | AH29: =AE29*AF29 -> 886870 | AI29: =AH29/$M$7 -> 0.1773091 | AS29: =AS28+1 -> 45301
C30: =C29+1 -> 11 | D30: 1 | E30: =TEXT(AA30,"m") -> 1 | F30: =F29+1 -> 45302 | G30: =TEXT(AS30,"ddd") -> Thu | J30: 263220 | L30: =IF(D30=0,0,$K$6) -> 221794.94 | M30: =IF(D30=0,0,J30-L30) -> 41425.056 | N30: =IFERROR(J30/L30,"0%") -> 1.1867719 | P30: =IF(D30=0,0,SUM($L$20:L30)) -> 1108974.7 | Q30: =IF(D30=0,0,SUM($J$20:J30)) -> 1354420 | R30: =IF(D30=0,0,Q30-P30) -> 245445.28 | S30: =IFERROR(Q30/P30,"0%") -> 1.2213263 | U30: =IF(D30=0,0,SUM($L$20:L30)) -> 1108974.7 | V30: =IF(D30=0,0,SUM($J$20:J30)) -> 1354420 | W30: =IF(D30=0,0,V30-U30) -> 245445.28 | X30: =IFERROR(V30/U30,"0%") -> 1.2213263 | Z30: =Z29+1 -> 45302 | AA30: =AA29+1 -> 45302 | AB30: 45302 | AC30: 2 | AD30: 木 | AE30: =AVERAGEIFS(J51:J79,D51:D79,1,G51:G79,"thu") -> 233396 | AF30: =COUNTIFS(D51:D79,1,G51:G79,"thu") -> 5 | AH30: =AE30*AF30 -> 1166980 | AI30: =AH30/$M$7 -> 0.23331061 | AS30: =AS29+1 -> 45302
C31: =C30+1 -> 12 | D31: 1 | E31: =TEXT(AA31,"m") -> 1 | F31: =F30+1 -> 45303 | G31: =TEXT(AS31,"ddd") -> Fri | J31: 230860 | L31: =IF(D31=0,0,$K$6) -> 221794.94 | M31: =IF(D31=0,0,J31-L31) -> 9065.0557 | N31: =IFERROR(J31/L31,"0%") -> 1.0408713 | P31: =IF(D31=0,0,SUM($L$20:L31)) -> 1330769.7 | Q31: =IF(D31=0,0,SUM($J$20:J31)) -> 1585280 | R31: =IF(D31=0,0,Q31-P31) -> 254510.33 | S31: =IFERROR(Q31/P31,"0%") -> 1.1912505 | U31: =IF(D31=0,0,SUM($L$20:L31)) -> 1330769.7 | V31: =IF(D31=0,0,SUM($J$20:J31)) -> 1585280 | W31: =IF(D31=0,0,V31-U31) -> 254510.33 | X31: =IFERROR(V31/U31,"0%") -> 1.1912505 | Z31: =Z30+1 -> 45303 | AA31: =AA30+1 -> 45303 | AB31: 45303 | AC31: 2 | AD31: 金 | AE31: =AVERAGEIFS(J51:J79,D51:D79,1,G51:G79,"fri") -> 283893.33 | AF31: =COUNTIFS(D51:D79,1,G51:G79,"fri") -> 3 | AH31: =AE31*AF31 -> 851680 | AI31: =AH31/$M$7 -> 0.17027368 | AS31: =AS30+1 -> 45303
C32: =C31+1 -> 13 | D32: 1 | E32: =TEXT(AA32,"m") -> 1 | F32: =F31+1 -> 45304 | G32: =TEXT(AS32,"ddd") -> Sat | J32: 50050 | L32: =IF(D32=0,0,$K$6) -> 221794.94 | M32: =IF(D32=0,0,J32-L32) -> -171744.94 | N32: =IFERROR(J32/L32,"0%") -> 0.22565889 | P32: =IF(D32=0,0,SUM($L$20:L32)) -> 1552564.6 | Q32: =IF(D32=0,0,SUM($J$20:J32)) -> 1635330 | R32: =IF(D32=0,0,Q32-P32) -> 82765.39 | S32: =IFERROR(Q32/P32,"0%") -> 1.0533088 | U32: =IF(D32=0,0,SUM($L$20:L32)) -> 1552564.6 | V32: =IF(D32=0,0,SUM($J$20:J32)) -> 1635330 | W32: =IF(D32=0,0,V32-U32) -> 82765.39 | X32: =IFERROR(V32/U32,"0%") -> 1.0533088 | Z32: =Z31+1 -> 45304 | AA32: =AA31+1 -> 45304 | AB32: 45304 | AC32: 2 | AD32: 土 | AE32: =AVERAGEIFS(J51:J79,D51:D79,1,G51:G79,"sat") -> 136392.5 | AF32: =COUNTIFS(D51:D79,1,G51:G79,"sat") -> 4 | AH32: =AE32*AF32 -> 545570 | AI32: =AH32/$M$7 -> 0.10907408 | AS32: =AS31+1 -> 45304
C33: =C32+1 -> 14 | D33: 0 | E33: =TEXT(AA33,"m") -> 1 | F33: =F32+1 -> 45305 | G33: =TEXT(AS33,"ddd") -> Sun | J33: 0 | L33: =IF(D33=0,0,$K$6) -> 0 | M33: =IF(D33=0,0,J33-L33) -> 0 | N33: =IFERROR(J33/L33,"0%") -> 0% | P33: =IF(D33=0,0,SUM($L$20:L33)) -> 0 | Q33: =IF(D33=0,0,SUM($J$20:J33)) -> 0 | R33: =IF(D33=0,0,Q33-P33) -> 0 | S33: =IFERROR(Q33/P33,"0%") -> 0% | U33: =IF(D33=0,0,SUM($L$20:L33)) -> 0 | V33: =IF(D33=0,0,SUM($J$20:J33)) -> 0 | W33: =IF(D33=0,0,V33-U33) -> 0 | X33: =IFERROR(V33/U33,"0%") -> 0% | Z33: =Z32+1 -> 45305 | AA33: =AA32+1 -> 45305 | AB33: 45305 | AC33: 2 | AD33: 日 | AE33: =IFERROR(AVERAGEIFS(J51:J79,D51:D79,1,G51:G79,"sun"),0) -> 0 | AF33: =IFERROR(COUNTIFS(D51:D79,1,G51:G79,"sun"),0) -> 0 | AH33: =AE33*AF33 -> 0 | AI33: =AH33/$M$7 -> 0 | AS33: =AS32+1 -> 45305
C34: =C33+1 -> 15 | D34: 1 | E34: =TEXT(AA34,"m") -> 1 | F34: =F33+1 -> 45306 | G34: =TEXT(AS34,"ddd") -> Mon | J34: 189100 | L34: =IF(D34=0,0,$K$6) -> 221794.94 | M34: =IF(D34=0,0,J34-L34) -> -32694.944 | N34: =IFERROR(J34/L34,"0%") -> 0.85258932 | P34: =IF(D34=0,0,SUM($L$20:L34)) -> 1774359.6 | Q34: =IF(D34=0,0,SUM($J$20:J34)) -> 1824430 | R34: =IF(D34=0,0,Q34-P34) -> 50070.446 | S34: =IFERROR(Q34/P34,"0%") -> 1.0282189 | U34: =IF(D34=0,0,SUM($L$20:L34)) -> 1774359.6 | V34: =IF(D34=0,0,SUM($J$20:J34)) -> 1824430 | W34: =IF(D34=0,0,V34-U34) -> 50070.446 | X34: =IFERROR(V34/U34,"0%") -> 1.0282189 | Z34: =Z33+1 -> 45306 | AA34: =AA33+1 -> 45306 | AB34: 45306 | AC34: 3 | AD34: 月 | AE34: =AVERAGEIFS(J80:J110,D80:D110,1,G80:G110,"mon") -> 228962.5 | AF34: =COUNTIFS( D80:D110,1,G80:G110,"Mon") -> 4 | AH34: =AE34*AF34 -> 915850 | AI34: =AH34/$M$8 -> 0.1417591 | AJ34: =SUM(AI34:AI40) -> 1 | AK34: 80〜110 | AS34: =AS33+1 -> 45306
C35: =C34+1 -> 16 | D35: 1 | E35: =TEXT(AA35,"m") -> 1 | F35: =F34+1 -> 45307 | G35: =TEXT(AS35,"ddd") -> Tue | J35: 212700 | L35: =IF(D35=0,0,$K$6) -> 221794.94 | M35: =IF(D35=0,0,J35-L35) -> -9094.9443 | N35: =IFERROR(J35/L35,"0%") -> 0.95899391 | P35: =IF(D35=0,0,SUM($L$20:L35)) -> 1996154.5 | Q35: =IF(D35=0,0,SUM($J$20:J35)) -> 2037130 | R35: =IF(D35=0,0,Q35-P35) -> 40975.501 | S35: =IFERROR(Q35/P35,"0%") -> 1.0205272 | U35: =IF(D35=0,0,SUM($L$20:L35)) -> 1996154.5 | V35: =IF(D35=0,0,SUM($J$20:J35)) -> 2037130 | W35: =IF(D35=0,0,V35-U35) -> 40975.501 | X35: =IFERROR(V35/U35,"0%") -> 1.0205272 | Z35: =Z34+1 -> 45307 | AA35: =AA34+1 -> 45307 | AB35: 45307 | AC35: 3 | AD35: 火 | AE35: =AVERAGEIFS(J80:J110,D80:D110,1,G80:G110,"tue") -> 263967.5 | AF35: =COUNTIFS( D80:D110,1,G80:G110,"tue") -> 4 | AH35: =AE35*AF35 -> 1055870 | AI35: =AH35/$M$8 -> 0.16343199 | AS35: =AS34+1 -> 45307
C36: =C35+1 -> 17 | D36: 1 | E36: =TEXT(AA36,"m") -> 1 | F36: =F35+1 -> 45308 | G36: =TEXT(AS36,"ddd") -> Wed | J36: 172600 | L36: =IF(D36=0,0,$K$6) -> 221794.94 | M36: =IF(D36=0,0,J36-L36) -> -49194.944 | N36: =IFERROR(J36/L36,"0%") -> 0.77819628 | P36: =IF(D36=0,0,SUM($L$20:L36)) -> 2217949.4 | Q36: =IF(D36=0,0,SUM($J$20:J36)) -> 2209730 | R36: =IF(D36=0,0,Q36-P36) -> -8219.4429 | S36: =IFERROR(Q36/P36,"0%") -> 0.99629413 | U36: =IF(D36=0,0,SUM($L$20:L36)) -> 2217949.4 | V36: =IF(D36=0,0,SUM($J$20:J36)) -> 2209730 | W36: =IF(D36=0,0,V36-U36) -> -8219.4429 | X36: =IFERROR(V36/U36,"0%") -> 0.99629413 | Z36: =Z35+1 -> 45308 | AA36: =AA35+1 -> 45308 | AB36: 45308 | AC36: 3 | AD36: 水 | AE36: =AVERAGEIFS(J80:J110,D80:D110,1,G80:G110,"wed") -> 293950 | AF36: =COUNTIFS( D80:D110,1,G80:G110,"wed") -> 3 | AH36: =AE36*AF36 -> 881850 | AI36: =AH36/$M$8 -> 0.13649644 | AS36: =AS35+1 -> 45308
C37: =C36+1 -> 18 | D37: 1 | E37: =TEXT(AA37,"m") -> 1 | F37: =F36+1 -> 45309 | G37: =TEXT(AS37,"ddd") -> Thu | J37: 155450 | L37: =IF(D37=0,0,$K$6) -> 221794.94 | M37: =IF(D37=0,0,J37-L37) -> -66344.944 | N37: =IFERROR(J37/L37,"0%") -> 0.7008726 | P37: =IF(D37=0,0,SUM($L$20:L37)) -> 2439744.4 | Q37: =IF(D37=0,0,SUM($J$20:J37)) -> 2365180 | R37: =IF(D37=0,0,Q37-P37) -> -74564.387 | S37: =IFERROR(Q37/P37,"0%") -> 0.96943762 | U37: =IF(D37=0,0,SUM($L$20:L37)) -> 2439744.4 | V37: =IF(D37=0,0,SUM($J$20:J37)) -> 2365180 | W37: =IF(D37=0,0,V37-U37) -> -74564.387 | X37: =IFERROR(V37/U37,"0%") -> 0.96943762 | Z37: =Z36+1 -> 45309 | AA37: =AA36+1 -> 45309 | AB37: 45309 | AC37: 3 | AD37: 木 | AE37: =AVERAGEIFS(J80:J110,D80:D110,1,G80:G110,"thu") -> 308607.5 | AF37: =COUNTIFS( D80:D110,1,G80:G110,"thu") -> 4 | AH37: =AE37*AF37 -> 1234430 | AI37: =AH37/$M$8 -> 0.19107025 | AS37: =AS36+1 -> 45309
C38: =C37+1 -> 19 | D38: 1 | E38: =TEXT(AA38,"m") -> 1 | F38: =F37+1 -> 45310 | G38: =TEXT(AS38,"ddd") -> Fri | J38: 286750 | L38: =IF(D38=0,0,$K$6) -> 221794.94 | M38: =IF(D38=0,0,J38-L38) -> 64955.056 | N38: =IFERROR(J38/L38,"0%") -> 1.2928608 | P38: =IF(D38=0,0,SUM($L$20:L38)) -> 2661539.3 | Q38: =IF(D38=0,0,SUM($J$20:J38)) -> 2651930 | R38: =IF(D38=0,0,Q38-P38) -> -9609.3315 | S38: =IFERROR(Q38/P38,"0%") -> 0.99638956 | U38: =IF(D38=0,0,SUM($L$20:L38)) -> 2661539.3 | V38: =IF(D38=0,0,SUM($J$20:J38)) -> 2651930 | W38: =IF(D38=0,0,V38-U38) -> -9609.3315 | X38: =IFERROR(V38/U38,"0%") -> 0.99638956 | Z38: =Z37+1 -> 45310 | AA38: =AA37+1 -> 45310 | AB38: 45310 | AC38: 3 | AD38: 金 | AE38: =AVERAGEIFS(J80:J110,D80:D110,1,G80:G110,"fri") -> 322626 | AF38: =COUNTIFS( D80:D110,1,G80:G110,"fri") -> 5 | AH38: =AE38*AF38 -> 1613130 | AI38: =AH38/$M$8 -> 0.24968703 | AS38: =AS37+1 -> 45310
C39: =C38+1 -> 20 | D39: 1 | E39: =TEXT(AA39,"m") -> 1 | F39: =F38+1 -> 45311 | G39: =TEXT(AS39,"ddd") -> Sat | J39: 139100 | L39: =IF(D39=0,0,$K$6) -> 221794.94 | M39: =IF(D39=0,0,J39-L39) -> -82694.944 | N39: =IFERROR(J39/L39,"0%") -> 0.62715586 | P39: =IF(D39=0,0,SUM($L$20:L39)) -> 2883334.3 | Q39: =IF(D39=0,0,SUM($J$20:J39)) -> 2791030 | R39: =IF(D39=0,0,Q39-P39) -> -92304.276 | S39: =IFERROR(Q39/P39,"0%") -> 0.96798697 | U39: =IF(D39=0,0,SUM($L$20:L39)) -> 2883334.3 | V39: =IF(D39=0,0,SUM($J$20:J39)) -> 2791030 | W39: =IF(D39=0,0,V39-U39) -> -92304.276 | X39: =IFERROR(V39/U39,"0%") -> 0.96798697 | Z39: =Z38+1 -> 45311 | AA39: =AA38+1 -> 45311 | AB39: 45311 | AC39: 3 | AD39: 土 | AE39: =AVERAGEIFS(J80:J110,D80:D110,1,G80:G110,"sat") -> 151895.6 | AF39: =COUNTIFS( D80:D110,1,G80:G110,"sat") -> 5 | AH39: =AE39*AF39 -> 759478 | AI39: =AH39/$M$8 -> 0.11755519 | AS39: =AS38+1 -> 45311
C40: =C39+1 -> 21 | D40: 0 | E40: =TEXT(AA40,"m") -> 1 | F40: =F39+1 -> 45312 | G40: =TEXT(AS40,"ddd") -> Sun | H40: 日曜日 | J40: 0 | L40: =IF(D40=0,0,$K$6) -> 0 | M40: =IF(D40=0,0,J40-L40) -> 0 | N40: =IFERROR(J40/L40,"0%") -> 0% | P40: =IF(D40=0,0,SUM($L$20:L40)) -> 0 | Q40: =IF(D40=0,0,SUM($J$20:J40)) -> 0 | R40: =IF(D40=0,0,Q40-P40) -> 0 | S40: =IFERROR(Q40/P40,"0%") -> 0% | U40: =IF(D40=0,0,SUM($L$20:L40)) -> 0 | V40: =IF(D40=0,0,SUM($J$20:J40)) -> 0 | W40: =IF(D40=0,0,V40-U40) -> 0 | X40: =IFERROR(V40/U40,"0%") -> 0% | Z40: =Z39+1 -> 45312 | AA40: =AA39+1 -> 45312 | AB40: 45312 | AC40: 3 | AD40: 日 | AE40: =IFERROR(AVERAGEIFS(J80:J110,D80:D110,3,G80:G110,"sun"),0) -> 0 | AF40: =IFERROR(COUNTIFS( D80:D110,1,G80:G110,"sun"),0) -> 0 | AH40: =AE40*AF40 -> 0 | AI40: =AH40/$M$8 -> 0 | AS40: =AS39+1 -> 45312
C41: =C40+1 -> 22 | D41: 1 | E41: =TEXT(AA41,"m") -> 1 | F41: =F40+1 -> 45313 | G41: =TEXT(AS41,"ddd") -> Mon | J41: 250550 | L41: =IF(D41=0,0,$K$6) -> 221794.94 | M41: =IF(D41=0,0,J41-L41) -> 28755.056 | N41: =IFERROR(J41/L41,"0%") -> 1.129647 | P41: =IF(D41=0,0,SUM($L$20:L41)) -> 3105129.2 | Q41: =IF(D41=0,0,SUM($J$20:J41)) -> 3041580 | R41: =IF(D41=0,0,Q41-P41) -> -63549.22 | S41: =IFERROR(Q41/P41,"0%") -> 0.97953411 | U41: =IF(D41=0,0,SUM($L$20:L41)) -> 3105129.2 | V41: =IF(D41=0,0,SUM($J$20:J41)) -> 3041580 | W41: =IF(D41=0,0,V41-U41) -> -63549.22 | X41: =IFERROR(V41/U41,"0%") -> 0.97953411 | Z41: =Z40+1 -> 45313 | AA41: =AA40+1 -> 45313 | AB41: 45313 | AC41: 4 | AD41: 月 | AE41: =AVERAGEIFS(J111:J140,D111:D140,1,G111:G140,"mon") -> 228365 | AF41: =COUNTIFS(D111:D140,1,G111:G140,"Mon") -> 4 | AH41: =AE41*AF41 -> 913460 | AI41: =AH41/$M$9 -> 0.13681398 | AJ41: =SUM(AI41:AI47) -> 1 | AK41: 111〜140 | AS41: =AS40+1 -> 45313
C42: =C41+1 -> 23 | D42: 1 | E42: =TEXT(AA42,"m") -> 1 | F42: =F41+1 -> 45314 | G42: =TEXT(AS42,"ddd") -> Tue | J42: 312544 | L42: =IF(D42=0,0,$K$6) -> 221794.94 | M42: =IF(D42=0,0,J42-L42) -> 90749.056 | N42: =IFERROR(J42/L42,"0%") -> 1.4091575 | P42: =IF(D42=0,0,SUM($L$20:L42)) -> 3326924.2 | Q42: =IF(D42=0,0,SUM($J$20:J42)) -> 3354124 | R42: =IF(D42=0,0,Q42-P42) -> 27199.836 | S42: =IFERROR(Q42/P42,"0%") -> 1.0081757 | U42: =IF(D42=0,0,SUM($L$20:L42)) -> 3326924.2 | V42: =IF(D42=0,0,SUM($J$20:J42)) -> 3354124 | W42: =IF(D42=0,0,V42-U42) -> 27199.836 | X42: =IFERROR(V42/U42,"0%") -> 1.0081757 | Z42: =Z41+1 -> 45314 | AA42: =AA41+1 -> 45314 | AB42: 45314 | AC42: 4 | AD42: 火 | AE42: =AVERAGEIFS(J111:J140,D111:D140,1,G111:G140,"tue") -> 269807.4 | AF42: =COUNTIFS(D111:D140,1,G111:G140,"tue") -> 5 | AH42: =AE42*AF42 -> 1349037 | AI42: =AH42/$M$9 -> 0.20205276 | AS42: =AS41+1 -> 45314
C43: =C42+1 -> 24 | D43: 1 | E43: =TEXT(AA43,"m") -> 1 | F43: =F42+1 -> 45315 | G43: =TEXT(AS43,"ddd") -> Wed | J43: 255500 | L43: =IF(D43=0,0,$K$6) -> 221794.94 | M43: =IF(D43=0,0,J43-L43) -> 33705.056 | N43: =IFERROR(J43/L43,"0%") -> 1.1519649 | P43: =IF(D43=0,0,SUM($L$20:L43)) -> 3548719.1 | Q43: =IF(D43=0,0,SUM($J$20:J43)) -> 3609624 | R43: =IF(D43=0,0,Q43-P43) -> 60904.891 | S43: =IFERROR(Q43/P43,"0%") -> 1.0171625 | U43: =IF(D43=0,0,SUM($L$20:L43)) -> 3548719.1 | V43: =IF(D43=0,0,SUM($J$20:J43)) -> 3609624 | W43: =IF(D43=0,0,V43-U43) -> 60904.891 | X43: =IFERROR(V43/U43,"0%") -> 1.0171625 | Z43: =Z42+1 -> 45315 | AA43: =AA42+1 -> 45315 | AB43: 45315 | AC43: 4 | AD43: 水 | AE43: =AVERAGEIFS(J111:J140,D111:D140,1,G111:G140,"wed") -> 292710 | AF43: =COUNTIFS(D111:D140,1,G111:G140,"wed") -> 4 | AH43: =AE43*AF43 -> 1170840 | AI43: =AH43/$M$9 -> 0.17536321 | AS43: =AS42+1 -> 45315
C44: =C43+1 -> 25 | D44: 1 | E44: =TEXT(AA44,"m") -> 1 | F44: =F43+1 -> 45316 | G44: =TEXT(AS44,"ddd") -> Thu | J44: 252450 | L44: =IF(D44=0,0,$K$6) -> 221794.94 | M44: =IF(D44=0,0,J44-L44) -> 30655.056 | N44: =IFERROR(J44/L44,"0%") -> 1.1382135 | P44: =IF(D44=0,0,SUM($L$20:L44)) -> 3770514.1 | Q44: =IF(D44=0,0,SUM($J$20:J44)) -> 3862074 | R44: =IF(D44=0,0,Q44-P44) -> 91559.947 | S44: =IFERROR(Q44/P44,"0%") -> 1.0242831 | U44: =IF(D44=0,0,SUM($L$20:L44)) -> 3770514.1 | V44: =IF(D44=0,0,SUM($J$20:J44)) -> 3862074 | W44: =IF(D44=0,0,V44-U44) -> 91559.947 | X44: =IFERROR(V44/U44,"0%") -> 1.0242831 | Z44: =Z43+1 -> 45316 | AA44: =AA43+1 -> 45316 | AB44: 45316 | AC44: 4 | AD44: 木 | AE44: =AVERAGEIFS(J111:J140,D111:D140,1,G111:G140,"thu") -> 278042.5 | AF44: =COUNTIFS(D111:D140,1,G111:G140,"thu") -> 4 | AH44: =AE44*AF44 -> 1112170 | AI44: =AH44/$M$9 -> 0.16657588 | AS44: =AS43+1 -> 45316
C45: =C44+1 -> 26 | D45: 1 | E45: =TEXT(AA45,"m") -> 1 | F45: =F44+1 -> 45317 | G45: =TEXT(AS45,"ddd") -> Fri | J45: 288150 | L45: =IF(D45=0,0,$K$6) -> 221794.94 | M45: =IF(D45=0,0,J45-L45) -> 66355.056 | N45: =IFERROR(J45/L45,"0%") -> 1.299173 | P45: =IF(D45=0,0,SUM($L$20:L45)) -> 3992309 | Q45: =IF(D45=0,0,SUM($J$20:J45)) -> 4150224 | R45: =IF(D45=0,0,Q45-P45) -> 157915 | S45: =IFERROR(Q45/P45,"0%") -> 1.0395548 | U45: =IF(D45=0,0,SUM($L$20:L45)) -> 3992309 | V45: =IF(D45=0,0,SUM($J$20:J45)) -> 4150224 | W45: =IF(D45=0,0,V45-U45) -> 157915 | X45: =IFERROR(V45/U45,"0%") -> 1.0395548 | Z45: =Z44+1 -> 45317 | AA45: =AA44+1 -> 45317 | AB45: 45317 | AC45: 4 | AD45: 金 | AE45: =AVERAGEIFS(J111:J140,D111:D140,1,G111:G140,"fri") -> 331130 | AF45: =COUNTIFS(D111:D140,1,G111:G140,"fri") -> 4 | AH45: =AE45*AF45 -> 1324520 | AI45: =AH45/$M$9 -> 0.19838072 | AS45: =AS44+1 -> 45317
C46: =C45+1 -> 27 | D46: 1 | E46: =TEXT(AA46,"m") -> 1 | F46: =F45+1 -> 45318 | G46: =TEXT(AS46,"ddd") -> Sat | J46: 114650 | L46: =IF(D46=0,0,$K$6) -> 221794.94 | M46: =IF(D46=0,0,J46-L46) -> -107144.94 | N46: =IFERROR(J46/L46,"0%") -> 0.51691891 | P46: =IF(D46=0,0,SUM($L$20:L46)) -> 4214103.9 | Q46: =IF(D46=0,0,SUM($J$20:J46)) -> 4264874 | R46: =IF(D46=0,0,Q46-P46) -> 50770.058 | S46: =IFERROR(Q46/P46,"0%") -> 1.0120477 | U46: =IF(D46=0,0,SUM($L$20:L46)) -> 4214103.9 | V46: =IF(D46=0,0,SUM($J$20:J46)) -> 4264874 | W46: =IF(D46=0,0,V46-U46) -> 50770.058 | X46: =IFERROR(V46/U46,"0%") -> 1.0120477 | Z46: =Z45+1 -> 45318 | AA46: =AA45+1 -> 45318 | AB46: 45318 | AC46: 4 | AD46: 土 | AE46: =AVERAGEIFS(J111:J140,D111:D140,1,G111:G140,"sat") -> 201657.5 | AF46: =COUNTIFS(D111:D140,1,G111:G140,"sat") -> 4 | AH46: =AE46*AF46 -> 806630 | AI46: =AH46/$M$9 -> 0.12081345 | AS46: =AS45+1 -> 45318
C47: =C46+1 -> 28 | D47: 0 | E47: =TEXT(AA47,"m") -> 1 | F47: =F46+1 -> 45319 | G47: =TEXT(AS47,"ddd") -> Sun | H47: 日曜日 | J47: 0 | L47: =IF(D47=0,0,$K$6) -> 0 | M47: =IF(D47=0,0,J47-L47) -> 0 | N47: =IFERROR(J47/L47,"0%") -> 0% | P47: =IF(D47=0,0,SUM($L$20:L47)) -> 0 | Q47: =IF(D47=0,0,SUM($J$20:J47)) -> 0 | R47: =IF(D47=0,0,Q47-P47) -> 0 | S47: =IFERROR(Q47/P47,"0%") -> 0% | U47: =IF(D47=0,0,SUM($L$20:L47)) -> 0 | V47: =IF(D47=0,0,SUM($J$20:J47)) -> 0 | W47: =IF(D47=0,0,V47-U47) -> 0 | X47: =IFERROR(V47/U47,"0%") -> 0% | Z47: =Z46+1 -> 45319 | AA47: =AA46+1 -> 45319 | AB47: 45319 | AC47: 4 | AD47: 日 | AE47: =IFERROR(AVERAGEIFS(J111:J140,D111:D140,1,G111:G140,"sun"),0) -> 0 | AF47: =IFERROR(COUNTIFS(D111:D140,1,G111:G140,"sun"),0) -> 0 | AH47: =AE47*AF47 -> 0 | AI47: =AH47/$M$9 -> 0 | AS47: =AS46+1 -> 45319
C48: =C47+1 -> 29 | D48: 1 | E48: =TEXT(AA48,"m") -> 1 | F48: =F47+1 -> 45320 | G48: =TEXT(AS48,"ddd") -> Mon | J48: 322450 | L48: =IF(D48=0,0,$K$6) -> 221794.94 | M48: =IF(D48=0,0,J48-L48) -> 100655.06 | N48: =IFERROR(J48/L48,"0%") -> 1.4538203 | P48: =IF(D48=0,0,SUM($L$20:L48)) -> 4435898.9 | Q48: =IF(D48=0,0,SUM($J$20:J48)) -> 4587324 | R48: =IF(D48=0,0,Q48-P48) -> 151425.11 | S48: =IFERROR(Q48/P48,"0%") -> 1.0341363 | U48: =IF(D48=0,0,SUM($L$20:L48)) -> 4435898.9 | V48: =IF(D48=0,0,SUM($J$20:J48)) -> 4587324 | W48: =IF(D48=0,0,V48-U48) -> 151425.11 | X48: =IFERROR(V48/U48,"0%") -> 1.0341363 | Z48: =Z47+1 -> 45320 | AA48: =AA47+1 -> 45320 | AB48: 45320 | AC48: 5 | AD48: 月 | AE48: =AVERAGEIFS(J141:J171,D141:D171,1,G141:G171,"mon") -> 238610 | AF48: =COUNTIFS(D141:D171,1,G141:G171,"Mon") -> 3 | AH48: =AE48*AF48 -> 715830 | AI48: =AH48/$M$10 -> 0.11611173 | AJ48: =SUM(AI48:AI54) -> 1 | AK48: 141〜171 | AS48: =AS47+1 -> 45320
C49: =C48+1 -> 30 | D49: 1 | E49: =TEXT(AA49,"m") -> 1 | F49: =F48+1 -> 45321 | G49: =TEXT(AS49,"ddd") -> Tue | J49: 188550 | L49: =IF(D49=0,0,$K$6) -> 221794.94 | M49: =IF(D49=0,0,J49-L49) -> -33244.944 | N49: =IFERROR(J49/L49,"0%") -> 0.85010955 | P49: =IF(D49=0,0,SUM($L$20:L49)) -> 4657693.8 | Q49: =IF(D49=0,0,SUM($J$20:J49)) -> 4775874 | R49: =IF(D49=0,0,Q49-P49) -> 118180.17 | S49: =IFERROR(Q49/P49,"0%") -> 1.0253731 | U49: =IF(D49=0,0,SUM($L$20:L49)) -> 4657693.8 | V49: =IF(D49=0,0,SUM($J$20:J49)) -> 4775874 | W49: =IF(D49=0,0,V49-U49) -> 118180.17 | X49: =IFERROR(V49/U49,"0%") -> 1.0253731 | Z49: =Z48+1 -> 45321 | AA49: =AA48+1 -> 45321 | AB49: 45321 | AC49: 5 | AD49: 火 | AE49: =AVERAGEIFS(J141:J171,D141:D171,1,G141:G171,"tue") -> 232011.25 | AF49: =COUNTIFS(D141:D171,1,G141:G171,"tue") -> 4 | AH49: =AE49*AF49 -> 928045 | AI49: =AH49/$M$10 -> 0.15053422 | AS49: =AS48+1 -> 45321
C50: =C49+1 -> 31 | D50: 1 | E50: =TEXT(AA50,"m") -> 1 | F50: =F49+1 -> 45322 | G50: =TEXT(AS50,"ddd") -> Wed | J50: 206500 | L50: =IF(D50=0,0,$K$6) -> 221794.94 | M50: =IF(D50=0,0,J50-L50) -> -15294.944 | N50: =IFERROR(J50/L50,"0%") -> 0.93104016 | P50: =IF(D50=0,0,SUM($L$20:L50)) -> 4879488.8 | Q50: =IF(D50=0,0,SUM($J$20:J50)) -> 4982374 | R50: =IF(D50=0,0,Q50-P50) -> 102885.23 | S50: =IFERROR(Q50/P50,"0%") -> 1.0210852 | U50: =IF(D50=0,0,SUM($L$20:L50)) -> 4879488.8 | V50: =IF(D50=0,0,SUM($J$20:J50)) -> 4982374 | W50: =IF(D50=0,0,V50-U50) -> 102885.23 | X50: =IFERROR(V50/U50,"0%") -> 1.0210852 | Z50: =Z49+1 -> 45322 | AA50: =AA49+1 -> 45322 | AB50: 45322 | AC50: 5 | AD50: 水 | AE50: =AVERAGEIFS(J141:J171,D141:D171,1,G141:G171,"wed") -> 320767 | AF50: =COUNTIFS(D141:D171,1,G141:G171,"wed") -> 5 | AH50: =AE50*AF50 -> 1603835 | AI50: =AH50/$M$10 -> 0.26015124 | AS50: =AS49+1 -> 45322
C51: =C50+1 -> 32 | D51: 1 | E51: =TEXT(AA51,"m") -> 2 | F51: =F50+1 -> 45323 | G51: =TEXT(AS51,"ddd") -> Thu | J51: 218090 | L51: =IF(D51=0,0,$K$7) -> 209473 | M51: =IF(D51=0,0,J51-L51) -> 8616.9971 | N51: =IFERROR(J51/L51,"0%") -> 1.0411366 | P51: =IF(D51=0,0,$L$51) -> 209473 | Q51: =IF(D51=0,0,$J$51) -> 218090 | R51: =IF(D51=0,0,Q51-P51) -> 8616.9971 | S51: =IFERROR(Q51/P51,"0%") -> 1.0411366 | U51: =IF(D51=0,0,SUM($L$20:L51)) -> 5088961.8 | V51: =IF(D51=0,0,SUM($J$20:J51)) -> 5200464 | W51: =IF(D51=0,0,V51-U51) -> 111502.22 | X51: =IFERROR(V51/U51,"0%") -> 1.0219106 | Z51: =Z50+1 -> 45323 | AA51: =AA50+1 -> 45323 | AB51: 45323 | AC51: 5 | AD51: 木 | AE51: =AVERAGEIFS(J141:J171,D141:D171,1,G141:G171,"thu") -> 220418 | AF51: =COUNTIFS(D141:D171,1,G141:G171,"thu") -> 5 | AH51: =AE51*AF51 -> 1102090 | AI51: =AH51/$M$10 -> 0.17876532 | AS51: =AS50+1 -> 45323
C52: =C51+1 -> 33 | D52: 1 | E52: =TEXT(AA52,"m") -> 2 | F52: =F51+1 -> 45324 | G52: =TEXT(AS52,"ddd") -> Fri | J52: 236480 | L52: =IF(D52=0,0,$K$7) -> 209473 | M52: =IF(D52=0,0,J52-L52) -> 27006.997 | N52: =IFERROR(J52/L52,"0%") -> 1.1289283 | P52: =IF(D52=0,0,SUM($L$51:L52)) -> 418946.01 | Q52: =IF(D52=0,0,SUM($J$51:J52)) -> 454570 | R52: =IF(D52=0,0,Q52-P52) -> 35623.994 | S52: =IFERROR(Q52/P52,"0%") -> 1.0850324 | U52: =IF(D52=0,0,SUM($L$20:L52)) -> 5298434.8 | V52: =IF(D52=0,0,SUM($J$20:J52)) -> 5436944 | W52: =IF(D52=0,0,V52-U52) -> 138509.22 | X52: =IFERROR(V52/U52,"0%") -> 1.0261415 | Z52: =Z51+1 -> 45324 | AA52: =AA51+1 -> 45324 | AB52: 45324 | AC52: 5 | AD52: 金 | AE52: =AVERAGEIFS(J141:J171,D141:D171,1,G141:G171,"fri") -> 350012.5 | AF52: =COUNTIFS(D141:D171,1,G141:G171,"fri") -> 4 | AH52: =AE52*AF52 -> 1400050 | AI52: =AH52/$M$10 -> 0.22709614 | AS52: =AS51+1 -> 45324
C53: =C52+1 -> 34 | D53: 1 | E53: =TEXT(AA53,"m") -> 2 | F53: =F52+1 -> 45325 | G53: =TEXT(AS53,"ddd") -> Sat | J53: 113750 | L53: =IF(D53=0,0,$K$7) -> 209473 | M53: =IF(D53=0,0,J53-L53) -> -95723.003 | N53: =IFERROR(J53/L53,"0%") -> 0.5430294 | P53: =IF(D53=0,0,SUM($L$51:L53)) -> 628419.01 | Q53: =IF(D53=0,0,SUM($J$51:J53)) -> 568320 | R53: =IF(D53=0,0,Q53-P53) -> -60099.009 | S53: =IFERROR(Q53/P53,"0%") -> 0.90436475 | U53: =IF(D53=0,0,SUM($L$20:L53)) -> 5507907.8 | V53: =IF(D53=0,0,SUM($J$20:J53)) -> 5550694 | W53: =IF(D53=0,0,V53-U53) -> 42786.217 | X53: =IFERROR(V53/U53,"0%") -> 1.0077681 | Z53: =Z52+1 -> 45325 | AA53: =AA52+1 -> 45325 | AB53: 45325 | AC53: 5 | AD53: 土 | AE53: =AVERAGEIFS(J141:J171,D141:D171,1,G141:G171,"sat") -> 138386.67 | AF53: =COUNTIFS(D141:D171,1,G141:G171,"sat") -> 3 | AH53: =AE53*AF53 -> 415160 | AI53: =AH53/$M$10 -> 0.067341334 | AS53: =AS52+1 -> 45325
C54: =C53+1 -> 35 | D54: 0 | E54: =TEXT(AA54,"m") -> 2 | F54: =F53+1 -> 45326 | G54: =TEXT(AS54,"ddd") -> Sun | H54: 日曜日 | J54: 0 | L54: =IF(D54=0,0,$K$7) -> 0 | M54: =IF(D54=0,0,J54-L54) -> 0 | N54: =IFERROR(J54/L54,"0%") -> 0% | P54: =IF(D54=0,0,SUM($L$51:L54)) -> 0 | Q54: =IF(D54=0,0,SUM($J$51:J54)) -> 0 | R54: =IF(D54=0,0,Q54-P54) -> 0 | S54: =IFERROR(Q54/P54,"0%") -> 0% | U54: =IF(D54=0,0,SUM($L$20:L54)) -> 0 | V54: =IF(D54=0,0,SUM($J$20:J54)) -> 0 | W54: =IF(D54=0,0,V54-U54) -> 0 | X54: =IFERROR(V54/U54,"0%") -> 0% | Z54: =Z53+1 -> 45326 | AA54: =AA53+1 -> 45326 | AB54: 45326 | AC54: 5 | AD54: 日 | AE54: =IFERROR(AVERAGEIFS(J141:J171,D141:D171,1,G141:G171,"sun"),0) -> 0 | AF54: =IFERROR(COUNTIFS(D141:D171,1,G141:G171,"sun"),0) -> 0 | AH54: =AE54*AF54 -> 0 | AI54: =AH54/$M$10 -> 0 | AS54: =AS53+1 -> 45326
C55: =C54+1 -> 36 | D55: 1 | E55: =TEXT(AA55,"m") -> 2 | F55: =F54+1 -> 45327 | G55: =TEXT(AS55,"ddd") -> Mon | J55: 155200 | L55: =IF(D55=0,0,$K$7) -> 209473 | M55: =IF(D55=0,0,J55-L55) -> -54273.003 | N55: =IFERROR(J55/L55,"0%") -> 0.74090693 | P55: =IF(D55=0,0,SUM($L$51:L55)) -> 837892.01 | Q55: =IF(D55=0,0,SUM($J$51:J55)) -> 723520 | R55: =IF(D55=0,0,Q55-P55) -> -114372.01 | S55: =IFERROR(Q55/P55,"0%") -> 0.8635003 | U55: =IF(D55=0,0,SUM($L$20:L55)) -> 5717380.8 | V55: =IF(D55=0,0,SUM($J$20:J55)) -> 5705894 | W55: =IF(D55=0,0,V55-U55) -> -11486.786 | X55: =IFERROR(V55/U55,"0%") -> 0.9979909 | Z55: =Z54+1 -> 45327 | AA55: =AA54+1 -> 45327 | AB55: 45327 | AC55: 6 | AD55: 月 | AE55: =AVERAGEIFS(J172:J201,D172:D201,1,G172:G201,"mon") -> 192255 | AF55: =COUNTIFS(D172:D201,1,G172:G201,"Mon") -> 4 | AH55: =AE55*AF55 -> 769020 | AI55: =AH55/$M$11 -> 0.13016698 | AJ55: =SUM(AI55:AI61) -> 1 | AK55: 172〜201 | AS55: =AS54+1 -> 45327
C56: =C55+1 -> 37 | D56: 1 | E56: =TEXT(AA56,"m") -> 2 | F56: =F55+1 -> 45328 | G56: =TEXT(AS56,"ddd") -> Tue | J56: 191910 | L56: =IF(D56=0,0,$K$7) -> 209473 | M56: =IF(D56=0,0,J56-L56) -> -17563.003 | N56: =IFERROR(J56/L56,"0%") -> 0.91615625 | P56: =IF(D56=0,0,SUM($L$51:L56)) -> 1047365 | Q56: =IF(D56=0,0,SUM($J$51:J56)) -> 915430 | R56: =IF(D56=0,0,Q56-P56) -> -131935.01 | S56: =IFERROR(Q56/P56,"0%") -> 0.87403149 | U56: =IF(D56=0,0,SUM($L$20:L56)) -> 5926853.8 | V56: =IF(D56=0,0,SUM($J$20:J56)) -> 5897804 | W56: =IF(D56=0,0,V56-U56) -> -29049.789 | X56: =IFERROR(V56/U56,"0%") -> 0.99509862 | Z56: =Z55+1 -> 45328 | AA56: =AA55+1 -> 45328 | AB56: 45328 | AC56: 6 | AD56: 火 | AE56: =AVERAGEIFS(J172:J201,D172:D201,1,G172:G201,"tue") -> 204712.5 | AF56: =COUNTIFS(D172:D201,1,G172:G201,"tue") -> 4 | AH56: =AE56*AF56 -> 818850 | AI56: =AH56/$M$11 -> 0.13860138 | AS56: =AS55+1 -> 45328
C57: =C56+1 -> 38 | D57: 1 | E57: =TEXT(AA57,"m") -> 2 | F57: =F56+1 -> 45329 | G57: =TEXT(AS57,"ddd") -> Wed | J57: 331350 | L57: =IF(D57=0,0,$K$7) -> 209473 | M57: =IF(D57=0,0,J57-L57) -> 121877 | N57: =IFERROR(J57/L57,"0%") -> 1.5818268 | P57: =IF(D57=0,0,SUM($L$51:L57)) -> 1256838 | Q57: =IF(D57=0,0,SUM($J$51:J57)) -> 1246780 | R57: =IF(D57=0,0,Q57-P57) -> -10058.018 | S57: =IFERROR(Q57/P57,"0%") -> 0.99199736 | U57: =IF(D57=0,0,SUM($L$20:L57)) -> 6136326.8 | V57: =IF(D57=0,0,SUM($J$20:J57)) -> 6229154 | W57: =IF(D57=0,0,V57-U57) -> 92827.208 | X57: =IFERROR(V57/U57,"0%") -> 1.0151275 | Z57: =Z56+1 -> 45329 | AA57: =AA56+1 -> 45329 | AB57: 45329 | AC57: 6 | AD57: 水 | AE57: =AVERAGEIFS(J172:J201,D172:D201,1,G172:G201,"wed") -> 308407.5 | AF57: =COUNTIFS(D172:D201,1,G172:G201,"wed") -> 4 | AH57: =AE57*AF57 -> 1233630 | AI57: =AH57/$M$11 -> 0.20880847 | AS57: =AS56+1 -> 45329
C58: =C57+1 -> 39 | D58: 1 | E58: =TEXT(AA58,"m") -> 2 | F58: =F57+1 -> 45330 | G58: =TEXT(AS58,"ddd") -> Thu | J58: 178550 | L58: =IF(D58=0,0,$K$7) -> 209473 | M58: =IF(D58=0,0,J58-L58) -> -30923.003 | N58: =IFERROR(J58/L58,"0%") -> 0.85237714 | P58: =IF(D58=0,0,SUM($L$51:L58)) -> 1466311 | Q58: =IF(D58=0,0,SUM($J$51:J58)) -> 1425330 | R58: =IF(D58=0,0,Q58-P58) -> -40981.021 | S58: =IFERROR(Q58/P58,"0%") -> 0.97205162 | U58: =IF(D58=0,0,SUM($L$20:L58)) -> 6345799.8 | V58: =IF(D58=0,0,SUM($J$20:J58)) -> 6407704 | W58: =IF(D58=0,0,V58-U58) -> 61904.205 | X58: =IFERROR(V58/U58,"0%") -> 1.0097551 | Z58: =Z57+1 -> 45330 | AA58: =AA57+1 -> 45330 | AB58: 45330 | AC58: 6 | AD58: 木 | AE58: =AVERAGEIFS(J172:J201,D172:D201,1,G172:G201,"thu") -> 279470 | AF58: =COUNTIFS(D172:D201,1,G172:G201,"thu") -> 4 | AH58: =AE58*AF58 -> 1117880 | AI58: =AH58/$M$11 -> 0.18921623 | AS58: =AS57+1 -> 45330
C59: =C58+1 -> 40 | D59: 1 | E59: =TEXT(AA59,"m") -> 2 | F59: =F58+1 -> 45331 | G59: =TEXT(AS59,"ddd") -> Fri | J59: 291050 | L59: =IF(D59=0,0,$K$7) -> 209473 | M59: =IF(D59=0,0,J59-L59) -> 81576.997 | N59: =IFERROR(J59/L59,"0%") -> 1.3894392 | P59: =IF(D59=0,0,SUM($L$51:L59)) -> 1675784 | Q59: =IF(D59=0,0,SUM($J$51:J59)) -> 1716380 | R59: =IF(D59=0,0,Q59-P59) -> 40595.976 | S59: =IFERROR(Q59/P59,"0%") -> 1.0242251 | U59: =IF(D59=0,0,SUM($L$20:L59)) -> 6555272.8 | V59: =IF(D59=0,0,SUM($J$20:J59)) -> 6698754 | W59: =IF(D59=0,0,V59-U59) -> 143481.2 | X59: =IFERROR(V59/U59,"0%") -> 1.0218879 | Z59: =Z58+1 -> 45331 | AA59: =AA58+1 -> 45331 | AB59: 45331 | AC59: 6 | AD59: 金 | AE59: =AVERAGEIFS(J172:J201,D172:D201,1,G172:G201,"fri") -> 322747.5 | AF59: =COUNTIFS(D172:D201,1,G172:G201,"fri") -> 4 | AH59: =AE59*AF59 -> 1290990 | AI59: =AH59/$M$11 -> 0.21851742 | AS59: =AS58+1 -> 45331
C60: =C59+1 -> 41 | D60: 1 | E60: =TEXT(AA60,"m") -> 2 | F60: =F59+1 -> 45332 | G60: =TEXT(AS60,"ddd") -> Sat | J60: 222220 | L60: =IF(D60=0,0,$K$7) -> 209473 | M60: =IF(D60=0,0,J60-L60) -> 12746.997 | N60: =IFERROR(J60/L60,"0%") -> 1.0608527 | P60: =IF(D60=0,0,SUM($L$51:L60)) -> 1885257 | Q60: =IF(D60=0,0,SUM($J$51:J60)) -> 1938600 | R60: =IF(D60=0,0,Q60-P60) -> 53342.974 | S60: =IFERROR(Q60/P60,"0%") -> 1.0282948 | U60: =IF(D60=0,0,SUM($L$20:L60)) -> 6764745.8 | V60: =IF(D60=0,0,SUM($J$20:J60)) -> 6920974 | W60: =IF(D60=0,0,V60-U60) -> 156228.2 | X60: =IFERROR(V60/U60,"0%") -> 1.0230945 | Z60: =Z59+1 -> 45332 | AA60: =AA59+1 -> 45332 | AB60: 45332 | AC60: 6 | AD60: 土 | AE60: =AVERAGEIFS(J172:J201,D172:D201,1,G172:G201,"sat") -> 135516 | AF60: =COUNTIFS(D172:D201,1,G172:G201,"sat") -> 5 | AH60: =AE60*AF60 -> 677580 | AI60: =AH60/$M$11 -> 0.11468953 | AS60: =AS59+1 -> 45332
C61: =C60+1 -> 42 | D61: 0 | E61: =TEXT(AA61,"m") -> 2 | F61: =F60+1 -> 45333 | G61: =TEXT(AS61,"ddd") -> Sun | H61: 日曜日 | J61: 0 | L61: =IF(D61=0,0,$K$7) -> 0 | M61: =IF(D61=0,0,J61-L61) -> 0 | N61: =IFERROR(J61/L61,"0%") -> 0% | P61: =IF(D61=0,0,SUM($L$51:L61)) -> 0 | Q61: =IF(D61=0,0,SUM($J$51:J61)) -> 0 | R61: =IF(D61=0,0,Q61-P61) -> 0 | S61: =IFERROR(Q61/P61,"0%") -> 0% | U61: =IF(D61=0,0,SUM($L$20:L61)) -> 0 | V61: =IF(D61=0,0,SUM($J$20:J61)) -> 0 | W61: =IF(D61=0,0,V61-U61) -> 0 | X61: =IFERROR(V61/U61,"0%") -> 0% | Z61: =Z60+1 -> 45333 | AA61: =AA60+1 -> 45333 | AB61: 45333 | AC61: 6 | AD61: 日 | AE61: =IFERROR(AVERAGEIFS(J172:J201,D172:D201,1,G172:G201,"sun"),0) -> 0 | AF61: =IFERROR(COUNTIFS(D172:D201,1,G172:G201,"sun"),0) -> 0 | AH61: =AE61*AF61 -> 0 | AI61: =AH61/$M$11 -> 0 | AS61: =AS60+1 -> 45333
C62: =C61+1 -> 43 | D62: 0 | E62: =TEXT(AA62,"m") -> 2 | F62: =F61+1 -> 45334 | G62: =TEXT(AS62,"ddd") -> Mon | H62: 祝日 | J62: 0 | L62: =IF(D62=0,0,$K$7) -> 0 | M62: =IF(D62=0,0,J62-L62) -> 0 | N62: =IFERROR(J62/L62,"0%") -> 0% | P62: =IF(D62=0,0,SUM($L$51:L62)) -> 0 | Q62: =IF(D62=0,0,SUM($J$51:J62)) -> 0 | R62: =IF(D62=0,0,Q62-P62) -> 0 | S62: =IFERROR(Q62/P62,"0%") -> 0% | U62: =IF(D62=0,0,SUM($L$20:L62)) -> 0 | V62: =IF(D62=0,0,SUM($J$20:J62)) -> 0 | W62: =IF(D62=0,0,V62-U62) -> 0 | X62: =IFERROR(V62/U62,"0%") -> 0% | Z62: =Z61+1 -> 45334 | AA62: =AA61+1 -> 45334 | AB62: 45334 | AC62: 7 | AD62: 月 | AE62: =AVERAGEIFS(J202:J232,D202:D232,1,G202:G232,"mon") -> 247005 | AF62: =COUNTIFS(D202:D232,1,G202:G232,"Mon") -> 4 | AH62: =AE62*AF62 -> 988020 | AI62: =AH62/$M$12 -> 0.15148604 | AJ62: =SUM(AI62:AI68) -> 1 | AK62: 202〜232 | AS62: =AS61+1 -> 45334
C63: =C62+1 -> 44 | D63: 1 | E63: =TEXT(AA63,"m") -> 2 | F63: =F62+1 -> 45335 | G63: =TEXT(AS63,"ddd") -> Tue | J63: 138350 | L63: =IF(D63=0,0,$K$7) -> 209473 | M63: =IF(D63=0,0,J63-L63) -> -71123.003 | N63: =IFERROR(J63/L63,"0%") -> 0.66046697 | P63: =IF(D63=0,0,SUM($L$51:L63)) -> 2094730 | Q63: =IF(D63=0,0,SUM($J$51:J63)) -> 2076950 | R63: =IF(D63=0,0,Q63-P63) -> -17780.029 | S63: =IFERROR(Q63/P63,"0%") -> 0.99151202 | U63: =IF(D63=0,0,SUM($L$20:L63)) -> 6974218.8 | V63: =IF(D63=0,0,SUM($J$20:J63)) -> 7059324 | W63: =IF(D63=0,0,V63-U63) -> 85105.196 | X63: =IFERROR(V63/U63,"0%") -> 1.0122028 | Z63: =Z62+1 -> 45335 | AA63: =AA62+1 -> 45335 | AB63: 45335 | AC63: 7 | AD63: 火 | AE63: =AVERAGEIFS(J202:J232,D202:D232,1,G202:G232,"tue") -> 186148 | AF63: =COUNTIFS(D202:D232,1,G202:G232,"tue") -> 5 | AH63: =AE63*AF63 -> 930740 | AI63: =AH63/$M$12 -> 0.14270371 | AS63: =AS62+1 -> 45335
C64: =C63+1 -> 45 | D64: 1 | E64: =TEXT(AA64,"m") -> 2 | F64: =F63+1 -> 45336 | G64: =TEXT(AS64,"ddd") -> Wed | J64: 185750 | L64: =IF(D64=0,0,$K$7) -> 209473 | M64: =IF(D64=0,0,J64-L64) -> -23723.003 | N64: =IFERROR(J64/L64,"0%") -> 0.88674912 | P64: =IF(D64=0,0,SUM($L$51:L64)) -> 2304203 | Q64: =IF(D64=0,0,SUM($J$51:J64)) -> 2262700 | R64: =IF(D64=0,0,Q64-P64) -> -41503.032 | S64: =IFERROR(Q64/P64,"0%") -> 0.98198812 | U64: =IF(D64=0,0,SUM($L$20:L64)) -> 7183691.8 | V64: =IF(D64=0,0,SUM($J$20:J64)) -> 7245074 | W64: =IF(D64=0,0,V64-U64) -> 61382.193 | X64: =IFERROR(V64/U64,"0%") -> 1.0085447 | Z64: =Z63+1 -> 45336 | AA64: =AA63+1 -> 45336 | AB64: 45336 | AC64: 7 | AD64: 水 | AE64: =AVERAGEIFS(J202:J232,D202:D232,1,G202:G232,"wed") -> 269772 | AF64: =COUNTIFS(D202:D232,1,G202:G232,"wed") -> 5 | AH64: =AE64*AF64 -> 1348860 | AI64: =AH64/$M$12 -> 0.20681106 | AS64: =AS63+1 -> 45336
C65: =C64+1 -> 46 | D65: 1 | E65: =TEXT(AA65,"m") -> 2 | F65: =F64+1 -> 45337 | G65: =TEXT(AS65,"ddd") -> Thu | J65: 270370 | L65: =IF(D65=0,0,$K$7) -> 209473 | M65: =IF(D65=0,0,J65-L65) -> 60896.997 | N65: =IFERROR(J65/L65,"0%") -> 1.2907153 | P65: =IF(D65=0,0,SUM($L$51:L65)) -> 2513676 | Q65: =IF(D65=0,0,SUM($J$51:J65)) -> 2533070 | R65: =IF(D65=0,0,Q65-P65) -> 19393.965 | S65: =IFERROR(Q65/P65,"0%") -> 1.0077154 | U65: =IF(D65=0,0,SUM($L$20:L65)) -> 7393164.8 | V65: =IF(D65=0,0,SUM($J$20:J65)) -> 7515444 | W65: =IF(D65=0,0,V65-U65) -> 122279.19 | X65: =IFERROR(V65/U65,"0%") -> 1.0165395 | Z65: =Z64+1 -> 45337 | AA65: =AA64+1 -> 45337 | AB65: 45337 | AC65: 7 | AD65: 木 | AE65: =AVERAGEIFS(J202:J232,D202:D232,1,G202:G232,"thu") -> 302282.5 | AF65: =COUNTIFS(D202:D232,1,G202:G232,"thu") -> 4 | AH65: =AE65*AF65 -> 1209130 | AI65: =AH65/$M$12 -> 0.18538726 | AS65: =AS64+1 -> 45337
C66: =C65+1 -> 47 | D66: 1 | E66: =TEXT(AA66,"m") -> 2 | F66: =F65+1 -> 45338 | G66: =TEXT(AS66,"ddd") -> Fri | J66: 324150 | L66: =IF(D66=0,0,$K$7) -> 209473 | M66: =IF(D66=0,0,J66-L66) -> 114677 | N66: =IFERROR(J66/L66,"0%") -> 1.5474548 | P66: =IF(D66=0,0,SUM($L$51:L66)) -> 2723149 | Q66: =IF(D66=0,0,SUM($J$51:J66)) -> 2857220 | R66: =IF(D66=0,0,Q66-P66) -> 134070.96 | S66: =IFERROR(Q66/P66,"0%") -> 1.0492338 | U66: =IF(D66=0,0,SUM($L$20:L66)) -> 7602637.8 | V66: =IF(D66=0,0,SUM($J$20:J66)) -> 7839594 | W66: =IF(D66=0,0,V66-U66) -> 236956.19 | X66: =IFERROR(V66/U66,"0%") -> 1.0311676 | Z66: =Z65+1 -> 45338 | AA66: =AA65+1 -> 45338 | AB66: 45338 | AC66: 7 | AD66: 金 | AE66: =AVERAGEIFS(J202:J232,D202:D232,1,G202:G232,"fri") -> 362762.5 | AF66: =COUNTIFS(D202:D232,1,G202:G232,"fri") -> 4 | AH66: =AE66*AF66 -> 1451050 | AI66: =AH66/$M$12 -> 0.22247912 | AS66: =AS65+1 -> 45338
C67: =C66+1 -> 48 | D67: 1 | E67: =TEXT(AA67,"m") -> 2 | F67: =F66+1 -> 45339 | G67: =TEXT(AS67,"ddd") -> Sat | J67: 136800 | L67: =IF(D67=0,0,$K$7) -> 209473 | M67: =IF(D67=0,0,J67-L67) -> -72673.003 | N67: =IFERROR(J67/L67,"0%") -> 0.65306745 | P67: =IF(D67=0,0,SUM($L$51:L67)) -> 2932622 | Q67: =IF(D67=0,0,SUM($J$51:J67)) -> 2994020 | R67: =IF(D67=0,0,Q67-P67) -> 61397.959 | S67: =IFERROR(Q67/P67,"0%") -> 1.0209362 | U67: =IF(D67=0,0,SUM($L$20:L67)) -> 7812110.8 | V67: =IF(D67=0,0,SUM($J$20:J67)) -> 7976394 | W67: =IF(D67=0,0,V67-U67) -> 164283.18 | X67: =IFERROR(V67/U67,"0%") -> 1.0210293 | Z67: =Z66+1 -> 45339 | AA67: =AA66+1 -> 45339 | AB67: 45339 | AC67: 7 | AD67: 土 | AE67: =AVERAGEIFS(J202:J232,D202:D232,1,G202:G232,"sat") -> 148596.25 | AF67: =COUNTIFS(D202:D232,1,G202:G232,"sat") -> 4 | AH67: =AE67*AF67 -> 594385 | AI67: =AH67/$M$12 -> 0.091132803 | AS67: =AS66+1 -> 45339
C68: =C67+1 -> 49 | D68: 0 | E68: =TEXT(AA68,"m") -> 2 | F68: =F67+1 -> 45340 | G68: =TEXT(AS68,"ddd") -> Sun | H68: 日曜日 | J68: 0 | L68: =IF(D68=0,0,$K$7) -> 0 | M68: =IF(D68=0,0,J68-L68) -> 0 | N68: =IFERROR(J68/L68,"0%") -> 0% | P68: =IF(D68=0,0,SUM($L$51:L68)) -> 0 | Q68: =IF(D68=0,0,SUM($J$51:J68)) -> 0 | R68: =IF(D68=0,0,Q68-P68) -> 0 | S68: =IFERROR(Q68/P68,"0%") -> 0% | U68: =IF(D68=0,0,SUM($L$20:L68)) -> 0 | V68: =IF(D68=0,0,SUM($J$20:J68)) -> 0 | W68: =IF(D68=0,0,V68-U68) -> 0 | X68: =IFERROR(V68/U68,"0%") -> 0% | Z68: =Z67+1 -> 45340 | AA68: =AA67+1 -> 45340 | AB68: 45340 | AC68: 7 | AD68: 日 | AE68: =IFERROR(AVERAGEIFS(J202:J232,D202:D232,1,G202:G232,"sun"),0) -> 0 | AF68: =IFERROR(COUNTIFS(D202:D232,1,G202:G232,"sun"),0) -> 0 | AH68: =AE68*AF68 -> 0 | AI68: =AH68/$M$12 -> 0 | AS68: =AS67+1 -> 45340
C69: =C68+1 -> 50 | D69: 1 | E69: =TEXT(AA69,"m") -> 2 | F69: =F68+1 -> 45341 | G69: =TEXT(AS69,"ddd") -> Mon | J69: 285600 | L69: =IF(D69=0,0,$K$7) -> 209473 | M69: =IF(D69=0,0,J69-L69) -> 76126.997 | N69: =IFERROR(J69/L69,"0%") -> 1.3634215 | P69: =IF(D69=0,0,SUM($L$51:L69)) -> 3142095 | Q69: =IF(D69=0,0,SUM($J$51:J69)) -> 3279620 | R69: =IF(D69=0,0,Q69-P69) -> 137524.96 | S69: =IFERROR(Q69/P69,"0%") -> 1.0437686 | U69: =IF(D69=0,0,SUM($L$20:L69)) -> 8021583.8 | V69: =IF(D69=0,0,SUM($J$20:J69)) -> 8261994 | W69: =IF(D69=0,0,V69-U69) -> 240410.18 | X69: =IFERROR(V69/U69,"0%") -> 1.0299704 | Z69: =Z68+1 -> 45341 | AA69: =AA68+1 -> 45341 | AB69: 45341 | AC69: 8 | AD69: 月 | AE69: =AVERAGEIFS(J233:J263,D233:D263,1,G233:G263,"mon") -> 187033.33 | AF69: =COUNTIFS(D233:D263,1,G233:G263,"Mon") -> 3 | AH69: =AE69*AF69 -> 561100 | AI69: =AH69/$M$13 -> 0.12435721 | AJ69: =SUM(AI69:AI75) -> 1 | AK69: 233〜263 | AS69: =AS68+1 -> 45341
C70: =C69+1 -> 51 | D70: 1 | E70: =TEXT(AA70,"m") -> 2 | F70: =F69+1 -> 45342 | G70: =TEXT(AS70,"ddd") -> Tue | J70: 316820 | L70: =IF(D70=0,0,$K$7) -> 209473 | M70: =IF(D70=0,0,J70-L70) -> 107347 | N70: =IFERROR(J70/L70,"0%") -> 1.5124622 | P70: =IF(D70=0,0,SUM($L$51:L70)) -> 3351568 | Q70: =IF(D70=0,0,SUM($J$51:J70)) -> 3596440 | R70: =IF(D70=0,0,Q70-P70) -> 244871.95 | S70: =IFERROR(Q70/P70,"0%") -> 1.0730619 | U70: =IF(D70=0,0,SUM($L$20:L70)) -> 8231056.8 | V70: =IF(D70=0,0,SUM($J$20:J70)) -> 8578814 | W70: =IF(D70=0,0,V70-U70) -> 347757.18 | X70: =IFERROR(V70/U70,"0%") -> 1.0422494 | Z70: =Z69+1 -> 45342 | AA70: =AA69+1 -> 45342 | AB70: 45342 | AC70: 8 | AD70: 火 | AE70: =AVERAGEIFS(J233:J263,D233:D263,1,G233:G263,"tue") -> 156850 | AF70: =COUNTIFS(D233:D263,1,G233:G263,"tue") -> 3 | AH70: =AE70*AF70 -> 470550 | AI70: =AH70/$M$13 -> 0.10428852 | AS70: =AS69+1 -> 45342
C71: =C70+1 -> 52 | D71: 1 | E71: =TEXT(AA71,"m") -> 2 | F71: =F70+1 -> 45343 | G71: =TEXT(AS71,"ddd") -> Wed | J71: 135300 | L71: =IF(D71=0,0,$K$7) -> 209473 | M71: =IF(D71=0,0,J71-L71) -> -74173.003 | N71: =IFERROR(J71/L71,"0%") -> 0.64590662 | P71: =IF(D71=0,0,SUM($L$51:L71)) -> 3561041 | Q71: =IF(D71=0,0,SUM($J$51:J71)) -> 3731740 | R71: =IF(D71=0,0,Q71-P71) -> 170698.95 | S71: =IFERROR(Q71/P71,"0%") -> 1.0479351 | U71: =IF(D71=0,0,SUM($L$20:L71)) -> 8440529.8 | V71: =IF(D71=0,0,SUM($J$20:J71)) -> 8714114 | W71: =IF(D71=0,0,V71-U71) -> 273584.18 | X71: =IFERROR(V71/U71,"0%") -> 1.0324132 | Z71: =Z70+1 -> 45343 | AA71: =AA70+1 -> 45343 | AB71: 45343 | AC71: 8 | AD71: 水 | AE71: =AVERAGEIFS(J233:J263,D233:D263,1,G233:G263,"wed") -> 294026.33 | AF71: =COUNTIFS(D233:D263,1,G233:G263,"wed") -> 3 | AH71: =AE71*AF71 -> 882079 | AI71: =AH71/$M$13 -> 0.19549615 | AS71: =AS70+1 -> 45343
C72: =C71+1 -> 53 | D72: 1 | E72: =TEXT(AA72,"m") -> 2 | F72: =F71+1 -> 45344 | G72: =TEXT(AS72,"ddd") -> Thu | J72: 331320 | L72: =IF(D72=0,0,$K$7) -> 209473 | M72: =IF(D72=0,0,J72-L72) -> 121847 | N72: =IFERROR(J72/L72,"0%") -> 1.5816835 | P72: =IF(D72=0,0,SUM($L$51:L72)) -> 3770514.1 | Q72: =IF(D72=0,0,SUM($J$51:J72)) -> 4063060 | R72: =IF(D72=0,0,Q72-P72) -> 292545.95 | S72: =IFERROR(Q72/P72,"0%") -> 1.0775878 | U72: =IF(D72=0,0,SUM($L$20:L72)) -> 8650002.8 | V72: =IF(D72=0,0,SUM($J$20:J72)) -> 9045434 | W72: =IF(D72=0,0,V72-U72) -> 395431.17 | X72: =IFERROR(V72/U72,"0%") -> 1.0457146 | Z72: =Z71+1 -> 45344 | AA72: =AA71+1 -> 45344 | AB72: 45344 | AC72: 8 | AD72: 木 | AE72: =AVERAGEIFS(J233:J263,D233:D263,1,G233:G263,"thu") -> 205528.25 | AF72: =COUNTIFS(D233:D263,1,G233:G263,"thu") -> 4 | AH72: =AE72*AF72 -> 822113 | AI72: =AH72/$M$13 -> 0.18220581 | AS72: =AS71+1 -> 45344
C73: =C72+1 -> 54 | D73: 0 | E73: =TEXT(AA73,"m") -> 2 | F73: =F72+1 -> 45345 | G73: =TEXT(AS73,"ddd") -> Fri | H73: 祝日 | J73: 0 | L73: =IF(D73=0,0,$K$7) -> 0 | M73: =IF(D73=0,0,J73-L73) -> 0 | N73: =IFERROR(J73/L73,"0%") -> 0% | P73: =IF(D73=0,0,SUM($L$51:L73)) -> 0 | Q73: =IF(D73=0,0,SUM($J$51:J73)) -> 0 | R73: =IF(D73=0,0,Q73-P73) -> 0 | S73: =IFERROR(Q73/P73,"0%") -> 0% | U73: =IF(D73=0,0,SUM($L$20:L73)) -> 0 | V73: =IF(D73=0,0,SUM($J$20:J73)) -> 0 | W73: =IF(D73=0,0,V73-U73) -> 0 | X73: =IFERROR(V73/U73,"0%") -> 0% | Z73: =Z72+1 -> 45345 | AA73: =AA72+1 -> 45345 | AB73: 45345 | AC73: 8 | AD73: 金 | AE73: =AVERAGEIFS(J233:J263,D233:D263,1,G233:G263,"fri") -> 287530 | AF73: =COUNTIFS(D233:D263,1,G233:G263,"fri") -> 4 | AH73: =AE73*AF73 -> 1150120 | AI73: =AH73/$M$13 -> 0.25490237 | AS73: =AS72+1 -> 45345
C74: =C73+1 -> 55 | D74: 1 | E74: =TEXT(AA74,"m") -> 2 | F74: =F73+1 -> 45346 | G74: =TEXT(AS74,"ddd") -> Sat | J74: 72800 | L74: =IF(D74=0,0,$K$7) -> 209473 | M74: =IF(D74=0,0,J74-L74) -> -136673 | N74: =IFERROR(J74/L74,"0%") -> 0.34753882 | P74: =IF(D74=0,0,SUM($L$51:L74)) -> 3979987.1 | Q74: =IF(D74=0,0,SUM($J$51:J74)) -> 4135860 | R74: =IF(D74=0,0,Q74-P74) -> 155872.94 | S74: =IFERROR(Q74/P74,"0%") -> 1.0391642 | U74: =IF(D74=0,0,SUM($L$20:L74)) -> 8859475.8 | V74: =IF(D74=0,0,SUM($J$20:J74)) -> 9118234 | W74: =IF(D74=0,0,V74-U74) -> 258758.17 | X74: =IFERROR(V74/U74,"0%") -> 1.0292069 | Z74: =Z73+1 -> 45346 | AA74: =AA73+1 -> 45346 | AB74: 45346 | AC74: 8 | AD74: 土 | AE74: =AVERAGEIFS(J233:J263,D233:D263,1,G233:G263,"sat") -> 125208 | AF74: =COUNTIFS(D233:D263,1,G233:G263,"sat") -> 5 | AH74: =AE74*AF74 -> 626040 | AI74: =AH74/$M$13 -> 0.13874994 | AS74: =AS73+1 -> 45346
C75: =C74+1 -> 56 | D75: 0 | E75: =TEXT(AA75,"m") -> 2 | F75: =F74+1 -> 45347 | G75: =TEXT(AS75,"ddd") -> Sun | H75: 日曜日 | J75: 0 | L75: =IF(D75=0,0,$K$7) -> 0 | M75: =IF(D75=0,0,J75-L75) -> 0 | N75: =IFERROR(J75/L75,"0%") -> 0% | P75: =IF(D75=0,0,SUM($L$51:L75)) -> 0 | Q75: =IF(D75=0,0,SUM($J$51:J75)) -> 0 | R75: =IF(D75=0,0,Q75-P75) -> 0 | S75: =IFERROR(Q75/P75,"0%") -> 0% | U75: =IF(D75=0,0,SUM($L$20:L75)) -> 0 | V75: =IF(D75=0,0,SUM($J$20:J75)) -> 0 | W75: =IF(D75=0,0,V75-U75) -> 0 | X75: =IFERROR(V75/U75,"0%") -> 0% | Z75: =Z74+1 -> 45347 | AA75: =AA74+1 -> 45347 | AB75: 45347 | AC75: 8 | AD75: 日 | AE75: =IFERROR(AVERAGEIFS(J233:J263,D233:D263,1,G233:G263,"sun"),0) -> 0 | AF75: =IFERROR(COUNTIFS(D233:D263,1,G233:G263,"sun"),0) -> 0 | AH75: =AE75*AF75 -> 0 | AI75: =AH75/$M$13 -> 0 | AS75: =AS74+1 -> 45347
C76: =C75+1 -> 57 | D76: 1 | E76: =TEXT(AA76,"m") -> 2 | F76: =F75+1 -> 45348 | G76: =TEXT(AS76,"ddd") -> Mon | J76: 252950 | L76: =IF(D76=0,0,$K$7) -> 209473 | M76: =IF(D76=0,0,J76-L76) -> 43476.997 | N76: =IFERROR(J76/L76,"0%") -> 1.2075542 | P76: =IF(D76=0,0,SUM($L$51:L76)) -> 4189460.1 | Q76: =IF(D76=0,0,SUM($J$51:J76)) -> 4388810 | R76: =IF(D76=0,0,Q76-P76) -> 199349.94 | S76: =IFERROR(Q76/P76,"0%") -> 1.0475837 | U76: =IF(D76=0,0,SUM($L$20:L76)) -> 9068948.8 | V76: =IF(D76=0,0,SUM($J$20:J76)) -> 9371184 | W76: =IF(D76=0,0,V76-U76) -> 302235.17 | X76: =IFERROR(V76/U76,"0%") -> 1.0333264 | Z76: =Z75+1 -> 45348 | AA76: =AA75+1 -> 45348 | AB76: 45348 | AC76: 9 | AD76: 月 | AE76: =AVERAGEIFS(J264:J293,D264:D293,1,G264:G293,"mon") -> 236500 | AF76: =COUNTIFS(D264:D293,1,G264:G293,"Mon") -> 3 | AH76: =AE76*AF76 -> 709500 | AI76: =AH76/$M$14 -> 0.1307816 | AJ76: =SUM(AI76:AI82) -> 1 | AK76: 264〜293 | AS76: =AS75+1 -> 45348
C77: =C76+1 -> 58 | D77: 1 | E77: =TEXT(AA77,"m") -> 2 | F77: =F76+1 -> 45349 | G77: =TEXT(AS77,"ddd") -> Tue | J77: 209900 | L77: =IF(D77=0,0,$K$7) -> 209473 | M77: =IF(D77=0,0,J77-L77) -> 426.99706 | N77: =IFERROR(J77/L77,"0%") -> 1.0020384 | P77: =IF(D77=0,0,SUM($L$51:L77)) -> 4398933.1 | Q77: =IF(D77=0,0,SUM($J$51:J77)) -> 4598710 | R77: =IF(D77=0,0,Q77-P77) -> 199776.94 | S77: =IFERROR(Q77/P77,"0%") -> 1.0454149 | U77: =IF(D77=0,0,SUM($L$20:L77)) -> 9278421.8 | V77: =IF(D77=0,0,SUM($J$20:J77)) -> 9581084 | W77: =IF(D77=0,0,V77-U77) -> 302662.16 | X77: =IFERROR(V77/U77,"0%") -> 1.03262 | Z77: =Z76+1 -> 45349 | AA77: =AA76+1 -> 45349 | AB77: 45349 | AC77: 9 | AD77: 火 | AE77: =AVERAGEIFS(J264:J293,D264:D293,1,G264:G293,"tue") -> 293290 | AF77: =COUNTIFS(D264:D293,1,G264:G293,"tue") -> 4 | AH77: =AE77*AF77 -> 1173160 | AI77: =AH77/$M$14 -> 0.2162477 | AS77: =AS76+1 -> 45349
C78: =C77+1 -> 59 | D78: 1 | E78: =TEXT(AA78,"m") -> 2 | F78: =F77+1 -> 45350 | G78: =TEXT(AS78,"ddd") -> Wed | J78: 234470 | L78: =IF(D78=0,0,$K$7) -> 209473 | M78: =IF(D78=0,0,J78-L78) -> 24996.997 | N78: =IFERROR(J78/L78,"0%") -> 1.1193328 | P78: =IF(D78=0,0,SUM($L$51:L78)) -> 4608406.1 | Q78: =IF(D78=0,0,SUM($J$51:J78)) -> 4833180 | R78: =IF(D78=0,0,Q78-P78) -> 224773.94 | S78: =IFERROR(Q78/P78,"0%") -> 1.0487748 | U78: =IF(D78=0,0,SUM($L$20:L78)) -> 9487894.8 | V78: =IF(D78=0,0,SUM($J$20:J78)) -> 9815554 | W78: =IF(D78=0,0,V78-U78) -> 327659.16 | X78: =IFERROR(V78/U78,"0%") -> 1.0345344 | Z78: =Z77+1 -> 45350 | AA78: =AA77+1 -> 45350 | AB78: 45350 | AC78: 9 | AD78: 水 | AE78: =AVERAGEIFS(J264:J293,D264:D293,1,G264:G293,"wed") -> 197822.5 | AF78: =COUNTIFS(D264:D293,1,G264:G293,"wed") -> 4 | AH78: =AE78*AF78 -> 791290 | AI78: =AH78/$M$14 -> 0.14585789 | AS78: =AS77+1 -> 45350
C79: =C78+1 -> 60 | D79: 1 | E79: =TEXT(AA79,"m") -> 2 | F79: =F78+1 -> 45351 | G79: =TEXT(AS79,"ddd") -> Thu | J79: 168650 | L79: =IF(D79=0,0,$K$7) -> 209473 | M79: =IF(D79=0,0,J79-L79) -> -40823.003 | N79: =IFERROR(J79/L79,"0%") -> 0.80511568 | P79: =IF(D79=0,0,SUM($L$51:L79)) -> 4817879.1 | Q79: =IF(D79=0,0,SUM($J$51:J79)) -> 5001830 | R79: =IF(D79=0,0,Q79-P79) -> 183950.93 | S79: =IFERROR(Q79/P79,"0%") -> 1.0381809 | U79: =IF(D79=0,0,SUM($L$20:L79)) -> 9697367.8 | V79: =IF(D79=0,0,SUM($J$20:J79)) -> 9984204 | W79: =IF(D79=0,0,V79-U79) -> 286836.16 | X79: =IFERROR(V79/U79,"0%") -> 1.0295788 | Z79: =Z78+1 -> 45351 | AA79: =AA78+1 -> 45351 | AB79: 45351 | AC79: 9 | AD79: 木 | AE79: =AVERAGEIFS(J264:J293,D264:D293,1,G264:G293,"thu") -> 222967.5 | AF79: =COUNTIFS(D264:D293,1,G264:G293,"thu") -> 4 | AH79: =AE79*AF79 -> 891870 | AI79: =AH79/$M$14 -> 0.16439773 | AS79: =AS78+1 -> 45351
C80: =C79+1 -> 61 | D80: 1 | E80: =TEXT(AA80,"m") -> 3 | F80: =F79+1 -> 45352 | G80: =TEXT(AS80,"ddd") -> Fri | J80: 305050 | L80: =IF(D80=0,0,$K$8) -> 246438.83 | M80: =IF(D80=0,0,J80-L80) -> 58611.173 | N80: =IFERROR(J80/L80,"0%") -> 1.2378325 | P80: =IF(D80=0,0,$L$80) -> 246438.83 | Q80: =IF(D80=0,0,$J$80) -> 305050 | R80: =IF(D80=0,0,Q80-P80) -> 58611.173 | S80: =IFERROR(Q80/P80,"0%") -> 1.2378325 | U80: =IF(D80=0,0,SUM($L$20:L80)) -> 9943806.7 | V80: =IF(D80=0,0,SUM($J$20:J80)) -> 10289254 | W80: =IF(D80=0,0,V80-U80) -> 345447.33 | X80: =IFERROR(V80/U80,"0%") -> 1.0347399 | Z80: =Z79+1 -> 45352 | AA80: =AA79+1 -> 45352 | AB80: 45352 | AC80: 9 | AD80: 金 | AE80: =AVERAGEIFS(J264:J293,D264:D293,1,G264:G293,"fri") -> 331241.25 | AF80: =COUNTIFS(D264:D293,1,G264:G293,"fri") -> 4 | AH80: =AE80*AF80 -> 1324965 | AI80: =AH80/$M$14 -> 0.2442298 | AS80: =AS79+1 -> 45352
C81: =C80+1 -> 62 | D81: 1 | E81: =TEXT(AA81,"m") -> 3 | F81: =F80+1 -> 45353 | G81: =TEXT(AS81,"ddd") -> Sat | J81: 148490 | L81: =IF(D81=0,0,$K$8) -> 246438.83 | M81: =IF(D81=0,0,J81-L81) -> -97948.827 | N81: =IFERROR(J81/L81,"0%") -> 0.60254304 | P81: =IF(D81=0,0,SUM($L$80:L81)) -> 492877.65 | Q81: =IF(D81=0,0,SUM($J$80:J81)) -> 453540 | R81: =IF(D81=0,0,Q81-P81) -> -39337.654 | S81: =IFERROR(Q81/P81,"0%") -> 0.92018779 | U81: =IF(D81=0,0,SUM($L$20:L81)) -> 10190245 | V81: =IF(D81=0,0,SUM($J$20:J81)) -> 10437744 | W81: =IF(D81=0,0,V81-U81) -> 247498.5 | X81: =IFERROR(V81/U81,"0%") -> 1.0242878 | Z81: =Z80+1 -> 45353 | AA81: =AA80+1 -> 45353 | AB81: 45353 | AC81: 9 | AD81: 土 | AE81: =AVERAGEIFS(J264:J293,D264:D293,1,G264:G293,"sat") -> 133572.5 | AF81: =COUNTIFS(D264:D293,1,G264:G293,"sat") -> 4 | AH81: =AE81*AF81 -> 534290 | AI81: =AH81/$M$14 -> 0.098485274 | AS81: =AS80+1 -> 45353
C82: =C81+1 -> 63 | D82: 0 | E82: =TEXT(AA82,"m") -> 3 | F82: =F81+1 -> 45354 | G82: =TEXT(AS82,"ddd") -> Sun | H82: 日曜日 | J82: 0 | L82: =IF(D82=0,0,$K$8) -> 0 | M82: =IF(D82=0,0,J82-L82) -> 0 | N82: =IFERROR(J82/L82,"0%") -> 0% | P82: =IF(D82=0,0,SUM($L$80:L82)) -> 0 | Q82: =IF(D82=0,0,SUM($J$80:J82)) -> 0 | R82: =IF(D82=0,0,Q82-P82) -> 0 | S82: =IFERROR(Q82/P82,"0%") -> 0% | U82: =IF(D82=0,0,SUM($L$20:L82)) -> 0 | V82: =IF(D82=0,0,SUM($J$20:J82)) -> 0 | W82: =IF(D82=0,0,V82-U82) -> 0 | X82: =IFERROR(V82/U82,"0%") -> 0% | Z82: =Z81+1 -> 45354 | AA82: =AA81+1 -> 45354 | AB82: 45354 | AC82: 9 | AD82: 日 | AE82: =IFERROR(AVERAGEIFS(J264:J293,D264:D293,1,G264:G293,"sun"),0) -> 0 | AF82: =IFERROR(COUNTIFS(D264:D293,1,G264:G293,"sun"),0) -> 0 | AH82: =AE82*AF82 -> 0 | AI82: =AH82/$M$14 -> 0 | AS82: =AS81+1 -> 45354
C83: =C82+1 -> 64 | D83: 1 | E83: =TEXT(AA83,"m") -> 3 | F83: =F82+1 -> 45355 | G83: =TEXT(AS83,"ddd") -> Mon | J83: 166560 | L83: =IF(D83=0,0,$K$8) -> 246438.83 | M83: =IF(D83=0,0,J83-L83) -> -79878.827 | N83: =IFERROR(J83/L83,"0%") -> 0.67586752 | P83: =IF(D83=0,0,SUM($L$80:L83)) -> 739316.48 | Q83: =IF(D83=0,0,SUM($J$80:J83)) -> 620100 | R83: =IF(D83=0,0,Q83-P83) -> -119216.48 | S83: =IFERROR(Q83/P83,"0%") -> 0.8387477 | U83: =IF(D83=0,0,SUM($L$20:L83)) -> 10436684 | V83: =IF(D83=0,0,SUM($J$20:J83)) -> 10604304 | W83: =IF(D83=0,0,V83-U83) -> 167619.68 | X83: =IFERROR(V83/U83,"0%") -> 1.0160606 | Z83: =Z82+1 -> 45355 | AA83: =AA82+1 -> 45355 | AB83: 45355 | AC83: 10 | AD83: 月 | AE83: =AVERAGEIFS(J294:J324,D294:D324,1,G294:G324,"mon") -> 234683.33 | AF83: =COUNTIFS(D294:D324,1,G294:G324,"Mon") -> 3 | AH83: =AE83*AF83 -> 704050 | AI83: =AH83/$M$15 -> 0.12672958 | AJ83: =SUM(AI83:AI89) -> 1 | AK83: 294〜324 | AS83: =AS82+1 -> 45355
C84: =C83+1 -> 65 | D84: 1 | E84: =TEXT(AA84,"m") -> 3 | F84: =F83+1 -> 45356 | G84: =TEXT(AS84,"ddd") -> Tue | J84: 292350 | L84: =IF(D84=0,0,$K$8) -> 246438.83 | M84: =IF(D84=0,0,J84-L84) -> 45911.173 | N84: =IFERROR(J84/L84,"0%") -> 1.1862985 | P84: =IF(D84=0,0,SUM($L$80:L84)) -> 985755.31 | Q84: =IF(D84=0,0,SUM($J$80:J84)) -> 912450 | R84: =IF(D84=0,0,Q84-P84) -> -73305.308 | S84: =IFERROR(Q84/P84,"0%") -> 0.92563539 | U84: =IF(D84=0,0,SUM($L$20:L84)) -> 10683123 | V84: =IF(D84=0,0,SUM($J$20:J84)) -> 10896654 | W84: =IF(D84=0,0,V84-U84) -> 213530.85 | X84: =IFERROR(V84/U84,"0%") -> 1.0199877 | Z84: =Z83+1 -> 45356 | AA84: =AA83+1 -> 45356 | AB84: 45356 | AC84: 10 | AD84: 火 | AE84: =AVERAGEIFS(J294:J324,D294:D324,1,G294:G324,"tue") -> 197950 | AF84: =COUNTIFS(D294:D324,1,G294:G324,"tue") -> 5 | AH84: =AE84*AF84 -> 989750 | AI84: =AH84/$M$15 -> 0.17815582 | AS84: =AS83+1 -> 45356
C85: =C84+1 -> 66 | D85: 1 | E85: =TEXT(AA85,"m") -> 3 | F85: =F84+1 -> 45357 | G85: =TEXT(AS85,"ddd") -> Wed | J85: 145450 | L85: =IF(D85=0,0,$K$8) -> 246438.83 | M85: =IF(D85=0,0,J85-L85) -> -100988.83 | N85: =IFERROR(J85/L85,"0%") -> 0.59020732 | P85: =IF(D85=0,0,SUM($L$80:L85)) -> 1232194.1 | Q85: =IF(D85=0,0,SUM($J$80:J85)) -> 1057900 | R85: =IF(D85=0,0,Q85-P85) -> -174294.13 | S85: =IFERROR(Q85/P85,"0%") -> 0.85854978 | U85: =IF(D85=0,0,SUM($L$20:L85)) -> 10929562 | V85: =IF(D85=0,0,SUM($J$20:J85)) -> 11042104 | W85: =IF(D85=0,0,V85-U85) -> 112542.02 | X85: =IFERROR(V85/U85,"0%") -> 1.010297 | Z85: =Z84+1 -> 45357 | AA85: =AA84+1 -> 45357 | AB85: 45357 | AC85: 10 | AD85: 水 | AE85: =AVERAGEIFS(J294:J324,D294:D324,1,G294:G324,"wed") -> 213546 | AF85: =COUNTIFS(D294:D324,1,G294:G324,"wed") -> 5 | AH85: =AE85*AF85 -> 1067730 | AI85: =AH85/$M$15 -> 0.19219228 | AS85: =AS84+1 -> 45357
C86: =C85+1 -> 67 | D86: 1 | E86: =TEXT(AA86,"m") -> 3 | F86: =F85+1 -> 45358 | G86: =TEXT(AS86,"ddd") -> Thu | J86: 317890 | L86: =IF(D86=0,0,$K$8) -> 246438.83 | M86: =IF(D86=0,0,J86-L86) -> 71451.173 | N86: =IFERROR(J86/L86,"0%") -> 1.2899347 | P86: =IF(D86=0,0,SUM($L$80:L86)) -> 1478633 | Q86: =IF(D86=0,0,SUM($J$80:J86)) -> 1375790 | R86: =IF(D86=0,0,Q86-P86) -> -102842.96 | S86: =IFERROR(Q86/P86,"0%") -> 0.93044727 | U86: =IF(D86=0,0,SUM($L$20:L86)) -> 11176001 | V86: =IF(D86=0,0,SUM($J$20:J86)) -> 11359994 | W86: =IF(D86=0,0,V86-U86) -> 183993.2 | X86: =IFERROR(V86/U86,"0%") -> 1.0164632 | Z86: =Z85+1 -> 45358 | AA86: =AA85+1 -> 45358 | AB86: 45358 | AC86: 10 | AD86: 木 | AE86: =AVERAGEIFS(J294:J324,D294:D324,1,G294:G324,"thu") -> 249020 | AF86: =COUNTIFS(D294:D324,1,G294:G324,"thu") -> 5 | AH86: =AE86*AF86 -> 1245100 | AI86: =AH86/$M$15 -> 0.22411903 | AS86: =AS85+1 -> 45358
C87: =C86+1 -> 68 | D87: 1 | E87: =TEXT(AA87,"m") -> 3 | F87: =F86+1 -> 45359 | G87: =TEXT(AS87,"ddd") -> Fri | J87: 266360 | L87: =IF(D87=0,0,$K$8) -> 246438.83 | M87: =IF(D87=0,0,J87-L87) -> 19921.173 | N87: =IFERROR(J87/L87,"0%") -> 1.0808362 | P87: =IF(D87=0,0,SUM($L$80:L87)) -> 1725071.8 | Q87: =IF(D87=0,0,SUM($J$80:J87)) -> 1642150 | R87: =IF(D87=0,0,Q87-P87) -> -82921.789 | S87: =IFERROR(Q87/P87,"0%") -> 0.9519314 | U87: =IF(D87=0,0,SUM($L$20:L87)) -> 11422440 | V87: =IF(D87=0,0,SUM($J$20:J87)) -> 11626354 | W87: =IF(D87=0,0,V87-U87) -> 203914.37 | X87: =IFERROR(V87/U87,"0%") -> 1.0178521 | Z87: =Z86+1 -> 45359 | AA87: =AA86+1 -> 45359 | AB87: 45359 | AC87: 10 | AD87: 金 | AE87: =AVERAGEIFS(J294:J324,D294:D324,1,G294:G324,"fri") -> 250932.5 | AF87: =COUNTIFS(D294:D324,1,G294:G324,"fri") -> 4 | AH87: =AE87*AF87 -> 1003730 | AI87: =AH87/$M$15 -> 0.18067223 | AS87: =AS86+1 -> 45359
C88: =C87+1 -> 69 | D88: 1 | E88: =TEXT(AA88,"m") -> 3 | F88: =F87+1 -> 45360 | G88: =TEXT(AS88,"ddd") -> Sat | J88: 118114 | L88: =IF(D88=0,0,$K$8) -> 246438.83 | M88: =IF(D88=0,0,J88-L88) -> -128324.83 | N88: =IFERROR(J88/L88,"0%") -> 0.47928324 | P88: =IF(D88=0,0,SUM($L$80:L88)) -> 1971510.6 | Q88: =IF(D88=0,0,SUM($J$80:J88)) -> 1760264 | R88: =IF(D88=0,0,Q88-P88) -> -211246.62 | S88: =IFERROR(Q88/P88,"0%") -> 0.89285038 | U88: =IF(D88=0,0,SUM($L$20:L88)) -> 11668878 | V88: =IF(D88=0,0,SUM($J$20:J88)) -> 11744468 | W88: =IF(D88=0,0,V88-U88) -> 75589.542 | X88: =IFERROR(V88/U88,"0%") -> 1.0064779 | Z88: =Z87+1 -> 45360 | AA88: =AA87+1 -> 45360 | AB88: 45360 | AC88: 10 | AD88: 土 | AE88: =AVERAGEIFS(J294:J324,D294:D324,1,G294:G324,"sat") -> 136292.5 | AF88: =COUNTIFS(D294:D324,1,G294:G324,"sat") -> 4 | AH88: =AE88*AF88 -> 545170 | AI88: =AH88/$M$15 -> 0.098131051 | AS88: =AS87+1 -> 45360
C89: =C88+1 -> 70 | D89: 0 | E89: =TEXT(AA89,"m") -> 3 | F89: =F88+1 -> 45361 | G89: =TEXT(AS89,"ddd") -> Sun | H89: 日曜日 | J89: 0 | L89: =IF(D89=0,0,$K$8) -> 0 | M89: =IF(D89=0,0,J89-L89) -> 0 | N89: =IFERROR(J89/L89,"0%") -> 0% | P89: =IF(D89=0,0,SUM($L$80:L89)) -> 0 | Q89: =IF(D89=0,0,SUM($J$80:J89)) -> 0 | R89: =IF(D89=0,0,Q89-P89) -> 0 | S89: =IFERROR(Q89/P89,"0%") -> 0% | U89: =IF(D89=0,0,SUM($L$20:L89)) -> 0 | V89: =IF(D89=0,0,SUM($J$20:J89)) -> 0 | W89: =IF(D89=0,0,V89-U89) -> 0 | X89: =IFERROR(V89/U89,"0%") -> 0% | Z89: =Z88+1 -> 45361 | AA89: =AA88+1 -> 45361 | AB89: 45361 | AC89: 10 | AD89: 日 | AE89: =IFERROR(AVERAGEIFS(J294:J324,D294:D324,1,G294:G324,"sun"),0) -> 0 | AF89: =IFERROR(COUNTIFS(D294:D324,1,G294:G324,"sun"),0) -> 0 | AH89: =AE89*AF89 -> 0 | AI89: =AH89/$M$15 -> 0 | AS89: =AS88+1 -> 45361
C90: =C89+1 -> 71 | D90: 1 | E90: =TEXT(AA90,"m") -> 3 | F90: =F89+1 -> 45362 | G90: =TEXT(AS90,"ddd") -> Mon | J90: 315600 | L90: =IF(D90=0,0,$K$8) -> 246438.83 | M90: =IF(D90=0,0,J90-L90) -> 69161.173 | N90: =IFERROR(J90/L90,"0%") -> 1.2806424 | P90: =IF(D90=0,0,SUM($L$80:L90)) -> 2217949.4 | Q90: =IF(D90=0,0,SUM($J$80:J90)) -> 2075864 | R90: =IF(D90=0,0,Q90-P90) -> -142085.44 | S90: =IFERROR(Q90/P90,"0%") -> 0.93593838 | U90: =IF(D90=0,0,SUM($L$20:L90)) -> 11915317 | V90: =IF(D90=0,0,SUM($J$20:J90)) -> 12060068 | W90: =IF(D90=0,0,V90-U90) -> 144750.72 | X90: =IFERROR(V90/U90,"0%") -> 1.0121483 | Z90: =Z89+1 -> 45362 | AA90: =AA89+1 -> 45362 | AB90: 45362 | AC90: 11 | AD90: 月 | AE90: =AVERAGEIFS(J325:J354,D325:D354,1,G325:G354,"mon") -> 176316.67 | AF90: =COUNTIFS(D325:D354,1,G325:G354,"Mon") -> 3 | AH90: =AE90*AF90 -> 528950 | AI90: =AH90/$M$16 -> 0.086540743 | AJ90: =SUM(AI90:AI96) -> 1 | AK90: 325〜354 | AS90: =AS89+1 -> 45362
C91: =C90+1 -> 72 | D91: 1 | E91: =TEXT(AA91,"m") -> 3 | F91: =F90+1 -> 45363 | G91: =TEXT(AS91,"ddd") -> Tue | J91: 320300 | L91: =IF(D91=0,0,$K$8) -> 246438.83 | M91: =IF(D91=0,0,J91-L91) -> 73861.173 | N91: =IFERROR(J91/L91,"0%") -> 1.299714 | P91: =IF(D91=0,0,SUM($L$80:L91)) -> 2464388.3 | Q91: =IF(D91=0,0,SUM($J$80:J91)) -> 2396164 | R91: =IF(D91=0,0,Q91-P91) -> -68224.27 | S91: =IFERROR(Q91/P91,"0%") -> 0.97231594 | U91: =IF(D91=0,0,SUM($L$20:L91)) -> 12161756 | V91: =IF(D91=0,0,SUM($J$20:J91)) -> 12380368 | W91: =IF(D91=0,0,V91-U91) -> 218611.89 | X91: =IFERROR(V91/U91,"0%") -> 1.0179754 | Z91: =Z90+1 -> 45363 | AA91: =AA90+1 -> 45363 | AB91: 45363 | AC91: 11 | AD91: 火 | AE91: =AVERAGEIFS(J325:J354,D325:D354,1,G325:G354,"tue") -> 231565 | AF91: =COUNTIFS(D325:D354,1,G325:G354,"tue") -> 4 | AH91: =AE91*AF91 -> 926260 | AI91: =AH91/$M$16 -> 0.15154406 | AS91: =AS90+1 -> 45363
C92: =C91+1 -> 73 | D92: 1 | E92: =TEXT(AA92,"m") -> 3 | F92: =F91+1 -> 45364 | G92: =TEXT(AS92,"ddd") -> Wed | J92: 318550 | L92: =IF(D92=0,0,$K$8) -> 246438.83 | M92: =IF(D92=0,0,J92-L92) -> 72111.173 | N92: =IFERROR(J92/L92,"0%") -> 1.2926129 | P92: =IF(D92=0,0,SUM($L$80:L92)) -> 2710827.1 | Q92: =IF(D92=0,0,SUM($J$80:J92)) -> 2714714 | R92: =IF(D92=0,0,Q92-P92) -> 3886.9031 | S92: =IFERROR(Q92/P92,"0%") -> 1.0014338 | U92: =IF(D92=0,0,SUM($L$20:L92)) -> 12408195 | V92: =IF(D92=0,0,SUM($J$20:J92)) -> 12698918 | W92: =IF(D92=0,0,V92-U92) -> 290723.06 | X92: =IFERROR(V92/U92,"0%") -> 1.0234299 | Z92: =Z91+1 -> 45364 | AA92: =AA91+1 -> 45364 | AB92: 45364 | AC92: 11 | AD92: 水 | AE92: =AVERAGEIFS(J325:J354,D325:D354,1,G325:G354,"wed") -> 267002.5 | AF92: =COUNTIFS(D325:D354,1,G325:G354,"wed") -> 4 | AH92: =AE92*AF92 -> 1068010 | AI92: =AH92/$M$16 -> 0.17473557 | AS92: =AS91+1 -> 45364
C93: =C92+1 -> 74 | D93: 1 | E93: =TEXT(AA93,"m") -> 3 | F93: =F92+1 -> 45365 | G93: =TEXT(AS93,"ddd") -> Thu | J93: 219880 | L93: =IF(D93=0,0,$K$8) -> 246438.83 | M93: =IF(D93=0,0,J93-L93) -> -26558.827 | N93: =IFERROR(J93/L93,"0%") -> 0.89222953 | P93: =IF(D93=0,0,SUM($L$80:L93)) -> 2957265.9 | Q93: =IF(D93=0,0,SUM($J$80:J93)) -> 2934594 | R93: =IF(D93=0,0,Q93-P93) -> -22671.924 | S93: =IFERROR(Q93/P93,"0%") -> 0.99233348 | U93: =IF(D93=0,0,SUM($L$20:L93)) -> 12654634 | V93: =IF(D93=0,0,SUM($J$20:J93)) -> 12918798 | W93: =IF(D93=0,0,V93-U93) -> 264164.23 | X93: =IFERROR(V93/U93,"0%") -> 1.0208749 | Z93: =Z92+1 -> 45365 | AA93: =AA92+1 -> 45365 | AB93: 45365 | AC93: 11 | AD93: 木 | AE93: =AVERAGEIFS(J325:J354,D325:D354,1,G325:G354,"thu") -> 260102.5 | AF93: =COUNTIFS(D325:D354,1,G325:G354,"thu") -> 4 | AH93: =AE93*AF93 -> 1040410 | AI93: =AH93/$M$16 -> 0.17021997 | AS93: =AS92+1 -> 45365
C94: =C93+1 -> 75 | D94: 1 | E94: =TEXT(AA94,"m") -> 3 | F94: =F93+1 -> 45366 | G94: =TEXT(AS94,"ddd") -> Fri | J94: 350170 | L94: =IF(D94=0,0,$K$8) -> 246438.83 | M94: =IF(D94=0,0,J94-L94) -> 103731.17 | N94: =IFERROR(J94/L94,"0%") -> 1.4209206 | P94: =IF(D94=0,0,SUM($L$80:L94)) -> 3203704.8 | Q94: =IF(D94=0,0,SUM($J$80:J94)) -> 3284764 | R94: =IF(D94=0,0,Q94-P94) -> 81059.249 | S94: =IFERROR(Q94/P94,"0%") -> 1.0253017 | U94: =IF(D94=0,0,SUM($L$20:L94)) -> 12901073 | V94: =IF(D94=0,0,SUM($J$20:J94)) -> 13268968 | W94: =IF(D94=0,0,V94-U94) -> 367895.41 | X94: =IFERROR(V94/U94,"0%") -> 1.0285167 | Z94: =Z93+1 -> 45366 | AA94: =AA93+1 -> 45366 | AB94: 45366 | AC94: 11 | AD94: 金 | AE94: =AVERAGEIFS(J325:J354,D325:D354,1,G325:G354,"fri") -> 333106 | AF94: =COUNTIFS(D325:D354,1,G325:G354,"fri") -> 5 | AH94: =AE94*AF94 -> 1665530 | AI94: =AH94/$M$16 -> 0.27249495 | AS94: =AS93+1 -> 45366
C95: =C94+1 -> 76 | D95: 1 | E95: =TEXT(AA95,"m") -> 3 | F95: =F94+1 -> 45367 | G95: =TEXT(AS95,"ddd") -> Sat | J95: 156750 | L95: =IF(D95=0,0,$K$8) -> 246438.83 | M95: =IF(D95=0,0,J95-L95) -> -89688.827 | N95: =IFERROR(J95/L95,"0%") -> 0.63606049 | P95: =IF(D95=0,0,SUM($L$80:L95)) -> 3450143.6 | Q95: =IF(D95=0,0,SUM($J$80:J95)) -> 3441514 | R95: =IF(D95=0,0,Q95-P95) -> -8629.5779 | S95: =IFERROR(Q95/P95,"0%") -> 0.99749878 | U95: =IF(D95=0,0,SUM($L$20:L95)) -> 13147511 | V95: =IF(D95=0,0,SUM($J$20:J95)) -> 13425718 | W95: =IF(D95=0,0,V95-U95) -> 278206.58 | X95: =IFERROR(V95/U95,"0%") -> 1.0211604 | Z95: =Z94+1 -> 45367 | AA95: =AA94+1 -> 45367 | AB95: 45367 | AC95: 11 | AD95: 土 | AE95: =AVERAGEIFS(J325:J354,D325:D354,1,G325:G354,"sat") -> 220747.5 | AF95: =COUNTIFS(D325:D354,1,G325:G354,"sat") -> 4 | AH95: =AE95*AF95 -> 882990 | AI95: =AH95/$M$16 -> 0.14446471 | AS95: =AS94+1 -> 45367
C96: =C95+1 -> 77 | D96: 0 | E96: =TEXT(AA96,"m") -> 3 | F96: =F95+1 -> 45368 | G96: =TEXT(AS96,"ddd") -> Sun | H96: 日曜日 | J96: 0 | L96: =IF(D96=0,0,$K$8) -> 0 | M96: =IF(D96=0,0,J96-L96) -> 0 | N96: =IFERROR(J96/L96,"0%") -> 0% | P96: =IF(D96=0,0,SUM($L$80:L96)) -> 0 | Q96: =IF(D96=0,0,SUM($J$80:J96)) -> 0 | R96: =IF(D96=0,0,Q96-P96) -> 0 | S96: =IFERROR(Q96/P96,"0%") -> 0% | U96: =IF(D96=0,0,SUM($L$20:L96)) -> 0 | V96: =IF(D96=0,0,SUM($J$20:J96)) -> 0 | W96: =IF(D96=0,0,V96-U96) -> 0 | X96: =IFERROR(V96/U96,"0%") -> 0% | Z96: =Z95+1 -> 45368 | AA96: =AA95+1 -> 45368 | AB96: 45368 | AC96: 11 | AD96: 日 | AE96: =IFERROR(AVERAGEIFS(J325:J354,D325:D354,1,G325:G354,"sun"),0) -> 0 | AF96: =IFERROR(COUNTIFS(D325:D354,1,G325:G354,"sun"),0) -> 0 | AH96: =AE96*AF96 -> 0 | AI96: =AH96/$M$16 -> 0 | AS96: =AS95+1 -> 45368
C97: =C96+1 -> 78 | D97: 1 | E97: =TEXT(AA97,"m") -> 3 | F97: =F96+1 -> 45369 | G97: =TEXT(AS97,"ddd") -> Mon | J97: 201050 | L97: =IF(D97=0,0,$K$8) -> 246438.83 | M97: =IF(D97=0,0,J97-L97) -> -45388.827 | N97: =IFERROR(J97/L97,"0%") -> 0.81582112 | P97: =IF(D97=0,0,SUM($L$80:L97)) -> 3696582.4 | Q97: =IF(D97=0,0,SUM($J$80:J97)) -> 3642564 | R97: =IF(D97=0,0,Q97-P97) -> -54018.405 | S97: =IFERROR(Q97/P97,"0%") -> 0.98538693 | U97: =IF(D97=0,0,SUM($L$20:L97)) -> 13393950 | V97: =IF(D97=0,0,SUM($J$20:J97)) -> 13626768 | W97: =IF(D97=0,0,V97-U97) -> 232817.75 | X97: =IFERROR(V97/U97,"0%") -> 1.0173823 | Z97: =Z96+1 -> 45369 | AA97: =AA96+1 -> 45369 | AB97: 45369 | AC97: 12 | AD97: 月 | AE97: =AVERAGEIFS(J355:J385,D355:D385,1,G355:G385,"mon") -> 283835 | AF97: =COUNTIFS(D355:D385,1,G355:G385,"Mon") -> 4 | AH97: =AE97*AF97 -> 1135340 | AI97: =AH97/$M$17 -> 0.14372393 | AJ97: =SUM(AI97:AI103) -> 1 | AK97: 355〜385 | AS97: =AS96+1 -> 45369
C98: =C97+1 -> 79 | D98: 1 | E98: =TEXT(AA98,"m") -> 3 | F98: =F97+1 -> 45370 | G98: =TEXT(AS98,"ddd") -> Tue | J98: 220700 | L98: =IF(D98=0,0,$K$8) -> 246438.83 | M98: =IF(D98=0,0,J98-L98) -> -25738.827 | N98: =IFERROR(J98/L98,"0%") -> 0.89555693 | P98: =IF(D98=0,0,SUM($L$80:L98)) -> 3943021.2 | Q98: =IF(D98=0,0,SUM($J$80:J98)) -> 3863264 | R98: =IF(D98=0,0,Q98-P98) -> -79757.232 | S98: =IFERROR(Q98/P98,"0%") -> 0.97977256 | U98: =IF(D98=0,0,SUM($L$20:L98)) -> 13640389 | V98: =IF(D98=0,0,SUM($J$20:J98)) -> 13847468 | W98: =IF(D98=0,0,V98-U98) -> 207078.93 | X98: =IFERROR(V98/U98,"0%") -> 1.0151813 | Z98: =Z97+1 -> 45370 | AA98: =AA97+1 -> 45370 | AB98: 45370 | AC98: 12 | AD98: 火 | AE98: =AVERAGEIFS(J355:J385,D355:D385,1,G355:G385,"tue") -> 312370 | AF98: =COUNTIFS(D355:D385,1,G355:G385,"tue") -> 4 | AH98: =AE98*AF98 -> 1249480 | AI98: =AH98/$M$17 -> 0.15817304 | AS98: =AS97+1 -> 45370
C99: =C98+1 -> 80 | D99: 0 | E99: =TEXT(AA99,"m") -> 3 | F99: =F98+1 -> 45371 | G99: =TEXT(AS99,"ddd") -> Wed | H99: 祝日 | J99: 0 | L99: =IF(D99=0,0,$K$8) -> 0 | M99: =IF(D99=0,0,J99-L99) -> 0 | N99: =IFERROR(J99/L99,"0%") -> 0% | P99: =IF(D99=0,0,SUM($L$80:L99)) -> 0 | Q99: =IF(D99=0,0,SUM($J$80:J99)) -> 0 | R99: =IF(D99=0,0,Q99-P99) -> 0 | S99: =IFERROR(Q99/P99,"0%") -> 0% | U99: =IF(D99=0,0,SUM($L$20:L99)) -> 0 | V99: =IF(D99=0,0,SUM($J$20:J99)) -> 0 | W99: =IF(D99=0,0,V99-U99) -> 0 | X99: =IFERROR(V99/U99,"0%") -> 0% | Z99: =Z98+1 -> 45371 | AA99: =AA98+1 -> 45371 | AB99: 45371 | AC99: 12 | AD99: 水 | AE99: =AVERAGEIFS(J355:J385,D355:D385,1,G355:G385,"wed") -> 388307.5 | AF99: =COUNTIFS(D355:D385,1,G355:G385,"wed") -> 4 | AH99: =AE99*AF99 -> 1553230 | AI99: =AH99/$M$17 -> 0.19662508 | AS99: =AS98+1 -> 45371
C100: =C99+1 -> 81 | D100: 1 | E100: =TEXT(AA100,"m") -> 3 | F100: =F99+1 -> 45372 | G100: =TEXT(AS100,"ddd") -> Thu | J100: 369500 | L100: =IF(D100=0,0,$K$8) -> 246438.83 | M100: =IF(D100=0,0,J100-L100) -> 123061.17 | N100: =IFERROR(J100/L100,"0%") -> 1.4993579 | P100: =IF(D100=0,0,SUM($L$80:L100)) -> 4189460.1 | Q100: =IF(D100=0,0,SUM($J$80:J100)) -> 4232764 | R100: =IF(D100=0,0,Q100-P100) -> 43303.941 | S100: =IFERROR(Q100/P100,"0%") -> 1.0103364 | U100: =IF(D100=0,0,SUM($L$20:L100)) -> 13886828 | V100: =IF(D100=0,0,SUM($J$20:J100)) -> 14216968 | W100: =IF(D100=0,0,V100-U100) -> 330140.1 | X100: =IFERROR(V100/U100,"0%") -> 1.0237736 | Z100: =Z99+1 -> 45372 | AA100: =AA99+1 -> 45372 | AB100: 45372 | AC100: 12 | AD100: 木 | AE100: =AVERAGEIFS(J355:J385,D355:D385,1,G355:G385,"thu") -> 336157.5 | AF100: =COUNTIFS(D355:D385,1,G355:G385,"thu") -> 4 | AH100: =AE100*AF100 -> 1344630 | AI100: =AH100/$M$17 -> 0.17021818 | AS100: =AS99+1 -> 45372
C101: =C100+1 -> 82 | D101: 1 | E101: =TEXT(AA101,"m") -> 3 | F101: =F100+1 -> 45373 | G101: =TEXT(AS101,"ddd") -> Fri | J101: 333000 | L101: =IF(D101=0,0,$K$8) -> 246438.83 | M101: =IF(D101=0,0,J101-L101) -> 86561.173 | N101: =IFERROR(J101/L101,"0%") -> 1.3512481 | P101: =IF(D101=0,0,SUM($L$80:L101)) -> 4435898.9 | Q101: =IF(D101=0,0,SUM($J$80:J101)) -> 4565764 | R101: =IF(D101=0,0,Q101-P101) -> 129865.11 | S101: =IFERROR(Q101/P101,"0%") -> 1.0292759 | U101: =IF(D101=0,0,SUM($L$20:L101)) -> 14133267 | V101: =IF(D101=0,0,SUM($J$20:J101)) -> 14549968 | W101: =IF(D101=0,0,V101-U101) -> 416701.27 | X101: =IFERROR(V101/U101,"0%") -> 1.0294837 | Z101: =Z100+1 -> 45373 | AA101: =AA100+1 -> 45373 | AB101: 45373 | AC101: 12 | AD101: 金 | AE101: =AVERAGEIFS(J355:J385,D355:D385,1,G355:G385,"fri") -> 418530 | AF101: =COUNTIFS(D355:D385,1,G355:G385,"fri") -> 4 | AH101: =AE101*AF101 -> 1674120 | AI101: =AH101/$M$17 -> 0.21192868 | AS101: =AS100+1 -> 45373
C102: =C101+1 -> 83 | D102: 1 | E102: =TEXT(AA102,"m") -> 3 | F102: =F101+1 -> 45374 | G102: =TEXT(AS102,"ddd") -> Sat | J102: 118964 | L102: =IF(D102=0,0,$K$8) -> 246438.83 | M102: =IF(D102=0,0,J102-L102) -> -127474.83 | N102: =IFERROR(J102/L102,"0%") -> 0.48273237 | P102: =IF(D102=0,0,SUM($L$80:L102)) -> 4682337.7 | Q102: =IF(D102=0,0,SUM($J$80:J102)) -> 4684728 | R102: =IF(D102=0,0,Q102-P102) -> 2390.2872 | S102: =IFERROR(Q102/P102,"0%") -> 1.0005105 | U102: =IF(D102=0,0,SUM($L$20:L102)) -> 14379706 | V102: =IF(D102=0,0,SUM($J$20:J102)) -> 14668932 | W102: =IF(D102=0,0,V102-U102) -> 289226.45 | X102: =IFERROR(V102/U102,"0%") -> 1.0201135 | Z102: =Z101+1 -> 45374 | AA102: =AA101+1 -> 45374 | AB102: 45374 | AC102: 12 | AD102: 土 | AE102: =AVERAGEIFS(J355:J385,D355:D385,1,G355:G385,"sat") -> 235662.5 | AF102: =COUNTIFS(D355:D385,1,G355:G385,"sat") -> 4 | AH102: =AE102*AF102 -> 942650 | AI102: =AH102/$M$17 -> 0.11933109 | AS102: =AS101+1 -> 45374
C103: =C102+1 -> 84 | D103: 0 | E103: =TEXT(AA103,"m") -> 3 | F103: =F102+1 -> 45375 | G103: =TEXT(AS103,"ddd") -> Sun | H103: 日曜日 | J103: 0 | L103: =IF(D103=0,0,$K$8) -> 0 | M103: =IF(D103=0,0,J103-L103) -> 0 | N103: =IFERROR(J103/L103,"0%") -> 0% | P103: =IF(D103=0,0,SUM($L$80:L103)) -> 0 | Q103: =IF(D103=0,0,SUM($J$80:J103)) -> 0 | R103: =IF(D103=0,0,Q103-P103) -> 0 | S103: =IFERROR(Q103/P103,"0%") -> 0% | U103: =IF(D103=0,0,SUM($L$20:L103)) -> 0 | V103: =IF(D103=0,0,SUM($J$20:J103)) -> 0 | W103: =IF(D103=0,0,V103-U103) -> 0 | X103: =IFERROR(V103/U103,"0%") -> 0% | Z103: =Z102+1 -> 45375 | AA103: =AA102+1 -> 45375 | AB103: 45375 | AC103: 12 | AD103: 日 | AE103: =IFERROR(AVERAGEIFS(J355:J385,D355:D385,1,G355:G385,"sun"),0) -> 0 | AF103: =IFERROR(COUNTIFS(D355:D385,1,G355:G385,"sun"),0) -> 0 | AH103: =AE103*AF103 -> 0 | AI103: =AH103/$M$17 -> 0 | AS103: =AS102+1 -> 45375
...

Sheet 2024($)
B2: 45292 | E2: ①年間営業日 | G2: ②年間目標売上 | I2: 年間売上％設定 | M2: 年間売上合計 | O2: 年間実質売上 | Q2: 年間利益率 | R2: 年間予想利益額
E3: =SUM(F6:F17) -> 289 | G3: =71220821/B13 -> 645466.93 | I3: =SUM(AP6:AP17)*100 -> 0.9999996 | K3: =G3*I3 -> 645466.67 | M3: =SUM(J20:J385) -> 645466.93 | O3: =M3-G3 -> 0 | Q3: 0.21 | R3: =M3*Q3 -> 135548.06
B5: 平均日次売上目標額 | E5: 月 | F5: 月次営業日数 | G5: 平均月間売上目標額 | H5: 月次繁閑期%設定 | J5: 月次目標売上 | K5: 日次目標売上 | M5: 月次売上 | N5: 月間差額 | P5: 月次実質% | R5: 1日の売上目標値 参考例 | AO5: =TEXT(K6,"¥0") -> ¥2010
B6: ② ÷ ① | E6: 1月 | F6: =COUNTIF(D20:D50,1) -> 22 | G6: =$B$7*F6 -> 49135.891 | H6: 0.9 | J6: =G6*H6 -> 44222.302 | K6: =J6/F6 -> 2010.1046 | M6: =SUM(J20:J50) -> 45154.74 | N6: =M6-J6 -> 932.43815 | P6: =M6/G6 -> 0.91897672 | R6: 目標売上 | T6: ¥233564 | V6: 0.76 | AO6: =TEXT(K7,"¥0") -> ¥1898 | AP6: =(H6/100)*AQ6 -> 0.0007499997 | AQ6: 0.0833333
B7: =G3/E3 -> 2233.4496 | E7: 2月 | F7: =COUNTIF(D51:D79,1) -> 23 | G7: =$B$7*F7 -> 51369.34 | H7: 0.85 | J7: =G7*H7 -> 43663.939 | K7: =J7/F7 -> 1898.4321 | M7: =SUM(J51:J79) -> 45331.068 | N7: =M7-J7 -> 1667.1283 | P7: =M7/G7 -> 0.88245376 | T7: =T6*V6 -> 177508.64 | AO7: =TEXT(K8,"¥0") -> ¥2233 | AP7: =(H7/100)*AQ7 -> 0.00070833305 | AQ7: 0.0833333
E8: 3月 | F8: =COUNTIF(D80:D110,1) -> 25 | G8: =$B$7*F8 -> 55836.24 | H8: 1 | J8: =G8*H8 -> 55836.24 | K8: =J8/F8 -> 2233.4496 | M8: =SUM(J80:J110) -> 58551.822 | N8: =M8-J8 -> 2715.5821 | P8: =M8/G8 -> 1.0486348 | R8: 差額 | T8: =T9-T6 -> 87436 | AO8: =TEXT(K9,"¥0") -> ¥2345 | AP8: =(H8/100)*AQ8 -> 0.000833333 | AQ8: 0.0833333
E9: 4月 | F9: =COUNTIF(D111:D140,1) -> 25 | G9: =$B$7*F9 -> 55836.24 | H9: 1.05 | J9: =G9*H9 -> 58628.052 | K9: =J9/F9 -> 2345.1221 | M9: =SUM(J111:J140) -> 60509.851 | N9: =M9-J9 -> 1881.7998 | P9: =M9/G9 -> 1.0837021 | R9: 仮1日売上総合計 | T9: =SUM(V11:V16) -> 321000 | AO9: =TEXT(K10,"¥0") -> ¥2233 | AP9: =(H9/100)*AQ9 -> 0.00087499965 | AQ9: 0.0833333
E10: 5月 | F10: =COUNTIF(D141:D171,1) -> 24 | G10: =$B$7*F10 -> 53602.79 | H10: 1 | J10: =G10*H10 -> 53602.79 | K10: =J10/F10 -> 2233.4496 | M10: =SUM(J141:J171) -> 55872.848 | N10: =M10-J10 -> 2270.0576 | P10: =M10/G10 -> 1.0423496 | R10: 項目 | S10: 仮客単価 | T10: 集客数 | V10: 仮1日の売上小計 | AO10: =TEXT(K11,"¥0") -> ¥2010 | AP10: =(H10/100)*AQ10 -> 0.000833333 | AQ10: 0.0833333
E11: 6月 | F11: =COUNTIF(D172:D201,1) -> 25 | G11: =$B$7*F11 -> 55836.24 | H11: 0.9 | J11: =G11*H11 -> 50252.616 | K11: =J11/F11 -> 2010.1046 | M11: =SUM(J172:J201) -> 53543.139 | N11: =M11-J11 -> 3290.5238 | P11: =M11/G11 -> 0.95893169 | R11: ランチ | S11: 1100 | T11: 60 | V11: =S11*T11 -> 66000 | AO11: =TEXT(K12,"¥0") -> ¥2122 | AP11: =(H11/100)*AQ11 -> 0.0007499997 | AQ11: 0.0833333
E12: 7月 | F12: =COUNTIF(D202:D232,1) -> 26 | G12: =$B$7*F12 -> 58069.689 | H12: 0.95 | J12: =G12*H12 -> 55166.205 | K12: =J12/F12 -> 2121.7771 | M12: =SUM(J202:J232) -> 59109.888 | N12: =M12-J12 -> 3943.6829 | P12: =M12/G12 -> 1.0179129 | R12: ディナー | S12: 4500 | T12: 20 | V12: =S12*T12 -> 90000 | AO12: =TEXT(K13,"¥0") -> ¥1787 | AP12: =(H12/100)*AQ12 -> 0.00079166635 | AQ12: 0.0833333
B13: 110.34 | E13: 8月 | F13: =COUNTIF(D233:D263,1) -> 22 | G13: =$B$7*F13 -> 49135.891 | H13: 0.8 | J13: =G13*H13 -> 39308.713 | K13: =J13/F13 -> 1786.7597 | M13: =SUM(J233:J263) -> 40891.807 | N13: =M13-J13 -> 1583.0945 | P13: =M13/G13 -> 0.8322187 | R13: Party 5500 | S13: 5500 | T13: 30 | V13: =S13*T13 -> 165000 | AO13: =TEXT(K14,"¥0") -> ¥2122 | AP13: =(H13/100)*AQ13 -> 0.0006666664 | AQ13: 0.0833333
E14: 9 月 | F14: =COUNTIF(D264:D293,1) -> 23 | G14: =$B$7*F14 -> 51369.34 | H14: 0.95 | J14: =G14*H14 -> 48800.873 | K14: =J14/F14 -> 2121.7771 | M14: =SUM(J264:J293) -> 49166.893 | N14: =M14-J14 -> 366.01985 | P14: =M14/G14 -> 0.95712526 | T14: 0 | V14: =S14*T14 -> 0 | AO14: =TEXT(K15,"¥0") -> ¥2792 | AP14: =(H14/100)*AQ14 -> 0.00079166635 | AQ14: 0.0833333
E15: 10月 | F15: =COUNTIF(D294:D324,1) -> 26 | G15: =$B$7*F15 -> 58069.689 | H15: 1.25 | J15: =G15*H15 -> 72587.111 | K15: =J15/F15 -> 2791.812 | M15: =SUM(J294:J324) -> 50349.193 | N15: =M15-J15 -> -22237.918 | P15: =M15/G15 -> 0.86704775 | T15: 0 | V15: =S15*T15 -> 0 | AO15: =TEXT(K16,"¥0") -> ¥2345 | AP15: =(H15/100)*AQ15 -> 0.0010416662 | AQ15: 0.0833333
E16: 11月 | F16: =COUNTIF(D325:D354,1) -> 24 | G16: =$B$7*F16 -> 53602.79 | H16: 1.05 | J16: =G16*H16 -> 56282.929 | K16: =J16/F16 -> 2345.1221 | M16: =SUM(J325:J354) -> 55393.783 | N16: =M16-J16 -> -889.14664 | P16: =M16/G16 -> 1.0334123 | T16: 0 | V16: =S16*T16 -> 0 | AO16: =TEXT(K17,"¥0") -> ¥2903 | AP16: =(H16/100)*AQ16 -> 0.00087499965 | AQ16: 0.0833333
E17: 12月 | F17: =COUNTIF(D355:D385,1) -> 24 | G17: =$B$7*F17 -> 53602.79 | H17: 1.3 | J17: =G17*H17 -> 69683.627 | K17: =J17/F17 -> 2903.4845 | M17: =SUM(J355:J385) -> 71591.898 | N17: =M17-J17 -> 1908.2708 | P17: =M17/G17 -> 1.3356002 | AP17: =(H17/100)*AQ17 -> 0.0010833329 | AQ17: 0.0833333
E19: 月 | F19: 日程 | G19: 曜日 | H19: 休店日理由 | J19: Daily売上入力 | L19: 目標売上 KPI | M19: 日次実質売上 | N19: 実質% | P19: 月次目標売上 | Q19: 月次実質売上 | R19: 月次差額(勝率) | S19: 月次実質% | U19: 年次目標売上 | V19: 年次実質売上 | W19: 年次差額(勝率) | X19: 年次実質% | AC19: 月 | AD19: 曜日 | AE19: 平均売上 | AF19: 曜日回数 | AH19: 曜日合計額 | AI19: 加重比率
C20: 1 | D20: 0 | E20: =TEXT(AA20,"m") -> 1 | F20: =B2 -> 45292 | G20: =TEXT(AS20,"ddd") -> Mon | H20: 元旦 | L20: =IF(D20=0,0,$K$6) -> 0 | M20: =IF(D20=0,0,J20-L20) -> 0 | N20: =IFERROR(J20/L20,"0%") -> 0% | P20: =IF(D20=0,0,$K$6) -> 0 | Q20: =IF(D20=0,0,$J$20) -> 0 | R20: =IF(D20=0,0,Q20-P20) -> 0 | S20: =IFERROR(Q20/P20,"0%") -> 0% | U20: =IF(D20=0,0,$L$20) -> 0 | V20: =IF(D20=0,0,$J$20) -> 0 | W20: =IF(D20=0,0,V20-U20) -> 0 | X20: =IFERROR(V20/U20,"0%") -> 0% | Z20: =B2 -> 45292 | AA20: =B2 -> 45292 | AB20: 45292 | AC20: 1 | AD20: 月 | AE20: =IFERROR(AVERAGEIFS(J20:J50,D20:D50,1,G20:G50,"mon"),0) -> 2293.1394 | AF20: =COUNTIFS(D20:D50,1,G20:G50,"Mon") -> 4 | AG20: =SUMIFS(J20:J50,D20:D50,1,G20:G50,"mon") -> 9172.5575 | AH20: =AE20*AF20 -> 9172.5575 | AI20: =AH20/$M$6 -> 0.2031361 | AJ20: =SUM(AI20:AI26) -> 1 | AS20: =B2 -> 45292
C21: =C20+1 -> 2 | D21: 0 | E21: =TEXT(AA21,"m") -> 1 | F21: =F20+1 -> 45293 | G21: =TEXT(AS21,"ddd") -> Tue | H21: 休み | L21: =IF(D21=0,0,$K$6) -> 0 | M21: =IF(D21=0,0,J21-L21) -> 0 | N21: =IFERROR(J21/L21,"0%") -> 0% | P21: =IF(D21=0,0,SUM($L$20:L21)) -> 0 | Q21: =IF(D21=0,0,SUM($J$20:J21)) -> 0 | R21: =IF(D21=0,0,Q21-P21) -> 0 | S21: =IFERROR(Q21/P21,"0%") -> 0% | U21: =IF(D21=0,0,SUM($L$20:L21)) -> 0 | V21: =IF(D21=0,0,SUM($J$20:J21)) -> 0 | W21: =IF(D21=0,0,V21-U21) -> 0 | X21: =IFERROR(V21/U21,"0%") -> 0% | Z21: =Z20+1 -> 45293 | AA21: =AA20+1 -> 45293 | AB21: 45293 | AC21: 1 | AD21: 火 | AE21: =IFERROR(AVERAGEIFS(J20:J50,D20:D50,1,G20:G50,"tue"),0) -> 1943.1847 | AF21: =COUNTIFS(D20:D50,1,G20:G50,"Tue") -> 4 | AH21: =AE21*AF21 -> 7772.7388 | AI21: =AH21/$M$6 -> 0.17213561 | AS21: =AS20+1 -> 45293
C22: =C21+1 -> 3 | D22: 0 | E22: =TEXT(AA22,"m") -> 1 | F22: =F21+1 -> 45294 | G22: =TEXT(AS22,"ddd") -> Wed | H22: 休み | L22: =IF(D22=0,0,$K$6) -> 0 | M22: =IF(D22=0,0,J22-L22) -> 0 | N22: =IFERROR(J22/L22,"0%") -> 0% | P22: =IF(D22=0,0,SUM($L$20:L22)) -> 0 | Q22: =IF(D22=0,0,SUM($J$20:J22)) -> 0 | R22: =IF(D22=0,0,Q22-P22) -> 0 | S22: =IFERROR(Q22/P22,"0%") -> 0% | U22: =IF(D22=0,0,SUM($L$20:L22)) -> 0 | V22: =IF(D22=0,0,SUM($J$20:J22)) -> 0 | W22: =IF(D22=0,0,V22-U22) -> 0 | X22: =IFERROR(V22/U22,"0%") -> 0% | Z22: =Z21+1 -> 45294 | AA22: =AA21+1 -> 45294 | AB22: 45294 | AC22: 1 | AD22: 水 | AE22: =IFERROR(AVERAGEIFS(J20:J50,D20:D50,1,G20:G50,"wed"),0) -> 2188.6895 | AF22: =COUNTIFS(D20:D50,1,G20:G50,"wed") -> 4 | AH22: =AE22*AF22 -> 8754.758 | AI22: =AH22/$M$6 -> 0.19388348 | AS22: =AS21+1 -> 45294
C23: =C22+1 -> 4 | D23: 0 | E23: =TEXT(AA23,"m") -> 1 | F23: =F22+1 -> 45295 | G23: =TEXT(AS23,"ddd") -> Thu | H23: 祝日 | L23: =IF(D23=0,0,$K$6) -> 0 | M23: =IF(D23=0,0,J23-L23) -> 0 | N23: =IFERROR(J23/L23,"0%") -> 0% | P23: =IF(D23=0,0,SUM($L$20:L23)) -> 0 | Q23: =IF(D23=0,0,SUM($J$20:J23)) -> 0 | R23: =IF(D23=0,0,Q23-P23) -> 0 | S23: =IFERROR(Q23/P23,"0%") -> 0% | U23: =IF(D23=0,0,SUM($L$20:L23)) -> 0 | V23: =IF(D23=0,0,SUM($J$20:J23)) -> 0 | W23: =IF(D23=0,0,V23-U23) -> 0 | X23: =IFERROR(V23/U23,"0%") -> 0% | Z23: =Z22+1 -> 45295 | AA23: =AA22+1 -> 45295 | AB23: 45295 | AC23: 1 | AD23: 木 | AE23: =IFERROR(AVERAGEIFS(J20:J50,D20:D50,1,G20:G50,"thu"),0) -> 2027.4304 | AF23: =COUNTIFS(D20:D50,1,G20:G50,"thu") -> 3 | AH23: =AE23*AF23 -> 6082.2911 | AI23: =AH23/$M$6 -> 0.13469884 | AS23: =AS22+1 -> 45295
C24: =C23+1 -> 5 | D24: 1 | E24: =TEXT(AA24,"m") -> 1 | F24: =F23+1 -> 45296 | G24: =TEXT(AS24,"ddd") -> Fri | J24: =365950/$B$13 -> 3316.567 | L24: =IF(D24=0,0,$K$6) -> 2010.1046 | M24: =IF(D24=0,0,J24-L24) -> 1306.4624 | N24: =IFERROR(J24/L24,"0%") -> 1.6499474 | P24: =IF(D24=0,0,SUM($L$20:L24)) -> 2010.1046 | Q24: =IF(D24=0,0,SUM($J$20:J24)) -> 3316.567 | R24: =IF(D24=0,0,Q24-P24) -> 1306.4624 | S24: =IFERROR(Q24/P24,"0%") -> 1.6499474 | U24: =IF(D24=0,0,SUM($L$20:L24)) -> 2010.1046 | V24: =IF(D24=0,0,SUM($J$20:J24)) -> 3316.567 | W24: =IF(D24=0,0,V24-U24) -> 1306.4624 | X24: =IFERROR(V24/U24,"0%") -> 1.6499474 | Z24: =Z23+1 -> 45296 | AA24: =AA23+1 -> 45296 | AB24: 45296 | AC24: 1 | AD24: 金 | AE24: =IFERROR(AVERAGEIFS(J20:J50,D20:D50,1,G20:G50,"fri"),0) -> 2654.7716 | AF24: =COUNTIFS(D20:D50,1,G20:G50,"fri") -> 4 | AH24: =AE24*AF24 -> 10619.086 | AI24: =AH24/$M$6 -> 0.23517102 | AS24: =AS23+1 -> 45296
C25: =C24+1 -> 6 | D25: 0 | E25: =TEXT(AA25,"m") -> 1 | F25: =F24+1 -> 45297 | G25: =TEXT(AS25,"ddd") -> Sat | L25: =IF(D25=0,0,$K$6) -> 0 | M25: =IF(D25=0,0,J25-L25) -> 0 | N25: =IFERROR(J25/L25,"0%") -> 0% | P25: =IF(D25=0,0,SUM($L$20:L25)) -> 0 | Q25: =IF(D25=0,0,SUM($J$20:J25)) -> 0 | R25: =IF(D25=0,0,Q25-P25) -> 0 | S25: =IFERROR(Q25/P25,"0%") -> 0% | U25: =IF(D25=0,0,SUM($L$20:L25)) -> 0 | V25: =IF(D25=0,0,SUM($J$20:J25)) -> 0 | W25: =IF(D25=0,0,V25-U25) -> 0 | X25: =IFERROR(V25/U25,"0%") -> 0% | Z25: =Z24+1 -> 45297 | AA25: =AA24+1 -> 45297 | AB25: 45297 | AC25: 1 | AD25: 土 | AE25: =IFERROR(AVERAGEIFS(J20:J50,D20:D50,1,G20:G50,"sat"),0) -> 917.76932 | AF25: =COUNTIFS(D20:D50,1,G20:G50,"sat") -> 3 | AH25: =AE25*AF25 -> 2753.308 | AI25: =AH25/$M$6 -> 0.060974949 | AS25: =AS24+1 -> 45297
C26: =C25+1 -> 7 | D26: 0 | E26: =TEXT(AA26,"m") -> 1 | F26: =F25+1 -> 45298 | G26: =TEXT(AS26,"ddd") -> Sun | H26: 日曜日 | L26: =IF(D26=0,0,$K$6) -> 0 | M26: =IF(D26=0,0,J26-L26) -> 0 | N26: =IFERROR(J26/L26,"0%") -> 0% | P26: =IF(D26=0,0,SUM($L$20:L26)) -> 0 | Q26: =IF(D26=0,0,SUM($J$20:J26)) -> 0 | R26: =IF(D26=0,0,Q26-P26) -> 0 | S26: =IFERROR(Q26/P26,"0%") -> 0% | U26: =IF(D26=0,0,SUM($L$20:L26)) -> 0 | V26: =IF(D26=0,0,SUM($J$20:J26)) -> 0 | W26: =IF(D26=0,0,V26-U26) -> 0 | X26: =IFERROR(V26/U26,"0%") -> 0% | Z26: =Z25+1 -> 45298 | AA26: =AA25+1 -> 45298 | AB26: 45298 | AC26: 1 | AD26: 日 | AE26: =IFERROR(AVERAGEIFS(J20:J50,D20:D50,1,G20:G50,"sun"),0) -> 0 | AF26: =IFERROR(COUNTIFS(D20:D50,1,G20:G50,"sun"),0) -> 0 | AH26: =AE26*AF26 -> 0 | AI26: =AH26/$M$6 -> 0 | AS26: =AS25+1 -> 45298
C27: =C26+1 -> 8 | D27: 1 | E27: =TEXT(AA27,"m") -> 1 | F27: =F26+1 -> 45299 | G27: =TEXT(AS27,"ddd") -> Mon | J27: =250000/$B$13 -> 2265.7241 | L27: =IF(D27=0,0,$K$6) -> 2010.1046 | M27: =IF(D27=0,0,J27-L27) -> 255.6195 | N27: =IFERROR(J27/L27,"0%") -> 1.1271673 | P27: =IF(D27=0,0,SUM($L$20:L27)) -> 4020.2092 | Q27: =IF(D27=0,0,SUM($J$20:J27)) -> 5582.2911 | R27: =IF(D27=0,0,Q27-P27) -> 1562.0819 | S27: =IFERROR(Q27/P27,"0%") -> 1.3885573 | U27: =IF(D27=0,0,SUM($L$20:L27)) -> 4020.2092 | V27: =IF(D27=0,0,SUM($J$20:J27)) -> 5582.2911 | W27: =IF(D27=0,0,V27-U27) -> 1562.0819 | X27: =IFERROR(V27/U27,"0%") -> 1.3885573 | Z27: =Z26+1 -> 45299 | AA27: =AA26+1 -> 45299 | AB27: 45299 | AC27: 2 | AD27: 月 | AE27: =AVERAGEIFS(J51:J79,D51:D79,1,G51:G79,"mon") -> 2095.7948 | AF27: =COUNTIFS(D51:D79,1,G51:G79,"Mon") -> 3 | AH27: =AE27*AF27 -> 6287.3844 | AI27: =AH27/$M$7 -> 0.13869924 | AJ27: =SUM(AI27:AI33) -> 1 | AK27: 51〜79 | AS27: =AS26+1 -> 45299
C28: =C27+1 -> 9 | D28: 1 | E28: =TEXT(AA28,"m") -> 1 | F28: =F27+1 -> 45300 | G28: =TEXT(AS28,"ddd") -> Tue | J28: =143850/$B$13 -> 1303.6977 | L28: =IF(D28=0,0,$K$6) -> 2010.1046 | M28: =IF(D28=0,0,J28-L28) -> -706.40696 | N28: =IFERROR(J28/L28,"0%") -> 0.64857204 | P28: =IF(D28=0,0,SUM($L$20:L28)) -> 6030.3139 | Q28: =IF(D28=0,0,SUM($J$20:J28)) -> 6885.9888 | R28: =IF(D28=0,0,Q28-P28) -> 855.67489 | S28: =IFERROR(Q28/P28,"0%") -> 1.1418956 | U28: =IF(D28=0,0,SUM($L$20:L28)) -> 6030.3139 | V28: =IF(D28=0,0,SUM($J$20:J28)) -> 6885.9888 | W28: =IF(D28=0,0,V28-U28) -> 855.67489 | X28: =IFERROR(V28/U28,"0%") -> 1.1418956 | Z28: =Z27+1 -> 45300 | AA28: =AA27+1 -> 45300 | AB28: 45300 | AC28: 2 | AD28: 火 | AE28: =AVERAGEIFS(J51:J79,D51:D79,1,G51:G79,"tue") -> 1941.6803 | AF28: =COUNTIFS(D51:D79,1,G51:G79,"tue") -> 4 | AH28: =AE28*AF28 -> 7766.721 | AI28: =AH28/$M$7 -> 0.17133329 | AS28: =AS27+1 -> 45300
C29: =C28+1 -> 10 | D29: 1 | E29: =TEXT(AA29,"m") -> 1 | F29: =F28+1 -> 45301 | G29: =TEXT(AS29,"ddd") -> Wed | J29: =331400/$B$13 -> 3003.4439 | L29: =IF(D29=0,0,$K$6) -> 2010.1046 | M29: =IF(D29=0,0,J29-L29) -> 993.33928 | N29: =IFERROR(J29/L29,"0%") -> 1.4941729 | P29: =IF(D29=0,0,SUM($L$20:L29)) -> 8040.4185 | Q29: =IF(D29=0,0,SUM($J$20:J29)) -> 9889.4327 | R29: =IF(D29=0,0,Q29-P29) -> 1849.0142 | S29: =IFERROR(Q29/P29,"0%") -> 1.2299649 | U29: =IF(D29=0,0,SUM($L$20:L29)) -> 8040.4185 | V29: =IF(D29=0,0,SUM($J$20:J29)) -> 9889.4327 | W29: =IF(D29=0,0,V29-U29) -> 1849.0142 | X29: =IFERROR(V29/U29,"0%") -> 1.2299649 | Z29: =Z28+1 -> 45301 | AA29: =AA28+1 -> 45301 | AB29: 45301 | AC29: 2 | AD29: 水 | AE29: =AVERAGEIFS(J51:J79,D51:D79,1,G51:G79,"wed") -> 2009.4028 | AF29: =COUNTIFS(D51:D79,1,G51:G79,"wed") -> 4 | AH29: =AE29*AF29 -> 8037.611 | AI29: =AH29/$M$7 -> 0.1773091 | AS29: =AS28+1 -> 45301
C30: =C29+1 -> 11 | D30: 1 | E30: =TEXT(AA30,"m") -> 1 | F30: =F29+1 -> 45302 | G30: =TEXT(AS30,"ddd") -> Thu | J30: =263220/$B$13 -> 2385.5356 | L30: =IF(D30=0,0,$K$6) -> 2010.1046 | M30: =IF(D30=0,0,J30-L30) -> 375.43099 | N30: =IFERROR(J30/L30,"0%") -> 1.1867719 | P30: =IF(D30=0,0,SUM($L$20:L30)) -> 10050.523 | Q30: =IF(D30=0,0,SUM($J$20:J30)) -> 12274.968 | R30: =IF(D30=0,0,Q30-P30) -> 2224.4452 | S30: =IFERROR(Q30/P30,"0%") -> 1.2213263 | U30: =IF(D30=0,0,SUM($L$20:L30)) -> 10050.523 | V30: =IF(D30=0,0,SUM($J$20:J30)) -> 12274.968 | W30: =IF(D30=0,0,V30-U30) -> 2224.4452 | X30: =IFERROR(V30/U30,"0%") -> 1.2213263 | Z30: =Z29+1 -> 45302 | AA30: =AA29+1 -> 45302 | AB30: 45302 | AC30: 2 | AD30: 木 | AE30: =AVERAGEIFS(J51:J79,D51:D79,1,G51:G79,"thu") -> 2115.2438 | AF30: =COUNTIFS(D51:D79,1,G51:G79,"thu") -> 5 | AH30: =AE30*AF30 -> 10576.219 | AI30: =AH30/$M$7 -> 0.23331061 | AS30: =AS29+1 -> 45302
C31: =C30+1 -> 12 | D31: 1 | E31: =TEXT(AA31,"m") -> 1 | F31: =F30+1 -> 45303 | G31: =TEXT(AS31,"ddd") -> Fri | J31: =230860/$B$13 -> 2092.2603 | L31: =IF(D31=0,0,$K$6) -> 2010.1046 | M31: =IF(D31=0,0,J31-L31) -> 82.155662 | N31: =IFERROR(J31/L31,"0%") -> 1.0408713 | P31: =IF(D31=0,0,SUM($L$20:L31)) -> 12060.628 | Q31: =IF(D31=0,0,SUM($J$20:J31)) -> 14367.229 | R31: =IF(D31=0,0,Q31-P31) -> 2306.6008 | S31: =IFERROR(Q31/P31,"0%") -> 1.1912505 | U31: =IF(D31=0,0,SUM($L$20:L31)) -> 12060.628 | V31: =IF(D31=0,0,SUM($J$20:J31)) -> 14367.229 | W31: =IF(D31=0,0,V31-U31) -> 2306.6008 | X31: =IFERROR(V31/U31,"0%") -> 1.1912505 | Z31: =Z30+1 -> 45303 | AA31: =AA30+1 -> 45303 | AB31: 45303 | AC31: 2 | AD31: 金 | AE31: =AVERAGEIFS(J51:J79,D51:D79,1,G51:G79,"fri") -> 2572.8959 | AF31: =COUNTIFS(D51:D79,1,G51:G79,"fri") -> 3 | AH31: =AE31*AF31 -> 7718.6877 | AI31: =AH31/$M$7 -> 0.17027368 | AS31: =AS30+1 -> 45303
C32: =C31+1 -> 13 | D32: 1 | E32: =TEXT(AA32,"m") -> 1 | F32: =F31+1 -> 45304 | G32: =TEXT(AS32,"ddd") -> Sat | J32: =50050/$B$13 -> 453.59797 | L32: =IF(D32=0,0,$K$6) -> 2010.1046 | M32: =IF(D32=0,0,J32-L32) -> -1556.5067 | N32: =IFERROR(J32/L32,"0%") -> 0.22565889 | P32: =IF(D32=0,0,SUM($L$20:L32)) -> 14070.732 | Q32: =IF(D32=0,0,SUM($J$20:J32)) -> 14820.827 | R32: =IF(D32=0,0,Q32-P32) -> 750.09416 | S32: =IFERROR(Q32/P32,"0%") -> 1.0533088 | U32: =IF(D32=0,0,SUM($L$20:L32)) -> 14070.732 | V32: =IF(D32=0,0,SUM($J$20:J32)) -> 14820.827 | W32: =IF(D32=0,0,V32-U32) -> 750.09416 | X32: =IFERROR(V32/U32,"0%") -> 1.0533088 | Z32: =Z31+1 -> 45304 | AA32: =AA31+1 -> 45304 | AB32: 45304 | AC32: 2 | AD32: 土 | AE32: =AVERAGEIFS(J51:J79,D51:D79,1,G51:G79,"sat") -> 1236.1111 | AF32: =COUNTIFS(D51:D79,1,G51:G79,"sat") -> 4 | AH32: =AE32*AF32 -> 4944.4444 | AI32: =AH32/$M$7 -> 0.10907408 | AS32: =AS31+1 -> 45304
C33: =C32+1 -> 14 | D33: 0 | E33: =TEXT(AA33,"m") -> 1 | F33: =F32+1 -> 45305 | G33: =TEXT(AS33,"ddd") -> Sun | L33: =IF(D33=0,0,$K$6) -> 0 | M33: =IF(D33=0,0,J33-L33) -> 0 | N33: =IFERROR(J33/L33,"0%") -> 0% | P33: =IF(D33=0,0,SUM($L$20:L33)) -> 0 | Q33: =IF(D33=0,0,SUM($J$20:J33)) -> 0 | R33: =IF(D33=0,0,Q33-P33) -> 0 | S33: =IFERROR(Q33/P33,"0%") -> 0% | U33: =IF(D33=0,0,SUM($L$20:L33)) -> 0 | V33: =IF(D33=0,0,SUM($J$20:J33)) -> 0 | W33: =IF(D33=0,0,V33-U33) -> 0 | X33: =IFERROR(V33/U33,"0%") -> 0% | Z33: =Z32+1 -> 45305 | AA33: =AA32+1 -> 45305 | AB33: 45305 | AC33: 2 | AD33: 日 | AE33: =IFERROR(AVERAGEIFS(J51:J79,D51:D79,1,G51:G79,"sun"),0) -> 0 | AF33: =IFERROR(COUNTIFS(D51:D79,1,G51:G79,"sun"),0) -> 0 | AH33: =AE33*AF33 -> 0 | AI33: =AH33/$M$7 -> 0 | AS33: =AS32+1 -> 45305
C34: =C33+1 -> 15 | D34: 1 | E34: =TEXT(AA34,"m") -> 1 | F34: =F33+1 -> 45306 | G34: =TEXT(AS34,"ddd") -> Mon | J34: =189100/$B$13 -> 1713.7937 | L34: =IF(D34=0,0,$K$6) -> 2010.1046 | M34: =IF(D34=0,0,J34-L34) -> -296.3109 | N34: =IFERROR(J34/L34,"0%") -> 0.85258932 | P34: =IF(D34=0,0,SUM($L$20:L34)) -> 16080.837 | Q34: =IF(D34=0,0,SUM($J$20:J34)) -> 16534.62 | R34: =IF(D34=0,0,Q34-P34) -> 453.78327 | S34: =IFERROR(Q34/P34,"0%") -> 1.0282189 | U34: =IF(D34=0,0,SUM($L$20:L34)) -> 16080.837 | V34: =IF(D34=0,0,SUM($J$20:J34)) -> 16534.62 | W34: =IF(D34=0,0,V34-U34) -> 453.78327 | X34: =IFERROR(V34/U34,"0%") -> 1.0282189 | Z34: =Z33+1 -> 45306 | AA34: =AA33+1 -> 45306 | AB34: 45306 | AC34: 3 | AD34: 月 | AE34: =AVERAGEIFS(J80:J110,D80:D110,1,G80:G110,"mon") -> 2075.0634 | AF34: =COUNTIFS( D80:D110,1,G80:G110,"Mon") -> 4 | AH34: =AE34*AF34 -> 8300.2538 | AI34: =AH34/$M$8 -> 0.1417591 | AJ34: =SUM(AI34:AI40) -> 1 | AK34: 80〜110 | AS34: =AS33+1 -> 45306
C35: =C34+1 -> 16 | D35: 1 | E35: =TEXT(AA35,"m") -> 1 | F35: =F34+1 -> 45307 | G35: =TEXT(AS35,"ddd") -> Tue | J35: =212700/$B$13 -> 1927.6781 | L35: =IF(D35=0,0,$K$6) -> 2010.1046 | M35: =IF(D35=0,0,J35-L35) -> -82.426539 | N35: =IFERROR(J35/L35,"0%") -> 0.95899391 | P35: =IF(D35=0,0,SUM($L$20:L35)) -> 18090.942 | Q35: =IF(D35=0,0,SUM($J$20:J35)) -> 18462.298 | R35: =IF(D35=0,0,Q35-P35) -> 371.35673 | S35: =IFERROR(Q35/P35,"0%") -> 1.0205272 | U35: =IF(D35=0,0,SUM($L$20:L35)) -> 18090.942 | V35: =IF(D35=0,0,SUM($J$20:J35)) -> 18462.298 | W35: =IF(D35=0,0,V35-U35) -> 371.35673 | X35: =IFERROR(V35/U35,"0%") -> 1.0205272 | Z35: =Z34+1 -> 45307 | AA35: =AA34+1 -> 45307 | AB35: 45307 | AC35: 3 | AD35: 火 | AE35: =AVERAGEIFS(J80:J110,D80:D110,1,G80:G110,"tue") -> 2392.3101 | AF35: =COUNTIFS( D80:D110,1,G80:G110,"tue") -> 4 | AH35: =AE35*AF35 -> 9569.2405 | AI35: =AH35/$M$8 -> 0.16343199 | AS35: =AS34+1 -> 45307
C36: =C35+1 -> 17 | D36: 1 | E36: =TEXT(AA36,"m") -> 1 | F36: =F35+1 -> 45308 | G36: =TEXT(AS36,"ddd") -> Wed | J36: =172600/$B$13 -> 1564.2559 | L36: =IF(D36=0,0,$K$6) -> 2010.1046 | M36: =IF(D36=0,0,J36-L36) -> -445.84869 | N36: =IFERROR(J36/L36,"0%") -> 0.77819628 | P36: =IF(D36=0,0,SUM($L$20:L36)) -> 20101.046 | Q36: =IF(D36=0,0,SUM($J$20:J36)) -> 20026.554 | R36: =IF(D36=0,0,Q36-P36) -> -74.49196 | S36: =IFERROR(Q36/P36,"0%") -> 0.99629413 | U36: =IF(D36=0,0,SUM($L$20:L36)) -> 20101.046 | V36: =IF(D36=0,0,SUM($J$20:J36)) -> 20026.554 | W36: =IF(D36=0,0,V36-U36) -> -74.49196 | X36: =IFERROR(V36/U36,"0%") -> 0.99629413 | Z36: =Z35+1 -> 45308 | AA36: =AA35+1 -> 45308 | AB36: 45308 | AC36: 3 | AD36: 水 | AE36: =AVERAGEIFS(J80:J110,D80:D110,1,G80:G110,"wed") -> 2664.0384 | AF36: =COUNTIFS( D80:D110,1,G80:G110,"wed") -> 3 | AH36: =AE36*AF36 -> 7992.1153 | AI36: =AH36/$M$8 -> 0.13649644 | AS36: =AS35+1 -> 45308
C37: =C36+1 -> 18 | D37: 1 | E37: =TEXT(AA37,"m") -> 1 | F37: =F36+1 -> 45309 | G37: =TEXT(AS37,"ddd") -> Thu | J37: =155450/$B$13 -> 1408.8273 | L37: =IF(D37=0,0,$K$6) -> 2010.1046 | M37: =IF(D37=0,0,J37-L37) -> -601.27736 | N37: =IFERROR(J37/L37,"0%") -> 0.7008726 | P37: =IF(D37=0,0,SUM($L$20:L37)) -> 22111.151 | Q37: =IF(D37=0,0,SUM($J$20:J37)) -> 21435.382 | R37: =IF(D37=0,0,Q37-P37) -> -675.76932 | S37: =IFERROR(Q37/P37,"0%") -> 0.96943762 | U37: =IF(D37=0,0,SUM($L$20:L37)) -> 22111.151 | V37: =IF(D37=0,0,SUM($J$20:J37)) -> 21435.382 | W37: =IF(D37=0,0,V37-U37) -> -675.76932 | X37: =IFERROR(V37/U37,"0%") -> 0.96943762 | Z37: =Z36+1 -> 45309 | AA37: =AA36+1 -> 45309 | AB37: 45309 | AC37: 3 | AD37: 木 | AE37: =AVERAGEIFS(J80:J110,D80:D110,1,G80:G110,"thu") -> 2796.8778 | AF37: =COUNTIFS( D80:D110,1,G80:G110,"thu") -> 4 | AH37: =AE37*AF37 -> 11187.511 | AI37: =AH37/$M$8 -> 0.19107025 | AS37: =AS36+1 -> 45309
C38: =C37+1 -> 19 | D38: 1 | E38: =TEXT(AA38,"m") -> 1 | F38: =F37+1 -> 45310 | G38: =TEXT(AS38,"ddd") -> Fri | J38: =286750/$B$13 -> 2598.7856 | L38: =IF(D38=0,0,$K$6) -> 2010.1046 | M38: =IF(D38=0,0,J38-L38) -> 588.68095 | N38: =IFERROR(J38/L38,"0%") -> 1.2928608 | P38: =IF(D38=0,0,SUM($L$20:L38)) -> 24121.255 | Q38: =IF(D38=0,0,SUM($J$20:J38)) -> 24034.167 | R38: =IF(D38=0,0,Q38-P38) -> -87.088377 | S38: =IFERROR(Q38/P38,"0%") -> 0.99638956 | U38: =IF(D38=0,0,SUM($L$20:L38)) -> 24121.255 | V38: =IF(D38=0,0,SUM($J$20:J38)) -> 24034.167 | W38: =IF(D38=0,0,V38-U38) -> -87.088377 | X38: =IFERROR(V38/U38,"0%") -> 0.99638956 | Z38: =Z37+1 -> 45310 | AA38: =AA37+1 -> 45310 | AB38: 45310 | AC38: 3 | AD38: 金 | AE38: =AVERAGEIFS(J80:J110,D80:D110,1,G80:G110,"fri") -> 2923.926 | AF38: =COUNTIFS( D80:D110,1,G80:G110,"fri") -> 5 | AH38: =AE38*AF38 -> 14619.63 | AI38: =AH38/$M$8 -> 0.24968703 | AS38: =AS37+1 -> 45310
C39: =C38+1 -> 20 | D39: 1 | E39: =TEXT(AA39,"m") -> 1 | F39: =F38+1 -> 45311 | G39: =TEXT(AS39,"ddd") -> Sat | J39: =139100/$B$13 -> 1260.6489 | L39: =IF(D39=0,0,$K$6) -> 2010.1046 | M39: =IF(D39=0,0,J39-L39) -> -749.45572 | N39: =IFERROR(J39/L39,"0%") -> 0.62715586 | P39: =IF(D39=0,0,SUM($L$20:L39)) -> 26131.36 | Q39: =IF(D39=0,0,SUM($J$20:J39)) -> 25294.816 | R39: =IF(D39=0,0,Q39-P39) -> -836.5441 | S39: =IFERROR(Q39/P39,"0%") -> 0.96798697 | U39: =IF(D39=0,0,SUM($L$20:L39)) -> 26131.36 | V39: =IF(D39=0,0,SUM($J$20:J39)) -> 25294.816 | W39: =IF(D39=0,0,V39-U39) -> -836.5441 | X39: =IFERROR(V39/U39,"0%") -> 0.96798697 | Z39: =Z38+1 -> 45311 | AA39: =AA38+1 -> 45311 | AB39: 45311 | AC39: 3 | AD39: 土 | AE39: =AVERAGEIFS(J80:J110,D80:D110,1,G80:G110,"sat") -> 1376.6141 | AF39: =COUNTIFS( D80:D110,1,G80:G110,"sat") -> 5 | AH39: =AE39*AF39 -> 6883.0705 | AI39: =AH39/$M$8 -> 0.11755519 | AS39: =AS38+1 -> 45311
C40: =C39+1 -> 21 | D40: 0 | E40: =TEXT(AA40,"m") -> 1 | F40: =F39+1 -> 45312 | G40: =TEXT(AS40,"ddd") -> Sun | H40: 日曜日 | L40: =IF(D40=0,0,$K$6) -> 0 | M40: =IF(D40=0,0,J40-L40) -> 0 | N40: =IFERROR(J40/L40,"0%") -> 0% | P40: =IF(D40=0,0,SUM($L$20:L40)) -> 0 | Q40: =IF(D40=0,0,SUM($J$20:J40)) -> 0 | R40: =IF(D40=0,0,Q40-P40) -> 0 | S40: =IFERROR(Q40/P40,"0%") -> 0% | U40: =IF(D40=0,0,SUM($L$20:L40)) -> 0 | V40: =IF(D40=0,0,SUM($J$20:J40)) -> 0 | W40: =IF(D40=0,0,V40-U40) -> 0 | X40: =IFERROR(V40/U40,"0%") -> 0% | Z40: =Z39+1 -> 45312 | AA40: =AA39+1 -> 45312 | AB40: 45312 | AC40: 3 | AD40: 日 | AE40: =IFERROR(AVERAGEIFS(J80:J110,D80:D110,3,G80:G110,"sun"),0) -> 0 | AF40: =IFERROR(COUNTIFS( D80:D110,1,G80:G110,"sun"),0) -> 0 | AH40: =AE40*AF40 -> 0 | AI40: =AH40/$M$8 -> 0 | AS40: =AS39+1 -> 45312
C41: =C40+1 -> 22 | D41: 1 | E41: =TEXT(AA41,"m") -> 1 | F41: =F40+1 -> 45313 | G41: =TEXT(AS41,"ddd") -> Mon | J41: =250550/$B$13 -> 2270.7087 | L41: =IF(D41=0,0,$K$6) -> 2010.1046 | M41: =IF(D41=0,0,J41-L41) -> 260.60409 | N41: =IFERROR(J41/L41,"0%") -> 1.129647 | P41: =IF(D41=0,0,SUM($L$20:L41)) -> 28141.465 | Q41: =IF(D41=0,0,SUM($J$20:J41)) -> 27565.525 | R41: =IF(D41=0,0,Q41-P41) -> -575.94 | S41: =IFERROR(Q41/P41,"0%") -> 0.97953411 | U41: =IF(D41=0,0,SUM($L$20:L41)) -> 28141.465 | V41: =IF(D41=0,0,SUM($J$20:J41)) -> 27565.525 | W41: =IF(D41=0,0,V41-U41) -> -575.94 | X41: =IFERROR(V41/U41,"0%") -> 0.97953411 | Z41: =Z40+1 -> 45313 | AA41: =AA40+1 -> 45313 | AB41: 45313 | AC41: 4 | AD41: 月 | AE41: =AVERAGEIFS(J111:J140,D111:D140,1,G111:G140,"mon") -> 2069.6484 | AF41: =COUNTIFS(D111:D140,1,G111:G140,"Mon") -> 4 | AH41: =AE41*AF41 -> 8278.5934 | AI41: =AH41/$M$9 -> 0.13681398 | AJ41: =SUM(AI41:AI47) -> 1 | AK41: 111〜140 | AS41: =AS40+1 -> 45313
C42: =C41+1 -> 23 | D42: 1 | E42: =TEXT(AA42,"m") -> 1 | F42: =F41+1 -> 45314 | G42: =TEXT(AS42,"ddd") -> Tue | J42: =312544/$B$13 -> 2832.5539 | L42: =IF(D42=0,0,$K$6) -> 2010.1046 | M42: =IF(D42=0,0,J42-L42) -> 822.4493 | N42: =IFERROR(J42/L42,"0%") -> 1.4091575 | P42: =IF(D42=0,0,SUM($L$20:L42)) -> 30151.569 | Q42: =IF(D42=0,0,SUM($J$20:J42)) -> 30398.079 | R42: =IF(D42=0,0,Q42-P42) -> 246.5093 | S42: =IFERROR(Q42/P42,"0%") -> 1.0081757 | U42: =IF(D42=0,0,SUM($L$20:L42)) -> 30151.569 | V42: =IF(D42=0,0,SUM($J$20:J42)) -> 30398.079 | W42: =IF(D42=0,0,V42-U42) -> 246.5093 | X42: =IFERROR(V42/U42,"0%") -> 1.0081757 | Z42: =Z41+1 -> 45314 | AA42: =AA41+1 -> 45314 | AB42: 45314 | AC42: 4 | AD42: 火 | AE42: =AVERAGEIFS(J111:J140,D111:D140,1,G111:G140,"tue") -> 2445.2365 | AF42: =COUNTIFS(D111:D140,1,G111:G140,"tue") -> 5 | AH42: =AE42*AF42 -> 12226.183 | AI42: =AH42/$M$9 -> 0.20205276 | AS42: =AS41+1 -> 45314
C43: =C42+1 -> 24 | D43: 1 | E43: =TEXT(AA43,"m") -> 1 | F43: =F42+1 -> 45315 | G43: =TEXT(AS43,"ddd") -> Wed | J43: =255500/$B$13 -> 2315.5701 | L43: =IF(D43=0,0,$K$6) -> 2010.1046 | M43: =IF(D43=0,0,J43-L43) -> 305.46543 | N43: =IFERROR(J43/L43,"0%") -> 1.1519649 | P43: =IF(D43=0,0,SUM($L$20:L43)) -> 32161.674 | Q43: =IF(D43=0,0,SUM($J$20:J43)) -> 32713.649 | R43: =IF(D43=0,0,Q43-P43) -> 551.97473 | S43: =IFERROR(Q43/P43,"0%") -> 1.0171625 | U43: =IF(D43=0,0,SUM($L$20:L43)) -> 32161.674 | V43: =IF(D43=0,0,SUM($J$20:J43)) -> 32713.649 | W43: =IF(D43=0,0,V43-U43) -> 551.97473 | X43: =IFERROR(V43/U43,"0%") -> 1.0171625 | Z43: =Z42+1 -> 45315 | AA43: =AA42+1 -> 45315 | AB43: 45315 | AC43: 4 | AD43: 水 | AE43: =AVERAGEIFS(J111:J140,D111:D140,1,G111:G140,"wed") -> 2652.8004 | AF43: =COUNTIFS(D111:D140,1,G111:G140,"wed") -> 4 | AH43: =AE43*AF43 -> 10611.202 | AI43: =AH43/$M$9 -> 0.17536321 | AS43: =AS42+1 -> 45315
C44: =C43+1 -> 25 | D44: 1 | E44: =TEXT(AA44,"m") -> 1 | F44: =F43+1 -> 45316 | G44: =TEXT(AS44,"ddd") -> Thu | J44: =252450/$B$13 -> 2287.9282 | L44: =IF(D44=0,0,$K$6) -> 2010.1046 | M44: =IF(D44=0,0,J44-L44) -> 277.8236 | N44: =IFERROR(J44/L44,"0%") -> 1.1382135 | P44: =IF(D44=0,0,SUM($L$20:L44)) -> 34171.779 | Q44: =IF(D44=0,0,SUM($J$20:J44)) -> 35001.577 | R44: =IF(D44=0,0,Q44-P44) -> 829.79832 | S44: =IFERROR(Q44/P44,"0%") -> 1.0242831 | U44: =IF(D44=0,0,SUM($L$20:L44)) -> 34171.779 | V44: =IF(D44=0,0,SUM($J$20:J44)) -> 35001.577 | W44: =IF(D44=0,0,V44-U44) -> 829.79832 | X44: =IFERROR(V44/U44,"0%") -> 1.0242831 | Z44: =Z43+1 -> 45316 | AA44: =AA43+1 -> 45316 | AB44: 45316 | AC44: 4 | AD44: 木 | AE44: =AVERAGEIFS(J111:J140,D111:D140,1,G111:G140,"thu") -> 2519.8704 | AF44: =COUNTIFS(D111:D140,1,G111:G140,"thu") -> 4 | AH44: =AE44*AF44 -> 10079.482 | AI44: =AH44/$M$9 -> 0.16657588 | AS44: =AS43+1 -> 45316
C45: =C44+1 -> 26 | D45: 1 | E45: =TEXT(AA45,"m") -> 1 | F45: =F44+1 -> 45317 | G45: =TEXT(AS45,"ddd") -> Fri | J45: =288150/$B$13 -> 2611.4736 | L45: =IF(D45=0,0,$K$6) -> 2010.1046 | M45: =IF(D45=0,0,J45-L45) -> 601.369 | N45: =IFERROR(J45/L45,"0%") -> 1.299173 | P45: =IF(D45=0,0,SUM($L$20:L45)) -> 36181.883 | Q45: =IF(D45=0,0,SUM($J$20:J45)) -> 37613.051 | R45: =IF(D45=0,0,Q45-P45) -> 1431.1673 | S45: =IFERROR(Q45/P45,"0%") -> 1.0395548 | U45: =IF(D45=0,0,SUM($L$20:L45)) -> 36181.883 | V45: =IF(D45=0,0,SUM($J$20:J45)) -> 37613.051 | W45: =IF(D45=0,0,V45-U45) -> 1431.1673 | X45: =IFERROR(V45/U45,"0%") -> 1.0395548 | Z45: =Z44+1 -> 45317 | AA45: =AA44+1 -> 45317 | AB45: 45317 | AC45: 4 | AD45: 金 | AE45: =AVERAGEIFS(J111:J140,D111:D140,1,G111:G140,"fri") -> 3000.9969 | AF45: =COUNTIFS(D111:D140,1,G111:G140,"fri") -> 4 | AH45: =AE45*AF45 -> 12003.988 | AI45: =AH45/$M$9 -> 0.19838072 | AS45: =AS44+1 -> 45317
C46: =C45+1 -> 27 | D46: 1 | E46: =TEXT(AA46,"m") -> 1 | F46: =F45+1 -> 45318 | G46: =TEXT(AS46,"ddd") -> Sat | J46: =114650/$B$13 -> 1039.0611 | L46: =IF(D46=0,0,$K$6) -> 2010.1046 | M46: =IF(D46=0,0,J46-L46) -> -971.04354 | N46: =IFERROR(J46/L46,"0%") -> 0.51691891 | P46: =IF(D46=0,0,SUM($L$20:L46)) -> 38191.988 | Q46: =IF(D46=0,0,SUM($J$20:J46)) -> 38652.112 | R46: =IF(D46=0,0,Q46-P46) -> 460.12379 | S46: =IFERROR(Q46/P46,"0%") -> 1.0120477 | U46: =IF(D46=0,0,SUM($L$20:L46)) -> 38191.988 | V46: =IF(D46=0,0,SUM($J$20:J46)) -> 38652.112 | W46: =IF(D46=0,0,V46-U46) -> 460.12379 | X46: =IFERROR(V46/U46,"0%") -> 1.0120477 | Z46: =Z45+1 -> 45318 | AA46: =AA45+1 -> 45318 | AB46: 45318 | AC46: 4 | AD46: 土 | AE46: =AVERAGEIFS(J111:J140,D111:D140,1,G111:G140,"sat") -> 1827.6011 | AF46: =COUNTIFS(D111:D140,1,G111:G140,"sat") -> 4 | AH46: =AE46*AF46 -> 7310.4042 | AI46: =AH46/$M$9 -> 0.12081345 | AS46: =AS45+1 -> 45318
C47: =C46+1 -> 28 | D47: 0 | E47: =TEXT(AA47,"m") -> 1 | F47: =F46+1 -> 45319 | G47: =TEXT(AS47,"ddd") -> Sun | H47: 日曜日 | L47: =IF(D47=0,0,$K$6) -> 0 | M47: =IF(D47=0,0,J47-L47) -> 0 | N47: =IFERROR(J47/L47,"0%") -> 0% | P47: =IF(D47=0,0,SUM($L$20:L47)) -> 0 | Q47: =IF(D47=0,0,SUM($J$20:J47)) -> 0 | R47: =IF(D47=0,0,Q47-P47) -> 0 | S47: =IFERROR(Q47/P47,"0%") -> 0% | U47: =IF(D47=0,0,SUM($L$20:L47)) -> 0 | V47: =IF(D47=0,0,SUM($J$20:J47)) -> 0 | W47: =IF(D47=0,0,V47-U47) -> 0 | X47: =IFERROR(V47/U47,"0%") -> 0% | Z47: =Z46+1 -> 45319 | AA47: =AA46+1 -> 45319 | AB47: 45319 | AC47: 4 | AD47: 日 | AE47: =IFERROR(AVERAGEIFS(J111:J140,D111:D140,1,G111:G140,"sun"),0) -> 0 | AF47: =IFERROR(COUNTIFS(D111:D140,1,G111:G140,"sun"),0) -> 0 | AH47: =AE47*AF47 -> 0 | AI47: =AH47/$M$9 -> 0 | AS47: =AS46+1 -> 45319
C48: =C47+1 -> 29 | D48: 1 | E48: =TEXT(AA48,"m") -> 1 | F48: =F47+1 -> 45320 | G48: =TEXT(AS48,"ddd") -> Mon | J48: =322450/$B$13 -> 2922.331 | L48: =IF(D48=0,0,$K$6) -> 2010.1046 | M48: =IF(D48=0,0,J48-L48) -> 912.22635 | N48: =IFERROR(J48/L48,"0%") -> 1.4538203 | P48: =IF(D48=0,0,SUM($L$20:L48)) -> 40202.092 | Q48: =IF(D48=0,0,SUM($J$20:J48)) -> 41574.443 | R48: =IF(D48=0,0,Q48-P48) -> 1372.3501 | S48: =IFERROR(Q48/P48,"0%") -> 1.0341363 | U48: =IF(D48=0,0,SUM($L$20:L48)) -> 40202.092 | V48: =IF(D48=0,0,SUM($J$20:J48)) -> 41574.443 | W48: =IF(D48=0,0,V48-U48) -> 1372.3501 | X48: =IFERROR(V48/U48,"0%") -> 1.0341363 | Z48: =Z47+1 -> 45320 | AA48: =AA47+1 -> 45320 | AB48: 45320 | AC48: 5 | AD48: 月 | AE48: =AVERAGEIFS(J141:J171,D141:D171,1,G141:G171,"mon") -> 2162.4977 | AF48: =COUNTIFS(D141:D171,1,G141:G171,"Mon") -> 3 | AH48: =AE48*AF48 -> 6487.4932 | AI48: =AH48/$M$10 -> 0.11611173 | AJ48: =SUM(AI48:AI54) -> 1 | AK48: 141〜171 | AS48: =AS47+1 -> 45320
C49: =C48+1 -> 30 | D49: 1 | E49: =TEXT(AA49,"m") -> 1 | F49: =F48+1 -> 45321 | G49: =TEXT(AS49,"ddd") -> Tue | J49: =188550/$B$13 -> 1708.8091 | L49: =IF(D49=0,0,$K$6) -> 2010.1046 | M49: =IF(D49=0,0,J49-L49) -> -301.29549 | N49: =IFERROR(J49/L49,"0%") -> 0.85010955 | P49: =IF(D49=0,0,SUM($L$20:L49)) -> 42212.197 | Q49: =IF(D49=0,0,SUM($J$20:J49)) -> 43283.252 | R49: =IF(D49=0,0,Q49-P49) -> 1071.0546 | S49: =IFERROR(Q49/P49,"0%") -> 1.0253731 | U49: =IF(D49=0,0,SUM($L$20:L49)) -> 42212.197 | V49: =IF(D49=0,0,SUM($J$20:J49)) -> 43283.252 | W49: =IF(D49=0,0,V49-U49) -> 1071.0546 | X49: =IFERROR(V49/U49,"0%") -> 1.0253731 | Z49: =Z48+1 -> 45321 | AA49: =AA48+1 -> 45321 | AB49: 45321 | AC49: 5 | AD49: 火 | AE49: =AVERAGEIFS(J141:J171,D141:D171,1,G141:G171,"tue") -> 2102.6939 | AF49: =COUNTIFS(D141:D171,1,G141:G171,"tue") -> 4 | AH49: =AE49*AF49 -> 8410.7758 | AI49: =AH49/$M$10 -> 0.15053422 | AS49: =AS48+1 -> 45321
C50: =C49+1 -> 31 | D50: 1 | E50: =TEXT(AA50,"m") -> 1 | F50: =F49+1 -> 45322 | G50: =TEXT(AS50,"ddd") -> Wed | J50: =206500/$B$13 -> 1871.4881 | L50: =IF(D50=0,0,$K$6) -> 2010.1046 | M50: =IF(D50=0,0,J50-L50) -> -138.6165 | N50: =IFERROR(J50/L50,"0%") -> 0.93104016 | P50: =IF(D50=0,0,SUM($L$20:L50)) -> 44222.302 | Q50: =IF(D50=0,0,SUM($J$20:J50)) -> 45154.74 | R50: =IF(D50=0,0,Q50-P50) -> 932.43815 | S50: =IFERROR(Q50/P50,"0%") -> 1.0210852 | U50: =IF(D50=0,0,SUM($L$20:L50)) -> 44222.302 | V50: =IF(D50=0,0,SUM($J$20:J50)) -> 45154.74 | W50: =IF(D50=0,0,V50-U50) -> 932.43815 | X50: =IFERROR(V50/U50,"0%") -> 1.0210852 | Z50: =Z49+1 -> 45322 | AA50: =AA49+1 -> 45322 | AB50: 45322 | AC50: 5 | AD50: 水 | AE50: =AVERAGEIFS(J141:J171,D141:D171,1,G141:G171,"wed") -> 2907.0781 | AF50: =COUNTIFS(D141:D171,1,G141:G171,"wed") -> 5 | AH50: =AE50*AF50 -> 14535.391 | AI50: =AH50/$M$10 -> 0.26015124 | AS50: =AS49+1 -> 45322
C51: =C50+1 -> 32 | D51: 1 | E51: =TEXT(AA51,"m") -> 2 | F51: =F50+1 -> 45323 | G51: =TEXT(AS51,"ddd") -> Thu | J51: =218090/$B$13 -> 1976.5271 | L51: =IF(D51=0,0,$K$7) -> 1898.4321 | M51: =IF(D51=0,0,J51-L51) -> 78.094952 | N51: =IFERROR(J51/L51,"0%") -> 1.0411366 | P51: =IF(D51=0,0,$L$51) -> 1898.4321 | Q51: =IF(D51=0,0,$J$51) -> 1976.5271 | R51: =IF(D51=0,0,Q51-P51) -> 78.094952 | S51: =IFERROR(Q51/P51,"0%") -> 1.0411366 | U51: =IF(D51=0,0,SUM($L$20:L51)) -> 46120.734 | V51: =IF(D51=0,0,SUM($J$20:J51)) -> 47131.267 | W51: =IF(D51=0,0,V51-U51) -> 1010.5331 | X51: =IFERROR(V51/U51,"0%") -> 1.0219106 | Z51: =Z50+1 -> 45323 | AA51: =AA50+1 -> 45323 | AB51: 45323 | AC51: 5 | AD51: 木 | AE51: =AVERAGEIFS(J141:J171,D141:D171,1,G141:G171,"thu") -> 1997.6255 | AF51: =COUNTIFS(D141:D171,1,G141:G171,"thu") -> 5 | AH51: =AE51*AF51 -> 9988.1276 | AI51: =AH51/$M$10 -> 0.17876532 | AS51: =AS50+1 -> 45323
C52: =C51+1 -> 33 | D52: 1 | E52: =TEXT(AA52,"m") -> 2 | F52: =F51+1 -> 45324 | G52: =TEXT(AS52,"ddd") -> Fri | J52: =236480/$B$13 -> 2143.1938 | L52: =IF(D52=0,0,$K$7) -> 1898.4321 | M52: =IF(D52=0,0,J52-L52) -> 244.76162 | N52: =IFERROR(J52/L52,"0%") -> 1.1289283 | P52: =IF(D52=0,0,SUM($L$51:L52)) -> 3796.8643 | Q52: =IF(D52=0,0,SUM($J$51:J52)) -> 4119.7209 | R52: =IF(D52=0,0,Q52-P52) -> 322.85657 | S52: =IFERROR(Q52/P52,"0%") -> 1.0850324 | U52: =IF(D52=0,0,SUM($L$20:L52)) -> 48019.166 | V52: =IF(D52=0,0,SUM($J$20:J52)) -> 49274.461 | W52: =IF(D52=0,0,V52-U52) -> 1255.2947 | X52: =IFERROR(V52/U52,"0%") -> 1.0261415 | Z52: =Z51+1 -> 45324 | AA52: =AA51+1 -> 45324 | AB52: 45324 | AC52: 5 | AD52: 金 | AE52: =AVERAGEIFS(J141:J171,D141:D171,1,G141:G171,"fri") -> 3172.1271 | AF52: =COUNTIFS(D141:D171,1,G141:G171,"fri") -> 4 | AH52: =AE52*AF52 -> 12688.508 | AI52: =AH52/$M$10 -> 0.22709614 | AS52: =AS51+1 -> 45324
C53: =C52+1 -> 34 | D53: 1 | E53: =TEXT(AA53,"m") -> 2 | F53: =F52+1 -> 45325 | G53: =TEXT(AS53,"ddd") -> Sat | J53: =113750/$B$13 -> 1030.9045 | L53: =IF(D53=0,0,$K$7) -> 1898.4321 | M53: =IF(D53=0,0,J53-L53) -> -867.52767 | N53: =IFERROR(J53/L53,"0%") -> 0.5430294 | P53: =IF(D53=0,0,SUM($L$51:L53)) -> 5695.2964 | Q53: =IF(D53=0,0,SUM($J$51:J53)) -> 5150.6253 | R53: =IF(D53=0,0,Q53-P53) -> -544.6711 | S53: =IFERROR(Q53/P53,"0%") -> 0.90436475 | U53: =IF(D53=0,0,SUM($L$20:L53)) -> 49917.598 | V53: =IF(D53=0,0,SUM($J$20:J53)) -> 50305.365 | W53: =IF(D53=0,0,V53-U53) -> 387.76705 | X53: =IFERROR(V53/U53,"0%") -> 1.0077681 | Z53: =Z52+1 -> 45325 | AA53: =AA52+1 -> 45325 | AB53: 45325 | AC53: 5 | AD53: 土 | AE53: =AVERAGEIFS(J141:J171,D141:D171,1,G141:G171,"sat") -> 1254.184 | AF53: =COUNTIFS(D141:D171,1,G141:G171,"sat") -> 3 | AH53: =AE53*AF53 -> 3762.5521 | AI53: =AH53/$M$10 -> 0.067341334 | AS53: =AS52+1 -> 45325
C54: =C53+1 -> 35 | D54: 0 | E54: =TEXT(AA54,"m") -> 2 | F54: =F53+1 -> 45326 | G54: =TEXT(AS54,"ddd") -> Sun | H54: 日曜日 | L54: =IF(D54=0,0,$K$7) -> 0 | M54: =IF(D54=0,0,J54-L54) -> 0 | N54: =IFERROR(J54/L54,"0%") -> 0% | P54: =IF(D54=0,0,SUM($L$51:L54)) -> 0 | Q54: =IF(D54=0,0,SUM($J$51:J54)) -> 0 | R54: =IF(D54=0,0,Q54-P54) -> 0 | S54: =IFERROR(Q54/P54,"0%") -> 0% | U54: =IF(D54=0,0,SUM($L$20:L54)) -> 0 | V54: =IF(D54=0,0,SUM($J$20:J54)) -> 0 | W54: =IF(D54=0,0,V54-U54) -> 0 | X54: =IFERROR(V54/U54,"0%") -> 0% | Z54: =Z53+1 -> 45326 | AA54: =AA53+1 -> 45326 | AB54: 45326 | AC54: 5 | AD54: 日 | AE54: =IFERROR(AVERAGEIFS(J141:J171,D141:D171,1,G141:G171,"sun"),0) -> 0 | AF54: =IFERROR(COUNTIFS(D141:D171,1,G141:G171,"sun"),0) -> 0 | AH54: =AE54*AF54 -> 0 | AI54: =AH54/$M$10 -> 0 | AS54: =AS53+1 -> 45326
C55: =C54+1 -> 36 | D55: 1 | E55: =TEXT(AA55,"m") -> 2 | F55: =F54+1 -> 45327 | G55: =TEXT(AS55,"ddd") -> Mon | J55: =155200/$B$13 -> 1406.5615 | L55: =IF(D55=0,0,$K$7) -> 1898.4321 | M55: =IF(D55=0,0,J55-L55) -> -491.87061 | N55: =IFERROR(J55/L55,"0%") -> 0.74090693 | P55: =IF(D55=0,0,SUM($L$51:L55)) -> 7593.7286 | Q55: =IF(D55=0,0,SUM($J$51:J55)) -> 6557.1869 | R55: =IF(D55=0,0,Q55-P55) -> -1036.5417 | S55: =IFERROR(Q55/P55,"0%") -> 0.8635003 | U55: =IF(D55=0,0,SUM($L$20:L55)) -> 51816.03 | V55: =IF(D55=0,0,SUM($J$20:J55)) -> 51711.927 | W55: =IF(D55=0,0,V55-U55) -> -104.10355 | X55: =IFERROR(V55/U55,"0%") -> 0.9979909 | Z55: =Z54+1 -> 45327 | AA55: =AA54+1 -> 45327 | AB55: 45327 | AC55: 6 | AD55: 月 | AE55: =AVERAGEIFS(J172:J201,D172:D201,1,G172:G201,"mon") -> 1742.3872 | AF55: =COUNTIFS(D172:D201,1,G172:G201,"Mon") -> 4 | AH55: =AE55*AF55 -> 6969.5487 | AI55: =AH55/$M$11 -> 0.13016698 | AJ55: =SUM(AI55:AI61) -> 1 | AK55: 172〜201 | AS55: =AS54+1 -> 45327
C56: =C55+1 -> 37 | D56: 1 | E56: =TEXT(AA56,"m") -> 2 | F56: =F55+1 -> 45328 | G56: =TEXT(AS56,"ddd") -> Tue | J56: =191910/$B$13 -> 1739.2605 | L56: =IF(D56=0,0,$K$7) -> 1898.4321 | M56: =IF(D56=0,0,J56-L56) -> -159.17168 | N56: =IFERROR(J56/L56,"0%") -> 0.91615625 | P56: =IF(D56=0,0,SUM($L$51:L56)) -> 9492.1607 | Q56: =IF(D56=0,0,SUM($J$51:J56)) -> 8296.4473 | R56: =IF(D56=0,0,Q56-P56) -> -1195.7134 | S56: =IFERROR(Q56/P56,"0%") -> 0.87403149 | U56: =IF(D56=0,0,SUM($L$20:L56)) -> 53714.462 | V56: =IF(D56=0,0,SUM($J$20:J56)) -> 53451.187 | W56: =IF(D56=0,0,V56-U56) -> -263.27523 | X56: =IFERROR(V56/U56,"0%") -> 0.99509862 | Z56: =Z55+1 -> 45328 | AA56: =AA55+1 -> 45328 | AB56: 45328 | AC56: 6 | AD56: 火 | AE56: =AVERAGEIFS(J172:J201,D172:D201,1,G172:G201,"tue") -> 1855.2882 | AF56: =COUNTIFS(D172:D201,1,G172:G201,"tue") -> 4 | AH56: =AE56*AF56 -> 7421.1528 | AI56: =AH56/$M$11 -> 0.13860138 | AS56: =AS55+1 -> 45328
C57: =C56+1 -> 38 | D57: 1 | E57: =TEXT(AA57,"m") -> 2 | F57: =F56+1 -> 45329 | G57: =TEXT(AS57,"ddd") -> Wed | J57: =331350/$B$13 -> 3002.9908 | L57: =IF(D57=0,0,$K$7) -> 1898.4321 | M57: =IF(D57=0,0,J57-L57) -> 1104.5586 | N57: =IFERROR(J57/L57,"0%") -> 1.5818268 | P57: =IF(D57=0,0,SUM($L$51:L57)) -> 11390.593 | Q57: =IF(D57=0,0,SUM($J$51:J57)) -> 11299.438 | R57: =IF(D57=0,0,Q57-P57) -> -91.154773 | S57: =IFERROR(Q57/P57,"0%") -> 0.99199736 | U57: =IF(D57=0,0,SUM($L$20:L57)) -> 55612.895 | V57: =IF(D57=0,0,SUM($J$20:J57)) -> 56454.178 | W57: =IF(D57=0,0,V57-U57) -> 841.28338 | X57: =IFERROR(V57/U57,"0%") -> 1.0151275 | Z57: =Z56+1 -> 45329 | AA57: =AA56+1 -> 45329 | AB57: 45329 | AC57: 6 | AD57: 水 | AE57: =AVERAGEIFS(J172:J201,D172:D201,1,G172:G201,"wed") -> 2795.0653 | AF57: =COUNTIFS(D172:D201,1,G172:G201,"wed") -> 4 | AH57: =AE57*AF57 -> 11180.261 | AI57: =AH57/$M$11 -> 0.20880847 | AS57: =AS56+1 -> 45329
C58: =C57+1 -> 39 | D58: 1 | E58: =TEXT(AA58,"m") -> 2 | F58: =F57+1 -> 45330 | G58: =TEXT(AS58,"ddd") -> Thu | J58: =178550/$B$13 -> 1618.1802 | L58: =IF(D58=0,0,$K$7) -> 1898.4321 | M58: =IF(D58=0,0,J58-L58) -> -280.25198 | N58: =IFERROR(J58/L58,"0%") -> 0.85237714 | P58: =IF(D58=0,0,SUM($L$51:L58)) -> 13289.025 | Q58: =IF(D58=0,0,SUM($J$51:J58)) -> 12917.618 | R58: =IF(D58=0,0,Q58-P58) -> -371.40675 | S58: =IFERROR(Q58/P58,"0%") -> 0.97205162 | U58: =IF(D58=0,0,SUM($L$20:L58)) -> 57511.327 | V58: =IF(D58=0,0,SUM($J$20:J58)) -> 58072.358 | W58: =IF(D58=0,0,V58-U58) -> 561.0314 | X58: =IFERROR(V58/U58,"0%") -> 1.0097551 | Z58: =Z57+1 -> 45330 | AA58: =AA57+1 -> 45330 | AB58: 45330 | AC58: 6 | AD58: 木 | AE58: =AVERAGEIFS(J172:J201,D172:D201,1,G172:G201,"thu") -> 2532.8077 | AF58: =COUNTIFS(D172:D201,1,G172:G201,"thu") -> 4 | AH58: =AE58*AF58 -> 10131.231 | AI58: =AH58/$M$11 -> 0.18921623 | AS58: =AS57+1 -> 45330
C59: =C58+1 -> 40 | D59: 1 | E59: =TEXT(AA59,"m") -> 2 | F59: =F58+1 -> 45331 | G59: =TEXT(AS59,"ddd") -> Fri | J59: =291050/$B$13 -> 2637.756 | L59: =IF(D59=0,0,$K$7) -> 1898.4321 | M59: =IF(D59=0,0,J59-L59) -> 739.32388 | N59: =IFERROR(J59/L59,"0%") -> 1.3894392 | P59: =IF(D59=0,0,SUM($L$51:L59)) -> 15187.457 | Q59: =IF(D59=0,0,SUM($J$51:J59)) -> 15555.374 | R59: =IF(D59=0,0,Q59-P59) -> 367.91713 | S59: =IFERROR(Q59/P59,"0%") -> 1.0242251 | U59: =IF(D59=0,0,SUM($L$20:L59)) -> 59409.759 | V59: =IF(D59=0,0,SUM($J$20:J59)) -> 60710.114 | W59: =IF(D59=0,0,V59-U59) -> 1300.3553 | X59: =IFERROR(V59/U59,"0%") -> 1.0218879 | Z59: =Z58+1 -> 45331 | AA59: =AA58+1 -> 45331 | AB59: 45331 | AC59: 6 | AD59: 金 | AE59: =AVERAGEIFS(J172:J201,D172:D201,1,G172:G201,"fri") -> 2925.0272 | AF59: =COUNTIFS(D172:D201,1,G172:G201,"fri") -> 4 | AH59: =AE59*AF59 -> 11700.109 | AI59: =AH59/$M$11 -> 0.21851742 | AS59: =AS58+1 -> 45331
C60: =C59+1 -> 41 | D60: 1 | E60: =TEXT(AA60,"m") -> 2 | F60: =F59+1 -> 45332 | G60: =TEXT(AS60,"ddd") -> Sat | J60: =222220/$B$13 -> 2013.9569 | L60: =IF(D60=0,0,$K$7) -> 1898.4321 | M60: =IF(D60=0,0,J60-L60) -> 115.52472 | N60: =IFERROR(J60/L60,"0%") -> 1.0608527 | P60: =IF(D60=0,0,SUM($L$51:L60)) -> 17085.889 | Q60: =IF(D60=0,0,SUM($J$51:J60)) -> 17569.331 | R60: =IF(D60=0,0,Q60-P60) -> 483.44185 | S60: =IFERROR(Q60/P60,"0%") -> 1.0282948 | U60: =IF(D60=0,0,SUM($L$20:L60)) -> 61308.191 | V60: =IF(D60=0,0,SUM($J$20:J60)) -> 62724.071 | W60: =IF(D60=0,0,V60-U60) -> 1415.88 | X60: =IFERROR(V60/U60,"0%") -> 1.0230945 | Z60: =Z59+1 -> 45332 | AA60: =AA59+1 -> 45332 | AB60: 45332 | AC60: 6 | AD60: 土 | AE60: =AVERAGEIFS(J172:J201,D172:D201,1,G172:G201,"sat") -> 1228.1675 | AF60: =COUNTIFS(D172:D201,1,G172:G201,"sat") -> 5 | AH60: =AE60*AF60 -> 6140.8374 | AI60: =AH60/$M$11 -> 0.11468953 | AS60: =AS59+1 -> 45332
C61: =C60+1 -> 42 | D61: 0 | E61: =TEXT(AA61,"m") -> 2 | F61: =F60+1 -> 45333 | G61: =TEXT(AS61,"ddd") -> Sun | H61: 日曜日 | L61: =IF(D61=0,0,$K$7) -> 0 | M61: =IF(D61=0,0,J61-L61) -> 0 | N61: =IFERROR(J61/L61,"0%") -> 0% | P61: =IF(D61=0,0,SUM($L$51:L61)) -> 0 | Q61: =IF(D61=0,0,SUM($J$51:J61)) -> 0 | R61: =IF(D61=0,0,Q61-P61) -> 0 | S61: =IFERROR(Q61/P61,"0%") -> 0% | U61: =IF(D61=0,0,SUM($L$20:L61)) -> 0 | V61: =IF(D61=0,0,SUM($J$20:J61)) -> 0 | W61: =IF(D61=0,0,V61-U61) -> 0 | X61: =IFERROR(V61/U61,"0%") -> 0% | Z61: =Z60+1 -> 45333 | AA61: =AA60+1 -> 45333 | AB61: 45333 | AC61: 6 | AD61: 日 | AE61: =IFERROR(AVERAGEIFS(J172:J201,D172:D201,1,G172:G201,"sun"),0) -> 0 | AF61: =IFERROR(COUNTIFS(D172:D201,1,G172:G201,"sun"),0) -> 0 | AH61: =AE61*AF61 -> 0 | AI61: =AH61/$M$11 -> 0 | AS61: =AS60+1 -> 45333
C62: =C61+1 -> 43 | D62: 0 | E62: =TEXT(AA62,"m") -> 2 | F62: =F61+1 -> 45334 | G62: =TEXT(AS62,"ddd") -> Mon | H62: 祝日 | L62: =IF(D62=0,0,$K$7) -> 0 | M62: =IF(D62=0,0,J62-L62) -> 0 | N62: =IFERROR(J62/L62,"0%") -> 0% | P62: =IF(D62=0,0,SUM($L$51:L62)) -> 0 | Q62: =IF(D62=0,0,SUM($J$51:J62)) -> 0 | R62: =IF(D62=0,0,Q62-P62) -> 0 | S62: =IFERROR(Q62/P62,"0%") -> 0% | U62: =IF(D62=0,0,SUM($L$20:L62)) -> 0 | V62: =IF(D62=0,0,SUM($J$20:J62)) -> 0 | W62: =IF(D62=0,0,V62-U62) -> 0 | X62: =IFERROR(V62/U62,"0%") -> 0% | Z62: =Z61+1 -> 45334 | AA62: =AA61+1 -> 45334 | AB62: 45334 | AC62: 7 | AD62: 月 | AE62: =AVERAGEIFS(J202:J232,D202:D232,1,G202:G232,"mon") -> 2238.5808 | AF62: =COUNTIFS(D202:D232,1,G202:G232,"Mon") -> 4 | AH62: =AE62*AF62 -> 8954.323 | AI62: =AH62/$M$12 -> 0.15148604 | AJ62: =SUM(AI62:AI68) -> 1 | AK62: 202〜232 | AS62: =AS61+1 -> 45334
C63: =C62+1 -> 44 | D63: 1 | E63: =TEXT(AA63,"m") -> 2 | F63: =F62+1 -> 45335 | G63: =TEXT(AS63,"ddd") -> Tue | J63: =138350/$B$13 -> 1253.8517 | L63: =IF(D63=0,0,$K$7) -> 1898.4321 | M63: =IF(D63=0,0,J63-L63) -> -644.58041 | N63: =IFERROR(J63/L63,"0%") -> 0.66046697 | P63: =IF(D63=0,0,SUM($L$51:L63)) -> 18984.321 | Q63: =IF(D63=0,0,SUM($J$51:J63)) -> 18823.183 | R63: =IF(D63=0,0,Q63-P63) -> -161.13857 | S63: =IFERROR(Q63/P63,"0%") -> 0.99151202 | U63: =IF(D63=0,0,SUM($L$20:L63)) -> 63206.623 | V63: =IF(D63=0,0,SUM($J$20:J63)) -> 63977.923 | W63: =IF(D63=0,0,V63-U63) -> 771.29958 | X63: =IFERROR(V63/U63,"0%") -> 1.0122028 | Z63: =Z62+1 -> 45335 | AA63: =AA62+1 -> 45335 | AB63: 45335 | AC63: 7 | AD63: 火 | AE63: =AVERAGEIFS(J202:J232,D202:D232,1,G202:G232,"tue") -> 1687.0401 | AF63: =COUNTIFS(D202:D232,1,G202:G232,"tue") -> 5 | AH63: =AE63*AF63 -> 8435.2003 | AI63: =AH63/$M$12 -> 0.14270371 | AS63: =AS62+1 -> 45335
C64: =C63+1 -> 45 | D64: 1 | E64: =TEXT(AA64,"m") -> 2 | F64: =F63+1 -> 45336 | G64: =TEXT(AS64,"ddd") -> Wed | J64: =185750/$B$13 -> 1683.433 | L64: =IF(D64=0,0,$K$7) -> 1898.4321 | M64: =IF(D64=0,0,J64-L64) -> -214.99912 | N64: =IFERROR(J64/L64,"0%") -> 0.88674912 | P64: =IF(D64=0,0,SUM($L$51:L64)) -> 20882.754 | Q64: =IF(D64=0,0,SUM($J$51:J64)) -> 20506.616 | R64: =IF(D64=0,0,Q64-P64) -> -376.13769 | S64: =IFERROR(Q64/P64,"0%") -> 0.98198812 | U64: =IF(D64=0,0,SUM($L$20:L64)) -> 65105.055 | V64: =IF(D64=0,0,SUM($J$20:J64)) -> 65661.356 | W64: =IF(D64=0,0,V64-U64) -> 556.30046 | X64: =IFERROR(V64/U64,"0%") -> 1.0085447 | Z64: =Z63+1 -> 45336 | AA64: =AA63+1 -> 45336 | AB64: 45336 | AC64: 7 | AD64: 水 | AE64: =AVERAGEIFS(J202:J232,D202:D232,1,G202:G232,"wed") -> 2444.9157 | AF64: =COUNTIFS(D202:D232,1,G202:G232,"wed") -> 5 | AH64: =AE64*AF64 -> 12224.579 | AI64: =AH64/$M$12 -> 0.20681106 | AS64: =AS63+1 -> 45336
C65: =C64+1 -> 46 | D65: 1 | E65: =TEXT(AA65,"m") -> 2 | F65: =F64+1 -> 45337 | G65: =TEXT(AS65,"ddd") -> Thu | J65: =270370/$B$13 -> 2450.3353 | L65: =IF(D65=0,0,$K$7) -> 1898.4321 | M65: =IF(D65=0,0,J65-L65) -> 551.90318 | N65: =IFERROR(J65/L65,"0%") -> 1.2907153 | P65: =IF(D65=0,0,SUM($L$51:L65)) -> 22781.186 | Q65: =IF(D65=0,0,SUM($J$51:J65)) -> 22956.951 | R65: =IF(D65=0,0,Q65-P65) -> 175.76549 | S65: =IFERROR(Q65/P65,"0%") -> 1.0077154 | U65: =IF(D65=0,0,SUM($L$20:L65)) -> 67003.487 | V65: =IF(D65=0,0,SUM($J$20:J65)) -> 68111.691 | W65: =IF(D65=0,0,V65-U65) -> 1108.2036 | X65: =IFERROR(V65/U65,"0%") -> 1.0165395 | Z65: =Z64+1 -> 45337 | AA65: =AA64+1 -> 45337 | AB65: 45337 | AC65: 7 | AD65: 木 | AE65: =AVERAGEIFS(J202:J232,D202:D232,1,G202:G232,"thu") -> 2739.555 | AF65: =COUNTIFS(D202:D232,1,G202:G232,"thu") -> 4 | AH65: =AE65*AF65 -> 10958.22 | AI65: =AH65/$M$12 -> 0.18538726 | AS65: =AS64+1 -> 45337
C66: =C65+1 -> 47 | D66: 1 | E66: =TEXT(AA66,"m") -> 2 | F66: =F65+1 -> 45338 | G66: =TEXT(AS66,"ddd") -> Fri | J66: =324150/$B$13 -> 2937.7379 | L66: =IF(D66=0,0,$K$7) -> 1898.4321 | M66: =IF(D66=0,0,J66-L66) -> 1039.3058 | N66: =IFERROR(J66/L66,"0%") -> 1.5474548 | P66: =IF(D66=0,0,SUM($L$51:L66)) -> 24679.618 | Q66: =IF(D66=0,0,SUM($J$51:J66)) -> 25894.689 | R66: =IF(D66=0,0,Q66-P66) -> 1215.0713 | S66: =IFERROR(Q66/P66,"0%") -> 1.0492338 | U66: =IF(D66=0,0,SUM($L$20:L66)) -> 68901.92 | V66: =IF(D66=0,0,SUM($J$20:J66)) -> 71049.429 | W66: =IF(D66=0,0,V66-U66) -> 2147.5094 | X66: =IFERROR(V66/U66,"0%") -> 1.0311676 | Z66: =Z65+1 -> 45338 | AA66: =AA65+1 -> 45338 | AB66: 45338 | AC66: 7 | AD66: 金 | AE66: =AVERAGEIFS(J202:J232,D202:D232,1,G202:G232,"fri") -> 3287.679 | AF66: =COUNTIFS(D202:D232,1,G202:G232,"fri") -> 4 | AH66: =AE66*AF66 -> 13150.716 | AI66: =AH66/$M$12 -> 0.22247912 | AS66: =AS65+1 -> 45338
C67: =C66+1 -> 48 | D67: 1 | E67: =TEXT(AA67,"m") -> 2 | F67: =F66+1 -> 45339 | G67: =TEXT(AS67,"ddd") -> Sat | J67: =136800/$B$13 -> 1239.8042 | L67: =IF(D67=0,0,$K$7) -> 1898.4321 | M67: =IF(D67=0,0,J67-L67) -> -658.6279 | N67: =IFERROR(J67/L67,"0%") -> 0.65306745 | P67: =IF(D67=0,0,SUM($L$51:L67)) -> 26578.05 | Q67: =IF(D67=0,0,SUM($J$51:J67)) -> 27134.493 | R67: =IF(D67=0,0,Q67-P67) -> 556.44335 | S67: =IFERROR(Q67/P67,"0%") -> 1.0209362 | U67: =IF(D67=0,0,SUM($L$20:L67)) -> 70800.352 | V67: =IF(D67=0,0,SUM($J$20:J67)) -> 72289.233 | W67: =IF(D67=0,0,V67-U67) -> 1488.8815 | X67: =IFERROR(V67/U67,"0%") -> 1.0210293 | Z67: =Z66+1 -> 45339 | AA67: =AA66+1 -> 45339 | AB67: 45339 | AC67: 7 | AD67: 土 | AE67: =AVERAGEIFS(J202:J232,D202:D232,1,G202:G232,"sat") -> 1346.7124 | AF67: =COUNTIFS(D202:D232,1,G202:G232,"sat") -> 4 | AH67: =AE67*AF67 -> 5386.8497 | AI67: =AH67/$M$12 -> 0.091132803 | AS67: =AS66+1 -> 45339
C68: =C67+1 -> 49 | D68: 0 | E68: =TEXT(AA68,"m") -> 2 | F68: =F67+1 -> 45340 | G68: =TEXT(AS68,"ddd") -> Sun | H68: 日曜日 | L68: =IF(D68=0,0,$K$7) -> 0 | M68: =IF(D68=0,0,J68-L68) -> 0 | N68: =IFERROR(J68/L68,"0%") -> 0% | P68: =IF(D68=0,0,SUM($L$51:L68)) -> 0 | Q68: =IF(D68=0,0,SUM($J$51:J68)) -> 0 | R68: =IF(D68=0,0,Q68-P68) -> 0 | S68: =IFERROR(Q68/P68,"0%") -> 0% | U68: =IF(D68=0,0,SUM($L$20:L68)) -> 0 | V68: =IF(D68=0,0,SUM($J$20:J68)) -> 0 | W68: =IF(D68=0,0,V68-U68) -> 0 | X68: =IFERROR(V68/U68,"0%") -> 0% | Z68: =Z67+1 -> 45340 | AA68: =AA67+1 -> 45340 | AB68: 45340 | AC68: 7 | AD68: 日 | AE68: =IFERROR(AVERAGEIFS(J202:J232,D202:D232,1,G202:G232,"sun"),0) -> 0 | AF68: =IFERROR(COUNTIFS(D202:D232,1,G202:G232,"sun"),0) -> 0 | AH68: =AE68*AF68 -> 0 | AI68: =AH68/$M$12 -> 0 | AS68: =AS67+1 -> 45340
C69: =C68+1 -> 50 | D69: 1 | E69: =TEXT(AA69,"m") -> 2 | F69: =F68+1 -> 45341 | G69: =TEXT(AS69,"ddd") -> Mon | J69: =285600/$B$13 -> 2588.3632 | L69: =IF(D69=0,0,$K$7) -> 1898.4321 | M69: =IF(D69=0,0,J69-L69) -> 689.9311 | N69: =IFERROR(J69/L69,"0%") -> 1.3634215 | P69: =IF(D69=0,0,SUM($L$51:L69)) -> 28476.482 | Q69: =IF(D69=0,0,SUM($J$51:J69)) -> 29722.857 | R69: =IF(D69=0,0,Q69-P69) -> 1246.3744 | S69: =IFERROR(Q69/P69,"0%") -> 1.0437686 | U69: =IF(D69=0,0,SUM($L$20:L69)) -> 72698.784 | V69: =IF(D69=0,0,SUM($J$20:J69)) -> 74877.597 | W69: =IF(D69=0,0,V69-U69) -> 2178.8126 | X69: =IFERROR(V69/U69,"0%") -> 1.0299704 | Z69: =Z68+1 -> 45341 | AA69: =AA68+1 -> 45341 | AB69: 45341 | AC69: 8 | AD69: 月 | AE69: =AVERAGEIFS(J233:J263,D233:D263,1,G233:G263,"mon") -> 1695.0637 | AF69: =COUNTIFS(D233:D263,1,G233:G263,"Mon") -> 3 | AH69: =AE69*AF69 -> 5085.1912 | AI69: =AH69/$M$13 -> 0.12435721 | AJ69: =SUM(AI69:AI75) -> 1 | AK69: 233〜263 | AS69: =AS68+1 -> 45341
C70: =C69+1 -> 51 | D70: 1 | E70: =TEXT(AA70,"m") -> 2 | F70: =F69+1 -> 45342 | G70: =TEXT(AS70,"ddd") -> Tue | J70: =316820/$B$13 -> 2871.3069 | L70: =IF(D70=0,0,$K$7) -> 1898.4321 | M70: =IF(D70=0,0,J70-L70) -> 972.87472 | N70: =IFERROR(J70/L70,"0%") -> 1.5124622 | P70: =IF(D70=0,0,SUM($L$51:L70)) -> 30374.914 | Q70: =IF(D70=0,0,SUM($J$51:J70)) -> 32594.163 | R70: =IF(D70=0,0,Q70-P70) -> 2219.2492 | S70: =IFERROR(Q70/P70,"0%") -> 1.0730619 | U70: =IF(D70=0,0,SUM($L$20:L70)) -> 74597.216 | V70: =IF(D70=0,0,SUM($J$20:J70)) -> 77748.903 | W70: =IF(D70=0,0,V70-U70) -> 3151.6873 | X70: =IFERROR(V70/U70,"0%") -> 1.0422494 | Z70: =Z69+1 -> 45342 | AA70: =AA69+1 -> 45342 | AB70: 45342 | AC70: 8 | AD70: 火 | AE70: =AVERAGEIFS(J233:J263,D233:D263,1,G233:G263,"tue") -> 1421.5153 | AF70: =COUNTIFS(D233:D263,1,G233:G263,"tue") -> 3 | AH70: =AE70*AF70 -> 4264.5459 | AI70: =AH70/$M$13 -> 0.10428852 | AS70: =AS69+1 -> 45342
C71: =C70+1 -> 52 | D71: 1 | E71: =TEXT(AA71,"m") -> 2 | F71: =F70+1 -> 45343 | G71: =TEXT(AS71,"ddd") -> Wed | J71: =135300/$B$13 -> 1226.2099 | L71: =IF(D71=0,0,$K$7) -> 1898.4321 | M71: =IF(D71=0,0,J71-L71) -> -672.22225 | N71: =IFERROR(J71/L71,"0%") -> 0.64590662 | P71: =IF(D71=0,0,SUM($L$51:L71)) -> 32273.346 | Q71: =IF(D71=0,0,SUM($J$51:J71)) -> 33820.373 | R71: =IF(D71=0,0,Q71-P71) -> 1547.0269 | S71: =IFERROR(Q71/P71,"0%") -> 1.0479351 | U71: =IF(D71=0,0,SUM($L$20:L71)) -> 76495.648 | V71: =IF(D71=0,0,SUM($J$20:J71)) -> 78975.113 | W71: =IF(D71=0,0,V71-U71) -> 2479.4651 | X71: =IFERROR(V71/U71,"0%") -> 1.0324132 | Z71: =Z70+1 -> 45343 | AA71: =AA70+1 -> 45343 | AB71: 45343 | AC71: 8 | AD71: 水 | AE71: =AVERAGEIFS(J233:J263,D233:D263,1,G233:G263,"wed") -> 2664.7302 | AF71: =COUNTIFS(D233:D263,1,G233:G263,"wed") -> 3 | AH71: =AE71*AF71 -> 7994.1907 | AI71: =AH71/$M$13 -> 0.19549615 | AS71: =AS70+1 -> 45343
C72: =C71+1 -> 53 | D72: 1 | E72: =TEXT(AA72,"m") -> 2 | F72: =F71+1 -> 45344 | G72: =TEXT(AS72,"ddd") -> Thu | J72: =331320/$B$13 -> 3002.7189 | L72: =IF(D72=0,0,$K$7) -> 1898.4321 | M72: =IF(D72=0,0,J72-L72) -> 1104.2867 | N72: =IFERROR(J72/L72,"0%") -> 1.5816835 | P72: =IF(D72=0,0,SUM($L$51:L72)) -> 34171.779 | Q72: =IF(D72=0,0,SUM($J$51:J72)) -> 36823.092 | R72: =IF(D72=0,0,Q72-P72) -> 2651.3136 | S72: =IFERROR(Q72/P72,"0%") -> 1.0775878 | U72: =IF(D72=0,0,SUM($L$20:L72)) -> 78394.08 | V72: =IF(D72=0,0,SUM($J$20:J72)) -> 81977.832 | W72: =IF(D72=0,0,V72-U72) -> 3583.7518 | X72: =IFERROR(V72/U72,"0%") -> 1.0457146 | Z72: =Z71+1 -> 45344 | AA72: =AA71+1 -> 45344 | AB72: 45344 | AC72: 8 | AD72: 木 | AE72: =AVERAGEIFS(J233:J263,D233:D263,1,G233:G263,"thu") -> 1862.6813 | AF72: =COUNTIFS(D233:D263,1,G233:G263,"thu") -> 4 | AH72: =AE72*AF72 -> 7450.725 | AI72: =AH72/$M$13 -> 0.18220581 | AS72: =AS71+1 -> 45344
C73: =C72+1 -> 54 | D73: 0 | E73: =TEXT(AA73,"m") -> 2 | F73: =F72+1 -> 45345 | G73: =TEXT(AS73,"ddd") -> Fri | H73: 祝日 | L73: =IF(D73=0,0,$K$7) -> 0 | M73: =IF(D73=0,0,J73-L73) -> 0 | N73: =IFERROR(J73/L73,"0%") -> 0% | P73: =IF(D73=0,0,SUM($L$51:L73)) -> 0 | Q73: =IF(D73=0,0,SUM($J$51:J73)) -> 0 | R73: =IF(D73=0,0,Q73-P73) -> 0 | S73: =IFERROR(Q73/P73,"0%") -> 0% | U73: =IF(D73=0,0,SUM($L$20:L73)) -> 0 | V73: =IF(D73=0,0,SUM($J$20:J73)) -> 0 | W73: =IF(D73=0,0,V73-U73) -> 0 | X73: =IFERROR(V73/U73,"0%") -> 0% | Z73: =Z72+1 -> 45345 | AA73: =AA72+1 -> 45345 | AB73: 45345 | AC73: 8 | AD73: 金 | AE73: =AVERAGEIFS(J233:J263,D233:D263,1,G233:G263,"fri") -> 2605.8546 | AF73: =COUNTIFS(D233:D263,1,G233:G263,"fri") -> 4 | AH73: =AE73*AF73 -> 10423.419 | AI73: =AH73/$M$13 -> 0.25490237 | AS73: =AS72+1 -> 45345
C74: =C73+1 -> 55 | D74: 1 | E74: =TEXT(AA74,"m") -> 2 | F74: =F73+1 -> 45346 | G74: =TEXT(AS74,"ddd") -> Sat | J74: =72800/$B$13 -> 659.77887 | L74: =IF(D74=0,0,$K$7) -> 1898.4321 | M74: =IF(D74=0,0,J74-L74) -> -1238.6533 | N74: =IFERROR(J74/L74,"0%") -> 0.34753882 | P74: =IF(D74=0,0,SUM($L$51:L74)) -> 36070.211 | Q74: =IF(D74=0,0,SUM($J$51:J74)) -> 37482.871 | R74: =IF(D74=0,0,Q74-P74) -> 1412.6604 | S74: =IFERROR(Q74/P74,"0%") -> 1.0391642 | U74: =IF(D74=0,0,SUM($L$20:L74)) -> 80292.513 | V74: =IF(D74=0,0,SUM($J$20:J74)) -> 82637.611 | W74: =IF(D74=0,0,V74-U74) -> 2345.0985 | X74: =IFERROR(V74/U74,"0%") -> 1.0292069 | Z74: =Z73+1 -> 45346 | AA74: =AA73+1 -> 45346 | AB74: 45346 | AC74: 8 | AD74: 土 | AE74: =AVERAGEIFS(J233:J263,D233:D263,1,G233:G263,"sat") -> 1134.7471 | AF74: =COUNTIFS(D233:D263,1,G233:G263,"sat") -> 5 | AH74: =AE74*AF74 -> 5673.7357 | AI74: =AH74/$M$13 -> 0.13874994 | AS74: =AS73+1 -> 45346
C75: =C74+1 -> 56 | D75: 0 | E75: =TEXT(AA75,"m") -> 2 | F75: =F74+1 -> 45347 | G75: =TEXT(AS75,"ddd") -> Sun | H75: 日曜日 | L75: =IF(D75=0,0,$K$7) -> 0 | M75: =IF(D75=0,0,J75-L75) -> 0 | N75: =IFERROR(J75/L75,"0%") -> 0% | P75: =IF(D75=0,0,SUM($L$51:L75)) -> 0 | Q75: =IF(D75=0,0,SUM($J$51:J75)) -> 0 | R75: =IF(D75=0,0,Q75-P75) -> 0 | S75: =IFERROR(Q75/P75,"0%") -> 0% | U75: =IF(D75=0,0,SUM($L$20:L75)) -> 0 | V75: =IF(D75=0,0,SUM($J$20:J75)) -> 0 | W75: =IF(D75=0,0,V75-U75) -> 0 | X75: =IFERROR(V75/U75,"0%") -> 0% | Z75: =Z74+1 -> 45347 | AA75: =AA74+1 -> 45347 | AB75: 45347 | AC75: 8 | AD75: 日 | AE75: =IFERROR(AVERAGEIFS(J233:J263,D233:D263,1,G233:G263,"sun"),0) -> 0 | AF75: =IFERROR(COUNTIFS(D233:D263,1,G233:G263,"sun"),0) -> 0 | AH75: =AE75*AF75 -> 0 | AI75: =AH75/$M$13 -> 0 | AS75: =AS74+1 -> 45347
C76: =C75+1 -> 57 | D76: 1 | E76: =TEXT(AA76,"m") -> 2 | F76: =F75+1 -> 45348 | G76: =TEXT(AS76,"ddd") -> Mon | J76: =252950/$B$13 -> 2292.4597 | L76: =IF(D76=0,0,$K$7) -> 1898.4321 | M76: =IF(D76=0,0,J76-L76) -> 394.02752 | N76: =IFERROR(J76/L76,"0%") -> 1.2075542 | P76: =IF(D76=0,0,SUM($L$51:L76)) -> 37968.643 | Q76: =IF(D76=0,0,SUM($J$51:J76)) -> 39775.331 | R76: =IF(D76=0,0,Q76-P76) -> 1806.6879 | S76: =IFERROR(Q76/P76,"0%") -> 1.0475837 | U76: =IF(D76=0,0,SUM($L$20:L76)) -> 82190.945 | V76: =IF(D76=0,0,SUM($J$20:J76)) -> 84930.071 | W76: =IF(D76=0,0,V76-U76) -> 2739.126 | X76: =IFERROR(V76/U76,"0%") -> 1.0333264 | Z76: =Z75+1 -> 45348 | AA76: =AA75+1 -> 45348 | AB76: 45348 | AC76: 9 | AD76: 月 | AE76: =AVERAGEIFS(J264:J293,D264:D293,1,G264:G293,"mon") -> 2143.375 | AF76: =COUNTIFS(D264:D293,1,G264:G293,"Mon") -> 3 | AH76: =AE76*AF76 -> 6430.1251 | AI76: =AH76/$M$14 -> 0.1307816 | AJ76: =SUM(AI76:AI82) -> 1 | AK76: 264〜293 | AS76: =AS75+1 -> 45348
C77: =C76+1 -> 58 | D77: 1 | E77: =TEXT(AA77,"m") -> 2 | F77: =F76+1 -> 45349 | G77: =TEXT(AS77,"ddd") -> Tue | J77: =209900/$B$13 -> 1902.302 | L77: =IF(D77=0,0,$K$7) -> 1898.4321 | M77: =IF(D77=0,0,J77-L77) -> 3.8698302 | N77: =IFERROR(J77/L77,"0%") -> 1.0020384 | P77: =IF(D77=0,0,SUM($L$51:L77)) -> 39867.075 | Q77: =IF(D77=0,0,SUM($J$51:J77)) -> 41677.633 | R77: =IF(D77=0,0,Q77-P77) -> 1810.5577 | S77: =IFERROR(Q77/P77,"0%") -> 1.0454149 | U77: =IF(D77=0,0,SUM($L$20:L77)) -> 84089.377 | V77: =IF(D77=0,0,SUM($J$20:J77)) -> 86832.373 | W77: =IF(D77=0,0,V77-U77) -> 2742.9959 | X77: =IFERROR(V77/U77,"0%") -> 1.03262 | Z77: =Z76+1 -> 45349 | AA77: =AA76+1 -> 45349 | AB77: 45349 | AC77: 9 | AD77: 火 | AE77: =AVERAGEIFS(J264:J293,D264:D293,1,G264:G293,"tue") -> 2658.0569 | AF77: =COUNTIFS(D264:D293,1,G264:G293,"tue") -> 4 | AH77: =AE77*AF77 -> 10632.228 | AI77: =AH77/$M$14 -> 0.2162477 | AS77: =AS76+1 -> 45349
C78: =C77+1 -> 59 | D78: 1 | E78: =TEXT(AA78,"m") -> 2 | F78: =F77+1 -> 45350 | G78: =TEXT(AS78,"ddd") -> Wed | J78: =234470/$B$13 -> 2124.9773 | L78: =IF(D78=0,0,$K$7) -> 1898.4321 | M78: =IF(D78=0,0,J78-L78) -> 226.5452 | N78: =IFERROR(J78/L78,"0%") -> 1.1193328 | P78: =IF(D78=0,0,SUM($L$51:L78)) -> 41765.507 | Q78: =IF(D78=0,0,SUM($J$51:J78)) -> 43802.61 | R78: =IF(D78=0,0,Q78-P78) -> 2037.1029 | S78: =IFERROR(Q78/P78,"0%") -> 1.0487748 | U78: =IF(D78=0,0,SUM($L$20:L78)) -> 85987.809 | V78: =IF(D78=0,0,SUM($J$20:J78)) -> 88957.35 | W78: =IF(D78=0,0,V78-U78) -> 2969.5411 | X78: =IFERROR(V78/U78,"0%") -> 1.0345344 | Z78: =Z77+1 -> 45350 | AA78: =AA77+1 -> 45350 | AB78: 45350 | AC78: 9 | AD78: 水 | AE78: =AVERAGEIFS(J264:J293,D264:D293,1,G264:G293,"wed") -> 1792.8448 | AF78: =COUNTIFS(D264:D293,1,G264:G293,"wed") -> 4 | AH78: =AE78*AF78 -> 7171.3794 | AI78: =AH78/$M$14 -> 0.14585789 | AS78: =AS77+1 -> 45350
C79: =C78+1 -> 60 | D79: 1 | E79: =TEXT(AA79,"m") -> 2 | F79: =F78+1 -> 45351 | G79: =TEXT(AS79,"ddd") -> Thu | J79: =168650/$B$13 -> 1528.4575 | L79: =IF(D79=0,0,$K$7) -> 1898.4321 | M79: =IF(D79=0,0,J79-L79) -> -369.97465 | N79: =IFERROR(J79/L79,"0%") -> 0.80511568 | P79: =IF(D79=0,0,SUM($L$51:L79)) -> 43663.939 | Q79: =IF(D79=0,0,SUM($J$51:J79)) -> 45331.068 | R79: =IF(D79=0,0,Q79-P79) -> 1667.1283 | S79: =IFERROR(Q79/P79,"0%") -> 1.0381809 | U79: =IF(D79=0,0,SUM($L$20:L79)) -> 87886.241 | V79: =IF(D79=0,0,SUM($J$20:J79)) -> 90485.808 | W79: =IF(D79=0,0,V79-U79) -> 2599.5664 | X79: =IFERROR(V79/U79,"0%") -> 1.0295788 | Z79: =Z78+1 -> 45351 | AA79: =AA78+1 -> 45351 | AB79: 45351 | AC79: 9 | AD79: 木 | AE79: =AVERAGEIFS(J264:J293,D264:D293,1,G264:G293,"thu") -> 2020.7314 | AF79: =COUNTIFS(D264:D293,1,G264:G293,"thu") -> 4 | AH79: =AE79*AF79 -> 8082.9255 | AI79: =AH79/$M$14 -> 0.16439773 | AS79: =AS78+1 -> 45351
C80: =C79+1 -> 61 | D80: 1 | E80: =TEXT(AA80,"m") -> 3 | F80: =F79+1 -> 45352 | G80: =TEXT(AS80,"ddd") -> Fri | J80: =305050/$B$13 -> 2764.6366 | L80: =IF(D80=0,0,$K$8) -> 2233.4496 | M80: =IF(D80=0,0,J80-L80) -> 531.18699 | N80: =IFERROR(J80/L80,"0%") -> 1.2378325 | P80: =IF(D80=0,0,$L$80) -> 2233.4496 | Q80: =IF(D80=0,0,$J$80) -> 2764.6366 | R80: =IF(D80=0,0,Q80-P80) -> 531.18699 | S80: =IFERROR(Q80/P80,"0%") -> 1.2378325 | U80: =IF(D80=0,0,SUM($L$20:L80)) -> 90119.691 | V80: =IF(D80=0,0,SUM($J$20:J80)) -> 93250.444 | W80: =IF(D80=0,0,V80-U80) -> 3130.7534 | X80: =IFERROR(V80/U80,"0%") -> 1.0347399 | Z80: =Z79+1 -> 45352 | AA80: =AA79+1 -> 45352 | AB80: 45352 | AC80: 9 | AD80: 金 | AE80: =AVERAGEIFS(J264:J293,D264:D293,1,G264:G293,"fri") -> 3002.0052 | AF80: =COUNTIFS(D264:D293,1,G264:G293,"fri") -> 4 | AH80: =AE80*AF80 -> 12008.021 | AI80: =AH80/$M$14 -> 0.2442298 | AS80: =AS79+1 -> 45352
C81: =C80+1 -> 62 | D81: 1 | E81: =TEXT(AA81,"m") -> 3 | F81: =F80+1 -> 45353 | G81: =TEXT(AS81,"ddd") -> Sat | J81: =148490/$B$13 -> 1345.7495 | L81: =IF(D81=0,0,$K$8) -> 2233.4496 | M81: =IF(D81=0,0,J81-L81) -> -887.70008 | N81: =IFERROR(J81/L81,"0%") -> 0.60254304 | P81: =IF(D81=0,0,SUM($L$80:L81)) -> 4466.8992 | Q81: =IF(D81=0,0,SUM($J$80:J81)) -> 4110.3861 | R81: =IF(D81=0,0,Q81-P81) -> -356.51309 | S81: =IFERROR(Q81/P81,"0%") -> 0.92018779 | U81: =IF(D81=0,0,SUM($L$20:L81)) -> 92353.14 | V81: =IF(D81=0,0,SUM($J$20:J81)) -> 94596.194 | W81: =IF(D81=0,0,V81-U81) -> 2243.0533 | X81: =IFERROR(V81/U81,"0%") -> 1.0242878 | Z81: =Z80+1 -> 45353 | AA81: =AA80+1 -> 45353 | AB81: 45353 | AC81: 9 | AD81: 土 | AE81: =AVERAGEIFS(J264:J293,D264:D293,1,G264:G293,"sat") -> 1210.5537 | AF81: =COUNTIFS(D264:D293,1,G264:G293,"sat") -> 4 | AH81: =AE81*AF81 -> 4842.215 | AI81: =AH81/$M$14 -> 0.098485274 | AS81: =AS80+1 -> 45353
C82: =C81+1 -> 63 | D82: 0 | E82: =TEXT(AA82,"m") -> 3 | F82: =F81+1 -> 45354 | G82: =TEXT(AS82,"ddd") -> Sun | H82: 日曜日 | L82: =IF(D82=0,0,$K$8) -> 0 | M82: =IF(D82=0,0,J82-L82) -> 0 | N82: =IFERROR(J82/L82,"0%") -> 0% | P82: =IF(D82=0,0,SUM($L$80:L82)) -> 0 | Q82: =IF(D82=0,0,SUM($J$80:J82)) -> 0 | R82: =IF(D82=0,0,Q82-P82) -> 0 | S82: =IFERROR(Q82/P82,"0%") -> 0% | U82: =IF(D82=0,0,SUM($L$20:L82)) -> 0 | V82: =IF(D82=0,0,SUM($J$20:J82)) -> 0 | W82: =IF(D82=0,0,V82-U82) -> 0 | X82: =IFERROR(V82/U82,"0%") -> 0% | Z82: =Z81+1 -> 45354 | AA82: =AA81+1 -> 45354 | AB82: 45354 | AC82: 9 | AD82: 日 | AE82: =IFERROR(AVERAGEIFS(J264:J293,D264:D293,1,G264:G293,"sun"),0) -> 0 | AF82: =IFERROR(COUNTIFS(D264:D293,1,G264:G293,"sun"),0) -> 0 | AH82: =AE82*AF82 -> 0 | AI82: =AH82/$M$14 -> 0 | AS82: =AS81+1 -> 45354
C83: =C82+1 -> 64 | D83: 1 | E83: =TEXT(AA83,"m") -> 3 | F83: =F82+1 -> 45355 | G83: =TEXT(AS83,"ddd") -> Mon | J83: =166560/$B$13 -> 1509.516 | L83: =IF(D83=0,0,$K$8) -> 2233.4496 | M83: =IF(D83=0,0,J83-L83) -> -723.93354 | N83: =IFERROR(J83/L83,"0%") -> 0.67586752 | P83: =IF(D83=0,0,SUM($L$80:L83)) -> 6700.3487 | Q83: =IF(D83=0,0,SUM($J$80:J83)) -> 5619.9021 | R83: =IF(D83=0,0,Q83-P83) -> -1080.4466 | S83: =IFERROR(Q83/P83,"0%") -> 0.8387477 | U83: =IF(D83=0,0,SUM($L$20:L83)) -> 94586.59 | V83: =IF(D83=0,0,SUM($J$20:J83)) -> 96105.71 | W83: =IF(D83=0,0,V83-U83) -> 1519.1198 | X83: =IFERROR(V83/U83,"0%") -> 1.0160606 | Z83: =Z82+1 -> 45355 | AA83: =AA82+1 -> 45355 | AB83: 45355 | AC83: 10 | AD83: 月 | AE83: =AVERAGEIFS(J294:J324,D294:D324,1,G294:G324,"mon") -> 2126.9108 | AF83: =COUNTIFS(D294:D324,1,G294:G324,"Mon") -> 3 | AH83: =AE83*AF83 -> 6380.7323 | AI83: =AH83/$M$15 -> 0.12672958 | AJ83: =SUM(AI83:AI89) -> 1 | AK83: 294〜324 | AS83: =AS82+1 -> 45355
C84: =C83+1 -> 65 | D84: 1 | E84: =TEXT(AA84,"m") -> 3 | F84: =F83+1 -> 45356 | G84: =TEXT(AS84,"ddd") -> Tue | J84: =292350/$B$13 -> 2649.5378 | L84: =IF(D84=0,0,$K$8) -> 2233.4496 | M84: =IF(D84=0,0,J84-L84) -> 416.08821 | N84: =IFERROR(J84/L84,"0%") -> 1.1862985 | P84: =IF(D84=0,0,SUM($L$80:L84)) -> 8933.7983 | Q84: =IF(D84=0,0,SUM($J$80:J84)) -> 8269.4399 | R84: =IF(D84=0,0,Q84-P84) -> -664.35842 | S84: =IFERROR(Q84/P84,"0%") -> 0.92563539 | U84: =IF(D84=0,0,SUM($L$20:L84)) -> 96820.039 | V84: =IF(D84=0,0,SUM($J$20:J84)) -> 98755.247 | W84: =IF(D84=0,0,V84-U84) -> 1935.208 | X84: =IFERROR(V84/U84,"0%") -> 1.0199877 | Z84: =Z83+1 -> 45356 | AA84: =AA83+1 -> 45356 | AB84: 45356 | AC84: 10 | AD84: 火 | AE84: =AVERAGEIFS(J294:J324,D294:D324,1,G294:G324,"tue") -> 1794.0004 | AF84: =COUNTIFS(D294:D324,1,G294:G324,"tue") -> 5 | AH84: =AE84*AF84 -> 8970.0018 | AI84: =AH84/$M$15 -> 0.17815582 | AS84: =AS83+1 -> 45356
C85: =C84+1 -> 66 | D85: 1 | E85: =TEXT(AA85,"m") -> 3 | F85: =F84+1 -> 45357 | G85: =TEXT(AS85,"ddd") -> Wed | J85: =145450/$B$13 -> 1318.1983 | L85: =IF(D85=0,0,$K$8) -> 2233.4496 | M85: =IF(D85=0,0,J85-L85) -> -915.25129 | N85: =IFERROR(J85/L85,"0%") -> 0.59020732 | P85: =IF(D85=0,0,SUM($L$80:L85)) -> 11167.248 | Q85: =IF(D85=0,0,SUM($J$80:J85)) -> 9587.6382 | R85: =IF(D85=0,0,Q85-P85) -> -1579.6097 | S85: =IFERROR(Q85/P85,"0%") -> 0.85854978 | U85: =IF(D85=0,0,SUM($L$20:L85)) -> 99053.489 | V85: =IF(D85=0,0,SUM($J$20:J85)) -> 100073.45 | W85: =IF(D85=0,0,V85-U85) -> 1019.9567 | X85: =IFERROR(V85/U85,"0%") -> 1.010297 | Z85: =Z84+1 -> 45357 | AA85: =AA84+1 -> 45357 | AB85: 45357 | AC85: 10 | AD85: 水 | AE85: =AVERAGEIFS(J294:J324,D294:D324,1,G294:G324,"wed") -> 1935.3453 | AF85: =COUNTIFS(D294:D324,1,G294:G324,"wed") -> 5 | AH85: =AE85*AF85 -> 9676.7265 | AI85: =AH85/$M$15 -> 0.19219228 | AS85: =AS84+1 -> 45357
C86: =C85+1 -> 67 | D86: 1 | E86: =TEXT(AA86,"m") -> 3 | F86: =F85+1 -> 45358 | G86: =TEXT(AS86,"ddd") -> Thu | J86: =317890/$B$13 -> 2881.0042 | L86: =IF(D86=0,0,$K$8) -> 2233.4496 | M86: =IF(D86=0,0,J86-L86) -> 647.55459 | N86: =IFERROR(J86/L86,"0%") -> 1.2899347 | P86: =IF(D86=0,0,SUM($L$80:L86)) -> 13400.697 | Q86: =IF(D86=0,0,SUM($J$80:J86)) -> 12468.642 | R86: =IF(D86=0,0,Q86-P86) -> -932.05512 | S86: =IFERROR(Q86/P86,"0%") -> 0.93044727 | U86: =IF(D86=0,0,SUM($L$20:L86)) -> 101286.94 | V86: =IF(D86=0,0,SUM($J$20:J86)) -> 102954.45 | W86: =IF(D86=0,0,V86-U86) -> 1667.5113 | X86: =IFERROR(V86/U86,"0%") -> 1.0164632 | Z86: =Z85+1 -> 45358 | AA86: =AA85+1 -> 45358 | AB86: 45358 | AC86: 10 | AD86: 木 | AE86: =AVERAGEIFS(J294:J324,D294:D324,1,G294:G324,"thu") -> 2256.8425 | AF86: =COUNTIFS(D294:D324,1,G294:G324,"thu") -> 5 | AH86: =AE86*AF86 -> 11284.212 | AI86: =AH86/$M$15 -> 0.22411903 | AS86: =AS85+1 -> 45358
C87: =C86+1 -> 68 | D87: 1 | E87: =TEXT(AA87,"m") -> 3 | F87: =F86+1 -> 45359 | G87: =TEXT(AS87,"ddd") -> Fri | J87: =266360/$B$13 -> 2413.9931 | L87: =IF(D87=0,0,$K$8) -> 2233.4496 | M87: =IF(D87=0,0,J87-L87) -> 180.54353 | N87: =IFERROR(J87/L87,"0%") -> 1.0808362 | P87: =IF(D87=0,0,SUM($L$80:L87)) -> 15634.147 | Q87: =IF(D87=0,0,SUM($J$80:J87)) -> 14882.635 | R87: =IF(D87=0,0,Q87-P87) -> -751.51159 | S87: =IFERROR(Q87/P87,"0%") -> 0.9519314 | U87: =IF(D87=0,0,SUM($L$20:L87)) -> 103520.39 | V87: =IF(D87=0,0,SUM($J$20:J87)) -> 105368.44 | W87: =IF(D87=0,0,V87-U87) -> 1848.0548 | X87: =IFERROR(V87/U87,"0%") -> 1.0178521 | Z87: =Z86+1 -> 45359 | AA87: =AA86+1 -> 45359 | AB87: 45359 | AC87: 10 | AD87: 金 | AE87: =AVERAGEIFS(J294:J324,D294:D324,1,G294:G324,"fri") -> 2274.1753 | AF87: =COUNTIFS(D294:D324,1,G294:G324,"fri") -> 4 | AH87: =AE87*AF87 -> 9096.7011 | AI87: =AH87/$M$15 -> 0.18067223 | AS87: =AS86+1 -> 45359
C88: =C87+1 -> 69 | D88: 1 | E88: =TEXT(AA88,"m") -> 3 | F88: =F87+1 -> 45360 | G88: =TEXT(AS88,"ddd") -> Sat | J88: =118114/$B$13 -> 1070.455 | L88: =IF(D88=0,0,$K$8) -> 2233.4496 | M88: =IF(D88=0,0,J88-L88) -> -1162.9946 | N88: =IFERROR(J88/L88,"0%") -> 0.47928324 | P88: =IF(D88=0,0,SUM($L$80:L88)) -> 17867.597 | Q88: =IF(D88=0,0,SUM($J$80:J88)) -> 15953.09 | R88: =IF(D88=0,0,Q88-P88) -> -1914.5062 | S88: =IFERROR(Q88/P88,"0%") -> 0.89285038 | U88: =IF(D88=0,0,SUM($L$20:L88)) -> 105753.84 | V88: =IF(D88=0,0,SUM($J$20:J88)) -> 106438.9 | W88: =IF(D88=0,0,V88-U88) -> 685.0602 | X88: =IFERROR(V88/U88,"0%") -> 1.0064779 | Z88: =Z87+1 -> 45360 | AA88: =AA87+1 -> 45360 | AB88: 45360 | AC88: 10 | AD88: 土 | AE88: =AVERAGEIFS(J294:J324,D294:D324,1,G294:G324,"sat") -> 1235.2048 | AF88: =COUNTIFS(D294:D324,1,G294:G324,"sat") -> 4 | AH88: =AE88*AF88 -> 4940.8193 | AI88: =AH88/$M$15 -> 0.098131051 | AS88: =AS87+1 -> 45360
C89: =C88+1 -> 70 | D89: 0 | E89: =TEXT(AA89,"m") -> 3 | F89: =F88+1 -> 45361 | G89: =TEXT(AS89,"ddd") -> Sun | H89: 日曜日 | L89: =IF(D89=0,0,$K$8) -> 0 | M89: =IF(D89=0,0,J89-L89) -> 0 | N89: =IFERROR(J89/L89,"0%") -> 0% | P89: =IF(D89=0,0,SUM($L$80:L89)) -> 0 | Q89: =IF(D89=0,0,SUM($J$80:J89)) -> 0 | R89: =IF(D89=0,0,Q89-P89) -> 0 | S89: =IFERROR(Q89/P89,"0%") -> 0% | U89: =IF(D89=0,0,SUM($L$20:L89)) -> 0 | V89: =IF(D89=0,0,SUM($J$20:J89)) -> 0 | W89: =IF(D89=0,0,V89-U89) -> 0 | X89: =IFERROR(V89/U89,"0%") -> 0% | Z89: =Z88+1 -> 45361 | AA89: =AA88+1 -> 45361 | AB89: 45361 | AC89: 10 | AD89: 日 | AE89: =IFERROR(AVERAGEIFS(J294:J324,D294:D324,1,G294:G324,"sun"),0) -> 0 | AF89: =IFERROR(COUNTIFS(D294:D324,1,G294:G324,"sun"),0) -> 0 | AH89: =AE89*AF89 -> 0 | AI89: =AH89/$M$15 -> 0 | AS89: =AS88+1 -> 45361
C90: =C89+1 -> 71 | D90: 1 | E90: =TEXT(AA90,"m") -> 3 | F90: =F89+1 -> 45362 | G90: =TEXT(AS90,"ddd") -> Mon | J90: =315600/$B$13 -> 2860.2501 | L90: =IF(D90=0,0,$K$8) -> 2233.4496 | M90: =IF(D90=0,0,J90-L90) -> 626.80055 | N90: =IFERROR(J90/L90,"0%") -> 1.2806424 | P90: =IF(D90=0,0,SUM($L$80:L90)) -> 20101.046 | Q90: =IF(D90=0,0,SUM($J$80:J90)) -> 18813.341 | R90: =IF(D90=0,0,Q90-P90) -> -1287.7057 | S90: =IFERROR(Q90/P90,"0%") -> 0.93593838 | U90: =IF(D90=0,0,SUM($L$20:L90)) -> 107987.29 | V90: =IF(D90=0,0,SUM($J$20:J90)) -> 109299.15 | W90: =IF(D90=0,0,V90-U90) -> 1311.8607 | X90: =IFERROR(V90/U90,"0%") -> 1.0121483 | Z90: =Z89+1 -> 45362 | AA90: =AA89+1 -> 45362 | AB90: 45362 | AC90: 11 | AD90: 月 | AE90: =AVERAGEIFS(J325:J354,D325:D354,1,G325:G354,"mon") -> 1597.9397 | AF90: =COUNTIFS(D325:D354,1,G325:G354,"Mon") -> 3 | AH90: =AE90*AF90 -> 4793.8191 | AI90: =AH90/$M$16 -> 0.086540743 | AJ90: =SUM(AI90:AI96) -> 1 | AK90: 325〜354 | AS90: =AS89+1 -> 45362
C91: =C90+1 -> 72 | D91: 1 | E91: =TEXT(AA91,"m") -> 3 | F91: =F90+1 -> 45363 | G91: =TEXT(AS91,"ddd") -> Tue | J91: =320300/$B$13 -> 2902.8457 | L91: =IF(D91=0,0,$K$8) -> 2233.4496 | M91: =IF(D91=0,0,J91-L91) -> 669.39617 | N91: =IFERROR(J91/L91,"0%") -> 1.299714 | P91: =IF(D91=0,0,SUM($L$80:L91)) -> 22334.496 | Q91: =IF(D91=0,0,SUM($J$80:J91)) -> 21716.186 | R91: =IF(D91=0,0,Q91-P91) -> -618.3095 | S91: =IFERROR(Q91/P91,"0%") -> 0.97231594 | U91: =IF(D91=0,0,SUM($L$20:L91)) -> 110220.74 | V91: =IF(D91=0,0,SUM($J$20:J91)) -> 112201.99 | W91: =IF(D91=0,0,V91-U91) -> 1981.2569 | X91: =IFERROR(V91/U91,"0%") -> 1.0179754 | Z91: =Z90+1 -> 45363 | AA91: =AA90+1 -> 45363 | AB91: 45363 | AC91: 11 | AD91: 火 | AE91: =AVERAGEIFS(J325:J354,D325:D354,1,G325:G354,"tue") -> 2098.6496 | AF91: =COUNTIFS(D325:D354,1,G325:G354,"tue") -> 4 | AH91: =AE91*AF91 -> 8394.5985 | AI91: =AH91/$M$16 -> 0.15154406 | AS91: =AS90+1 -> 45363
C92: =C91+1 -> 73 | D92: 1 | E92: =TEXT(AA92,"m") -> 3 | F92: =F91+1 -> 45364 | G92: =TEXT(AS92,"ddd") -> Wed | J92: =318550/$B$13 -> 2886.9857 | L92: =IF(D92=0,0,$K$8) -> 2233.4496 | M92: =IF(D92=0,0,J92-L92) -> 653.5361 | N92: =IFERROR(J92/L92,"0%") -> 1.2926129 | P92: =IF(D92=0,0,SUM($L$80:L92)) -> 24567.945 | Q92: =IF(D92=0,0,SUM($J$80:J92)) -> 24603.172 | R92: =IF(D92=0,0,Q92-P92) -> 35.226601 | S92: =IFERROR(Q92/P92,"0%") -> 1.0014338 | U92: =IF(D92=0,0,SUM($L$20:L92)) -> 112454.19 | V92: =IF(D92=0,0,SUM($J$20:J92)) -> 115088.98 | W92: =IF(D92=0,0,V92-U92) -> 2634.793 | X92: =IFERROR(V92/U92,"0%") -> 1.0234299 | Z92: =Z91+1 -> 45364 | AA92: =AA91+1 -> 45364 | AB92: 45364 | AC92: 11 | AD92: 水 | AE92: =AVERAGEIFS(J325:J354,D325:D354,1,G325:G354,"wed") -> 2419.816 | AF92: =COUNTIFS(D325:D354,1,G325:G354,"wed") -> 4 | AH92: =AE92*AF92 -> 9679.2641 | AI92: =AH92/$M$16 -> 0.17473557 | AS92: =AS91+1 -> 45364
C93: =C92+1 -> 74 | D93: 1 | E93: =TEXT(AA93,"m") -> 3 | F93: =F92+1 -> 45365 | G93: =TEXT(AS93,"ddd") -> Thu | J93: =219880/$B$13 -> 1992.7497 | L93: =IF(D93=0,0,$K$8) -> 2233.4496 | M93: =IF(D93=0,0,J93-L93) -> -240.6999 | N93: =IFERROR(J93/L93,"0%") -> 0.89222953 | P93: =IF(D93=0,0,SUM($L$80:L93)) -> 26801.395 | Q93: =IF(D93=0,0,SUM($J$80:J93)) -> 26595.922 | R93: =IF(D93=0,0,Q93-P93) -> -205.4733 | S93: =IFERROR(Q93/P93,"0%") -> 0.99233348 | U93: =IF(D93=0,0,SUM($L$20:L93)) -> 114687.64 | V93: =IF(D93=0,0,SUM($J$20:J93)) -> 117081.73 | W93: =IF(D93=0,0,V93-U93) -> 2394.0931 | X93: =IFERROR(V93/U93,"0%") -> 1.0208749 | Z93: =Z92+1 -> 45365 | AA93: =AA92+1 -> 45365 | AB93: 45365 | AC93: 11 | AD93: 木 | AE93: =AVERAGEIFS(J325:J354,D325:D354,1,G325:G354,"thu") -> 2357.282 | AF93: =COUNTIFS(D325:D354,1,G325:G354,"thu") -> 4 | AH93: =AE93*AF93 -> 9429.1281 | AI93: =AH93/$M$16 -> 0.17021997 | AS93: =AS92+1 -> 45365
C94: =C93+1 -> 75 | D94: 1 | E94: =TEXT(AA94,"m") -> 3 | F94: =F93+1 -> 45366 | G94: =TEXT(AS94,"ddd") -> Fri | J94: =350170/$B$13 -> 3173.5545 | L94: =IF(D94=0,0,$K$8) -> 2233.4496 | M94: =IF(D94=0,0,J94-L94) -> 940.10488 | N94: =IFERROR(J94/L94,"0%") -> 1.4209206 | P94: =IF(D94=0,0,SUM($L$80:L94)) -> 29034.845 | Q94: =IF(D94=0,0,SUM($J$80:J94)) -> 29769.476 | R94: =IF(D94=0,0,Q94-P94) -> 734.63159 | S94: =IFERROR(Q94/P94,"0%") -> 1.0253017 | U94: =IF(D94=0,0,SUM($L$20:L94)) -> 116921.09 | V94: =IF(D94=0,0,SUM($J$20:J94)) -> 120255.28 | W94: =IF(D94=0,0,V94-U94) -> 3334.198 | X94: =IFERROR(V94/U94,"0%") -> 1.0285167 | Z94: =Z93+1 -> 45366 | AA94: =AA93+1 -> 45366 | AB94: 45366 | AC94: 11 | AD94: 金 | AE94: =AVERAGEIFS(J325:J354,D325:D354,1,G325:G354,"fri") -> 3018.9052 | AF94: =COUNTIFS(D325:D354,1,G325:G354,"fri") -> 5 | AH94: =AE94*AF94 -> 15094.526 | AI94: =AH94/$M$16 -> 0.27249495 | AS94: =AS93+1 -> 45366
C95: =C94+1 -> 76 | D95: 1 | E95: =TEXT(AA95,"m") -> 3 | F95: =F94+1 -> 45367 | G95: =TEXT(AS95,"ddd") -> Sat | J95: =156750/$B$13 -> 1420.609 | L95: =IF(D95=0,0,$K$8) -> 2233.4496 | M95: =IF(D95=0,0,J95-L95) -> -812.84056 | N95: =IFERROR(J95/L95,"0%") -> 0.63606049 | P95: =IF(D95=0,0,SUM($L$80:L95)) -> 31268.294 | Q95: =IF(D95=0,0,SUM($J$80:J95)) -> 31190.085 | R95: =IF(D95=0,0,Q95-P95) -> -78.208971 | S95: =IFERROR(Q95/P95,"0%") -> 0.99749878 | U95: =IF(D95=0,0,SUM($L$20:L95)) -> 119154.54 | V95: =IF(D95=0,0,SUM($J$20:J95)) -> 121675.89 | W95: =IF(D95=0,0,V95-U95) -> 2521.3574 | X95: =IFERROR(V95/U95,"0%") -> 1.0211604 | Z95: =Z94+1 -> 45367 | AA95: =AA94+1 -> 45367 | AB95: 45367 | AC95: 11 | AD95: 土 | AE95: =AVERAGEIFS(J325:J354,D325:D354,1,G325:G354,"sat") -> 2000.6117 | AF95: =COUNTIFS(D325:D354,1,G325:G354,"sat") -> 4 | AH95: =AE95*AF95 -> 8002.447 | AI95: =AH95/$M$16 -> 0.14446471 | AS95: =AS94+1 -> 45367
C96: =C95+1 -> 77 | D96: 0 | E96: =TEXT(AA96,"m") -> 3 | F96: =F95+1 -> 45368 | G96: =TEXT(AS96,"ddd") -> Sun | H96: 日曜日 | L96: =IF(D96=0,0,$K$8) -> 0 | M96: =IF(D96=0,0,J96-L96) -> 0 | N96: =IFERROR(J96/L96,"0%") -> 0% | P96: =IF(D96=0,0,SUM($L$80:L96)) -> 0 | Q96: =IF(D96=0,0,SUM($J$80:J96)) -> 0 | R96: =IF(D96=0,0,Q96-P96) -> 0 | S96: =IFERROR(Q96/P96,"0%") -> 0% | U96: =IF(D96=0,0,SUM($L$20:L96)) -> 0 | V96: =IF(D96=0,0,SUM($J$20:J96)) -> 0 | W96: =IF(D96=0,0,V96-U96) -> 0 | X96: =IFERROR(V96/U96,"0%") -> 0% | Z96: =Z95+1 -> 45368 | AA96: =AA95+1 -> 45368 | AB96: 45368 | AC96: 11 | AD96: 日 | AE96: =IFERROR(AVERAGEIFS(J325:J354,D325:D354,1,G325:G354,"sun"),0) -> 0 | AF96: =IFERROR(COUNTIFS(D325:D354,1,G325:G354,"sun"),0) -> 0 | AH96: =AE96*AF96 -> 0 | AI96: =AH96/$M$16 -> 0 | AS96: =AS95+1 -> 45368
C97: =C96+1 -> 78 | D97: 1 | E97: =TEXT(AA97,"m") -> 3 | F97: =F96+1 -> 45369 | G97: =TEXT(AS97,"ddd") -> Mon | J97: =201050/$B$13 -> 1822.0953 | L97: =IF(D97=0,0,$K$8) -> 2233.4496 | M97: =IF(D97=0,0,J97-L97) -> -411.35424 | N97: =IFERROR(J97/L97,"0%") -> 0.81582112 | P97: =IF(D97=0,0,SUM($L$80:L97)) -> 33501.744 | Q97: =IF(D97=0,0,SUM($J$80:J97)) -> 33012.181 | R97: =IF(D97=0,0,Q97-P97) -> -489.56321 | S97: =IFERROR(Q97/P97,"0%") -> 0.98538693 | U97: =IF(D97=0,0,SUM($L$20:L97)) -> 121387.98 | V97: =IF(D97=0,0,SUM($J$20:J97)) -> 123497.99 | W97: =IF(D97=0,0,V97-U97) -> 2110.0032 | X97: =IFERROR(V97/U97,"0%") -> 1.0173823 | Z97: =Z96+1 -> 45369 | AA97: =AA96+1 -> 45369 | AB97: 45369 | AC97: 12 | AD97: 月 | AE97: =AVERAGEIFS(J355:J385,D355:D385,1,G355:G385,"mon") -> 2572.3672 | AF97: =COUNTIFS(D355:D385,1,G355:G385,"Mon") -> 4 | AH97: =AE97*AF97 -> 10289.469 | AI97: =AH97/$M$17 -> 0.14372393 | AJ97: =SUM(AI97:AI103) -> 1 | AK97: 355〜385 | AS97: =AS96+1 -> 45369
C98: =C97+1 -> 79 | D98: 1 | E98: =TEXT(AA98,"m") -> 3 | F98: =F97+1 -> 45370 | G98: =TEXT(AS98,"ddd") -> Tue | J98: =220700/$B$13 -> 2000.1813 | L98: =IF(D98=0,0,$K$8) -> 2233.4496 | M98: =IF(D98=0,0,J98-L98) -> -233.26833 | N98: =IFERROR(J98/L98,"0%") -> 0.89555693 | P98: =IF(D98=0,0,SUM($L$80:L98)) -> 35735.193 | Q98: =IF(D98=0,0,SUM($J$80:J98)) -> 35012.362 | R98: =IF(D98=0,0,Q98-P98) -> -722.83154 | S98: =IFERROR(Q98/P98,"0%") -> 0.97977256 | U98: =IF(D98=0,0,SUM($L$20:L98)) -> 123621.43 | V98: =IF(D98=0,0,SUM($J$20:J98)) -> 125498.17 | W98: =IF(D98=0,0,V98-U98) -> 1876.7349 | X98: =IFERROR(V98/U98,"0%") -> 1.0151813 | Z98: =Z97+1 -> 45370 | AA98: =AA97+1 -> 45370 | AB98: 45370 | AC98: 12 | AD98: 火 | AE98: =AVERAGEIFS(J355:J385,D355:D385,1,G355:G385,"tue") -> 2830.977 | AF98: =COUNTIFS(D355:D385,1,G355:G385,"tue") -> 4 | AH98: =AE98*AF98 -> 11323.908 | AI98: =AH98/$M$17 -> 0.15817304 | AS98: =AS97+1 -> 45370
C99: =C98+1 -> 80 | D99: 0 | E99: =TEXT(AA99,"m") -> 3 | F99: =F98+1 -> 45371 | G99: =TEXT(AS99,"ddd") -> Wed | H99: 祝日 | L99: =IF(D99=0,0,$K$8) -> 0 | M99: =IF(D99=0,0,J99-L99) -> 0 | N99: =IFERROR(J99/L99,"0%") -> 0% | P99: =IF(D99=0,0,SUM($L$80:L99)) -> 0 | Q99: =IF(D99=0,0,SUM($J$80:J99)) -> 0 | R99: =IF(D99=0,0,Q99-P99) -> 0 | S99: =IFERROR(Q99/P99,"0%") -> 0% | U99: =IF(D99=0,0,SUM($L$20:L99)) -> 0 | V99: =IF(D99=0,0,SUM($J$20:J99)) -> 0 | W99: =IF(D99=0,0,V99-U99) -> 0 | X99: =IFERROR(V99/U99,"0%") -> 0% | Z99: =Z98+1 -> 45371 | AA99: =AA98+1 -> 45371 | AB99: 45371 | AC99: 12 | AD99: 水 | AE99: =AVERAGEIFS(J355:J385,D355:D385,1,G355:G385,"wed") -> 3519.1907 | AF99: =COUNTIFS(D355:D385,1,G355:G385,"wed") -> 4 | AH99: =AE99*AF99 -> 14076.763 | AI99: =AH99/$M$17 -> 0.19662508 | AS99: =AS98+1 -> 45371
C100: =C99+1 -> 81 | D100: 1 | E100: =TEXT(AA100,"m") -> 3 | F100: =F99+1 -> 45372 | G100: =TEXT(AS100,"ddd") -> Thu | J100: =369500/$B$13 -> 3348.7403 | L100: =IF(D100=0,0,$K$8) -> 2233.4496 | M100: =IF(D100=0,0,J100-L100) -> 1115.2907 | N100: =IFERROR(J100/L100,"0%") -> 1.4993579 | P100: =IF(D100=0,0,SUM($L$80:L100)) -> 37968.643 | Q100: =IF(D100=0,0,SUM($J$80:J100)) -> 38361.102 | R100: =IF(D100=0,0,Q100-P100) -> 392.45914 | S100: =IFERROR(Q100/P100,"0%") -> 1.0103364 | U100: =IF(D100=0,0,SUM($L$20:L100)) -> 125854.88 | V100: =IF(D100=0,0,SUM($J$20:J100)) -> 128846.91 | W100: =IF(D100=0,0,V100-U100) -> 2992.0255 | X100: =IFERROR(V100/U100,"0%") -> 1.0237736 | Z100: =Z99+1 -> 45372 | AA100: =AA99+1 -> 45372 | AB100: 45372 | AC100: 12 | AD100: 木 | AE100: =AVERAGEIFS(J355:J385,D355:D385,1,G355:G385,"thu") -> 3046.5606 | AF100: =COUNTIFS(D355:D385,1,G355:G385,"thu") -> 4 | AH100: =AE100*AF100 -> 12186.243 | AI100: =AH100/$M$17 -> 0.17021818 | AS100: =AS99+1 -> 45372
C101: =C100+1 -> 82 | D101: 1 | E101: =TEXT(AA101,"m") -> 3 | F101: =F100+1 -> 45373 | G101: =TEXT(AS101,"ddd") -> Fri | J101: =333000/$B$13 -> 3017.9445 | L101: =IF(D101=0,0,$K$8) -> 2233.4496 | M101: =IF(D101=0,0,J101-L101) -> 784.49495 | N101: =IFERROR(J101/L101,"0%") -> 1.3512481 | P101: =IF(D101=0,0,SUM($L$80:L101)) -> 40202.092 | Q101: =IF(D101=0,0,SUM($J$80:J101)) -> 41379.047 | R101: =IF(D101=0,0,Q101-P101) -> 1176.9541 | S101: =IFERROR(Q101/P101,"0%") -> 1.0292759 | U101: =IF(D101=0,0,SUM($L$20:L101)) -> 128088.33 | V101: =IF(D101=0,0,SUM($J$20:J101)) -> 131864.85 | W101: =IF(D101=0,0,V101-U101) -> 3776.5205 | X101: =IFERROR(V101/U101,"0%") -> 1.0294837 | Z101: =Z100+1 -> 45373 | AA101: =AA100+1 -> 45373 | AB101: 45373 | AC101: 12 | AD101: 金 | AE101: =AVERAGEIFS(J355:J385,D355:D385,1,G355:G385,"fri") -> 3793.0941 | AF101: =COUNTIFS(D355:D385,1,G355:G385,"fri") -> 4 | AH101: =AE101*AF101 -> 15172.376 | AI101: =AH101/$M$17 -> 0.21192868 | AS101: =AS100+1 -> 45373
C102: =C101+1 -> 83 | D102: 1 | E102: =TEXT(AA102,"m") -> 3 | F102: =F101+1 -> 45374 | G102: =TEXT(AS102,"ddd") -> Sat | J102: =118964/$B$13 -> 1078.1584 | L102: =IF(D102=0,0,$K$8) -> 2233.4496 | M102: =IF(D102=0,0,J102-L102) -> -1155.2912 | N102: =IFERROR(J102/L102,"0%") -> 0.48273237 | P102: =IF(D102=0,0,SUM($L$80:L102)) -> 42435.542 | Q102: =IF(D102=0,0,SUM($J$80:J102)) -> 42457.205 | R102: =IF(D102=0,0,Q102-P102) -> 21.662925 | S102: =IFERROR(Q102/P102,"0%") -> 1.0005105 | U102: =IF(D102=0,0,SUM($L$20:L102)) -> 130321.78 | V102: =IF(D102=0,0,SUM($J$20:J102)) -> 132943.01 | W102: =IF(D102=0,0,V102-U102) -> 2621.2293 | X102: =IFERROR(V102/U102,"0%") -> 1.0201135 | Z102: =Z101+1 -> 45374 | AA102: =AA101+1 -> 45374 | AB102: 45374 | AC102: 12 | AD102: 土 | AE102: =AVERAGEIFS(J355:J385,D355:D385,1,G355:G385,"sat") -> 2135.7848 | AF102: =COUNTIFS(D355:D385,1,G355:G385,"sat") -> 4 | AH102: =AE102*AF102 -> 8543.1394 | AI102: =AH102/$M$17 -> 0.11933109 | AS102: =AS101+1 -> 45374
C103: =C102+1 -> 84 | D103: 0 | E103: =TEXT(AA103,"m") -> 3 | F103: =F102+1 -> 45375 | G103: =TEXT(AS103,"ddd") -> Sun | H103: 日曜日 | L103: =IF(D103=0,0,$K$8) -> 0 | M103: =IF(D103=0,0,J103-L103) -> 0 | N103: =IFERROR(J103/L103,"0%") -> 0% | P103: =IF(D103=0,0,SUM($L$80:L103)) -> 0 | Q103: =IF(D103=0,0,SUM($J$80:J103)) -> 0 | R103: =IF(D103=0,0,Q103-P103) -> 0 | S103: =IFERROR(Q103/P103,"0%") -> 0% | U103: =IF(D103=0,0,SUM($L$20:L103)) -> 0 | V103: =IF(D103=0,0,SUM($J$20:J103)) -> 0 | W103: =IF(D103=0,0,V103-U103) -> 0 | X103: =IFERROR(V103/U103,"0%") -> 0% | Z103: =Z102+1 -> 45375 | AA103: =AA102+1 -> 45375 | AB103: 45375 | AC103: 12 | AD103: 日 | AE103: =IFERROR(AVERAGEIFS(J355:J385,D355:D385,1,G355:G385,"sun"),0) -> 0 | AF103: =IFERROR(COUNTIFS(D355:D385,1,G355:G385,"sun"),0) -> 0 | AH103: =AE103*AF103 -> 0 | AI103: =AH103/$M$17 -> 0 | AS103: =AS102+1 -> 45375
...

Sheet 2025(¥)
B2: 45658 | E2: ①年間営業日 | G2: ②年間目標売上 | H2: 年間総売上％ | K2: 年間売上合計 | M2: 実質売上 | P2: 1月 | Q2: 2月 | R2: 3月 | S2: 4月 | T2: ←目標の月へジャンプ
E3: =SUM(F7:F18) -> 286 | G3: 72000000 | H3: =SUM(AK7:AK18)*100 -> 0.999996 | I3: =G3*H3 -> 71999712 | K3: =SUM(J21:J385) -> 76266459 | M3: =K3-G3 -> 4266459 | N3: =K3/I3 -> 1.0592606 | P3: 5月 | Q3: 6月 | R3: 7月 | S3: 8月
P4: 9月 | Q4: 10月 | R4: 11月 | S4: 12月
B6: 平均日次売上目標額 | E6: 月 | F6: 月次営業日数 | G6: 平均月間売上目標額 | H6: 月次繁閑期%設定 | I6: 月次目標売上 | K6: 日次目標売上 | M6: 月次売上実績 | N6: 月間KGI | P6: 月次平均%(繁閑期) | Q6: 月次実質%
B7: ② ÷ ① | E7: 1月 | F7: =COUNTIF(D21:D51,1) -> 22 | G7: =$B$8*F7 -> 5538461.5 | H7: 0.85 | I7: =G7*H7 -> 4707692.3 | K7: =I7/F7 -> 213986.01 | M7: =SUM(J21:J51) -> 5613250 | N7: =M7-I7 -> 905557.69 | P7: =M7/G7 -> 1.0135035 | Q7: =M7/I7 -> 1.192357 | R7: 1 | AK7: =(H7/100)*AL7 -> 0.0007083305 | AL7: 0.083333
B8: =G3/E3 -> 251748.25 | E8: 2月 | F8: =COUNTIF(D52:D79,1) -> 22 | G8: =$B$8*F8 -> 5538461.5 | H8: 0.85 | I8: =G8*H8 -> 4707692.3 | K8: =I8/F8 -> 213986.01 | M8: =SUM(J52:J79) -> 5503840 | N8: =M8-I8 -> 796147.69 | P8: =M8/G8 -> 0.99374889 | Q8: =M8/I8 -> 1.1691163 | R8: 2 | AK8: =(H8/100)*AL8 -> 0.0007083305 | AL8: 0.083333
E9: 3月 | F9: =COUNTIF(D80:D110,1) -> 25 | G9: =$B$8*F9 -> 6293706.3 | H9: 1 | I9: =G9*H9 -> 6293706.3 | K9: =I9/F9 -> 251748.25 | M9: =SUM(J80:J110) -> 6144090 | N9: =M9-I9 -> -149616.29 | P9: =M9/G9 -> 0.97622763 | Q9: =M9/I9 -> 0.97622763 | R9: 3 | AK9: =(H9/100)*AL9 -> 0.00083333 | AL9: 0.083333
E10: 4月 | F10: =COUNTIF(D111:D140,1) -> 25 | G10: =$B$8*F10 -> 6293706.3 | H10: 1.1 | I10: =G10*H10 -> 6923076.9 | K10: =I10/F10 -> 276923.08 | M10: =SUM(J111:J140) -> 6763280 | N10: =M10-I10 -> -159796.92 | P10: =M10/G10 -> 1.07461 | Q10: =M10/I10 -> 0.97691822 | R10: 4 | AK10: =(H10/100)*AL10 -> 0.000916663 | AL10: 0.083333
E11: 5月 | F11: =COUNTIF(D141:D171,1) -> 24 | G11: =$B$8*F11 -> 6041958 | H11: 1 | I11: =G11*H11 -> 6041958 | K11: =I11/F11 -> 251748.25 | M11: =SUM(J141:J171) -> 6041958 | N11: =M11-I11 -> 0 | P11: =M11/G11 -> 1 | Q11: =M11/I11 -> 1 | R11: 5 | AK11: =(H11/100)*AL11 -> 0.00083333 | AL11: 0.083333
E12: 6月 | F12: =COUNTIF(D172:D201,1) -> 25 | G12: =$B$8*F12 -> 6293706.3 | H12: 0.85 | I12: =G12*H12 -> 5349650.3 | K12: =I12/F12 -> 213986.01 | M12: =SUM(J172:J201) -> 6103080 | N12: =M12-I12 -> 753429.65 | P12: =M12/G12 -> 0.9697116 | Q12: =M12/I12 -> 1.1408372 | R12: 6 | AK12: =(H12/100)*AL12 -> 0.0007083305 | AL12: 0.083333
E13: 7月 | F13: =COUNTIF(D202:D232,1) -> 26 | G13: =$B$8*F13 -> 6545454.5 | H13: 1 | I13: =G13*H13 -> 6545454.5 | K13: =I13/F13 -> 251748.25 | M13: =SUM(J202:J232) -> 6581320 | N13: =M13-I13 -> 35865.455 | P13: =M13/G13 -> 1.0054794 | Q13: =M13/I13 -> 1.0054794 | R13: 7 | AK13: =(H13/100)*AL13 -> 0.00083333 | AL13: 0.083333
E14: 8月 | F14: =COUNTIF(D233:D263,1) -> 20 | G14: =$B$8*F14 -> 5034965 | H14: 1 | I14: =G14*H14 -> 5034965 | K14: =I14/F14 -> 251748.25 | M14: =SUM(J233:J263) -> 4857250 | N14: =M14-I14 -> -177715.03 | P14: =M14/G14 -> 0.96470382 | Q14: =M14/I14 -> 0.96470382 | R14: 8 | AK14: =(H14/100)*AL14 -> 0.00083333 | AL14: 0.083333
E15: 9 月 | F15: =COUNTIF(D264:D293,1) -> 24 | G15: =$B$8*F15 -> 6041958 | H15: 1 | I15: =G15*H15 -> 6041958 | K15: =I15/F15 -> 251748.25 | M15: =SUM(J264:J293) -> 6227066 | N15: =M15-I15 -> 185107.96 | P15: =M15/G15 -> 1.0306371 | Q15: =M15/I15 -> 1.0306371 | R15: 9 | AK15: =(H15/100)*AL15 -> 0.00083333 | AL15: 0.083333
E16: 10月 | F16: =COUNTIF(D294:D324,1) -> 26 | G16: =$B$8*F16 -> 6545454.5 | H16: 1.1 | I16: =G16*H16 -> 7200000 | K16: =I16/F16 -> 276923.08 | M16: =SUM(J294:J324) -> 7804180 | N16: =M16-I16 -> 604180 | P16: =M16/G16 -> 1.1923053 | Q16: =M16/I16 -> 1.0839139 | R16: 10 | AK16: =(H16/100)*AL16 -> 0.000916663 | AL16: 0.083333
E17: 11月 | F17: =COUNTIF(D325:D354,1) -> 23 | G17: =$B$8*F17 -> 5790209.8 | H17: 1.1 | I17: =G17*H17 -> 6369230.8 | K17: =I17/F17 -> 276923.08 | M17: =SUM(J325:J354) -> 6871130 | N17: =M17-I17 -> 501899.23 | P17: =M17/G17 -> 1.1866807 | Q17: =M17/I17 -> 1.0788006 | R17: 11 | AK17: =(H17/100)*AL17 -> 0.000916663 | AL17: 0.083333
E18: 12月 | F18: =COUNTIF(D355:D385,1) -> 24 | G18: =$B$8*F18 -> 6041958 | H18: 1.15 | I18: =G18*H18 -> 6948251.7 | K18: =I18/F18 -> 289510.49 | M18: =SUM(J355:J385) -> 7756015 | N18: =M18-I18 -> 807763.25 | P18: =M18/G18 -> 1.2836923 | Q18: =M18/I18 -> 1.1162542 | R18: 12 | AK18: =(H18/100)*AL18 -> 0.0009583295 | AL18: 0.083333
E20: 月 | F20: 日程 | G20: 曜日 | H20: 日祝日 | J20: Daily売上入力 | L20: 目標売上 | M20: 実質売上 | N20: 実質% | P20: 月次目標売上 | Q20: 月次実質売上 | R20: 月次差額 | S20: 月次達成率 | U20: 年次目標売上 | V20: 年次実質売上 | W20: 年次差額 | X20: 年次達成率 | AA20: 月 | AB20: 曜日 | AC20: 実質曜日平均売上 | AD20: 曜日回数 | AE20: 曜日毎目標売上額 | AF20: 曜日毎トータル額
C21: 1 | D21: 0 | E21: =MONTH(Y21) -> 1 | F21: =B2 -> 45658 | G21: =TEXT(Z21,"ddd") -> Wed | H21: 元旦 | L21: =IF(D21=0,0,IFERROR(SUMIFS($AE$21:$AE$104,$AA$21:$AA$104,$E21,$AB$21:$AB$104,$G21),0)) -> 0 | M21: =IF(D21=0,0,J21-L21) -> 0 | N21: =IFERROR(J21/L21,"¥0") -> ¥0 | P21: =IF(D21=0,0,$K$7) -> 0 | Q21: =IF(D21=0,0,$J$21) -> 0 | R21: =IF(D21=0,0,Q21-P21) -> 0 | S21: =IF(D21=0,0,Q21/P21) -> 0 | U21: =IF(D21=0,0,$L$21) -> 0 | V21: =IF(D21=0,0,$J$21) -> 0 | W21: =IF(D21=0,0,V21-U21) -> 0 | X21: =IF(D21=0,0,V21/U21) -> 0 | Y21: =B2 -> 45658 | Z21: =B2 -> 45658 | AA21: 1 | AB21: mon | AC21: =IFERROR(AVERAGEIFS(J21:J51,D21:D51,1,G21:G51,"mon"),0) -> 241486.67 | AD21: =COUNTIFS(D21:D51,1,G21:G51,"Mon") -> 3 | AE21: =($I$7*'2024(¥)'!AI20)/AD21 -> 318767.41 | AF21: =AD21*AE21 -> 956302.23 | AG21: 21〜51
C22: 2 | D22: 0 | E22: =MONTH(Y22) -> 1 | F22: =F21+1 -> 45659 | G22: =TEXT(Z22,"ddd") -> Thu | H22: 休み | L22: =IF(D22=0,0,IFERROR(SUMIFS($AE$21:$AE$104,$AA$21:$AA$104,$E22,$AB$21:$AB$104,$G22),0)) -> 0 | M22: =IF(D22=0,0,J22-L22) -> 0 | N22: =IFERROR(J22/L22,"¥0") -> ¥0 | P22: =IF(D22=0,0,SUM($L$21:L22)) -> 0 | Q22: =IF(D22=0,0,SUM($J$21:J22)) -> 0 | R22: =IF(D22=0,0,Q22-P22) -> 0 | S22: =IF(D22=0,0,Q22/P22) -> 0 | U22: =IF(D22=0,0,SUM($L$21:L22)) -> 0 | V22: =IF(D22=0,0,SUM($J$21:J22)) -> 0 | W22: =IF(D22=0,0,V22-U22) -> 0 | X22: =IF(D22=0,0,V22/U22) -> 0 | Y22: =Y21+1 -> 45659 | Z22: =Z21+1 -> 45659 | AA22: 1 | AB22: tue | AC22: =IFERROR(AVERAGEIFS(J21:J51,D21:D51,1,G21:G51,"tue"),0) -> 263727.5 | AD22: =COUNTIFS(D21:D51,1,G21:G51,"tue") -> 4 | AE22: =($I$7*'2024(¥)'!AI21)/AD22 -> 202590.37 | AF22: =AD22*AE22 -> 810361.5
C23: 3 | D23: 0 | E23: =MONTH(Y23) -> 1 | F23: =F22+1 -> 45660 | G23: =TEXT(Z23,"ddd") -> Fri | H23: 休み | L23: =IF(D23=0,0,IFERROR(SUMIFS($AE$21:$AE$104,$AA$21:$AA$104,$E23,$AB$21:$AB$104,$G23),0)) -> 0 | M23: =IF(D23=0,0,J23-L23) -> 0 | N23: =IFERROR(J23/L23,"¥0") -> ¥0 | P23: =IF(D23=0,0,SUM($L$21:L23)) -> 0 | Q23: =IF(D23=0,0,SUM($J$21:J23)) -> 0 | R23: =IF(D23=0,0,Q23-P23) -> 0 | S23: =IF(D23=0,0,Q23/P23) -> 0 | U23: =IF(D23=0,0,SUM($L$21:L23)) -> 0 | V23: =IF(D23=0,0,SUM($J$21:J23)) -> 0 | W23: =IF(D23=0,0,V23-U23) -> 0 | X23: =IF(D23=0,0,V23/U23) -> 0 | Y23: =Y22+1 -> 45660 | Z23: =Z22+1 -> 45660 | AA23: 1 | AB23: wed | AC23: =IFERROR(AVERAGEIFS(J21:J51,D21:D51,1,G21:G51,"wed"),0) -> 230627.5 | AD23: =COUNTIFS(D21:D51,1,G21:G51,"wed") -> 4 | AE23: =IFERROR(($I$7*'2024(¥)'!AI22)/AD23,0) -> 228185.94 | AF23: =AD23*AE23 -> 912743.76
C24: 4 | D24: 0 | E24: =MONTH(Y24) -> 1 | F24: =F23+1 -> 45661 | G24: =TEXT(Z24,"ddd") -> Sat | L24: =IF(D24=0,0,IFERROR(SUMIFS($AE$21:$AE$104,$AA$21:$AA$104,$E24,$AB$21:$AB$104,$G24),0)) -> 0 | M24: =IF(D24=0,0,J24-L24) -> 0 | N24: =IFERROR(J24/L24,"¥0") -> ¥0 | P24: =IF(D24=0,0,SUM($L$21:L24)) -> 0 | Q24: =IF(D24=0,0,SUM($J$21:J24)) -> 0 | R24: =IF(D24=0,0,Q24-P24) -> 0 | S24: =IF(D24=0,0,Q24/P24) -> 0 | U24: =IF(D24=0,0,SUM($L$21:L24)) -> 0 | V24: =IF(D24=0,0,SUM($J$21:J24)) -> 0 | W24: =IF(D24=0,0,V24-U24) -> 0 | X24: =IF(D24=0,0,V24/U24) -> 0 | Y24: =Y23+1 -> 45661 | Z24: =Z23+1 -> 45661 | AA24: 1 | AB24: thu | AC24: =IFERROR(AVERAGEIFS(J21:J51,D21:D51,1,G21:G51,"thu"),0) -> 303017.5 | AD24: =COUNTIFS(D21:D51,1,G21:G51,"thu") -> 4 | AE24: =($I$7*'2024(¥)'!AI23)/AD24 -> 158530.17 | AF24: =AD24*AE24 -> 634120.69
C25: 5 | D25: 0 | E25: =MONTH(Y25) -> 1 | F25: =F24+1 -> 45662 | G25: =TEXT(Z25,"ddd") -> Sun | L25: =IF(D25=0,0,IFERROR(SUMIFS($AE$21:$AE$104,$AA$21:$AA$104,$E25,$AB$21:$AB$104,$G25),0)) -> 0 | M25: =IF(D25=0,0,J25-L25) -> 0 | N25: =IFERROR(J25/L25,"¥0") -> ¥0 | P25: =IF(D25=0,0,SUM($L$21:L25)) -> 0 | Q25: =IF(D25=0,0,SUM($J$21:J25)) -> 0 | R25: =IF(D25=0,0,Q25-P25) -> 0 | S25: =IF(D25=0,0,Q25/P25) -> 0 | U25: =IF(D25=0,0,SUM($L$21:L25)) -> 0 | V25: =IF(D25=0,0,SUM($J$21:J25)) -> 0 | W25: =IF(D25=0,0,V25-U25) -> 0 | X25: =IF(D25=0,0,V25/U25) -> 0 | Y25: =Y24+1 -> 45662 | Z25: =Z24+1 -> 45662 | AA25: 1 | AB25: fri | AC25: =IFERROR(AVERAGEIFS(J21:J51,D21:D51,1,G21:G51,"fri"),0) -> 352387.5 | AD25: =COUNTIFS(D21:D51,1,G21:G51,"fri") -> 4 | AE25: =($I$7*'2024(¥)'!AI24)/AD25 -> 276778.21 | AF25: =AD25*AE25 -> 1107112.8
C26: 6 | D26: 1 | E26: =MONTH(Y26) -> 1 | F26: =F25+1 -> 45663 | G26: =TEXT(Z26,"ddd") -> Mon | J26: 215720 | L26: =IF(D26=0,0,IFERROR(SUMIFS($AE$21:$AE$104,$AA$21:$AA$104,$E26,$AB$21:$AB$104,$G26),0)) -> 318767.41 | M26: =IF(D26=0,0,J26-L26) -> -103047.41 | N26: =IFERROR(J26/L26,"¥0") -> 0.67673166 | P26: =IF(D26=0,0,SUM($L$21:L26)) -> 318767.41 | Q26: =IF(D26=0,0,SUM($J$21:J26)) -> 215720 | R26: =IF(D26=0,0,Q26-P26) -> -103047.41 | S26: =IF(D26=0,0,Q26/P26) -> 0.67673166 | U26: =IF(D26=0,0,SUM($L$21:L26)) -> 318767.41 | V26: =IF(D26=0,0,SUM($J$21:J26)) -> 215720 | W26: =IF(D26=0,0,V26-U26) -> -103047.41 | X26: =IF(D26=0,0,V26/U26) -> 0.67673166 | Y26: =Y25+1 -> 45663 | Z26: =Z25+1 -> 45663 | AA26: 1 | AB26: sat | AC26: =IFERROR(AVERAGEIFS(J21:J51,D21:D51,1,G21:G51,"sat"),0) -> 96583.333 | AD26: =COUNTIFS(D21:D51,1,G21:G51,"sat") -> 3 | AE26: =($I$7*'2024(¥)'!AI25)/AD26 -> 95683.766 | AF26: =AD26*AE26 -> 287051.3 | AG26: 1月目標売り上げ
C27: 7 | D27: 1 | E27: =MONTH(Y27) -> 1 | F27: =F26+1 -> 45664 | G27: =TEXT(Z27,"ddd") -> Tue | J27: 224970 | L27: =IF(D27=0,0,IFERROR(SUMIFS($AE$21:$AE$104,$AA$21:$AA$104,$E27,$AB$21:$AB$104,$G27),0)) -> 202590.37 | M27: =IF(D27=0,0,J27-L27) -> 22379.625 | N27: =IFERROR(J27/L27,"¥0") -> 1.1104674 | P27: =IF(D27=0,0,SUM($L$21:L27)) -> 521357.79 | Q27: =IF(D27=0,0,SUM($J$21:J27)) -> 440690 | R27: =IF(D27=0,0,Q27-P27) -> -80667.786 | S27: =IF(D27=0,0,Q27/P27) -> 0.84527365 | U27: =IF(D27=0,0,SUM($L$21:L27)) -> 521357.79 | V27: =IF(D27=0,0,SUM($J$21:J27)) -> 440690 | W27: =IF(D27=0,0,V27-U27) -> -80667.786 | X27: =IF(D27=0,0,V27/U27) -> 0.84527365 | Y27: =Y26+1 -> 45664 | Z27: =Z26+1 -> 45664 | AA27: 1 | AB27: sun | AC27: =IFERROR(AVERAGEIFS(J21:J51,D21:D51,1,G21:G51,"sun"),0) -> 0 | AD27: =IFERROR(COUNTIFS(D21:D51,1,G21:G51,"sun"),0) -> 0 | AE27: =IFERROR(($I$7*'2024(¥)'!AI26)/AD27,0) -> 0 | AF27: =SUM(AF21:AF26) -> 4707692.3 | AG27: =I7 -> 4707692.3
C28: 8 | D28: 1 | E28: =MONTH(Y28) -> 1 | F28: =F27+1 -> 45665 | G28: =TEXT(Z28,"ddd") -> Wed | J28: 194050 | L28: =IF(D28=0,0,IFERROR(SUMIFS($AE$21:$AE$104,$AA$21:$AA$104,$E28,$AB$21:$AB$104,$G28),0)) -> 228185.94 | M28: =IF(D28=0,0,J28-L28) -> -34135.94 | N28: =IFERROR(J28/L28,"¥0") -> 0.85040297 | P28: =IF(D28=0,0,SUM($L$21:L28)) -> 749543.73 | Q28: =IF(D28=0,0,SUM($J$21:J28)) -> 634740 | R28: =IF(D28=0,0,Q28-P28) -> -114803.73 | S28: =IF(D28=0,0,Q28/P28) -> 0.84683519 | U28: =IF(D28=0,0,SUM($L$21:L28)) -> 749543.73 | V28: =IF(D28=0,0,SUM($J$21:J28)) -> 634740 | W28: =IF(D28=0,0,V28-U28) -> -114803.73 | X28: =IF(D28=0,0,V28/U28) -> 0.84683519 | Y28: =Y27+1 -> 45665 | Z28: =Z27+1 -> 45665 | AA28: 2 | AB28: Mon | AC28: =IFERROR(AVERAGEIFS(J52:J79,D52:D79,1,G52:G79,"mon"),0) -> 218376.67 | AD28: =COUNTIFS(D52:D79,1,G52:G79,"Mon") -> 3 | AE28: =($I$8*'2024(¥)'!AI27)/AD28 -> 217651.11 | AF28: =AD28*AE28 -> 652953.33 | AG28: 52〜79
C29: 9 | D29: 1 | E29: =MONTH(Y29) -> 1 | F29: =F28+1 -> 45666 | G29: =TEXT(Z29,"ddd") -> Thu | J29: 259520 | L29: =IF(D29=0,0,IFERROR(SUMIFS($AE$21:$AE$104,$AA$21:$AA$104,$E29,$AB$21:$AB$104,$G29),0)) -> 158530.17 | M29: =IF(D29=0,0,J29-L29) -> 100989.83 | N29: =IFERROR(J29/L29,"¥0") -> 1.6370385 | P29: =IF(D29=0,0,SUM($L$21:L29)) -> 908073.9 | Q29: =IF(D29=0,0,SUM($J$21:J29)) -> 894260 | R29: =IF(D29=0,0,Q29-P29) -> -13813.899 | S29: =IF(D29=0,0,Q29/P29) -> 0.98478769 | U29: =IF(D29=0,0,SUM($L$21:L29)) -> 908073.9 | V29: =IF(D29=0,0,SUM($J$21:J29)) -> 894260 | W29: =IF(D29=0,0,V29-U29) -> -13813.899 | X29: =IF(D29=0,0,V29/U29) -> 0.98478769 | Y29: =Y28+1 -> 45666 | Z29: =Z28+1 -> 45666 | AA29: 2 | AB29: Tue | AC29: =IFERROR(AVERAGEIFS(J53:J80,D53:D80,1,G53:G80,"tue"),0) -> 260000 | AD29: =COUNTIFS(D52:D79,1,G52:G79,"tue") -> 3 | AE29: =($I$8*'2024(¥)'!AI28)/AD29 -> 268861.47 | AF29: =AD29*AE29 -> 806584.42
C30: 10 | D30: 1 | E30: =MONTH(Y30) -> 1 | F30: =F29+1 -> 45667 | G30: =TEXT(Z30,"ddd") -> Fri | J30: 364100 | L30: =IF(D30=0,0,IFERROR(SUMIFS($AE$21:$AE$104,$AA$21:$AA$104,$E30,$AB$21:$AB$104,$G30),0)) -> 276778.21 | M30: =IF(D30=0,0,J30-L30) -> 87321.794 | N30: =IFERROR(J30/L30,"¥0") -> 1.3154937 | P30: =IF(D30=0,0,SUM($L$21:L30)) -> 1184852.1 | Q30: =IF(D30=0,0,SUM($J$21:J30)) -> 1258360 | R30: =IF(D30=0,0,Q30-P30) -> 73507.895 | S30: =IF(D30=0,0,Q30/P30) -> 1.0620397 | U30: =IF(D30=0,0,SUM($L$21:L30)) -> 1184852.1 | V30: =IF(D30=0,0,SUM($J$21:J30)) -> 1258360 | W30: =IF(D30=0,0,V30-U30) -> 73507.895 | X30: =IF(D30=0,0,V30/U30) -> 1.0620397 | Y30: =Y29+1 -> 45667 | Z30: =Z29+1 -> 45667 | AA30: 2 | AB30: Wed | AC30: =IFERROR(AVERAGEIFS(J52:J79,D52:D79,1,G52:G79,"wed"),0) -> 266700 | AD30: =COUNTIFS(D52:D79,1,G52:G79,"wed") -> 4 | AE30: =($I$8*'2024(¥)'!AI29)/AD30 -> 208679.18 | AF30: =AD30*AE30 -> 834716.71
C31: 11 | D31: 1 | E31: =MONTH(Y31) -> 1 | F31: =F30+1 -> 45668 | G31: =TEXT(Z31,"ddd") -> Sat | J31: 113500 | L31: =IF(D31=0,0,IFERROR(SUMIFS($AE$21:$AE$104,$AA$21:$AA$104,$E31,$AB$21:$AB$104,$G31),0)) -> 95683.766 | M31: =IF(D31=0,0,J31-L31) -> 17816.234 | N31: =IFERROR(J31/L31,"¥0") -> 1.1861991 | P31: =IF(D31=0,0,SUM($L$21:L31)) -> 1280535.9 | Q31: =IF(D31=0,0,SUM($J$21:J31)) -> 1371860 | R31: =IF(D31=0,0,Q31-P31) -> 91324.129 | S31: =IF(D31=0,0,Q31/P31) -> 1.0713171 | U31: =IF(D31=0,0,SUM($L$21:L31)) -> 1280535.9 | V31: =IF(D31=0,0,SUM($J$21:J31)) -> 1371860 | W31: =IF(D31=0,0,V31-U31) -> 91324.129 | X31: =IF(D31=0,0,V31/U31) -> 1.0713171 | Y31: =Y30+1 -> 45668 | Z31: =Z30+1 -> 45668 | AA31: 2 | AB31: Thu | AC31: =IFERROR(AVERAGEIFS(J52:J79,D52:D79,1,G52:G79,"thu"),0) -> 323732.5 | AD31: =COUNTIFS(D52:D79,1,G52:G79,"thu") -> 4 | AE31: =($I$8*'2024(¥)'!AI30)/AD31 -> 274588.64 | AF31: =AD31*AE31 -> 1098354.6
C32: 12 | D32: 0 | E32: =MONTH(Y32) -> 1 | F32: =F31+1 -> 45669 | G32: =TEXT(Z32,"ddd") -> Sun | L32: =IF(D32=0,0,IFERROR(SUMIFS($AE$21:$AE$104,$AA$21:$AA$104,$E32,$AB$21:$AB$104,$G32),0)) -> 0 | M32: =IF(D32=0,0,J32-L32) -> 0 | N32: =IFERROR(J32/L32,"¥0") -> ¥0 | P32: =IF(D32=0,0,SUM($L$21:L32)) -> 0 | Q32: =IF(D32=0,0,SUM($J$21:J32)) -> 0 | R32: =IF(D32=0,0,Q32-P32) -> 0 | S32: =IF(D32=0,0,Q32/P32) -> 0 | U32: =IF(D32=0,0,SUM($L$21:L32)) -> 0 | V32: =IF(D32=0,0,SUM($J$21:J32)) -> 0 | W32: =IF(D32=0,0,V32-U32) -> 0 | X32: =IF(D32=0,0,V32/U32) -> 0 | Y32: =Y31+1 -> 45669 | Z32: =Z31+1 -> 45669 | AA32: 2 | AB32: Fri | AC32: =IFERROR(AVERAGEIFS(J52:J79,D52:D79,1,G52:G79,"fri"),0) -> 342030 | AD32: =COUNTIFS(D52:D79,1,G52:G79,"fri") -> 4 | AE32: =($I$8*'2024(¥)'!AI31)/AD32 -> 200399.02 | AF32: =AD32*AE32 -> 801596.09
C33: 13 | D33: 0 | E33: =MONTH(Y33) -> 1 | F33: =F32+1 -> 45670 | G33: =TEXT(Z33,"ddd") -> Mon | H33: 成人の日 | L33: =IF(D33=0,0,IFERROR(SUMIFS($AE$21:$AE$104,$AA$21:$AA$104,$E33,$AB$21:$AB$104,$G33),0)) -> 0 | M33: =IF(D33=0,0,J33-L33) -> 0 | N33: =IFERROR(J33/L33,"¥0") -> ¥0 | P33: =IF(D33=0,0,SUM($L$21:L33)) -> 0 | Q33: =IF(D33=0,0,SUM($J$21:J33)) -> 0 | R33: =IF(D33=0,0,Q33-P33) -> 0 | S33: =IF(D33=0,0,Q33/P33) -> 0 | U33: =IF(D33=0,0,SUM($L$21:L33)) -> 0 | V33: =IF(D33=0,0,SUM($J$21:J33)) -> 0 | W33: =IF(D33=0,0,V33-U33) -> 0 | X33: =IF(D33=0,0,V33/U33) -> 0 | Y33: =Y32+1 -> 45670 | Z33: =Z32+1 -> 45670 | AA33: 2 | AB33: Sat | AC33: =IFERROR(AVERAGEIFS(J52:J79,D52:D79,1,G52:G79,"sat"),0) -> 84715 | AD33: =COUNTIFS(D52:D79,1,G52:G79,"sat") -> 4 | AE33: =($I$8*'2024(¥)'!AI32)/AD33 -> 128371.8 | AF33: =AD33*AE33 -> 513487.2 | AG33: 2月目標売り上げ
C34: 14 | D34: 1 | E34: =MONTH(Y34) -> 1 | F34: =F33+1 -> 45671 | G34: =TEXT(Z34,"ddd") -> Tue | J34: 312590 | L34: =IF(D34=0,0,IFERROR(SUMIFS($AE$21:$AE$104,$AA$21:$AA$104,$E34,$AB$21:$AB$104,$G34),0)) -> 202590.37 | M34: =IF(D34=0,0,J34-L34) -> 109999.63 | N34: =IFERROR(J34/L34,"¥0") -> 1.5429657 | P34: =IF(D34=0,0,SUM($L$21:L34)) -> 1483126.2 | Q34: =IF(D34=0,0,SUM($J$21:J34)) -> 1684450 | R34: =IF(D34=0,0,Q34-P34) -> 201323.75 | S34: =IF(D34=0,0,Q34/P34) -> 1.1357428 | U34: =IF(D34=0,0,SUM($L$21:L34)) -> 1483126.2 | V34: =IF(D34=0,0,SUM($J$21:J34)) -> 1684450 | W34: =IF(D34=0,0,V34-U34) -> 201323.75 | X34: =IF(D34=0,0,V34/U34) -> 1.1357428 | Y34: =Y33+1 -> 45671 | Z34: =Z33+1 -> 45671 | AA34: 2 | AB34: Sun | AC34: =IFERROR(AVERAGEIFS(J52:J79,D52:D79,1,G52:G79,"sun"),0) -> 0 | AD34: =IFERROR(COUNTIFS(D52:D79,1,G52:G79,"sun"),0) -> 0 | AE34: =IFERROR(($I$8*'2024(¥)'!AI33)/AD34,0) -> 0 | AF34: =SUM(AF28:AF33) -> 4707692.3 | AG34: =I8 -> 4707692.3
C35: 15 | D35: 1 | E35: =MONTH(Y35) -> 1 | F35: =F34+1 -> 45672 | G35: =TEXT(Z35,"ddd") -> Wed | J35: 242580 | L35: =IF(D35=0,0,IFERROR(SUMIFS($AE$21:$AE$104,$AA$21:$AA$104,$E35,$AB$21:$AB$104,$G35),0)) -> 228185.94 | M35: =IF(D35=0,0,J35-L35) -> 14394.06 | N35: =IFERROR(J35/L35,"¥0") -> 1.0630804 | P35: =IF(D35=0,0,SUM($L$21:L35)) -> 1711312.2 | Q35: =IF(D35=0,0,SUM($J$21:J35)) -> 1927030 | R35: =IF(D35=0,0,Q35-P35) -> 215717.81 | S35: =IF(D35=0,0,Q35/P35) -> 1.126054 | U35: =IF(D35=0,0,SUM($L$21:L35)) -> 1711312.2 | V35: =IF(D35=0,0,SUM($J$21:J35)) -> 1927030 | W35: =IF(D35=0,0,V35-U35) -> 215717.81 | X35: =IF(D35=0,0,V35/U35) -> 1.126054 | Y35: =Y34+1 -> 45672 | Z35: =Z34+1 -> 45672 | AA35: 3 | AB35: Mon | AC35: =IFERROR(AVERAGEIFS(J80:J110,D80:D110,1,G80:G110,"mon"),0) -> 271114 | AD35: =COUNTIFS(D80:D110,1,G80:G110,"Mon") -> 5 | AE35: =($I$9*'2024(¥)'!AI34)/AD35 -> 178438.03 | AF35: =AD35*AE35 -> 892190.16 | AG35: 80〜110
C36: 16 | D36: 1 | E36: =MONTH(Y36) -> 1 | F36: =F35+1 -> 45673 | G36: =TEXT(Z36,"ddd") -> Thu | J36: 332580 | L36: =IF(D36=0,0,IFERROR(SUMIFS($AE$21:$AE$104,$AA$21:$AA$104,$E36,$AB$21:$AB$104,$G36),0)) -> 158530.17 | M36: =IF(D36=0,0,J36-L36) -> 174049.83 | N36: =IFERROR(J36/L36,"¥0") -> 2.0978972 | P36: =IF(D36=0,0,SUM($L$21:L36)) -> 1869842.4 | Q36: =IF(D36=0,0,SUM($J$21:J36)) -> 2259610 | R36: =IF(D36=0,0,Q36-P36) -> 389767.64 | S36: =IF(D36=0,0,Q36/P36) -> 1.2084495 | U36: =IF(D36=0,0,SUM($L$21:L36)) -> 1869842.4 | V36: =IF(D36=0,0,SUM($J$21:J36)) -> 2259610 | W36: =IF(D36=0,0,V36-U36) -> 389767.64 | X36: =IF(D36=0,0,V36/U36) -> 1.2084495 | Y36: =Y35+1 -> 45673 | Z36: =Z35+1 -> 45673 | AA36: 3 | AB36: Tue | AC36: =IFERROR(AVERAGEIFS(J80:J110,D80:D110,1,G80:G110,"tue"),0) -> 240440 | AD36: =COUNTIFS(D80:D110,1,G80:G110,"tue") -> 4 | AE36: =($I$9*'2024(¥)'!AI35)/AD36 -> 257148.23 | AF36: =AD36*AE36 -> 1028592.9
C37: 17 | D37: 1 | E37: =MONTH(Y37) -> 1 | F37: =F36+1 -> 45674 | G37: =TEXT(Z37,"ddd") -> Fri | J37: 312220 | L37: =IF(D37=0,0,IFERROR(SUMIFS($AE$21:$AE$104,$AA$21:$AA$104,$E37,$AB$21:$AB$104,$G37),0)) -> 276778.21 | M37: =IF(D37=0,0,J37-L37) -> 35441.794 | N37: =IFERROR(J37/L37,"¥0") -> 1.1280512 | P37: =IF(D37=0,0,SUM($L$21:L37)) -> 2146620.6 | Q37: =IF(D37=0,0,SUM($J$21:J37)) -> 2571830 | R37: =IF(D37=0,0,Q37-P37) -> 425209.43 | S37: =IF(D37=0,0,Q37/P37) -> 1.1980832 | U37: =IF(D37=0,0,SUM($L$21:L37)) -> 2146620.6 | V37: =IF(D37=0,0,SUM($J$21:J37)) -> 2571830 | W37: =IF(D37=0,0,V37-U37) -> 425209.43 | X37: =IF(D37=0,0,V37/U37) -> 1.1980832 | Y37: =Y36+1 -> 45674 | Z37: =Z36+1 -> 45674 | AA37: 3 | AB37: Wed | AC37: =IFERROR(AVERAGEIFS(J80:J110,D80:D110,1,G80:G110,"wed"),0) -> 286265 | AD37: =COUNTIFS(D80:D110,1,G80:G110,"wed") -> 4 | AE37: =($I$9*'2024(¥)'!AI36)/AD37 -> 214767.13 | AF37: =AD37*AE37 -> 859068.51
C38: 18 | D38: 1 | E38: =MONTH(Y38) -> 1 | F38: =F37+1 -> 45675 | G38: =TEXT(Z38,"ddd") -> Sat | J38: 76270 | L38: =IF(D38=0,0,IFERROR(SUMIFS($AE$21:$AE$104,$AA$21:$AA$104,$E38,$AB$21:$AB$104,$G38),0)) -> 95683.766 | M38: =IF(D38=0,0,J38-L38) -> -19413.766 | N38: =IFERROR(J38/L38,"¥0") -> 0.79710491 | P38: =IF(D38=0,0,SUM($L$21:L38)) -> 2242304.3 | Q38: =IF(D38=0,0,SUM($J$21:J38)) -> 2648100 | R38: =IF(D38=0,0,Q38-P38) -> 405795.67 | S38: =IF(D38=0,0,Q38/P38) -> 1.1809726 | U38: =IF(D38=0,0,SUM($L$21:L38)) -> 2242304.3 | V38: =IF(D38=0,0,SUM($J$21:J38)) -> 2648100 | W38: =IF(D38=0,0,V38-U38) -> 405795.67 | X38: =IF(D38=0,0,V38/U38) -> 1.1809726 | Y38: =Y37+1 -> 45675 | Z38: =Z37+1 -> 45675 | AA38: 3 | AB38: Thu | AC38: =IFERROR(AVERAGEIFS(J80:J110,D80:D110,1,G80:G110,"thu"),0) -> 328390 | AD38: =COUNTIFS(D80:D110,1,G80:G110,"thu") -> 3 | AE38: =($I$9*'2024(¥)'!AI37)/AD38 -> 400846.68 | AF38: =AD38*AE38 -> 1202540
C39: 19 | D39: 0 | E39: =MONTH(Y39) -> 1 | F39: =F38+1 -> 45676 | G39: =TEXT(Z39,"ddd") -> Sun | L39: =IF(D39=0,0,IFERROR(SUMIFS($AE$21:$AE$104,$AA$21:$AA$104,$E39,$AB$21:$AB$104,$G39),0)) -> 0 | M39: =IF(D39=0,0,J39-L39) -> 0 | N39: =IFERROR(J39/L39,"¥0") -> ¥0 | P39: =IF(D39=0,0,SUM($L$21:L39)) -> 0 | Q39: =IF(D39=0,0,SUM($J$21:J39)) -> 0 | R39: =IF(D39=0,0,Q39-P39) -> 0 | S39: =IF(D39=0,0,Q39/P39) -> 0 | U39: =IF(D39=0,0,SUM($L$21:L39)) -> 0 | V39: =IF(D39=0,0,SUM($J$21:J39)) -> 0 | W39: =IF(D39=0,0,V39-U39) -> 0 | X39: =IF(D39=0,0,V39/U39) -> 0 | Y39: =Y38+1 -> 45676 | Z39: =Z38+1 -> 45676 | AA39: 3 | AB39: Fri | AC39: =IFERROR(AVERAGEIFS(J80:J110,D80:D110,1,G80:G110,"fri"),0) -> 333300 | AD39: =COUNTIFS(D80:D110,1,G80:G110,"fri") -> 4 | AE39: =($I$9*'2024(¥)'!AI38)/AD39 -> 392864.2 | AF39: =AD39*AE39 -> 1571456.8
C40: 20 | D40: 1 | E40: =MONTH(Y40) -> 1 | F40: =F39+1 -> 45677 | G40: =TEXT(Z40,"ddd") -> Mon | J40: 238030 | L40: =IF(D40=0,0,IFERROR(SUMIFS($AE$21:$AE$104,$AA$21:$AA$104,$E40,$AB$21:$AB$104,$G40),0)) -> 318767.41 | M40: =IF(D40=0,0,J40-L40) -> -80737.411 | N40: =IFERROR(J40/L40,"¥0") -> 0.74672 | P40: =IF(D40=0,0,SUM($L$21:L40)) -> 2561071.7 | Q40: =IF(D40=0,0,SUM($J$21:J40)) -> 2886130 | R40: =IF(D40=0,0,Q40-P40) -> 325058.26 | S40: =IF(D40=0,0,Q40/P40) -> 1.1269227 | U40: =IF(D40=0,0,SUM($L$21:L40)) -> 2561071.7 | V40: =IF(D40=0,0,SUM($J$21:J40)) -> 2886130 | W40: =IF(D40=0,0,V40-U40) -> 325058.26 | X40: =IF(D40=0,0,V40/U40) -> 1.1269227 | Y40: =Y39+1 -> 45677 | Z40: =Z39+1 -> 45677 | AA40: 3 | AB40: Sat | AC40: =IFERROR(AVERAGEIFS(J80:J110,D80:D110,1,G80:G110,"sat"),0) -> 72666 | AD40: =COUNTIFS(D80:D110,1,G80:G110,"sat") -> 5 | AE40: =($I$9*'2024(¥)'!AI39)/AD40 -> 147971.57 | AF40: =AD40*AE40 -> 739857.84 | AG40: 3月目標売り上げ
C41: 21 | D41: 1 | E41: =MONTH(Y41) -> 1 | F41: =F40+1 -> 45678 | G41: =TEXT(Z41,"ddd") -> Tue | J41: 246550 | L41: =IF(D41=0,0,IFERROR(SUMIFS($AE$21:$AE$104,$AA$21:$AA$104,$E41,$AB$21:$AB$104,$G41),0)) -> 202590.37 | M41: =IF(D41=0,0,J41-L41) -> 43959.625 | N41: =IFERROR(J41/L41,"¥0") -> 1.2169877 | P41: =IF(D41=0,0,SUM($L$21:L41)) -> 2763662.1 | Q41: =IF(D41=0,0,SUM($J$21:J41)) -> 3132680 | R41: =IF(D41=0,0,Q41-P41) -> 369017.88 | S41: =IF(D41=0,0,Q41/P41) -> 1.133525 | U41: =IF(D41=0,0,SUM($L$21:L41)) -> 2763662.1 | V41: =IF(D41=0,0,SUM($J$21:J41)) -> 3132680 | W41: =IF(D41=0,0,V41-U41) -> 369017.88 | X41: =IF(D41=0,0,V41/U41) -> 1.133525 | Y41: =Y40+1 -> 45678 | Z41: =Z40+1 -> 45678 | AA41: 3 | AB41: Sun | AC41: =IFERROR(AVERAGEIFS(J80:J110,D80:D110,1,G80:G110,"sun"),0) -> 0 | AD41: =IFERROR(COUNTIFS(D80:D110,1,G80:G110,"sun"),0) -> 0 | AE41: =IFERROR(($I$9*'2024(¥)'!AI40)/AD41,0) -> 0 | AF41: =SUM(AF35:AF40) -> 6293706.3 | AG41: =I9 -> 6293706.3
C42: 22 | D42: 1 | E42: =MONTH(Y42) -> 1 | F42: =F41+1 -> 45679 | G42: =TEXT(Z42,"ddd") -> Wed | J42: 207530 | L42: =IF(D42=0,0,IFERROR(SUMIFS($AE$21:$AE$104,$AA$21:$AA$104,$E42,$AB$21:$AB$104,$G42),0)) -> 228185.94 | M42: =IF(D42=0,0,J42-L42) -> -20655.94 | N42: =IFERROR(J42/L42,"¥0") -> 0.9094776 | P42: =IF(D42=0,0,SUM($L$21:L42)) -> 2991848.1 | Q42: =IF(D42=0,0,SUM($J$21:J42)) -> 3340210 | R42: =IF(D42=0,0,Q42-P42) -> 348361.94 | S42: =IF(D42=0,0,Q42/P42) -> 1.116437 | U42: =IF(D42=0,0,SUM($L$21:L42)) -> 2991848.1 | V42: =IF(D42=0,0,SUM($J$21:J42)) -> 3340210 | W42: =IF(D42=0,0,V42-U42) -> 348361.94 | X42: =IF(D42=0,0,V42/U42) -> 1.116437 | Y42: =Y41+1 -> 45679 | Z42: =Z41+1 -> 45679 | AA42: 4 | AB42: Mon | AC42: =IFERROR(AVERAGEIFS(J111:J140,D111:D140,1,G111:G140,"mon"),0) -> 259995 | AD42: =COUNTIFS(D111:D140,1,G111:G140,"Mon") -> 4 | AE42: =($I$10*'2024(¥)'!AI41)/AD42 -> 236793.42 | AF42: =AD42*AE42 -> 947173.69 | AG42: 111〜140
C43: 23 | D43: 1 | E43: =MONTH(Y43) -> 1 | F43: =F42+1 -> 45680 | G43: =TEXT(Z43,"ddd") -> Thu | J43: 302150 | L43: =IF(D43=0,0,IFERROR(SUMIFS($AE$21:$AE$104,$AA$21:$AA$104,$E43,$AB$21:$AB$104,$G43),0)) -> 158530.17 | M43: =IF(D43=0,0,J43-L43) -> 143619.83 | N43: =IFERROR(J43/L43,"¥0") -> 1.9059463 | P43: =IF(D43=0,0,SUM($L$21:L43)) -> 3150378.2 | Q43: =IF(D43=0,0,SUM($J$21:J43)) -> 3642360 | R43: =IF(D43=0,0,Q43-P43) -> 491981.77 | S43: =IF(D43=0,0,Q43/P43) -> 1.1561659 | U43: =IF(D43=0,0,SUM($L$21:L43)) -> 3150378.2 | V43: =IF(D43=0,0,SUM($J$21:J43)) -> 3642360 | W43: =IF(D43=0,0,V43-U43) -> 491981.77 | X43: =IF(D43=0,0,V43/U43) -> 1.1561659 | Y43: =Y42+1 -> 45680 | Z43: =Z42+1 -> 45680 | AA43: 4 | AB43: Tue | AC43: =IFERROR(AVERAGEIFS(J111:J140,D111:D140,1,G111:G140,"tue"),0) -> 299070 | AD43: =COUNTIFS(D111:D140,1,G111:G140,"tue") -> 4 | AE43: =($I$10*'2024(¥)'!AI42)/AD43 -> 349706.71 | AF43: =AD43*AE43 -> 1398826.8
C44: 24 | D44: 1 | E44: =MONTH(Y44) -> 1 | F44: =F43+1 -> 45681 | G44: =TEXT(Z44,"ddd") -> Fri | J44: 398010 | L44: =IF(D44=0,0,IFERROR(SUMIFS($AE$21:$AE$104,$AA$21:$AA$104,$E44,$AB$21:$AB$104,$G44),0)) -> 276778.21 | M44: =IF(D44=0,0,J44-L44) -> 121231.79 | N44: =IFERROR(J44/L44,"¥0") -> 1.4380106 | P44: =IF(D44=0,0,SUM($L$21:L44)) -> 3427156.4 | Q44: =IF(D44=0,0,SUM($J$21:J44)) -> 4040370 | R44: =IF(D44=0,0,Q44-P44) -> 613213.56 | S44: =IF(D44=0,0,Q44/P44) -> 1.1789278 | U44: =IF(D44=0,0,SUM($L$21:L44)) -> 3427156.4 | V44: =IF(D44=0,0,SUM($J$21:J44)) -> 4040370 | W44: =IF(D44=0,0,V44-U44) -> 613213.56 | X44: =IF(D44=0,0,V44/U44) -> 1.1789278 | Y44: =Y43+1 -> 45681 | Z44: =Z43+1 -> 45681 | AA44: 4 | AB44: Wed | AC44: =IFERROR(AVERAGEIFS(J111:J140,D111:D140,1,G111:G140,"wed"),0) -> 275436 | AD44: =COUNTIFS(D111:D140,1,G111:G140,"wed") -> 5 | AE44: =($I$10*'2024(¥)'!AI43)/AD44 -> 242810.6 | AF44: =AD44*AE44 -> 1214053
C45: 25 | D45: 1 | E45: =MONTH(Y45) -> 1 | F45: =F44+1 -> 45682 | G45: =TEXT(Z45,"ddd") -> Sat | J45: 99980 | L45: =IF(D45=0,0,IFERROR(SUMIFS($AE$21:$AE$104,$AA$21:$AA$104,$E45,$AB$21:$AB$104,$G45),0)) -> 95683.766 | M45: =IF(D45=0,0,J45-L45) -> 4296.234 | N45: =IFERROR(J45/L45,"¥0") -> 1.0449003 | P45: =IF(D45=0,0,SUM($L$21:L45)) -> 3522840.2 | Q45: =IF(D45=0,0,SUM($J$21:J45)) -> 4140350 | R45: =IF(D45=0,0,Q45-P45) -> 617509.8 | S45: =IF(D45=0,0,Q45/P45) -> 1.1752875 | U45: =IF(D45=0,0,SUM($L$21:L45)) -> 3522840.2 | V45: =IF(D45=0,0,SUM($J$21:J45)) -> 4140350 | W45: =IF(D45=0,0,V45-U45) -> 617509.8 | X45: =IF(D45=0,0,V45/U45) -> 1.1752875 | Y45: =Y44+1 -> 45682 | Z45: =Z44+1 -> 45682 | AA45: 4 | AB45: Thu | AC45: =IFERROR(AVERAGEIFS(J111:J140,D111:D140,1,G111:G140,"thu"),0) -> 347200 | AD45: =COUNTIFS(D111:D140,1,G111:G140,"thu") -> 4 | AE45: =($I$10*'2024(¥)'!AI44)/AD45 -> 288304.4 | AF45: =AD45*AE45 -> 1153217.6
C46: 26 | D46: 0 | E46: =MONTH(Y46) -> 1 | F46: =F45+1 -> 45683 | G46: =TEXT(Z46,"ddd") -> Sun | L46: =IF(D46=0,0,IFERROR(SUMIFS($AE$21:$AE$104,$AA$21:$AA$104,$E46,$AB$21:$AB$104,$G46),0)) -> 0 | M46: =IF(D46=0,0,J46-L46) -> 0 | N46: =IFERROR(J46/L46,"¥0") -> ¥0 | P46: =IF(D46=0,0,SUM($L$21:L46)) -> 0 | Q46: =IF(D46=0,0,SUM($J$21:J46)) -> 0 | R46: =IF(D46=0,0,Q46-P46) -> 0 | S46: =IF(D46=0,0,Q46/P46) -> 0 | U46: =IF(D46=0,0,SUM($L$21:L46)) -> 0 | V46: =IF(D46=0,0,SUM($J$21:J46)) -> 0 | W46: =IF(D46=0,0,V46-U46) -> 0 | X46: =IF(D46=0,0,V46/U46) -> 0 | Y46: =Y45+1 -> 45683 | Z46: =Z45+1 -> 45683 | AA46: 4 | AB46: Fri | AC46: =IFERROR(AVERAGEIFS(J111:J140,D111:D140,1,G111:G140,"fri"),0) -> 347270 | AD46: =COUNTIFS(D111:D140,1,G111:G140,"fri") -> 4 | AE46: =($I$10*'2024(¥)'!AI45)/AD46 -> 343351.24 | AF46: =AD46*AE46 -> 1373405
