Workbook

Sheet ★プラナバルカ戦略表
A2: プラナバルカ | B2: 45962 | C2: =MONTH(B2) -> 11
B3: =B15 -> 45974 | D3: =TEXT(B3, "aaa") -> 木
B4: 目標売上 | C4: =_xlfn.XLOOKUP(D3, B7:B12, C7:C12, "該当なし") -> 該当なし
B6: 9月 曜日毎の目標売上 | D6: 傾向 | G6: 対策考察
B7: mon | C7: =SUMIFS(目標_2025R7!$AE$22:$AE$104, 目標_2025R7!$AA$22:$AA$104, MONTH($B$2), 目標_2025R7!$AB$22:$AB$104, B7) -> 219995.68 | D7: ランチ・ディナーともに客数は安定傾向。売上は全体平均よりやや下回るが、曜日内ではバランスの取れた動きが見られる。ランチ構成比が高め。 | G7: 週のスタートとして安心感を訴求する投稿が有効。ディナーの客単価は高めな一方、客数は少ないため、リピート促進や「月曜限定メニュー」などで来店動機づけを強化。
B8: tue | C8: =SUMIFS(目標_2025R7!$AE$22:$AE$104, 目標_2025R7!$AA$22:$AA$104, MONTH($B$2), 目標_2025R7!$AB$22:$AB$104, B8) -> 192620.47 | D8: 全体平均を下回る売上水準。ディナーの客単価・客数が共に控えめで、回転率の低さが目立つ。 | G8: 来店促進のため、SNSでのクーポンやペア割の訴求が効果的。ランチの来客数は一定のため、固定ファン向けの新メニューや限定セットで強化を図る。
B9: wed | C9: =SUMIFS(目標_2025R7!$AE$22:$AE$104, 目標_2025R7!$AA$22:$AA$104, MONTH($B$2), 目標_2025R7!$AB$22:$AB$104, B9) -> 222098.1 | D9: 全曜日中、最も売上が高く、ランチ・ディナー共に客単価・客数ともに好調。特にディナーの売上が突出。 | G9: 定着需要があると推測されるため、人気メニューの再告知や満席対策が重要。週前半のピークに備えてスタッフ体制を厚めに配置。
B10: thu | C10: =SUMIFS(目標_2025R7!$AE$22:$AE$104, 目標_2025R7!$AA$22:$AA$104, MONTH($B$2), 目標_2025R7!$AB$22:$AB$104, B10) -> 216358.54 | D10: 平均をやや上回る水準で安定。ランチ・ディナーともに偏りなく客数が確保されている。 | G10: 中間日としての安定運用が可能。レビュー促進やLINE登録キャンペーンなど、継続来店につながる施策を試みたい。
B11: fri | C11: =SUMIFS(目標_2025R7!$AE$22:$AE$104, 目標_2025R7!$AA$22:$AA$104, MONTH($B$2), 目標_2025R7!$AB$22:$AB$104, B11) -> 346355.42 | D11: 水曜に次ぐ高売上曜日。特にディナーの客数が最多であり、終末への流れによる需要の高まりが顕著。 | G11: ピーク帯の事前予約推奨、オペレーション効率化が必須。混雑時の待ち時間緩和策（簡易ドリンク提供等）も検討価値あり。
B12: sat | C12: =SUMIFS(目標_2025R7!$AE$22:$AE$104, 目標_2025R7!$AA$22:$AA$104, MONTH($B$2), 目標_2025R7!$AB$22:$AB$104, B12) -> 146897.8 | D12: 売上は全体平均を下回るが、ランチ客単価は最も高い。客数が少ないため、単価依存の構成となっている。 | G12: 昼飲みや記念日需要への訴求を強化。Instagramなどビジュアル訴求による週末の集客導線設計がカギ。予約なし来店の傾向も加味しつつ対応を。
E14: 下方修正案 | H14: 現状案
A15: プラナバルカ | B15: 45974 | C15: =TEXT(B15, "ddd") -> Thu | E15: 年間目標金額 | F15: =F29 -> 63000000 | H15: 年間目標金額 | I15: 75000000
A16: 日次 | B16: 売上 | C16: =_xlfn.XLOOKUP(B15, 目標_2025R7!F21:F385,目標_2025R7!J21:J385,"該当なし") -> 79100 | E16: 月次目標売上 | F16: =INDEX(目標_2025R7!I7:I18, MATCH(MONTH(B2), 目標_2025R7!AC7:AC18, 0)) -> 5084210.5 | H16: 月次目標売上 | I16: =INDEX(目標_2025R7!I7:I18, MATCH(MONTH(B2), 目標_2025R7!AC7:AC18, 0)) -> 5084210.5 | N16: 月 | O16: 傾向分析
B17: 平均目標売上 | C17: =INDEX(目標_2025R7!K7:K18, MATCH(C2, 目標_2025R7!AC7:AC18, 0)) -> 221052.63 | E17: 月次累計実績売上 | F17: =C22 -> 1636190 | H17: 月次累計実績売上 | I17: =C22 -> 1636190
B18: 目標売上 | C18: =_xlfn.XLOOKUP(C15, B7:B12, C7:C12, "該当なし") -> 216358.54 | E18: 差額 | F18: =F16-F17 -> 3448020.5 | H18: 差額 | I18: =I16-I17 -> 3448020.5 | N18: 1月 | O18: A: 月初・末が強い（中旬落ち）
B19: 差額 | C19: =C16-C18 -> -137258.54 | E19: 当月残営業日 | F19: {=(SUMPRODUCT((目標_2025R7!F21:F385>=B15)*(目標_2025R7!E21:E385=C2)*(目標_2025R7!D21:D385=1)))-1} -> 13 | H19: 当月残営業日 | I19: =F19 -> 13 | N19: 2月 | O19: B: 月末にかけて上がる
B20: 達成率 | C20: =IFERROR(C16/C18,0) -> 0.36559684 | E20: 今月1日あたりの目標売上 | F20: =IFERROR(F18/F19,0) -> 265232.35 | H20: 今月1日あたりの目標売上 | I20: =I18/I19 -> 265232.35 | N20: 3月 | O20: B: 同様に右肩上がり傾向
N21: 4月 | O21: A: 月初も末も強く安定感あり
A22: 月次 | B22: 累積売上 | C22: =_xlfn.XLOOKUP(B15, 目標_2025R7!F21:F385,目標_2025R7!Q21:Q385,"該当なし") -> 1636190 | N22: 5月 | O22: B: 徐々に上がる
B23: 累積目標売上 | C23: =_xlfn.XLOOKUP(B15, 目標_2025R7!F21:F385,目標_2025R7!P21:P385,"該当なし") -> 2122300.9 | E23: 年間営業日数 | F23: =目標_2025R7!E3 -> 285 | N23: 分類 | O23: 説明
B24: 差額 | C24: =C22-C23 -> -486110.94 | E24: =B34 -> 今年の残営業日数 | F24: =C34 -> 37 | N24: A: 初・末が強い | O24: 月初・月末の売上が高く、中旬が落ちるパターン
B25: 達成率 | C25: =IFERROR(C22/C23,0) -> 0.77095098 | E25: 直近までの営業日数 | F25: =F23-F24 -> 248 | N25: B: 徐々に上がる | O25: 月初が弱く、末に向かって売上が上がる
N26: C: 平均的 or 中旬強い | O26: 大きな偏りがない or 中旬が強いパターン
A27: 年次 | B27: 累積売上 | C27: =_xlfn.XLOOKUP(B15, 目標_2025R7!F21:F385,目標_2025R7!V21:V385,"該当なし") -> 54634150 | E27: 今年の今までの営業日平均売上 | F27: =C27/F25 -> 220298.99
B28: 累積目標売上 | C28: =_xlfn.XLOOKUP(B15, 目標_2025R7!F21:F385,目標_2025R7!U21:U385,"該当なし") -> 54710722 | E28: 今年の残営業日数での売上 | F28: =F27*F24 -> 8151062.7
B29: 差額 | C29: =C27-C28 -> -76571.992 | E29: 合計 | F29: 63000000
B30: 達成率 | C30: =IFERROR(C27/C28,0) -> 0.99860042
B32: 年次目標売上 | C32: =目標_2025R7!G3 -> 63000000
B33: 目標達成までの残額 | C33: =C32-C27 -> 8365850
B34: 今年の残営業日数 | C34: {=(SUMPRODUCT((目標_2025R7!F21:F385>=B15)*(目標_2025R7!D21:D385=1)))-1} -> 37
B35: 1日あたりの売上額 | C35: =IFERROR(C33/C34,0) -> 226104.05
B36: 年間達成率 | C36: =1-(C33/C32) -> 0.86720873
B38: 2025年7月の情報
B39: 曜日 | C39: 出現回数 | D39: 加重比率 | E39: 曜日別割当額 | F39: 1日あたり目標
B40: 月 | C40: 4 | D40: 0.1193 | E40: 894636 | F40: 223659
B41: 火 | C41: 5 | D41: 0.1404 | E41: 1053371 | F41: 210674
B42: 水 | C42: 5 | D42: 0.2035 | E42: 1526394 | F42: 305279
B43: 木 | C43: 5 | D43: 0.2281 | E43: 1710568 | F43: 342114
B44: 金 | C44: 4 | D44: 0.2189 | E44: 1641933 | F44: 410483
B45: 土 | C45: 4 | D45: 0.0897 | E45: 673097 | F45: 168274
B46: 日 | D46: 0 | E46: 0 | F46: 0
B47: 合計 | C47: =SUM(C40:C46) -> 27 | D47: 1 | E47: ¥7,500,000 ✔ | F47: —
A49: プラナバルカ | B49: 曜日 | C49: 売上 | D49: 平均目標売上 | E49: 曜日繁閑期目標売上 | F49: 差額 | G49: 達成率 | H49: 累積売上 | I49: 累積目標売上 | J49: 差額 | K49: 達成率
B50: =B2 -> 45962 | C50: 316470 | D50: =$C$17 -> 221052.63 | E50: =$C$8 -> 192620.47 | F50: =C50-E50 -> 123849.53 | G50: =IFERROR(C50/E50,0) -> 1.6429718 | H50: =IF(C50=0,0,C50) -> 316470 | I50: =IF(C50=0,0,E50) -> 192620.47 | J50: =H50-I50 -> 123849.53 | K50: =IFERROR(H50/I50,0) -> 1.6429718
B51: =B50+1 -> 45963 | C51: 347600 | D51: =$C$17 -> 221052.63 | E51: =$C$9 -> 222098.1 | F51: =C51-E51 -> 125501.9 | G51: =IFERROR(C51/E51,0) -> 1.5650742 | H51: =IF(C51=0,0,(H50+C51)) -> 664070 | I51: =IF(C51=0,0,(I50+E51)) -> 414718.57 | J51: =H51-I51 -> 249351.43 | K51: =IFERROR(H51/I51,0) -> 1.6012545
B52: =B51+1 -> 45964 | C52: 221970 | D52: =$C$17 -> 221052.63 | E52: =$C$10 -> 216358.54 | F52: =C52-E52 -> 5611.457 | G52: =IFERROR(C52/E52,0) -> 1.0259359 | H52: =IF(C52=0,0,(H51+C52)) -> 886040 | I52: =IF(C52=0,0,(I51+E52)) -> 631077.12 | J52: =H52-I52 -> 254962.88 | K52: =IFERROR(H52/I52,0) -> 1.4040122
B53: =B52+1 -> 45965 | C53: 329910 | D53: =$C$17 -> 221052.63 | E53: =$C$11 -> 346355.42 | F53: =C53-E53 -> -16445.421 | G53: =IFERROR(C53/E53,0) -> 0.95251865 | H53: =IF(C53=0,0,(H52+C53)) -> 1215950 | I53: =IF(C53=0,0,(I52+E53)) -> 977432.54 | J53: =H53-I53 -> 238517.46 | K53: =IFERROR(H53/I53,0) -> 1.2440245
B54: =B53+1 -> 45966 | C54: 76330 | D54: =$C$17 -> 221052.63 | E54: =$C$12 -> 146897.8 | F54: =C54-E54 -> -70567.804 | G54: =IFERROR(C54/E54,0) -> 0.51961294 | H54: =IF(C54=0,0,(H53+C54)) -> 1292280 | I54: =IF(C54=0,0,(I53+E54)) -> 1124330.3 | J54: =H54-I54 -> 167949.66 | K54: =IFERROR(H54/I54,0) -> 1.1493775
B55: =B54+1 -> 45967 | D55: 0 | F55: =C55-E55 -> 0 | G55: =IFERROR(C55/E55,0) -> 0 | H55: =IF(C55=0,0,(H54+C55)) -> 0 | I55: =IF(C55=0,0,(I54+E55)) -> 0 | J55: =H55-I55 -> 0 | K55: =IFERROR(H55/I55,0) -> 0
B56: =B55+1 -> 45968 | C56: 94600 | D56: =$C$17 -> 221052.63 | E56: =$C$7 -> 219995.68 | F56: =C56-E56 -> -125395.68 | G56: =IFERROR(C56/E56,0) -> 0.43000845 | H56: =IF(C56=0,0,(H55+C56)) -> 94600 | I56: =IF(C56=0,0,(I55+E56)) -> 219995.68 | J56: =H56-I56 -> -125395.68 | K56: =IFERROR(H56/I56,0) -> 0.43000845
B57: =B56+1 -> 45969 | C57: 283650 | D57: =$C$17 -> 221052.63 | E57: =$C$8 -> 192620.47 | F57: =C57-E57 -> 91029.529 | G57: =IFERROR(C57/E57,0) -> 1.4725849 | H57: =IF(C57=0,0,(H56+C57)) -> 378250 | I57: =IF(C57=0,0,(I56+E57)) -> 412616.15 | J57: =H57-I57 -> -34366.148 | K57: =IFERROR(H57/I57,0) -> 0.91671158
B58: =B57+1 -> 45970 | C58: 221610 | D58: =$C$17 -> 221052.63 | E58: =$C$9 -> 222098.1 | F58: =C58-E58 -> -488.10313 | G58: =IFERROR(C58/E58,0) -> 0.99780231 | H58: =IF(C58=0,0,(H57+C58)) -> 599860 | I58: =IF(C58=0,0,(I57+E58)) -> 634714.25 | J58: =H58-I58 -> -34854.251 | K58: =IFERROR(H58/I58,0) -> 0.9450867
B59: =B58+1 -> 45971 | D59: =$C$17 -> 221052.63 | E59: =$C$10 -> 216358.54 | F59: =C59-E59 -> -216358.54 | G59: =IFERROR(C59/E59,0) -> 0 | H59: =IF(C59=0,0,(H58+C59)) -> 0 | I59: =IF(C59=0,0,(I58+E59)) -> 0 | J59: =H59-I59 -> 0 | K59: =IFERROR(H59/I59,0) -> 0
B60: =B59+1 -> 45972 | D60: =$C$17 -> 221052.63 | E60: =$C$11 -> 346355.42 | F60: =C60-E60 -> -346355.42 | G60: =IFERROR(C60/E60,0) -> 0 | H60: =IF(C60=0,0,(H59+C60)) -> 0 | I60: =IF(C60=0,0,(I59+E60)) -> 0 | J60: =H60-I60 -> 0 | K60: =IFERROR(H60/I60,0) -> 0
B61: =B60+1 -> 45973 | D61: =$C$17 -> 221052.63 | E61: =$C$12 -> 146897.8 | F61: =C61-E61 -> -146897.8 | G61: =IFERROR(C61/E61,0) -> 0 | H61: =IF(C61=0,0,(H60+C61)) -> 0 | I61: =IF(C61=0,0,(I60+E61)) -> 0 | J61: =H61-I61 -> 0 | K61: =IFERROR(H61/I61,0) -> 0
B62: =B61+1 -> 45974 | D62: 0 | F62: =C62-E62 -> 0 | G62: =IFERROR(C62/E62,0) -> 0 | H62: =IF(C62=0,0,(H61+C62)) -> 0 | I62: =IF(C62=0,0,(I61+E62)) -> 0 | J62: =H62-I62 -> 0 | K62: =IFERROR(H62/I62,0) -> 0
B63: =B62+1 -> 45975 | D63: =$C$17 -> 221052.63 | E63: =$C$7 -> 219995.68 | F63: =C63-E63 -> -219995.68 | G63: =IFERROR(C63/E63,0) -> 0 | H63: =IF(C63=0,0,(H62+C63)) -> 0 | I63: =IF(C63=0,0,(I62+E63)) -> 0 | J63: =H63-I63 -> 0 | K63: =IFERROR(H63/I63,0) -> 0
B64: =B63+1 -> 45976 | D64: =$C$17 -> 221052.63 | E64: =$C$8 -> 192620.47 | F64: =C64-E64 -> -192620.47 | G64: =IFERROR(C64/E64,0) -> 0 | H64: =IF(C64=0,0,(H63+C64)) -> 0 | I64: =IF(C64=0,0,(I63+E64)) -> 0 | J64: =H64-I64 -> 0 | K64: =IFERROR(H64/I64,0) -> 0
B65: =B64+1 -> 45977 | D65: =$C$17 -> 221052.63 | E65: =$C$9 -> 222098.1 | F65: =C65-E65 -> -222098.1 | G65: =IFERROR(C65/E65,0) -> 0 | H65: =IF(C65=0,0,(H64+C65)) -> 0 | I65: =IF(C65=0,0,(I64+E65)) -> 0 | J65: =H65-I65 -> 0 | K65: =IFERROR(H65/I65,0) -> 0
B66: =B65+1 -> 45978 | D66: =$C$17 -> 221052.63 | E66: =$C$10 -> 216358.54 | F66: =C66-E66 -> -216358.54 | G66: =IFERROR(C66/E66,0) -> 0 | H66: =IF(C66=0,0,(H65+C66)) -> 0 | I66: =IF(C66=0,0,(I65+E66)) -> 0 | J66: =H66-I66 -> 0 | K66: =IFERROR(H66/I66,0) -> 0
B67: =B66+1 -> 45979 | D67: =$C$17 -> 221052.63 | E67: =$C$11 -> 346355.42 | F67: =C67-E67 -> -346355.42 | G67: =IFERROR(C67/E67,0) -> 0 | H67: =IF(C67=0,0,(H66+C67)) -> 0 | I67: =IF(C67=0,0,(I66+E67)) -> 0 | J67: =H67-I67 -> 0 | K67: =IFERROR(H67/I67,0) -> 0
B68: =B67+1 -> 45980 | D68: =$C$17 -> 221052.63 | E68: =$C$12 -> 146897.8 | F68: =C68-E68 -> -146897.8 | G68: =IFERROR(C68/E68,0) -> 0 | H68: =IF(C68=0,0,(H67+C68)) -> 0 | I68: =IF(C68=0,0,(I67+E68)) -> 0 | J68: =H68-I68 -> 0 | K68: =IFERROR(H68/I68,0) -> 0
B69: =B68+1 -> 45981 | D69: 0 | F69: =C69-E69 -> 0 | G69: =IFERROR(C69/E69,0) -> 0 | H69: =IF(C69=0,0,(H68+C69)) -> 0 | I69: =IF(C69=0,0,(I68+E69)) -> 0 | J69: =H69-I69 -> 0 | K69: =IFERROR(H69/I69,0) -> 0
B70: =B69+1 -> 45982 | D70: 0 | F70: =C70-E70 -> 0 | G70: =IFERROR(C70/E70,0) -> 0 | H70: =IF(C70=0,0,(H69+C70)) -> 0 | I70: =IF(C70=0,0,(I69+E70)) -> 0 | J70: =H70-I70 -> 0 | K70: =IFERROR(H70/I70,0) -> 0
B71: =B70+1 -> 45983 | D71: =$C$17 -> 221052.63 | E71: =$C$8 -> 192620.47 | F71: =C71-E71 -> -192620.47 | G71: =IFERROR(C71/E71,0) -> 0 | H71: =IF(C71=0,0,(H70+C71)) -> 0 | I71: =IF(C71=0,0,(I70+E71)) -> 0 | J71: =H71-I71 -> 0 | K71: =IFERROR(H71/I71,0) -> 0
B72: =B71+1 -> 45984 | D72: =$C$17 -> 221052.63 | E72: =$C$9 -> 222098.1 | F72: =C72-E72 -> -222098.1 | G72: =IFERROR(C72/E72,0) -> 0 | H72: =IF(C72=0,0,(H71+C72)) -> 0 | I72: =IF(C72=0,0,(I71+E72)) -> 0 | J72: =H72-I72 -> 0 | K72: =IFERROR(H72/I72,0) -> 0
B73: =B72+1 -> 45985 | D73: =$C$17 -> 221052.63 | E73: =$C$10 -> 216358.54 | F73: =C73-E73 -> -216358.54 | G73: =IFERROR(C73/E73,0) -> 0 | H73: =IF(C73=0,0,(H72+C73)) -> 0 | I73: =IF(C73=0,0,(I72+E73)) -> 0 | J73: =H73-I73 -> 0 | K73: =IFERROR(H73/I73,0) -> 0
B74: =B73+1 -> 45986 | D74: =$C$17 -> 221052.63 | E74: =$C$11 -> 346355.42 | F74: =C74-E74 -> -346355.42 | G74: =IFERROR(C74/E74,0) -> 0 | H74: =IF(C74=0,0,(H73+C74)) -> 0 | I74: =IF(C74=0,0,(I73+E74)) -> 0 | J74: =H74-I74 -> 0 | K74: =IFERROR(H74/I74,0) -> 0
B75: =B74+1 -> 45987 | D75: =$C$17 -> 221052.63 | E75: =$C$12 -> 146897.8 | F75: =C75-E75 -> -146897.8 | G75: =IFERROR(C75/E75,0) -> 0 | H75: =IF(C75=0,0,(H74+C75)) -> 0 | I75: =IF(C75=0,0,(I74+E75)) -> 0 | J75: =H75-I75 -> 0 | K75: =IFERROR(H75/I75,0) -> 0
B76: =B75+1 -> 45988 | D76: 0 | F76: =C76-E76 -> 0 | G76: =IFERROR(C76/E76,0) -> 0 | H76: =IF(C76=0,0,(H75+C76)) -> 0 | I76: =IF(C76=0,0,(I75+E76)) -> 0 | J76: =H76-I76 -> 0 | K76: =IFERROR(H76/I76,0) -> 0
B77: =B76+1 -> 45989 | D77: =$C$17 -> 221052.63 | E77: =$C$7 -> 219995.68 | F77: =C77-E77 -> -219995.68 | G77: =IFERROR(C77/E77,0) -> 0 | H77: =IF(C77=0,0,(H76+C77)) -> 0 | I77: =IF(C77=0,0,(I76+E77)) -> 0 | J77: =H77-I77 -> 0 | K77: =IFERROR(H77/I77,0) -> 0
B78: =B77+1 -> 45990 | D78: =$C$17 -> 221052.63 | E78: =$C$8 -> 192620.47 | F78: =C78-E78 -> -192620.47 | G78: =IFERROR(C78/E78,0) -> 0 | H78: =IF(C78=0,0,(H77+C78)) -> 0 | I78: =IF(C78=0,0,(I77+E78)) -> 0 | J78: =H78-I78 -> 0 | K78: =IFERROR(H78/I78,0) -> 0
B79: =B78+1 -> 45991 | D79: =$C$17 -> 221052.63 | E79: =$C$9 -> 222098.1 | F79: =C79-E79 -> -222098.1 | G79: =IFERROR(C79/E79,0) -> 0 | H79: =IF(C79=0,0,(H78+C79)) -> 0 | I79: =IF(C79=0,0,(I78+E79)) -> 0 | J79: =H79-I79 -> 0 | K79: =IFERROR(H79/I79,0) -> 0
B80: =B79+1 -> 45992 | D80: =$C$17 -> 221052.63 | E80: =$C$10 -> 216358.54 | F80: =C80-E80 -> -216358.54 | G80: =IFERROR(C80/E80,0) -> 0 | H80: =IF(C80=0,0,(H79+C80)) -> 0 | I80: =IF(C80=0,0,(I79+E80)) -> 0 | J80: =H80-I80 -> 0 | K80: =IFERROR(H80/I80,0) -> 0
C81: =SUM(C50:C80) -> 1892140 | D81: =SUM(D50:D80) -> 5747368.4 | E81: =SUM(E50:E80) -> 5788385.5
C82: =IFERROR(C81/D81,0) -> 0.3292185 | E82: =E81-F16 -> 704174.99

Sheet 下方修正案
C2: 実績売上額 | D2: 目標売上額 | E2: 達成率 | F2: 営業日数 | G2: 平均売上額
B3: 1月 | C3: 6112150 | D3: 5538461.5 | E3: =C3/D3 -> 1.1035826 | F3: 22 | G3: =C3/F3 -> 277825 | I3: =IF(H3=1,G3,"")
B4: 2月 | C4: 5368670 | D4: 4923076.9 | E4: =C4/D4 -> 1.0905111 | F4: 22 | G4: =C4/F4 -> 244030.45 | I4: =IF(H4=1,G4,"")
B5: 3月 | C5: 7189290 | D5: 7692307.7 | E5: =C5/D5 -> 0.9346077 | F5: 25 | G5: =C5/F5 -> 287571.6 | I5: =IF(H5=1,G5,"")
B6: 4月 | C6: 7232940 | D6: 7692307.7 | E6: =C6/D6 -> 0.9402822 | F6: 25 | G6: =C6/F6 -> 289317.6 | I6: =IF(H6=1,G6,"")
B7: 5月 | C7: 5931330 | D7: 5370629.4 | E7: =C7/D7 -> 1.1044013 | F7: 24 | G7: =C7/F7 -> 247138.75 | I7: =IF(H7=1,G7,"")
B8: 6月 | C8: 5714340 | D8: 5944055.9 | E8: =C8/D8 -> 0.96135367 | F8: 25 | G8: =C8/F8 -> 228573.6 | H8: 1 | I8: =IF(H8=1,G8,"") -> 228573.6
B9: 7月 | C9: 5338530 | D9: 6545454.5 | E9: =C9/D9 -> 0.81560875 | F9: 26 | G9: =C9/F9 -> 205328.08 | H9: 1 | I9: =IF(H9=1,G9,"") -> 205328.08
B10: 8月 | C10: 2414310 | D10: 5594405.6 | E10: =C10/D10 -> 0.43155791 | F10: 20 | G10: =C10/F10 -> 120715.5 | H10: 1 | I10: =IF(H10=1,G10,"") -> 120715.5
C11: =SUM(C3:C10) -> 45301560 | F11: =SUM(F3:F10) -> 189 | H11: 平均 | I11: =AVERAGE(I3:I10) -> 184872.39
B13: 9 月 | C13: =$I$11*F13 -> 4436937.4 | D13: 5663505.2 | E13: =C13/D13 -> 0.78342603 | F13: 24 | G13: =C13/F13 -> 184872.39
B14: 10月 | C14: =$I$11*F14 -> 4806682.2 | D14: 6749010.4 | E14: =C14/D14 -> 0.71220548 | F14: 26 | G14: =C14/F14 -> 184872.39
B15: 11月 | C15: =$I$11*F15 -> 4252065 | D15: 6513031 | E15: =C15/D15 -> 0.65285502 | F15: 23 | G15: =C15/F15 -> 184872.39
B16: 12月 | C16: =$I$11*F16 -> 4436937.4 | D16: 7079381.5 | E16: =C16/D16 -> 0.62674082 | F16: 24 | G16: =C16/F16 -> 184872.39
C17: =SUM(C13:C16) -> 17932622 | F17: =SUM(F13:F16) -> 97
F18: =F11+F17 -> 286
B19: 年間合計 | C19: =SUM(C3:C10,SUM(C13:C16)) -> 63234182
C20: =[2]★プラナバルカ戦略表!F29 -> 63000000 | D20: 75000000 | E20: 80000000
C21: =C19-C20 -> 234182.05 | D21: =C19-D20 -> -11765818 | E21: =C19-E20 -> -16765818

Sheet 目標_2025R7
B2: 45658 | E2: ①年間営業日 | G2: ②年間目標売上 | H2: 年間総売上％ | K2: 年間売上合計 | M2: 実質売上 | P2: 1月 | Q2: 2月 | R2: 3月 | S2: 4月 | T2: ←目標の月へジャンプ
E3: =SUM(F7:F18) -> 285 | G3: =★プラナバルカ戦略表!F29 -> 63000000 | H3: =SUM(AD7:AD18)*100 -> 0.999996 | I3: =G3*H3 -> 62999748 | K3: =SUM(J21:J385) -> 56787100 | M3: =K3-G3 -> -6212900 | P3: 5月 | Q3: 6月 | R3: 7月 | S3: 8月
M4: =AVERAGE(M7:M13) -> 6111675.7 | P4: 9月 | Q4: 10月 | R4: 11月 | S4: 12月
B6: 平均日次売上目標額 | E6: 月 | F6: 月次営業日数 | G6: 平均月間売上目標額 | H6: 月次繁閑期%設定 | I6: 月次目標売上 | K6: 日次目標売上 | M6: 月次売上実績 | N6: 月間KGI | P6: 月次平均%(繁閑期) | Q6: 月次実質%
B7: ② ÷ ① | E7: 1月 | F7: =COUNTIF(D21:D51,1) -> 22 | G7: =$B$8*F7 -> 4863157.9 | H7: 1.2 | I7: =G7*H7 -> 5835789.5 | K7: =I7/F7 -> 265263.16 | M7: =SUM(J21:J51) -> 6006630 | N7: =M7-I7 -> 170840.53 | P7: =M7/G7 -> 1.2351295 | Q7: =M7/I7 -> 1.0292746 | R7: 0.9 | AA7: =TEXT(K7,"¥0") -> ¥265263 | AC7: 1 | AD7: =(H7/100)*AE7 -> 0.000999996 | AE7: 0.083333
B8: =G3/E3 -> 221052.63 | E8: 2月 | F8: =COUNTIF(D52:D79,1) -> 22 | G8: =$B$8*F8 -> 4863157.9 | H8: 1 | I8: =G8*H8 -> 4863157.9 | K8: =I8/F8 -> 221052.63 | M8: =SUM(J52:J79) -> 5368670 | N8: =M8-I8 -> 505512.11 | P8: =M8/G8 -> 1.1039473 | Q8: =M8/I8 -> 1.1039473 | R8: 0.8 | AA8: =TEXT(K8,"¥0") -> ¥221053 | AC8: 2 | AD8: =(H8/100)*AE8 -> 0.00083333 | AE8: 0.083333
E9: 3月 | F9: =COUNTIF(D80:D110,1) -> 25 | G9: =$B$8*F9 -> 5526315.8 | H9: 1.3 | I9: =G9*H9 -> 7184210.5 | K9: =I9/F9 -> 287368.42 | M9: =SUM(J80:J110) -> 7189290 | N9: =M9-I9 -> 5079.4737 | P9: =M9/G9 -> 1.3009191 | Q9: =M9/I9 -> 1.000707 | R9: 1.1 | AA9: =TEXT(K9,"¥0") -> ¥287368 | AC9: 3 | AD9: =(H9/100)*AE9 -> 0.001083329 | AE9: 0.083333
E10: 4月 | F10: =COUNTIF(D111:D140,1) -> 25 | G10: =$B$8*F10 -> 5526315.8 | H10: 1.3 | I10: =G10*H10 -> 7184210.5 | K10: =I10/F10 -> 287368.42 | M10: =SUM(J111:J140) -> 7232940 | N10: =M10-I10 -> 48729.474 | P10: =M10/G10 -> 1.3088177 | Q10: =M10/I10 -> 1.0067829 | R10: 1.1 | AA10: =TEXT(K10,"¥0") -> ¥287368 | AC10: 4 | AD10: =(H10/100)*AE10 -> 0.001083329 | AE10: 0.083333
E11: 5月 | F11: =COUNTIF(D141:D171,1) -> 24 | G11: =$B$8*F11 -> 5305263.2 | H11: 1.1 | I11: =G11*H11 -> 5835789.5 | K11: =I11/F11 -> 243157.89 | M11: =SUM(J141:J171) -> 5931330 | N11: =M11-I11 -> 95540.526 | P11: =M11/G11 -> 1.1180086 | Q11: =M11/I11 -> 1.0163715 | R11: 0.8 | AA11: =TEXT(K11,"¥0") -> ¥243158 | AC11: 5 | AD11: =(H11/100)*AE11 -> 0.000916663 | AE11: 0.083333
E12: 6月 | F12: =COUNTIF(D172:D201,1) -> 25 | G12: =$B$8*F12 -> 5526315.8 | H12: 1.1 | I12: =G12*H12 -> 6078947.4 | K12: =I12/F12 -> 243157.89 | M12: =SUM(J172:J201) -> 5714340 | N12: =M12-I12 -> -364607.37 | P12: =M12/G12 -> 1.0340234 | Q12: =M12/I12 -> 0.9400213 | R12: 0.85 | AA12: =TEXT(K12,"¥0") -> ¥243158 | AC12: 6 | AD12: =(H12/100)*AE12 -> 0.000916663 | AE12: 0.083333
E13: 7月 | F13: =COUNTIF(D202:D232,1) -> 26 | G13: =$B$8*F13 -> 5747368.4 | H13: 0.9 | I13: =G13*H13 -> 5172631.6 | K13: =I13/F13 -> 198947.37 | M13: =SUM(J202:J232) -> 5338530 | N13: =M13-I13 -> 165898.42 | P13: =M13/G13 -> 0.92886511 | Q13: =M13/I13 -> 1.0320723 | R13: 0.9 | AA13: =TEXT(K13,"¥0") -> ¥198947 | AC13: 7 | AD13: =(H13/100)*AE13 -> 0.000749997 | AE13: 0.083333
E14: 8月 | F14: =COUNTIF(D233:D263,1) -> 20 | G14: =$B$8*F14 -> 4421052.6 | H14: 0.5 | I14: =G14*H14 -> 2210526.3 | K14: =I14/F14 -> 110526.32 | M14: =SUM(J233:J263) -> 2414310 | N14: =M14-I14 -> 203783.68 | P14: =M14/G14 -> 0.54609393 | Q14: =M14/I14 -> 1.0921879 | R14: 1 | AA14: =TEXT(K14,"¥0") -> ¥110526 | AC14: 8 | AD14: =(H14/100)*AE14 -> 0.000416665 | AE14: 0.083333
E15: 9 月 | F15: =COUNTIF(D264:D293,1) -> 23 | G15: =$B$8*F15 -> 5084210.5 | H15: 0.6 | I15: =G15*H15 -> 3050526.3 | K15: =I15/F15 -> 132631.58 | M15: =SUM(J264:J293) -> 3957920 | N15: =M15-I15 -> 907393.68 | P15: =M15/G15 -> 0.77847288 | Q15: =M15/I15 -> 1.2974548 | R15: 1 | AA15: =TEXT(K15,"¥0") -> ¥132632 | AC15: 9 | AD15: =(H15/100)*AE15 -> 0.000499998 | AE15: 0.083333
E16: 10月 | F16: =COUNTIF(D294:D324,1) -> 26 | G16: =$B$8*F16 -> 5747368.4 | H16: 0.9 | I16: =G16*H16 -> 5172631.6 | K16: =I16/F16 -> 198947.37 | M16: =SUM(J294:J324) -> 3844000 | N16: =M16-I16 -> -1328631.6 | P16: =M16/G16 -> 0.66882784 | Q16: =M16/I16 -> 0.74314204 | R16: 1.1 | AA16: =TEXT(K16,"¥0") -> ¥198947 | AC16: 10 | AD16: =(H16/100)*AE16 -> 0.000749997 | AE16: 0.083333
E17: 11月 | F17: =COUNTIF(D325:D354,1) -> 23 | G17: =$B$8*F17 -> 5084210.5 | H17: 1 | I17: =G17*H17 -> 5084210.5 | K17: =I17/F17 -> 221052.63 | M17: =SUM(J325:J354) -> 3789140 | N17: =M17-I17 -> -1295070.5 | P17: =M17/G17 -> 0.74527598 | Q17: =M17/I17 -> 0.74527598 | R17: 1.2 | AA17: =TEXT(K17,"¥0") -> ¥221053 | AC17: 11 | AD17: =(H17/100)*AE17 -> 0.00083333 | AE17: 0.083333
E18: 12月 | F18: =COUNTIF(D355:D385,1) -> 24 | G18: =$B$8*F18 -> 5305263.2 | H18: 1.1 | I18: =G18*H18 -> 5835789.5 | K18: =I18/F18 -> 243157.89 | M18: =SUM(J355:J385) -> 0 | N18: =M18-I18 -> -5835789.5 | P18: =M18/G18 -> 0 | Q18: =M18/I18 -> 0 | R18: 1.25 | AA18: =TEXT(K18,"¥0") -> ¥243158 | AC18: 12 | AD18: =(H18/100)*AE18 -> 0.000916663 | AE18: 0.083333
E20: 月 | F20: 日程 | G20: 曜日 | H20: 日祝日 | J20: Daily売上入力 | L20: 目標売上 | M20: 実質売上 | N20: 実質% | P20: 月次目標売上 | Q20: 月次実質売上 | R20: 月次差額 | S20: 月次達成率 | U20: 年次目標売上 | V20: 年次実質売上 | W20: 年次差額 | X20: 年次達成率 | AA20: 月 | AB20: 曜日 | AC20: 実質曜日平均売上 | AD20: 曜日回数 | AE20: 曜日毎目標売上額 | AF20: 曜日毎トータル額
C21: 1 | D21: 0 | E21: =MONTH(Y21) -> 1 | F21: =B2 -> 45658 | G21: =TEXT(Z21,"ddd") -> Wed | H21: 元旦 | L21: =IF(D21=0,0,IFERROR(SUMIFS($AE$21:$AE$104,$AA$21:$AA$104,$E21,$AB$21:$AB$104,$G21),0)) -> 0 | M21: =IF(D21=0,0,J21-L21) -> 0 | N21: =IFERROR(J21/L21,"¥0") -> ¥0 | P21: =IF(D21=0,0,$K$7) -> 0 | Q21: =IF(D21=0,0,$J$21) -> 0 | R21: =IF(D21=0,0,Q21-P21) -> 0 | S21: =IF(D21=0,0,Q21/P21) -> 0 | U21: =IF(D21=0,0,$L$21) -> 0 | V21: =IF(D21=0,0,$J$21) -> 0 | W21: =IF(D21=0,0,V21-U21) -> 0 | X21: =IF(D21=0,0,V21/U21) -> 0 | Y21: =B2 -> 45658 | Z21: =B2 -> 45658 | AA21: 1 | AB21: mon | AC21: =IFERROR(AVERAGEIFS(J21:J51,D21:D51,1,G21:G51,"mon"),0) -> 299840 | AD21: =COUNTIFS(D21:D51,1,G21:G51,"Mon") -> 3 | AE21: =($I$7*実績_2024R6!AI20)/AD21 -> 395153.16 | AF21: =AD21*AE21 -> 1185459.5 | AG21: 21〜51
C22: 2 | D22: 0 | E22: =MONTH(Y22) -> 1 | F22: =F21+1 -> 45659 | G22: =TEXT(Z22,"ddd") -> Thu | H22: 休み | L22: =IF(D22=0,0,IFERROR(SUMIFS($AE$21:$AE$104,$AA$21:$AA$104,$E22,$AB$21:$AB$104,$G22),0)) -> 0 | M22: =IF(D22=0,0,J22-L22) -> 0 | N22: =IFERROR(J22/L22,"¥0") -> ¥0 | P22: =IF(D22=0,0,SUM($L$21:L22)) -> 0 | Q22: =IF(D22=0,0,SUM($J$21:J22)) -> 0 | R22: =IF(D22=0,0,Q22-P22) -> 0 | S22: =IF(D22=0,0,Q22/P22) -> 0 | U22: =IF(D22=0,0,SUM($L$21:L22)) -> 0 | V22: =IF(D22=0,0,SUM($J$21:J22)) -> 0 | W22: =IF(D22=0,0,V22-U22) -> 0 | X22: =IF(D22=0,0,V22/U22) -> 0 | Y22: =Y21+1 -> 45659 | Z22: =Z21+1 -> 45659 | AA22: 1 | AB22: tue | AC22: =IFERROR(AVERAGEIFS(J21:J51,D21:D51,1,G21:G51,"tue"),0) -> 241427.5 | AD22: =COUNTIFS(D21:D51,1,G21:G51,"tue") -> 4 | AE22: =($I$7*実績_2024R6!AI21)/AD22 -> 251136.8 | AF22: =AD22*AE22 -> 1004547.2
C23: 3 | D23: 0 | E23: =MONTH(Y23) -> 1 | F23: =F22+1 -> 45660 | G23: =TEXT(Z23,"ddd") -> Fri | H23: 休み | L23: =IF(D23=0,0,IFERROR(SUMIFS($AE$21:$AE$104,$AA$21:$AA$104,$E23,$AB$21:$AB$104,$G23),0)) -> 0 | M23: =IF(D23=0,0,J23-L23) -> 0 | N23: =IFERROR(J23/L23,"¥0") -> ¥0 | P23: =IF(D23=0,0,SUM($L$21:L23)) -> 0 | Q23: =IF(D23=0,0,SUM($J$21:J23)) -> 0 | R23: =IF(D23=0,0,Q23-P23) -> 0 | S23: =IF(D23=0,0,Q23/P23) -> 0 | U23: =IF(D23=0,0,SUM($L$21:L23)) -> 0 | V23: =IF(D23=0,0,SUM($J$21:J23)) -> 0 | W23: =IF(D23=0,0,V23-U23) -> 0 | X23: =IF(D23=0,0,V23/U23) -> 0 | Y23: =Y22+1 -> 45660 | Z23: =Z22+1 -> 45660 | AA23: 1 | AB23: wed | AC23: =IFERROR(AVERAGEIFS(J21:J51,D21:D51,1,G21:G51,"wed"),0) -> 230592.5 | AD23: =COUNTIFS(D21:D51,1,G21:G51,"wed") -> 4 | AE23: =IFERROR(($I$7*実績_2024R6!AI22)/AD23,0) -> 282865.79 | AF23: =AD23*AE23 -> 1131463.2
C24: 4 | D24: 0 | E24: =MONTH(Y24) -> 1 | F24: =F23+1 -> 45661 | G24: =TEXT(Z24,"ddd") -> Sat | H24: 休み | L24: =IF(D24=0,0,IFERROR(SUMIFS($AE$21:$AE$104,$AA$21:$AA$104,$E24,$AB$21:$AB$104,$G24),0)) -> 0 | M24: =IF(D24=0,0,J24-L24) -> 0 | N24: =IFERROR(J24/L24,"¥0") -> ¥0 | P24: =IF(D24=0,0,SUM($L$21:L24)) -> 0 | Q24: =IF(D24=0,0,SUM($J$21:J24)) -> 0 | R24: =IF(D24=0,0,Q24-P24) -> 0 | S24: =IF(D24=0,0,Q24/P24) -> 0 | U24: =IF(D24=0,0,SUM($L$21:L24)) -> 0 | V24: =IF(D24=0,0,SUM($J$21:J24)) -> 0 | W24: =IF(D24=0,0,V24-U24) -> 0 | X24: =IF(D24=0,0,V24/U24) -> 0 | Y24: =Y23+1 -> 45661 | Z24: =Z23+1 -> 45661 | AA24: 1 | AB24: thu | AC24: =IFERROR(AVERAGEIFS(J21:J51,D21:D51,1,G21:G51,"thu"),0) -> 392675 | AD24: =COUNTIFS(D21:D51,1,G21:G51,"thu") -> 4 | AE24: =($I$7*実績_2024R6!AI23)/AD24 -> 196518.52 | AF24: =AD24*AE24 -> 786074.07
C25: 5 | D25: 0 | E25: =MONTH(Y25) -> 1 | F25: =F24+1 -> 45662 | G25: =TEXT(Z25,"ddd") -> Sun | H25: 日曜日 | L25: =IF(D25=0,0,IFERROR(SUMIFS($AE$21:$AE$104,$AA$21:$AA$104,$E25,$AB$21:$AB$104,$G25),0)) -> 0 | M25: =IF(D25=0,0,J25-L25) -> 0 | N25: =IFERROR(J25/L25,"¥0") -> ¥0 | P25: =IF(D25=0,0,SUM($L$21:L25)) -> 0 | Q25: =IF(D25=0,0,SUM($J$21:J25)) -> 0 | R25: =IF(D25=0,0,Q25-P25) -> 0 | S25: =IF(D25=0,0,Q25/P25) -> 0 | U25: =IF(D25=0,0,SUM($L$21:L25)) -> 0 | V25: =IF(D25=0,0,SUM($J$21:J25)) -> 0 | W25: =IF(D25=0,0,V25-U25) -> 0 | X25: =IF(D25=0,0,V25/U25) -> 0 | Y25: =Y24+1 -> 45662 | Z25: =Z24+1 -> 45662 | AA25: 1 | AB25: fri | AC25: =IFERROR(AVERAGEIFS(J21:J51,D21:D51,1,G21:G51,"fri"),0) -> 330490 | AD25: =COUNTIFS(D21:D51,1,G21:G51,"fri") -> 4 | AE25: =($I$7*実績_2024R6!AI24)/AD25 -> 343102.15 | AF25: =AD25*AE25 -> 1372408.6
C26: 6 | D26: 1 | E26: =MONTH(Y26) -> 1 | F26: =F25+1 -> 45663 | G26: =TEXT(Z26,"ddd") -> Mon | J26: 349800 | L26: =IF(D26=0,0,IFERROR(SUMIFS($AE$21:$AE$104,$AA$21:$AA$104,$E26,$AB$21:$AB$104,$G26),0)) -> 395153.16 | M26: =IF(D26=0,0,J26-L26) -> -45353.162 | N26: =IFERROR(J26/L26,"¥0") -> 0.88522637 | P26: =IF(D26=0,0,SUM($L$21:L26)) -> 395153.16 | Q26: =IF(D26=0,0,SUM($J$21:J26)) -> 349800 | R26: =IF(D26=0,0,Q26-P26) -> -45353.162 | S26: =IF(D26=0,0,Q26/P26) -> 0.88522637 | U26: =IF(D26=0,0,SUM($L$21:L26)) -> 395153.16 | V26: =IF(D26=0,0,SUM($J$21:J26)) -> 349800 | W26: =IF(D26=0,0,V26-U26) -> -45353.162 | X26: =IF(D26=0,0,V26/U26) -> 0.88522637 | Y26: =Y25+1 -> 45663 | Z26: =Z25+1 -> 45663 | AA26: 1 | AB26: sat | AC26: =IFERROR(AVERAGEIFS(J21:J51,D21:D51,1,G21:G51,"sat"),0) -> 108790 | AD26: =COUNTIFS(D21:D51,1,G21:G51,"sat") -> 3 | AE26: =($I$7*実績_2024R6!AI25)/AD26 -> 118612.32 | AF26: =AD26*AE26 -> 355836.96 | AG26: 1月目標売り上げ
C27: 7 | D27: 1 | E27: =MONTH(Y27) -> 1 | F27: =F26+1 -> 45664 | G27: =TEXT(Z27,"ddd") -> Tue | J27: 88530 | L27: =IF(D27=0,0,IFERROR(SUMIFS($AE$21:$AE$104,$AA$21:$AA$104,$E27,$AB$21:$AB$104,$G27),0)) -> 251136.8 | M27: =IF(D27=0,0,J27-L27) -> -162606.8 | N27: =IFERROR(J27/L27,"¥0") -> 0.35251704 | P27: =IF(D27=0,0,SUM($L$21:L27)) -> 646289.96 | Q27: =IF(D27=0,0,SUM($J$21:J27)) -> 438330 | R27: =IF(D27=0,0,Q27-P27) -> -207959.96 | S27: =IF(D27=0,0,Q27/P27) -> 0.67822499 | U27: =IF(D27=0,0,SUM($L$21:L27)) -> 646289.96 | V27: =IF(D27=0,0,SUM($J$21:J27)) -> 438330 | W27: =IF(D27=0,0,V27-U27) -> -207959.96 | X27: =IF(D27=0,0,V27/U27) -> 0.67822499 | Y27: =Y26+1 -> 45664 | Z27: =Z26+1 -> 45664 | AA27: 1 | AB27: sun | AC27: =IFERROR(AVERAGEIFS(J21:J51,D21:D51,1,G21:G51,"sun"),0) -> 0 | AD27: =IFERROR(COUNTIFS(D21:D51,1,G21:G51,"sun"),0) -> 0 | AE27: =IFERROR(($I$7*実績_2024R6!AI26)/AD27,0) -> 0 | AF27: =SUM(AF21:AF26) -> 5835789.5 | AG27: =I7 -> 5835789.5
C28: 8 | D28: 1 | E28: =MONTH(Y28) -> 1 | F28: =F27+1 -> 45665 | G28: =TEXT(Z28,"ddd") -> Wed | J28: 177630 | L28: =IF(D28=0,0,IFERROR(SUMIFS($AE$21:$AE$104,$AA$21:$AA$104,$E28,$AB$21:$AB$104,$G28),0)) -> 282865.79 | M28: =IF(D28=0,0,J28-L28) -> -105235.79 | N28: =IFERROR(J28/L28,"¥0") -> 0.62796565 | P28: =IF(D28=0,0,SUM($L$21:L28)) -> 929155.75 | Q28: =IF(D28=0,0,SUM($J$21:J28)) -> 615960 | R28: =IF(D28=0,0,Q28-P28) -> -313195.75 | S28: =IF(D28=0,0,Q28/P28) -> 0.66292438 | U28: =IF(D28=0,0,SUM($L$21:L28)) -> 929155.75 | V28: =IF(D28=0,0,SUM($J$21:J28)) -> 615960 | W28: =IF(D28=0,0,V28-U28) -> -313195.75 | X28: =IF(D28=0,0,V28/U28) -> 0.66292438 | Y28: =Y27+1 -> 45665 | Z28: =Z27+1 -> 45665 | AA28: 2 | AB28: Mon | AC28: =IFERROR(AVERAGEIFS(J52:J79,D52:D79,1,G52:G79,"mon"),0) -> 136670 | AD28: =COUNTIFS(D52:D79,1,G52:G79,"Mon") -> 3 | AE28: =($I$8*実績_2024R6!AI27)/AD28 -> 224838.76 | AF28: =AD28*AE28 -> 674516.28 | AG28: 52〜79
C29: 9 | D29: 1 | E29: =MONTH(Y29) -> 1 | F29: =F28+1 -> 45666 | G29: =TEXT(Z29,"ddd") -> Thu | J29: 376670 | L29: =IF(D29=0,0,IFERROR(SUMIFS($AE$21:$AE$104,$AA$21:$AA$104,$E29,$AB$21:$AB$104,$G29),0)) -> 196518.52 | M29: =IF(D29=0,0,J29-L29) -> 180151.48 | N29: =IFERROR(J29/L29,"¥0") -> 1.916715 | P29: =IF(D29=0,0,SUM($L$21:L29)) -> 1125674.3 | Q29: =IF(D29=0,0,SUM($J$21:J29)) -> 992630 | R29: =IF(D29=0,0,Q29-P29) -> -133044.27 | S29: =IF(D29=0,0,Q29/P29) -> 0.88180926 | U29: =IF(D29=0,0,SUM($L$21:L29)) -> 1125674.3 | V29: =IF(D29=0,0,SUM($J$21:J29)) -> 992630 | W29: =IF(D29=0,0,V29-U29) -> -133044.27 | X29: =IF(D29=0,0,V29/U29) -> 0.88180926 | Y29: =Y28+1 -> 45666 | Z29: =Z28+1 -> 45666 | AA29: 2 | AB29: Tue | AC29: =IFERROR(AVERAGEIFS(J53:J80,D53:D80,1,G53:G80,"tue"),0) -> 198143.33 | AD29: =COUNTIFS(D52:D79,1,G52:G79,"tue") -> 3 | AE29: =($I$8*実績_2024R6!AI28)/AD29 -> 277740.28 | AF29: =AD29*AE29 -> 833220.85
C30: 10 | D30: 1 | E30: =MONTH(Y30) -> 1 | F30: =F29+1 -> 45667 | G30: =TEXT(Z30,"ddd") -> Fri | J30: 377100 | L30: =IF(D30=0,0,IFERROR(SUMIFS($AE$21:$AE$104,$AA$21:$AA$104,$E30,$AB$21:$AB$104,$G30),0)) -> 343102.15 | M30: =IF(D30=0,0,J30-L30) -> 33997.852 | N30: =IFERROR(J30/L30,"¥0") -> 1.0990896 | P30: =IF(D30=0,0,SUM($L$21:L30)) -> 1468776.4 | Q30: =IF(D30=0,0,SUM($J$21:J30)) -> 1369730 | R30: =IF(D30=0,0,Q30-P30) -> -99046.418 | S30: =IF(D30=0,0,Q30/P30) -> 0.93256535 | U30: =IF(D30=0,0,SUM($L$21:L30)) -> 1468776.4 | V30: =IF(D30=0,0,SUM($J$21:J30)) -> 1369730 | W30: =IF(D30=0,0,V30-U30) -> -99046.418 | X30: =IF(D30=0,0,V30/U30) -> 0.93256535 | Y30: =Y29+1 -> 45667 | Z30: =Z29+1 -> 45667 | AA30: 2 | AB30: Wed | AC30: =IFERROR(AVERAGEIFS(J52:J79,D52:D79,1,G52:G79,"wed"),0) -> 268685 | AD30: =COUNTIFS(D52:D79,1,G52:G79,"wed") -> 4 | AE30: =($I$8*実績_2024R6!AI29)/AD30 -> 215570.54 | AF30: =AD30*AE30 -> 862282.17
C31: 11 | D31: 1 | E31: =MONTH(Y31) -> 1 | F31: =F30+1 -> 45668 | G31: =TEXT(Z31,"ddd") -> Sat | J31: 66550 | L31: =IF(D31=0,0,IFERROR(SUMIFS($AE$21:$AE$104,$AA$21:$AA$104,$E31,$AB$21:$AB$104,$G31),0)) -> 118612.32 | M31: =IF(D31=0,0,J31-L31) -> -52062.322 | N31: =IFERROR(J31/L31,"¥0") -> 0.56107156 | P31: =IF(D31=0,0,SUM($L$21:L31)) -> 1587388.7 | Q31: =IF(D31=0,0,SUM($J$21:J31)) -> 1436280 | R31: =IF(D31=0,0,Q31-P31) -> -151108.74 | S31: =IF(D31=0,0,Q31/P31) -> 0.90480672 | U31: =IF(D31=0,0,SUM($L$21:L31)) -> 1587388.7 | V31: =IF(D31=0,0,SUM($J$21:J31)) -> 1436280 | W31: =IF(D31=0,0,V31-U31) -> -151108.74 | X31: =IF(D31=0,0,V31/U31) -> 0.90480672 | Y31: =Y30+1 -> 45668 | Z31: =Z30+1 -> 45668 | AA31: 2 | AB31: Thu | AC31: =IFERROR(AVERAGEIFS(J52:J79,D52:D79,1,G52:G79,"thu"),0) -> 369147.5 | AD31: =COUNTIFS(D52:D79,1,G52:G79,"thu") -> 4 | AE31: =($I$8*実績_2024R6!AI30)/AD31 -> 283656.58 | AF31: =AD31*AE31 -> 1134626.3
C32: 12 | D32: 0 | E32: =MONTH(Y32) -> 1 | F32: =F31+1 -> 45669 | G32: =TEXT(Z32,"ddd") -> Sun | H32: 日曜日 | L32: =IF(D32=0,0,IFERROR(SUMIFS($AE$21:$AE$104,$AA$21:$AA$104,$E32,$AB$21:$AB$104,$G32),0)) -> 0 | M32: =IF(D32=0,0,J32-L32) -> 0 | N32: =IFERROR(J32/L32,"¥0") -> ¥0 | P32: =IF(D32=0,0,SUM($L$21:L32)) -> 0 | Q32: =IF(D32=0,0,SUM($J$21:J32)) -> 0 | R32: =IF(D32=0,0,Q32-P32) -> 0 | S32: =IF(D32=0,0,Q32/P32) -> 0 | U32: =IF(D32=0,0,SUM($L$21:L32)) -> 0 | V32: =IF(D32=0,0,SUM($J$21:J32)) -> 0 | W32: =IF(D32=0,0,V32-U32) -> 0 | X32: =IF(D32=0,0,V32/U32) -> 0 | Y32: =Y31+1 -> 45669 | Z32: =Z31+1 -> 45669 | AA32: 2 | AB32: Fri | AC32: =IFERROR(AVERAGEIFS(J52:J79,D52:D79,1,G52:G79,"fri"),0) -> 310005 | AD32: =COUNTIFS(D52:D79,1,G52:G79,"fri") -> 4 | AE32: =($I$8*実績_2024R6!AI31)/AD32 -> 207016.95 | AF32: =AD32*AE32 -> 828067.79
C33: 13 | D33: 0 | E33: =MONTH(Y33) -> 1 | F33: =F32+1 -> 45670 | G33: =TEXT(Z33,"ddd") -> Mon | H33: 成人の日 | L33: =IF(D33=0,0,IFERROR(SUMIFS($AE$21:$AE$104,$AA$21:$AA$104,$E33,$AB$21:$AB$104,$G33),0)) -> 0 | M33: =IF(D33=0,0,J33-L33) -> 0 | N33: =IFERROR(J33/L33,"¥0") -> ¥0 | P33: =IF(D33=0,0,SUM($L$21:L33)) -> 0 | Q33: =IF(D33=0,0,SUM($J$21:J33)) -> 0 | R33: =IF(D33=0,0,Q33-P33) -> 0 | S33: =IF(D33=0,0,Q33/P33) -> 0 | U33: =IF(D33=0,0,SUM($L$21:L33)) -> 0 | V33: =IF(D33=0,0,SUM($J$21:J33)) -> 0 | W33: =IF(D33=0,0,V33-U33) -> 0 | X33: =IF(D33=0,0,V33/U33) -> 0 | Y33: =Y32+1 -> 45670 | Z33: =Z32+1 -> 45670 | AA33: 2 | AB33: Sat | AC33: =IFERROR(AVERAGEIFS(J52:J79,D52:D79,1,G52:G79,"sat"),0) -> 143220 | AD33: =COUNTIFS(D52:D79,1,G52:G79,"sat") -> 4 | AE33: =($I$8*実績_2024R6!AI32)/AD33 -> 132611.12 | AF33: =AD33*AE33 -> 530444.47 | AG33: 2月目標売り上げ
C34: 14 | D34: 1 | E34: =MONTH(Y34) -> 1 | F34: =F33+1 -> 45671 | G34: =TEXT(Z34,"ddd") -> Tue | J34: 372310 | L34: =IF(D34=0,0,IFERROR(SUMIFS($AE$21:$AE$104,$AA$21:$AA$104,$E34,$AB$21:$AB$104,$G34),0)) -> 251136.8 | M34: =IF(D34=0,0,J34-L34) -> 121173.2 | N34: =IFERROR(J34/L34,"¥0") -> 1.4824988 | P34: =IF(D34=0,0,SUM($L$21:L34)) -> 1838525.5 | Q34: =IF(D34=0,0,SUM($J$21:J34)) -> 1808590 | R34: =IF(D34=0,0,Q34-P34) -> -29935.538 | S34: =IF(D34=0,0,Q34/P34) -> 0.98371764 | U34: =IF(D34=0,0,SUM($L$21:L34)) -> 1838525.5 | V34: =IF(D34=0,0,SUM($J$21:J34)) -> 1808590 | W34: =IF(D34=0,0,V34-U34) -> -29935.538 | X34: =IF(D34=0,0,V34/U34) -> 0.98371764 | Y34: =Y33+1 -> 45671 | Z34: =Z33+1 -> 45671 | AA34: 2 | AB34: Sun | AC34: =IFERROR(AVERAGEIFS(J52:J79,D52:D79,1,G52:G79,"sun"),0) -> 0 | AD34: =IFERROR(COUNTIFS(D52:D79,1,G52:G79,"sun"),0) -> 0 | AE34: =IFERROR(($I$8*実績_2024R6!AI33)/AD34,0) -> 0 | AF34: =SUM(AF28:AF33) -> 4863157.9 | AG34: =I8 -> 4863157.9
C35: 15 | D35: 1 | E35: =MONTH(Y35) -> 1 | F35: =F34+1 -> 45672 | G35: =TEXT(Z35,"ddd") -> Wed | J35: 246200 | L35: =IF(D35=0,0,IFERROR(SUMIFS($AE$21:$AE$104,$AA$21:$AA$104,$E35,$AB$21:$AB$104,$G35),0)) -> 282865.79 | M35: =IF(D35=0,0,J35-L35) -> -36665.79 | N35: =IFERROR(J35/L35,"¥0") -> 0.87037743 | P35: =IF(D35=0,0,SUM($L$21:L35)) -> 2121391.3 | Q35: =IF(D35=0,0,SUM($J$21:J35)) -> 2054790 | R35: =IF(D35=0,0,Q35-P35) -> -66601.328 | S35: =IF(D35=0,0,Q35/P35) -> 0.96860488 | U35: =IF(D35=0,0,SUM($L$21:L35)) -> 2121391.3 | V35: =IF(D35=0,0,SUM($J$21:J35)) -> 2054790 | W35: =IF(D35=0,0,V35-U35) -> -66601.328 | X35: =IF(D35=0,0,V35/U35) -> 0.96860488 | Y35: =Y34+1 -> 45672 | Z35: =Z34+1 -> 45672 | AA35: 3 | AB35: Mon | AC35: =IFERROR(AVERAGEIFS(J80:J110,D80:D110,1,G80:G110,"mon"),0) -> 199934 | AD35: =COUNTIFS(D80:D110,1,G80:G110,"Mon") -> 5 | AE35: =($I$9*実績_2024R6!AI34)/AD35 -> 203685.45 | AF35: =AD35*AE35 -> 1018427.2 | AG35: 80〜110
C36: 16 | D36: 1 | E36: =MONTH(Y36) -> 1 | F36: =F35+1 -> 45673 | G36: =TEXT(Z36,"ddd") -> Thu | J36: 400950 | L36: =IF(D36=0,0,IFERROR(SUMIFS($AE$21:$AE$104,$AA$21:$AA$104,$E36,$AB$21:$AB$104,$G36),0)) -> 196518.52 | M36: =IF(D36=0,0,J36-L36) -> 204431.48 | N36: =IFERROR(J36/L36,"¥0") -> 2.0402657 | P36: =IF(D36=0,0,SUM($L$21:L36)) -> 2317909.8 | Q36: =IF(D36=0,0,SUM($J$21:J36)) -> 2455740 | R36: =IF(D36=0,0,Q36-P36) -> 137830.15 | S36: =IF(D36=0,0,Q36/P36) -> 1.0594631 | U36: =IF(D36=0,0,SUM($L$21:L36)) -> 2317909.8 | V36: =IF(D36=0,0,SUM($J$21:J36)) -> 2455740 | W36: =IF(D36=0,0,V36-U36) -> 137830.15 | X36: =IF(D36=0,0,V36/U36) -> 1.0594631 | Y36: =Y35+1 -> 45673 | Z36: =Z35+1 -> 45673 | AA36: 3 | AB36: Tue | AC36: =IFERROR(AVERAGEIFS(J80:J110,D80:D110,1,G80:G110,"tue"),0) -> 314582.5 | AD36: =COUNTIFS(D80:D110,1,G80:G110,"tue") -> 4 | AE36: =($I$9*実績_2024R6!AI35)/AD36 -> 293532.45 | AF36: =AD36*AE36 -> 1174129.8
C37: 17 | D37: 1 | E37: =MONTH(Y37) -> 1 | F37: =F36+1 -> 45674 | G37: =TEXT(Z37,"ddd") -> Fri | J37: 262380 | L37: =IF(D37=0,0,IFERROR(SUMIFS($AE$21:$AE$104,$AA$21:$AA$104,$E37,$AB$21:$AB$104,$G37),0)) -> 343102.15 | M37: =IF(D37=0,0,J37-L37) -> -80722.148 | N37: =IFERROR(J37/L37,"¥0") -> 0.76472853 | P37: =IF(D37=0,0,SUM($L$21:L37)) -> 2661012 | Q37: =IF(D37=0,0,SUM($J$21:J37)) -> 2718120 | R37: =IF(D37=0,0,Q37-P37) -> 57108.005 | S37: =IF(D37=0,0,Q37/P37) -> 1.021461 | U37: =IF(D37=0,0,SUM($L$21:L37)) -> 2661012 | V37: =IF(D37=0,0,SUM($J$21:J37)) -> 2718120 | W37: =IF(D37=0,0,V37-U37) -> 57108.005 | X37: =IF(D37=0,0,V37/U37) -> 1.021461 | Y37: =Y36+1 -> 45674 | Z37: =Z36+1 -> 45674 | AA37: 3 | AB37: Wed | AC37: =IFERROR(AVERAGEIFS(J80:J110,D80:D110,1,G80:G110,"wed"),0) -> 355035 | AD37: =COUNTIFS(D80:D110,1,G80:G110,"wed") -> 4 | AE37: =($I$9*実績_2024R6!AI36)/AD37 -> 245154.79 | AF37: =AD37*AE37 -> 980619.17
C38: 18 | D38: 1 | E38: =MONTH(Y38) -> 1 | F38: =F37+1 -> 45675 | G38: =TEXT(Z38,"ddd") -> Sat | J38: 137800 | L38: =IF(D38=0,0,IFERROR(SUMIFS($AE$21:$AE$104,$AA$21:$AA$104,$E38,$AB$21:$AB$104,$G38),0)) -> 118612.32 | M38: =IF(D38=0,0,J38-L38) -> 19187.678 | N38: =IFERROR(J38/L38,"¥0") -> 1.161768 | P38: =IF(D38=0,0,SUM($L$21:L38)) -> 2779624.3 | Q38: =IF(D38=0,0,SUM($J$21:J38)) -> 2855920 | R38: =IF(D38=0,0,Q38-P38) -> 76295.684 | S38: =IF(D38=0,0,Q38/P38) -> 1.0274482 | U38: =IF(D38=0,0,SUM($L$21:L38)) -> 2779624.3 | V38: =IF(D38=0,0,SUM($J$21:J38)) -> 2855920 | W38: =IF(D38=0,0,V38-U38) -> 76295.684 | X38: =IF(D38=0,0,V38/U38) -> 1.0274482 | Y38: =Y37+1 -> 45675 | Z38: =Z37+1 -> 45675 | AA38: 3 | AB38: Thu | AC38: =IFERROR(AVERAGEIFS(J80:J110,D80:D110,1,G80:G110,"thu"),0) -> 355676.67 | AD38: =COUNTIFS(D80:D110,1,G80:G110,"thu") -> 3 | AE38: =($I$9*実績_2024R6!AI37)/AD38 -> 457562.97 | AF38: =AD38*AE38 -> 1372688.9
C39: 19 | D39: 0 | E39: =MONTH(Y39) -> 1 | F39: =F38+1 -> 45676 | G39: =TEXT(Z39,"ddd") -> Sun | L39: =IF(D39=0,0,IFERROR(SUMIFS($AE$21:$AE$104,$AA$21:$AA$104,$E39,$AB$21:$AB$104,$G39),0)) -> 0 | M39: =IF(D39=0,0,J39-L39) -> 0 | N39: =IFERROR(J39/L39,"¥0") -> ¥0 | P39: =IF(D39=0,0,SUM($L$21:L39)) -> 0 | Q39: =IF(D39=0,0,SUM($J$21:J39)) -> 0 | R39: =IF(D39=0,0,Q39-P39) -> 0 | S39: =IF(D39=0,0,Q39/P39) -> 0 | U39: =IF(D39=0,0,SUM($L$21:L39)) -> 0 | V39: =IF(D39=0,0,SUM($J$21:J39)) -> 0 | W39: =IF(D39=0,0,V39-U39) -> 0 | X39: =IF(D39=0,0,V39/U39) -> 0 | Y39: =Y38+1 -> 45676 | Z39: =Z38+1 -> 45676 | AA39: 3 | AB39: Fri | AC39: =IFERROR(AVERAGEIFS(J80:J110,D80:D110,1,G80:G110,"fri"),0) -> 406890 | AD39: =COUNTIFS(D80:D110,1,G80:G110,"fri") -> 4 | AE39: =($I$9*実績_2024R6!AI38)/AD39 -> 448451.04 | AF39: =AD39*AE39 -> 1793804.2
C40: 20 | D40: 1 | E40: =MONTH(Y40) -> 1 | F40: =F39+1 -> 45677 | G40: =TEXT(Z40,"ddd") -> Mon | J40: 265910 | L40: =IF(D40=0,0,IFERROR(SUMIFS($AE$21:$AE$104,$AA$21:$AA$104,$E40,$AB$21:$AB$104,$G40),0)) -> 395153.16 | M40: =IF(D40=0,0,J40-L40) -> -129243.16 | N40: =IFERROR(J40/L40,"¥0") -> 0.67292894 | P40: =IF(D40=0,0,SUM($L$21:L40)) -> 3174777.5 | Q40: =IF(D40=0,0,SUM($J$21:J40)) -> 3121830 | R40: =IF(D40=0,0,Q40-P40) -> -52947.479 | S40: =IF(D40=0,0,Q40/P40) -> 0.98332246 | U40: =IF(D40=0,0,SUM($L$21:L40)) -> 3174777.5 | V40: =IF(D40=0,0,SUM($J$21:J40)) -> 3121830 | W40: =IF(D40=0,0,V40-U40) -> -52947.479 | X40: =IF(D40=0,0,V40/U40) -> 0.98332246 | Y40: =Y39+1 -> 45677 | Z40: =Z39+1 -> 45677 | AA40: 3 | AB40: Sat | AC40: =IFERROR(AVERAGEIFS(J80:J110,D80:D110,1,G80:G110,"sat"),0) -> 163312 | AD40: =COUNTIFS(D80:D110,1,G80:G110,"sat") -> 5 | AE40: =($I$9*実績_2024R6!AI39)/AD40 -> 168908.25 | AF40: =AD40*AE40 -> 844541.23 | AG40: 3月目標売り上げ
C41: 21 | D41: 1 | E41: =MONTH(Y41) -> 1 | F41: =F40+1 -> 45678 | G41: =TEXT(Z41,"ddd") -> Tue | J41: 175950 | L41: =IF(D41=0,0,IFERROR(SUMIFS($AE$21:$AE$104,$AA$21:$AA$104,$E41,$AB$21:$AB$104,$G41),0)) -> 251136.8 | M41: =IF(D41=0,0,J41-L41) -> -75186.799 | N41: =IFERROR(J41/L41,"¥0") -> 0.70061417 | P41: =IF(D41=0,0,SUM($L$21:L41)) -> 3425914.3 | Q41: =IF(D41=0,0,SUM($J$21:J41)) -> 3297780 | R41: =IF(D41=0,0,Q41-P41) -> -128134.28 | S41: =IF(D41=0,0,Q41/P41) -> 0.96259852 | U41: =IF(D41=0,0,SUM($L$21:L41)) -> 3425914.3 | V41: =IF(D41=0,0,SUM($J$21:J41)) -> 3297780 | W41: =IF(D41=0,0,V41-U41) -> -128134.28 | X41: =IF(D41=0,0,V41/U41) -> 0.96259852 | Y41: =Y40+1 -> 45678 | Z41: =Z40+1 -> 45678 | AA41: 3 | AB41: Sun | AC41: =IFERROR(AVERAGEIFS(J80:J110,D80:D110,1,G80:G110,"sun"),0) -> 0 | AD41: =IFERROR(COUNTIFS(D80:D110,1,G80:G110,"sun"),0) -> 0 | AE41: =IFERROR(($I$9*実績_2024R6!AI40)/AD41,0) -> 0 | AF41: =SUM(AF35:AF40) -> 7184210.5 | AG41: =I9 -> 7184210.5
C42: 22 | D42: 1 | E42: =MONTH(Y42) -> 1 | F42: =F41+1 -> 45679 | G42: =TEXT(Z42,"ddd") -> Wed | J42: 262170 | L42: =IF(D42=0,0,IFERROR(SUMIFS($AE$21:$AE$104,$AA$21:$AA$104,$E42,$AB$21:$AB$104,$G42),0)) -> 282865.79 | M42: =IF(D42=0,0,J42-L42) -> -20695.79 | N42: =IFERROR(J42/L42,"¥0") -> 0.9268353 | P42: =IF(D42=0,0,SUM($L$21:L42)) -> 3708780.1 | Q42: =IF(D42=0,0,SUM($J$21:J42)) -> 3559950 | R42: =IF(D42=0,0,Q42-P42) -> -148830.07 | S42: =IF(D42=0,0,Q42/P42) -> 0.95987088 | U42: =IF(D42=0,0,SUM($L$21:L42)) -> 3708780.1 | V42: =IF(D42=0,0,SUM($J$21:J42)) -> 3559950 | W42: =IF(D42=0,0,V42-U42) -> -148830.07 | X42: =IF(D42=0,0,V42/U42) -> 0.95987088 | Y42: =Y41+1 -> 45679 | Z42: =Z41+1 -> 45679 | AA42: 4 | AB42: Mon | AC42: =IFERROR(AVERAGEIFS(J111:J140,D111:D140,1,G111:G140,"mon"),0) -> 244835 | AD42: =COUNTIFS(D111:D140,1,G111:G140,"Mon") -> 4 | AE42: =($I$10*実績_2024R6!AI41)/AD42 -> 245725.1 | AF42: =AD42*AE42 -> 982900.42 | AG42: 111〜140
C43: 23 | D43: 1 | E43: =MONTH(Y43) -> 1 | F43: =F42+1 -> 45680 | G43: =TEXT(Z43,"ddd") -> Thu | J43: 342980 | L43: =IF(D43=0,0,IFERROR(SUMIFS($AE$21:$AE$104,$AA$21:$AA$104,$E43,$AB$21:$AB$104,$G43),0)) -> 196518.52 | M43: =IF(D43=0,0,J43-L43) -> 146461.48 | N43: =IFERROR(J43/L43,"¥0") -> 1.7452808 | P43: =IF(D43=0,0,SUM($L$21:L43)) -> 3905298.6 | Q43: =IF(D43=0,0,SUM($J$21:J43)) -> 3902930 | R43: =IF(D43=0,0,Q43-P43) -> -2368.5864 | S43: =IF(D43=0,0,Q43/P43) -> 0.99939349 | U43: =IF(D43=0,0,SUM($L$21:L43)) -> 3905298.6 | V43: =IF(D43=0,0,SUM($J$21:J43)) -> 3902930 | W43: =IF(D43=0,0,V43-U43) -> -2368.5864 | X43: =IF(D43=0,0,V43/U43) -> 0.99939349 | Y43: =Y42+1 -> 45680 | Z43: =Z42+1 -> 45680 | AA43: 4 | AB43: Tue | AC43: =IFERROR(AVERAGEIFS(J111:J140,D111:D140,1,G111:G140,"tue"),0) -> 270190 | AD43: =COUNTIFS(D111:D140,1,G111:G140,"tue") -> 4 | AE43: =($I$10*実績_2024R6!AI42)/AD43 -> 362897.4 | AF43: =AD43*AE43 -> 1451589.6
C44: 24 | D44: 1 | E44: =MONTH(Y44) -> 1 | F44: =F43+1 -> 45681 | G44: =TEXT(Z44,"ddd") -> Fri | J44: 330440 | L44: =IF(D44=0,0,IFERROR(SUMIFS($AE$21:$AE$104,$AA$21:$AA$104,$E44,$AB$21:$AB$104,$G44),0)) -> 343102.15 | M44: =IF(D44=0,0,J44-L44) -> -12662.148 | N44: =IFERROR(J44/L44,"¥0") -> 0.96309511 | P44: =IF(D44=0,0,SUM($L$21:L44)) -> 4248400.7 | Q44: =IF(D44=0,0,SUM($J$21:J44)) -> 4233370 | R44: =IF(D44=0,0,Q44-P44) -> -15030.734 | S44: =IF(D44=0,0,Q44/P44) -> 0.99646203 | U44: =IF(D44=0,0,SUM($L$21:L44)) -> 4248400.7 | V44: =IF(D44=0,0,SUM($J$21:J44)) -> 4233370 | W44: =IF(D44=0,0,V44-U44) -> -15030.734 | X44: =IF(D44=0,0,V44/U44) -> 0.99646203 | Y44: =Y43+1 -> 45681 | Z44: =Z43+1 -> 45681 | AA44: 4 | AB44: Wed | AC44: =IFERROR(AVERAGEIFS(J111:J140,D111:D140,1,G111:G140,"wed"),0) -> 301842 | AD44: =COUNTIFS(D111:D140,1,G111:G140,"wed") -> 5 | AE44: =($I$10*実績_2024R6!AI43)/AD44 -> 251969.24 | AF44: =AD44*AE44 -> 1259846.2
C45: 25 | D45: 1 | E45: =MONTH(Y45) -> 1 | F45: =F44+1 -> 45682 | G45: =TEXT(Z45,"ddd") -> Sat | J45: 122020 | L45: =IF(D45=0,0,IFERROR(SUMIFS($AE$21:$AE$104,$AA$21:$AA$104,$E45,$AB$21:$AB$104,$G45),0)) -> 118612.32 | M45: =IF(D45=0,0,J45-L45) -> 3407.6784 | N45: =IFERROR(J45/L45,"¥0") -> 1.0287295 | P45: =IF(D45=0,0,SUM($L$21:L45)) -> 4367013.1 | Q45: =IF(D45=0,0,SUM($J$21:J45)) -> 4355390 | R45: =IF(D45=0,0,Q45-P45) -> -11623.056 | S45: =IF(D45=0,0,Q45/P45) -> 0.99733844 | U45: =IF(D45=0,0,SUM($L$21:L45)) -> 4367013.1 | V45: =IF(D45=0,0,SUM($J$21:J45)) -> 4355390 | W45: =IF(D45=0,0,V45-U45) -> -11623.056 | X45: =IF(D45=0,0,V45/U45) -> 0.99733844 | Y45: =Y44+1 -> 45682 | Z45: =Z44+1 -> 45682 | AA45: 4 | AB45: Thu | AC45: =IFERROR(AVERAGEIFS(J111:J140,D111:D140,1,G111:G140,"thu"),0) -> 335847.5 | AD45: =COUNTIFS(D111:D140,1,G111:G140,"thu") -> 4 | AE45: =($I$10*実績_2024R6!AI44)/AD45 -> 299179.04 | AF45: =AD45*AE45 -> 1196716.2
C46: 26 | D46: 0 | E46: =MONTH(Y46) -> 1 | F46: =F45+1 -> 45683 | G46: =TEXT(Z46,"ddd") -> Sun | L46: =IF(D46=0,0,IFERROR(SUMIFS($AE$21:$AE$104,$AA$21:$AA$104,$E46,$AB$21:$AB$104,$G46),0)) -> 0 | M46: =IF(D46=0,0,J46-L46) -> 0 | N46: =IFERROR(J46/L46,"¥0") -> ¥0 | P46: =IF(D46=0,0,SUM($L$21:L46)) -> 0 | Q46: =IF(D46=0,0,SUM($J$21:J46)) -> 0 | R46: =IF(D46=0,0,Q46-P46) -> 0 | S46: =IF(D46=0,0,Q46/P46) -> 0 | U46: =IF(D46=0,0,SUM($L$21:L46)) -> 0 | V46: =IF(D46=0,0,SUM($J$21:J46)) -> 0 | W46: =IF(D46=0,0,V46-U46) -> 0 | X46: =IF(D46=0,0,V46/U46) -> 0 | Y46: =Y45+1 -> 45683 | Z46: =Z45+1 -> 45683 | AA46: 4 | AB46: Fri | AC46: =IFERROR(AVERAGEIFS(J111:J140,D111:D140,1,G111:G140,"fri"),0) -> 419375 | AD46: =COUNTIFS(D111:D140,1,G111:G140,"fri") -> 4 | AE46: =($I$10*実績_2024R6!AI45)/AD46 -> 356302.21 | AF46: =AD46*AE46 -> 1425208.8
C47: 27 | D47: 1 | E47: =MONTH(Y47) -> 1 | F47: =F46+1 -> 45684 | G47: =TEXT(Z47,"ddd") -> Mon | J47: 283810 | L47: =IF(D47=0,0,IFERROR(SUMIFS($AE$21:$AE$104,$AA$21:$AA$104,$E47,$AB$21:$AB$104,$G47),0)) -> 395153.16 | M47: =IF(D47=0,0,J47-L47) -> -111343.16 | N47: =IFERROR(J47/L47,"¥0") -> 0.71822783 | P47: =IF(D47=0,0,SUM($L$21:L47)) -> 4762166.2 | Q47: =IF(D47=0,0,SUM($J$21:J47)) -> 4639200 | R47: =IF(D47=0,0,Q47-P47) -> -122966.22 | S47: =IF(D47=0,0,Q47/P47) -> 0.97417851 | U47: =IF(D47=0,0,SUM($L$21:L47)) -> 4762166.2 | V47: =IF(D47=0,0,SUM($J$21:J47)) -> 4639200 | W47: =IF(D47=0,0,V47-U47) -> -122966.22 | X47: =IF(D47=0,0,V47/U47) -> 0.97417851 | Y47: =Y46+1 -> 45684 | Z47: =Z46+1 -> 45684 | AA47: 4 | AB47: Sat | AC47: =IFERROR(AVERAGEIFS(J111:J140,D111:D140,1,G111:G140,"sat"),0) -> 160685 | AD47: =COUNTIFS(D111:D140,1,G111:G140,"sat") -> 4 | AE47: =($I$10*実績_2024R6!AI46)/AD47 -> 216987.32 | AF47: =AD47*AE47 -> 867949.3 | AG47: 4月目標売り上げ
C48: 28 | D48: 1 | E48: =MONTH(Y48) -> 1 | F48: =F47+1 -> 45685 | G48: =TEXT(Z48,"ddd") -> Tue | J48: 328920 | L48: =IF(D48=0,0,IFERROR(SUMIFS($AE$21:$AE$104,$AA$21:$AA$104,$E48,$AB$21:$AB$104,$G48),0)) -> 251136.8 | M48: =IF(D48=0,0,J48-L48) -> 77783.201 | N48: =IFERROR(J48/L48,"¥0") -> 1.3097244 | P48: =IF(D48=0,0,SUM($L$21:L48)) -> 5013303 | Q48: =IF(D48=0,0,SUM($J$21:J48)) -> 4968120 | R48: =IF(D48=0,0,Q48-P48) -> -45183.017 | S48: =IF(D48=0,0,Q48/P48) -> 0.99098738 | U48: =IF(D48=0,0,SUM($L$21:L48)) -> 5013303 | V48: =IF(D48=0,0,SUM($J$21:J48)) -> 4968120 | W48: =IF(D48=0,0,V48-U48) -> -45183.017 | X48: =IF(D48=0,0,V48/U48) -> 0.99098738 | Y48: =Y47+1 -> 45685 | Z48: =Z47+1 -> 45685 | AA48: 4 | AB48: Sun | AC48: =IFERROR(AVERAGEIFS(J111:J140,D111:D140,1,G111:G140,"sun"),0) -> 0 | AD48: =IFERROR(COUNTIFS(D111:D140,1,G111:G140,"sun"),0) -> 0 | AE48: =IFERROR(($I$10*実績_2024R6!AI47)/AD48,0) -> 0 | AF48: =SUM(AF42:AF47) -> 7184210.5 | AG48: =I10 -> 7184210.5
C49: 29 | D49: 1 | E49: =MONTH(Y49) -> 1 | F49: =F48+1 -> 45686 | G49: =TEXT(Z49,"ddd") -> Wed | J49: 236370 | L49: =IF(D49=0,0,IFERROR(SUMIFS($AE$21:$AE$104,$AA$21:$AA$104,$E49,$AB$21:$AB$104,$G49),0)) -> 282865.79 | M49: =IF(D49=0,0,J49-L49) -> -46495.79 | N49: =IFERROR(J49/L49,"¥0") -> 0.83562597 | P49: =IF(D49=0,0,SUM($L$21:L49)) -> 5296168.8 | Q49: =IF(D49=0,0,SUM($J$21:J49)) -> 5204490 | R49: =IF(D49=0,0,Q49-P49) -> -91678.807 | S49: =IF(D49=0,0,Q49/P49) -> 0.9826896 | U49: =IF(D49=0,0,SUM($L$21:L49)) -> 5296168.8 | V49: =IF(D49=0,0,SUM($J$21:J49)) -> 5204490 | W49: =IF(D49=0,0,V49-U49) -> -91678.807 | X49: =IF(D49=0,0,V49/U49) -> 0.9826896 | Y49: =Y48+1 -> 45686 | Z49: =Z48+1 -> 45686 | AA49: 5 | AB49: Mon | AC49: =IFERROR(AVERAGEIFS(J141:J171,D141:D171,1,G141:G171,"mon"),0) -> 196620 | AD49: =COUNTIFS(D141:D171,1,G141:G171,"Mon") -> 3 | AE49: =($I$11*実績_2024R6!AI48)/AD49 -> 225867.88 | AF49: =AD49*AE49 -> 677603.63 | AG49: 141〜171
C50: 30 | D50: 1 | E50: =MONTH(Y50) -> 1 | F50: =F49+1 -> 45687 | G50: =TEXT(Z50,"ddd") -> Thu | J50: 450100 | L50: =IF(D50=0,0,IFERROR(SUMIFS($AE$21:$AE$104,$AA$21:$AA$104,$E50,$AB$21:$AB$104,$G50),0)) -> 196518.52 | M50: =IF(D50=0,0,J50-L50) -> 253581.48 | N50: =IFERROR(J50/L50,"¥0") -> 2.2903694 | P50: =IF(D50=0,0,SUM($L$21:L50)) -> 5492687.3 | Q50: =IF(D50=0,0,SUM($J$21:J50)) -> 5654590 | R50: =IF(D50=0,0,Q50-P50) -> 161902.67 | S50: =IF(D50=0,0,Q50/P50) -> 1.029476 | U50: =IF(D50=0,0,SUM($L$21:L50)) -> 5492687.3 | V50: =IF(D50=0,0,SUM($J$21:J50)) -> 5654590 | W50: =IF(D50=0,0,V50-U50) -> 161902.67 | X50: =IF(D50=0,0,V50/U50) -> 1.029476 | Y50: =Y49+1 -> 45687 | Z50: =Z49+1 -> 45687 | AA50: 5 | AB50: Tue | AC50: =IFERROR(AVERAGEIFS(J141:J171,D141:D171,1,G141:G171,"tue"),0) -> 236453.33 | AD50: =COUNTIFS(D141:D171,1,G141:G171,"tue") -> 3 | AE50: =($I$11*実績_2024R6!AI49)/AD50 -> 292828.68 | AF50: =AD50*AE50 -> 878486.04
C51: 31 | D51: 1 | E51: =MONTH(Y51) -> 1 | F51: =F50+1 -> 45688 | G51: =TEXT(Z51,"ddd") -> Fri | J51: 352040 | L51: =IF(D51=0,0,IFERROR(SUMIFS($AE$21:$AE$104,$AA$21:$AA$104,$E51,$AB$21:$AB$104,$G51),0)) -> 343102.15 | M51: =IF(D51=0,0,J51-L51) -> 8937.8521 | N51: =IFERROR(J51/L51,"¥0") -> 1.0260501 | P51: =IF(D51=0,0,SUM($L$21:L51)) -> 5835789.5 | Q51: =IF(D51=0,0,SUM($J$21:J51)) -> 6006630 | R51: =IF(D51=0,0,Q51-P51) -> 170840.53 | S51: =IF(D51=0,0,Q51/P51) -> 1.0292746 | U51: =IF(D51=0,0,SUM($L$21:L51)) -> 5835789.5 | V51: =IF(D51=0,0,SUM($J$21:J51)) -> 6006630 | W51: =IF(D51=0,0,V51-U51) -> 170840.53 | X51: =IF(D51=0,0,V51/U51) -> 1.0292746 | Y51: =Y50+1 -> 45688 | Z51: =Z50+1 -> 45688 | AA51: 5 | AB51: Wed | AC51: =IFERROR(AVERAGEIFS(J141:J171,D141:D171,1,G141:G171,"wed"),0) -> 347390 | AD51: =COUNTIFS(D141:D171,1,G141:G171,"wed") -> 4 | AE51: =($I$11*実績_2024R6!AI50)/AD51 -> 379546.97 | AF51: =AD51*AE51 -> 1518187.9
C52: 32 | D52: 1 | E52: =MONTH(Y52) -> 2 | F52: =F51+1 -> 45689 | G52: =TEXT(Z52,"ddd") -> Sat | J52: 183250 | L52: =IF(D52=0,0,IFERROR(SUMIFS($AE$21:$AE$104,$AA$21:$AA$104,$E52,$AB$21:$AB$104,$G52),0)) -> 132611.12 | M52: =IF(D52=0,0,J52-L52) -> 50638.883 | N52: =IFERROR(J52/L52,"¥0") -> 1.38186 | P52: =IF(D52=0,0,$L$52) -> 132611.12 | Q52: =IF(D52=0,0,$J$52) -> 183250 | R52: =IF(D52=0,0,Q52-P52) -> 50638.883 | S52: =IF(D52=0,0,Q52/P52) -> 1.38186 | U52: =IF(D52=0,0,SUM($L$21:L52)) -> 5968400.6 | V52: =IF(D52=0,0,SUM($J$21:J52)) -> 6189880 | W52: =IF(D52=0,0,V52-U52) -> 221479.41 | X52: =IF(D52=0,0,V52/U52) -> 1.0371087 | Y52: =Y51+1 -> 45689 | Z52: =Z51+1 -> 45689 | AA52: 5 | AB52: Thu | AC52: =IFERROR(AVERAGEIFS(J141:J171,D141:D171,1,G141:G171,"thu"),0) -> 226140 | AD52: =COUNTIFS(D141:D171,1,G141:G171,"thu") -> 5 | AE52: =($I$11*実績_2024R6!AI51)/AD52 -> 208647.36 | AF52: =AD52*AE52 -> 1043236.8
C53: 33 | D53: 0 | E53: =MONTH(Y53) -> 2 | F53: =F52+1 -> 45690 | G53: =TEXT(Z53,"ddd") -> Sun | L53: =IF(D53=0,0,IFERROR(SUMIFS($AE$21:$AE$104,$AA$21:$AA$104,$E53,$AB$21:$AB$104,$G53),0)) -> 0 | M53: =IF(D53=0,0,J53-L53) -> 0 | N53: =IFERROR(J53/L53,"¥0") -> ¥0 | P53: =IF(D53=0,0,SUM($L$52:L53)) -> 0 | Q53: =IF(D53=0,0,SUM($J$52:J53)) -> 0 | R53: =IF(D53=0,0,Q53-P53) -> 0 | S53: =IF(D53=0,0,Q53/P53) -> 0 | U53: =IF(D53=0,0,SUM($L$21:L53)) -> 0 | V53: =IF(D53=0,0,SUM($J$21:J53)) -> 0 | W53: =IF(D53=0,0,V53-U53) -> 0 | X53: =IF(D53=0,0,V53/U53) -> 0 | Y53: =Y52+1 -> 45690 | Z53: =Z52+1 -> 45690 | AA53: 5 | AB53: Fri | AC53: =IFERROR(AVERAGEIFS(J141:J171,D141:D171,1,G141:G171,"fri"),0) -> 291050 | AD53: =COUNTIFS(D141:D171,1,G141:G171,"fri") -> 5 | AE53: =($I$11*実績_2024R6!AI52)/AD53 -> 265057.06 | AF53: =AD53*AE53 -> 1325285.3
C54: 34 | D54: 1 | E54: =MONTH(Y54) -> 2 | F54: =F53+1 -> 45691 | G54: =TEXT(Z54,"ddd") -> Mon | J54: 101150 | L54: =IF(D54=0,0,IFERROR(SUMIFS($AE$21:$AE$104,$AA$21:$AA$104,$E54,$AB$21:$AB$104,$G54),0)) -> 224838.76 | M54: =IF(D54=0,0,J54-L54) -> -123688.76 | N54: =IFERROR(J54/L54,"¥0") -> 0.44987794 | P54: =IF(D54=0,0,SUM($L$52:L54)) -> 357449.88 | Q54: =IF(D54=0,0,SUM($J$52:J54)) -> 284400 | R54: =IF(D54=0,0,Q54-P54) -> -73049.879 | S54: =IF(D54=0,0,Q54/P54) -> 0.79563602 | U54: =IF(D54=0,0,SUM($L$21:L54)) -> 6193239.4 | V54: =IF(D54=0,0,SUM($J$21:J54)) -> 6291030 | W54: =IF(D54=0,0,V54-U54) -> 97790.648 | X54: =IF(D54=0,0,V54/U54) -> 1.0157899 | Y54: =Y53+1 -> 45691 | Z54: =Z53+1 -> 45691 | AA54: 5 | AB54: Sat | AC54: =IFERROR(AVERAGEIFS(J141:J171,D141:D171,1,G141:G171,"sat"),0) -> 164150 | AD54: =COUNTIFS(D141:D171,1,G141:G171,"sat") -> 4 | AE54: =($I$11*実績_2024R6!AI53)/AD54 -> 98247.463 | AF54: =AD54*AE54 -> 392989.85 | AG54: 5月目標売り上げ
C55: 35 | D55: 1 | E55: =MONTH(Y55) -> 2 | F55: =F54+1 -> 45692 | G55: =TEXT(Z55,"ddd") -> Tue | J55: 152530 | L55: =IF(D55=0,0,IFERROR(SUMIFS($AE$21:$AE$104,$AA$21:$AA$104,$E55,$AB$21:$AB$104,$G55),0)) -> 277740.28 | M55: =IF(D55=0,0,J55-L55) -> -125210.28 | N55: =IFERROR(J55/L55,"¥0") -> 0.54918213 | P55: =IF(D55=0,0,SUM($L$52:L55)) -> 635190.16 | Q55: =IF(D55=0,0,SUM($J$52:J55)) -> 436930 | R55: =IF(D55=0,0,Q55-P55) -> -198260.16 | S55: =IF(D55=0,0,Q55/P55) -> 0.68787274 | U55: =IF(D55=0,0,SUM($L$21:L55)) -> 6470979.6 | V55: =IF(D55=0,0,SUM($J$21:J55)) -> 6443560 | W55: =IF(D55=0,0,V55-U55) -> -27419.636 | X55: =IF(D55=0,0,V55/U55) -> 0.99576268 | Y55: =Y54+1 -> 45692 | Z55: =Z54+1 -> 45692 | AA55: 5 | AB55: Sun | AC55: =IFERROR(AVERAGEIFS(J141:J171,D141:D171,1,G141:G171,"sun"),0) -> 0 | AD55: =IFERROR(COUNTIFS(D141:D171,1,G141:G171,"sun"),0) -> 0 | AE55: =IFERROR(($I$11*実績_2024R6!AI54)/AD55,0) -> 0 | AF55: =SUM(AF49:AF54) -> 5835789.5 | AG55: =I11 -> 5835789.5
C56: 36 | D56: 1 | E56: =MONTH(Y56) -> 2 | F56: =F55+1 -> 45693 | G56: =TEXT(Z56,"ddd") -> Wed | J56: 227650 | L56: =IF(D56=0,0,IFERROR(SUMIFS($AE$21:$AE$104,$AA$21:$AA$104,$E56,$AB$21:$AB$104,$G56),0)) -> 215570.54 | M56: =IF(D56=0,0,J56-L56) -> 12079.457 | N56: =IFERROR(J56/L56,"¥0") -> 1.0560348 | P56: =IF(D56=0,0,SUM($L$52:L56)) -> 850760.71 | Q56: =IF(D56=0,0,SUM($J$52:J56)) -> 664580 | R56: =IF(D56=0,0,Q56-P56) -> -186180.71 | S56: =IF(D56=0,0,Q56/P56) -> 0.78115973 | U56: =IF(D56=0,0,SUM($L$21:L56)) -> 6686550.2 | V56: =IF(D56=0,0,SUM($J$21:J56)) -> 6671210 | W56: =IF(D56=0,0,V56-U56) -> -15340.179 | X56: =IF(D56=0,0,V56/U56) -> 0.99770582 | Y56: =Y55+1 -> 45693 | Z56: =Z55+1 -> 45693 | AA56: 6 | AB56: Mon | AC56: =IFERROR(AVERAGEIFS(J172:J201,D172:D201,1,G172:G201,"mon"),0) -> 193860 | AD56: =COUNTIFS(D172:D201,1,G172:G201,"Mon") -> 5 | AE56: =($I$12*実績_2024R6!AI55)/AD56 -> 158255.64 | AF56: =AD56*AE56 -> 791278.21 | AG56: 172〜201
C57: 37 | D57: 1 | E57: =MONTH(Y57) -> 2 | F57: =F56+1 -> 45694 | G57: =TEXT(Z57,"ddd") -> Thu | J57: 339200 | L57: =IF(D57=0,0,IFERROR(SUMIFS($AE$21:$AE$104,$AA$21:$AA$104,$E57,$AB$21:$AB$104,$G57),0)) -> 283656.58 | M57: =IF(D57=0,0,J57-L57) -> 55543.418 | N57: =IFERROR(J57/L57,"¥0") -> 1.1958122 | P57: =IF(D57=0,0,SUM($L$52:L57)) -> 1134417.3 | Q57: =IF(D57=0,0,SUM($J$52:J57)) -> 1003780 | R57: =IF(D57=0,0,Q57-P57) -> -130637.29 | S57: =IF(D57=0,0,Q57/P57) -> 0.88484195 | U57: =IF(D57=0,0,SUM($L$21:L57)) -> 6970206.8 | V57: =IF(D57=0,0,SUM($J$21:J57)) -> 7010410 | W57: =IF(D57=0,0,V57-U57) -> 40203.239 | X57: =IF(D57=0,0,V57/U57) -> 1.0057679 | Y57: =Y56+1 -> 45694 | Z57: =Z56+1 -> 45694 | AA57: 6 | AB57: Tue | AC57: =IFERROR(AVERAGEIFS(J172:J201,D172:D201,1,G172:G201,"tue"),0) -> 287705 | AD57: =COUNTIFS(D172:D201,1,G172:G201,"tue") -> 4 | AE57: =($I$12*実績_2024R6!AI56)/AD57 -> 210637.62 | AF57: =AD57*AE57 -> 842550.47
C58: 38 | D58: 1 | E58: =MONTH(Y58) -> 2 | F58: =F57+1 -> 45695 | G58: =TEXT(Z58,"ddd") -> Fri | J58: 330170 | L58: =IF(D58=0,0,IFERROR(SUMIFS($AE$21:$AE$104,$AA$21:$AA$104,$E58,$AB$21:$AB$104,$G58),0)) -> 207016.95 | M58: =IF(D58=0,0,J58-L58) -> 123153.05 | N58: =IFERROR(J58/L58,"¥0") -> 1.5948936 | P58: =IF(D58=0,0,SUM($L$52:L58)) -> 1341434.2 | Q58: =IF(D58=0,0,SUM($J$52:J58)) -> 1333950 | R58: =IF(D58=0,0,Q58-P58) -> -7484.2351 | S58: =IF(D58=0,0,Q58/P58) -> 0.99442072 | U58: =IF(D58=0,0,SUM($L$21:L58)) -> 7177223.7 | V58: =IF(D58=0,0,SUM($J$21:J58)) -> 7340580 | W58: =IF(D58=0,0,V58-U58) -> 163356.29 | X58: =IF(D58=0,0,V58/U58) -> 1.0227604 | Y58: =Y57+1 -> 45695 | Z58: =Z57+1 -> 45695 | AA58: 6 | AB58: Wed | AC58: =IFERROR(AVERAGEIFS(J172:J201,D172:D201,1,G172:G201,"wed"),0) -> 234007.5 | AD58: =COUNTIFS(D172:D201,1,G172:G201,"wed") -> 4 | AE58: =($I$12*実績_2024R6!AI57)/AD58 -> 317333.92 | AF58: =AD58*AE58 -> 1269335.7
C59: 39 | D59: 1 | E59: =MONTH(Y59) -> 2 | F59: =F58+1 -> 45696 | G59: =TEXT(Z59,"ddd") -> Sat | J59: 156800 | L59: =IF(D59=0,0,IFERROR(SUMIFS($AE$21:$AE$104,$AA$21:$AA$104,$E59,$AB$21:$AB$104,$G59),0)) -> 132611.12 | M59: =IF(D59=0,0,J59-L59) -> 24188.883 | N59: =IFERROR(J59/L59,"¥0") -> 1.1824046 | P59: =IF(D59=0,0,SUM($L$52:L59)) -> 1474045.4 | Q59: =IF(D59=0,0,SUM($J$52:J59)) -> 1490750 | R59: =IF(D59=0,0,Q59-P59) -> 16704.648 | S59: =IF(D59=0,0,Q59/P59) -> 1.0113325 | U59: =IF(D59=0,0,SUM($L$21:L59)) -> 7309834.8 | V59: =IF(D59=0,0,SUM($J$21:J59)) -> 7497380 | W59: =IF(D59=0,0,V59-U59) -> 187545.17 | X59: =IF(D59=0,0,V59/U59) -> 1.0256566 | Y59: =Y58+1 -> 45696 | Z59: =Z58+1 -> 45696 | AA59: 6 | AB59: Thu | AC59: =IFERROR(AVERAGEIFS(J172:J201,D172:D201,1,G172:G201,"thu"),0) -> 236795 | AD59: =COUNTIFS(D172:D201,1,G172:G201,"thu") -> 4 | AE59: =($I$12*実績_2024R6!AI58)/AD59 -> 287558.87 | AF59: =AD59*AE59 -> 1150235.5
C60: 40 | D60: 0 | E60: =MONTH(Y60) -> 2 | F60: =F59+1 -> 45697 | G60: =TEXT(Z60,"ddd") -> Sun | L60: =IF(D60=0,0,IFERROR(SUMIFS($AE$21:$AE$104,$AA$21:$AA$104,$E60,$AB$21:$AB$104,$G60),0)) -> 0 | M60: =IF(D60=0,0,J60-L60) -> 0 | N60: =IFERROR(J60/L60,"¥0") -> ¥0 | P60: =IF(D60=0,0,SUM($L$52:L60)) -> 0 | Q60: =IF(D60=0,0,SUM($J$52:J60)) -> 0 | R60: =IF(D60=0,0,Q60-P60) -> 0 | S60: =IF(D60=0,0,Q60/P60) -> 0 | U60: =IF(D60=0,0,SUM($L$21:L60)) -> 0 | V60: =IF(D60=0,0,SUM($J$21:J60)) -> 0 | W60: =IF(D60=0,0,V60-U60) -> 0 | X60: =IF(D60=0,0,V60/U60) -> 0 | Y60: =Y59+1 -> 45697 | Z60: =Z59+1 -> 45697 | AA60: 6 | AB60: Fri | AC60: =IFERROR(AVERAGEIFS(J172:J201,D172:D201,1,G172:G201,"fri"),0) -> 301740 | AD60: =COUNTIFS(D172:D201,1,G172:G201,"fri") -> 4 | AE60: =($I$12*実績_2024R6!AI59)/AD60 -> 332088.98 | AF60: =AD60*AE60 -> 1328355.9
C61: 41 | D61: 1 | E61: =MONTH(Y61) -> 2 | F61: =F60+1 -> 45698 | G61: =TEXT(Z61,"ddd") -> Mon | J61: 99600 | L61: =IF(D61=0,0,IFERROR(SUMIFS($AE$21:$AE$104,$AA$21:$AA$104,$E61,$AB$21:$AB$104,$G61),0)) -> 224838.76 | M61: =IF(D61=0,0,J61-L61) -> -125238.76 | N61: =IFERROR(J61/L61,"¥0") -> 0.44298412 | P61: =IF(D61=0,0,SUM($L$52:L61)) -> 1698884.1 | Q61: =IF(D61=0,0,SUM($J$52:J61)) -> 1590350 | R61: =IF(D61=0,0,Q61-P61) -> -108534.11 | S61: =IF(D61=0,0,Q61/P61) -> 0.93611447 | U61: =IF(D61=0,0,SUM($L$21:L61)) -> 7534673.6 | V61: =IF(D61=0,0,SUM($J$21:J61)) -> 7596980 | W61: =IF(D61=0,0,V61-U61) -> 62306.413 | X61: =IF(D61=0,0,V61/U61) -> 1.0082693 | Y61: =Y60+1 -> 45698 | Z61: =Z60+1 -> 45698 | AA61: 6 | AB61: Sat | AC61: =IFERROR(AVERAGEIFS(J172:J201,D172:D201,1,G172:G201,"sat"),0) -> 126012.5 | AD61: =COUNTIFS(D172:D201,1,G172:G201,"sat") -> 4 | AE61: =($I$12*実績_2024R6!AI60)/AD61 -> 174297.9 | AF61: =AD61*AE61 -> 697191.61 | AG61: 6月目標売り上げ
C62: 42 | D62: 0 | E62: =MONTH(Y62) -> 2 | F62: =F61+1 -> 45699 | G62: =TEXT(Z62,"ddd") -> Tue | L62: =IF(D62=0,0,IFERROR(SUMIFS($AE$21:$AE$104,$AA$21:$AA$104,$E62,$AB$21:$AB$104,$G62),0)) -> 0 | M62: =IF(D62=0,0,J62-L62) -> 0 | N62: =IFERROR(J62/L62,"¥0") -> ¥0 | P62: =IF(D62=0,0,SUM($L$52:L62)) -> 0 | Q62: =IF(D62=0,0,SUM($J$52:J62)) -> 0 | R62: =IF(D62=0,0,Q62-P62) -> 0 | S62: =IF(D62=0,0,Q62/P62) -> 0 | U62: =IF(D62=0,0,SUM($L$21:L62)) -> 0 | V62: =IF(D62=0,0,SUM($J$21:J62)) -> 0 | W62: =IF(D62=0,0,V62-U62) -> 0 | X62: =IF(D62=0,0,V62/U62) -> 0 | Y62: =Y61+1 -> 45699 | Z62: =Z61+1 -> 45699 | AA62: 6 | AB62: Sun | AC62: =IFERROR(AVERAGEIFS(J172:J201,D172:D201,1,G172:G201,"sun"),0) -> 0 | AD62: =IFERROR(COUNTIFS(D172:D201,1,G172:G201,"sun"),0) -> 0 | AE62: =IFERROR(($I$12*実績_2024R6!AI61)/AD62,0) -> 0 | AF62: =SUM(AF56:AF61) -> 6078947.4 | AG62: =I12 -> 6078947.4
C63: 43 | D63: 1 | E63: =MONTH(Y63) -> 2 | F63: =F62+1 -> 45700 | G63: =TEXT(Z63,"ddd") -> Wed | J63: 323330 | L63: =IF(D63=0,0,IFERROR(SUMIFS($AE$21:$AE$104,$AA$21:$AA$104,$E63,$AB$21:$AB$104,$G63),0)) -> 215570.54 | M63: =IF(D63=0,0,J63-L63) -> 107759.46 | N63: =IFERROR(J63/L63,"¥0") -> 1.4998802 | P63: =IF(D63=0,0,SUM($L$52:L63)) -> 1914454.7 | Q63: =IF(D63=0,0,SUM($J$52:J63)) -> 1913680 | R63: =IF(D63=0,0,Q63-P63) -> -774.65696 | S63: =IF(D63=0,0,Q63/P63) -> 0.99959536 | U63: =IF(D63=0,0,SUM($L$21:L63)) -> 7750244.1 | V63: =IF(D63=0,0,SUM($J$21:J63)) -> 7920310 | W63: =IF(D63=0,0,V63-U63) -> 170065.87 | X63: =IF(D63=0,0,V63/U63) -> 1.0219433 | Y63: =Y62+1 -> 45700 | Z63: =Z62+1 -> 45700 | AA63: 7 | AB63: Mon | AC63: =IFERROR(AVERAGEIFS(J202:J232,D202:D232,1,G202:G232,"mon"),0) -> 179653.33 | AD63: =COUNTIFS(D202:D232,1,G202:G232,"Mon") -> 3 | AE63: =($I$13*実績_2024R6!AI62)/AD63 -> 261193.83 | AF63: =AD63*AE63 -> 783581.49 | AG63: 202〜232
C64: 44 | D64: 1 | E64: =MONTH(Y64) -> 2 | F64: =F63+1 -> 45701 | G64: =TEXT(Z64,"ddd") -> Thu | J64: 346290 | L64: =IF(D64=0,0,IFERROR(SUMIFS($AE$21:$AE$104,$AA$21:$AA$104,$E64,$AB$21:$AB$104,$G64),0)) -> 283656.58 | M64: =IF(D64=0,0,J64-L64) -> 62633.418 | N64: =IFERROR(J64/L64,"¥0") -> 1.2208072 | P64: =IF(D64=0,0,SUM($L$52:L64)) -> 2198111.2 | Q64: =IF(D64=0,0,SUM($J$52:J64)) -> 2259970 | R64: =IF(D64=0,0,Q64-P64) -> 61858.761 | S64: =IF(D64=0,0,Q64/P64) -> 1.0281418 | U64: =IF(D64=0,0,SUM($L$21:L64)) -> 8033900.7 | V64: =IF(D64=0,0,SUM($J$21:J64)) -> 8266600 | W64: =IF(D64=0,0,V64-U64) -> 232699.29 | X64: =IF(D64=0,0,V64/U64) -> 1.0289647 | Y64: =Y63+1 -> 45701 | Z64: =Z63+1 -> 45701 | AA64: 7 | AB64: Tue | AC64: =IFERROR(AVERAGEIFS(J202:J232,D202:D232,1,G202:G232,"tue"),0) -> 221320 | AD64: =COUNTIFS(D202:D232,1,G202:G232,"tue") -> 5 | AE64: =($I$13*実績_2024R6!AI63)/AD64 -> 147630.74 | AF64: =AD64*AE64 -> 738153.72
C65: 45 | D65: 1 | E65: =MONTH(Y65) -> 2 | F65: =F64+1 -> 45702 | G65: =TEXT(Z65,"ddd") -> Fri | J65: 324250 | L65: =IF(D65=0,0,IFERROR(SUMIFS($AE$21:$AE$104,$AA$21:$AA$104,$E65,$AB$21:$AB$104,$G65),0)) -> 207016.95 | M65: =IF(D65=0,0,J65-L65) -> 117233.05 | N65: =IFERROR(J65/L65,"¥0") -> 1.5662969 | P65: =IF(D65=0,0,SUM($L$52:L65)) -> 2405128.2 | Q65: =IF(D65=0,0,SUM($J$52:J65)) -> 2584220 | R65: =IF(D65=0,0,Q65-P65) -> 179091.81 | S65: =IF(D65=0,0,Q65/P65) -> 1.0744625 | U65: =IF(D65=0,0,SUM($L$21:L65)) -> 8240917.7 | V65: =IF(D65=0,0,SUM($J$21:J65)) -> 8590850 | W65: =IF(D65=0,0,V65-U65) -> 349932.34 | X65: =IF(D65=0,0,V65/U65) -> 1.0424628 | Y65: =Y64+1 -> 45702 | Z65: =Z64+1 -> 45702 | AA65: 7 | AB65: Wed | AC65: =IFERROR(AVERAGEIFS(J202:J232,D202:D232,1,G202:G232,"wed"),0) -> 203138 | AD65: =COUNTIFS(D202:D232,1,G202:G232,"wed") -> 5 | AE65: =($I$13*実績_2024R6!AI64)/AD65 -> 213951.49 | AF65: =AD65*AE65 -> 1069757.4
C66: 46 | D66: 1 | E66: =MONTH(Y66) -> 2 | F66: =F65+1 -> 45703 | G66: =TEXT(Z66,"ddd") -> Sat | J66: 59330 | L66: =IF(D66=0,0,IFERROR(SUMIFS($AE$21:$AE$104,$AA$21:$AA$104,$E66,$AB$21:$AB$104,$G66),0)) -> 132611.12 | M66: =IF(D66=0,0,J66-L66) -> -73281.117 | N66: =IFERROR(J66/L66,"¥0") -> 0.44739839 | P66: =IF(D66=0,0,SUM($L$52:L66)) -> 2537739.3 | Q66: =IF(D66=0,0,SUM($J$52:J66)) -> 2643550 | R66: =IF(D66=0,0,Q66-P66) -> 105810.7 | S66: =IF(D66=0,0,Q66/P66) -> 1.0416949 | U66: =IF(D66=0,0,SUM($L$21:L66)) -> 8373528.8 | V66: =IF(D66=0,0,SUM($J$21:J66)) -> 8650180 | W66: =IF(D66=0,0,V66-U66) -> 276651.22 | X66: =IF(D66=0,0,V66/U66) -> 1.0330388 | Y66: =Y65+1 -> 45703 | Z66: =Z65+1 -> 45703 | AA66: 7 | AB66: Thu | AC66: =IFERROR(AVERAGEIFS(J202:J232,D202:D232,1,G202:G232,"thu"),0) -> 288590 | AD66: =COUNTIFS(D202:D232,1,G202:G232,"thu") -> 5 | AE66: =($I$13*実績_2024R6!AI65)/AD66 -> 191788 | AF66: =AD66*AE66 -> 958939.99
C67: 47 | D67: 0 | E67: =MONTH(Y67) -> 2 | F67: =F66+1 -> 45704 | G67: =TEXT(Z67,"ddd") -> Sun | L67: =IF(D67=0,0,IFERROR(SUMIFS($AE$21:$AE$104,$AA$21:$AA$104,$E67,$AB$21:$AB$104,$G67),0)) -> 0 | M67: =IF(D67=0,0,J67-L67) -> 0 | N67: =IFERROR(J67/L67,"¥0") -> ¥0 | P67: =IF(D67=0,0,SUM($L$52:L67)) -> 0 | Q67: =IF(D67=0,0,SUM($J$52:J67)) -> 0 | R67: =IF(D67=0,0,Q67-P67) -> 0 | S67: =IF(D67=0,0,Q67/P67) -> 0 | U67: =IF(D67=0,0,SUM($L$21:L67)) -> 0 | V67: =IF(D67=0,0,SUM($J$21:J67)) -> 0 | W67: =IF(D67=0,0,V67-U67) -> 0 | X67: =IF(D67=0,0,V67/U67) -> 0 | Y67: =Y66+1 -> 45704 | Z67: =Z66+1 -> 45704 | AA67: 7 | AB67: Fri | AC67: =IFERROR(AVERAGEIFS(J202:J232,D202:D232,1,G202:G232,"fri"),0) -> 209600 | AD67: =COUNTIFS(D202:D232,1,G202:G232,"fri") -> 4 | AE67: =($I$13*実績_2024R6!AI66)/AD67 -> 287700.63 | AF67: =AD67*AE67 -> 1150802.5
C68: 48 | D68: 1 | E68: =MONTH(Y68) -> 2 | F68: =F67+1 -> 45705 | G68: =TEXT(Z68,"ddd") -> Mon | J68: 209260 | L68: =IF(D68=0,0,IFERROR(SUMIFS($AE$21:$AE$104,$AA$21:$AA$104,$E68,$AB$21:$AB$104,$G68),0)) -> 224838.76 | M68: =IF(D68=0,0,J68-L68) -> -15578.762 | N68: =IFERROR(J68/L68,"¥0") -> 0.93071141 | P68: =IF(D68=0,0,SUM($L$52:L68)) -> 2762578.1 | Q68: =IF(D68=0,0,SUM($J$52:J68)) -> 2852810 | R68: =IF(D68=0,0,Q68-P68) -> 90231.935 | S68: =IF(D68=0,0,Q68/P68) -> 1.0326622 | U68: =IF(D68=0,0,SUM($L$21:L68)) -> 8598367.5 | V68: =IF(D68=0,0,SUM($J$21:J68)) -> 8859440 | W68: =IF(D68=0,0,V68-U68) -> 261072.46 | X68: =IF(D68=0,0,V68/U68) -> 1.030363 | Y68: =Y67+1 -> 45705 | Z68: =Z67+1 -> 45705 | AA68: 7 | AB68: Sat | AC68: =IFERROR(AVERAGEIFS(J202:J232,D202:D232,1,G202:G232,"sat"),0) -> 98982.5 | AD68: =COUNTIFS(D202:D232,1,G202:G232,"sat") -> 4 | AE68: =($I$13*実績_2024R6!AI67)/AD68 -> 117849.1 | AF68: =AD68*AE68 -> 471396.41 | AG68: 7月目標売り上げ
C69: 49 | D69: 1 | E69: =MONTH(Y69) -> 2 | F69: =F68+1 -> 45706 | G69: =TEXT(Z69,"ddd") -> Tue | J69: 124000 | L69: =IF(D69=0,0,IFERROR(SUMIFS($AE$21:$AE$104,$AA$21:$AA$104,$E69,$AB$21:$AB$104,$G69),0)) -> 277740.28 | M69: =IF(D69=0,0,J69-L69) -> -153740.28 | N69: =IFERROR(J69/L69,"¥0") -> 0.44646026 | P69: =IF(D69=0,0,SUM($L$52:L69)) -> 3040318.3 | Q69: =IF(D69=0,0,SUM($J$52:J69)) -> 2976810 | R69: =IF(D69=0,0,Q69-P69) -> -63508.349 | S69: =IF(D69=0,0,Q69/P69) -> 0.97911128 | U69: =IF(D69=0,0,SUM($L$21:L69)) -> 8876107.8 | V69: =IF(D69=0,0,SUM($J$21:J69)) -> 8983440 | W69: =IF(D69=0,0,V69-U69) -> 107332.18 | X69: =IF(D69=0,0,V69/U69) -> 1.0120923 | Y69: =Y68+1 -> 45706 | Z69: =Z68+1 -> 45706 | AA69: 7 | AB69: Sun | AC69: =IFERROR(AVERAGEIFS(J202:J232,D202:D232,1,G202:G232,"sun"),0) -> 0 | AD69: =IFERROR(COUNTIFS(D202:D232,1,G202:G232,"sun"),0) -> 0 | AE69: =IFERROR(($I$13*実績_2024R6!AI68)/AD69,0) -> 0 | AF69: =SUM(AF63:AF68) -> 5172631.6 | AG69: =I13 -> 5172631.6
C70: 50 | D70: 1 | E70: =MONTH(Y70) -> 2 | F70: =F69+1 -> 45707 | G70: =TEXT(Z70,"ddd") -> Wed | J70: 223000 | L70: =IF(D70=0,0,IFERROR(SUMIFS($AE$21:$AE$104,$AA$21:$AA$104,$E70,$AB$21:$AB$104,$G70),0)) -> 215570.54 | M70: =IF(D70=0,0,J70-L70) -> 7429.4567 | N70: =IFERROR(J70/L70,"¥0") -> 1.0344642 | P70: =IF(D70=0,0,SUM($L$52:L70)) -> 3255888.9 | Q70: =IF(D70=0,0,SUM($J$52:J70)) -> 3199810 | R70: =IF(D70=0,0,Q70-P70) -> -56078.892 | S70: =IF(D70=0,0,Q70/P70) -> 0.98277617 | U70: =IF(D70=0,0,SUM($L$21:L70)) -> 9091678.4 | V70: =IF(D70=0,0,SUM($J$21:J70)) -> 9206440 | W70: =IF(D70=0,0,V70-U70) -> 114761.63 | X70: =IF(D70=0,0,V70/U70) -> 1.0126227 | Y70: =Y69+1 -> 45707 | Z70: =Z69+1 -> 45707 | AA70: 8 | AB70: Mon | AC70: =IFERROR(AVERAGEIFS(J233:J263,D233:D263,1,G233:G263,"mon"),0) -> 133416.67 | AD70: =COUNTIFS(D233:D263,1,G233:G263,"Mon") -> 3 | AE70: =($I$14*実績_2024R6!AI69)/AD70 -> 91631.632 | AF70: =AD70*AE70 -> 274894.89 | AG70: 233〜263
C71: 51 | D71: 1 | E71: =MONTH(Y71) -> 2 | F71: =F70+1 -> 45708 | G71: =TEXT(Z71,"ddd") -> Thu | J71: 425750 | L71: =IF(D71=0,0,IFERROR(SUMIFS($AE$21:$AE$104,$AA$21:$AA$104,$E71,$AB$21:$AB$104,$G71),0)) -> 283656.58 | M71: =IF(D71=0,0,J71-L71) -> 142093.42 | N71: =IFERROR(J71/L71,"¥0") -> 1.5009347 | P71: =IF(D71=0,0,SUM($L$52:L71)) -> 3539545.5 | Q71: =IF(D71=0,0,SUM($J$52:J71)) -> 3625560 | R71: =IF(D71=0,0,Q71-P71) -> 86014.526 | S71: =IF(D71=0,0,Q71/P71) -> 1.024301 | U71: =IF(D71=0,0,SUM($L$21:L71)) -> 9375334.9 | V71: =IF(D71=0,0,SUM($J$21:J71)) -> 9632190 | W71: =IF(D71=0,0,V71-U71) -> 256855.05 | X71: =IF(D71=0,0,V71/U71) -> 1.0273969 | Y71: =Y70+1 -> 45708 | Z71: =Z70+1 -> 45708 | AA71: 8 | AB71: Tue | AC71: =IFERROR(AVERAGEIFS(J233:J263,D233:D263,1,G233:G263,"tue"),0) -> 121666.67 | AD71: =COUNTIFS(D233:D263,1,G233:G263,"tue") -> 3 | AE71: =($I$14*実績_2024R6!AI70)/AD71 -> 76844.171 | AF71: =AD71*AE71 -> 230532.51
C72: 52 | D72: 1 | E72: =MONTH(Y72) -> 2 | F72: =F71+1 -> 45709 | G72: =TEXT(Z72,"ddd") -> Fri | J72: 260660 | L72: =IF(D72=0,0,IFERROR(SUMIFS($AE$21:$AE$104,$AA$21:$AA$104,$E72,$AB$21:$AB$104,$G72),0)) -> 207016.95 | M72: =IF(D72=0,0,J72-L72) -> 53643.052 | N72: =IFERROR(J72/L72,"¥0") -> 1.259124 | P72: =IF(D72=0,0,SUM($L$52:L72)) -> 3746562.4 | Q72: =IF(D72=0,0,SUM($J$52:J72)) -> 3886220 | R72: =IF(D72=0,0,Q72-P72) -> 139657.58 | S72: =IF(D72=0,0,Q72/P72) -> 1.0372762 | U72: =IF(D72=0,0,SUM($L$21:L72)) -> 9582351.9 | V72: =IF(D72=0,0,SUM($J$21:J72)) -> 9892850 | W72: =IF(D72=0,0,V72-U72) -> 310498.11 | X72: =IF(D72=0,0,V72/U72) -> 1.0324031 | Y72: =Y71+1 -> 45709 | Z72: =Z71+1 -> 45709 | AA72: 8 | AB72: Wed | AC72: =IFERROR(AVERAGEIFS(J233:J263,D233:D263,1,G233:G263,"wed"),0) -> 95833.333 | AD72: =COUNTIFS(D233:D263,1,G233:G263,"wed") -> 3 | AE72: =($I$14*実績_2024R6!AI71)/AD72 -> 144049.79 | AF72: =AD72*AE72 -> 432149.37
C73: 53 | D73: 1 | E73: =MONTH(Y73) -> 2 | F73: =F72+1 -> 45710 | G73: =TEXT(Z73,"ddd") -> Sat | J73: 173500 | L73: =IF(D73=0,0,IFERROR(SUMIFS($AE$21:$AE$104,$AA$21:$AA$104,$E73,$AB$21:$AB$104,$G73),0)) -> 132611.12 | M73: =IF(D73=0,0,J73-L73) -> 40888.883 | N73: =IFERROR(J73/L73,"¥0") -> 1.3083368 | P73: =IF(D73=0,0,SUM($L$52:L73)) -> 3879173.5 | Q73: =IF(D73=0,0,SUM($J$52:J73)) -> 4059720 | R73: =IF(D73=0,0,Q73-P73) -> 180546.46 | S73: =IF(D73=0,0,Q73/P73) -> 1.0465425 | U73: =IF(D73=0,0,SUM($L$21:L73)) -> 9714963 | V73: =IF(D73=0,0,SUM($J$21:J73)) -> 10066350 | W73: =IF(D73=0,0,V73-U73) -> 351386.99 | X73: =IF(D73=0,0,V73/U73) -> 1.0361697 | Y73: =Y72+1 -> 45710 | Z73: =Z72+1 -> 45710 | AA73: 8 | AB73: Thu | AC73: =IFERROR(AVERAGEIFS(J233:J263,D233:D263,1,G233:G263,"thu"),0) -> 122210 | AD73: =COUNTIFS(D233:D263,1,G233:G263,"thu") -> 3 | AE73: =($I$14*実績_2024R6!AI72)/AD73 -> 134256.92 | AF73: =AD73*AE73 -> 402770.75
C74: 54 | D74: 0 | E74: =MONTH(Y74) -> 2 | F74: =F73+1 -> 45711 | G74: =TEXT(Z74,"ddd") -> Sun | L74: =IF(D74=0,0,IFERROR(SUMIFS($AE$21:$AE$104,$AA$21:$AA$104,$E74,$AB$21:$AB$104,$G74),0)) -> 0 | M74: =IF(D74=0,0,J74-L74) -> 0 | N74: =IFERROR(J74/L74,"¥0") -> ¥0 | P74: =IF(D74=0,0,SUM($L$52:L74)) -> 0 | Q74: =IF(D74=0,0,SUM($J$52:J74)) -> 0 | R74: =IF(D74=0,0,Q74-P74) -> 0 | S74: =IF(D74=0,0,Q74/P74) -> 0 | U74: =IF(D74=0,0,SUM($L$21:L74)) -> 0 | V74: =IF(D74=0,0,SUM($J$21:J74)) -> 0 | W74: =IF(D74=0,0,V74-U74) -> 0 | X74: =IF(D74=0,0,V74/U74) -> 0 | Y74: =Y73+1 -> 45711 | Z74: =Z73+1 -> 45711 | AA74: 8 | AB74: Fri | AC74: =IFERROR(AVERAGEIFS(J233:J263,D233:D263,1,G233:G263,"fri"),0) -> 169465 | AD74: =COUNTIFS(D233:D263,1,G233:G263,"fri") -> 4 | AE74: =($I$14*実績_2024R6!AI73)/AD74 -> 140867.1 | AF74: =AD74*AE74 -> 563468.4
C75: 55 | D75: 0 | E75: =MONTH(Y75) -> 2 | F75: =F74+1 -> 45712 | G75: =TEXT(Z75,"ddd") -> Mon | L75: =IF(D75=0,0,IFERROR(SUMIFS($AE$21:$AE$104,$AA$21:$AA$104,$E75,$AB$21:$AB$104,$G75),0)) -> 0 | M75: =IF(D75=0,0,J75-L75) -> 0 | N75: =IFERROR(J75/L75,"¥0") -> ¥0 | P75: =IF(D75=0,0,SUM($L$52:L75)) -> 0 | Q75: =IF(D75=0,0,SUM($J$52:J75)) -> 0 | R75: =IF(D75=0,0,Q75-P75) -> 0 | S75: =IF(D75=0,0,Q75/P75) -> 0 | U75: =IF(D75=0,0,SUM($L$21:L75)) -> 0 | V75: =IF(D75=0,0,SUM($J$21:J75)) -> 0 | W75: =IF(D75=0,0,V75-U75) -> 0 | X75: =IF(D75=0,0,V75/U75) -> 0 | Y75: =Y74+1 -> 45712 | Z75: =Z74+1 -> 45712 | AA75: 8 | AB75: Sat | AC75: =IFERROR(AVERAGEIFS(J233:J263,D233:D263,1,G233:G263,"sat"),0) -> 79267.5 | AD75: =COUNTIFS(D233:D263,1,G233:G263,"sat") -> 4 | AE75: =($I$14*実績_2024R6!AI74)/AD75 -> 76677.598 | AF75: =AD75*AE75 -> 306710.39 | AG75: 8月目標売り上げ
C76: 56 | D76: 1 | E76: =MONTH(Y76) -> 2 | F76: =F75+1 -> 45713 | G76: =TEXT(Z76,"ddd") -> Tue | J76: 317900 | L76: =IF(D76=0,0,IFERROR(SUMIFS($AE$21:$AE$104,$AA$21:$AA$104,$E76,$AB$21:$AB$104,$G76),0)) -> 277740.28 | M76: =IF(D76=0,0,J76-L76) -> 40159.716 | N76: =IFERROR(J76/L76,"¥0") -> 1.1445945 | P76: =IF(D76=0,0,SUM($L$52:L76)) -> 4156913.8 | Q76: =IF(D76=0,0,SUM($J$52:J76)) -> 4377620 | R76: =IF(D76=0,0,Q76-P76) -> 220706.18 | S76: =IF(D76=0,0,Q76/P76) -> 1.0530938 | U76: =IF(D76=0,0,SUM($L$21:L76)) -> 9992703.3 | V76: =IF(D76=0,0,SUM($J$21:J76)) -> 10384250 | W76: =IF(D76=0,0,V76-U76) -> 391546.7 | X76: =IF(D76=0,0,V76/U76) -> 1.0391833 | Y76: =Y75+1 -> 45713 | Z76: =Z75+1 -> 45713 | AA76: 8 | AB76: Sun | AC76: =IFERROR(AVERAGEIFS(J233:J263,D233:D263,1,G233:G263,"sun"),0) -> 0 | AD76: =IFERROR(COUNTIFS(D233:D263,1,G233:G263,"sun"),0) -> 0 | AE76: =IFERROR(($I$14*実績_2024R6!AI75)/AD76,0) -> 0 | AF76: =SUM(AF70:AF75) -> 2210526.3 | AG76: =I14 -> 2210526.3
C77: 57 | D77: 1 | E77: =MONTH(Y77) -> 2 | F77: =F76+1 -> 45714 | G77: =TEXT(Z77,"ddd") -> Wed | J77: 300760 | L77: =IF(D77=0,0,IFERROR(SUMIFS($AE$21:$AE$104,$AA$21:$AA$104,$E77,$AB$21:$AB$104,$G77),0)) -> 215570.54 | M77: =IF(D77=0,0,J77-L77) -> 85189.457 | N77: =IFERROR(J77/L77,"¥0") -> 1.3951813 | P77: =IF(D77=0,0,SUM($L$52:L77)) -> 4372484.4 | Q77: =IF(D77=0,0,SUM($J$52:J77)) -> 4678380 | R77: =IF(D77=0,0,Q77-P77) -> 305895.63 | S77: =IF(D77=0,0,Q77/P77) -> 1.0699592 | U77: =IF(D77=0,0,SUM($L$21:L77)) -> 10208274 | V77: =IF(D77=0,0,SUM($J$21:J77)) -> 10685010 | W77: =IF(D77=0,0,V77-U77) -> 476736.16 | X77: =IF(D77=0,0,V77/U77) -> 1.046701 | Y77: =Y76+1 -> 45714 | Z77: =Z76+1 -> 45714 | AA77: 9 | AB77: Mon | AC77: =IFERROR(AVERAGEIFS(J264:J293,D264:D293,1,G264:G293,"mon"),0) -> 152812.5 | AD77: =COUNTIFS(D264:D293,1,G264:G293,"Mon") -> 4 | AE77: =($I$15*実績_2024R6!AI76)/AD77 -> 99738.18 | AF77: =AD77*AE77 -> 398952.72 | AG77: 264〜293
C78: 58 | D78: 1 | E78: =MONTH(Y78) -> 2 | F78: =F77+1 -> 45715 | G78: =TEXT(Z78,"ddd") -> Thu | J78: 365350 | L78: =IF(D78=0,0,IFERROR(SUMIFS($AE$21:$AE$104,$AA$21:$AA$104,$E78,$AB$21:$AB$104,$G78),0)) -> 283656.58 | M78: =IF(D78=0,0,J78-L78) -> 81693.418 | N78: =IFERROR(J78/L78,"¥0") -> 1.2880011 | P78: =IF(D78=0,0,SUM($L$52:L78)) -> 4656140.9 | Q78: =IF(D78=0,0,SUM($J$52:J78)) -> 5043730 | R78: =IF(D78=0,0,Q78-P78) -> 387589.05 | S78: =IF(D78=0,0,Q78/P78) -> 1.0832426 | U78: =IF(D78=0,0,SUM($L$21:L78)) -> 10491930 | V78: =IF(D78=0,0,SUM($J$21:J78)) -> 11050360 | W78: =IF(D78=0,0,V78-U78) -> 558429.58 | X78: =IF(D78=0,0,V78/U78) -> 1.0532247 | Y78: =Y77+1 -> 45715 | Z78: =Z77+1 -> 45715 | AA78: 9 | AB78: Tue | AC78: =IFERROR(AVERAGEIFS(J264:J293,D264:D293,1,G264:G293,"tue"),0) -> 190260 | AD78: =COUNTIFS(D264:D293,1,G264:G293,"tue") -> 4 | AE78: =($I$15*実績_2024R6!AI77)/AD78 -> 164917.33 | AF78: =AD78*AE78 -> 659669.3
C79: 59 | D79: 1 | E79: =MONTH(Y79) -> 2 | F79: =F78+1 -> 45716 | G79: =TEXT(Z79,"ddd") -> Fri | J79: 324940 | L79: =IF(D79=0,0,IFERROR(SUMIFS($AE$21:$AE$104,$AA$21:$AA$104,$E79,$AB$21:$AB$104,$G79),0)) -> 207016.95 | M79: =IF(D79=0,0,J79-L79) -> 117923.05 | N79: =IFERROR(J79/L79,"¥0") -> 1.5696299 | P79: =IF(D79=0,0,SUM($L$52:L79)) -> 4863157.9 | Q79: =IF(D79=0,0,SUM($J$52:J79)) -> 5368670 | R79: =IF(D79=0,0,Q79-P79) -> 505512.11 | S79: =IF(D79=0,0,Q79/P79) -> 1.1039473 | U79: =IF(D79=0,0,SUM($L$21:L79)) -> 10698947 | V79: =IF(D79=0,0,SUM($J$21:J79)) -> 11375300 | W79: =IF(D79=0,0,V79-U79) -> 676352.63 | X79: =IF(D79=0,0,V79/U79) -> 1.0632167 | Y79: =Y78+1 -> 45716 | Z79: =Z78+1 -> 45716 | AA79: 9 | AB79: Wed | AC79: =IFERROR(AVERAGEIFS(J264:J293,D264:D293,1,G264:G293,"wed"),0) -> 192220 | AD79: =COUNTIFS(D264:D293,1,G264:G293,"wed") -> 4 | AE79: =($I$15*実績_2024R6!AI78)/AD79 -> 111235.83 | AF79: =AD79*AE79 -> 444943.34
C80: 60 | D80: 1 | E80: =MONTH(Y80) -> 3 | F80: =F79+1 -> 45717 | G80: =TEXT(Z80,"ddd") -> Sat | J80: 123200 | L80: =IF(D80=0,0,IFERROR(SUMIFS($AE$21:$AE$104,$AA$21:$AA$104,$E80,$AB$21:$AB$104,$G80),0)) -> 168908.25 | M80: =IF(D80=0,0,J80-L80) -> -45708.246 | N80: =IFERROR(J80/L80,"¥0") -> 0.72939008 | P80: =IF(D80=0,0,$L$80) -> 168908.25 | Q80: =IF(D80=0,0,$J$80) -> 123200 | R80: =IF(D80=0,0,Q80-P80) -> -45708.246 | S80: =IF(D80=0,0,Q80/P80) -> 0.72939008 | U80: =IF(D80=0,0,SUM($L$21:L80)) -> 10867856 | V80: =IF(D80=0,0,SUM($J$21:J80)) -> 11498500 | W80: =IF(D80=0,0,V80-U80) -> 630644.39 | X80: =IF(D80=0,0,V80/U80) -> 1.0580284 | Y80: =Y79+1 -> 45717 | Z80: =Z79+1 -> 45717 | AA80: 9 | AB80: Thu | AC80: =IFERROR(AVERAGEIFS(J264:J293,D264:D293,1,G264:G293,"thu"),0) -> 172712.5 | AD80: =COUNTIFS(D264:D293,1,G264:G293,"thu") -> 4 | AE80: =($I$15*実績_2024R6!AI79)/AD80 -> 125374.9 | AF80: =AD80*AE80 -> 501499.59
C81: 61 | D81: 0 | E81: =MONTH(Y81) -> 3 | F81: =F80+1 -> 45718 | G81: =TEXT(Z81,"ddd") -> Sun | L81: =IF(D81=0,0,IFERROR(SUMIFS($AE$21:$AE$104,$AA$21:$AA$104,$E81,$AB$21:$AB$104,$G81),0)) -> 0 | M81: =IF(D81=0,0,J81-L81) -> 0 | N81: =IFERROR(J81/L81,"¥0") -> ¥0 | P81: =IF(D81=0,0,SUM($L$80:L81)) -> 0 | Q81: =IF(D81=0,0,SUM($J$80:J81)) -> 0 | R81: =IF(D81=0,0,Q81-P81) -> 0 | S81: =IF(D81=0,0,Q81/P81) -> 0 | U81: =IF(D81=0,0,SUM($L$21:L81)) -> 0 | V81: =IF(D81=0,0,SUM($J$21:J81)) -> 0 | W81: =IF(D81=0,0,V81-U81) -> 0 | X81: =IF(D81=0,0,V81/U81) -> 0 | Y81: =Y80+1 -> 45718 | Z81: =Z80+1 -> 45718 | AA81: 9 | AB81: Fri | AC81: =IFERROR(AVERAGEIFS(J264:J293,D264:D293,1,G264:G293,"fri"),0) -> 187900 | AD81: =COUNTIFS(D264:D293,1,G264:G293,"fri") -> 4 | AE81: =($I$15*実績_2024R6!AI80)/AD81 -> 186257.36 | AF81: =AD81*AE81 -> 745029.44
C82: 62 | D82: 1 | E82: =MONTH(Y82) -> 3 | F82: =F81+1 -> 45719 | G82: =TEXT(Z82,"ddd") -> Mon | J82: 162400 | L82: =IF(D82=0,0,IFERROR(SUMIFS($AE$21:$AE$104,$AA$21:$AA$104,$E82,$AB$21:$AB$104,$G82),0)) -> 203685.45 | M82: =IF(D82=0,0,J82-L82) -> -41285.449 | N82: =IFERROR(J82/L82,"¥0") -> 0.79730781 | P82: =IF(D82=0,0,SUM($L$80:L82)) -> 372593.7 | Q82: =IF(D82=0,0,SUM($J$80:J82)) -> 285600 | R82: =IF(D82=0,0,Q82-P82) -> -86993.696 | S82: =IF(D82=0,0,Q82/P82) -> 0.76651861 | U82: =IF(D82=0,0,SUM($L$21:L82)) -> 11071541 | V82: =IF(D82=0,0,SUM($J$21:J82)) -> 11660900 | W82: =IF(D82=0,0,V82-U82) -> 589358.94 | X82: =IF(D82=0,0,V82/U82) -> 1.0532319 | Y82: =Y81+1 -> 45719 | Z82: =Z81+1 -> 45719 | AA82: 9 | AB82: Sat | AC82: =IFERROR(AVERAGEIFS(J264:J293,D264:D293,1,G264:G293,"sat"),0) -> 124766.67 | AD82: =COUNTIFS(D264:D293,1,G264:G293,"sat") -> 3 | AE82: =($I$15*実績_2024R6!AI81)/AD82 -> 100143.97 | AF82: =AD82*AE82 -> 300431.92 | AG82: 9月目標売り上げ
C83: 63 | D83: 1 | E83: =MONTH(Y83) -> 3 | F83: =F82+1 -> 45720 | G83: =TEXT(Z83,"ddd") -> Tue | J83: 156050 | L83: =IF(D83=0,0,IFERROR(SUMIFS($AE$21:$AE$104,$AA$21:$AA$104,$E83,$AB$21:$AB$104,$G83),0)) -> 293532.45 | M83: =IF(D83=0,0,J83-L83) -> -137482.45 | N83: =IFERROR(J83/L83,"¥0") -> 0.53162776 | P83: =IF(D83=0,0,SUM($L$80:L83)) -> 666126.15 | Q83: =IF(D83=0,0,SUM($J$80:J83)) -> 441650 | R83: =IF(D83=0,0,Q83-P83) -> -224476.15 | S83: =IF(D83=0,0,Q83/P83) -> 0.66301256 | U83: =IF(D83=0,0,SUM($L$21:L83)) -> 11365074 | V83: =IF(D83=0,0,SUM($J$21:J83)) -> 11816950 | W83: =IF(D83=0,0,V83-U83) -> 451876.49 | X83: =IF(D83=0,0,V83/U83) -> 1.0397601 | Y83: =Y82+1 -> 45720 | Z83: =Z82+1 -> 45720 | AA83: 9 | AB83: Sun | AC83: =IFERROR(AVERAGEIFS(J264:J293,D264:D293,1,G264:G293,"sun"),0) -> 0 | AD83: =IFERROR(COUNTIFS(D264:D293,1,G264:G293,"sun"),0) -> 0 | AE83: =IFERROR(($I$15*実績_2024R6!AI82)/AD83,0) -> 0 | AF83: =SUM(AF77:AF82) -> 3050526.3 | AG83: =I15 -> 3050526.3
C84: 64 | D84: 1 | E84: =MONTH(Y84) -> 3 | F84: =F83+1 -> 45721 | G84: =TEXT(Z84,"ddd") -> Wed | J84: 269410 | L84: =IF(D84=0,0,IFERROR(SUMIFS($AE$21:$AE$104,$AA$21:$AA$104,$E84,$AB$21:$AB$104,$G84),0)) -> 245154.79 | M84: =IF(D84=0,0,J84-L84) -> 24255.208 | N84: =IFERROR(J84/L84,"¥0") -> 1.0989383 | P84: =IF(D84=0,0,SUM($L$80:L84)) -> 911280.94 | Q84: =IF(D84=0,0,SUM($J$80:J84)) -> 711060 | R84: =IF(D84=0,0,Q84-P84) -> -200220.94 | S84: =IF(D84=0,0,Q84/P84) -> 0.78028627 | U84: =IF(D84=0,0,SUM($L$21:L84)) -> 11610228 | V84: =IF(D84=0,0,SUM($J$21:J84)) -> 12086360 | W84: =IF(D84=0,0,V84-U84) -> 476131.69 | X84: =IF(D84=0,0,V84/U84) -> 1.0410097 | Y84: =Y83+1 -> 45721 | Z84: =Z83+1 -> 45721 | AA84: 10 | AB84: Mon | AC84: =IFERROR(AVERAGEIFS(J294:J324,D294:D324,1,G294:G324,"mon"),0) -> 70123.333 | AD84: =COUNTIFS(D294:D324,1,G294:G324,"Mon") -> 3 | AE84: =($I$16*実績_2024R6!AI83)/AD84 -> 218508.48 | AF84: =AD84*AE84 -> 655525.44 | AG84: 294〜324
C85: 65 | D85: 1 | E85: =MONTH(Y85) -> 3 | F85: =F84+1 -> 45722 | G85: =TEXT(Z85,"ddd") -> Thu | J85: 371500 | L85: =IF(D85=0,0,IFERROR(SUMIFS($AE$21:$AE$104,$AA$21:$AA$104,$E85,$AB$21:$AB$104,$G85),0)) -> 457562.97 | M85: =IF(D85=0,0,J85-L85) -> -86062.972 | N85: =IFERROR(J85/L85,"¥0") -> 0.8119101 | P85: =IF(D85=0,0,SUM($L$80:L85)) -> 1368843.9 | Q85: =IF(D85=0,0,SUM($J$80:J85)) -> 1082560 | R85: =IF(D85=0,0,Q85-P85) -> -286283.91 | S85: =IF(D85=0,0,Q85/P85) -> 0.79085715 | U85: =IF(D85=0,0,SUM($L$21:L85)) -> 12067791 | V85: =IF(D85=0,0,SUM($J$21:J85)) -> 12457860 | W85: =IF(D85=0,0,V85-U85) -> 390068.72 | X85: =IF(D85=0,0,V85/U85) -> 1.0323231 | Y85: =Y84+1 -> 45722 | Z85: =Z84+1 -> 45722 | AA85: 10 | AB85: Tue | AC85: =IFERROR(AVERAGEIFS(J294:J324,D294:D324,1,G294:G324,"tue"),0) -> 152140 | AD85: =COUNTIFS(D294:D324,1,G294:G324,"tue") -> 4 | AE85: =($I$16*実績_2024R6!AI84)/AD85 -> 230383.6 | AF85: =AD85*AE85 -> 921534.42
C86: 66 | D86: 1 | E86: =MONTH(Y86) -> 3 | F86: =F85+1 -> 45723 | G86: =TEXT(Z86,"ddd") -> Fri | J86: 493250 | L86: =IF(D86=0,0,IFERROR(SUMIFS($AE$21:$AE$104,$AA$21:$AA$104,$E86,$AB$21:$AB$104,$G86),0)) -> 448451.04 | M86: =IF(D86=0,0,J86-L86) -> 44798.959 | N86: =IFERROR(J86/L86,"¥0") -> 1.0998971 | P86: =IF(D86=0,0,SUM($L$80:L86)) -> 1817295 | Q86: =IF(D86=0,0,SUM($J$80:J86)) -> 1575810 | R86: =IF(D86=0,0,Q86-P86) -> -241484.95 | S86: =IF(D86=0,0,Q86/P86) -> 0.86711846 | U86: =IF(D86=0,0,SUM($L$21:L86)) -> 12516242 | V86: =IF(D86=0,0,SUM($J$21:J86)) -> 12951110 | W86: =IF(D86=0,0,V86-U86) -> 434867.68 | X86: =IF(D86=0,0,V86/U86) -> 1.0347443 | Y86: =Y85+1 -> 45723 | Z86: =Z85+1 -> 45723 | AA86: 10 | AB86: Wed | AC86: =IFERROR(AVERAGEIFS(J294:J324,D294:D324,1,G294:G324,"wed"),0) -> 130114 | AD86: =COUNTIFS(D294:D324,1,G294:G324,"wed") -> 5 | AE86: =($I$16*実績_2024R6!AI85)/AD86 -> 198827.98 | AF86: =AD86*AE86 -> 994139.88
C87: 67 | D87: 1 | E87: =MONTH(Y87) -> 3 | F87: =F86+1 -> 45724 | G87: =TEXT(Z87,"ddd") -> Sat | J87: 129200 | L87: =IF(D87=0,0,IFERROR(SUMIFS($AE$21:$AE$104,$AA$21:$AA$104,$E87,$AB$21:$AB$104,$G87),0)) -> 168908.25 | M87: =IF(D87=0,0,J87-L87) -> -39708.246 | N87: =IFERROR(J87/L87,"¥0") -> 0.76491233 | P87: =IF(D87=0,0,SUM($L$80:L87)) -> 1986203.2 | Q87: =IF(D87=0,0,SUM($J$80:J87)) -> 1705010 | R87: =IF(D87=0,0,Q87-P87) -> -281193.2 | S87: =IF(D87=0,0,Q87/P87) -> 0.85842677 | U87: =IF(D87=0,0,SUM($L$21:L87)) -> 12685151 | V87: =IF(D87=0,0,SUM($J$21:J87)) -> 13080310 | W87: =IF(D87=0,0,V87-U87) -> 395159.43 | X87: =IF(D87=0,0,V87/U87) -> 1.0311513 | Y87: =Y86+1 -> 45724 | Z87: =Z86+1 -> 45724 | AA87: 10 | AB87: Thu | AC87: =IFERROR(AVERAGEIFS(J294:J324,D294:D324,1,G294:G324,"thu"),0) -> 163740 | AD87: =COUNTIFS(D294:D324,1,G294:G324,"thu") -> 5 | AE87: =($I$16*実績_2024R6!AI86)/AD87 -> 231857.04 | AF87: =AD87*AE87 -> 1159285.2
C88: 68 | D88: 0 | E88: =MONTH(Y88) -> 3 | F88: =F87+1 -> 45725 | G88: =TEXT(Z88,"ddd") -> Sun | L88: =IF(D88=0,0,IFERROR(SUMIFS($AE$21:$AE$104,$AA$21:$AA$104,$E88,$AB$21:$AB$104,$G88),0)) -> 0 | M88: =IF(D88=0,0,J88-L88) -> 0 | N88: =IFERROR(J88/L88,"¥0") -> ¥0 | P88: =IF(D88=0,0,SUM($L$80:L88)) -> 0 | Q88: =IF(D88=0,0,SUM($J$80:J88)) -> 0 | R88: =IF(D88=0,0,Q88-P88) -> 0 | S88: =IF(D88=0,0,Q88/P88) -> 0 | U88: =IF(D88=0,0,SUM($L$21:L88)) -> 0 | V88: =IF(D88=0,0,SUM($J$21:J88)) -> 0 | W88: =IF(D88=0,0,V88-U88) -> 0 | X88: =IF(D88=0,0,V88/U88) -> 0 | Y88: =Y87+1 -> 45725 | Z88: =Z87+1 -> 45725 | AA88: 10 | AB88: Fri | AC88: =IFERROR(AVERAGEIFS(J294:J324,D294:D324,1,G294:G324,"fri"),0) -> 216448 | AD88: =COUNTIFS(D294:D324,1,G294:G324,"fri") -> 5 | AE88: =($I$16*実績_2024R6!AI87)/AD88 -> 186910.18 | AF88: =AD88*AE88 -> 934550.89
C89: 69 | D89: 1 | E89: =MONTH(Y89) -> 3 | F89: =F88+1 -> 45726 | G89: =TEXT(Z89,"ddd") -> Mon | J89: 140470 | L89: =IF(D89=0,0,IFERROR(SUMIFS($AE$21:$AE$104,$AA$21:$AA$104,$E89,$AB$21:$AB$104,$G89),0)) -> 203685.45 | M89: =IF(D89=0,0,J89-L89) -> -63215.449 | N89: =IFERROR(J89/L89,"¥0") -> 0.6896418 | P89: =IF(D89=0,0,SUM($L$80:L89)) -> 2189888.6 | Q89: =IF(D89=0,0,SUM($J$80:J89)) -> 1845480 | R89: =IF(D89=0,0,Q89-P89) -> -344408.65 | S89: =IF(D89=0,0,Q89/P89) -> 0.84272778 | U89: =IF(D89=0,0,SUM($L$21:L89)) -> 12888836 | V89: =IF(D89=0,0,SUM($J$21:J89)) -> 13220780 | W89: =IF(D89=0,0,V89-U89) -> 331943.99 | X89: =IF(D89=0,0,V89/U89) -> 1.0257544 | Y89: =Y88+1 -> 45726 | Z89: =Z88+1 -> 45726 | AA89: 10 | AB89: Sat | AC89: =IFERROR(AVERAGEIFS(J294:J324,D294:D324,1,G294:G324,"sat"),0) -> 118390 | AD89: =COUNTIFS(D294:D324,1,G294:G324,"sat") -> 4 | AE89: =($I$16*実績_2024R6!AI88)/AD89 -> 126898.94 | AF89: =AD89*AE89 -> 507595.78 | AG89: 10月目標売り上げ
C90: 70 | D90: 1 | E90: =MONTH(Y90) -> 3 | F90: =F89+1 -> 45727 | G90: =TEXT(Z90,"ddd") -> Tue | J90: 379560 | L90: =IF(D90=0,0,IFERROR(SUMIFS($AE$21:$AE$104,$AA$21:$AA$104,$E90,$AB$21:$AB$104,$G90),0)) -> 293532.45 | M90: =IF(D90=0,0,J90-L90) -> 86027.55 | N90: =IFERROR(J90/L90,"¥0") -> 1.2930768 | P90: =IF(D90=0,0,SUM($L$80:L90)) -> 2483421.1 | Q90: =IF(D90=0,0,SUM($J$80:J90)) -> 2225040 | R90: =IF(D90=0,0,Q90-P90) -> -258381.1 | S90: =IF(D90=0,0,Q90/P90) -> 0.8959576 | U90: =IF(D90=0,0,SUM($L$21:L90)) -> 13182368 | V90: =IF(D90=0,0,SUM($J$21:J90)) -> 13600340 | W90: =IF(D90=0,0,V90-U90) -> 417971.54 | X90: =IF(D90=0,0,V90/U90) -> 1.0317069 | Y90: =Y89+1 -> 45727 | Z90: =Z89+1 -> 45727 | AA90: 10 | AB90: Sun | AC90: =IFERROR(AVERAGEIFS(J294:J324,D294:D324,1,G294:G324,"sun"),0) -> 0 | AD90: =IFERROR(COUNTIFS(D294:D324,1,G294:G324,"sun"),0) -> 0 | AE90: =IFERROR(($I$16*実績_2024R6!AI89)/AD90,0) -> 0 | AF90: =SUM(AF84:AF89) -> 5172631.6 | AG90: =I16 -> 5172631.6
C91: 71 | D91: 1 | E91: =MONTH(Y91) -> 3 | F91: =F90+1 -> 45728 | G91: =TEXT(Z91,"ddd") -> Wed | J91: 320100 | L91: =IF(D91=0,0,IFERROR(SUMIFS($AE$21:$AE$104,$AA$21:$AA$104,$E91,$AB$21:$AB$104,$G91),0)) -> 245154.79 | M91: =IF(D91=0,0,J91-L91) -> 74945.208 | N91: =IFERROR(J91/L91,"¥0") -> 1.3057057 | P91: =IF(D91=0,0,SUM($L$80:L91)) -> 2728575.9 | Q91: =IF(D91=0,0,SUM($J$80:J91)) -> 2545140 | R91: =IF(D91=0,0,Q91-P91) -> -183435.89 | S91: =IF(D91=0,0,Q91/P91) -> 0.9327723 | U91: =IF(D91=0,0,SUM($L$21:L91)) -> 13427523 | V91: =IF(D91=0,0,SUM($J$21:J91)) -> 13920440 | W91: =IF(D91=0,0,V91-U91) -> 492916.74 | X91: =IF(D91=0,0,V91/U91) -> 1.0367094 | Y91: =Y90+1 -> 45728 | Z91: =Z90+1 -> 45728 | AA91: 11 | AB91: Mon | AC91: =IFERROR(AVERAGEIFS(J325:J354,D325:D354,1,G325:G354,"mon"),0) -> 61975 | AD91: =COUNTIFS(D325:D354,1,G325:G354,"Mon") -> 2 | AE91: =($I$17*実績_2024R6!AI90)/AD91 -> 219995.68 | AF91: =AD91*AE91 -> 439991.35 | AG91: 325〜354
C92: 72 | D92: 1 | E92: =MONTH(Y92) -> 3 | F92: =F91+1 -> 45729 | G92: =TEXT(Z92,"ddd") -> Thu | J92: 327800 | L92: =IF(D92=0,0,IFERROR(SUMIFS($AE$21:$AE$104,$AA$21:$AA$104,$E92,$AB$21:$AB$104,$G92),0)) -> 457562.97 | M92: =IF(D92=0,0,J92-L92) -> -129762.97 | N92: =IFERROR(J92/L92,"¥0") -> 0.71640412 | P92: =IF(D92=0,0,SUM($L$80:L92)) -> 3186138.9 | Q92: =IF(D92=0,0,SUM($J$80:J92)) -> 2872940 | R92: =IF(D92=0,0,Q92-P92) -> -313198.86 | S92: =IF(D92=0,0,Q92/P92) -> 0.90169956 | U92: =IF(D92=0,0,SUM($L$21:L92)) -> 13885086 | V92: =IF(D92=0,0,SUM($J$21:J92)) -> 14248240 | W92: =IF(D92=0,0,V92-U92) -> 363153.77 | X92: =IF(D92=0,0,V92/U92) -> 1.0261542 | Y92: =Y91+1 -> 45729 | Z92: =Z91+1 -> 45729 | AA92: 11 | AB92: Tue | AC92: =IFERROR(AVERAGEIFS(J325:J354,D325:D354,1,G325:G354,"tue"),0) -> 166397.5 | AD92: =COUNTIFS(D325:D354,1,G325:G354,"tue") -> 4 | AE92: =($I$17*実績_2024R6!AI91)/AD92 -> 192620.47 | AF92: =AD92*AE92 -> 770481.88
C93: 73 | D93: 1 | E93: =MONTH(Y93) -> 3 | F93: =F92+1 -> 45730 | G93: =TEXT(Z93,"ddd") -> Fri | J93: 409660 | L93: =IF(D93=0,0,IFERROR(SUMIFS($AE$21:$AE$104,$AA$21:$AA$104,$E93,$AB$21:$AB$104,$G93),0)) -> 448451.04 | M93: =IF(D93=0,0,J93-L93) -> -38791.041 | N93: =IFERROR(J93/L93,"¥0") -> 0.91349994 | P93: =IF(D93=0,0,SUM($L$80:L93)) -> 3634589.9 | Q93: =IF(D93=0,0,SUM($J$80:J93)) -> 3282600 | R93: =IF(D93=0,0,Q93-P93) -> -351989.9 | S93: =IF(D93=0,0,Q93/P93) -> 0.90315554 | U93: =IF(D93=0,0,SUM($L$21:L93)) -> 14333537 | V93: =IF(D93=0,0,SUM($J$21:J93)) -> 14657900 | W93: =IF(D93=0,0,V93-U93) -> 324362.73 | X93: =IF(D93=0,0,V93/U93) -> 1.0226296 | Y93: =Y92+1 -> 45730 | Z93: =Z92+1 -> 45730 | AA93: 11 | AB93: Wed | AC93: =IFERROR(AVERAGEIFS(J325:J354,D325:D354,1,G325:G354,"wed"),0) -> 188960 | AD93: =COUNTIFS(D325:D354,1,G325:G354,"wed") -> 4 | AE93: =($I$17*実績_2024R6!AI92)/AD93 -> 222098.1 | AF93: =AD93*AE93 -> 888392.41
C94: 74 | D94: 1 | E94: =MONTH(Y94) -> 3 | F94: =F93+1 -> 45731 | G94: =TEXT(Z94,"ddd") -> Sat | J94: 139390 | L94: =IF(D94=0,0,IFERROR(SUMIFS($AE$21:$AE$104,$AA$21:$AA$104,$E94,$AB$21:$AB$104,$G94),0)) -> 168908.25 | M94: =IF(D94=0,0,J94-L94) -> -29518.246 | N94: =IFERROR(J94/L94,"¥0") -> 0.82524094 | P94: =IF(D94=0,0,SUM($L$80:L94)) -> 3803498.1 | Q94: =IF(D94=0,0,SUM($J$80:J94)) -> 3421990 | R94: =IF(D94=0,0,Q94-P94) -> -381508.15 | S94: =IF(D94=0,0,Q94/P94) -> 0.89969546 | U94: =IF(D94=0,0,SUM($L$21:L94)) -> 14502446 | V94: =IF(D94=0,0,SUM($J$21:J94)) -> 14797290 | W94: =IF(D94=0,0,V94-U94) -> 294844.48 | X94: =IF(D94=0,0,V94/U94) -> 1.0203307 | Y94: =Y93+1 -> 45731 | Z94: =Z93+1 -> 45731 | AA94: 11 | AB94: Thu | AC94: =IFERROR(AVERAGEIFS(J325:J354,D325:D354,1,G325:G354,"thu"),0) -> 191240 | AD94: =COUNTIFS(D325:D354,1,G325:G354,"thu") -> 4 | AE94: =($I$17*実績_2024R6!AI93)/AD94 -> 216358.54 | AF94: =AD94*AE94 -> 865434.17
C95: 75 | D95: 0 | E95: =MONTH(Y95) -> 3 | F95: =F94+1 -> 45732 | G95: =TEXT(Z95,"ddd") -> Sun | L95: =IF(D95=0,0,IFERROR(SUMIFS($AE$21:$AE$104,$AA$21:$AA$104,$E95,$AB$21:$AB$104,$G95),0)) -> 0 | M95: =IF(D95=0,0,J95-L95) -> 0 | N95: =IFERROR(J95/L95,"¥0") -> ¥0 | P95: =IF(D95=0,0,SUM($L$80:L95)) -> 0 | Q95: =IF(D95=0,0,SUM($J$80:J95)) -> 0 | R95: =IF(D95=0,0,Q95-P95) -> 0 | S95: =IF(D95=0,0,Q95/P95) -> 0 | U95: =IF(D95=0,0,SUM($L$21:L95)) -> 0 | V95: =IF(D95=0,0,SUM($J$21:J95)) -> 0 | W95: =IF(D95=0,0,V95-U95) -> 0 | X95: =IF(D95=0,0,V95/U95) -> 0 | Y95: =Y94+1 -> 45732 | Z95: =Z94+1 -> 45732 | AA95: 11 | AB95: Fri | AC95: =IFERROR(AVERAGEIFS(J325:J354,D325:D354,1,G325:G354,"fri"),0) -> 252295 | AD95: =COUNTIFS(D325:D354,1,G325:G354,"fri") -> 4 | AE95: =($I$17*実績_2024R6!AI94)/AD95 -> 346355.42 | AF95: =AD95*AE95 -> 1385421.7
C96: 76 | D96: 1 | E96: =MONTH(Y96) -> 3 | F96: =F95+1 -> 45733 | G96: =TEXT(Z96,"ddd") -> Mon | J96: 329600 | L96: =IF(D96=0,0,IFERROR(SUMIFS($AE$21:$AE$104,$AA$21:$AA$104,$E96,$AB$21:$AB$104,$G96),0)) -> 203685.45 | M96: =IF(D96=0,0,J96-L96) -> 125914.55 | N96: =IFERROR(J96/L96,"¥0") -> 1.6181814 | P96: =IF(D96=0,0,SUM($L$80:L96)) -> 4007183.6 | Q96: =IF(D96=0,0,SUM($J$80:J96)) -> 3751590 | R96: =IF(D96=0,0,Q96-P96) -> -255593.6 | S96: =IF(D96=0,0,Q96/P96) -> 0.93621615 | U96: =IF(D96=0,0,SUM($L$21:L96)) -> 14706131 | V96: =IF(D96=0,0,SUM($J$21:J96)) -> 15126890 | W96: =IF(D96=0,0,V96-U96) -> 420759.03 | X96: =IF(D96=0,0,V96/U96) -> 1.0286111 | Y96: =Y95+1 -> 45733 | Z96: =Z95+1 -> 45733 | AA96: 11 | AB96: Sat | AC96: =IFERROR(AVERAGEIFS(J325:J354,D325:D354,1,G325:G354,"sat"),0) -> 93924 | AD96: =COUNTIFS(D325:D354,1,G325:G354,"sat") -> 5 | AE96: =($I$17*実績_2024R6!AI95)/AD96 -> 146897.8 | AF96: =AD96*AE96 -> 734489.02 | AG96: 11月目標売り上げ
C97: 77 | D97: 1 | E97: =MONTH(Y97) -> 3 | F97: =F96+1 -> 45734 | G97: =TEXT(Z97,"ddd") -> Tue | J97: 373470 | L97: =IF(D97=0,0,IFERROR(SUMIFS($AE$21:$AE$104,$AA$21:$AA$104,$E97,$AB$21:$AB$104,$G97),0)) -> 293532.45 | M97: =IF(D97=0,0,J97-L97) -> 79937.55 | N97: =IFERROR(J97/L97,"¥0") -> 1.2723295 | P97: =IF(D97=0,0,SUM($L$80:L97)) -> 4300716 | Q97: =IF(D97=0,0,SUM($J$80:J97)) -> 4125060 | R97: =IF(D97=0,0,Q97-P97) -> -175656.05 | S97: =IF(D97=0,0,Q97/P97) -> 0.95915656 | U97: =IF(D97=0,0,SUM($L$21:L97)) -> 14999663 | V97: =IF(D97=0,0,SUM($J$21:J97)) -> 15500360 | W97: =IF(D97=0,0,V97-U97) -> 500696.58 | X97: =IF(D97=0,0,V97/U97) -> 1.0333805 | Y97: =Y96+1 -> 45734 | Z97: =Z96+1 -> 45734 | AA97: 11 | AB97: Sun | AC97: =IFERROR(AVERAGEIFS(J325:J354,D325:D354,1,G325:G354,"sun"),0) -> 0 | AD97: =IFERROR(COUNTIFS(D325:D354,1,G325:G354,"sun"),0) -> 0 | AE97: =IFERROR(($I$17*実績_2024R6!AI96)/AD97,0) -> 0 | AF97: =SUM(AF91:AF96) -> 5084210.5 | AG97: =I17 -> 5084210.5
C98: 78 | D98: 1 | E98: =MONTH(Y98) -> 3 | F98: =F97+1 -> 45735 | G98: =TEXT(Z98,"ddd") -> Wed | J98: 383950 | L98: =IF(D98=0,0,IFERROR(SUMIFS($AE$21:$AE$104,$AA$21:$AA$104,$E98,$AB$21:$AB$104,$G98),0)) -> 245154.79 | M98: =IF(D98=0,0,J98-L98) -> 138795.21 | N98: =IFERROR(J98/L98,"¥0") -> 1.5661534 | P98: =IF(D98=0,0,SUM($L$80:L98)) -> 4545870.8 | Q98: =IF(D98=0,0,SUM($J$80:J98)) -> 4509010 | R98: =IF(D98=0,0,Q98-P98) -> -36860.839 | S98: =IF(D98=0,0,Q98/P98) -> 0.99189136 | U98: =IF(D98=0,0,SUM($L$21:L98)) -> 15244818 | V98: =IF(D98=0,0,SUM($J$21:J98)) -> 15884310 | W98: =IF(D98=0,0,V98-U98) -> 639491.79 | X98: =IF(D98=0,0,V98/U98) -> 1.0419481 | Y98: =Y97+1 -> 45735 | Z98: =Z97+1 -> 45735 | AA98: 12 | AB98: Mon | AC98: =IFERROR(AVERAGEIFS(J355:J385,D355:D385,1,G355:G385,"mon"),0) -> 0 | AD98: =COUNTIFS(D355:D385,1,G355:G385,"Mon") -> 4 | AE98: =($I$18*実績_2024R6!AI97)/AD98 -> 209685.65 | AF98: =AD98*AE98 -> 838742.6 | AG98: 355〜385
C99: 79 | D99: 0 | E99: =MONTH(Y99) -> 3 | F99: =F98+1 -> 45736 | G99: =TEXT(Z99,"ddd") -> Thu | L99: =IF(D99=0,0,IFERROR(SUMIFS($AE$21:$AE$104,$AA$21:$AA$104,$E99,$AB$21:$AB$104,$G99),0)) -> 0 | M99: =IF(D99=0,0,J99-L99) -> 0 | N99: =IFERROR(J99/L99,"¥0") -> ¥0 | P99: =IF(D99=0,0,SUM($L$80:L99)) -> 0 | Q99: =IF(D99=0,0,SUM($J$80:J99)) -> 0 | R99: =IF(D99=0,0,Q99-P99) -> 0 | S99: =IF(D99=0,0,Q99/P99) -> 0 | U99: =IF(D99=0,0,SUM($L$21:L99)) -> 0 | V99: =IF(D99=0,0,SUM($J$21:J99)) -> 0 | W99: =IF(D99=0,0,V99-U99) -> 0 | X99: =IF(D99=0,0,V99/U99) -> 0 | Y99: =Y98+1 -> 45736 | Z99: =Z98+1 -> 45736 | AA99: 12 | AB99: Tue | AC99: =IFERROR(AVERAGEIFS(J355:J385,D355:D385,1,G355:G385,"tue"),0) -> 0 | AD99: =COUNTIFS(D355:D385,1,G355:G385,"tue") -> 4 | AE99: =($I$18*実績_2024R6!AI98)/AD99 -> 230766.14 | AF99: =AD99*AE99 -> 923064.55
C100: 80 | D100: 1 | E100: =MONTH(Y100) -> 3 | F100: =F99+1 -> 45737 | G100: =TEXT(Z100,"ddd") -> Fri | J100: 283190 | L100: =IF(D100=0,0,IFERROR(SUMIFS($AE$21:$AE$104,$AA$21:$AA$104,$E100,$AB$21:$AB$104,$G100),0)) -> 448451.04 | M100: =IF(D100=0,0,J100-L100) -> -165261.04 | N100: =IFERROR(J100/L100,"¥0") -> 0.63148476 | P100: =IF(D100=0,0,SUM($L$80:L100)) -> 4994321.9 | Q100: =IF(D100=0,0,SUM($J$80:J100)) -> 4792200 | R100: =IF(D100=0,0,Q100-P100) -> -202121.88 | S100: =IF(D100=0,0,Q100/P100) -> 0.95952966 | U100: =IF(D100=0,0,SUM($L$21:L100)) -> 15693269 | V100: =IF(D100=0,0,SUM($J$21:J100)) -> 16167500 | W100: =IF(D100=0,0,V100-U100) -> 474230.75 | X100: =IF(D100=0,0,V100/U100) -> 1.0302187 | Y100: =Y99+1 -> 45737 | Z100: =Z99+1 -> 45737 | AA100: 12 | AB100: Wed | AC100: =IFERROR(AVERAGEIFS(J355:J385,D355:D385,1,G355:G385,"wed"),0) -> 0 | AD100: =COUNTIFS(D355:D385,1,G355:G385,"wed") -> 4 | AE100: =($I$18*実績_2024R6!AI99)/AD100 -> 286865.65 | AF100: =AD100*AE100 -> 1147462.6
C101: 81 | D101: 1 | E101: =MONTH(Y101) -> 3 | F101: =F100+1 -> 45738 | G101: =TEXT(Z101,"ddd") -> Sat | J101: 300980 | L101: =IF(D101=0,0,IFERROR(SUMIFS($AE$21:$AE$104,$AA$21:$AA$104,$E101,$AB$21:$AB$104,$G101),0)) -> 168908.25 | M101: =IF(D101=0,0,J101-L101) -> 132071.75 | N101: =IFERROR(J101/L101,"¥0") -> 1.7819142 | P101: =IF(D101=0,0,SUM($L$80:L101)) -> 5163230.1 | Q101: =IF(D101=0,0,SUM($J$80:J101)) -> 5093180 | R101: =IF(D101=0,0,Q101-P101) -> -70050.126 | S101: =IF(D101=0,0,Q101/P101) -> 0.98643289 | U101: =IF(D101=0,0,SUM($L$21:L101)) -> 15862177 | V101: =IF(D101=0,0,SUM($J$21:J101)) -> 16468480 | W101: =IF(D101=0,0,V101-U101) -> 606302.51 | X101: =IF(D101=0,0,V101/U101) -> 1.0382232 | Y101: =Y100+1 -> 45738 | Z101: =Z100+1 -> 45738 | AA101: 12 | AB101: Thu | AC101: =IFERROR(AVERAGEIFS(J355:J385,D355:D385,1,G355:G385,"thu"),0) -> 0 | AD101: =COUNTIFS(D355:D385,1,G355:G385,"thu") -> 4 | AE101: =($I$18*実績_2024R6!AI100)/AD101 -> 248339.37 | AF101: =AD101*AE101 -> 993357.46
C102: 82 | D102: 0 | E102: =MONTH(Y102) -> 3 | F102: =F101+1 -> 45739 | G102: =TEXT(Z102,"ddd") -> Sun | L102: =IF(D102=0,0,IFERROR(SUMIFS($AE$21:$AE$104,$AA$21:$AA$104,$E102,$AB$21:$AB$104,$G102),0)) -> 0 | M102: =IF(D102=0,0,J102-L102) -> 0 | N102: =IFERROR(J102/L102,"¥0") -> ¥0 | P102: =IF(D102=0,0,SUM($L$80:L102)) -> 0 | Q102: =IF(D102=0,0,SUM($J$80:J102)) -> 0 | R102: =IF(D102=0,0,Q102-P102) -> 0 | S102: =IF(D102=0,0,Q102/P102) -> 0 | U102: =IF(D102=0,0,SUM($L$21:L102)) -> 0 | V102: =IF(D102=0,0,SUM($J$21:J102)) -> 0 | W102: =IF(D102=0,0,V102-U102) -> 0 | X102: =IF(D102=0,0,V102/U102) -> 0 | Y102: =Y101+1 -> 45739 | Z102: =Z101+1 -> 45739 | AA102: 12 | AB102: Fri | AC102: =IFERROR(AVERAGEIFS(J355:J385,D355:D385,1,G355:G385,"fri"),0) -> 0 | AD102: =COUNTIFS(D355:D385,1,G355:G385,"fri") -> 4 | AE102: =($I$18*実績_2024R6!AI101)/AD102 -> 309192.79 | AF102: =AD102*AE102 -> 1236771.2
C103: 83 | D103: 1 | E103: =MONTH(Y103) -> 3 | F103: =F102+1 -> 45740 | G103: =TEXT(Z103,"ddd") -> Mon | J103: 204700 | L103: =IF(D103=0,0,IFERROR(SUMIFS($AE$21:$AE$104,$AA$21:$AA$104,$E103,$AB$21:$AB$104,$G103),0)) -> 203685.45 | M103: =IF(D103=0,0,J103-L103) -> 1014.5509 | N103: =IFERROR(J103/L103,"¥0") -> 1.004981 | P103: =IF(D103=0,0,SUM($L$80:L103)) -> 5366915.6 | Q103: =IF(D103=0,0,SUM($J$80:J103)) -> 5297880 | R103: =IF(D103=0,0,Q103-P103) -> -69035.576 | S103: =IF(D103=0,0,Q103/P103) -> 0.98713682 | U103: =IF(D103=0,0,SUM($L$21:L103)) -> 16065863 | V103: =IF(D103=0,0,SUM($J$21:J103)) -> 16673180 | W103: =IF(D103=0,0,V103-U103) -> 607317.06 | X103: =IF(D103=0,0,V103/U103) -> 1.0378017 | Y103: =Y102+1 -> 45740 | Z103: =Z102+1 -> 45740 | AA103: 12 | AB103: Sat | AC103: =IFERROR(AVERAGEIFS(J355:J385,D355:D385,1,G355:G385,"sat"),0) -> 0 | AD103: =COUNTIFS(D355:D385,1,G355:G385,"sat") -> 4 | AE103: =($I$18*実績_2024R6!AI102)/AD103 -> 174097.78 | AF103: =AD103*AE103 -> 696391.13 | AG103: 12月目標売り上げ
...

Sheet 目標_2025R7 (2)
B2: 45658 | E2: ①年間営業日 | G2: ②年間目標売上 | H2: 年間総売上％ | K2: 年間売上合計 | M2: 実質売上 | P2: 1月 | Q2: 2月 | R2: 3月 | S2: 4月 | T2: ←目標の月へジャンプ
E3: =SUM(F7:F18) -> 286 | G3: 80000000 | H3: =SUM(AD7:AD18)*100 -> 0.999996 | I3: =G3*H3 -> 79999680 | K3: =SUM(J21:J385) -> 31748860 | M3: =K3-G3 -> -48251140 | P3: 5月 | Q3: 6月 | R3: 7月 | S3: 8月
P4: 9月 | Q4: 10月 | R4: 11月 | S4: 12月
B6: 平均日次売上目標額 | E6: 月 | F6: 月次営業日数 | G6: 平均月間売上目標額 | H6: 月次繁閑期%設定 | I6: 月次目標売上 | K6: 日次目標売上 | M6: 月次売上実績 | N6: 月間KGI | P6: 月次平均%(繁閑期) | Q6: 月次実質%
B7: ② ÷ ① | E7: 1月 | F7: =COUNTIF(D21:D51,1) -> 22 | G7: =$B$8*F7 -> 6153846.2 | H7: 0.95 | I7: =G7*H7 -> 5846153.8 | K7: =I7/F7 -> 265734.27 | M7: =SUM(J21:J51) -> 6005630 | N7: =M7-I7 -> 159476.15 | P7: =M7/G7 -> 0.97591487 | Q7: =M7/I7 -> 1.0272788 | AA7: =TEXT(K7,"¥0") -> ¥265734 | AD7: =(H7/100)*AE7 -> 0.0007916635 | AE7: 0.083333
B8: =G3/E3 -> 279720.28 | E8: 2月 | F8: =COUNTIF(D52:D79,1) -> 22 | G8: =$B$8*F8 -> 6153846.2 | H8: 0.85 | I8: =G8*H8 -> 5230769.2 | K8: =I8/F8 -> 237762.24 | M8: =SUM(J52:J79) -> 5377670 | N8: =M8-I8 -> 146900.77 | P8: =M8/G8 -> 0.87387138 | Q8: =M8/I8 -> 1.028084 | AA8: =TEXT(K8,"¥0") -> ¥237762 | AD8: =(H8/100)*AE8 -> 0.0007083305 | AE8: 0.083333
E9: 3月 | F9: =COUNTIF(D80:D110,1) -> 25 | G9: =$B$8*F9 -> 6993007 | H9: 1.1 | I9: =G9*H9 -> 7692307.7 | K9: =I9/F9 -> 307692.31 | M9: =SUM(J80:J110) -> 7195290 | N9: =M9-I9 -> -497017.69 | P9: =M9/G9 -> 1.0289265 | Q9: =M9/I9 -> 0.9353877 | AA9: =TEXT(K9,"¥0") -> ¥307692 | AD9: =(H9/100)*AE9 -> 0.000916663 | AE9: 0.083333
E10: 4月 | F10: =COUNTIF(D111:D140,1) -> 25 | G10: =$B$8*F10 -> 6993007 | H10: 1.1 | I10: =G10*H10 -> 7692307.7 | K10: =I10/F10 -> 307692.31 | M10: =SUM(J111:J140) -> 7238940 | N10: =M10-I10 -> -453367.69 | P10: =M10/G10 -> 1.0351684 | Q10: =M10/I10 -> 0.9410622 | AA10: =TEXT(K10,"¥0") -> ¥307692 | AD10: =(H10/100)*AE10 -> 0.000916663 | AE10: 0.083333
E11: 5月 | F11: =COUNTIF(D141:D171,1) -> 24 | G11: =$B$8*F11 -> 6713286.7 | H11: 0.85 | I11: =G11*H11 -> 5706293.7 | K11: =I11/F11 -> 237762.24 | M11: =SUM(J141:J171) -> 5931330 | N11: =M11-I11 -> 225036.29 | P11: =M11/G11 -> 0.88352103 | Q11: =M11/I11 -> 1.0394365 | AA11: =TEXT(K11,"¥0") -> ¥237762 | AD11: =(H11/100)*AE11 -> 0.0007083305 | AE11: 0.083333
E12: 6月 | F12: =COUNTIF(D172:D201,1) -> 25 | G12: =$B$8*F12 -> 6993007 | H12: 0.8 | I12: =G12*H12 -> 5594405.6 | K12: =I12/F12 -> 223776.22 | M12: =SUM(J172:J201) -> 0 | N12: =M12-I12 -> -5594405.6 | P12: =M12/G12 -> 0 | Q12: =M12/I12 -> 0 | AA12: =TEXT(K12,"¥0") -> ¥223776 | AD12: =(H12/100)*AE12 -> 0.000666664 | AE12: 0.083333
E13: 7月 | F13: =COUNTIF(D202:D232,1) -> 26 | G13: =$B$8*F13 -> 7272727.3 | H13: 0.9 | I13: =G13*H13 -> 6545454.5 | K13: =I13/F13 -> 251748.25 | M13: =SUM(J202:J232) -> 0 | N13: =M13-I13 -> -6545454.5 | P13: =M13/G13 -> 0 | Q13: =M13/I13 -> 0 | AA13: =TEXT(K13,"¥0") -> ¥251748 | AD13: =(H13/100)*AE13 -> 0.000749997 | AE13: 0.083333
E14: 8月 | F14: =COUNTIF(D233:D263,1) -> 20 | G14: =$B$8*F14 -> 5594405.6 | H14: 1 | I14: =G14*H14 -> 5594405.6 | K14: =I14/F14 -> 279720.28 | M14: =SUM(J233:J263) -> 0 | N14: =M14-I14 -> -5594405.6 | P14: =M14/G14 -> 0 | Q14: =M14/I14 -> 0 | AA14: =TEXT(K14,"¥0") -> ¥279720 | AD14: =(H14/100)*AE14 -> 0.00083333 | AE14: 0.083333
E15: 9 月 | F15: =COUNTIF(D264:D293,1) -> 24 | G15: =$B$8*F15 -> 6713286.7 | H15: 1 | I15: =G15*H15 -> 6713286.7 | K15: =I15/F15 -> 279720.28 | M15: =SUM(J264:J293) -> 0 | N15: =M15-I15 -> -6713286.7 | P15: =M15/G15 -> 0 | Q15: =M15/I15 -> 0 | AA15: =TEXT(K15,"¥0") -> ¥279720 | AD15: =(H15/100)*AE15 -> 0.00083333 | AE15: 0.083333
E16: 10月 | F16: =COUNTIF(D294:D324,1) -> 26 | G16: =$B$8*F16 -> 7272727.3 | H16: 1.05 | I16: =G16*H16 -> 7636363.6 | K16: =I16/F16 -> 293706.29 | M16: =SUM(J294:J324) -> 0 | N16: =M16-I16 -> -7636363.6 | P16: =M16/G16 -> 0 | Q16: =M16/I16 -> 0 | AA16: =TEXT(K16,"¥0") -> ¥293706 | AD16: =(H16/100)*AE16 -> 0.0008749965 | AE16: 0.083333
E17: 11月 | F17: =COUNTIF(D325:D354,1) -> 23 | G17: =$B$8*F17 -> 6433566.4 | H17: 1.2 | I17: =G17*H17 -> 7720279.7 | K17: =I17/F17 -> 335664.34 | M17: =SUM(J325:J354) -> 0 | N17: =M17-I17 -> -7720279.7 | P17: =M17/G17 -> 0 | Q17: =M17/I17 -> 0 | AA17: =TEXT(K17,"¥0") -> ¥335664 | AD17: =(H17/100)*AE17 -> 0.000999996 | AE17: 0.083333
E18: 12月 | F18: =COUNTIF(D355:D385,1) -> 24 | G18: =$B$8*F18 -> 6713286.7 | H18: 1.2 | I18: =G18*H18 -> 8055944.1 | K18: =I18/F18 -> 335664.34 | M18: =SUM(J355:J385) -> 0 | N18: =M18-I18 -> -8055944.1 | P18: =M18/G18 -> 0 | Q18: =M18/I18 -> 0 | AA18: =TEXT(K18,"¥0") -> ¥335664 | AD18: =(H18/100)*AE18 -> 0.000999996 | AE18: 0.083333
E20: 月 | F20: 日程 | G20: 曜日 | H20: 日祝日 | J20: Daily売上入力 | L20: 目標売上 | M20: 実質売上 | N20: 実質% | P20: 月次目標売上 | Q20: 月次実質売上 | R20: 月次差額 | S20: 月次達成率 | U20: 年次目標売上 | V20: 年次実質売上 | W20: 年次差額 | X20: 年次達成率
C21: 1 | D21: 0 | E21: =MONTH(Y21) -> 1 | F21: =B2 -> 45658 | G21: =TEXT(Z21,"ddd") -> Wed | H21: 元旦 | L21: =IF(D21=0,0,$K$7) -> 0 | M21: =IF(D21=0,0,J21-L21) -> 0 | N21: =IFERROR(J21/L21,"¥0") -> ¥0 | P21: =IF(D21=0,0,$K$7) -> 0 | Q21: =IF(D21=0,0,$J$21) -> 0 | R21: =IF(D21=0,0,Q21-P21) -> 0 | S21: =IF(D21=0,0,Q21/P21) -> 0 | U21: =IF(D21=0,0,$L$21) -> 0 | V21: =IF(D21=0,0,$J$21) -> 0 | W21: =IF(D21=0,0,V21-U21) -> 0 | X21: =IF(D21=0,0,V21/U21) -> 0 | Y21: =B2 -> 45658 | Z21: =B2 -> 45658
C22: 2 | D22: 0 | E22: =MONTH(Y22) -> 1 | F22: =F21+1 -> 45659 | G22: =TEXT(Z22,"ddd") -> Thu | H22: 休み | L22: =IF(D22=0,0,$K$7) -> 0 | M22: =IF(D22=0,0,J22-L22) -> 0 | N22: =IFERROR(J22/L22,"¥0") -> ¥0 | P22: =IF(D22=0,0,SUM($L$21:L22)) -> 0 | Q22: =IF(D22=0,0,SUM($J$21:J22)) -> 0 | R22: =IF(D22=0,0,Q22-P22) -> 0 | S22: =IF(D22=0,0,Q22/P22) -> 0 | U22: =IF(D22=0,0,SUM($L$21:L22)) -> 0 | V22: =IF(D22=0,0,SUM($J$21:J22)) -> 0 | W22: =IF(D22=0,0,V22-U22) -> 0 | X22: =IF(D22=0,0,V22/U22) -> 0 | Y22: =Y21+1 -> 45659 | Z22: =Z21+1 -> 45659
C23: 3 | D23: 0 | E23: =MONTH(Y23) -> 1 | F23: =F22+1 -> 45660 | G23: =TEXT(Z23,"ddd") -> Fri | H23: 休み | L23: =IF(D23=0,0,$K$7) -> 0 | M23: =IF(D23=0,0,J23-L23) -> 0 | N23: =IFERROR(J23/L23,"¥0") -> ¥0 | P23: =IF(D23=0,0,SUM($L$21:L23)) -> 0 | Q23: =IF(D23=0,0,SUM($J$21:J23)) -> 0 | R23: =IF(D23=0,0,Q23-P23) -> 0 | S23: =IF(D23=0,0,Q23/P23) -> 0 | U23: =IF(D23=0,0,SUM($L$21:L23)) -> 0 | V23: =IF(D23=0,0,SUM($J$21:J23)) -> 0 | W23: =IF(D23=0,0,V23-U23) -> 0 | X23: =IF(D23=0,0,V23/U23) -> 0 | Y23: =Y22+1 -> 45660 | Z23: =Z22+1 -> 45660
C24: 4 | D24: 0 | E24: =MONTH(Y24) -> 1 | F24: =F23+1 -> 45661 | G24: =TEXT(Z24,"ddd") -> Sat | H24: 休み | L24: =IF(D24=0,0,$K$7) -> 0 | M24: =IF(D24=0,0,J24-L24) -> 0 | N24: =IFERROR(J24/L24,"¥0") -> ¥0 | P24: =IF(D24=0,0,SUM($L$21:L24)) -> 0 | Q24: =IF(D24=0,0,SUM($J$21:J24)) -> 0 | R24: =IF(D24=0,0,Q24-P24) -> 0 | S24: =IF(D24=0,0,Q24/P24) -> 0 | U24: =IF(D24=0,0,SUM($L$21:L24)) -> 0 | V24: =IF(D24=0,0,SUM($J$21:J24)) -> 0 | W24: =IF(D24=0,0,V24-U24) -> 0 | X24: =IF(D24=0,0,V24/U24) -> 0 | Y24: =Y23+1 -> 45661 | Z24: =Z23+1 -> 45661
C25: 5 | D25: 0 | E25: =MONTH(Y25) -> 1 | F25: =F24+1 -> 45662 | G25: =TEXT(Z25,"ddd") -> Sun | H25: 日曜日 | L25: =IF(D25=0,0,$K$7) -> 0 | M25: =IF(D25=0,0,J25-L25) -> 0 | N25: =IFERROR(J25/L25,"¥0") -> ¥0 | P25: =IF(D25=0,0,SUM($L$21:L25)) -> 0 | Q25: =IF(D25=0,0,SUM($J$21:J25)) -> 0 | R25: =IF(D25=0,0,Q25-P25) -> 0 | S25: =IF(D25=0,0,Q25/P25) -> 0 | U25: =IF(D25=0,0,SUM($L$21:L25)) -> 0 | V25: =IF(D25=0,0,SUM($J$21:J25)) -> 0 | W25: =IF(D25=0,0,V25-U25) -> 0 | X25: =IF(D25=0,0,V25/U25) -> 0 | Y25: =Y24+1 -> 45662 | Z25: =Z24+1 -> 45662
C26: 6 | D26: 1 | E26: =MONTH(Y26) -> 1 | F26: =F25+1 -> 45663 | G26: =TEXT(Z26,"ddd") -> Mon | J26: 349800 | L26: =IF(D26=0,0,$K$7) -> 265734.27 | M26: =IF(D26=0,0,J26-L26) -> 84065.734 | N26: =IFERROR(J26/L26,"¥0") -> 1.3163526 | P26: =IF(D26=0,0,SUM($L$21:L26)) -> 265734.27 | Q26: =IF(D26=0,0,SUM($J$21:J26)) -> 349800 | R26: =IF(D26=0,0,Q26-P26) -> 84065.734 | S26: =IF(D26=0,0,Q26/P26) -> 1.3163526 | U26: =IF(D26=0,0,SUM($L$21:L26)) -> 265734.27 | V26: =IF(D26=0,0,SUM($J$21:J26)) -> 349800 | W26: =IF(D26=0,0,V26-U26) -> 84065.734 | X26: =IF(D26=0,0,V26/U26) -> 1.3163526 | Y26: =Y25+1 -> 45663 | Z26: =Z25+1 -> 45663
C27: 7 | D27: 1 | E27: =MONTH(Y27) -> 1 | F27: =F26+1 -> 45664 | G27: =TEXT(Z27,"ddd") -> Tue | J27: 88530 | L27: =IF(D27=0,0,$K$7) -> 265734.27 | M27: =IF(D27=0,0,J27-L27) -> -177204.27 | N27: =IFERROR(J27/L27,"¥0") -> 0.33315237 | P27: =IF(D27=0,0,SUM($L$21:L27)) -> 531468.53 | Q27: =IF(D27=0,0,SUM($J$21:J27)) -> 438330 | R27: =IF(D27=0,0,Q27-P27) -> -93138.531 | S27: =IF(D27=0,0,Q27/P27) -> 0.8247525 | U27: =IF(D27=0,0,SUM($L$21:L27)) -> 531468.53 | V27: =IF(D27=0,0,SUM($J$21:J27)) -> 438330 | W27: =IF(D27=0,0,V27-U27) -> -93138.531 | X27: =IF(D27=0,0,V27/U27) -> 0.8247525 | Y27: =Y26+1 -> 45664 | Z27: =Z26+1 -> 45664
C28: 8 | D28: 1 | E28: =MONTH(Y28) -> 1 | F28: =F27+1 -> 45665 | G28: =TEXT(Z28,"ddd") -> Wed | J28: 177630 | L28: =IF(D28=0,0,$K$7) -> 265734.27 | M28: =IF(D28=0,0,J28-L28) -> -88104.266 | N28: =IFERROR(J28/L28,"¥0") -> 0.66844974 | P28: =IF(D28=0,0,SUM($L$21:L28)) -> 797202.8 | Q28: =IF(D28=0,0,SUM($J$21:J28)) -> 615960 | R28: =IF(D28=0,0,Q28-P28) -> -181242.8 | S28: =IF(D28=0,0,Q28/P28) -> 0.77265158 | U28: =IF(D28=0,0,SUM($L$21:L28)) -> 797202.8 | V28: =IF(D28=0,0,SUM($J$21:J28)) -> 615960 | W28: =IF(D28=0,0,V28-U28) -> -181242.8 | X28: =IF(D28=0,0,V28/U28) -> 0.77265158 | Y28: =Y27+1 -> 45665 | Z28: =Z27+1 -> 45665
C29: 9 | D29: 1 | E29: =MONTH(Y29) -> 1 | F29: =F28+1 -> 45666 | G29: =TEXT(Z29,"ddd") -> Thu | J29: 376670 | L29: =IF(D29=0,0,$K$7) -> 265734.27 | M29: =IF(D29=0,0,J29-L29) -> 110935.73 | N29: =IFERROR(J29/L29,"¥0") -> 1.4174687 | P29: =IF(D29=0,0,SUM($L$21:L29)) -> 1062937.1 | Q29: =IF(D29=0,0,SUM($J$21:J29)) -> 992630 | R29: =IF(D29=0,0,Q29-P29) -> -70307.063 | S29: =IF(D29=0,0,Q29/P29) -> 0.93385586 | U29: =IF(D29=0,0,SUM($L$21:L29)) -> 1062937.1 | V29: =IF(D29=0,0,SUM($J$21:J29)) -> 992630 | W29: =IF(D29=0,0,V29-U29) -> -70307.063 | X29: =IF(D29=0,0,V29/U29) -> 0.93385586 | Y29: =Y28+1 -> 45666 | Z29: =Z28+1 -> 45666
C30: 10 | D30: 1 | E30: =MONTH(Y30) -> 1 | F30: =F29+1 -> 45667 | G30: =TEXT(Z30,"ddd") -> Fri | J30: 377100 | L30: =IF(D30=0,0,$K$7) -> 265734.27 | M30: =IF(D30=0,0,J30-L30) -> 111365.73 | N30: =IFERROR(J30/L30,"¥0") -> 1.4190868 | P30: =IF(D30=0,0,SUM($L$21:L30)) -> 1328671.3 | Q30: =IF(D30=0,0,SUM($J$21:J30)) -> 1369730 | R30: =IF(D30=0,0,Q30-P30) -> 41058.671 | S30: =IF(D30=0,0,Q30/P30) -> 1.0309021 | U30: =IF(D30=0,0,SUM($L$21:L30)) -> 1328671.3 | V30: =IF(D30=0,0,SUM($J$21:J30)) -> 1369730 | W30: =IF(D30=0,0,V30-U30) -> 41058.671 | X30: =IF(D30=0,0,V30/U30) -> 1.0309021 | Y30: =Y29+1 -> 45667 | Z30: =Z29+1 -> 45667
C31: 11 | D31: 1 | E31: =MONTH(Y31) -> 1 | F31: =F30+1 -> 45668 | G31: =TEXT(Z31,"ddd") -> Sat | J31: 66550 | L31: =IF(D31=0,0,$K$7) -> 265734.27 | M31: =IF(D31=0,0,J31-L31) -> -199184.27 | N31: =IFERROR(J31/L31,"¥0") -> 0.25043816 | P31: =IF(D31=0,0,SUM($L$21:L31)) -> 1594405.6 | Q31: =IF(D31=0,0,SUM($J$21:J31)) -> 1436280 | R31: =IF(D31=0,0,Q31-P31) -> -158125.59 | S31: =IF(D31=0,0,Q31/P31) -> 0.90082474 | U31: =IF(D31=0,0,SUM($L$21:L31)) -> 1594405.6 | V31: =IF(D31=0,0,SUM($J$21:J31)) -> 1436280 | W31: =IF(D31=0,0,V31-U31) -> -158125.59 | X31: =IF(D31=0,0,V31/U31) -> 0.90082474 | Y31: =Y30+1 -> 45668 | Z31: =Z30+1 -> 45668
C32: 12 | D32: 0 | E32: =MONTH(Y32) -> 1 | F32: =F31+1 -> 45669 | G32: =TEXT(Z32,"ddd") -> Sun | H32: 日曜日 | L32: =IF(D32=0,0,$K$7) -> 0 | M32: =IF(D32=0,0,J32-L32) -> 0 | N32: =IFERROR(J32/L32,"¥0") -> ¥0 | P32: =IF(D32=0,0,SUM($L$21:L32)) -> 0 | Q32: =IF(D32=0,0,SUM($J$21:J32)) -> 0 | R32: =IF(D32=0,0,Q32-P32) -> 0 | S32: =IF(D32=0,0,Q32/P32) -> 0 | U32: =IF(D32=0,0,SUM($L$21:L32)) -> 0 | V32: =IF(D32=0,0,SUM($J$21:J32)) -> 0 | W32: =IF(D32=0,0,V32-U32) -> 0 | X32: =IF(D32=0,0,V32/U32) -> 0 | Y32: =Y31+1 -> 45669 | Z32: =Z31+1 -> 45669
C33: 13 | D33: 0 | E33: =MONTH(Y33) -> 1 | F33: =F32+1 -> 45670 | G33: =TEXT(Z33,"ddd") -> Mon | H33: 成人の日 | L33: =IF(D33=0,0,$K$7) -> 0 | M33: =IF(D33=0,0,J33-L33) -> 0 | N33: =IFERROR(J33/L33,"¥0") -> ¥0 | P33: =IF(D33=0,0,SUM($L$21:L33)) -> 0 | Q33: =IF(D33=0,0,SUM($J$21:J33)) -> 0 | R33: =IF(D33=0,0,Q33-P33) -> 0 | S33: =IF(D33=0,0,Q33/P33) -> 0 | U33: =IF(D33=0,0,SUM($L$21:L33)) -> 0 | V33: =IF(D33=0,0,SUM($J$21:J33)) -> 0 | W33: =IF(D33=0,0,V33-U33) -> 0 | X33: =IF(D33=0,0,V33/U33) -> 0 | Y33: =Y32+1 -> 45670 | Z33: =Z32+1 -> 45670
C34: 14 | D34: 1 | E34: =MONTH(Y34) -> 1 | F34: =F33+1 -> 45671 | G34: =TEXT(Z34,"ddd") -> Tue | J34: 372310 | L34: =IF(D34=0,0,$K$7) -> 265734.27 | M34: =IF(D34=0,0,J34-L34) -> 106575.73 | N34: =IFERROR(J34/L34,"¥0") -> 1.4010613 | P34: =IF(D34=0,0,SUM($L$21:L34)) -> 1860139.9 | Q34: =IF(D34=0,0,SUM($J$21:J34)) -> 1808590 | R34: =IF(D34=0,0,Q34-P34) -> -51549.86 | S34: =IF(D34=0,0,Q34/P34) -> 0.97228711 | U34: =IF(D34=0,0,SUM($L$21:L34)) -> 1860139.9 | V34: =IF(D34=0,0,SUM($J$21:J34)) -> 1808590 | W34: =IF(D34=0,0,V34-U34) -> -51549.86 | X34: =IF(D34=0,0,V34/U34) -> 0.97228711 | Y34: =Y33+1 -> 45671 | Z34: =Z33+1 -> 45671
C35: 15 | D35: 1 | E35: =MONTH(Y35) -> 1 | F35: =F34+1 -> 45672 | G35: =TEXT(Z35,"ddd") -> Wed | J35: 246200 | L35: =IF(D35=0,0,$K$7) -> 265734.27 | M35: =IF(D35=0,0,J35-L35) -> -19534.266 | N35: =IFERROR(J35/L35,"¥0") -> 0.92648947 | P35: =IF(D35=0,0,SUM($L$21:L35)) -> 2125874.1 | Q35: =IF(D35=0,0,SUM($J$21:J35)) -> 2054790 | R35: =IF(D35=0,0,Q35-P35) -> -71084.126 | S35: =IF(D35=0,0,Q35/P35) -> 0.9665624 | U35: =IF(D35=0,0,SUM($L$21:L35)) -> 2125874.1 | V35: =IF(D35=0,0,SUM($J$21:J35)) -> 2054790 | W35: =IF(D35=0,0,V35-U35) -> -71084.126 | X35: =IF(D35=0,0,V35/U35) -> 0.9665624 | Y35: =Y34+1 -> 45672 | Z35: =Z34+1 -> 45672
C36: 16 | D36: 1 | E36: =MONTH(Y36) -> 1 | F36: =F35+1 -> 45673 | G36: =TEXT(Z36,"ddd") -> Thu | J36: 400950 | L36: =IF(D36=0,0,$K$7) -> 265734.27 | M36: =IF(D36=0,0,J36-L36) -> 135215.73 | N36: =IFERROR(J36/L36,"¥0") -> 1.5088382 | P36: =IF(D36=0,0,SUM($L$21:L36)) -> 2391608.4 | Q36: =IF(D36=0,0,SUM($J$21:J36)) -> 2455740 | R36: =IF(D36=0,0,Q36-P36) -> 64131.608 | S36: =IF(D36=0,0,Q36/P36) -> 1.0268153 | U36: =IF(D36=0,0,SUM($L$21:L36)) -> 2391608.4 | V36: =IF(D36=0,0,SUM($J$21:J36)) -> 2455740 | W36: =IF(D36=0,0,V36-U36) -> 64131.608 | X36: =IF(D36=0,0,V36/U36) -> 1.0268153 | Y36: =Y35+1 -> 45673 | Z36: =Z35+1 -> 45673
C37: 17 | D37: 1 | E37: =MONTH(Y37) -> 1 | F37: =F36+1 -> 45674 | G37: =TEXT(Z37,"ddd") -> Fri | J37: 262380 | L37: =IF(D37=0,0,$K$7) -> 265734.27 | M37: =IF(D37=0,0,J37-L37) -> -3354.2657 | N37: =IFERROR(J37/L37,"¥0") -> 0.98737737 | P37: =IF(D37=0,0,SUM($L$21:L37)) -> 2657342.7 | Q37: =IF(D37=0,0,SUM($J$21:J37)) -> 2718120 | R37: =IF(D37=0,0,Q37-P37) -> 60777.343 | S37: =IF(D37=0,0,Q37/P37) -> 1.0228715 | U37: =IF(D37=0,0,SUM($L$21:L37)) -> 2657342.7 | V37: =IF(D37=0,0,SUM($J$21:J37)) -> 2718120 | W37: =IF(D37=0,0,V37-U37) -> 60777.343 | X37: =IF(D37=0,0,V37/U37) -> 1.0228715 | Y37: =Y36+1 -> 45674 | Z37: =Z36+1 -> 45674
C38: 18 | D38: 1 | E38: =MONTH(Y38) -> 1 | F38: =F37+1 -> 45675 | G38: =TEXT(Z38,"ddd") -> Sat | J38: 137800 | L38: =IF(D38=0,0,$K$7) -> 265734.27 | M38: =IF(D38=0,0,J38-L38) -> -127934.27 | N38: =IFERROR(J38/L38,"¥0") -> 0.51856316 | P38: =IF(D38=0,0,SUM($L$21:L38)) -> 2923076.9 | Q38: =IF(D38=0,0,SUM($J$21:J38)) -> 2855920 | R38: =IF(D38=0,0,Q38-P38) -> -67156.923 | S38: =IF(D38=0,0,Q38/P38) -> 0.97702526 | U38: =IF(D38=0,0,SUM($L$21:L38)) -> 2923076.9 | V38: =IF(D38=0,0,SUM($J$21:J38)) -> 2855920 | W38: =IF(D38=0,0,V38-U38) -> -67156.923 | X38: =IF(D38=0,0,V38/U38) -> 0.97702526 | Y38: =Y37+1 -> 45675 | Z38: =Z37+1 -> 45675
C39: 19 | D39: 0 | E39: =MONTH(Y39) -> 1 | F39: =F38+1 -> 45676 | G39: =TEXT(Z39,"ddd") -> Sun | L39: =IF(D39=0,0,$K$7) -> 0 | M39: =IF(D39=0,0,J39-L39) -> 0 | N39: =IFERROR(J39/L39,"¥0") -> ¥0 | P39: =IF(D39=0,0,SUM($L$21:L39)) -> 0 | Q39: =IF(D39=0,0,SUM($J$21:J39)) -> 0 | R39: =IF(D39=0,0,Q39-P39) -> 0 | S39: =IF(D39=0,0,Q39/P39) -> 0 | U39: =IF(D39=0,0,SUM($L$21:L39)) -> 0 | V39: =IF(D39=0,0,SUM($J$21:J39)) -> 0 | W39: =IF(D39=0,0,V39-U39) -> 0 | X39: =IF(D39=0,0,V39/U39) -> 0 | Y39: =Y38+1 -> 45676 | Z39: =Z38+1 -> 45676
C40: 20 | D40: 1 | E40: =MONTH(Y40) -> 1 | F40: =F39+1 -> 45677 | G40: =TEXT(Z40,"ddd") -> Mon | J40: 265910 | L40: =IF(D40=0,0,$K$7) -> 265734.27 | M40: =IF(D40=0,0,J40-L40) -> 175.73427 | N40: =IFERROR(J40/L40,"¥0") -> 1.0006613 | P40: =IF(D40=0,0,SUM($L$21:L40)) -> 3188811.2 | Q40: =IF(D40=0,0,SUM($J$21:J40)) -> 3121830 | R40: =IF(D40=0,0,Q40-P40) -> -66981.189 | S40: =IF(D40=0,0,Q40/P40) -> 0.97899493 | U40: =IF(D40=0,0,SUM($L$21:L40)) -> 3188811.2 | V40: =IF(D40=0,0,SUM($J$21:J40)) -> 3121830 | W40: =IF(D40=0,0,V40-U40) -> -66981.189 | X40: =IF(D40=0,0,V40/U40) -> 0.97899493 | Y40: =Y39+1 -> 45677 | Z40: =Z39+1 -> 45677
C41: 21 | D41: 1 | E41: =MONTH(Y41) -> 1 | F41: =F40+1 -> 45678 | G41: =TEXT(Z41,"ddd") -> Tue | J41: 175950 | L41: =IF(D41=0,0,$K$7) -> 265734.27 | M41: =IF(D41=0,0,J41-L41) -> -89784.266 | N41: =IFERROR(J41/L41,"¥0") -> 0.66212763 | P41: =IF(D41=0,0,SUM($L$21:L41)) -> 3454545.5 | Q41: =IF(D41=0,0,SUM($J$21:J41)) -> 3297780 | R41: =IF(D41=0,0,Q41-P41) -> -156765.45 | S41: =IF(D41=0,0,Q41/P41) -> 0.95462053 | U41: =IF(D41=0,0,SUM($L$21:L41)) -> 3454545.5 | V41: =IF(D41=0,0,SUM($J$21:J41)) -> 3297780 | W41: =IF(D41=0,0,V41-U41) -> -156765.45 | X41: =IF(D41=0,0,V41/U41) -> 0.95462053 | Y41: =Y40+1 -> 45678 | Z41: =Z40+1 -> 45678
C42: 22 | D42: 1 | E42: =MONTH(Y42) -> 1 | F42: =F41+1 -> 45679 | G42: =TEXT(Z42,"ddd") -> Wed | J42: 262170 | L42: =IF(D42=0,0,$K$7) -> 265734.27 | M42: =IF(D42=0,0,J42-L42) -> -3564.2657 | N42: =IFERROR(J42/L42,"¥0") -> 0.98658711 | P42: =IF(D42=0,0,SUM($L$21:L42)) -> 3720279.7 | Q42: =IF(D42=0,0,SUM($J$21:J42)) -> 3559950 | R42: =IF(D42=0,0,Q42-P42) -> -160329.72 | S42: =IF(D42=0,0,Q42/P42) -> 0.95690385 | U42: =IF(D42=0,0,SUM($L$21:L42)) -> 3720279.7 | V42: =IF(D42=0,0,SUM($J$21:J42)) -> 3559950 | W42: =IF(D42=0,0,V42-U42) -> -160329.72 | X42: =IF(D42=0,0,V42/U42) -> 0.95690385 | Y42: =Y41+1 -> 45679 | Z42: =Z41+1 -> 45679
C43: 23 | D43: 1 | E43: =MONTH(Y43) -> 1 | F43: =F42+1 -> 45680 | G43: =TEXT(Z43,"ddd") -> Thu | J43: 342980 | L43: =IF(D43=0,0,$K$7) -> 265734.27 | M43: =IF(D43=0,0,J43-L43) -> 77245.734 | N43: =IFERROR(J43/L43,"¥0") -> 1.2906879 | P43: =IF(D43=0,0,SUM($L$21:L43)) -> 3986014 | Q43: =IF(D43=0,0,SUM($J$21:J43)) -> 3902930 | R43: =IF(D43=0,0,Q43-P43) -> -83083.986 | S43: =IF(D43=0,0,Q43/P43) -> 0.97915612 | U43: =IF(D43=0,0,SUM($L$21:L43)) -> 3986014 | V43: =IF(D43=0,0,SUM($J$21:J43)) -> 3902930 | W43: =IF(D43=0,0,V43-U43) -> -83083.986 | X43: =IF(D43=0,0,V43/U43) -> 0.97915612 | Y43: =Y42+1 -> 45680 | Z43: =Z42+1 -> 45680
C44: 24 | D44: 1 | E44: =MONTH(Y44) -> 1 | F44: =F43+1 -> 45681 | G44: =TEXT(Z44,"ddd") -> Fri | J44: 330440 | L44: =IF(D44=0,0,$K$7) -> 265734.27 | M44: =IF(D44=0,0,J44-L44) -> 64705.734 | N44: =IFERROR(J44/L44,"¥0") -> 1.2434979 | P44: =IF(D44=0,0,SUM($L$21:L44)) -> 4251748.3 | Q44: =IF(D44=0,0,SUM($J$21:J44)) -> 4233370 | R44: =IF(D44=0,0,Q44-P44) -> -18378.252 | S44: =IF(D44=0,0,Q44/P44) -> 0.99567748 | U44: =IF(D44=0,0,SUM($L$21:L44)) -> 4251748.3 | V44: =IF(D44=0,0,SUM($J$21:J44)) -> 4233370 | W44: =IF(D44=0,0,V44-U44) -> -18378.252 | X44: =IF(D44=0,0,V44/U44) -> 0.99567748 | Y44: =Y43+1 -> 45681 | Z44: =Z43+1 -> 45681
C45: 25 | D45: 1 | E45: =MONTH(Y45) -> 1 | F45: =F44+1 -> 45682 | G45: =TEXT(Z45,"ddd") -> Sat | J45: 122020 | L45: =IF(D45=0,0,$K$7) -> 265734.27 | M45: =IF(D45=0,0,J45-L45) -> -143714.27 | N45: =IFERROR(J45/L45,"¥0") -> 0.45918053 | P45: =IF(D45=0,0,SUM($L$21:L45)) -> 4517482.5 | Q45: =IF(D45=0,0,SUM($J$21:J45)) -> 4355390 | R45: =IF(D45=0,0,Q45-P45) -> -162092.52 | S45: =IF(D45=0,0,Q45/P45) -> 0.96411884 | U45: =IF(D45=0,0,SUM($L$21:L45)) -> 4517482.5 | V45: =IF(D45=0,0,SUM($J$21:J45)) -> 4355390 | W45: =IF(D45=0,0,V45-U45) -> -162092.52 | X45: =IF(D45=0,0,V45/U45) -> 0.96411884 | Y45: =Y44+1 -> 45682 | Z45: =Z44+1 -> 45682
C46: 26 | D46: 0 | E46: =MONTH(Y46) -> 1 | F46: =F45+1 -> 45683 | G46: =TEXT(Z46,"ddd") -> Sun | L46: =IF(D46=0,0,$K$7) -> 0 | M46: =IF(D46=0,0,J46-L46) -> 0 | N46: =IFERROR(J46/L46,"¥0") -> ¥0 | P46: =IF(D46=0,0,SUM($L$21:L46)) -> 0 | Q46: =IF(D46=0,0,SUM($J$21:J46)) -> 0 | R46: =IF(D46=0,0,Q46-P46) -> 0 | S46: =IF(D46=0,0,Q46/P46) -> 0 | U46: =IF(D46=0,0,SUM($L$21:L46)) -> 0 | V46: =IF(D46=0,0,SUM($J$21:J46)) -> 0 | W46: =IF(D46=0,0,V46-U46) -> 0 | X46: =IF(D46=0,0,V46/U46) -> 0 | Y46: =Y45+1 -> 45683 | Z46: =Z45+1 -> 45683
C47: 27 | D47: 1 | E47: =MONTH(Y47) -> 1 | F47: =F46+1 -> 45684 | G47: =TEXT(Z47,"ddd") -> Mon | J47: 283810 | L47: =IF(D47=0,0,$K$7) -> 265734.27 | M47: =IF(D47=0,0,J47-L47) -> 18075.734 | N47: =IFERROR(J47/L47,"¥0") -> 1.0680218 | P47: =IF(D47=0,0,SUM($L$21:L47)) -> 4783216.8 | Q47: =IF(D47=0,0,SUM($J$21:J47)) -> 4639200 | R47: =IF(D47=0,0,Q47-P47) -> -144016.78 | S47: =IF(D47=0,0,Q47/P47) -> 0.96989123 | U47: =IF(D47=0,0,SUM($L$21:L47)) -> 4783216.8 | V47: =IF(D47=0,0,SUM($J$21:J47)) -> 4639200 | W47: =IF(D47=0,0,V47-U47) -> -144016.78 | X47: =IF(D47=0,0,V47/U47) -> 0.96989123 | Y47: =Y46+1 -> 45684 | Z47: =Z46+1 -> 45684
C48: 28 | D48: 1 | E48: =MONTH(Y48) -> 1 | F48: =F47+1 -> 45685 | G48: =TEXT(Z48,"ddd") -> Tue | J48: 328920 | L48: =IF(D48=0,0,$K$7) -> 265734.27 | M48: =IF(D48=0,0,J48-L48) -> 63185.734 | N48: =IFERROR(J48/L48,"¥0") -> 1.2377779 | P48: =IF(D48=0,0,SUM($L$21:L48)) -> 5048951 | Q48: =IF(D48=0,0,SUM($J$21:J48)) -> 4968120 | R48: =IF(D48=0,0,Q48-P48) -> -80831.049 | S48: =IF(D48=0,0,Q48/P48) -> 0.98399053 | U48: =IF(D48=0,0,SUM($L$21:L48)) -> 5048951 | V48: =IF(D48=0,0,SUM($J$21:J48)) -> 4968120 | W48: =IF(D48=0,0,V48-U48) -> -80831.049 | X48: =IF(D48=0,0,V48/U48) -> 0.98399053 | Y48: =Y47+1 -> 45685 | Z48: =Z47+1 -> 45685
C49: 29 | D49: 1 | E49: =MONTH(Y49) -> 1 | F49: =F48+1 -> 45686 | G49: =TEXT(Z49,"ddd") -> Wed | J49: 235370 | L49: =IF(D49=0,0,$K$7) -> 265734.27 | M49: =IF(D49=0,0,J49-L49) -> -30364.266 | N49: =IFERROR(J49/L49,"¥0") -> 0.88573447 | P49: =IF(D49=0,0,SUM($L$21:L49)) -> 5314685.3 | Q49: =IF(D49=0,0,SUM($J$21:J49)) -> 5203490 | R49: =IF(D49=0,0,Q49-P49) -> -111195.31 | S49: =IF(D49=0,0,Q49/P49) -> 0.97907772 | U49: =IF(D49=0,0,SUM($L$21:L49)) -> 5314685.3 | V49: =IF(D49=0,0,SUM($J$21:J49)) -> 5203490 | W49: =IF(D49=0,0,V49-U49) -> -111195.31 | X49: =IF(D49=0,0,V49/U49) -> 0.97907772 | Y49: =Y48+1 -> 45686 | Z49: =Z48+1 -> 45686
C50: 30 | D50: 1 | E50: =MONTH(Y50) -> 1 | F50: =F49+1 -> 45687 | G50: =TEXT(Z50,"ddd") -> Thu | J50: 450100 | L50: =IF(D50=0,0,$K$7) -> 265734.27 | M50: =IF(D50=0,0,J50-L50) -> 184365.73 | N50: =IFERROR(J50/L50,"¥0") -> 1.6937974 | P50: =IF(D50=0,0,SUM($L$21:L50)) -> 5580419.6 | Q50: =IF(D50=0,0,SUM($J$21:J50)) -> 5653590 | R50: =IF(D50=0,0,Q50-P50) -> 73170.42 | S50: =IF(D50=0,0,Q50/P50) -> 1.013112 | U50: =IF(D50=0,0,SUM($L$21:L50)) -> 5580419.6 | V50: =IF(D50=0,0,SUM($J$21:J50)) -> 5653590 | W50: =IF(D50=0,0,V50-U50) -> 73170.42 | X50: =IF(D50=0,0,V50/U50) -> 1.013112 | Y50: =Y49+1 -> 45687 | Z50: =Z49+1 -> 45687
C51: 31 | D51: 1 | E51: =MONTH(Y51) -> 1 | F51: =F50+1 -> 45688 | G51: =TEXT(Z51,"ddd") -> Fri | J51: 352040 | L51: =IF(D51=0,0,$K$7) -> 265734.27 | M51: =IF(D51=0,0,J51-L51) -> 86305.734 | N51: =IFERROR(J51/L51,"¥0") -> 1.3247821 | P51: =IF(D51=0,0,SUM($L$21:L51)) -> 5846153.8 | Q51: =IF(D51=0,0,SUM($J$21:J51)) -> 6005630 | R51: =IF(D51=0,0,Q51-P51) -> 159476.15 | S51: =IF(D51=0,0,Q51/P51) -> 1.0272788 | U51: =IF(D51=0,0,SUM($L$21:L51)) -> 5846153.8 | V51: =IF(D51=0,0,SUM($J$21:J51)) -> 6005630 | W51: =IF(D51=0,0,V51-U51) -> 159476.15 | X51: =IF(D51=0,0,V51/U51) -> 1.0272788 | Y51: =Y50+1 -> 45688 | Z51: =Z50+1 -> 45688
C52: 32 | D52: 1 | E52: =MONTH(Y52) -> 2 | F52: =F51+1 -> 45689 | G52: =TEXT(Z52,"ddd") -> Sat | J52: 182250 | L52: =IF(D52=0,0,$K$8) -> 237762.24 | M52: =IF(D52=0,0,J52-L52) -> -55512.238 | N52: =IFERROR(J52/L52,"¥0") -> 0.76652206 | P52: =IF(D52=0,0,$L$52) -> 237762.24 | Q52: =IF(D52=0,0,$J$52) -> 182250 | R52: =IF(D52=0,0,Q52-P52) -> -55512.238 | S52: =IF(D52=0,0,Q52/P52) -> 0.76652206 | U52: =IF(D52=0,0,SUM($L$21:L52)) -> 6083916.1 | V52: =IF(D52=0,0,SUM($J$21:J52)) -> 6187880 | W52: =IF(D52=0,0,V52-U52) -> 103963.92 | X52: =IF(D52=0,0,V52/U52) -> 1.0170883 | Y52: =Y51+1 -> 45689 | Z52: =Z51+1 -> 45689
C53: 33 | D53: 0 | E53: =MONTH(Y53) -> 2 | F53: =F52+1 -> 45690 | G53: =TEXT(Z53,"ddd") -> Sun | J53: 0 | L53: =IF(D53=0,0,$K$8) -> 0 | M53: =IF(D53=0,0,J53-L53) -> 0 | N53: =IFERROR(J53/L53,"¥0") -> ¥0 | P53: =IF(D53=0,0,SUM($L$52:L53)) -> 0 | Q53: =IF(D53=0,0,SUM($J$52:J53)) -> 0 | R53: =IF(D53=0,0,Q53-P53) -> 0 | S53: =IF(D53=0,0,Q53/P53) -> 0 | U53: =IF(D53=0,0,SUM($L$21:L53)) -> 0 | V53: =IF(D53=0,0,SUM($J$21:J53)) -> 0 | W53: =IF(D53=0,0,V53-U53) -> 0 | X53: =IF(D53=0,0,V53/U53) -> 0 | Y53: =Y52+1 -> 45690 | Z53: =Z52+1 -> 45690
C54: 34 | D54: 1 | E54: =MONTH(Y54) -> 2 | F54: =F53+1 -> 45691 | G54: =TEXT(Z54,"ddd") -> Mon | J54: 101150 | L54: =IF(D54=0,0,$K$8) -> 237762.24 | M54: =IF(D54=0,0,J54-L54) -> -136612.24 | N54: =IFERROR(J54/L54,"¥0") -> 0.425425 | P54: =IF(D54=0,0,SUM($L$52:L54)) -> 475524.48 | Q54: =IF(D54=0,0,SUM($J$52:J54)) -> 283400 | R54: =IF(D54=0,0,Q54-P54) -> -192124.48 | S54: =IF(D54=0,0,Q54/P54) -> 0.59597353 | U54: =IF(D54=0,0,SUM($L$21:L54)) -> 6321678.3 | V54: =IF(D54=0,0,SUM($J$21:J54)) -> 6289030 | W54: =IF(D54=0,0,V54-U54) -> -32648.322 | X54: =IF(D54=0,0,V54/U54) -> 0.9948355 | Y54: =Y53+1 -> 45691 | Z54: =Z53+1 -> 45691
C55: 35 | D55: 1 | E55: =MONTH(Y55) -> 2 | F55: =F54+1 -> 45692 | G55: =TEXT(Z55,"ddd") -> Tue | J55: 152530 | L55: =IF(D55=0,0,$K$8) -> 237762.24 | M55: =IF(D55=0,0,J55-L55) -> -85232.238 | N55: =IFERROR(J55/L55,"¥0") -> 0.64152324 | P55: =IF(D55=0,0,SUM($L$52:L55)) -> 713286.71 | Q55: =IF(D55=0,0,SUM($J$52:J55)) -> 435930 | R55: =IF(D55=0,0,Q55-P55) -> -277356.71 | S55: =IF(D55=0,0,Q55/P55) -> 0.61115676 | U55: =IF(D55=0,0,SUM($L$21:L55)) -> 6559440.6 | V55: =IF(D55=0,0,SUM($J$21:J55)) -> 6441560 | W55: =IF(D55=0,0,V55-U55) -> -117880.56 | X55: =IF(D55=0,0,V55/U55) -> 0.98202887 | Y55: =Y54+1 -> 45692 | Z55: =Z54+1 -> 45692
C56: 36 | D56: 1 | E56: =MONTH(Y56) -> 2 | F56: =F55+1 -> 45693 | G56: =TEXT(Z56,"ddd") -> Wed | J56: 227650 | L56: =IF(D56=0,0,$K$8) -> 237762.24 | M56: =IF(D56=0,0,J56-L56) -> -10112.238 | N56: =IFERROR(J56/L56,"¥0") -> 0.95746912 | P56: =IF(D56=0,0,SUM($L$52:L56)) -> 951048.95 | Q56: =IF(D56=0,0,SUM($J$52:J56)) -> 663580 | R56: =IF(D56=0,0,Q56-P56) -> -287468.95 | S56: =IF(D56=0,0,Q56/P56) -> 0.69773485 | U56: =IF(D56=0,0,SUM($L$21:L56)) -> 6797202.8 | V56: =IF(D56=0,0,SUM($J$21:J56)) -> 6669210 | W56: =IF(D56=0,0,V56-U56) -> -127992.8 | X56: =IF(D56=0,0,V56/U56) -> 0.98116978 | Y56: =Y55+1 -> 45693 | Z56: =Z55+1 -> 45693
C57: 37 | D57: 1 | E57: =MONTH(Y57) -> 2 | F57: =F56+1 -> 45694 | G57: =TEXT(Z57,"ddd") -> Thu | J57: 339200 | L57: =IF(D57=0,0,$K$8) -> 237762.24 | M57: =IF(D57=0,0,J57-L57) -> 101437.76 | N57: =IFERROR(J57/L57,"¥0") -> 1.4266353 | P57: =IF(D57=0,0,SUM($L$52:L57)) -> 1188811.2 | Q57: =IF(D57=0,0,SUM($J$52:J57)) -> 1002780 | R57: =IF(D57=0,0,Q57-P57) -> -186031.19 | S57: =IF(D57=0,0,Q57/P57) -> 0.84351494 | U57: =IF(D57=0,0,SUM($L$21:L57)) -> 7034965 | V57: =IF(D57=0,0,SUM($J$21:J57)) -> 7008410 | W57: =IF(D57=0,0,V57-U57) -> -26555.035 | X57: =IF(D57=0,0,V57/U57) -> 0.99622528 | Y57: =Y56+1 -> 45694 | Z57: =Z56+1 -> 45694
C58: 38 | D58: 1 | E58: =MONTH(Y58) -> 2 | F58: =F57+1 -> 45695 | G58: =TEXT(Z58,"ddd") -> Fri | J58: 330170 | L58: =IF(D58=0,0,$K$8) -> 237762.24 | M58: =IF(D58=0,0,J58-L58) -> 92407.762 | N58: =IFERROR(J58/L58,"¥0") -> 1.3886562 | P58: =IF(D58=0,0,SUM($L$52:L58)) -> 1426573.4 | Q58: =IF(D58=0,0,SUM($J$52:J58)) -> 1332950 | R58: =IF(D58=0,0,Q58-P58) -> -93623.427 | S58: =IF(D58=0,0,Q58/P58) -> 0.93437181 | U58: =IF(D58=0,0,SUM($L$21:L58)) -> 7272727.3 | V58: =IF(D58=0,0,SUM($J$21:J58)) -> 7338580 | W58: =IF(D58=0,0,V58-U58) -> 65852.727 | X58: =IF(D58=0,0,V58/U58) -> 1.0090548 | Y58: =Y57+1 -> 45695 | Z58: =Z57+1 -> 45695
C59: 39 | D59: 1 | E59: =MONTH(Y59) -> 2 | F59: =F58+1 -> 45696 | G59: =TEXT(Z59,"ddd") -> Sat | J59: 156800 | L59: =IF(D59=0,0,$K$8) -> 237762.24 | M59: =IF(D59=0,0,J59-L59) -> -80962.238 | N59: =IFERROR(J59/L59,"¥0") -> 0.65948235 | P59: =IF(D59=0,0,SUM($L$52:L59)) -> 1664335.7 | Q59: =IF(D59=0,0,SUM($J$52:J59)) -> 1489750 | R59: =IF(D59=0,0,Q59-P59) -> -174585.66 | S59: =IF(D59=0,0,Q59/P59) -> 0.89510189 | U59: =IF(D59=0,0,SUM($L$21:L59)) -> 7510489.5 | V59: =IF(D59=0,0,SUM($J$21:J59)) -> 7495380 | W59: =IF(D59=0,0,V59-U59) -> -15109.51 | X59: =IF(D59=0,0,V59/U59) -> 0.99798821 | Y59: =Y58+1 -> 45696 | Z59: =Z58+1 -> 45696
C60: 40 | D60: 0 | E60: =MONTH(Y60) -> 2 | F60: =F59+1 -> 45697 | G60: =TEXT(Z60,"ddd") -> Sun | J60: 0 | L60: =IF(D60=0,0,$K$8) -> 0 | M60: =IF(D60=0,0,J60-L60) -> 0 | N60: =IFERROR(J60/L60,"¥0") -> ¥0 | P60: =IF(D60=0,0,SUM($L$52:L60)) -> 0 | Q60: =IF(D60=0,0,SUM($J$52:J60)) -> 0 | R60: =IF(D60=0,0,Q60-P60) -> 0 | S60: =IF(D60=0,0,Q60/P60) -> 0 | U60: =IF(D60=0,0,SUM($L$21:L60)) -> 0 | V60: =IF(D60=0,0,SUM($J$21:J60)) -> 0 | W60: =IF(D60=0,0,V60-U60) -> 0 | X60: =IF(D60=0,0,V60/U60) -> 0 | Y60: =Y59+1 -> 45697 | Z60: =Z59+1 -> 45697
C61: 41 | D61: 1 | E61: =MONTH(Y61) -> 2 | F61: =F60+1 -> 45698 | G61: =TEXT(Z61,"ddd") -> Mon | J61: 99600 | L61: =IF(D61=0,0,$K$8) -> 237762.24 | M61: =IF(D61=0,0,J61-L61) -> -138162.24 | N61: =IFERROR(J61/L61,"¥0") -> 0.41890588 | P61: =IF(D61=0,0,SUM($L$52:L61)) -> 1902097.9 | Q61: =IF(D61=0,0,SUM($J$52:J61)) -> 1589350 | R61: =IF(D61=0,0,Q61-P61) -> -312747.9 | S61: =IF(D61=0,0,Q61/P61) -> 0.83557739 | U61: =IF(D61=0,0,SUM($L$21:L61)) -> 7748251.7 | V61: =IF(D61=0,0,SUM($J$21:J61)) -> 7594980 | W61: =IF(D61=0,0,V61-U61) -> -153271.75 | X61: =IF(D61=0,0,V61/U61) -> 0.98021854 | Y61: =Y60+1 -> 45698 | Z61: =Z60+1 -> 45698
C62: 42 | D62: 0 | E62: =MONTH(Y62) -> 2 | F62: =F61+1 -> 45699 | G62: =TEXT(Z62,"ddd") -> Tue | J62: 0 | L62: =IF(D62=0,0,$K$8) -> 0 | M62: =IF(D62=0,0,J62-L62) -> 0 | N62: =IFERROR(J62/L62,"¥0") -> ¥0 | P62: =IF(D62=0,0,SUM($L$52:L62)) -> 0 | Q62: =IF(D62=0,0,SUM($J$52:J62)) -> 0 | R62: =IF(D62=0,0,Q62-P62) -> 0 | S62: =IF(D62=0,0,Q62/P62) -> 0 | U62: =IF(D62=0,0,SUM($L$21:L62)) -> 0 | V62: =IF(D62=0,0,SUM($J$21:J62)) -> 0 | W62: =IF(D62=0,0,V62-U62) -> 0 | X62: =IF(D62=0,0,V62/U62) -> 0 | Y62: =Y61+1 -> 45699 | Z62: =Z61+1 -> 45699
C63: 43 | D63: 1 | E63: =MONTH(Y63) -> 2 | F63: =F62+1 -> 45700 | G63: =TEXT(Z63,"ddd") -> Wed | J63: 323330 | L63: =IF(D63=0,0,$K$8) -> 237762.24 | M63: =IF(D63=0,0,J63-L63) -> 85567.762 | N63: =IFERROR(J63/L63,"¥0") -> 1.3598879 | P63: =IF(D63=0,0,SUM($L$52:L63)) -> 2139860.1 | Q63: =IF(D63=0,0,SUM($J$52:J63)) -> 1912680 | R63: =IF(D63=0,0,Q63-P63) -> -227180.14 | S63: =IF(D63=0,0,Q63/P63) -> 0.89383412 | U63: =IF(D63=0,0,SUM($L$21:L63)) -> 7986014 | V63: =IF(D63=0,0,SUM($J$21:J63)) -> 7918310 | W63: =IF(D63=0,0,V63-U63) -> -67703.986 | X63: =IF(D63=0,0,V63/U63) -> 0.99152218 | Y63: =Y62+1 -> 45700 | Z63: =Z62+1 -> 45700
C64: 44 | D64: 1 | E64: =MONTH(Y64) -> 2 | F64: =F63+1 -> 45701 | G64: =TEXT(Z64,"ddd") -> Thu | J64: 346290 | L64: =IF(D64=0,0,$K$8) -> 237762.24 | M64: =IF(D64=0,0,J64-L64) -> 108527.76 | N64: =IFERROR(J64/L64,"¥0") -> 1.456455 | P64: =IF(D64=0,0,SUM($L$52:L64)) -> 2377622.4 | Q64: =IF(D64=0,0,SUM($J$52:J64)) -> 2258970 | R64: =IF(D64=0,0,Q64-P64) -> -118652.38 | S64: =IF(D64=0,0,Q64/P64) -> 0.95009621 | U64: =IF(D64=0,0,SUM($L$21:L64)) -> 8223776.2 | V64: =IF(D64=0,0,SUM($J$21:J64)) -> 8264600 | W64: =IF(D64=0,0,V64-U64) -> 40823.776 | X64: =IF(D64=0,0,V64/U64) -> 1.0049641 | Y64: =Y63+1 -> 45701 | Z64: =Z63+1 -> 45701
... C73: 53 | D73: 1 | E73: =MONTH(Y73) -> 2 | F73: =F72+1 -> 45710 | G73: =TEXT(Z73,"ddd") -> Sat | J73: 173500 | L73: =IF(D73=0,0,$K$8) -> 237762.24 | M73: =IF(D73=0,0,J73-L73) -> -64262.238 | N73: =IFERROR(J73/L73,"¥0") -> 0.72972059 | P73: =IF(D73=0,0,SUM($L$52:L73)) -> 4279720.3 | Q73: =IF(D73=0,0,SUM($J$52:J73)) -> 4068720 | R73: =IF(D73=0,0,Q73-P73) -> -211000.28 | S73: =IF(D73=0,0,Q73/P73) -> 0.95069765 | U73: =IF(D73=0,0,SUM($L$21:L73)) -> 10125874 | V73: =IF(D73=0,0,SUM($J$21:J73)) -> 10074350 | W73: =IF(D73=0,0,V73-U73) -> -51524.126 | X73: =IF(D73=0,0,V73/U73) -> 0.99491164 | Y73: =Y72+1 -> 45710 | Z73: =Z72+1 -> 45710
C74: 54 | D74: 0 | E74: =MONTH(Y74) -> 2 | F74: =F73+1 -> 45711 | G74: =TEXT(Z74,"ddd") -> Sun | L74: =IF(D74=0,0,$K$8) -> 0 | M74: =IF(D74=0,0,J74-L74) -> 0 | N74: =IFERROR(J74/L74,"¥0") -> ¥0 | P74: =IF(D74=0,0,SUM($L$52:L74)) -> 0 | Q74: =IF(D74=0,0,SUM($J$52:J74)) -> 0 | R74: =IF(D74=0,0,Q74-P74) -> 0 | S74: =IF(D74=0,0,Q74/P74) -> 0 | U74: =IF(D74=0,0,SUM($L$21:L74)) -> 0 | V74: =IF(D74=0,0,SUM($J$21:J74)) -> 0 | W74: =IF(D74=0,0,V74-U74) -> 0 | X74: =IF(D74=0,0,V74/U74) -> 0 | Y74: =Y73+1 -> 45711 | Z74: =Z73+1 -> 45711
C75: 55 | D75: 0 | E75: =MONTH(Y75) -> 2 | F75: =F74+1 -> 45712 | G75: =TEXT(Z75,"ddd") -> Mon | L75: =IF(D75=0,0,$K$8) -> 0 | M75: =IF(D75=0,0,J75-L75) -> 0 | N75: =IFERROR(J75/L75,"¥0") -> ¥0 | P75: =IF(D75=0,0,SUM($L$52:L75)) -> 0 | Q75: =IF(D75=0,0,SUM($J$52:J75)) -> 0 | R75: =IF(D75=0,0,Q75-P75) -> 0 | S75: =IF(D75=0,0,Q75/P75) -> 0 | U75: =IF(D75=0,0,SUM($L$21:L75)) -> 0 | V75: =IF(D75=0,0,SUM($J$21:J75)) -> 0 | W75: =IF(D75=0,0,V75-U75) -> 0 | X75: =IF(D75=0,0,V75/U75) -> 0 | Y75: =Y74+1 -> 45712 | Z75: =Z74+1 -> 45712
C76: 56 | D76: 1 | E76: =MONTH(Y76) -> 2 | F76: =F75+1 -> 45713 | G76: =TEXT(Z76,"ddd") -> Tue | J76: 317900 | L76: =IF(D76=0,0,$K$8) -> 237762.24 | M76: =IF(D76=0,0,J76-L76) -> 80137.762 | N76: =IFERROR(J76/L76,"¥0") -> 1.33705 | P76: =IF(D76=0,0,SUM($L$52:L76)) -> 4517482.5 | Q76: =IF(D76=0,0,SUM($J$52:J76)) -> 4386620 | R76: =IF(D76=0,0,Q76-P76) -> -130862.52 | S76: =IF(D76=0,0,Q76/P76) -> 0.97103198 | U76: =IF(D76=0,0,SUM($L$21:L76)) -> 10363636 | V76: =IF(D76=0,0,SUM($J$21:J76)) -> 10392250 | W76: =IF(D76=0,0,V76-U76) -> 28613.636 | X76: =IF(D76=0,0,V76/U76) -> 1.002761 | Y76: =Y75+1 -> 45713 | Z76: =Z75+1 -> 45713
C77: 57 | D77: 1 | E77: =MONTH(Y77) -> 2 | F77: =F76+1 -> 45714 | G77: =TEXT(Z77,"ddd") -> Wed | J77: 300760 | L77: =IF(D77=0,0,$K$8) -> 237762.24 | M77: =IF(D77=0,0,J77-L77) -> 62997.762 | N77: =IFERROR(J77/L77,"¥0") -> 1.2649612 | P77: =IF(D77=0,0,SUM($L$52:L77)) -> 4755244.8 | Q77: =IF(D77=0,0,SUM($J$52:J77)) -> 4687380 | R77: =IF(D77=0,0,Q77-P77) -> -67864.755 | S77: =IF(D77=0,0,Q77/P77) -> 0.98572844 | U77: =IF(D77=0,0,SUM($L$21:L77)) -> 10601399 | V77: =IF(D77=0,0,SUM($J$21:J77)) -> 10693010 | W77: =IF(D77=0,0,V77-U77) -> 91611.399 | X77: =IF(D77=0,0,V77/U77) -> 1.0086414 | Y77: =Y76+1 -> 45714 | Z77: =Z76+1 -> 45714
C78: 58 | D78: 1 | E78: =MONTH(Y78) -> 2 | F78: =F77+1 -> 45715 | G78: =TEXT(Z78,"ddd") -> Thu | J78: 365350 | L78: =IF(D78=0,0,$K$8) -> 237762.24 | M78: =IF(D78=0,0,J78-L78) -> 127587.76 | N78: =IFERROR(J78/L78,"¥0") -> 1.5366191 | P78: =IF(D78=0,0,SUM($L$52:L78)) -> 4993007 | Q78: =IF(D78=0,0,SUM($J$52:J78)) -> 5052730 | R78: =IF(D78=0,0,Q78-P78) -> 59723.007 | S78: =IF(D78=0,0,Q78/P78) -> 1.0119613 | U78: =IF(D78=0,0,SUM($L$21:L78)) -> 10839161 | V78: =IF(D78=0,0,SUM($J$21:J78)) -> 11058360 | W78: =IF(D78=0,0,V78-U78) -> 219199.16 | X78: =IF(D78=0,0,V78/U78) -> 1.0202229 | Y78: =Y77+1 -> 45715 | Z78: =Z77+1 -> 45715
C79: 59 | D79: 1 | E79: =MONTH(Y79) -> 2 | F79: =F78+1 -> 45716 | G79: =TEXT(Z79,"ddd") -> Fri | J79: 324940 | L79: =IF(D79=0,0,$K$8) -> 237762.24 | M79: =IF(D79=0,0,J79-L79) -> 87177.762 | N79: =IFERROR(J79/L79,"¥0") -> 1.3666594 | P79: =IF(D79=0,0,SUM($L$52:L79)) -> 5230769.2 | Q79: =IF(D79=0,0,SUM($J$52:J79)) -> 5377670 | R79: =IF(D79=0,0,Q79-P79) -> 146900.77 | S79: =IF(D79=0,0,Q79/P79) -> 1.028084 | U79: =IF(D79=0,0,SUM($L$21:L79)) -> 11076923 | V79: =IF(D79=0,0,SUM($J$21:J79)) -> 11383300 | W79: =IF(D79=0,0,V79-U79) -> 306376.92 | X79: =IF(D79=0,0,V79/U79) -> 1.027659 | Y79: =Y78+1 -> 45716 | Z79: =Z78+1 -> 45716
C80: 60 | D80: 1 | E80: =MONTH(Y80) -> 3 | F80: =F79+1 -> 45717 | G80: =TEXT(Z80,"ddd") -> Sat | J80: 123200 | L80: =IF(D80=0,0,$K$9) -> 307692.31 | M80: =IF(D80=0,0,J80-L80) -> -184492.31 | N80: =IFERROR(J80/L80,"¥0") -> 0.4004 | P80: =IF(D80=0,0,$L$80) -> 307692.31 | Q80: =IF(D80=0,0,$J$80) -> 123200 | R80: =IF(D80=0,0,Q80-P80) -> -184492.31 | S80: =IF(D80=0,0,Q80/P80) -> 0.4004 | U80: =IF(D80=0,0,SUM($L$21:L80)) -> 11384615 | V80: =IF(D80=0,0,SUM($J$21:J80)) -> 11506500 | W80: =IF(D80=0,0,V80-U80) -> 121884.62 | X80: =IF(D80=0,0,V80/U80) -> 1.0107061 | Y80: =Y79+1 -> 45717 | Z80: =Z79+1 -> 45717
C81: 61 | D81: 0 | E81: =MONTH(Y81) -> 3 | F81: =F80+1 -> 45718 | G81: =TEXT(Z81,"ddd") -> Sun | J81: 0 | L81: =IF(D81=0,0,$K$9) -> 0 | M81: =IF(D81=0,0,J81-L81) -> 0 | N81: =IFERROR(J81/L81,"¥0") -> ¥0 | P81: =IF(D81=0,0,SUM($L$80:L81)) -> 0 | Q81: =IF(D81=0,0,SUM($J$80:J81)) -> 0 | R81: =IF(D81=0,0,Q81-P81) -> 0 | S81: =IF(D81=0,0,Q81/P81) -> 0 | U81: =IF(D81=0,0,SUM($L$21:L81)) -> 0 | V81: =IF(D81=0,0,SUM($J$21:J81)) -> 0 | W81: =IF(D81=0,0,V81-U81) -> 0 | X81: =IF(D81=0,0,V81/U81) -> 0 | Y81: =Y80+1 -> 45718 | Z81: =Z80+1 -> 45718
C82: 62 | D82: 1 | E82: =MONTH(Y82) -> 3 | F82: =F81+1 -> 45719 | G82: =TEXT(Z82,"ddd") -> Mon | J82: 162400 | L82: =IF(D82=0,0,$K$9) -> 307692.31 | M82: =IF(D82=0,0,J82-L82) -> -145292.31 | N82: =IFERROR(J82/L82,"¥0") -> 0.5278 | P82: =IF(D82=0,0,SUM($L$80:L82)) -> 615384.62 | Q82: =IF(D82=0,0,SUM($J$80:J82)) -> 285600 | R82: =IF(D82=0,0,Q82-P82) -> -329784.62 | S82: =IF(D82=0,0,Q82/P82) -> 0.4641 | U82: =IF(D82=0,0,SUM($L$21:L82)) -> 11692308 | V82: =IF(D82=0,0,SUM($J$21:J82)) -> 11668900 | W82: =IF(D82=0,0,V82-U82) -> -23407.692 | X82: =IF(D82=0,0,V82/U82) -> 0.99799803 | Y82: =Y81+1 -> 45719 | Z82: =Z81+1 -> 45719
C83: 63 | D83: 1 | E83: =MONTH(Y83) -> 3 | F83: =F82+1 -> 45720 | G83: =TEXT(Z83,"ddd") -> Tue | J83: 156050 | L83: =IF(D83=0,0,$K$9) -> 307692.31 | M83: =IF(D83=0,0,J83-L83) -> -151642.31 | N83: =IFERROR(J83/L83,"¥0") -> 0.5071625 | P83: =IF(D83=0,0,SUM($L$80:L83)) -> 923076.92 | Q83: =IF(D83=0,0,SUM($J$80:J83)) -> 441650 | R83: =IF(D83=0,0,Q83-P83) -> -481426.92 | S83: =IF(D83=0,0,Q83/P83) -> 0.47845417 | U83: =IF(D83=0,0,SUM($L$21:L83)) -> 12000000 | V83: =IF(D83=0,0,SUM($J$21:J83)) -> 11824950 | W83: =IF(D83=0,0,V83-U83) -> -175050 | X83: =IF(D83=0,0,V83/U83) -> 0.9854125 | Y83: =Y82+1 -> 45720 | Z83: =Z82+1 -> 45720
C84: 64 | D84: 1 | E84: =MONTH(Y84) -> 3 | F84: =F83+1 -> 45721 | G84: =TEXT(Z84,"ddd") -> Wed | J84: 269410 | L84: =IF(D84=0,0,$K$9) -> 307692.31 | M84: =IF(D84=0,0,J84-L84) -> -38282.308 | N84: =IFERROR(J84/L84,"¥0") -> 0.8755825 | P84: =IF(D84=0,0,SUM($L$80:L84)) -> 1230769.2 | Q84: =IF(D84=0,0,SUM($J$80:J84)) -> 711060 | R84: =IF(D84=0,0,Q84-P84) -> -519709.23 | S84: =IF(D84=0,0,Q84/P84) -> 0.57773625 | U84: =IF(D84=0,0,SUM($L$21:L84)) -> 12307692 | V84: =IF(D84=0,0,SUM($J$21:J84)) -> 12094360 | W84: =IF(D84=0,0,V84-U84) -> -213332.31 | X84: =IF(D84=0,0,V84/U84) -> 0.98266675 | Y84: =Y83+1 -> 45721 | Z84: =Z83+1 -> 45721
C85: 65 | D85: 1 | E85: =MONTH(Y85) -> 3 | F85: =F84+1 -> 45722 | G85: =TEXT(Z85,"ddd") -> Thu | J85: 371500 | L85: =IF(D85=0,0,$K$9) -> 307692.31 | M85: =IF(D85=0,0,J85-L85) -> 63807.692 | N85: =IFERROR(J85/L85,"¥0") -> 1.207375 | P85: =IF(D85=0,0,SUM($L$80:L85)) -> 1538461.5 | Q85: =IF(D85=0,0,SUM($J$80:J85)) -> 1082560 | R85: =IF(D85=0,0,Q85-P85) -> -455901.54 | S85: =IF(D85=0,0,Q85/P85) -> 0.703664 | U85: =IF(D85=0,0,SUM($L$21:L85)) -> 12615385 | V85: =IF(D85=0,0,SUM($J$21:J85)) -> 12465860 | W85: =IF(D85=0,0,V85-U85) -> -149524.62 | X85: =IF(D85=0,0,V85/U85) -> 0.98814744 | Y85: =Y84+1 -> 45722 | Z85: =Z84+1 -> 45722
C86: 66 | D86: 1 | E86: =MONTH(Y86) -> 3 | F86: =F85+1 -> 45723 | G86: =TEXT(Z86,"ddd") -> Fri | J86: 493250 | L86: =IF(D86=0,0,$K$9) -> 307692.31 | M86: =IF(D86=0,0,J86-L86) -> 185557.69 | N86: =IFERROR(J86/L86,"¥0") -> 1.6030625 | P86: =IF(D86=0,0,SUM($L$80:L86)) -> 1846153.8 | Q86: =IF(D86=0,0,SUM($J$80:J86)) -> 1575810 | R86: =IF(D86=0,0,Q86-P86) -> -270343.85 | S86: =IF(D86=0,0,Q86/P86) -> 0.85356375 | U86: =IF(D86=0,0,SUM($L$21:L86)) -> 12923077 | V86: =IF(D86=0,0,SUM($J$21:J86)) -> 12959110 | W86: =IF(D86=0,0,V86-U86) -> 36033.077 | X86: =IF(D86=0,0,V86/U86) -> 1.0027883 | Y86: =Y85+1 -> 45723 | Z86: =Z85+1 -> 45723
C87: 67 | D87: 1 | E87: =MONTH(Y87) -> 3 | F87: =F86+1 -> 45724 | G87: =TEXT(Z87,"ddd") -> Sat | J87: 129200 | L87: =IF(D87=0,0,$K$9) -> 307692.31 | M87: =IF(D87=0,0,J87-L87) -> -178492.31 | N87: =IFERROR(J87/L87,"¥0") -> 0.4199 | P87: =IF(D87=0,0,SUM($L$80:L87)) -> 2153846.2 | Q87: =IF(D87=0,0,SUM($J$80:J87)) -> 1705010 | R87: =IF(D87=0,0,Q87-P87) -> -448836.15 | S87: =IF(D87=0,0,Q87/P87) -> 0.79161179 | U87: =IF(D87=0,0,SUM($L$21:L87)) -> 13230769 | V87: =IF(D87=0,0,SUM($J$21:J87)) -> 13088310 | W87: =IF(D87=0,0,V87-U87) -> -142459.23 | X87: =IF(D87=0,0,V87/U87) -> 0.98923273 | Y87: =Y86+1 -> 45724 | Z87: =Z86+1 -> 45724
C88: 68 | D88: 0 | E88: =MONTH(Y88) -> 3 | F88: =F87+1 -> 45725 | G88: =TEXT(Z88,"ddd") -> Sun | L88: =IF(D88=0,0,$K$9) -> 0 | M88: =IF(D88=0,0,J88-L88) -> 0 | N88: =IFERROR(J88/L88,"¥0") -> ¥0 | P88: =IF(D88=0,0,SUM($L$80:L88)) -> 0 | Q88: =IF(D88=0,0,SUM($J$80:J88)) -> 0 | R88: =IF(D88=0,0,Q88-P88) -> 0 | S88: =IF(D88=0,0,Q88/P88) -> 0 | U88: =IF(D88=0,0,SUM($L$21:L88)) -> 0 | V88: =IF(D88=0,0,SUM($J$21:J88)) -> 0 | W88: =IF(D88=0,0,V88-U88) -> 0 | X88: =IF(D88=0,0,V88/U88) -> 0 | Y88: =Y87+1 -> 45725 | Z88: =Z87+1 -> 45725
C89: 69 | D89: 1 | E89: =MONTH(Y89) -> 3 | F89: =F88+1 -> 45726 | G89: =TEXT(Z89,"ddd") -> Mon | J89: 140470 | L89: =IF(D89=0,0,$K$9) -> 307692.31 | M89: =IF(D89=0,0,J89-L89) -> -167222.31 | N89: =IFERROR(J89/L89,"¥0") -> 0.4565275 | P89: =IF(D89=0,0,SUM($L$80:L89)) -> 2461538.5 | Q89: =IF(D89=0,0,SUM($J$80:J89)) -> 1845480 | R89: =IF(D89=0,0,Q89-P89) -> -616058.46 | S89: =IF(D89=0,0,Q89/P89) -> 0.74972625 | U89: =IF(D89=0,0,SUM($L$21:L89)) -> 13538462 | V89: =IF(D89=0,0,SUM($J$21:J89)) -> 13228780 | W89: =IF(D89=0,0,V89-U89) -> -309681.54 | X89: =IF(D89=0,0,V89/U89) -> 0.9771258 | Y89: =Y88+1 -> 45726 | Z89: =Z88+1 -> 45726
C90: 70 | D90: 1 | E90: =MONTH(Y90) -> 3 | F90: =F89+1 -> 45727 | G90: =TEXT(Z90,"ddd") -> Tue | J90: 379560 | L90: =IF(D90=0,0,$K$9) -> 307692.31 | M90: =IF(D90=0,0,J90-L90) -> 71867.692 | N90: =IFERROR(J90/L90,"¥0") -> 1.23357 | P90: =IF(D90=0,0,SUM($L$80:L90)) -> 2769230.8 | Q90: =IF(D90=0,0,SUM($J$80:J90)) -> 2225040 | R90: =IF(D90=0,0,Q90-P90) -> -544190.77 | S90: =IF(D90=0,0,Q90/P90) -> 0.80348667 | U90: =IF(D90=0,0,SUM($L$21:L90)) -> 13846154 | V90: =IF(D90=0,0,SUM($J$21:J90)) -> 13608340 | W90: =IF(D90=0,0,V90-U90) -> -237813.85 | X90: =IF(D90=0,0,V90/U90) -> 0.98282456 | Y90: =Y89+1 -> 45727 | Z90: =Z89+1 -> 45727
C91: 71 | D91: 1 | E91: =MONTH(Y91) -> 3 | F91: =F90+1 -> 45728 | G91: =TEXT(Z91,"ddd") -> Wed | J91: 320100 | L91: =IF(D91=0,0,$K$9) -> 307692.31 | M91: =IF(D91=0,0,J91-L91) -> 12407.692 | N91: =IFERROR(J91/L91,"¥0") -> 1.040325 | P91: =IF(D91=0,0,SUM($L$80:L91)) -> 3076923.1 | Q91: =IF(D91=0,0,SUM($J$80:J91)) -> 2545140 | R91: =IF(D91=0,0,Q91-P91) -> -531783.08 | S91: =IF(D91=0,0,Q91/P91) -> 0.8271705 | U91: =IF(D91=0,0,SUM($L$21:L91)) -> 14153846 | V91: =IF(D91=0,0,SUM($J$21:J91)) -> 13928440 | W91: =IF(D91=0,0,V91-U91) -> -225406.15 | X91: =IF(D91=0,0,V91/U91) -> 0.98407457 | Y91: =Y90+1 -> 45728 | Z91: =Z90+1 -> 45728
C92: 72 | D92: 1 | E92: =MONTH(Y92) -> 3 | F92: =F91+1 -> 45729 | G92: =TEXT(Z92,"ddd") -> Thu | J92: 327800 | L92: =IF(D92=0,0,$K$9) -> 307692.31 | M92: =IF(D92=0,0,J92-L92) -> 20107.692 | N92: =IFERROR(J92/L92,"¥0") -> 1.06535 | P92: =IF(D92=0,0,SUM($L$80:L92)) -> 3384615.4 | Q92: =IF(D92=0,0,SUM($J$80:J92)) -> 2872940 | R92: =IF(D92=0,0,Q92-P92) -> -511675.38 | S92: =IF(D92=0,0,Q92/P92) -> 0.84882318 | U92: =IF(D92=0,0,SUM($L$21:L92)) -> 14461538 | V92: =IF(D92=0,0,SUM($J$21:J92)) -> 14256240 | W92: =IF(D92=0,0,V92-U92) -> -205298.46 | X92: =IF(D92=0,0,V92/U92) -> 0.98580383 | Y92: =Y91+1 -> 45729 | Z92: =Z91+1 -> 45729
C93: 73 | D93: 1 | E93: =MONTH(Y93) -> 3 | F93: =F92+1 -> 45730 | G93: =TEXT(Z93,"ddd") -> Fri | J93: 409660 | L93: =IF(D93=0,0,$K$9) -> 307692.31 | M93: =IF(D93=0,0,J93-L93) -> 101967.69 | N93: =IFERROR(J93/L93,"¥0") -> 1.331395 | P93: =IF(D93=0,0,SUM($L$80:L93)) -> 3692307.7 | Q93: =IF(D93=0,0,SUM($J$80:J93)) -> 3282600 | R93: =IF(D93=0,0,Q93-P93) -> -409707.69 | S93: =IF(D93=0,0,Q93/P93) -> 0.8890375 | U93: =IF(D93=0,0,SUM($L$21:L93)) -> 14769231 | V93: =IF(D93=0,0,SUM($J$21:J93)) -> 14665900 | W93: =IF(D93=0,0,V93-U93) -> -103330.77 | X93: =IF(D93=0,0,V93/U93) -> 0.99300365 | Y93: =Y92+1 -> 45730 | Z93: =Z92+1 -> 45730
C94: 74 | D94: 1 | E94: =MONTH(Y94) -> 3 | F94: =F93+1 -> 45731 | G94: =TEXT(Z94,"ddd") -> Sat | J94: 139390 | L94: =IF(D94=0,0,$K$9) -> 307692.31 | M94: =IF(D94=0,0,J94-L94) -> -168302.31 | N94: =IFERROR(J94/L94,"¥0") -> 0.4530175 | P94: =IF(D94=0,0,SUM($L$80:L94)) -> 4000000 | Q94: =IF(D94=0,0,SUM($J$80:J94)) -> 3421990 | R94: =IF(D94=0,0,Q94-P94) -> -578010 | S94: =IF(D94=0,0,Q94/P94) -> 0.8554975 | U94: =IF(D94=0,0,SUM($L$21:L94)) -> 15076923 | V94: =IF(D94=0,0,SUM($J$21:J94)) -> 14805290 | W94: =IF(D94=0,0,V94-U94) -> -271633.08 | X94: =IF(D94=0,0,V94/U94) -> 0.98198352 | Y94: =Y93+1 -> 45731 | Z94: =Z93+1 -> 45731
C95: 75 | D95: 0 | E95: =MONTH(Y95) -> 3 | F95: =F94+1 -> 45732 | G95: =TEXT(Z95,"ddd") -> Sun | L95: =IF(D95=0,0,$K$9) -> 0 | M95: =IF(D95=0,0,J95-L95) -> 0 | N95: =IFERROR(J95/L95,"¥0") -> ¥0 | P95: =IF(D95=0,0,SUM($L$80:L95)) -> 0 | Q95: =IF(D95=0,0,SUM($J$80:J95)) -> 0 | R95: =IF(D95=0,0,Q95-P95) -> 0 | S95: =IF(D95=0,0,Q95/P95) -> 0 | U95: =IF(D95=0,0,SUM($L$21:L95)) -> 0 | V95: =IF(D95=0,0,SUM($J$21:J95)) -> 0 | W95: =IF(D95=0,0,V95-U95) -> 0 | X95: =IF(D95=0,0,V95/U95) -> 0 | Y95: =Y94+1 -> 45732 | Z95: =Z94+1 -> 45732
C96: 76 | D96: 1 | E96: =MONTH(Y96) -> 3 | F96: =F95+1 -> 45733 | G96: =TEXT(Z96,"ddd") -> Mon | J96: 329600 | L96: =IF(D96=0,0,$K$9) -> 307692.31 | M96: =IF(D96=0,0,J96-L96) -> 21907.692 | N96: =IFERROR(J96/L96,"¥0") -> 1.0712 | P96: =IF(D96=0,0,SUM($L$80:L96)) -> 4307692.3 | Q96: =IF(D96=0,0,SUM($J$80:J96)) -> 3751590 | R96: =IF(D96=0,0,Q96-P96) -> -556102.31 | S96: =IF(D96=0,0,Q96/P96) -> 0.87090482 | U96: =IF(D96=0,0,SUM($L$21:L96)) -> 15384615 | V96: =IF(D96=0,0,SUM($J$21:J96)) -> 15134890 | W96: =IF(D96=0,0,V96-U96) -> -249725.38 | X96: =IF(D96=0,0,V96/U96) -> 0.98376785 | Y96: =Y95+1 -> 45733 | Z96: =Z95+1 -> 45733
C97: 77 | D97: 1 | E97: =MONTH(Y97) -> 3 | F97: =F96+1 -> 45734 | G97: =TEXT(Z97,"ddd") -> Tue | J97: 373470 | L97: =IF(D97=0,0,$K$9) -> 307692.31 | M97: =IF(D97=0,0,J97-L97) -> 65777.692 | N97: =IFERROR(J97/L97,"¥0") -> 1.2137775 | P97: =IF(D97=0,0,SUM($L$80:L97)) -> 4615384.6 | Q97: =IF(D97=0,0,SUM($J$80:J97)) -> 4125060 | R97: =IF(D97=0,0,Q97-P97) -> -490324.62 | S97: =IF(D97=0,0,Q97/P97) -> 0.893763 | U97: =IF(D97=0,0,SUM($L$21:L97)) -> 15692308 | V97: =IF(D97=0,0,SUM($J$21:J97)) -> 15508360 | W97: =IF(D97=0,0,V97-U97) -> -183947.69 | X97: =IF(D97=0,0,V97/U97) -> 0.98827784 | Y97: =Y96+1 -> 45734 | Z97: =Z96+1 -> 45734
C98: 78 | D98: 1 | E98: =MONTH(Y98) -> 3 | F98: =F97+1 -> 45735 | G98: =TEXT(Z98,"ddd") -> Wed | J98: 389950 | L98: =IF(D98=0,0,$K$9) -> 307692.31 | M98: =IF(D98=0,0,J98-L98) -> 82257.692 | N98: =IFERROR(J98/L98,"¥0") -> 1.2673375 | P98: =IF(D98=0,0,SUM($L$80:L98)) -> 4923076.9 | Q98: =IF(D98=0,0,SUM($J$80:J98)) -> 4515010 | R98: =IF(D98=0,0,Q98-P98) -> -408066.92 | S98: =IF(D98=0,0,Q98/P98) -> 0.91711141 | U98: =IF(D98=0,0,SUM($L$21:L98)) -> 16000000 | V98: =IF(D98=0,0,SUM($J$21:J98)) -> 15898310 | W98: =IF(D98=0,0,V98-U98) -> -101690 | X98: =IF(D98=0,0,V98/U98) -> 0.99364438 | Y98: =Y97+1 -> 45735 | Z98: =Z97+1 -> 45735
C99: 79 | D99: 0 | E99: =MONTH(Y99) -> 3 | F99: =F98+1 -> 45736 | G99: =TEXT(Z99,"ddd") -> Thu | L99: =IF(D99=0,0,$K$9) -> 0 | M99: =IF(D99=0,0,J99-L99) -> 0 | N99: =IFERROR(J99/L99,"¥0") -> ¥0 | P99: =IF(D99=0,0,SUM($L$80:L99)) -> 0 | Q99: =IF(D99=0,0,SUM($J$80:J99)) -> 0 | R99: =IF(D99=0,0,Q99-P99) -> 0 | S99: =IF(D99=0,0,Q99/P99) -> 0 | U99: =IF(D99=0,0,SUM($L$21:L99)) -> 0 | V99: =IF(D99=0,0,SUM($J$21:J99)) -> 0 | W99: =IF(D99=0,0,V99-U99) -> 0 | X99: =IF(D99=0,0,V99/U99) -> 0 | Y99: =Y98+1 -> 45736 | Z99: =Z98+1 -> 45736
C100: 80 | D100: 1 | E100: =MONTH(Y100) -> 3 | F100: =F99+1 -> 45737 | G100: =TEXT(Z100,"ddd") -> Fri | J100: 283190 | L100: =IF(D100=0,0,$K$9) -> 307692.31 | M100: =IF(D100=0,0,J100-L100) -> -24502.308 | N100: =IFERROR(J100/L100,"¥0") -> 0.9203675 | P100: =IF(D100=0,0,SUM($L$80:L100)) -> 5230769.2 | Q100: =IF(D100=0,0,SUM($J$80:J100)) -> 4798200 | R100: =IF(D100=0,0,Q100-P100) -> -432569.23 | S100: =IF(D100=0,0,Q100/P100) -> 0.91730294 | U100: =IF(D100=0,0,SUM($L$21:L100)) -> 16307692 | V100: =IF(D100=0,0,SUM($J$21:J100)) -> 16181500 | W100: =IF(D100=0,0,V100-U100) -> -126192.31 | X100: =IF(D100=0,0,V100/U100) -> 0.99226179 | Y100: =Y99+1 -> 45737 | Z100: =Z99+1 -> 45737
C101: 81 | D101: 1 | E101: =MONTH(Y101) -> 3 | F101: =F100+1 -> 45738 | G101: =TEXT(Z101,"ddd") -> Sat | J101: 300980 | L101: =IF(D101=0,0,$K$9) -> 307692.31 | M101: =IF(D101=0,0,J101-L101) -> -6712.3077 | N101: =IFERROR(J101/L101,"¥0") -> 0.978185 | P101: =IF(D101=0,0,SUM($L$80:L101)) -> 5538461.5 | Q101: =IF(D101=0,0,SUM($J$80:J101)) -> 5099180 | R101: =IF(D101=0,0,Q101-P101) -> -439281.54 | S101: =IF(D101=0,0,Q101/P101) -> 0.92068528 | U101: =IF(D101=0,0,SUM($L$21:L101)) -> 16615385 | V101: =IF(D101=0,0,SUM($J$21:J101)) -> 16482480 | W101: =IF(D101=0,0,V101-U101) -> -132904.62 | X101: =IF(D101=0,0,V101/U101) -> 0.99200111 | Y101: =Y100+1 -> 45738 | Z101: =Z100+1 -> 45738
C102: 82 | D102: 0 | E102: =MONTH(Y102) -> 3 | F102: =F101+1 -> 45739 | G102: =TEXT(Z102,"ddd") -> Sun | L102: =IF(D102=0,0,$K$9) -> 0 | M102: =IF(D102=0,0,J102-L102) -> 0 | N102: =IFERROR(J102/L102,"¥0") -> ¥0 | P102: =IF(D102=0,0,SUM($L$80:L102)) -> 0 | Q102: =IF(D102=0,0,SUM($J$80:J102)) -> 0 | R102: =IF(D102=0,0,Q102-P102) -> 0 | S102: =IF(D102=0,0,Q102/P102) -> 0 | U102: =IF(D102=0,0,SUM($L$21:L102)) -> 0 | V102: =IF(D102=0,0,SUM($J$21:J102)) -> 0 | W102: =IF(D102=0,0,V102-U102) -> 0 | X102: =IF(D102=0,0,V102/U102) -> 0 | Y102: =Y101+1 -> 45739 | Z102: =Z101+1 -> 45739
C103: 83 | D103: 1 | E103: =MONTH(Y103) -> 3 | F103: =F102+1 -> 45740 | G103: =TEXT(Z103,"ddd") -> Mon | J103: 204700 | L103: =IF(D103=0,0,$K$9) -> 307692.31 | M103: =IF(D103=0,0,J103-L103) -> -102992.31 | N103: =IFERROR(J103/L103,"¥0") -> 0.665275 | P103: =IF(D103=0,0,SUM($L$80:L103)) -> 5846153.8 | Q103: =IF(D103=0,0,SUM($J$80:J103)) -> 5303880 | R103: =IF(D103=0,0,Q103-P103) -> -542273.85 | S103: =IF(D103=0,0,Q103/P103) -> 0.90724263 | U103: =IF(D103=0,0,SUM($L$21:L103)) -> 16923077 | V103: =IF(D103=0,0,SUM($J$21:J103)) -> 16687180 | W103: =IF(D103=0,0,V103-U103) -> -235896.92 | X103: =IF(D103=0,0,V103/U103) -> 0.98606064 | Y103: =Y102+1 -> 45740 | Z103: =Z102+1 -> 45740
C104: 84 | D104: 1 | E104: =MONTH(Y104) -> 3 | F104: =F103+1 -> 45741 | G104: =TEXT(Z104,"ddd") -> Tue | J104: 349250 | L104: =IF(D104=0,0,$K$9) -> 307692.31 | M104: =IF(D104=0,0,J104-L104) -> 41557.692 | N104: =IFERROR(J104/L104,"¥0") -> 1.1350625 | P104: =IF(D104=0,0,SUM($L$80:L104)) -> 6153846.2 | Q104: =IF(D104=0,0,SUM($J$80:J104)) -> 5653130 | R104: =IF(D104=0,0,Q104-P104) -> -500716.15 | S104: =IF(D104=0,0,Q104/P104) -> 0.91863362 | U104: =IF(D104=0,0,SUM($L$21:L104)) -> 17230769 | V104: =IF(D104=0,0,SUM($J$21:J104)) -> 17036430 | W104: =IF(D104=0,0,V104-U104) -> -194339.23 | X104: =IF(D104=0,0,V104/U104) -> 0.98872138 | Y104: =Y103+1 -> 45741 | Z104: =Z103+1 -> 45741
C105: 85 | D105: 1 | E105: =MONTH(Y105) -> 3 | F105: =F104+1 -> 45742 | G105: =TEXT(Z105,"ddd") -> Wed | J105: 446680 | L105: =IF(D105=0,0,$K$9) -> 307692.31 | M105: =IF(D105=0,0,J105-L105) -> 138987.69 | N105: =IFERROR(J105/L105,"¥0") -> 1.45171 | P105: =IF(D105=0,0,SUM($L$80:L105)) -> 6461538.5 | Q105: =IF(D105=0,0,SUM($J$80:J105)) -> 6099810 | R105: =IF(D105=0,0,Q105-P105) -> -361728.46 | S105: =IF(D105=0,0,Q105/P105) -> 0.94401821 | U105: =IF(D105=0,0,SUM($L$21:L105)) -> 17538462 | V105: =IF(D105=0,0,SUM($J$21:J105)) -> 17483110 | W105: =IF(D105=0,0,V105-U105) -> -55351.538 | X105: =IF(D105=0,0,V105/U105) -> 0.99684399 | Y105: =Y104+1 -> 45742 | Z105: =Z104+1 -> 45742
C106: 86 | D106: 1 | E106: =MONTH(Y106) -> 3 | F106: =F105+1 -> 45743 | G106: =TEXT(Z106,"ddd") -> Thu | J106: 367730 | L106: =IF(D106=0,0,$K$9) -> 307692.31 | M106: =IF(D106=0,0,J106-L106) -> 60037.692 | N106: =IFERROR(J106/L106,"¥0") -> 1.1951225 | P106: =IF(D106=0,0,SUM($L$80:L106)) -> 6769230.8 | Q106: =IF(D106=0,0,SUM($J$80:J106)) -> 6467540 | R106: =IF(D106=0,0,Q106-P106) -> -301690.77 | S106: =IF(D106=0,0,Q106/P106) -> 0.95543205 | U106: =IF(D106=0,0,SUM($L$21:L106)) -> 17846154 | V106: =IF(D106=0,0,SUM($J$21:J106)) -> 17850840 | W106: =IF(D106=0,0,V106-U106) -> 4686.1538 | X106: =IF(D106=0,0,V106/U106) -> 1.0002626 | Y106: =Y105+1 -> 45743 | Z106: =Z105+1 -> 45743
C107: 87 | D107: 1 | E107: =MONTH(Y107) -> 3 | F107: =F106+1 -> 45744 | G107: =TEXT(Z107,"ddd") -> Fri | J107: 441460 | L107: =IF(D107=0,0,$K$9) -> 307692.31 | M107: =IF(D107=0,0,J107-L107) -> 133767.69 | N107: =IFERROR(J107/L107,"¥0") -> 1.434745 | P107: =IF(D107=0,0,SUM($L$80:L107)) -> 7076923.1 | Q107: =IF(D107=0,0,SUM($J$80:J107)) -> 6909000 | R107: =IF(D107=0,0,Q107-P107) -> -167923.08 | S107: =IF(D107=0,0,Q107/P107) -> 0.97627174 | U107: =IF(D107=0,0,SUM($L$21:L107)) -> 18153846 | V107: =IF(D107=0,0,SUM($J$21:J107)) -> 18292300 | W107: =IF(D107=0,0,V107-U107) -> 138453.85 | X107: =IF(D107=0,0,V107/U107) -> 1.0076267 | Y107: =Y106+1 -> 45744 | Z107: =Z106+1 -> 45744
C108: 88 | D108: 1 | E108: =MONTH(Y108) -> 3 | F108: =F107+1 -> 45745 | G108: =TEXT(Z108,"ddd") -> Sat | J108: 123790 | L108: =IF(D108=0,0,$K$9) -> 307692.31 | M108: =IF(D108=0,0,J108-L108) -> -183902.31 | N108: =IFERROR(J108/L108,"¥0") -> 0.4023175 | P108: =IF(D108=0,0,SUM($L$80:L108)) -> 7384615.4 | Q108: =IF(D108=0,0,SUM($J$80:J108)) -> 7032790 | R108: =IF(D108=0,0,Q108-P108) -> -351825.38 | S108: =IF(D108=0,0,Q108/P108) -> 0.95235698 | U108: =IF(D108=0,0,SUM($L$21:L108)) -> 18461538 | V108: =IF(D108=0,0,SUM($J$21:J108)) -> 18416090 | W108: =IF(D108=0,0,V108-U108) -> -45448.462 | X108: =IF(D108=0,0,V108/U108) -> 0.99753821 | Y108: =Y107+1 -> 45745 | Z108: =Z107+1 -> 45745
C109: 89 | D109: 0 | E109: =MONTH(Y109) -> 3 | F109: =F108+1 -> 45746 | G109: =TEXT(Z109,"ddd") -> Sun | L109: =IF(D109=0,0,$K$9) -> 0 | M109: =IF(D109=0,0,J109-L109) -> 0 | N109: =IFERROR(J109/L109,"¥0") -> ¥0 | P109: =IF(D109=0,0,SUM($L$80:L109)) -> 0 | Q109: =IF(D109=0,0,SUM($J$80:J109)) -> 0 | R109: =IF(D109=0,0,Q109-P109) -> 0 | S109: =IF(D109=0,0,Q109/P109) -> 0 | U109: =IF(D109=0,0,SUM($L$21:L109)) -> 0 | V109: =IF(D109=0,0,SUM($J$21:J109)) -> 0 | W109: =IF(D109=0,0,V109-U109) -> 0 | X109: =IF(D109=0,0,V109/U109) -> 0 | Y109: =Y108+1 -> 45746 | Z109: =Z108+1 -> 45746
C110: 90 | D110: 1 | E110: =MONTH(Y110) -> 3 | F110: =F109+1 -> 45747 | G110: =TEXT(Z110,"ddd") -> Mon | J110: 162500 | L110: =IF(D110=0,0,$K$9) -> 307692.31 | M110: =IF(D110=0,0,J110-L110) -> -145192.31 | N110: =IFERROR(J110/L110,"¥0") -> 0.528125 | P110: =IF(D110=0,0,SUM($L$80:L110)) -> 7692307.7 | Q110: =IF(D110=0,0,SUM($J$80:J110)) -> 7195290 | R110: =IF(D110=0,0,Q110-P110) -> -497017.69 | S110: =IF(D110=0,0,Q110/P110) -> 0.9353877 | U110: =IF(D110=0,0,SUM($L$21:L110)) -> 18769231 | V110: =IF(D110=0,0,SUM($J$21:J110)) -> 18578590 | W110: =IF(D110=0,0,V110-U110) -> -190640.77 | X110: =IF(D110=0,0,V110/U110) -> 0.98984291 | Y110: =Y109+1 -> 45747 | Z110: =Z109+1 -> 45747
C111: 91 | D111: 1 | E111: =MONTH(Y111) -> 4 | F111: =F110+1 -> 45748 | G111: =TEXT(Z111,"ddd") -> Tue | J111: 429950 | L111: =IF(D111=0,0,$K$10) -> 307692.31 | M111: =IF(D111=0,0,J111-L111) -> 122257.69 | N111: =IFERROR(J111/L111,"¥0") -> 1.3973375 | P111: =IF(D111=0,0,$L$111) -> 307692.31 | Q111: =IF(D111=0,0,$J$111) -> 429950 | R111: =IF(D111=0,0,Q111-P111) -> 122257.69 | S111: =IF(D111=0,0,Q111/P111) -> 1.3973375 | U111: =IF(D111=0,0,SUM($L$21:L111)) -> 19076923 | V111: =IF(D111=0,0,SUM($J$21:J111)) -> 19008540 | W111: =IF(D111=0,0,V111-U111) -> -68383.077 | X111: =IF(D111=0,0,V111/U111) -> 0.9964154 | Y111: =Y110+1 -> 45748 | Z111: =Z110+1 -> 45748
...

Sheet 適正原価率表(仕入れお小遣い制度)
B1: 2025年次売上目標額 | L1: 2024年売上実績
B2: 80000000 | C2: =SUM(B4:B27) -> 63508421 | L2: 71110161
B3: 目標売上額 | C3: 営業日数 | D3: カテゴリ | E3: 売上率(2024年) | F3: 想定売上額 | H3: 目標原価率 | I3: 月次目標原価額 | J3: 1日あたりの仕入額 | L3: 2024年仕入れ額 | M3: 差額=削減目標額 | O3: 食材原価率
A4: 45658 | B4: =目標_2025R7!I7 -> 5835789.5 | C4: =目標_2025R7!F7 -> 22 | D4: フード | E4: =バルカ18期!E12 -> 0.73432464 | F4: =B4*E4 -> 4285364 | H4: 0.3 | I4: =F4*H4 -> 1285609.2 | J4: =I4/C4 -> 58436.782 | L4: =バルカ18期!D13 -> 1264422 | M4: =I4-L4 -> 21187.203 | O4: =(I4+I5)/B4 -> 0.27343246
D5: ドリンク | E5: =バルカ18期!E14 -> 0.26567536 | F5: =B4*E5 -> 1550425.5 | H5: 0.2 | I5: =F5*H5 -> 310085.09 | J5: =I5/C4 -> 14094.777 | L5: =バルカ18期!D15 -> 486956 | M5: =I5-L5 -> -176870.91
A6: 45689 | B6: =目標_2025R7!I8 -> 4863157.9 | C6: =目標_2025R7!F8 -> 22 | D6: フード | E6: =バルカ18期!G12 -> 0.7316942 | F6: =B6*E6 -> 3558344.4 | H6: 0.3 | I6: =F6*H6 -> 1067503.3 | J6: =I6/C6 -> 48522.879 | L6: =バルカ18期!F13 -> 1416358 | M6: =I6-L6 -> -348854.67 | O6: =(I6+I7)/B6 -> 0.27316942
D7: ドリンク | E7: =バルカ18期!G14 -> 0.2683058 | F7: =B6*E7 -> 1304813.5 | H7: 0.2 | I7: =F7*H7 -> 260962.69 | J7: =I7/C6 -> 11861.941 | L7: =バルカ18期!F15 -> 361305 | M7: =I7-L7 -> -100342.31
A8: 45717 | B8: =目標_2025R7!I9 -> 7184210.5 | C8: =目標_2025R7!F9 -> 25 | D8: フード | E8: =バルカ18期!I12 -> 0.75556981 | F8: =B8*E8 -> 5428172.6 | H8: 0.3 | I8: =F8*H8 -> 1628451.8 | J8: =I8/C8 -> 65138.071 | L8: =バルカ18期!H13 -> 1742628 | M8: =I8-L8 -> -114176.23 | O8: =(I8+I9)/B8 -> 0.27555698
D9: ドリンク | E9: =バルカ18期!I14 -> 0.24443019 | F9: =B8*E9 -> 1756037.9 | H9: 0.2 | I9: =F9*H9 -> 351207.59 | J9: =I9/C8 -> 14048.304 | L9: =バルカ18期!H15 -> 394307 | M9: =I9-L9 -> -43099.41
A10: 45748 | B10: =目標_2025R7!I10 -> 7184210.5 | C10: =目標_2025R7!F10 -> 25 | D10: フード | E10: =バルカ18期!K12 -> 0.74456124 | F10: =B10*E10 -> 5349084.7 | H10: 0.3 | I10: =F10*H10 -> 1604725.4 | J10: =I10/C10 -> 64189.016 | L10: =バルカ18期!J13 -> 1870295 | M10: =I10-L10 -> -265569.6 | O10: =(I10+I11)/B10 -> 0.27445612
D11: ドリンク | E11: =バルカ18期!K14 -> 0.25543876 | F11: =B10*E11 -> 1835125.8 | H11: 0.2 | I11: =F11*H11 -> 367025.17 | J11: =I11/C10 -> 14681.007 | L11: =バルカ18期!J15 -> 369635 | M11: =I11-L11 -> -2609.8311
A12: 45778 | B12: =目標_2025R7!I11 -> 5835789.5 | C12: =目標_2025R7!F11 -> 24 | D12: フード | E12: =バルカ18期!M12 -> 0.75478872 | F12: =B12*E12 -> 4404788.1 | H12: 0.3 | I12: =F12*H12 -> 1321436.4 | J12: =I12/C12 -> 55059.851 | L12: =バルカ18期!L13 -> 1771753 | M12: =I12-L12 -> -450316.58 | O12: =(I12+I13)/B12 -> 0.27547887
D13: ドリンク | E13: =バルカ18期!M14 -> 0.24521128 | F13: =B12*E13 -> 1431001.4 | H13: 0.2 | I13: =F13*H13 -> 286200.28 | J13: =I13/C12 -> 11925.012 | L13: =バルカ18期!L15 -> 336516 | M13: =I13-L13 -> -50315.717
A14: 45809 | B14: =目標_2025R7!I12 -> 6078947.4 | C14: =目標_2025R7!F12 -> 25 | D14: フード | E14: =バルカ18期!O12 -> 0.75608291 | F14: =B14*E14 -> 4596188.2 | H14: 0.3 | I14: =F14*H14 -> 1378856.5 | J14: =I14/C14 -> 55154.258 | L14: =バルカ18期!N13 -> 2345230 | M14: =I14-L14 -> -966373.54 | O14: =(I14+I15)/B14 -> 0.27560829
D15: ドリンク | E15: =バルカ18期!O14 -> 0.24391709 | F15: =B14*E15 -> 1482759.2 | H15: 0.2 | I15: =F15*H15 -> 296551.84 | J15: =I15/C14 -> 11862.073 | L15: =バルカ18期!N15 -> 328916 | M15: =I15-L15 -> -32364.164
A16: 45839 | B16: =目標_2025R7!I13 -> 5172631.6 | C16: =目標_2025R7!F13 -> 26 | D16: フード | E16: =バルカ18期!Q12 -> 0.77721653 | F16: =B16*E16 -> 4020254.8 | H16: 0.3 | I16: =F16*H16 -> 1206076.4 | J16: =I16/C16 -> 46387.555 | L16: =バルカ18期!P13 -> 1682168 | M16: =I16-L16 -> -476091.57 | O16: =(I16+I17)/B16 -> 0.27772165
D17: ドリンク | E17: =バルカ18期!Q14 -> 0.22278347 | F17: =B16*E17 -> 1152376.8 | H17: 0.2 | I17: =F17*H17 -> 230475.36 | J17: =I17/C16 -> 8864.437 | L17: =バルカ18期!P15 -> 441503 | M17: =I17-L17 -> -211027.64
A18: 45870 | B18: =目標_2025R7!I14 -> 2210526.3 | C18: =目標_2025R7!F14 -> 20 | D18: フード | E18: =バルカ18期!S12 -> 0.76479 | F18: =B18*E18 -> 1690588.4 | H18: 0.3 | I18: =F18*H18 -> 507176.52 | J18: =I18/C18 -> 25358.826 | L18: =バルカ18期!R13 -> 1300325 | M18: =I18-L18 -> -793148.48 | O18: =(I18+I19)/B18 -> 0.276479
D19: ドリンク | E19: =バルカ18期!S14 -> 0.23521 | F19: =B18*E19 -> 519937.9 | H19: 0.2 | I19: =F19*H19 -> 103987.58 | J19: =I19/C18 -> 5199.379 | L19: =バルカ18期!R15 -> 225741 | M19: =I19-L19 -> -121753.42
A20: 45901 | B20: =目標_2025R7!I15 -> 3050526.3 | C20: =目標_2025R7!F15 -> 23 | D20: フード | E20: =バルカ18期!U12 -> 0.76676359 | F20: =B20*E20 -> 2339032.5 | H20: 0.3 | I20: =F20*H20 -> 701709.76 | J20: =I20/C20 -> 30509.12 | L20: =バルカ18期!T13 -> 1712780 | M20: =I20-L20 -> -1011070.2 | O20: =(I20+I21)/B20 -> 0.27667636
D21: ドリンク | E21: =バルカ18期!U14 -> 0.23323641 | F21: =B20*E21 -> 711493.8 | H21: 0.2 | I21: =F21*H21 -> 142298.76 | J21: =I21/C20 -> 6186.9026 | L21: =バルカ18期!T15 -> 358096 | M21: =I21-L21 -> -215797.24
A22: 45931 | B22: =目標_2025R7!I16 -> 5172631.6 | C22: =目標_2025R7!F16 -> 26 | D22: フード | E22: =バルカ18期!W12 -> 0.76291191 | F22: =B22*E22 -> 3946262.2 | H22: 0.3 | I22: =F22*H22 -> 1183878.7 | J22: =I22/C22 -> 45533.795 | L22: =バルカ18期!V13 -> 1877653 | M22: =I22-L22 -> -693774.33 | O22: =(I22+I23)/B22 -> 0.27629119
D23: ドリンク | E23: =バルカ18期!W14 -> 0.23708809 | F23: =B22*E23 -> 1226369.3 | H23: 0.2 | I23: =F23*H23 -> 245273.87 | J23: =I23/C22 -> 9433.6103 | L23: =バルカ18期!V15 -> 424058 | M23: =I23-L23 -> -178784.13
A24: 45962 | B24: =目標_2025R7!I17 -> 5084210.5 | C24: =目標_2025R7!F17 -> 23 | D24: フード | E24: =バルカ18期!Y12 -> 0.75359571 | F24: =B24*E24 -> 3831439.2 | H24: 0.3 | I24: =F24*H24 -> 1149431.8 | J24: =I24/C24 -> 49975.294 | L24: =バルカ18期!X13 -> 1365920 | M24: =I24-L24 -> -216488.23 | O24: =(I24+I25)/B24 -> 0.27535957
D25: ドリンク | E25: =バルカ18期!Y14 -> 0.24640429 | F25: =B24*E25 -> 1252771.3 | H25: 0.2 | I25: =F25*H25 -> 250554.26 | J25: =I25/C24 -> 10893.663 | L25: =バルカ18期!X15 -> 379401 | M25: =I25-L25 -> -128846.74
A26: 45992 | B26: =目標_2025R7!I18 -> 5835789.5 | C26: =目標_2025R7!F18 -> 24 | D26: フード | E26: =バルカ18期!AA12 -> 0.75430599 | F26: =B26*E26 -> 4401971 | H26: 0.3 | I26: =F26*H26 -> 1320591.3 | J26: =I26/C26 -> 55024.637 | L26: =バルカ18期!Z13 -> 2079765 | M26: =I26-L26 -> -759173.71 | O26: =(I26+I27)/B26 -> 0.2754306
D27: ドリンク | E27: =バルカ18期!AA14 -> 0.24569401 | F27: =B26*E27 -> 1433818.5 | H27: 0.2 | I27: =F27*H27 -> 286763.7 | J27: =I27/C26 -> 11948.488 | L27: =バルカ18期!Z15 -> 568462 | M27: =I27-L27 -> -281698.3
I28: =SUM(I4:I27) -> 17486833 | J28: =I28/B2 -> 0.21858542 | L28: =SUM(L4:L27) -> 25104193 | M28: =L28/L2 -> 0.35303243

Sheet 戦略シート
B2: 日程 | D2: ①日次目標売上 | E2: 月次目標売上 | F2: 同月営業残日数 | I2: ランチ平均客単価 | J2: ディナー平均客単価
B3: 45822 | D3: =INDEX(目標_2025R7!L20:L384, MATCH(B3, 目標_2025R7!F20:F384, 0)) -> 174297.9 | E3: {=INDEX(目標_2025R7!I7:I18, MONTH(B3))} -> 6078947.4 | F3: =SUMIFS(目標_2025R7!D20:D384, 目標_2025R7!F20:F384, ">=" & B3, 目標_2025R7!E20:E384, MONTH(B3)) -> 14 | I3: 1275 | J3: 6274
D5: ②前年同曜日実質売上額 | E5: {=IF( INDEX(実績_2024R6!D20:D385, MATCH(1, (実績_2024R6!G20:G385=TEXT(B3,"ddd"))* (実績_2024R6!F20:F385>=B3-370)* (実績_2024R6!F20:F385<=B3-358), 0) )=0, "店休日", INDEX(実績_2024R6!J20:J385, MATCH(1, (実績_2024R6!G20:G385=TEXT(B3,"ddd"))* (実績_2024R6!F20:F385>=B3-370)* (実績_2024R6!F20:F385<=B3-358), 0) ) )} -> 161770 | F5: {=TEXT( INDEX(実績_2024R6!F20:F385, MATCH(1, (実績_2024R6!G20:G385=TEXT(B3,"ddd"))* (実績_2024R6!F20:F385>=B3-370)* (実績_2024R6!F20:F385<=B3-358), 0) ), "yyyy/m/d (ddd)" )} -> 2024/6/15 (Sat) | G5: 前年同曜日の実績売上
D6: ②ー①差額 | E6: =E5-D3 -> -12527.902
D7: 達成率 | E7: =E5/D3 -> 0.92812362
D9: 月次売上額 | E9: =INDEX(目標_2025R7!Q20:Q384, MATCH(B3, 目標_2025R7!F20:F384, 0)) -> 2650720
D10: 月次目標売上額 | E10: =INDEX(目標_2025R7!P20:P384, MATCH(B3, 目標_2025R7!F20:F384, 0)) -> 2960345.9
D11: ③月次差額 | E11: =E9-E10 -> -309625.86
D12: 月次達成率 | E12: =E10/E9 -> 1.1168082
D13: 1日辺りに取返す額 | E13: =E11/F3 -> -22116.133 | F13: ＊営業残日数で③を割った値
D15: 年次売上額 | E15: =INDEX(目標_2025R7!V20:V384, MATCH(B3, 目標_2025R7!F20:F384, 0)) -> 34379580
D16: 年次目標売上額 | E16: =INDEX(目標_2025R7!U20:U384, MATCH(B3, 目標_2025R7!F20:F384, 0)) -> 33863504
D17: 年次差額 | E17: =E16-E15 -> -516076.24
D18: 年次達成率 | E18: =E15/E16 -> 1.0152399
D20: 1日の売上目標値 参考例
D21: 目標売上 | F21: =D3 -> 174297.9
D22: 実質予想売上額 | F22: =E5 -> 161770
D23: 差額 | F23: =F22-F21 -> -12527.902
D24: 仮1日売上総合計 | F24: =F25-F23 -> 217805.9
D25: シュミレーター | F25: =SUM(G27:G32) -> 205278
D26: 項目 | E26: 仮客単価 | F26: 集客数 | G26: 仮1日の売上小計
D27: ランチ | E27: ='2024年間データ'!G30 -> 1275.1667 | F27: 67 | G27: =E27*F27 -> 85436.167
D28: ディナー | E28: ='2024年間データ'!H30 -> 6274.4167 | F28: 14 | G28: =E28*F28 -> 87841.833
D29: Party 5500 | E29: 5500 | F29: 0 | G29: =E29*F29 -> 0
D30: Party 6800 | E30: 6800 | F30: 0 | G30: =E30*F30 -> 0
D31: Party 8000 | E31: 8000 | F31: 4 | G31: =E31*F31 -> 32000
F32: 0 | G32: =E32*F32 -> 0

Sheet 実績_2024R6
B2: 45292 | E2: ①年間営業日 | G2: ②年間目標売上 | I2: 年間売上％設定 | M2: 年間売上合計 | O2: 年間実質売上 | Q2: 年間利益率 | R2: 年間予想利益額
E3: =SUM(F6:F17) -> 289 | G3: 71220821 | I3: =SUM(AD6:AD17)*100 -> 0.9999996 | K3: =G3*I3 -> 71220793 | M3: =SUM(J20:J385) -> 71220821 | O3: =M3-G3 -> 0 | Q3: 0.21 | R3: =M3*Q3 -> 14956372
B5: 平均日次売上目標額 | E5: 月 | F5: 月次営業日数 | G5: 平均月間売上目標額 | H5: 月次繁閑期%設定 | J5: 月次目標売上 | K5: 日次目標売上 | M5: 月次売上 | N5: 月間差額 | P5: 月次実質% | R5: 1日の売上目標値 参考例 | AC5: =TEXT(K6,"¥0") -> ¥221795
B6: ② ÷ ① | E6: 1月 | F6: =COUNTIF(D20:D50,1) -> 22 | G6: =$B$7*F6 -> 5421654.2 | H6: 0.9 | J6: =G6*H6 -> 4879488.8 | K6: =J6/F6 -> 221794.94 | M6: =SUM(J20:J50) -> 4982374 | N6: =M6-J6 -> 102885.23 | P6: =M6/G6 -> 0.91897672 | R6: 目標売上 | T6: ¥233564 | V6: 0.76 | AC6: =TEXT(K7,"¥0") -> ¥209473 | AD6: =(H6/100)*AE6 -> 0.0007499997 | AE6: 0.0833333
B7: =G3/E3 -> 246438.83 | E7: 2月 | F7: =COUNTIF(D51:D79,1) -> 23 | G7: =$B$7*F7 -> 5668093 | H7: 0.85 | J7: =G7*H7 -> 4817879.1 | K7: =J7/F7 -> 209473 | M7: =SUM(J51:J79) -> 5001830 | N7: =M7-J7 -> 183950.93 | P7: =M7/G7 -> 0.88245376 | T7: =T6*V6 -> 177508.64 | AC7: =TEXT(K8,"¥0") -> ¥246439 | AD7: =(H7/100)*AE7 -> 0.00070833305 | AE7: 0.0833333
E8: 3月 | F8: =COUNTIF(D80:D110,1) -> 25 | G8: =$B$7*F8 -> 6160970.7 | H8: 1 | J8: =G8*H8 -> 6160970.7 | K8: =J8/F8 -> 246438.83 | M8: =SUM(J80:J110) -> 6460608 | N8: =M8-J8 -> 299637.33 | P8: =M8/G8 -> 1.0486348 | R8: 差額 | T8: =T9-T6 -> 87436 | AC8: =TEXT(K9,"¥0") -> ¥258761 | AD8: =(H8/100)*AE8 -> 0.000833333 | AE8: 0.0833333
E9: 4月 | F9: =COUNTIF(D111:D140,1) -> 25 | G9: =$B$7*F9 -> 6160970.7 | H9: 1.05 | J9: =G9*H9 -> 6469019.2 | K9: =J9/F9 -> 258760.77 | M9: =SUM(J111:J140) -> 6676657 | N9: =M9-J9 -> 207637.79 | P9: =M9/G9 -> 1.0837021 | R9: 仮1日売上総合計 | T9: =SUM(V11:V16) -> 321000 | AC9: =TEXT(K10,"¥0") -> ¥246439 | AD9: =(H9/100)*AE9 -> 0.00087499965 | AE9: 0.0833333
E10: 5月 | F10: =COUNTIF(D141:D171,1) -> 24 | G10: =$B$7*F10 -> 5914531.8 | H10: 1 | J10: =G10*H10 -> 5914531.8 | K10: =J10/F10 -> 246438.83 | M10: =SUM(J141:J171) -> 6165010 | N10: =M10-J10 -> 250478.15 | P10: =M10/G10 -> 1.0423496 | R10: 項目 | S10: 仮客単価 | T10: 集客数 | V10: 仮1日の売上小計 | AC10: =TEXT(K11,"¥0") -> ¥221795 | AD10: =(H10/100)*AE10 -> 0.000833333 | AE10: 0.0833333
E11: 6月 | F11: =COUNTIF(D172:D201,1) -> 25 | G11: =$B$7*F11 -> 6160970.7 | H11: 0.9 | J11: =G11*H11 -> 5544873.6 | K11: =J11/F11 -> 221794.94 | M11: =SUM(J172:J201) -> 5907950 | N11: =M11-J11 -> 363076.39 | P11: =M11/G11 -> 0.95893169 | R11: ランチ | S11: 1100 | T11: 60 | V11: =S11*T11 -> 66000 | AC11: =TEXT(K12,"¥0") -> ¥234117 | AD11: =(H11/100)*AE11 -> 0.0007499997 | AE11: 0.0833333
E12: 7月 | F12: =COUNTIF(D202:D232,1) -> 26 | G12: =$B$7*F12 -> 6407409.5 | H12: 0.95 | J12: =G12*H12 -> 6087039 | K12: =J12/F12 -> 234116.89 | M12: =SUM(J202:J232) -> 6522185 | N12: =M12-J12 -> 435145.97 | P12: =M12/G12 -> 1.0179129 | R12: ディナー | S12: 4500 | T12: 20 | V12: =S12*T12 -> 90000 | AC12: =TEXT(K13,"¥0") -> ¥197151 | AD12: =(H12/100)*AE12 -> 0.00079166635 | AE12: 0.0833333
E13: 8月 | F13: =COUNTIF(D233:D263,1) -> 22 | G13: =$B$7*F13 -> 5421654.2 | H13: 0.8 | J13: =G13*H13 -> 4337323.4 | K13: =J13/F13 -> 197151.06 | M13: =SUM(J233:J263) -> 4512002 | N13: =M13-J13 -> 174678.64 | P13: =M13/G13 -> 0.8322187 | R13: Party 5500 | S13: 5500 | T13: 30 | V13: =S13*T13 -> 165000 | AC13: =TEXT(K14,"¥0") -> ¥234117 | AD13: =(H13/100)*AE13 -> 0.0006666664 | AE13: 0.0833333
E14: 9 月 | F14: =COUNTIF(D264:D293,1) -> 23 | G14: =$B$7*F14 -> 5668093 | H14: 0.95 | J14: =G14*H14 -> 5384688.4 | K14: =J14/F14 -> 234116.89 | M14: =SUM(J264:J293) -> 5425075 | N14: =M14-J14 -> 40386.63 | P14: =M14/G14 -> 0.95712526 | T14: 0 | V14: =S14*T14 -> 0 | AC14: =TEXT(K15,"¥0") -> ¥308049 | AD14: =(H14/100)*AE14 -> 0.00079166635 | AE14: 0.0833333
E15: 10月 | F15: =COUNTIF(D294:D324,1) -> 26 | G15: =$B$7*F15 -> 6407409.5 | H15: 1.25 | J15: =G15*H15 -> 8009261.9 | K15: =J15/F15 -> 308048.53 | M15: =SUM(J294:J324) -> 5555530 | N15: =M15-J15 -> -2453731.9 | P15: =M15/G15 -> 0.86704775 | T15: 0 | V15: =S15*T15 -> 0 | AC15: =TEXT(K16,"¥0") -> ¥258761 | AD15: =(H15/100)*AE15 -> 0.0010416662 | AE15: 0.0833333
E16: 11月 | F16: =COUNTIF(D325:D354,1) -> 24 | G16: =$B$7*F16 -> 5914531.8 | H16: 1.05 | J16: =G16*H16 -> 6210258.4 | K16: =J16/F16 -> 258760.77 | M16: =SUM(J325:J354) -> 6112150 | N16: =M16-J16 -> -98108.44 | P16: =M16/G16 -> 1.0334123 | T16: 0 | V16: =S16*T16 -> 0 | AC16: =TEXT(K17,"¥0") -> ¥320370 | AD16: =(H16/100)*AE16 -> 0.00087499965 | AE16: 0.0833333
E17: 12月 | F17: =COUNTIF(D355:D385,1) -> 24 | G17: =$B$7*F17 -> 5914531.8 | H17: 1.3 | J17: =G17*H17 -> 7688891.4 | K17: =J17/F17 -> 320370.48 | M17: =SUM(J355:J385) -> 7899450 | N17: =M17-J17 -> 210558.6 | P17: =M17/G17 -> 1.3356002 | AD17: =(H17/100)*AE17 -> 0.0010833329 | AE17: 0.0833333
E19: 月 | F19: 日程 | G19: 曜日 | H19: 休店日理由 | J19: Daily売上入力 | L19: 目標売上 KPI | M19: 日次実質売上 | N19: 実質% | P19: 月次目標売上 | Q19: 月次実質売上 | R19: 月次差額(勝率) | S19: 月次実質% | U19: 年次目標売上 | V19: 年次実質売上 | W19: 年次差額(勝率) | X19: 年次実質% | AC19: 月 | AD19: 曜日 | AE19: 平均売上 | AF19: 曜日回数 | AH19: 曜日合計額 | AI19: 加重比率
C20: 1 | D20: 0 | E20: =TEXT(AA20,"m") -> 1 | F20: =B2 -> 45292 | G20: =TEXT(Z20,"ddd") -> Mon | H20: 元旦 | J20: 0 | L20: =IF(D20=0,0,$K$6) -> 0 | M20: =IF(D20=0,0,J20-L20) -> 0 | N20: =IFERROR(J20/L20,"0%") -> 0% | P20: =IF(D20=0,0,$K$6) -> 0 | Q20: =IF(D20=0,0,$J$20) -> 0 | R20: =IF(D20=0,0,Q20-P20) -> 0 | S20: =IFERROR(Q20/P20,"0%") -> 0% | U20: =IF(D20=0,0,$L$20) -> 0 | V20: =IF(D20=0,0,$J$20) -> 0 | W20: =IF(D20=0,0,V20-U20) -> 0 | X20: =IFERROR(V20/U20,"0%") -> 0% | Z20: =B2 -> 45292 | AA20: =B2 -> 45292 | AB20: 45292 | AC20: 1 | AD20: 月 | AE20: =IFERROR(AVERAGEIFS(J20:J50,D20:D50,1,G20:G50,"mon"),0) -> 253025 | AF20: =COUNTIFS(D20:D50,1,G20:G50,"Mon") -> 4 | AG20: =SUMIFS(J20:J50,D20:D50,1,G20:G50,"mon") -> 1012100 | AH20: =AE20*AF20 -> 1012100 | AI20: =AH20/$M$6 -> 0.2031361 | AJ20: =SUM(AI20:AI26) -> 1
C21: =C20+1 -> 2 | D21: 0 | E21: =TEXT(AA21,"m") -> 1 | F21: =F20+1 -> 45293 | G21: =TEXT(Z21,"ddd") -> Tue | H21: 休み | J21: 0 | L21: =IF(D21=0,0,$K$6) -> 0 | M21: =IF(D21=0,0,J21-L21) -> 0 | N21: =IFERROR(J21/L21,"0%") -> 0% | P21: =IF(D21=0,0,SUM($L$20:L21)) -> 0 | Q21: =IF(D21=0,0,SUM($J$20:J21)) -> 0 | R21: =IF(D21=0,0,Q21-P21) -> 0 | S21: =IFERROR(Q21/P21,"0%") -> 0% | U21: =IF(D21=0,0,SUM($L$20:L21)) -> 0 | V21: =IF(D21=0,0,SUM($J$20:J21)) -> 0 | W21: =IF(D21=0,0,V21-U21) -> 0 | X21: =IFERROR(V21/U21,"0%") -> 0% | Z21: =Z20+1 -> 45293 | AA21: =AA20+1 -> 45293 | AB21: 45293 | AC21: 1 | AD21: 火 | AE21: =IFERROR(AVERAGEIFS(J20:J50,D20:D50,1,G20:G50,"tue"),0) -> 214411 | AF21: =COUNTIFS(D20:D50,1,G20:G50,"Tue") -> 4 | AH21: =AE21*AF21 -> 857644 | AI21: =AH21/$M$6 -> 0.17213561
C22: =C21+1 -> 3 | D22: 0 | E22: =TEXT(AA22,"m") -> 1 | F22: =F21+1 -> 45294 | G22: =TEXT(Z22,"ddd") -> Wed | H22: 休み | J22: 0 | L22: =IF(D22=0,0,$K$6) -> 0 | M22: =IF(D22=0,0,J22-L22) -> 0 | N22: =IFERROR(J22/L22,"0%") -> 0% | P22: =IF(D22=0,0,SUM($L$20:L22)) -> 0 | Q22: =IF(D22=0,0,SUM($J$20:J22)) -> 0 | R22: =IF(D22=0,0,Q22-P22) -> 0 | S22: =IFERROR(Q22/P22,"0%") -> 0% | U22: =IF(D22=0,0,SUM($L$20:L22)) -> 0 | V22: =IF(D22=0,0,SUM($J$20:J22)) -> 0 | W22: =IF(D22=0,0,V22-U22) -> 0 | X22: =IFERROR(V22/U22,"0%") -> 0% | Z22: =Z21+1 -> 45294 | AA22: =AA21+1 -> 45294 | AB22: 45294 | AC22: 1 | AD22: 水 | AE22: =IFERROR(AVERAGEIFS(J20:J50,D20:D50,1,G20:G50,"wed"),0) -> 241500 | AF22: =COUNTIFS(D20:D50,1,G20:G50,"wed") -> 4 | AH22: =AE22*AF22 -> 966000 | AI22: =AH22/$M$6 -> 0.19388348
C23: =C22+1 -> 4 | D23: 0 | E23: =TEXT(AA23,"m") -> 1 | F23: =F22+1 -> 45295 | G23: =TEXT(Z23,"ddd") -> Thu | H23: 祝日 | J23: 0 | L23: =IF(D23=0,0,$K$6) -> 0 | M23: =IF(D23=0,0,J23-L23) -> 0 | N23: =IFERROR(J23/L23,"0%") -> 0% | P23: =IF(D23=0,0,SUM($L$20:L23)) -> 0 | Q23: =IF(D23=0,0,SUM($J$20:J23)) -> 0 | R23: =IF(D23=0,0,Q23-P23) -> 0 | S23: =IFERROR(Q23/P23,"0%") -> 0% | U23: =IF(D23=0,0,SUM($L$20:L23)) -> 0 | V23: =IF(D23=0,0,SUM($J$20:J23)) -> 0 | W23: =IF(D23=0,0,V23-U23) -> 0 | X23: =IFERROR(V23/U23,"0%") -> 0% | Z23: =Z22+1 -> 45295 | AA23: =AA22+1 -> 45295 | AB23: 45295 | AC23: 1 | AD23: 木 | AE23: =IFERROR(AVERAGEIFS(J20:J50,D20:D50,1,G20:G50,"thu"),0) -> 223706.67 | AF23: =COUNTIFS(D20:D50,1,G20:G50,"thu") -> 3 | AH23: =AE23*AF23 -> 671120 | AI23: =AH23/$M$6 -> 0.13469884
C24: =C23+1 -> 5 | D24: 1 | E24: =TEXT(AA24,"m") -> 1 | F24: =F23+1 -> 45296 | G24: =TEXT(Z24,"ddd") -> Fri | J24: 365950 | L24: =IF(D24=0,0,$K$6) -> 221794.94 | M24: =IF(D24=0,0,J24-L24) -> 144155.06 | N24: =IFERROR(J24/L24,"0%") -> 1.6499474 | P24: =IF(D24=0,0,SUM($L$20:L24)) -> 221794.94 | Q24: =IF(D24=0,0,SUM($J$20:J24)) -> 365950 | R24: =IF(D24=0,0,Q24-P24) -> 144155.06 | S24: =IFERROR(Q24/P24,"0%") -> 1.6499474 | U24: =IF(D24=0,0,SUM($L$20:L24)) -> 221794.94 | V24: =IF(D24=0,0,SUM($J$20:J24)) -> 365950 | W24: =IF(D24=0,0,V24-U24) -> 144155.06 | X24: =IFERROR(V24/U24,"0%") -> 1.6499474 | Z24: =Z23+1 -> 45296 | AA24: =AA23+1 -> 45296 | AB24: 45296 | AC24: 1 | AD24: 金 | AE24: =IFERROR(AVERAGEIFS(J20:J50,D20:D50,1,G20:G50,"fri"),0) -> 292927.5 | AF24: =COUNTIFS(D20:D50,1,G20:G50,"fri") -> 4 | AH24: =AE24*AF24 -> 1171710 | AI24: =AH24/$M$6 -> 0.23517102
C25: =C24+1 -> 6 | D25: 0 | E25: =TEXT(AA25,"m") -> 1 | F25: =F24+1 -> 45297 | G25: =TEXT(Z25,"ddd") -> Sat | J25: 0 | L25: =IF(D25=0,0,$K$6) -> 0 | M25: =IF(D25=0,0,J25-L25) -> 0 | N25: =IFERROR(J25/L25,"0%") -> 0% | P25: =IF(D25=0,0,SUM($L$20:L25)) -> 0 | Q25: =IF(D25=0,0,SUM($J$20:J25)) -> 0 | R25: =IF(D25=0,0,Q25-P25) -> 0 | S25: =IFERROR(Q25/P25,"0%") -> 0% | U25: =IF(D25=0,0,SUM($L$20:L25)) -> 0 | V25: =IF(D25=0,0,SUM($J$20:J25)) -> 0 | W25: =IF(D25=0,0,V25-U25) -> 0 | X25: =IFERROR(V25/U25,"0%") -> 0% | Z25: =Z24+1 -> 45297 | AA25: =AA24+1 -> 45297 | AB25: 45297 | AC25: 1 | AD25: 土 | AE25: =IFERROR(AVERAGEIFS(J20:J50,D20:D50,1,G20:G50,"sat"),0) -> 101266.67 | AF25: =COUNTIFS(D20:D50,1,G20:G50,"sat") -> 3 | AH25: =AE25*AF25 -> 303800 | AI25: =AH25/$M$6 -> 0.060974949
C26: =C25+1 -> 7 | D26: 0 | E26: =TEXT(AA26,"m") -> 1 | F26: =F25+1 -> 45298 | G26: =TEXT(Z26,"ddd") -> Sun | H26: 日曜日 | J26: 0 | L26: =IF(D26=0,0,$K$6) -> 0 | M26: =IF(D26=0,0,J26-L26) -> 0 | N26: =IFERROR(J26/L26,"0%") -> 0% | P26: =IF(D26=0,0,SUM($L$20:L26)) -> 0 | Q26: =IF(D26=0,0,SUM($J$20:J26)) -> 0 | R26: =IF(D26=0,0,Q26-P26) -> 0 | S26: =IFERROR(Q26/P26,"0%") -> 0% | U26: =IF(D26=0,0,SUM($L$20:L26)) -> 0 | V26: =IF(D26=0,0,SUM($J$20:J26)) -> 0 | W26: =IF(D26=0,0,V26-U26) -> 0 | X26: =IFERROR(V26/U26,"0%") -> 0% | Z26: =Z25+1 -> 45298 | AA26: =AA25+1 -> 45298 | AB26: 45298 | AC26: 1 | AD26: 日 | AE26: =IFERROR(AVERAGEIFS(J20:J50,D20:D50,1,G20:G50,"sun"),0) -> 0 | AF26: =IFERROR(COUNTIFS(D20:D50,1,G20:G50,"sun"),0) -> 0 | AH26: =AE26*AF26 -> 0 | AI26: =AH26/$M$6 -> 0
C27: =C26+1 -> 8 | D27: 1 | E27: =TEXT(AA27,"m") -> 1 | F27: =F26+1 -> 45299 | G27: =TEXT(Z27,"ddd") -> Mon | J27: 250000 | L27: =IF(D27=0,0,$K$6) -> 221794.94 | M27: =IF(D27=0,0,J27-L27) -> 28205.056 | N27: =IFERROR(J27/L27,"0%") -> 1.1271673 | P27: =IF(D27=0,0,SUM($L$20:L27)) -> 443589.89 | Q27: =IF(D27=0,0,SUM($J$20:J27)) -> 615950 | R27: =IF(D27=0,0,Q27-P27) -> 172360.11 | S27: =IFERROR(Q27/P27,"0%") -> 1.3885573 | U27: =IF(D27=0,0,SUM($L$20:L27)) -> 443589.89 | V27: =IF(D27=0,0,SUM($J$20:J27)) -> 615950 | W27: =IF(D27=0,0,V27-U27) -> 172360.11 | X27: =IFERROR(V27/U27,"0%") -> 1.3885573 | Z27: =Z26+1 -> 45299 | AA27: =AA26+1 -> 45299 | AB27: 45299 | AC27: 2 | AD27: 月 | AE27: =AVERAGEIFS(J51:J79,D51:D79,1,G51:G79,"mon") -> 231250 | AF27: =COUNTIFS(D51:D79,1,G51:G79,"Mon") -> 3 | AH27: =AE27*AF27 -> 693750 | AI27: =AH27/$M$7 -> 0.13869924 | AJ27: =SUM(AI27:AI33) -> 1 | AK27: 51〜79
C28: =C27+1 -> 9 | D28: 1 | E28: =TEXT(AA28,"m") -> 1 | F28: =F27+1 -> 45300 | G28: =TEXT(Z28,"ddd") -> Tue | J28: 143850 | L28: =IF(D28=0,0,$K$6) -> 221794.94 | M28: =IF(D28=0,0,J28-L28) -> -77944.944 | N28: =IFERROR(J28/L28,"0%") -> 0.64857204 | P28: =IF(D28=0,0,SUM($L$20:L28)) -> 665384.83 | Q28: =IF(D28=0,0,SUM($J$20:J28)) -> 759800 | R28: =IF(D28=0,0,Q28-P28) -> 94415.167 | S28: =IFERROR(Q28/P28,"0%") -> 1.1418956 | U28: =IF(D28=0,0,SUM($L$20:L28)) -> 665384.83 | V28: =IF(D28=0,0,SUM($J$20:J28)) -> 759800 | W28: =IF(D28=0,0,V28-U28) -> 94415.167 | X28: =IFERROR(V28/U28,"0%") -> 1.1418956 | Z28: =Z27+1 -> 45300 | AA28: =AA27+1 -> 45300 | AB28: 45300 | AC28: 2 | AD28: 火 | AE28: =AVERAGEIFS(J51:J79,D51:D79,1,G51:G79,"tue") -> 214245 | AF28: =COUNTIFS(D51:D79,1,G51:G79,"tue") -> 4 | AH28: =AE28*AF28 -> 856980 | AI28: =AH28/$M$7 -> 0.17133329
C29: =C28+1 -> 10 | D29: 1 | E29: =TEXT(AA29,"m") -> 1 | F29: =F28+1 -> 45301 | G29: =TEXT(Z29,"ddd") -> Wed | J29: 331400 | L29: =IF(D29=0,0,$K$6) -> 221794.94 | M29: =IF(D29=0,0,J29-L29) -> 109605.06 | N29: =IFERROR(J29/L29,"0%") -> 1.4941729 | P29: =IF(D29=0,0,SUM($L$20:L29)) -> 887179.78 | Q29: =IF(D29=0,0,SUM($J$20:J29)) -> 1091200 | R29: =IF(D29=0,0,Q29-P29) -> 204020.22 | S29: =IFERROR(Q29/P29,"0%") -> 1.2299649 | U29: =IF(D29=0,0,SUM($L$20:L29)) -> 887179.78 | V29: =IF(D29=0,0,SUM($J$20:J29)) -> 1091200 | W29: =IF(D29=0,0,V29-U29) -> 204020.22 | X29: =IFERROR(V29/U29,"0%") -> 1.2299649 | Z29: =Z28+1 -> 45301 | AA29: =AA28+1 -> 45301 | AB29: 45301 | AC29: 2 | AD29: 水 | AE29: =AVERAGEIFS(J51:J79,D51:D79,1,G51:G79,"wed") -> 221717.5 | AF29: =COUNTIFS(D51:D79,1,G51:G79,"wed") -> 4 | AH29: =AE29*AF29 -> 886870 | AI29: =AH29/$M$7 -> 0.1773091
C30: =C29+1 -> 11 | D30: 1 | E30: =TEXT(AA30,"m") -> 1 | F30: =F29+1 -> 45302 | G30: =TEXT(Z30,"ddd") -> Thu | J30: 263220 | L30: =IF(D30=0,0,$K$6) -> 221794.94 | M30: =IF(D30=0,0,J30-L30) -> 41425.056 | N30: =IFERROR(J30/L30,"0%") -> 1.1867719 | P30: =IF(D30=0,0,SUM($L$20:L30)) -> 1108974.7 | Q30: =IF(D30=0,0,SUM($J$20:J30)) -> 1354420 | R30: =IF(D30=0,0,Q30-P30) -> 245445.28 | S30: =IFERROR(Q30/P30,"0%") -> 1.2213263 | U30: =IF(D30=0,0,SUM($L$20:L30)) -> 1108974.7 | V30: =IF(D30=0,0,SUM($J$20:J30)) -> 1354420 | W30: =IF(D30=0,0,V30-U30) -> 245445.28 | X30: =IFERROR(V30/U30,"0%") -> 1.2213263 | Z30: =Z29+1 -> 45302 | AA30: =AA29+1 -> 45302 | AB30: 45302 | AC30: 2 | AD30: 木 | AE30: =AVERAGEIFS(J51:J79,D51:D79,1,G51:G79,"thu") -> 233396 | AF30: =COUNTIFS(D51:D79,1,G51:G79,"thu") -> 5 | AH30: =AE30*AF30 -> 1166980 | AI30: =AH30/$M$7 -> 0.23331061
C31: =C30+1 -> 12 | D31: 1 | E31: =TEXT(AA31,"m") -> 1 | F31: =F30+1 -> 45303 | G31: =TEXT(Z31,"ddd") -> Fri | J31: 230860 | L31: =IF(D31=0,0,$K$6) -> 221794.94 | M31: =IF(D31=0,0,J31-L31) -> 9065.0557 | N31: =IFERROR(J31/L31,"0%") -> 1.0408713 | P31: =IF(D31=0,0,SUM($L$20:L31)) -> 1330769.7 | Q31: =IF(D31=0,0,SUM($J$20:J31)) -> 1585280 | R31: =IF(D31=0,0,Q31-P31) -> 254510.33 | S31: =IFERROR(Q31/P31,"0%") -> 1.1912505 | U31: =IF(D31=0,0,SUM($L$20:L31)) -> 1330769.7 | V31: =IF(D31=0,0,SUM($J$20:J31)) -> 1585280 | W31: =IF(D31=0,0,V31-U31) -> 254510.33 | X31: =IFERROR(V31/U31,"0%") -> 1.1912505 | Z31: =Z30+1 -> 45303 | AA31: =AA30+1 -> 45303 | AB31: 45303 | AC31: 2 | AD31: 金 | AE31: =AVERAGEIFS(J51:J79,D51:D79,1,G51:G79,"fri") -> 283893.33 | AF31: =COUNTIFS(D51:D79,1,G51:G79,"fri") -> 3 | AH31: =AE31*AF31 -> 851680 | AI31: =AH31/$M$7 -> 0.17027368
C32: =C31+1 -> 13 | D32: 1 | E32: =TEXT(AA32,"m") -> 1 | F32: =F31+1 -> 45304 | G32: =TEXT(Z32,"ddd") -> Sat | J32: 50050 | L32: =IF(D32=0,0,$K$6) -> 221794.94 | M32: =IF(D32=0,0,J32-L32) -> -171744.94 | N32: =IFERROR(J32/L32,"0%") -> 0.22565889 | P32: =IF(D32=0,0,SUM($L$20:L32)) -> 1552564.6 | Q32: =IF(D32=0,0,SUM($J$20:J32)) -> 1635330 | R32: =IF(D32=0,0,Q32-P32) -> 82765.39 | S32: =IFERROR(Q32/P32,"0%") -> 1.0533088 | U32: =IF(D32=0,0,SUM($L$20:L32)) -> 1552564.6 | V32: =IF(D32=0,0,SUM($J$20:J32)) -> 1635330 | W32: =IF(D32=0,0,V32-U32) -> 82765.39 | X32: =IFERROR(V32/U32,"0%") -> 1.0533088 | Z32: =Z31+1 -> 45304 | AA32: =AA31+1 -> 45304 | AB32: 45304 | AC32: 2 | AD32: 土 | AE32: =AVERAGEIFS(J51:J79,D51:D79,1,G51:G79,"sat") -> 136392.5 | AF32: =COUNTIFS(D51:D79,1,G51:G79,"sat") -> 4 | AH32: =AE32*AF32 -> 545570 | AI32: =AH32/$M$7 -> 0.10907408
C33: =C32+1 -> 14 | D33: 0 | E33: =TEXT(AA33,"m") -> 1 | F33: =F32+1 -> 45305 | G33: =TEXT(Z33,"ddd") -> Sun | J33: 0 | L33: =IF(D33=0,0,$K$6) -> 0 | M33: =IF(D33=0,0,J33-L33) -> 0 | N33: =IFERROR(J33/L33,"0%") -> 0% | P33: =IF(D33=0,0,SUM($L$20:L33)) -> 0 | Q33: =IF(D33=0,0,SUM($J$20:J33)) -> 0 | R33: =IF(D33=0,0,Q33-P33) -> 0 | S33: =IFERROR(Q33/P33,"0%") -> 0% | U33: =IF(D33=0,0,SUM($L$20:L33)) -> 0 | V33: =IF(D33=0,0,SUM($J$20:J33)) -> 0 | W33: =IF(D33=0,0,V33-U33) -> 0 | X33: =IFERROR(V33/U33,"0%") -> 0% | Z33: =Z32+1 -> 45305 | AA33: =AA32+1 -> 45305 | AB33: 45305 | AC33: 2 | AD33: 日 | AE33: =IFERROR(AVERAGEIFS(J51:J79,D51:D79,1,G51:G79,"sun"),0) -> 0 | AF33: =IFERROR(COUNTIFS(D51:D79,1,G51:G79,"sun"),0) -> 0 | AH33: =AE33*AF33 -> 0 | AI33: =AH33/$M$7 -> 0
C34: =C33+1 -> 15 | D34: 1 | E34: =TEXT(AA34,"m") -> 1 | F34: =F33+1 -> 45306 | G34: =TEXT(Z34,"ddd") -> Mon | J34: 189100 | L34: =IF(D34=0,0,$K$6) -> 221794.94 | M34: =IF(D34=0,0,J34-L34) -> -32694.944 | N34: =IFERROR(J34/L34,"0%") -> 0.85258932 | P34: =IF(D34=0,0,SUM($L$20:L34)) -> 1774359.6 | Q34: =IF(D34=0,0,SUM($J$20:J34)) -> 1824430 | R34: =IF(D34=0,0,Q34-P34) -> 50070.446 | S34: =IFERROR(Q34/P34,"0%") -> 1.0282189 | U34: =IF(D34=0,0,SUM($L$20:L34)) -> 1774359.6 | V34: =IF(D34=0,0,SUM($J$20:J34)) -> 1824430 | W34: =IF(D34=0,0,V34-U34) -> 50070.446 | X34: =IFERROR(V34/U34,"0%") -> 1.0282189 | Z34: =Z33+1 -> 45306 | AA34: =AA33+1 -> 45306 | AB34: 45306 | AC34: 3 | AD34: 月 | AE34: =AVERAGEIFS(J80:J110,D80:D110,1,G80:G110,"mon") -> 228962.5 | AF34: =COUNTIFS( D80:D110,1,G80:G110,"Mon") -> 4 | AH34: =AE34*AF34 -> 915850 | AI34: =AH34/$M$8 -> 0.1417591 | AJ34: =SUM(AI34:AI40) -> 1 | AK34: 80〜110
C35: =C34+1 -> 16 | D35: 1 | E35: =TEXT(AA35,"m") -> 1 | F35: =F34+1 -> 45307 | G35: =TEXT(Z35,"ddd") -> Tue | J35: 212700 | L35: =IF(D35=0,0,$K$6) -> 221794.94 | M35: =IF(D35=0,0,J35-L35) -> -9094.9443 | N35: =IFERROR(J35/L35,"0%") -> 0.95899391 | P35: =IF(D35=0,0,SUM($L$20:L35)) -> 1996154.5 | Q35: =IF(D35=0,0,SUM($J$20:J35)) -> 2037130 | R35: =IF(D35=0,0,Q35-P35) -> 40975.501 | S35: =IFERROR(Q35/P35,"0%") -> 1.0205272 | U35: =IF(D35=0,0,SUM($L$20:L35)) -> 1996154.5 | V35: =IF(D35=0,0,SUM($J$20:J35)) -> 2037130 | W35: =IF(D35=0,0,V35-U35) -> 40975.501 | X35: =IFERROR(V35/U35,"0%") -> 1.0205272 | Z35: =Z34+1 -> 45307 | AA35: =AA34+1 -> 45307 | AB35: 45307 | AC35: 3 | AD35: 火 | AE35: =AVERAGEIFS(J80:J110,D80:D110,1,G80:G110,"tue") -> 263967.5 | AF35: =COUNTIFS( D80:D110,1,G80:G110,"tue") -> 4 | AH35: =AE35*AF35 -> 1055870 | AI35: =AH35/$M$8 -> 0.16343199
C36: =C35+1 -> 17 | D36: 1 | E36: =TEXT(AA36,"m") -> 1 | F36: =F35+1 -> 45308 | G36: =TEXT(Z36,"ddd") -> Wed | J36: 172600 | L36: =IF(D36=0,0,$K$6) -> 221794.94 | M36: =IF(D36=0,0,J36-L36) -> -49194.944 | N36: =IFERROR(J36/L36,"0%") -> 0.77819628 | P36: =IF(D36=0,0,SUM($L$20:L36)) -> 2217949.4 | Q36: =IF(D36=0,0,SUM($J$20:J36)) -> 2209730 | R36: =IF(D36=0,0,Q36-P36) -> -8219.4429 | S36: =IFERROR(Q36/P36,"0%") -> 0.99629413 | U36: =IF(D36=0,0,SUM($L$20:L36)) -> 2217949.4 | V36: =IF(D36=0,0,SUM($J$20:J36)) -> 2209730 | W36: =IF(D36=0,0,V36-U36) -> -8219.4429 | X36: =IFERROR(V36/U36,"0%") -> 0.99629413 | Z36: =Z35+1 -> 45308 | AA36: =AA35+1 -> 45308 | AB36: 45308 | AC36: 3 | AD36: 水 | AE36: =AVERAGEIFS(J80:J110,D80:D110,1,G80:G110,"wed") -> 293950 | AF36: =COUNTIFS( D80:D110,1,G80:G110,"wed") -> 3 | AH36: =AE36*AF36 -> 881850 | AI36: =AH36/$M$8 -> 0.13649644
C37: =C36+1 -> 18 | D37: 1 | E37: =TEXT(AA37,"m") -> 1 | F37: =F36+1 -> 45309 | G37: =TEXT(Z37,"ddd") -> Thu | J37: 155450 | L37: =IF(D37=0,0,$K$6) -> 221794.94 | M37: =IF(D37=0,0,J37-L37) -> -66344.944 | N37: =IFERROR(J37/L37,"0%") -> 0.7008726 | P37: =IF(D37=0,0,SUM($L$20:L37)) -> 2439744.4 | Q37: =IF(D37=0,0,SUM($J$20:J37)) -> 2365180 | R37: =IF(D37=0,0,Q37-P37) -> -74564.387 | S37: =IFERROR(Q37/P37,"0%") -> 0.96943762 | U37: =IF(D37=0,0,SUM($L$20:L37)) -> 2439744.4 | V37: =IF(D37=0,0,SUM($J$20:J37)) -> 2365180 | W37: =IF(D37=0,0,V37-U37) -> -74564.387 | X37: =IFERROR(V37/U37,"0%") -> 0.96943762 | Z37: =Z36+1 -> 45309 | AA37: =AA36+1 -> 45309 | AB37: 45309 | AC37: 3 | AD37: 木 | AE37: =AVERAGEIFS(J80:J110,D80:D110,1,G80:G110,"thu") -> 308607.5 | AF37: =COUNTIFS( D80:D110,1,G80:G110,"thu") -> 4 | AH37: =AE37*AF37 -> 1234430 | AI37: =AH37/$M$8 -> 0.19107025
C38: =C37+1 -> 19 | D38: 1 | E38: =TEXT(AA38,"m") -> 1 | F38: =F37+1 -> 45310 | G38: =TEXT(Z38,"ddd") -> Fri | J38: 286750 | L38: =IF(D38=0,0,$K$6) -> 221794.94 | M38: =IF(D38=0,0,J38-L38) -> 64955.056 | N38: =IFERROR(J38/L38,"0%") -> 1.2928608 | P38: =IF(D38=0,0,SUM($L$20:L38)) -> 2661539.3 | Q38: =IF(D38=0,0,SUM($J$20:J38)) -> 2651930 | R38: =IF(D38=0,0,Q38-P38) -> -9609.3315 | S38: =IFERROR(Q38/P38,"0%") -> 0.99638956 | U38: =IF(D38=0,0,SUM($L$20:L38)) -> 2661539.3 | V38: =IF(D38=0,0,SUM($J$20:J38)) -> 2651930 | W38: =IF(D38=0,0,V38-U38) -> -9609.3315 | X38: =IFERROR(V38/U38,"0%") -> 0.99638956 | Z38: =Z37+1 -> 45310 | AA38: =AA37+1 -> 45310 | AB38: 45310 | AC38: 3 | AD38: 金 | AE38: =AVERAGEIFS(J80:J110,D80:D110,1,G80:G110,"fri") -> 322626 | AF38: =COUNTIFS( D80:D110,1,G80:G110,"fri") -> 5 | AH38: =AE38*AF38 -> 1613130 | AI38: =AH38/$M$8 -> 0.24968703
C39: =C38+1 -> 20 | D39: 1 | E39: =TEXT(AA39,"m") -> 1 | F39: =F38+1 -> 45311 | G39: =TEXT(Z39,"ddd") -> Sat | J39: 139100 | L39: =IF(D39=0,0,$K$6) -> 221794.94 | M39: =IF(D39=0,0,J39-L39) -> -82694.944 | N39: =IFERROR(J39/L39,"0%") -> 0.62715586 | P39: =IF(D39=0,0,SUM($L$20:L39)) -> 2883334.3 | Q39: =IF(D39=0,0,SUM($J$20:J39)) -> 2791030 | R39: =IF(D39=0,0,Q39-P39) -> -92304.276 | S39: =IFERROR(Q39/P39,"0%") -> 0.96798697 | U39: =IF(D39=0,0,SUM($L$20:L39)) -> 2883334.3 | V39: =IF(D39=0,0,SUM($J$20:J39)) -> 2791030 | W39: =IF(D39=0,0,V39-U39) -> -92304.276 | X39: =IFERROR(V39/U39,"0%") -> 0.96798697 | Z39: =Z38+1 -> 45311 | AA39: =AA38+1 -> 45311 | AB39: 45311 | AC39: 3 | AD39: 土 | AE39: =AVERAGEIFS(J80:J110,D80:D110,1,G80:G110,"sat") -> 151895.6 | AF39: =COUNTIFS( D80:D110,1,G80:G110,"sat") -> 5 | AH39: =AE39*AF39 -> 759478 | AI39: =AH39/$M$8 -> 0.11755519
C40: =C39+1 -> 21 | D40: 0 | E40: =TEXT(AA40,"m") -> 1 | F40: =F39+1 -> 45312 | G40: =TEXT(Z40,"ddd") -> Sun | H40: 日曜日 | J40: 0 | L40: =IF(D40=0,0,$K$6) -> 0 | M40: =IF(D40=0,0,J40-L40) -> 0 | N40: =IFERROR(J40/L40,"0%") -> 0% | P40: =IF(D40=0,0,SUM($L$20:L40)) -> 0 | Q40: =IF(D40=0,0,SUM($J$20:J40)) -> 0 | R40: =IF(D40=0,0,Q40-P40) -> 0 | S40: =IFERROR(Q40/P40,"0%") -> 0% | U40: =IF(D40=0,0,SUM($L$20:L40)) -> 0 | V40: =IF(D40=0,0,SUM($J$20:J40)) -> 0 | W40: =IF(D40=0,0,V40-U40) -> 0 | X40: =IFERROR(V40/U40,"0%") -> 0% | Z40: =Z39+1 -> 45312 | AA40: =AA39+1 -> 45312 | AB40: 45312 | AC40: 3 | AD40: 日 | AE40: =IFERROR(AVERAGEIFS(J80:J110,D80:D110,3,G80:G110,"sun"),0) -> 0 | AF40: =IFERROR(COUNTIFS( D80:D110,1,G80:G110,"sun"),0) -> 0 | AH40: =AE40*AF40 -> 0 | AI40: =AH40/$M$8 -> 0
C41: =C40+1 -> 22 | D41: 1 | E41: =TEXT(AA41,"m") -> 1 | F41: =F40+1 -> 45313 | G41: =TEXT(Z41,"ddd") -> Mon | J41: 250550 | L41: =IF(D41=0,0,$K$6) -> 221794.94 | M41: =IF(D41=0,0,J41-L41) -> 28755.056 | N41: =IFERROR(J41/L41,"0%") -> 1.129647 | P41: =IF(D41=0,0,SUM($L$20:L41)) -> 3105129.2 | Q41: =IF(D41=0,0,SUM($J$20:J41)) -> 3041580 | R41: =IF(D41=0,0,Q41-P41) -> -63549.22 | S41: =IFERROR(Q41/P41,"0%") -> 0.97953411 | U41: =IF(D41=0,0,SUM($L$20:L41)) -> 3105129.2 | V41: =IF(D41=0,0,SUM($J$20:J41)) -> 3041580 | W41: =IF(D41=0,0,V41-U41) -> -63549.22 | X41: =IFERROR(V41/U41,"0%") -> 0.97953411 | Z41: =Z40+1 -> 45313 | AA41: =AA40+1 -> 45313 | AB41: 45313 | AC41: 4 | AD41: 月 | AE41: =AVERAGEIFS(J111:J140,D111:D140,1,G111:G140,"mon") -> 228365 | AF41: =COUNTIFS(D111:D140,1,G111:G140,"Mon") -> 4 | AH41: =AE41*AF41 -> 913460 | AI41: =AH41/$M$9 -> 0.13681398 | AJ41: =SUM(AI41:AI47) -> 1 | AK41: 111〜140
C42: =C41+1 -> 23 | D42: 1 | E42: =TEXT(AA42,"m") -> 1 | F42: =F41+1 -> 45314 | G42: =TEXT(Z42,"ddd") -> Tue | J42: 312544 | L42: =IF(D42=0,0,$K$6) -> 221794.94 | M42: =IF(D42=0,0,J42-L42) -> 90749.056 | N42: =IFERROR(J42/L42,"0%") -> 1.4091575 | P42: =IF(D42=0,0,SUM($L$20:L42)) -> 3326924.2 | Q42: =IF(D42=0,0,SUM($J$20:J42)) -> 3354124 | R42: =IF(D42=0,0,Q42-P42) -> 27199.836 | S42: =IFERROR(Q42/P42,"0%") -> 1.0081757 | U42: =IF(D42=0,0,SUM($L$20:L42)) -> 3326924.2 | V42: =IF(D42=0,0,SUM($J$20:J42)) -> 3354124 | W42: =IF(D42=0,0,V42-U42) -> 27199.836 | X42: =IFERROR(V42/U42,"0%") -> 1.0081757 | Z42: =Z41+1 -> 45314 | AA42: =AA41+1 -> 45314 | AB42: 45314 | AC42: 4 | AD42: 火 | AE42: =AVERAGEIFS(J111:J140,D111:D140,1,G111:G140,"tue") -> 269807.4 | AF42: =COUNTIFS(D111:D140,1,G111:G140,"tue") -> 5 | AH42: =AE42*AF42 -> 1349037 | AI42: =AH42/$M$9 -> 0.20205276
C43: =C42+1 -> 24 | D43: 1 | E43: =TEXT(AA43,"m") -> 1 | F43: =F42+1 -> 45315 | G43: =TEXT(Z43,"ddd") -> Wed | J43: 255500 | L43: =IF(D43=0,0,$K$6) -> 221794.94 | M43: =IF(D43=0,0,J43-L43) -> 33705.056 | N43: =IFERROR(J43/L43,"0%") -> 1.1519649 | P43: =IF(D43=0,0,SUM($L$20:L43)) -> 3548719.1 | Q43: =IF(D43=0,0,SUM($J$20:J43)) -> 3609624 | R43: =IF(D43=0,0,Q43-P43) -> 60904.891 | S43: =IFERROR(Q43/P43,"0%") -> 1.0171625 | U43: =IF(D43=0,0,SUM($L$20:L43)) -> 3548719.1 | V43: =IF(D43=0,0,SUM($J$20:J43)) -> 3609624 | W43: =IF(D43=0,0,V43-U43) -> 60904.891 | X43: =IFERROR(V43/U43,"0%") -> 1.0171625 | Z43: =Z42+1 -> 45315 | AA43: =AA42+1 -> 45315 | AB43: 45315 | AC43: 4 | AD43: 水 | AE43: =AVERAGEIFS(J111:J140,D111:D140,1,G111:G140,"wed") -> 292710 | AF43: =COUNTIFS(D111:D140,1,G111:G140,"wed") -> 4 | AH43: =AE43*AF43 -> 1170840 | AI43: =AH43/$M$9 -> 0.17536321
C44: =C43+1 -> 25 | D44: 1 | E44: =TEXT(AA44,"m") -> 1 | F44: =F43+1 -> 45316 | G44: =TEXT(Z44,"ddd") -> Thu | J44: 252450 | L44: =IF(D44=0,0,$K$6) -> 221794.94 | M44: =IF(D44=0,0,J44-L44) -> 30655.056 | N44: =IFERROR(J44/L44,"0%") -> 1.1382135 | P44: =IF(D44=0,0,SUM($L$20:L44)) -> 3770514.1 | Q44: =IF(D44=0,0,SUM($J$20:J44)) -> 3862074 | R44: =IF(D44=0,0,Q44-P44) -> 91559.947 | S44: =IFERROR(Q44/P44,"0%") -> 1.0242831 | U44: =IF(D44=0,0,SUM($L$20:L44)) -> 3770514.1 | V44: =IF(D44=0,0,SUM($J$20:J44)) -> 3862074 | W44: =IF(D44=0,0,V44-U44) -> 91559.947 | X44: =IFERROR(V44/U44,"0%") -> 1.0242831 | Z44: =Z43+1 -> 45316 | AA44: =AA43+1 -> 45316 | AB44: 45316 | AC44: 4 | AD44: 木 | AE44: =AVERAGEIFS(J111:J140,D111:D140,1,G111:G140,"thu") -> 278042.5 | AF44: =COUNTIFS(D111:D140,1,G111:G140,"thu") -> 4 | AH44: =AE44*AF44 -> 1112170 | AI44: =AH44/$M$9 -> 0.16657588
C45: =C44+1 -> 26 | D45: 1 | E45: =TEXT(AA45,"m") -> 1 | F45: =F44+1 -> 45317 | G45: =TEXT(Z45,"ddd") -> Fri | J45: 288150 | L45: =IF(D45=0,0,$K$6) -> 221794.94 | M45: =IF(D45=0,0,J45-L45) -> 66355.056 | N45: =IFERROR(J45/L45,"0%") -> 1.299173 | P45: =IF(D45=0,0,SUM($L$20:L45)) -> 3992309 | Q45: =IF(D45=0,0,SUM($J$20:J45)) -> 4150224 | R45: =IF(D45=0,0,Q45-P45) -> 157915 | S45: =IFERROR(Q45/P45,"0%") -> 1.0395548 | U45: =IF(D45=0,0,SUM($L$20:L45)) -> 3992309 | V45: =IF(D45=0,0,SUM($J$20:J45)) -> 4150224 | W45: =IF(D45=0,0,V45-U45) -> 157915 | X45: =IFERROR(V45/U45,"0%") -> 1.0395548 | Z45: =Z44+1 -> 45317 | AA45: =AA44+1 -> 45317 | AB45: 45317 | AC45: 4 | AD45: 金 | AE45: =AVERAGEIFS(J111:J140,D111:D140,1,G111:G140,"fri") -> 331130 | AF45: =COUNTIFS(D111:D140,1,G111:G140,"fri") -> 4 | AH45: =AE45*AF45 -> 1324520 | AI45: =AH45/$M$9 -> 0.19838072
C46: =C45+1 -> 27 | D46: 1 | E46: =TEXT(AA46,"m") -> 1 | F46: =F45+1 -> 45318 | G46: =TEXT(Z46,"ddd") -> Sat | J46: 114650 | L46: =IF(D46=0,0,$K$6) -> 221794.94 | M46: =IF(D46=0,0,J46-L46) -> -107144.94 | N46: =IFERROR(J46/L46,"0%") -> 0.51691891 | P46: =IF(D46=0,0,SUM($L$20:L46)) -> 4214103.9 | Q46: =IF(D46=0,0,SUM($J$20:J46)) -> 4264874 | R46: =IF(D46=0,0,Q46-P46) -> 50770.058 | S46: =IFERROR(Q46/P46,"0%") -> 1.0120477 | U46: =IF(D46=0,0,SUM($L$20:L46)) -> 4214103.9 | V46: =IF(D46=0,0,SUM($J$20:J46)) -> 4264874 | W46: =IF(D46=0,0,V46-U46) -> 50770.058 | X46: =IFERROR(V46/U46,"0%") -> 1.0120477 | Z46: =Z45+1 -> 45318 | AA46: =AA45+1 -> 45318 | AB46: 45318 | AC46: 4 | AD46: 土 | AE46: =AVERAGEIFS(J111:J140,D111:D140,1,G111:G140,"sat") -> 201657.5 | AF46: =COUNTIFS(D111:D140,1,G111:G140,"sat") -> 4 | AH46: =AE46*AF46 -> 806630 | AI46: =AH46/$M$9 -> 0.12081345
C47: =C46+1 -> 28 | D47: 0 | E47: =TEXT(AA47,"m") -> 1 | F47: =F46+1 -> 45319 | G47: =TEXT(Z47,"ddd") -> Sun | H47: 日曜日 | J47: 0 | L47: =IF(D47=0,0,$K$6) -> 0 | M47: =IF(D47=0,0,J47-L47) -> 0 | N47: =IFERROR(J47/L47,"0%") -> 0% | P47: =IF(D47=0,0,SUM($L$20:L47)) -> 0 | Q47: =IF(D47=0,0,SUM($J$20:J47)) -> 0 | R47: =IF(D47=0,0,Q47-P47) -> 0 | S47: =IFERROR(Q47/P47,"0%") -> 0% | U47: =IF(D47=0,0,SUM($L$20:L47)) -> 0 | V47: =IF(D47=0,0,SUM($J$20:J47)) -> 0 | W47: =IF(D47=0,0,V47-U47) -> 0 | X47: =IFERROR(V47/U47,"0%") -> 0% | Z47: =Z46+1 -> 45319 | AA47: =AA46+1 -> 45319 | AB47: 45319 | AC47: 4 | AD47: 日 | AE47: =IFERROR(AVERAGEIFS(J111:J140,D111:D140,1,G111:G140,"sun"),0) -> 0 | AF47: =IFERROR(COUNTIFS(D111:D140,1,G111:G140,"sun"),0) -> 0 | AH47: =AE47*AF47 -> 0 | AI47: =AH47/$M$9 -> 0
C48: =C47+1 -> 29 | D48: 1 | E48: =TEXT(AA48,"m") -> 1 | F48: =F47+1 -> 45320 | G48: =TEXT(Z48,"ddd") -> Mon | J48: 322450 | L48: =IF(D48=0,0,$K$6) -> 221794.94 | M48: =IF(D48=0,0,J48-L48) -> 100655.06 | N48: =IFERROR(J48/L48,"0%") -> 1.4538203 | P48: =IF(D48=0,0,SUM($L$20:L48)) -> 4435898.9 | Q48: =IF(D48=0,0,SUM($J$20:J48)) -> 4587324 | R48: =IF(D48=0,0,Q48-P48) -> 151425.11 | S48: =IFERROR(Q48/P48,"0%") -> 1.0341363 | U48: =IF(D48=0,0,SUM($L$20:L48)) -> 4435898.9 | V48: =IF(D48=0,0,SUM($J$20:J48)) -> 4587324 | W48: =IF(D48=0,0,V48-U48) -> 151425.11 | X48: =IFERROR(V48/U48,"0%") -> 1.0341363 | Z48: =Z47+1 -> 45320 | AA48: =AA47+1 -> 45320 | AB48: 45320 | AC48: 5 | AD48: 月 | AE48: =AVERAGEIFS(J141:J171,D141:D171,1,G141:G171,"mon") -> 238610 | AF48: =COUNTIFS(D141:D171,1,G141:G171,"Mon") -> 3 | AH48: =AE48*AF48 -> 715830 | AI48: =AH48/$M$10 -> 0.11611173 | AJ48: =SUM(AI48:AI54) -> 1 | AK48: 141〜171
C49: =C48+1 -> 30 | D49: 1 | E49: =TEXT(AA49,"m") -> 1 | F49: =F48+1 -> 45321 | G49: =TEXT(Z49,"ddd") -> Tue | J49: 188550 | L49: =IF(D49=0,0,$K$6) -> 221794.94 | M49: =IF(D49=0,0,J49-L49) -> -33244.944 | N49: =IFERROR(J49/L49,"0%") -> 0.85010955 | P49: =IF(D49=0,0,SUM($L$20:L49)) -> 4657693.8 | Q49: =IF(D49=0,0,SUM($J$20:J49)) -> 4775874 | R49: =IF(D49=0,0,Q49-P49) -> 118180.17 | S49: =IFERROR(Q49/P49,"0%") -> 1.0253731 | U49: =IF(D49=0,0,SUM($L$20:L49)) -> 4657693.8 | V49: =IF(D49=0,0,SUM($J$20:J49)) -> 4775874 | W49: =IF(D49=0,0,V49-U49) -> 118180.17 | X49: =IFERROR(V49/U49,"0%") -> 1.0253731 | Z49: =Z48+1 -> 45321 | AA49: =AA48+1 -> 45321 | AB49: 45321 | AC49: 5 | AD49: 火 | AE49: =AVERAGEIFS(J141:J171,D141:D171,1,G141:G171,"tue") -> 232011.25 | AF49: =COUNTIFS(D141:D171,1,G141:G171,"tue") -> 4 | AH49: =AE49*AF49 -> 928045 | AI49: =AH49/$M$10 -> 0.15053422
C50: =C49+1 -> 31 | D50: 1 | E50: =TEXT(AA50,"m") -> 1 | F50: =F49+1 -> 45322 | G50: =TEXT(Z50,"ddd") -> Wed | J50: 206500 | L50: =IF(D50=0,0,$K$6) -> 221794.94 | M50: =IF(D50=0,0,J50-L50) -> -15294.944 | N50: =IFERROR(J50/L50,"0%") -> 0.93104016 | P50: =IF(D50=0,0,SUM($L$20:L50)) -> 4879488.8 | Q50: =IF(D50=0,0,SUM($J$20:J50)) -> 4982374 | R50: =IF(D50=0,0,Q50-P50) -> 102885.23 | S50: =IFERROR(Q50/P50,"0%") -> 1.0210852 | U50: =IF(D50=0,0,SUM($L$20:L50)) -> 4879488.8 | V50: =IF(D50=0,0,SUM($J$20:J50)) -> 4982374 | W50: =IF(D50=0,0,V50-U50) -> 102885.23 | X50: =IFERROR(V50/U50,"0%") -> 1.0210852 | Z50: =Z49+1 -> 45322 | AA50: =AA49+1 -> 45322 | AB50: 45322 | AC50: 5 | AD50: 水 | AE50: =AVERAGEIFS(J141:J171,D141:D171,1,G141:G171,"wed") -> 320767 | AF50: =COUNTIFS(D141:D171,1,G141:G171,"wed") -> 5 | AH50: =AE50*AF50 -> 1603835 | AI50: =AH50/$M$10 -> 0.26015124
C51: =C50+1 -> 32 | D51: 1 | E51: =TEXT(AA51,"m") -> 2 | F51: =F50+1 -> 45323 | G51: =TEXT(Z51,"ddd") -> Thu | J51: 218090 | L51: =IF(D51=0,0,$K$7) -> 209473 | M51: =IF(D51=0,0,J51-L51) -> 8616.9971 | N51: =IFERROR(J51/L51,"0%") -> 1.0411366 | P51: =IF(D51=0,0,$L$51) -> 209473 | Q51: =IF(D51=0,0,$J$51) -> 218090 | R51: =IF(D51=0,0,Q51-P51) -> 8616.9971 | S51: =IFERROR(Q51/P51,"0%") -> 1.0411366 | U51: =IF(D51=0,0,SUM($L$20:L51)) -> 5088961.8 | V51: =IF(D51=0,0,SUM($J$20:J51)) -> 5200464 | W51: =IF(D51=0,0,V51-U51) -> 111502.22 | X51: =IFERROR(V51/U51,"0%") -> 1.0219106 | Z51: =Z50+1 -> 45323 | AA51: =AA50+1 -> 45323 | AB51: 45323 | AC51: 5 | AD51: 木 | AE51: =AVERAGEIFS(J141:J171,D141:D171,1,G141:G171,"thu") -> 220418 | AF51: =COUNTIFS(D141:D171,1,G141:G171,"thu") -> 5 | AH51: =AE51*AF51 -> 1102090 | AI51: =AH51/$M$10 -> 0.17876532
C52: =C51+1 -> 33 | D52: 1 | E52: =TEXT(AA52,"m") -> 2 | F52: =F51+1 -> 45324 | G52: =TEXT(Z52,"ddd") -> Fri | J52: 236480 | L52: =IF(D52=0,0,$K$7) -> 209473 | M52: =IF(D52=0,0,J52-L52) -> 27006.997 | N52: =IFERROR(J52/L52,"0%") -> 1.1289283 | P52: =IF(D52=0,0,SUM($L$51:L52)) -> 418946.01 | Q52: =IF(D52=0,0,SUM($J$51:J52)) -> 454570 | R52: =IF(D52=0,0,Q52-P52) -> 35623.994 | S52: =IFERROR(Q52/P52,"0%") -> 1.0850324 | U52: =IF(D52=0,0,SUM($L$20:L52)) -> 5298434.8 | V52: =IF(D52=0,0,SUM($J$20:J52)) -> 5436944 | W52: =IF(D52=0,0,V52-U52) -> 138509.22 | X52: =IFERROR(V52/U52,"0%") -> 1.0261415 | Z52: =Z51+1 -> 45324 | AA52: =AA51+1 -> 45324 | AB52: 45324 | AC52: 5 | AD52: 金 | AE52: =AVERAGEIFS(J141:J171,D141:D171,1,G141:G171,"fri") -> 350012.5 | AF52: =COUNTIFS(D141:D171,1,G141:G171,"fri") -> 4 | AH52: =AE52*AF52 -> 1400050 | AI52: =AH52/$M$10 -> 0.22709614
C53: =C52+1 -> 34 | D53: 1 | E53: =TEXT(AA53,"m") -> 2 | F53: =F52+1 -> 45325 | G53: =TEXT(Z53,"ddd") -> Sat | J53: 113750 | L53: =IF(D53=0,0,$K$7) -> 209473 | M53: =IF(D53=0,0,J53-L53) -> -95723.003 | N53: =IFERROR(J53/L53,"0%") -> 0.5430294 | P53: =IF(D53=0,0,SUM($L$51:L53)) -> 628419.01 | Q53: =IF(D53=0,0,SUM($J$51:J53)) -> 568320 | R53: =IF(D53=0,0,Q53-P53) -> -60099.009 | S53: =IFERROR(Q53/P53,"0%") -> 0.90436475 | U53: =IF(D53=0,0,SUM($L$20:L53)) -> 5507907.8 | V53: =IF(D53=0,0,SUM($J$20:J53)) -> 5550694 | W53: =IF(D53=0,0,V53-U53) -> 42786.217 | X53: =IFERROR(V53/U53,"0%") -> 1.0077681 | Z53: =Z52+1 -> 45325 | AA53: =AA52+1 -> 45325 | AB53: 45325 | AC53: 5 | AD53: 土 | AE53: =AVERAGEIFS(J141:J171,D141:D171,1,G141:G171,"sat") -> 138386.67 | AF53: =COUNTIFS(D141:D171,1,G141:G171,"sat") -> 3 | AH53: =AE53*AF53 -> 415160 | AI53: =AH53/$M$10 -> 0.067341334
C54: =C53+1 -> 35 | D54: 0 | E54: =TEXT(AA54,"m") -> 2 | F54: =F53+1 -> 45326 | G54: =TEXT(Z54,"ddd") -> Sun | H54: 日曜日 | J54: 0 | L54: =IF(D54=0,0,$K$7) -> 0 | M54: =IF(D54=0,0,J54-L54) -> 0 | N54: =IFERROR(J54/L54,"0%") -> 0% | P54: =IF(D54=0,0,SUM($L$51:L54)) -> 0 | Q54: =IF(D54=0,0,SUM($J$51:J54)) -> 0 | R54: =IF(D54=0,0,Q54-P54) -> 0 | S54: =IFERROR(Q54/P54,"0%") -> 0% | U54: =IF(D54=0,0,SUM($L$20:L54)) -> 0 | V54: =IF(D54=0,0,SUM($J$20:J54)) -> 0 | W54: =IF(D54=0,0,V54-U54) -> 0 | X54: =IFERROR(V54/U54,"0%") -> 0% | Z54: =Z53+1 -> 45326 | AA54: =AA53+1 -> 45326 | AB54: 45326 | AC54: 5 | AD54: 日 | AE54: =IFERROR(AVERAGEIFS(J141:J171,D141:D171,1,G141:G171,"sun"),0) -> 0 | AF54: =IFERROR(COUNTIFS(D141:D171,1,G141:G171,"sun"),0) -> 0 | AH54: =AE54*AF54 -> 0 | AI54: =AH54/$M$10 -> 0
C55: =C54+1 -> 36 | D55: 1 | E55: =TEXT(AA55,"m") -> 2 | F55: =F54+1 -> 45327 | G55: =TEXT(Z55,"ddd") -> Mon | J55: 155200 | L55: =IF(D55=0,0,$K$7) -> 209473 | M55: =IF(D55=0,0,J55-L55) -> -54273.003 | N55: =IFERROR(J55/L55,"0%") -> 0.74090693 | P55: =IF(D55=0,0,SUM($L$51:L55)) -> 837892.01 | Q55: =IF(D55=0,0,SUM($J$51:J55)) -> 723520 | R55: =IF(D55=0,0,Q55-P55) -> -114372.01 | S55: =IFERROR(Q55/P55,"0%") -> 0.8635003 | U55: =IF(D55=0,0,SUM($L$20:L55)) -> 5717380.8 | V55: =IF(D55=0,0,SUM($J$20:J55)) -> 5705894 | W55: =IF(D55=0,0,V55-U55) -> -11486.786 | X55: =IFERROR(V55/U55,"0%") -> 0.9979909 | Z55: =Z54+1 -> 45327 | AA55: =AA54+1 -> 45327 | AB55: 45327 | AC55: 6 | AD55: 月 | AE55: =AVERAGEIFS(J172:J201,D172:D201,1,G172:G201,"mon") -> 192255 | AF55: =COUNTIFS(D172:D201,1,G172:G201,"Mon") -> 4 | AH55: =AE55*AF55 -> 769020 | AI55: =AH55/$M$11 -> 0.13016698 | AJ55: =SUM(AI55:AI61) -> 1 | AK55: 172〜201
C56: =C55+1 -> 37 | D56: 1 | E56: =TEXT(AA56,"m") -> 2 | F56: =F55+1 -> 45328 | G56: =TEXT(Z56,"ddd") -> Tue | J56: 191910 | L56: =IF(D56=0,0,$K$7) -> 209473 | M56: =IF(D56=0,0,J56-L56) -> -17563.003 | N56: =IFERROR(J56/L56,"0%") -> 0.91615625 | P56: =IF(D56=0,0,SUM($L$51:L56)) -> 1047365 | Q56: =IF(D56=0,0,SUM($J$51:J56)) -> 915430 | R56: =IF(D56=0,0,Q56-P56) -> -131935.01 | S56: =IFERROR(Q56/P56,"0%") -> 0.87403149 | U56: =IF(D56=0,0,SUM($L$20:L56)) -> 5926853.8 | V56: =IF(D56=0,0,SUM($J$20:J56)) -> 5897804 | W56: =IF(D56=0,0,V56-U56) -> -29049.789 | X56: =IFERROR(V56/U56,"0%") -> 0.99509862 | Z56: =Z55+1 -> 45328 | AA56: =AA55+1 -> 45328 | AB56: 45328 | AC56: 6 | AD56: 火 | AE56: =AVERAGEIFS(J172:J201,D172:D201,1,G172:G201,"tue") -> 204712.5 | AF56: =COUNTIFS(D172:D201,1,G172:G201,"tue") -> 4 | AH56: =AE56*AF56 -> 818850 | AI56: =AH56/$M$11 -> 0.13860138
C57: =C56+1 -> 38 | D57: 1 | E57: =TEXT(AA57,"m") -> 2 | F57: =F56+1 -> 45329 | G57: =TEXT(Z57,"ddd") -> Wed | J57: 331350 | L57: =IF(D57=0,0,$K$7) -> 209473 | M57: =IF(D57=0,0,J57-L57) -> 121877 | N57: =IFERROR(J57/L57,"0%") -> 1.5818268 | P57: =IF(D57=0,0,SUM($L$51:L57)) -> 1256838 | Q57: =IF(D57=0,0,SUM($J$51:J57)) -> 1246780 | R57: =IF(D57=0,0,Q57-P57) -> -10058.018 | S57: =IFERROR(Q57/P57,"0%") -> 0.99199736 | U57: =IF(D57=0,0,SUM($L$20:L57)) -> 6136326.8 | V57: =IF(D57=0,0,SUM($J$20:J57)) -> 6229154 | W57: =IF(D57=0,0,V57-U57) -> 92827.208 | X57: =IFERROR(V57/U57,"0%") -> 1.0151275 | Z57: =Z56+1 -> 45329 | AA57: =AA56+1 -> 45329 | AB57: 45329 | AC57: 6 | AD57: 水 | AE57: =AVERAGEIFS(J172:J201,D172:D201,1,G172:G201,"wed") -> 308407.5 | AF57: =COUNTIFS(D172:D201,1,G172:G201,"wed") -> 4 | AH57: =AE57*AF57 -> 1233630 | AI57: =AH57/$M$11 -> 0.20880847
C58: =C57+1 -> 39 | D58: 1 | E58: =TEXT(AA58,"m") -> 2 | F58: =F57+1 -> 45330 | G58: =TEXT(Z58,"ddd") -> Thu | J58: 178550 | L58: =IF(D58=0,0,$K$7) -> 209473 | M58: =IF(D58=0,0,J58-L58) -> -30923.003 | N58: =IFERROR(J58/L58,"0%") -> 0.85237714 | P58: =IF(D58=0,0,SUM($L$51:L58)) -> 1466311 | Q58: =IF(D58=0,0,SUM($J$51:J58)) -> 1425330 | R58: =IF(D58=0,0,Q58-P58) -> -40981.021 | S58: =IFERROR(Q58/P58,"0%") -> 0.97205162 | U58: =IF(D58=0,0,SUM($L$20:L58)) -> 6345799.8 | V58: =IF(D58=0,0,SUM($J$20:J58)) -> 6407704 | W58: =IF(D58=0,0,V58-U58) -> 61904.205 | X58: =IFERROR(V58/U58,"0%") -> 1.0097551 | Z58: =Z57+1 -> 45330 | AA58: =AA57+1 -> 45330 | AB58: 45330 | AC58: 6 | AD58: 木 | AE58: =AVERAGEIFS(J172:J201,D172:D201,1,G172:G201,"thu") -> 279470 | AF58: =COUNTIFS(D172:D201,1,G172:G201,"thu") -> 4 | AH58: =AE58*AF58 -> 1117880 | AI58: =AH58/$M$11 -> 0.18921623
