Workbook

Sheet ★リトローボ戦略表
A2: リトローボ | B2: 45962 | C2: =MONTH(B2) -> 11 | D2: =TEXT(B2, "ddd") -> Sat
B3: =B16 -> 45970 | D3: =TEXT(B3, "aaa") -> 日
B4: 目標売上 | C4: {=_xludf.XLOOKUP(D3, B7:B13, C7:C13, "該当なし")} -> #NAME?
B6: 9月 曜日毎の目標売上 | D6: 傾向 | G6: 対策考察
B7: mon | C7: =SUMIFS(目標_2025R7!$AE$22:$AE$104, 目標_2025R7!$AA$22:$AA$104, MONTH($B$2), 目標_2025R7!$AB$22:$AB$104, B7) -> 0
B8: tue | C8: =SUMIFS(目標_2025R7!$AE$22:$AE$104, 目標_2025R7!$AA$22:$AA$104, MONTH($B$2), 目標_2025R7!$AB$22:$AB$104, B8) -> 0
B9: wed | C9: =SUMIFS(目標_2025R7!$AE$22:$AE$104, 目標_2025R7!$AA$22:$AA$104, MONTH($B$2), 目標_2025R7!$AB$22:$AB$104, B9) -> 0
B10: thu | C10: =SUMIFS(目標_2025R7!$AE$22:$AE$104, 目標_2025R7!$AA$22:$AA$104, MONTH($B$2), 目標_2025R7!$AB$22:$AB$104, B10) -> 0
B11: fri | C11: =SUMIFS(目標_2025R7!$AE$22:$AE$104, 目標_2025R7!$AA$22:$AA$104, MONTH($B$2), 目標_2025R7!$AB$22:$AB$104, B11) -> 0
B12: sat | C12: =SUMIFS(目標_2025R7!$AE$22:$AE$104, 目標_2025R7!$AA$22:$AA$104, MONTH($B$2), 目標_2025R7!$AB$22:$AB$104, B12) -> 0
B13: sun | C13: =SUMIFS(目標_2025R7!$AE$22:$AE$104, 目標_2025R7!$AA$22:$AA$104, MONTH($B$2), 目標_2025R7!$AB$22:$AB$104, B13) -> 0
A16: リトローボ | B16: 45970 | C16: =TEXT(B16, "ddd") -> Sun
A17: 日次 | B17: 売上 | C17: =_xlfn.XLOOKUP(B16, 目標_2025R7!F21:F385,目標_2025R7!J21:J385,"該当なし") -> 33600 | E17: 月次目標売上 | F17: {=INDEX(目標_2025R7!I7:I18, MATCH(MONTH(B2), 目標_2025R7!R7:R18, 0))} -> 2268041.2 | N17: 月 | O17: 傾向分析
B18: 平均目標売上 | C18: {=INDEX(目標_2025R7!K7:K18, MATCH(C2, 目標_2025R7!R7:R18, 0))} -> 103092.78 | E18: 月次累計実績売上 | F18: =C23 -> 606850
B19: 目標売上 | C19: =_xlfn.XLOOKUP(C16, B7:B13, C7:C13, "該当なし") -> 0 | E19: 差額 | F19: =F17-F18 -> 1661191.2 | N19: 1月 | O19: A: 月初・末が強い（中旬落ち）
B20: 差額 | C20: =IFERROR(C17-C19,0) -> 33600 | E20: 当月残営業日 | F20: {=(SUMPRODUCT((目標_2025R7!F21:F385>=B16)*(目標_2025R7!E21:E385=C2)*(目標_2025R7!D21:D385=1)))-1} -> 15 | N20: 2月 | O20: B: 月末にかけて上がる
B21: 達成率 | C21: =IFERROR(C17/C19,0) -> 0 | E21: 1日あたりの目標売上 | F21: =IFERROR(F19/F20,0) -> 110746.08 | N21: 3月 | O21: B: 同様に右肩上がり傾向
N22: 4月 | O22: A: 月初も末も強く安定感あり
A23: 月次 | B23: 累積売上 | C23: =_xlfn.XLOOKUP(B16, 目標_2025R7!F21:F385,目標_2025R7!Q21:Q385,"該当なし") -> 606850 | N23: 5月 | O23: B: 徐々に上がる
B24: 累積目標売上 | C24: =_xlfn.XLOOKUP(B16, 目標_2025R7!F21:F385,目標_2025R7!P21:P385,"該当なし") -> 721649.48 | N24: 分類 | O24: 説明
B25: 差額 | C25: =C23-C24 -> -114799.48 | N25: A: 初・末が強い | O25: 月初・月末の売上が高く、中旬が落ちるパターン
B26: 達成率 | C26: =IFERROR(C23/C24,0) -> 0.84092071 | N26: B: 徐々に上がる | O26: 月初が弱く、末に向かって売上が上がる
N27: C: 平均的 or 中旬強い | O27: 大きな偏りがない or 中旬が強いパターン
A28: 年次 | B28: 累積売上 | C28: =_xlfn.XLOOKUP(B16, 目標_2025R7!F21:F385,目標_2025R7!V21:V385,"該当なし") -> 21736375
B29: 累積目標売上 | C29: =_xlfn.XLOOKUP(B16, 目標_2025R7!F21:F385,目標_2025R7!U21:U385,"該当なし") -> 25680412
B30: 差額 | C30: =C28-C29 -> -3944037.4
B31: 達成率 | C31: =IFERROR(C28/C29,0) -> 0.84641846
B33: 年次目標売上 | C33: =目標_2025R7!G3 -> 30000000
B34: 目標達成までの残額 | C34: =C33-C29 -> 4319587.6
B35: 今年の残営業日数 | C35: {=(SUMPRODUCT((目標_2025R7!F21:F385>=B16)*(目標_2025R7!D21:D385=1)))-1} -> 39
B36: 1日あたりの売上額 | C36: =C34/C35 -> 110758.66
B37: 年間達成率 | C37: =1-(C34/C33) -> 0.85601375
A40: リトローボ | B40: 曜日 | C40: 売上 | D40: 平均目標売上 | E40: 曜日繁閑期目標売上 | F40: 差額 | G40: 達成率 | H40: 累積売上 | I40: 累積目標売上 | J40: 差額 | K40: 達成率
B41: =B2 -> 45962 | D41: =$C$18 -> 103092.78 | E41: =$C$8 -> 0 | F41: =C41-E41 -> 0 | G41: =IFERROR(C41/E41,0) -> 0 | H41: =IF(C41=0,0,C41) -> 0 | I41: =IF(C41=0,0,E41) -> 0 | J41: =H41-I41 -> 0 | K41: =IFERROR(H41/I41,0) -> 0
B42: =B41+1 -> 45963 | D42: =$C$18 -> 103092.78 | E42: =$C$9 -> 0 | F42: =C42-E42 -> 0 | G42: =IFERROR(C42/E42,0) -> 0 | H42: =IF(C42=0,0,(H41+C42)) -> 0 | I42: =IF(C42=0,0,(I41+E42)) -> 0 | J42: =H42-I42 -> 0 | K42: =IFERROR(H42/I42,0) -> 0
B43: =B42+1 -> 45964 | D43: =$C$18 -> 103092.78 | E43: =$C$10 -> 0 | F43: =C43-E43 -> 0 | G43: =IFERROR(C43/E43,0) -> 0 | H43: =IF(C43=0,0,(H42+C43)) -> 0 | I43: =IF(C43=0,0,(I42+E43)) -> 0 | J43: =H43-I43 -> 0 | K43: =IFERROR(H43/I43,0) -> 0
B44: =B43+1 -> 45965 | D44: =$C$18 -> 103092.78 | E44: =$C$11 -> 0 | F44: =C44-E44 -> 0 | G44: =IFERROR(C44/E44,0) -> 0 | H44: =IF(C44=0,0,(H43+C44)) -> 0 | I44: =IF(C44=0,0,(I43+E44)) -> 0 | J44: =H44-I44 -> 0 | K44: =IFERROR(H44/I44,0) -> 0
B45: =B44+1 -> 45966 | D45: =$C$18 -> 103092.78 | E45: =$C$12 -> 0 | F45: =C45-E45 -> 0 | G45: =IFERROR(C45/E45,0) -> 0 | H45: =IF(C45=0,0,(H44+C45)) -> 0 | I45: =IF(C45=0,0,(I44+E45)) -> 0 | J45: =H45-I45 -> 0 | K45: =IFERROR(H45/I45,0) -> 0
B46: =B45+1 -> 45967 | D46: 0 | E46: =$C$13 -> 0 | F46: =C46-E46 -> 0 | G46: =IFERROR(C46/E46,0) -> 0 | H46: =IF(C46=0,0,(H45+C46)) -> 0 | I46: =IF(C46=0,0,(I45+E46)) -> 0 | J46: =H46-I46 -> 0 | K46: =IFERROR(H46/I46,0) -> 0
B47: =B46+1 -> 45968 | D47: =$C$18 -> 103092.78 | E47: =$C$7 -> 0 | F47: =C47-E47 -> 0 | G47: =IFERROR(C47/E47,0) -> 0 | H47: =IF(C47=0,0,(H46+C47)) -> 0 | I47: =IF(C47=0,0,(I46+E47)) -> 0 | J47: =H47-I47 -> 0 | K47: =IFERROR(H47/I47,0) -> 0
B48: =B47+1 -> 45969 | D48: =$C$18 -> 103092.78 | E48: =$C$8 -> 0 | F48: =C48-E48 -> 0 | G48: =IFERROR(C48/E48,0) -> 0 | H48: =IF(C48=0,0,(H47+C48)) -> 0 | I48: =IF(C48=0,0,(I47+E48)) -> 0 | J48: =H48-I48 -> 0 | K48: =IFERROR(H48/I48,0) -> 0
B49: =B48+1 -> 45970 | D49: =$C$18 -> 103092.78 | E49: =$C$9 -> 0 | F49: =C49-E49 -> 0 | G49: =IFERROR(C49/E49,0) -> 0 | H49: =IF(C49=0,0,(H48+C49)) -> 0 | I49: =IF(C49=0,0,(I48+E49)) -> 0 | J49: =H49-I49 -> 0 | K49: =IFERROR(H49/I49,0) -> 0
B50: =B49+1 -> 45971 | D50: =$C$18 -> 103092.78 | E50: =$C$10 -> 0 | F50: =C50-E50 -> 0 | G50: =IFERROR(C50/E50,0) -> 0 | H50: =IF(C50=0,0,(H49+C50)) -> 0 | I50: =IF(C50=0,0,(I49+E50)) -> 0 | J50: =H50-I50 -> 0 | K50: =IFERROR(H50/I50,0) -> 0
B51: =B50+1 -> 45972 | D51: =$C$18 -> 103092.78 | E51: =$C$11 -> 0 | F51: =C51-E51 -> 0 | G51: =IFERROR(C51/E51,0) -> 0 | H51: =IF(C51=0,0,(H50+C51)) -> 0 | I51: =IF(C51=0,0,(I50+E51)) -> 0 | J51: =H51-I51 -> 0 | K51: =IFERROR(H51/I51,0) -> 0
B52: =B51+1 -> 45973 | D52: =$C$18 -> 103092.78 | E52: =$C$12 -> 0 | F52: =C52-E52 -> 0 | G52: =IFERROR(C52/E52,0) -> 0 | H52: =IF(C52=0,0,(H51+C52)) -> 0 | I52: =IF(C52=0,0,(I51+E52)) -> 0 | J52: =H52-I52 -> 0 | K52: =IFERROR(H52/I52,0) -> 0
B53: =B52+1 -> 45974 | D53: 0 | E53: =$C$13 -> 0 | F53: =C53-E53 -> 0 | G53: =IFERROR(C53/E53,0) -> 0 | H53: =IF(C53=0,0,(H52+C53)) -> 0 | I53: =IF(C53=0,0,(I52+E53)) -> 0 | J53: =H53-I53 -> 0 | K53: =IFERROR(H53/I53,0) -> 0
B54: =B53+1 -> 45975 | D54: =$C$18 -> 103092.78 | E54: =$C$7 -> 0 | F54: =C54-E54 -> 0 | G54: =IFERROR(C54/E54,0) -> 0 | H54: =IF(C54=0,0,(H53+C54)) -> 0 | I54: =IF(C54=0,0,(I53+E54)) -> 0 | J54: =H54-I54 -> 0 | K54: =IFERROR(H54/I54,0) -> 0
B55: =B54+1 -> 45976 | D55: =$C$18 -> 103092.78 | E55: =$C$8 -> 0 | F55: =C55-E55 -> 0 | G55: =IFERROR(C55/E55,0) -> 0 | H55: =IF(C55=0,0,(H54+C55)) -> 0 | I55: =IF(C55=0,0,(I54+E55)) -> 0 | J55: =H55-I55 -> 0 | K55: =IFERROR(H55/I55,0) -> 0
B56: =B55+1 -> 45977 | D56: =$C$18 -> 103092.78 | E56: =$C$9 -> 0 | F56: =C56-E56 -> 0 | G56: =IFERROR(C56/E56,0) -> 0 | H56: =IF(C56=0,0,(H55+C56)) -> 0 | I56: =IF(C56=0,0,(I55+E56)) -> 0 | J56: =H56-I56 -> 0 | K56: =IFERROR(H56/I56,0) -> 0
B57: =B56+1 -> 45978 | D57: =$C$18 -> 103092.78 | E57: =$C$10 -> 0 | F57: =C57-E57 -> 0 | G57: =IFERROR(C57/E57,0) -> 0 | H57: =IF(C57=0,0,(H56+C57)) -> 0 | I57: =IF(C57=0,0,(I56+E57)) -> 0 | J57: =H57-I57 -> 0 | K57: =IFERROR(H57/I57,0) -> 0
B58: =B57+1 -> 45979 | D58: =$C$18 -> 103092.78 | E58: =$C$11 -> 0 | F58: =C58-E58 -> 0 | G58: =IFERROR(C58/E58,0) -> 0 | H58: =IF(C58=0,0,(H57+C58)) -> 0 | I58: =IF(C58=0,0,(I57+E58)) -> 0 | J58: =H58-I58 -> 0 | K58: =IFERROR(H58/I58,0) -> 0
B59: =B58+1 -> 45980 | D59: =$C$18 -> 103092.78 | E59: =$C$12 -> 0 | F59: =C59-E59 -> 0 | G59: =IFERROR(C59/E59,0) -> 0 | H59: =IF(C59=0,0,(H58+C59)) -> 0 | I59: =IF(C59=0,0,(I58+E59)) -> 0 | J59: =H59-I59 -> 0 | K59: =IFERROR(H59/I59,0) -> 0
B60: =B59+1 -> 45981 | D60: 0 | E60: =$C$13 -> 0 | F60: =C60-E60 -> 0 | G60: =IFERROR(C60/E60,0) -> 0 | H60: =IF(C60=0,0,(H59+C60)) -> 0 | I60: =IF(C60=0,0,(I59+E60)) -> 0 | J60: =H60-I60 -> 0 | K60: =IFERROR(H60/I60,0) -> 0
B61: =B60+1 -> 45982 | D61: 0 | F61: =C61-E61 -> 0 | G61: =IFERROR(C61/E61,0) -> 0 | H61: =IF(C61=0,0,(H60+C61)) -> 0 | I61: =IF(C61=0,0,(I60+E61)) -> 0 | J61: =H61-I61 -> 0 | K61: =IFERROR(H61/I61,0) -> 0
B62: =B61+1 -> 45983 | D62: =$C$18 -> 103092.78 | E62: =$C$8 -> 0 | F62: =C62-E62 -> 0 | G62: =IFERROR(C62/E62,0) -> 0 | H62: =IF(C62=0,0,(H61+C62)) -> 0 | I62: =IF(C62=0,0,(I61+E62)) -> 0 | J62: =H62-I62 -> 0 | K62: =IFERROR(H62/I62,0) -> 0
B63: =B62+1 -> 45984 | D63: =$C$18 -> 103092.78 | E63: =$C$9 -> 0 | F63: =C63-E63 -> 0 | G63: =IFERROR(C63/E63,0) -> 0 | H63: =IF(C63=0,0,(H62+C63)) -> 0 | I63: =IF(C63=0,0,(I62+E63)) -> 0 | J63: =H63-I63 -> 0 | K63: =IFERROR(H63/I63,0) -> 0
B64: =B63+1 -> 45985 | D64: =$C$18 -> 103092.78 | E64: =$C$10 -> 0 | F64: =C64-E64 -> 0 | G64: =IFERROR(C64/E64,0) -> 0 | H64: =IF(C64=0,0,(H63+C64)) -> 0 | I64: =IF(C64=0,0,(I63+E64)) -> 0 | J64: =H64-I64 -> 0 | K64: =IFERROR(H64/I64,0) -> 0
B65: =B64+1 -> 45986 | D65: =$C$18 -> 103092.78 | E65: =$C$11 -> 0 | F65: =C65-E65 -> 0 | G65: =IFERROR(C65/E65,0) -> 0 | H65: =IF(C65=0,0,(H64+C65)) -> 0 | I65: =IF(C65=0,0,(I64+E65)) -> 0 | J65: =H65-I65 -> 0 | K65: =IFERROR(H65/I65,0) -> 0
B66: =B65+1 -> 45987 | D66: =$C$18 -> 103092.78 | E66: =$C$12 -> 0 | F66: =C66-E66 -> 0 | G66: =IFERROR(C66/E66,0) -> 0 | H66: =IF(C66=0,0,(H65+C66)) -> 0 | I66: =IF(C66=0,0,(I65+E66)) -> 0 | J66: =H66-I66 -> 0 | K66: =IFERROR(H66/I66,0) -> 0
B67: =B66+1 -> 45988 | D67: 0 | E67: =$C$13 -> 0 | F67: =C67-E67 -> 0 | G67: =IFERROR(C67/E67,0) -> 0 | H67: =IF(C67=0,0,(H66+C67)) -> 0 | I67: =IF(C67=0,0,(I66+E67)) -> 0 | J67: =H67-I67 -> 0 | K67: =IFERROR(H67/I67,0) -> 0
B68: =B67+1 -> 45989 | D68: =$C$18 -> 103092.78 | E68: =$C$7 -> 0 | F68: =C68-E68 -> 0 | G68: =IFERROR(C68/E68,0) -> 0 | H68: =IF(C68=0,0,(H67+C68)) -> 0 | I68: =IF(C68=0,0,(I67+E68)) -> 0 | J68: =H68-I68 -> 0 | K68: =IFERROR(H68/I68,0) -> 0
B69: =B68+1 -> 45990 | D69: =$C$18 -> 103092.78 | E69: =$C$8 -> 0 | F69: =C69-E69 -> 0 | G69: =IFERROR(C69/E69,0) -> 0 | H69: =IF(C69=0,0,(H68+C69)) -> 0 | I69: =IF(C69=0,0,(I68+E69)) -> 0 | J69: =H69-I69 -> 0 | K69: =IFERROR(H69/I69,0) -> 0
B70: =B69+1 -> 45991 | D70: =$C$18 -> 103092.78 | E70: =$C$9 -> 0 | F70: =C70-E70 -> 0 | G70: =IFERROR(C70/E70,0) -> 0 | H70: =IF(C70=0,0,(H69+C70)) -> 0 | I70: =IF(C70=0,0,(I69+E70)) -> 0 | J70: =H70-I70 -> 0 | K70: =IFERROR(H70/I70,0) -> 0
B71: =B70+1 -> 45992 | D71: =$C$18 -> 103092.78 | E71: =$C$10 -> 0 | F71: =C71-E71 -> 0 | G71: =IFERROR(C71/E71,0) -> 0 | H71: =IF(C71=0,0,(H70+C71)) -> 0 | I71: =IF(C71=0,0,(I70+E71)) -> 0 | J71: =H71-I71 -> 0 | K71: =IFERROR(H71/I71,0) -> 0
C72: =SUM(C41:C71) -> 0 | D72: =SUM(D41:D71) -> 2680412.4 | E72: =SUM(E41:E71) -> 0
C73: =IFERROR(C72/D72,0) -> 0 | E73: =E72-F17 -> -2268041.2

Sheet 目標_2025R7
B2: 45658 | E2: ①年間営業日 | G2: ②年間目標売上 | H2: 年間総売上％ | K2: 年間売上合計 | M2: 実質売上 | P2: 1月 | Q2: 2月 | R2: 3月 | S2: 4月 | T2: ←目標の月へジャンプ
E3: =SUM(F7:F18) -> 291 | G3: 30000000 | H3: =SUM(AD7:AD18)*100 -> 0.999996 | I3: =G3*H3 -> 29999880 | K3: =SUM(J21:J385) -> 21736375 | M3: =K3-G3 -> -8263625 | P3: 5月 | Q3: 6月 | R3: 7月 | S3: 8月
P4: 9月 | Q4: 10月 | R4: 11月 | S4: 12月
B6: 平均日次売上目標額 | E6: 月 | F6: 月次営業日数 | G6: 平均月間売上目標額 | H6: 月次繁閑期%設定 | I6: 月次目標売上 | K6: 日次目標売上 | M6: 月次売上実績 | N6: 月間KGI | P6: 月次平均%(繁閑期) | Q6: 月次実質%
B7: ② ÷ ① | E7: 1月 | F7: =COUNTIF(D21:D51,1) -> 22 | G7: =$B$8*F7 -> 2268041.2 | H7: 0.85 | I7: =G7*H7 -> 1927835.1 | K7: =I7/F7 -> 87628.866 | M7: =SUM(J21:J51) -> 1783850 | N7: =M7-I7 -> -143985.05 | P7: =M7/G7 -> 0.78651568 | Q7: =M7/I7 -> 0.92531257 | R7: 1 | AA7: =TEXT(K7,"¥0") -> ¥87629 | AD7: =(H7/100)*AE7 -> 0.0007083305 | AE7: 0.083333
B8: =G3/E3 -> 103092.78 | E8: 2月 | F8: =COUNTIF(D52:D79,1) -> 23 | G8: =$B$8*F8 -> 2371134 | H8: 0.85 | I8: =G8*H8 -> 2015463.9 | K8: =I8/F8 -> 87628.866 | M8: =SUM(J52:J79) -> 1822300 | N8: =M8-I8 -> -193163.92 | P8: =M8/G8 -> 0.76853522 | Q8: =M8/I8 -> 0.90415908 | R8: 2 | AA8: =TEXT(K8,"¥0") -> ¥87629 | AD8: =(H8/100)*AE8 -> 0.0007083305 | AE8: 0.083333
E9: 3月 | F9: =COUNTIF(D80:D110,1) -> 26 | G9: =$B$8*F9 -> 2680412.4 | H9: 1 | I9: =G9*H9 -> 2680412.4 | K9: =I9/F9 -> 103092.78 | M9: =SUM(J80:J110) -> 2158500 | N9: =M9-I9 -> -521912.37 | P9: =M9/G9 -> 0.80528654 | Q9: =M9/I9 -> 0.80528654 | R9: 3 | AA9: =TEXT(K9,"¥0") -> ¥103093 | AD9: =(H9/100)*AE9 -> 0.00083333 | AE9: 0.083333
E10: 4月 | F10: =COUNTIF(D111:D140,1) -> 25 | G10: =$B$8*F10 -> 2577319.6 | H10: 1.1 | I10: =G10*H10 -> 2835051.5 | K10: =I10/F10 -> 113402.06 | M10: =SUM(J111:J140) -> 2262450 | N10: =M10-I10 -> -572601.55 | P10: =M10/G10 -> 0.8778306 | Q10: =M10/I10 -> 0.79802782 | R10: 4 | AA10: =TEXT(K10,"¥0") -> ¥113402 | AD10: =(H10/100)*AE10 -> 0.000916663 | AE10: 0.083333
E11: 5月 | F11: =COUNTIF(D141:D171,1) -> 26 | G11: =$B$8*F11 -> 2680412.4 | H11: 1 | I11: =G11*H11 -> 2680412.4 | K11: =I11/F11 -> 103092.78 | M11: =SUM(J141:J171) -> 2494050 | N11: =M11-I11 -> -186362.37 | P11: =M11/G11 -> 0.9304725 | Q11: =M11/I11 -> 0.9304725 | R11: 5 | AA11: =TEXT(K11,"¥0") -> ¥103093 | AD11: =(H11/100)*AE11 -> 0.00083333 | AE11: 0.083333
E12: 6月 | F12: =COUNTIF(D172:D201,1) -> 25 | G12: =$B$8*F12 -> 2577319.6 | H12: 0.85 | I12: =G12*H12 -> 2190721.6 | K12: =I12/F12 -> 87628.866 | M12: =SUM(J172:J201) -> 2396250 | N12: =M12-I12 -> 205528.35 | P12: =M12/G12 -> 0.929745 | Q12: =M12/I12 -> 1.0938176 | R12: 6 | AA12: =TEXT(K12,"¥0") -> ¥87629 | AD12: =(H12/100)*AE12 -> 0.0007083305 | AE12: 0.083333
E13: 7月 | F13: =COUNTIF(D202:D232,1) -> 25 | G13: =$B$8*F13 -> 2577319.6 | H13: 1.1 | I13: =G13*H13 -> 2835051.5 | K13: =I13/F13 -> 113402.06 | M13: =SUM(J202:J232) -> 2307750 | N13: =M13-I13 -> -527301.55 | P13: =M13/G13 -> 0.895407 | Q13: =M13/I13 -> 0.81400636 | R13: 7 | AA13: =TEXT(K13,"¥0") -> ¥113402 | AD13: =(H13/100)*AE13 -> 0.000916663 | AE13: 0.083333
E14: 8月 | F14: =COUNTIF(D233:D263,1) -> 24 | G14: =$B$8*F14 -> 2474226.8 | H14: 1 | I14: =G14*H14 -> 2474226.8 | K14: =I14/F14 -> 103092.78 | M14: =SUM(J233:J263) -> 1980325 | N14: =M14-I14 -> -493901.8 | P14: =M14/G14 -> 0.80038135 | Q14: =M14/I14 -> 0.80038135 | R14: 8 | AA14: =TEXT(K14,"¥0") -> ¥103093 | AD14: =(H14/100)*AE14 -> 0.00083333 | AE14: 0.083333
E15: 9 月 | F15: =COUNTIF(D264:D293,1) -> 23 | G15: =$B$8*F15 -> 2371134 | H15: 1 | I15: =G15*H15 -> 2371134 | K15: =I15/F15 -> 103092.78 | M15: =SUM(J264:J293) -> 1800300 | N15: =M15-I15 -> -570834.02 | P15: =M15/G15 -> 0.75925696 | Q15: =M15/I15 -> 0.75925696 | R15: 9 | AA15: =TEXT(K15,"¥0") -> ¥103093 | AD15: =(H15/100)*AE15 -> 0.00083333 | AE15: 0.083333
E16: 10月 | F16: =COUNTIF(D294:D324,1) -> 26 | G16: =$B$8*F16 -> 2680412.4 | H16: 1.1 | I16: =G16*H16 -> 2948453.6 | K16: =I16/F16 -> 113402.06 | M16: =SUM(J294:J324) -> 2123750 | N16: =M16-I16 -> -824703.61 | P16: =M16/G16 -> 0.79232212 | Q16: =M16/I16 -> 0.72029283 | R16: 10 | AA16: =TEXT(K16,"¥0") -> ¥113402 | AD16: =(H16/100)*AE16 -> 0.000916663 | AE16: 0.083333
E17: 11月 | F17: =COUNTIF(D325:D354,1) -> 22 | G17: =$B$8*F17 -> 2268041.2 | H17: 1 | I17: =G17*H17 -> 2268041.2 | K17: =I17/F17 -> 103092.78 | M17: =SUM(J325:J354) -> 606850 | N17: =M17-I17 -> -1661191.2 | P17: =M17/G17 -> 0.26756568 | Q17: =M17/I17 -> 0.26756568 | R17: 11 | AA17: =TEXT(K17,"¥0") -> ¥103093 | AD17: =(H17/100)*AE17 -> 0.00083333 | AE17: 0.083333
E18: 12月 | F18: =COUNTIF(D355:D385,1) -> 24 | G18: =$B$8*F18 -> 2474226.8 | H18: 1.15 | I18: =G18*H18 -> 2845360.8 | K18: =I18/F18 -> 118556.7 | M18: =SUM(J355:J385) -> 0 | N18: =M18-I18 -> -2845360.8 | P18: =M18/G18 -> 0 | Q18: =M18/I18 -> 0 | R18: 12 | AA18: =TEXT(K18,"¥0") -> ¥118557 | AD18: =(H18/100)*AE18 -> 0.0009583295 | AE18: 0.083333
E20: 月 | F20: 日程 | G20: 曜日 | H20: 日祝日 | J20: Daily売上入力 | L20: 目標売上 | M20: 実質売上 | N20: 実質% | P20: 月次目標売上 | Q20: 月次実質売上 | R20: 月次差額 | S20: 月次達成率 | U20: 年次目標売上 | V20: 年次実質売上 | W20: 年次差額 | X20: 年次達成率 | AA20: 月 | AB20: 曜日 | AC20: 実質曜日平均売上 | AD20: 曜日回数 | AE20: 曜日毎目標売上額 | AF20: 曜日毎トータル額
C21: 1 | D21: 0 | E21: =MONTH(Y21) -> 1 | F21: =B2 -> 45658 | G21: =TEXT(Z21,"ddd") -> Wed | H21: 元旦 | L21: =IF(D21=0,0,$K$7) -> 0 | M21: =IF(D21=0,0,J21-L21) -> 0 | N21: =IFERROR(J21/L21,"¥0") -> ¥0 | P21: =IF(D21=0,0,$K$7) -> 0 | Q21: =IF(D21=0,0,$J$21) -> 0 | R21: =IF(D21=0,0,Q21-P21) -> 0 | S21: =IF(D21=0,0,Q21/P21) -> 0 | U21: =IF(D21=0,0,$L$21) -> 0 | V21: =IF(D21=0,0,$J$21) -> 0 | W21: =IF(D21=0,0,V21-U21) -> 0 | X21: =IF(D21=0,0,V21/U21) -> 0 | Y21: =B2 -> 45658 | Z21: =B2 -> 45658 | AA21: 1 | AB21: mon | AC21: =IFERROR(AVERAGEIFS(J21:J51,D21:D51,1,G21:G51,"mon"),0) -> 90400 | AD21: =COUNTIFS(D21:D51,1,G21:G51,"Mon") -> 1 | AE21: =($I$7*[1]リトローボ_実績_2024R6!AI20)/AD21 -> 0 | AF21: =AD21*AE21 -> 0 | AG21: 21〜51
C22: 2 | D22: 0 | E22: =MONTH(Y22) -> 1 | F22: =F21+1 -> 45659 | G22: =TEXT(Z22,"ddd") -> Thu | H22: 休み | L22: =IF(D22=0,0,$K$7) -> 0 | M22: =IF(D22=0,0,J22-L22) -> 0 | N22: =IFERROR(J22/L22,"¥0") -> ¥0 | P22: =IF(D22=0,0,SUM($L$21:L22)) -> 0 | Q22: =IF(D22=0,0,SUM($J$21:J22)) -> 0 | R22: =IF(D22=0,0,Q22-P22) -> 0 | S22: =IF(D22=0,0,Q22/P22) -> 0 | U22: =IF(D22=0,0,SUM($L$21:L22)) -> 0 | V22: =IF(D22=0,0,SUM($J$21:J22)) -> 0 | W22: =IF(D22=0,0,V22-U22) -> 0 | X22: =IF(D22=0,0,V22/U22) -> 0 | Y22: =Y21+1 -> 45659 | Z22: =Z21+1 -> 45659 | AA22: 1 | AB22: tue | AC22: =IFERROR(AVERAGEIFS(J21:J51,D21:D51,1,G21:G51,"tue"),0) -> 67750 | AD22: =COUNTIFS(D21:D51,1,G21:G51,"tue") -> 4 | AE22: =($I$7*[1]リトローボ_実績_2024R6!AI21)/AD22 -> 0 | AF22: =AD22*AE22 -> 0
C23: 3 | D23: 0 | E23: =MONTH(Y23) -> 1 | F23: =F22+1 -> 45660 | G23: =TEXT(Z23,"ddd") -> Fri | H23: 休み | L23: =IF(D23=0,0,$K$7) -> 0 | M23: =IF(D23=0,0,J23-L23) -> 0 | N23: =IFERROR(J23/L23,"¥0") -> ¥0 | P23: =IF(D23=0,0,SUM($L$21:L23)) -> 0 | Q23: =IF(D23=0,0,SUM($J$21:J23)) -> 0 | R23: =IF(D23=0,0,Q23-P23) -> 0 | S23: =IF(D23=0,0,Q23/P23) -> 0 | U23: =IF(D23=0,0,SUM($L$21:L23)) -> 0 | V23: =IF(D23=0,0,SUM($J$21:J23)) -> 0 | W23: =IF(D23=0,0,V23-U23) -> 0 | X23: =IF(D23=0,0,V23/U23) -> 0 | Y23: =Y22+1 -> 45660 | Z23: =Z22+1 -> 45660 | AA23: 1 | AB23: wed | AC23: =IFERROR(AVERAGEIFS(J21:J51,D21:D51,1,G21:G51,"wed"),0) -> 83862.5 | AD23: =COUNTIFS(D21:D51,1,G21:G51,"wed") -> 4 | AE23: =IFERROR(($I$7*[1]リトローボ_実績_2024R6!AI22)/AD23,0) -> 0 | AF23: =AD23*AE23 -> 0
C24: 4 | D24: 0 | E24: =MONTH(Y24) -> 1 | F24: =F23+1 -> 45661 | G24: =TEXT(Z24,"ddd") -> Sat | L24: =IF(D24=0,0,$K$7) -> 0 | M24: =IF(D24=0,0,J24-L24) -> 0 | N24: =IFERROR(J24/L24,"¥0") -> ¥0 | P24: =IF(D24=0,0,SUM($L$21:L24)) -> 0 | Q24: =IF(D24=0,0,SUM($J$21:J24)) -> 0 | R24: =IF(D24=0,0,Q24-P24) -> 0 | S24: =IF(D24=0,0,Q24/P24) -> 0 | U24: =IF(D24=0,0,SUM($L$21:L24)) -> 0 | V24: =IF(D24=0,0,SUM($J$21:J24)) -> 0 | W24: =IF(D24=0,0,V24-U24) -> 0 | X24: =IF(D24=0,0,V24/U24) -> 0 | Y24: =Y23+1 -> 45661 | Z24: =Z23+1 -> 45661 | AA24: 1 | AB24: thu | AC24: =IFERROR(AVERAGEIFS(J21:J51,D21:D51,1,G21:G51,"thu"),0) -> 78475 | AD24: =COUNTIFS(D21:D51,1,G21:G51,"thu") -> 4 | AE24: =($I$7*[1]リトローボ_実績_2024R6!AI23)/AD24 -> 0 | AF24: =AD24*AE24 -> 0
C25: 5 | D25: 0 | E25: =MONTH(Y25) -> 1 | F25: =F24+1 -> 45662 | G25: =TEXT(Z25,"ddd") -> Sun | L25: =IF(D25=0,0,$K$7) -> 0 | M25: =IF(D25=0,0,J25-L25) -> 0 | N25: =IFERROR(J25/L25,"¥0") -> ¥0 | P25: =IF(D25=0,0,SUM($L$21:L25)) -> 0 | Q25: =IF(D25=0,0,SUM($J$21:J25)) -> 0 | R25: =IF(D25=0,0,Q25-P25) -> 0 | S25: =IF(D25=0,0,Q25/P25) -> 0 | U25: =IF(D25=0,0,SUM($L$21:L25)) -> 0 | V25: =IF(D25=0,0,SUM($J$21:J25)) -> 0 | W25: =IF(D25=0,0,V25-U25) -> 0 | X25: =IF(D25=0,0,V25/U25) -> 0 | Y25: =Y24+1 -> 45662 | Z25: =Z24+1 -> 45662 | AA25: 1 | AB25: fri | AC25: =IFERROR(AVERAGEIFS(J21:J51,D21:D51,1,G21:G51,"fri"),0) -> 108412.5 | AD25: =COUNTIFS(D21:D51,1,G21:G51,"fri") -> 4 | AE25: =($I$7*[1]リトローボ_実績_2024R6!AI24)/AD25 -> 0 | AF25: =AD25*AE25 -> 0
C26: 6 | D26: 0 | E26: =MONTH(Y26) -> 1 | F26: =F25+1 -> 45663 | G26: =TEXT(Z26,"ddd") -> Mon | L26: =IF(D26=0,0,$K$7) -> 0 | M26: =IF(D26=0,0,J26-L26) -> 0 | N26: =IFERROR(J26/L26,"¥0") -> ¥0 | P26: =IF(D26=0,0,SUM($L$21:L26)) -> 0 | Q26: =IF(D26=0,0,SUM($J$21:J26)) -> 0 | R26: =IF(D26=0,0,Q26-P26) -> 0 | S26: =IF(D26=0,0,Q26/P26) -> 0 | U26: =IF(D26=0,0,SUM($L$21:L26)) -> 0 | V26: =IF(D26=0,0,SUM($J$21:J26)) -> 0 | W26: =IF(D26=0,0,V26-U26) -> 0 | X26: =IF(D26=0,0,V26/U26) -> 0 | Y26: =Y25+1 -> 45663 | Z26: =Z25+1 -> 45663 | AA26: 1 | AB26: sat | AC26: =IFERROR(AVERAGEIFS(J21:J51,D21:D51,1,G21:G51,"sat"),0) -> 62316.667 | AD26: =COUNTIFS(D21:D51,1,G21:G51,"sat") -> 3 | AE26: =($I$7*[1]リトローボ_実績_2024R6!AI25)/AD26 -> 0 | AF26: =AD26*AE26 -> 0 | AG26: 1月目標売り上げ
C27: 7 | D27: 1 | E27: =MONTH(Y27) -> 1 | F27: =F26+1 -> 45664 | G27: =TEXT(Z27,"ddd") -> Tue | J27: 47550 | L27: =IF(D27=0,0,$K$7) -> 87628.866 | M27: =IF(D27=0,0,J27-L27) -> -40078.866 | N27: =IFERROR(J27/L27,"¥0") -> 0.54262941 | P27: =IF(D27=0,0,SUM($L$21:L27)) -> 87628.866 | Q27: =IF(D27=0,0,SUM($J$21:J27)) -> 47550 | R27: =IF(D27=0,0,Q27-P27) -> -40078.866 | S27: =IF(D27=0,0,Q27/P27) -> 0.54262941 | U27: =IF(D27=0,0,SUM($L$21:L27)) -> 87628.866 | V27: =IF(D27=0,0,SUM($J$21:J27)) -> 47550 | W27: =IF(D27=0,0,V27-U27) -> -40078.866 | X27: =IF(D27=0,0,V27/U27) -> 0.54262941 | Y27: =Y26+1 -> 45664 | Z27: =Z26+1 -> 45664 | AA27: 1 | AB27: sun | AC27: =IFERROR(AVERAGEIFS(J21:J51,D21:D51,1,G21:G51,"sun"),0) -> 76250 | AD27: =IFERROR(COUNTIFS(D21:D51,1,G21:G51,"sun"),0) -> 2 | AE27: =IFERROR(($I$7*[1]リトローボ_実績_2024R6!AI26)/AD27,0) -> 0 | AF27: =SUM(AF21:AF26) -> 0 | AG27: =I7 -> 1927835.1
C28: 8 | D28: 1 | E28: =MONTH(Y28) -> 1 | F28: =F27+1 -> 45665 | G28: =TEXT(Z28,"ddd") -> Wed | J28: 36950 | L28: =IF(D28=0,0,$K$7) -> 87628.866 | M28: =IF(D28=0,0,J28-L28) -> -50678.866 | N28: =IFERROR(J28/L28,"¥0") -> 0.42166471 | P28: =IF(D28=0,0,SUM($L$21:L28)) -> 175257.73 | Q28: =IF(D28=0,0,SUM($J$21:J28)) -> 84500 | R28: =IF(D28=0,0,Q28-P28) -> -90757.732 | S28: =IF(D28=0,0,Q28/P28) -> 0.48214706 | U28: =IF(D28=0,0,SUM($L$21:L28)) -> 175257.73 | V28: =IF(D28=0,0,SUM($J$21:J28)) -> 84500 | W28: =IF(D28=0,0,V28-U28) -> -90757.732 | X28: =IF(D28=0,0,V28/U28) -> 0.48214706 | Y28: =Y27+1 -> 45665 | Z28: =Z27+1 -> 45665 | AA28: 2 | AB28: Mon | AC28: =IFERROR(AVERAGEIFS(J52:J79,D52:D79,1,G52:G79,"mon"),0) -> 0 | AD28: =COUNTIFS(D52:D79,1,G52:G79,"Mon") -> 0 | AE28: =IFERROR(($I$8*[1]リトローボ_実績_2024R6!AI27)/AD28,0) -> 0 | AF28: =AD28*AE28 -> 0 | AG28: 52〜79
C29: 9 | D29: 1 | E29: =MONTH(Y29) -> 1 | F29: =F28+1 -> 45666 | G29: =TEXT(Z29,"ddd") -> Thu | J29: 71250 | L29: =IF(D29=0,0,$K$7) -> 87628.866 | M29: =IF(D29=0,0,J29-L29) -> -16378.866 | N29: =IFERROR(J29/L29,"¥0") -> 0.81308824 | P29: =IF(D29=0,0,SUM($L$21:L29)) -> 262886.6 | Q29: =IF(D29=0,0,SUM($J$21:J29)) -> 155750 | R29: =IF(D29=0,0,Q29-P29) -> -107136.6 | S29: =IF(D29=0,0,Q29/P29) -> 0.59246078 | U29: =IF(D29=0,0,SUM($L$21:L29)) -> 262886.6 | V29: =IF(D29=0,0,SUM($J$21:J29)) -> 155750 | W29: =IF(D29=0,0,V29-U29) -> -107136.6 | X29: =IF(D29=0,0,V29/U29) -> 0.59246078 | Y29: =Y28+1 -> 45666 | Z29: =Z28+1 -> 45666 | AA29: 2 | AB29: Tue | AC29: =IFERROR(AVERAGEIFS(J53:J80,D53:D80,1,G53:G80,"tue"),0) -> 56766.667 | AD29: =COUNTIFS(D52:D79,1,G52:G79,"tue") -> 3 | AE29: =($I$8*[1]リトローボ_実績_2024R6!AI28)/AD29 -> 0 | AF29: =AD29*AE29 -> 0
C30: 10 | D30: 1 | E30: =MONTH(Y30) -> 1 | F30: =F29+1 -> 45667 | G30: =TEXT(Z30,"ddd") -> Fri | J30: 127150 | L30: =IF(D30=0,0,$K$7) -> 87628.866 | M30: =IF(D30=0,0,J30-L30) -> 39521.134 | N30: =IFERROR(J30/L30,"¥0") -> 1.4510059 | P30: =IF(D30=0,0,SUM($L$21:L30)) -> 350515.46 | Q30: =IF(D30=0,0,SUM($J$21:J30)) -> 282900 | R30: =IF(D30=0,0,Q30-P30) -> -67615.464 | S30: =IF(D30=0,0,Q30/P30) -> 0.80709706 | U30: =IF(D30=0,0,SUM($L$21:L30)) -> 350515.46 | V30: =IF(D30=0,0,SUM($J$21:J30)) -> 282900 | W30: =IF(D30=0,0,V30-U30) -> -67615.464 | X30: =IF(D30=0,0,V30/U30) -> 0.80709706 | Y30: =Y29+1 -> 45667 | Z30: =Z29+1 -> 45667 | AA30: 2 | AB30: Wed | AC30: =IFERROR(AVERAGEIFS(J52:J79,D52:D79,1,G52:G79,"wed"),0) -> 68750 | AD30: =COUNTIFS(D52:D79,1,G52:G79,"wed") -> 4 | AE30: =($I$8*[1]リトローボ_実績_2024R6!AI29)/AD30 -> 0 | AF30: =AD30*AE30 -> 0
C31: 11 | D31: 1 | E31: =MONTH(Y31) -> 1 | F31: =F30+1 -> 45668 | G31: =TEXT(Z31,"ddd") -> Sat | J31: 96850 | L31: =IF(D31=0,0,$K$7) -> 87628.866 | M31: =IF(D31=0,0,J31-L31) -> 9221.134 | N31: =IFERROR(J31/L31,"¥0") -> 1.1052294 | P31: =IF(D31=0,0,SUM($L$21:L31)) -> 438144.33 | Q31: =IF(D31=0,0,SUM($J$21:J31)) -> 379750 | R31: =IF(D31=0,0,Q31-P31) -> -58394.33 | S31: =IF(D31=0,0,Q31/P31) -> 0.86672353 | U31: =IF(D31=0,0,SUM($L$21:L31)) -> 438144.33 | V31: =IF(D31=0,0,SUM($J$21:J31)) -> 379750 | W31: =IF(D31=0,0,V31-U31) -> -58394.33 | X31: =IF(D31=0,0,V31/U31) -> 0.86672353 | Y31: =Y30+1 -> 45668 | Z31: =Z30+1 -> 45668 | AA31: 2 | AB31: Thu | AC31: =IFERROR(AVERAGEIFS(J52:J79,D52:D79,1,G52:G79,"thu"),0) -> 89987.5 | AD31: =COUNTIFS(D52:D79,1,G52:G79,"thu") -> 4 | AE31: =($I$8*[1]リトローボ_実績_2024R6!AI30)/AD31 -> 0 | AF31: =AD31*AE31 -> 0
C32: 12 | D32: 0 | E32: =MONTH(Y32) -> 1 | F32: =F31+1 -> 45669 | G32: =TEXT(Z32,"ddd") -> Sun | H32: 成人の日 | L32: =IF(D32=0,0,$K$7) -> 0 | M32: =IF(D32=0,0,J32-L32) -> 0 | N32: =IFERROR(J32/L32,"¥0") -> ¥0 | P32: =IF(D32=0,0,SUM($L$21:L32)) -> 0 | Q32: =IF(D32=0,0,SUM($J$21:J32)) -> 0 | R32: =IF(D32=0,0,Q32-P32) -> 0 | S32: =IF(D32=0,0,Q32/P32) -> 0 | U32: =IF(D32=0,0,SUM($L$21:L32)) -> 0 | V32: =IF(D32=0,0,SUM($J$21:J32)) -> 0 | W32: =IF(D32=0,0,V32-U32) -> 0 | X32: =IF(D32=0,0,V32/U32) -> 0 | Y32: =Y31+1 -> 45669 | Z32: =Z31+1 -> 45669 | AA32: 2 | AB32: Fri | AC32: =IFERROR(AVERAGEIFS(J52:J79,D52:D79,1,G52:G79,"fri"),0) -> 97600 | AD32: =COUNTIFS(D52:D79,1,G52:G79,"fri") -> 4 | AE32: =($I$8*[1]リトローボ_実績_2024R6!AI31)/AD32 -> 0 | AF32: =AD32*AE32 -> 0
C33: 13 | D33: 0 | E33: =MONTH(Y33) -> 1 | F33: =F32+1 -> 45670 | G33: =TEXT(Z33,"ddd") -> Mon | L33: =IF(D33=0,0,$K$7) -> 0 | M33: =IF(D33=0,0,J33-L33) -> 0 | N33: =IFERROR(J33/L33,"¥0") -> ¥0 | P33: =IF(D33=0,0,SUM($L$21:L33)) -> 0 | Q33: =IF(D33=0,0,SUM($J$21:J33)) -> 0 | R33: =IF(D33=0,0,Q33-P33) -> 0 | S33: =IF(D33=0,0,Q33/P33) -> 0 | U33: =IF(D33=0,0,SUM($L$21:L33)) -> 0 | V33: =IF(D33=0,0,SUM($J$21:J33)) -> 0 | W33: =IF(D33=0,0,V33-U33) -> 0 | X33: =IF(D33=0,0,V33/U33) -> 0 | Y33: =Y32+1 -> 45670 | Z33: =Z32+1 -> 45670 | AA33: 2 | AB33: Sat | AC33: =IFERROR(AVERAGEIFS(J52:J79,D52:D79,1,G52:G79,"sat"),0) -> 76175 | AD33: =COUNTIFS(D52:D79,1,G52:G79,"sat") -> 4 | AE33: =($I$8*[1]リトローボ_実績_2024R6!AI32)/AD33 -> 0 | AF33: =AD33*AE33 -> 0 | AG33: 2月目標売り上げ
C34: 14 | D34: 1 | E34: =MONTH(Y34) -> 1 | F34: =F33+1 -> 45671 | G34: =TEXT(Z34,"ddd") -> Tue | J34: 48100 | L34: =IF(D34=0,0,$K$7) -> 87628.866 | M34: =IF(D34=0,0,J34-L34) -> -39528.866 | N34: =IFERROR(J34/L34,"¥0") -> 0.54890588 | P34: =IF(D34=0,0,SUM($L$21:L34)) -> 525773.2 | Q34: =IF(D34=0,0,SUM($J$21:J34)) -> 427850 | R34: =IF(D34=0,0,Q34-P34) -> -97923.196 | S34: =IF(D34=0,0,Q34/P34) -> 0.81375392 | U34: =IF(D34=0,0,SUM($L$21:L34)) -> 525773.2 | V34: =IF(D34=0,0,SUM($J$21:J34)) -> 427850 | W34: =IF(D34=0,0,V34-U34) -> -97923.196 | X34: =IF(D34=0,0,V34/U34) -> 0.81375392 | Y34: =Y33+1 -> 45671 | Z34: =Z33+1 -> 45671 | AA34: 2 | AB34: Sun | AC34: =IFERROR(AVERAGEIFS(J52:J79,D52:D79,1,G52:G79,"sun"),0) -> 80487.5 | AD34: =IFERROR(COUNTIFS(D52:D79,1,G52:G79,"sun"),0) -> 4 | AE34: =IFERROR(($I$8*[1]リトローボ_実績_2024R6!AI33)/AD34,0) -> 0 | AF34: =SUM(AF28:AF33) -> 0 | AG34: =I8 -> 2015463.9
C35: 15 | D35: 1 | E35: =MONTH(Y35) -> 1 | F35: =F34+1 -> 45672 | G35: =TEXT(Z35,"ddd") -> Wed | J35: 86400 | L35: =IF(D35=0,0,$K$7) -> 87628.866 | M35: =IF(D35=0,0,J35-L35) -> -1228.866 | N35: =IFERROR(J35/L35,"¥0") -> 0.98597647 | P35: =IF(D35=0,0,SUM($L$21:L35)) -> 613402.06 | Q35: =IF(D35=0,0,SUM($J$21:J35)) -> 514250 | R35: =IF(D35=0,0,Q35-P35) -> -99152.062 | S35: =IF(D35=0,0,Q35/P35) -> 0.83835714 | U35: =IF(D35=0,0,SUM($L$21:L35)) -> 613402.06 | V35: =IF(D35=0,0,SUM($J$21:J35)) -> 514250 | W35: =IF(D35=0,0,V35-U35) -> -99152.062 | X35: =IF(D35=0,0,V35/U35) -> 0.83835714 | Y35: =Y34+1 -> 45672 | Z35: =Z34+1 -> 45672 | AA35: 3 | AB35: Mon | AC35: =IFERROR(AVERAGEIFS(J80:J110,D80:D110,1,G80:G110,"mon"),0) -> 0 | AD35: =COUNTIFS(D80:D110,1,G80:G110,"Mon") -> 0 | AE35: =IFERROR(($I$9*[1]リトローボ_実績_2024R6!AI34)/AD35,0) -> 0 | AF35: =AD35*AE35 -> 0 | AG35: 80〜110
C36: 16 | D36: 1 | E36: =MONTH(Y36) -> 1 | F36: =F35+1 -> 45673 | G36: =TEXT(Z36,"ddd") -> Thu | J36: 48200 | L36: =IF(D36=0,0,$K$7) -> 87628.866 | M36: =IF(D36=0,0,J36-L36) -> -39428.866 | N36: =IFERROR(J36/L36,"¥0") -> 0.55004706 | P36: =IF(D36=0,0,SUM($L$21:L36)) -> 701030.93 | Q36: =IF(D36=0,0,SUM($J$21:J36)) -> 562450 | R36: =IF(D36=0,0,Q36-P36) -> -138580.93 | S36: =IF(D36=0,0,Q36/P36) -> 0.80231838 | U36: =IF(D36=0,0,SUM($L$21:L36)) -> 701030.93 | V36: =IF(D36=0,0,SUM($J$21:J36)) -> 562450 | W36: =IF(D36=0,0,V36-U36) -> -138580.93 | X36: =IF(D36=0,0,V36/U36) -> 0.80231838 | Y36: =Y35+1 -> 45673 | Z36: =Z35+1 -> 45673 | AA36: 3 | AB36: Tue | AC36: =IFERROR(AVERAGEIFS(J80:J110,D80:D110,1,G80:G110,"tue"),0) -> 70550 | AD36: =COUNTIFS(D80:D110,1,G80:G110,"tue") -> 4 | AE36: =($I$9*[1]リトローボ_実績_2024R6!AI35)/AD36 -> 0 | AF36: =AD36*AE36 -> 0
C37: 17 | D37: 1 | E37: =MONTH(Y37) -> 1 | F37: =F36+1 -> 45674 | G37: =TEXT(Z37,"ddd") -> Fri | J37: 68350 | L37: =IF(D37=0,0,$K$7) -> 87628.866 | M37: =IF(D37=0,0,J37-L37) -> -19278.866 | N37: =IFERROR(J37/L37,"¥0") -> 0.77999412 | P37: =IF(D37=0,0,SUM($L$21:L37)) -> 788659.79 | Q37: =IF(D37=0,0,SUM($J$21:J37)) -> 630800 | R37: =IF(D37=0,0,Q37-P37) -> -157859.79 | S37: =IF(D37=0,0,Q37/P37) -> 0.79983791 | U37: =IF(D37=0,0,SUM($L$21:L37)) -> 788659.79 | V37: =IF(D37=0,0,SUM($J$21:J37)) -> 630800 | W37: =IF(D37=0,0,V37-U37) -> -157859.79 | X37: =IF(D37=0,0,V37/U37) -> 0.79983791 | Y37: =Y36+1 -> 45674 | Z37: =Z36+1 -> 45674 | AA37: 3 | AB37: Wed | AC37: =IFERROR(AVERAGEIFS(J80:J110,D80:D110,1,G80:G110,"wed"),0) -> 59562.5 | AD37: =COUNTIFS(D80:D110,1,G80:G110,"wed") -> 4 | AE37: =($I$9*[1]リトローボ_実績_2024R6!AI36)/AD37 -> 0 | AF37: =AD37*AE37 -> 0
C38: 18 | D38: 1 | E38: =MONTH(Y38) -> 1 | F38: =F37+1 -> 45675 | G38: =TEXT(Z38,"ddd") -> Sat | J38: 45750 | L38: =IF(D38=0,0,$K$7) -> 87628.866 | M38: =IF(D38=0,0,J38-L38) -> -41878.866 | N38: =IFERROR(J38/L38,"¥0") -> 0.52208824 | P38: =IF(D38=0,0,SUM($L$21:L38)) -> 876288.66 | Q38: =IF(D38=0,0,SUM($J$21:J38)) -> 676550 | R38: =IF(D38=0,0,Q38-P38) -> -199738.66 | S38: =IF(D38=0,0,Q38/P38) -> 0.77206294 | U38: =IF(D38=0,0,SUM($L$21:L38)) -> 876288.66 | V38: =IF(D38=0,0,SUM($J$21:J38)) -> 676550 | W38: =IF(D38=0,0,V38-U38) -> -199738.66 | X38: =IF(D38=0,0,V38/U38) -> 0.77206294 | Y38: =Y37+1 -> 45675 | Z38: =Z37+1 -> 45675 | AA38: 3 | AB38: Thu | AC38: =IFERROR(AVERAGEIFS(J80:J110,D80:D110,1,G80:G110,"thu"),0) -> 79837.5 | AD38: =COUNTIFS(D80:D110,1,G80:G110,"thu") -> 4 | AE38: =($I$9*[1]リトローボ_実績_2024R6!AI37)/AD38 -> 0 | AF38: =AD38*AE38 -> 0
C39: 19 | D39: 1 | E39: =MONTH(Y39) -> 1 | F39: =F38+1 -> 45676 | G39: =TEXT(Z39,"ddd") -> Sun | J39: 50250 | L39: =IF(D39=0,0,$K$7) -> 87628.866 | M39: =IF(D39=0,0,J39-L39) -> -37378.866 | N39: =IFERROR(J39/L39,"¥0") -> 0.57344118 | P39: =IF(D39=0,0,SUM($L$21:L39)) -> 963917.53 | Q39: =IF(D39=0,0,SUM($J$21:J39)) -> 726800 | R39: =IF(D39=0,0,Q39-P39) -> -237117.53 | S39: =IF(D39=0,0,Q39/P39) -> 0.75400642 | U39: =IF(D39=0,0,SUM($L$21:L39)) -> 963917.53 | V39: =IF(D39=0,0,SUM($J$21:J39)) -> 726800 | W39: =IF(D39=0,0,V39-U39) -> -237117.53 | X39: =IF(D39=0,0,V39/U39) -> 0.75400642 | Y39: =Y38+1 -> 45676 | Z39: =Z38+1 -> 45676 | AA39: 3 | AB39: Fri | AC39: =IFERROR(AVERAGEIFS(J80:J110,D80:D110,1,G80:G110,"fri"),0) -> 123225 | AD39: =COUNTIFS(D80:D110,1,G80:G110,"fri") -> 4 | AE39: =($I$9*[1]リトローボ_実績_2024R6!AI38)/AD39 -> 0 | AF39: =AD39*AE39 -> 0
C40: 20 | D40: 1 | E40: =MONTH(Y40) -> 1 | F40: =F39+1 -> 45677 | G40: =TEXT(Z40,"ddd") -> Mon | J40: 90400 | L40: =IF(D40=0,0,$K$7) -> 87628.866 | M40: =IF(D40=0,0,J40-L40) -> 2771.134 | N40: =IFERROR(J40/L40,"¥0") -> 1.0316235 | P40: =IF(D40=0,0,SUM($L$21:L40)) -> 1051546.4 | Q40: =IF(D40=0,0,SUM($J$21:J40)) -> 817200 | R40: =IF(D40=0,0,Q40-P40) -> -234346.39 | S40: =IF(D40=0,0,Q40/P40) -> 0.77714118 | U40: =IF(D40=0,0,SUM($L$21:L40)) -> 1051546.4 | V40: =IF(D40=0,0,SUM($J$21:J40)) -> 817200 | W40: =IF(D40=0,0,V40-U40) -> -234346.39 | X40: =IF(D40=0,0,V40/U40) -> 0.77714118 | Y40: =Y39+1 -> 45677 | Z40: =Z39+1 -> 45677 | AA40: 3 | AB40: Sat | AC40: =IFERROR(AVERAGEIFS(J80:J110,D80:D110,1,G80:G110,"sat"),0) -> 65640 | AD40: =COUNTIFS(D80:D110,1,G80:G110,"sat") -> 5 | AE40: =($I$9*[1]リトローボ_実績_2024R6!AI39)/AD40 -> 0 | AF40: =AD40*AE40 -> 0 | AG40: 3月目標売り上げ
C41: 21 | D41: 1 | E41: =MONTH(Y41) -> 1 | F41: =F40+1 -> 45678 | G41: =TEXT(Z41,"ddd") -> Tue | J41: 89450 | L41: =IF(D41=0,0,$K$7) -> 87628.866 | M41: =IF(D41=0,0,J41-L41) -> 1821.134 | N41: =IFERROR(J41/L41,"¥0") -> 1.0207824 | P41: =IF(D41=0,0,SUM($L$21:L41)) -> 1139175.3 | Q41: =IF(D41=0,0,SUM($J$21:J41)) -> 906650 | R41: =IF(D41=0,0,Q41-P41) -> -232525.26 | S41: =IF(D41=0,0,Q41/P41) -> 0.79588281 | U41: =IF(D41=0,0,SUM($L$21:L41)) -> 1139175.3 | V41: =IF(D41=0,0,SUM($J$21:J41)) -> 906650 | W41: =IF(D41=0,0,V41-U41) -> -232525.26 | X41: =IF(D41=0,0,V41/U41) -> 0.79588281 | Y41: =Y40+1 -> 45678 | Z41: =Z40+1 -> 45678 | AA41: 3 | AB41: Sun | AC41: =IFERROR(AVERAGEIFS(J80:J110,D80:D110,1,G80:G110,"sun"),0) -> 99520 | AD41: =IFERROR(COUNTIFS(D80:D110,1,G80:G110,"sun"),0) -> 5 | AE41: =IFERROR(($I$9*[1]リトローボ_実績_2024R6!AI40)/AD41,0) -> 0 | AF41: =SUM(AF35:AF40) -> 0 | AG41: =I9 -> 2680412.4
C42: 22 | D42: 1 | E42: =MONTH(Y42) -> 1 | F42: =F41+1 -> 45679 | G42: =TEXT(Z42,"ddd") -> Wed | J42: 134500 | L42: =IF(D42=0,0,$K$7) -> 87628.866 | M42: =IF(D42=0,0,J42-L42) -> 46871.134 | N42: =IFERROR(J42/L42,"¥0") -> 1.5348824 | P42: =IF(D42=0,0,SUM($L$21:L42)) -> 1226804.1 | Q42: =IF(D42=0,0,SUM($J$21:J42)) -> 1041150 | R42: =IF(D42=0,0,Q42-P42) -> -185654.12 | S42: =IF(D42=0,0,Q42/P42) -> 0.84866849 | U42: =IF(D42=0,0,SUM($L$21:L42)) -> 1226804.1 | V42: =IF(D42=0,0,SUM($J$21:J42)) -> 1041150 | W42: =IF(D42=0,0,V42-U42) -> -185654.12 | X42: =IF(D42=0,0,V42/U42) -> 0.84866849 | Y42: =Y41+1 -> 45679 | Z42: =Z41+1 -> 45679 | AA42: 4 | AB42: Mon | AC42: =IFERROR(AVERAGEIFS(J111:J140,D111:D140,1,G111:G140,"mon"),0) -> 0 | AD42: =COUNTIFS(D111:D140,1,G111:G140,"Mon") -> 0 | AE42: =IFERROR(($I$10*[1]リトローボ_実績_2024R6!AI41)/AD42,0) -> 0 | AF42: =AD42*AE42 -> 0 | AG42: 111〜140
C43: 23 | D43: 1 | E43: =MONTH(Y43) -> 1 | F43: =F42+1 -> 45680 | G43: =TEXT(Z43,"ddd") -> Thu | J43: 85000 | L43: =IF(D43=0,0,$K$7) -> 87628.866 | M43: =IF(D43=0,0,J43-L43) -> -2628.866 | N43: =IFERROR(J43/L43,"¥0") -> 0.97 | P43: =IF(D43=0,0,SUM($L$21:L43)) -> 1314433 | Q43: =IF(D43=0,0,SUM($J$21:J43)) -> 1126150 | R43: =IF(D43=0,0,Q43-P43) -> -188282.99 | S43: =IF(D43=0,0,Q43/P43) -> 0.85675725 | U43: =IF(D43=0,0,SUM($L$21:L43)) -> 1314433 | V43: =IF(D43=0,0,SUM($J$21:J43)) -> 1126150 | W43: =IF(D43=0,0,V43-U43) -> -188282.99 | X43: =IF(D43=0,0,V43/U43) -> 0.85675725 | Y43: =Y42+1 -> 45680 | Z43: =Z42+1 -> 45680 | AA43: 4 | AB43: Tue | AC43: =IFERROR(AVERAGEIFS(J111:J140,D111:D140,1,G111:G140,"tue"),0) -> 77012.5 | AD43: =COUNTIFS(D111:D140,1,G111:G140,"tue") -> 4 | AE43: =($I$10*[1]リトローボ_実績_2024R6!AI42)/AD43 -> 0 | AF43: =AD43*AE43 -> 0
C44: 24 | D44: 1 | E44: =MONTH(Y44) -> 1 | F44: =F43+1 -> 45681 | G44: =TEXT(Z44,"ddd") -> Fri | J44: 132300 | L44: =IF(D44=0,0,$K$7) -> 87628.866 | M44: =IF(D44=0,0,J44-L44) -> 44671.134 | N44: =IFERROR(J44/L44,"¥0") -> 1.5097765 | P44: =IF(D44=0,0,SUM($L$21:L44)) -> 1402061.9 | Q44: =IF(D44=0,0,SUM($J$21:J44)) -> 1258450 | R44: =IF(D44=0,0,Q44-P44) -> -143611.86 | S44: =IF(D44=0,0,Q44/P44) -> 0.89757096 | U44: =IF(D44=0,0,SUM($L$21:L44)) -> 1402061.9 | V44: =IF(D44=0,0,SUM($J$21:J44)) -> 1258450 | W44: =IF(D44=0,0,V44-U44) -> -143611.86 | X44: =IF(D44=0,0,V44/U44) -> 0.89757096 | Y44: =Y43+1 -> 45681 | Z44: =Z43+1 -> 45681 | AA44: 4 | AB44: Wed | AC44: =IFERROR(AVERAGEIFS(J111:J140,D111:D140,1,G111:G140,"wed"),0) -> 81170 | AD44: =COUNTIFS(D111:D140,1,G111:G140,"wed") -> 5 | AE44: =($I$10*[1]リトローボ_実績_2024R6!AI43)/AD44 -> 0 | AF44: =AD44*AE44 -> 0
C45: 25 | D45: 1 | E45: =MONTH(Y45) -> 1 | F45: =F44+1 -> 45682 | G45: =TEXT(Z45,"ddd") -> Sat | J45: 44350 | L45: =IF(D45=0,0,$K$7) -> 87628.866 | M45: =IF(D45=0,0,J45-L45) -> -43278.866 | N45: =IFERROR(J45/L45,"¥0") -> 0.50611176 | P45: =IF(D45=0,0,SUM($L$21:L45)) -> 1489690.7 | Q45: =IF(D45=0,0,SUM($J$21:J45)) -> 1302800 | R45: =IF(D45=0,0,Q45-P45) -> -186890.72 | S45: =IF(D45=0,0,Q45/P45) -> 0.87454394 | U45: =IF(D45=0,0,SUM($L$21:L45)) -> 1489690.7 | V45: =IF(D45=0,0,SUM($J$21:J45)) -> 1302800 | W45: =IF(D45=0,0,V45-U45) -> -186890.72 | X45: =IF(D45=0,0,V45/U45) -> 0.87454394 | Y45: =Y44+1 -> 45682 | Z45: =Z44+1 -> 45682 | AA45: 4 | AB45: Thu | AC45: =IFERROR(AVERAGEIFS(J111:J140,D111:D140,1,G111:G140,"thu"),0) -> 81112.5 | AD45: =COUNTIFS(D111:D140,1,G111:G140,"thu") -> 4 | AE45: =($I$10*[1]リトローボ_実績_2024R6!AI44)/AD45 -> 0 | AF45: =AD45*AE45 -> 0
C46: 26 | D46: 1 | E46: =MONTH(Y46) -> 1 | F46: =F45+1 -> 45683 | G46: =TEXT(Z46,"ddd") -> Sun | J46: 102250 | L46: =IF(D46=0,0,$K$7) -> 87628.866 | M46: =IF(D46=0,0,J46-L46) -> 14621.134 | N46: =IFERROR(J46/L46,"¥0") -> 1.1668529 | P46: =IF(D46=0,0,SUM($L$21:L46)) -> 1577319.6 | Q46: =IF(D46=0,0,SUM($J$21:J46)) -> 1405050 | R46: =IF(D46=0,0,Q46-P46) -> -172269.59 | S46: =IF(D46=0,0,Q46/P46) -> 0.89078333 | U46: =IF(D46=0,0,SUM($L$21:L46)) -> 1577319.6 | V46: =IF(D46=0,0,SUM($J$21:J46)) -> 1405050 | W46: =IF(D46=0,0,V46-U46) -> -172269.59 | X46: =IF(D46=0,0,V46/U46) -> 0.89078333 | Y46: =Y45+1 -> 45683 | Z46: =Z45+1 -> 45683 | AA46: 4 | AB46: Fri | AC46: =IFERROR(AVERAGEIFS(J111:J140,D111:D140,1,G111:G140,"fri"),0) -> 153125 | AD46: =COUNTIFS(D111:D140,1,G111:G140,"fri") -> 4 | AE46: =($I$10*[1]リトローボ_実績_2024R6!AI45)/AD46 -> 0 | AF46: =AD46*AE46 -> 0
C47: 27 | D47: 0 | E47: =MONTH(Y47) -> 1 | F47: =F46+1 -> 45684 | G47: =TEXT(Z47,"ddd") -> Mon | L47: =IF(D47=0,0,$K$7) -> 0 | M47: =IF(D47=0,0,J47-L47) -> 0 | N47: =IFERROR(J47/L47,"¥0") -> ¥0 | P47: =IF(D47=0,0,SUM($L$21:L47)) -> 0 | Q47: =IF(D47=0,0,SUM($J$21:J47)) -> 0 | R47: =IF(D47=0,0,Q47-P47) -> 0 | S47: =IF(D47=0,0,Q47/P47) -> 0 | U47: =IF(D47=0,0,SUM($L$21:L47)) -> 0 | V47: =IF(D47=0,0,SUM($J$21:J47)) -> 0 | W47: =IF(D47=0,0,V47-U47) -> 0 | X47: =IF(D47=0,0,V47/U47) -> 0 | Y47: =Y46+1 -> 45684 | Z47: =Z46+1 -> 45684 | AA47: 4 | AB47: Sat | AC47: =IFERROR(AVERAGEIFS(J111:J140,D111:D140,1,G111:G140,"sat"),0) -> 81612.5 | AD47: =COUNTIFS(D111:D140,1,G111:G140,"sat") -> 4 | AE47: =($I$10*[1]リトローボ_実績_2024R6!AI46)/AD47 -> 0 | AF47: =AD47*AE47 -> 0 | AG47: 4月目標売り上げ
C48: 28 | D48: 1 | E48: =MONTH(Y48) -> 1 | F48: =F47+1 -> 45685 | G48: =TEXT(Z48,"ddd") -> Tue | J48: 85900 | L48: =IF(D48=0,0,$K$7) -> 87628.866 | M48: =IF(D48=0,0,J48-L48) -> -1728.866 | N48: =IFERROR(J48/L48,"¥0") -> 0.98027059 | P48: =IF(D48=0,0,SUM($L$21:L48)) -> 1664948.5 | Q48: =IF(D48=0,0,SUM($J$21:J48)) -> 1490950 | R48: =IF(D48=0,0,Q48-P48) -> -173998.45 | S48: =IF(D48=0,0,Q48/P48) -> 0.89549319 | U48: =IF(D48=0,0,SUM($L$21:L48)) -> 1664948.5 | V48: =IF(D48=0,0,SUM($J$21:J48)) -> 1490950 | W48: =IF(D48=0,0,V48-U48) -> -173998.45 | X48: =IF(D48=0,0,V48/U48) -> 0.89549319 | Y48: =Y47+1 -> 45685 | Z48: =Z47+1 -> 45685 | AA48: 4 | AB48: Sun | AC48: =IFERROR(AVERAGEIFS(J111:J140,D111:D140,1,G111:G140,"sun"),0) -> 71287.5 | AD48: =IFERROR(COUNTIFS(D111:D140,1,G111:G140,"sun"),0) -> 4 | AE48: =IFERROR(($I$10*[1]リトローボ_実績_2024R6!AI47)/AD48,0) -> 0 | AF48: =SUM(AF42:AF47) -> 0 | AG48: =I10 -> 2835051.5
C49: 29 | D49: 1 | E49: =MONTH(Y49) -> 1 | F49: =F48+1 -> 45686 | G49: =TEXT(Z49,"ddd") -> Wed | J49: 77600 | L49: =IF(D49=0,0,$K$7) -> 87628.866 | M49: =IF(D49=0,0,J49-L49) -> -10028.866 | N49: =IFERROR(J49/L49,"¥0") -> 0.88555294 | P49: =IF(D49=0,0,SUM($L$21:L49)) -> 1752577.3 | Q49: =IF(D49=0,0,SUM($J$21:J49)) -> 1568550 | R49: =IF(D49=0,0,Q49-P49) -> -184027.32 | S49: =IF(D49=0,0,Q49/P49) -> 0.89499618 | U49: =IF(D49=0,0,SUM($L$21:L49)) -> 1752577.3 | V49: =IF(D49=0,0,SUM($J$21:J49)) -> 1568550 | W49: =IF(D49=0,0,V49-U49) -> -184027.32 | X49: =IF(D49=0,0,V49/U49) -> 0.89499618 | Y49: =Y48+1 -> 45686 | Z49: =Z48+1 -> 45686 | AA49: 5 | AB49: Mon | AC49: =IFERROR(AVERAGEIFS(J141:J171,D141:D171,1,G141:G171,"mon"),0) -> 0 | AD49: =COUNTIFS(D141:D171,1,G141:G171,"Mon") -> 0 | AE49: =IFERROR(($I$11*[1]リトローボ_実績_2024R6!AI48)/AD49,0) -> 0 | AF49: =AD49*AE49 -> 0 | AG49: 141〜171
C50: 30 | D50: 1 | E50: =MONTH(Y50) -> 1 | F50: =F49+1 -> 45687 | G50: =TEXT(Z50,"ddd") -> Thu | J50: 109450 | L50: =IF(D50=0,0,$K$7) -> 87628.866 | M50: =IF(D50=0,0,J50-L50) -> 21821.134 | N50: =IFERROR(J50/L50,"¥0") -> 1.2490176 | P50: =IF(D50=0,0,SUM($L$21:L50)) -> 1840206.2 | Q50: =IF(D50=0,0,SUM($J$21:J50)) -> 1678000 | R50: =IF(D50=0,0,Q50-P50) -> -162206.19 | S50: =IF(D50=0,0,Q50/P50) -> 0.91185434 | U50: =IF(D50=0,0,SUM($L$21:L50)) -> 1840206.2 | V50: =IF(D50=0,0,SUM($J$21:J50)) -> 1678000 | W50: =IF(D50=0,0,V50-U50) -> -162206.19 | X50: =IF(D50=0,0,V50/U50) -> 0.91185434 | Y50: =Y49+1 -> 45687 | Z50: =Z49+1 -> 45687 | AA50: 5 | AB50: Tue | AC50: =IFERROR(AVERAGEIFS(J141:J171,D141:D171,1,G141:G171,"tue"),0) -> 104633.33 | AD50: =COUNTIFS(D141:D171,1,G141:G171,"tue") -> 3 | AE50: =($I$11*[1]リトローボ_実績_2024R6!AI49)/AD50 -> 0 | AF50: =AD50*AE50 -> 0
C51: 31 | D51: 1 | E51: =MONTH(Y51) -> 1 | F51: =F50+1 -> 45688 | G51: =TEXT(Z51,"ddd") -> Fri | J51: 105850 | L51: =IF(D51=0,0,$K$7) -> 87628.866 | M51: =IF(D51=0,0,J51-L51) -> 18221.134 | N51: =IFERROR(J51/L51,"¥0") -> 1.2079353 | P51: =IF(D51=0,0,SUM($L$21:L51)) -> 1927835.1 | Q51: =IF(D51=0,0,SUM($J$21:J51)) -> 1783850 | R51: =IF(D51=0,0,Q51-P51) -> -143985.05 | S51: =IF(D51=0,0,Q51/P51) -> 0.92531257 | U51: =IF(D51=0,0,SUM($L$21:L51)) -> 1927835.1 | V51: =IF(D51=0,0,SUM($J$21:J51)) -> 1783850 | W51: =IF(D51=0,0,V51-U51) -> -143985.05 | X51: =IF(D51=0,0,V51/U51) -> 0.92531257 | Y51: =Y50+1 -> 45688 | Z51: =Z50+1 -> 45688 | AA51: 5 | AB51: Wed | AC51: =IFERROR(AVERAGEIFS(J141:J171,D141:D171,1,G141:G171,"wed"),0) -> 95525 | AD51: =COUNTIFS(D141:D171,1,G141:G171,"wed") -> 4 | AE51: =($I$11*[1]リトローボ_実績_2024R6!AI50)/AD51 -> 0 | AF51: =AD51*AE51 -> 0
C52: 32 | D52: 1 | E52: =MONTH(Y52) -> 2 | F52: =F51+1 -> 45689 | G52: =TEXT(Z52,"ddd") -> Sat | J52: 91350 | L52: =IF(D52=0,0,$K$8) -> 87628.866 | M52: =IF(D52=0,0,J52-L52) -> 3721.134 | N52: =IFERROR(J52/L52,"¥0") -> 1.0424647 | P52: =IF(D52=0,0,$L$52) -> 87628.866 | Q52: =IF(D52=0,0,$J$52) -> 91350 | R52: =IF(D52=0,0,Q52-P52) -> 3721.134 | S52: =IF(D52=0,0,Q52/P52) -> 1.0424647 | U52: =IF(D52=0,0,SUM($L$21:L52)) -> 2015463.9 | V52: =IF(D52=0,0,SUM($J$21:J52)) -> 1875200 | W52: =IF(D52=0,0,V52-U52) -> -140263.92 | X52: =IF(D52=0,0,V52/U52) -> 0.93040614 | Y52: =Y51+1 -> 45689 | Z52: =Z51+1 -> 45689 | AA52: 5 | AB52: Thu | AC52: =IFERROR(AVERAGEIFS(J141:J171,D141:D171,1,G141:G171,"thu"),0) -> 97580 | AD52: =COUNTIFS(D141:D171,1,G141:G171,"thu") -> 5 | AE52: =($I$11*[1]リトローボ_実績_2024R6!AI51)/AD52 -> 0 | AF52: =AD52*AE52 -> 0
C53: 33 | D53: 1 | E53: =MONTH(Y53) -> 2 | F53: =F52+1 -> 45690 | G53: =TEXT(Z53,"ddd") -> Sun | J53: 68200 | L53: =IF(D53=0,0,$K$8) -> 87628.866 | M53: =IF(D53=0,0,J53-L53) -> -19428.866 | N53: =IFERROR(J53/L53,"¥0") -> 0.77828235 | P53: =IF(D53=0,0,SUM($L$52:L53)) -> 175257.73 | Q53: =IF(D53=0,0,SUM($J$52:J53)) -> 159550 | R53: =IF(D53=0,0,Q53-P53) -> -15707.732 | S53: =IF(D53=0,0,Q53/P53) -> 0.91037353 | U53: =IF(D53=0,0,SUM($L$21:L53)) -> 2103092.8 | V53: =IF(D53=0,0,SUM($J$21:J53)) -> 1943400 | W53: =IF(D53=0,0,V53-U53) -> -159692.78 | X53: =IF(D53=0,0,V53/U53) -> 0.92406765 | Y53: =Y52+1 -> 45690 | Z53: =Z52+1 -> 45690 | AA53: 5 | AB53: Fri | AC53: =IFERROR(AVERAGEIFS(J141:J171,D141:D171,1,G141:G171,"fri"),0) -> 119400 | AD53: =COUNTIFS(D141:D171,1,G141:G171,"fri") -> 5 | AE53: =($I$11*[1]リトローボ_実績_2024R6!AI52)/AD53 -> 0 | AF53: =AD53*AE53 -> 0
C54: 34 | D54: 0 | E54: =MONTH(Y54) -> 2 | F54: =F53+1 -> 45691 | G54: =TEXT(Z54,"ddd") -> Mon | L54: =IF(D54=0,0,$K$8) -> 0 | M54: =IF(D54=0,0,J54-L54) -> 0 | N54: =IFERROR(J54/L54,"¥0") -> ¥0 | P54: =IF(D54=0,0,SUM($L$52:L54)) -> 0 | Q54: =IF(D54=0,0,SUM($J$52:J54)) -> 0 | R54: =IF(D54=0,0,Q54-P54) -> 0 | S54: =IF(D54=0,0,Q54/P54) -> 0 | U54: =IF(D54=0,0,SUM($L$21:L54)) -> 0 | V54: =IF(D54=0,0,SUM($J$21:J54)) -> 0 | W54: =IF(D54=0,0,V54-U54) -> 0 | X54: =IF(D54=0,0,V54/U54) -> 0 | Y54: =Y53+1 -> 45691 | Z54: =Z53+1 -> 45691 | AA54: 5 | AB54: Sat | AC54: =IFERROR(AVERAGEIFS(J141:J171,D141:D171,1,G141:G171,"sat"),0) -> 62300 | AD54: =COUNTIFS(D141:D171,1,G141:G171,"sat") -> 5 | AE54: =($I$11*[1]リトローボ_実績_2024R6!AI53)/AD54 -> 0 | AF54: =AD54*AE54 -> 0 | AG54: 5月目標売り上げ
C55: 35 | D55: 1 | E55: =MONTH(Y55) -> 2 | F55: =F54+1 -> 45692 | G55: =TEXT(Z55,"ddd") -> Tue | J55: 53050 | L55: =IF(D55=0,0,$K$8) -> 87628.866 | M55: =IF(D55=0,0,J55-L55) -> -34578.866 | N55: =IFERROR(J55/L55,"¥0") -> 0.60539412 | P55: =IF(D55=0,0,SUM($L$52:L55)) -> 262886.6 | Q55: =IF(D55=0,0,SUM($J$52:J55)) -> 212600 | R55: =IF(D55=0,0,Q55-P55) -> -50286.598 | S55: =IF(D55=0,0,Q55/P55) -> 0.80871373 | U55: =IF(D55=0,0,SUM($L$21:L55)) -> 2190721.6 | V55: =IF(D55=0,0,SUM($J$21:J55)) -> 1996450 | W55: =IF(D55=0,0,V55-U55) -> -194271.65 | X55: =IF(D55=0,0,V55/U55) -> 0.91132071 | Y55: =Y54+1 -> 45692 | Z55: =Z54+1 -> 45692 | AA55: 5 | AB55: Sun | AC55: =IFERROR(AVERAGEIFS(J141:J171,D141:D171,1,G141:G171,"sun"),0) -> 100412.5 | AD55: =IFERROR(COUNTIFS(D141:D171,1,G141:G171,"sun"),0) -> 4 | AE55: =IFERROR(($I$11*[1]リトローボ_実績_2024R6!AI54)/AD55,0) -> 0 | AF55: =SUM(AF49:AF54) -> 0 | AG55: =I11 -> 2680412.4
C56: 36 | D56: 1 | E56: =MONTH(Y56) -> 2 | F56: =F55+1 -> 45693 | G56: =TEXT(Z56,"ddd") -> Wed | J56: 70350 | L56: =IF(D56=0,0,$K$8) -> 87628.866 | M56: =IF(D56=0,0,J56-L56) -> -17278.866 | N56: =IFERROR(J56/L56,"¥0") -> 0.80281765 | P56: =IF(D56=0,0,SUM($L$52:L56)) -> 350515.46 | Q56: =IF(D56=0,0,SUM($J$52:J56)) -> 282950 | R56: =IF(D56=0,0,Q56-P56) -> -67565.464 | S56: =IF(D56=0,0,Q56/P56) -> 0.80723971 | U56: =IF(D56=0,0,SUM($L$21:L56)) -> 2278350.5 | V56: =IF(D56=0,0,SUM($J$21:J56)) -> 2066800 | W56: =IF(D56=0,0,V56-U56) -> -211550.52 | X56: =IF(D56=0,0,V56/U56) -> 0.90714751 | Y56: =Y55+1 -> 45693 | Z56: =Z55+1 -> 45693 | AA56: 6 | AB56: Mon | AC56: =IFERROR(AVERAGEIFS(J172:J201,D172:D201,1,G172:G201,"mon"),0) -> 0 | AD56: =COUNTIFS(D172:D201,1,G172:G201,"Mon") -> 0 | AE56: =IFERROR(($I$12*[1]リトローボ_実績_2024R6!AI55)/AD56,0) -> 0 | AF56: =AD56*AE56 -> 0 | AG56: 172〜201
C57: 37 | D57: 1 | E57: =MONTH(Y57) -> 2 | F57: =F56+1 -> 45694 | G57: =TEXT(Z57,"ddd") -> Thu | J57: 46900 | L57: =IF(D57=0,0,$K$8) -> 87628.866 | M57: =IF(D57=0,0,J57-L57) -> -40728.866 | N57: =IFERROR(J57/L57,"¥0") -> 0.53521176 | P57: =IF(D57=0,0,SUM($L$52:L57)) -> 438144.33 | Q57: =IF(D57=0,0,SUM($J$52:J57)) -> 329850 | R57: =IF(D57=0,0,Q57-P57) -> -108294.33 | S57: =IF(D57=0,0,Q57/P57) -> 0.75283412 | U57: =IF(D57=0,0,SUM($L$21:L57)) -> 2365979.4 | V57: =IF(D57=0,0,SUM($J$21:J57)) -> 2113700 | W57: =IF(D57=0,0,V57-U57) -> -252279.38 | X57: =IF(D57=0,0,V57/U57) -> 0.89337211 | Y57: =Y56+1 -> 45694 | Z57: =Z56+1 -> 45694 | AA57: 6 | AB57: Tue | AC57: =IFERROR(AVERAGEIFS(J172:J201,D172:D201,1,G172:G201,"tue"),0) -> 68600 | AD57: =COUNTIFS(D172:D201,1,G172:G201,"tue") -> 4 | AE57: =($I$12*[1]リトローボ_実績_2024R6!AI56)/AD57 -> 0 | AF57: =AD57*AE57 -> 0
C58: 38 | D58: 1 | E58: =MONTH(Y58) -> 2 | F58: =F57+1 -> 45695 | G58: =TEXT(Z58,"ddd") -> Fri | J58: 96350 | L58: =IF(D58=0,0,$K$8) -> 87628.866 | M58: =IF(D58=0,0,J58-L58) -> 8721.134 | N58: =IFERROR(J58/L58,"¥0") -> 1.0995235 | P58: =IF(D58=0,0,SUM($L$52:L58)) -> 525773.2 | Q58: =IF(D58=0,0,SUM($J$52:J58)) -> 426200 | R58: =IF(D58=0,0,Q58-P58) -> -99573.196 | S58: =IF(D58=0,0,Q58/P58) -> 0.81061569 | U58: =IF(D58=0,0,SUM($L$21:L58)) -> 2453608.2 | V58: =IF(D58=0,0,SUM($J$21:J58)) -> 2210050 | W58: =IF(D58=0,0,V58-U58) -> -243558.25 | X58: =IF(D58=0,0,V58/U58) -> 0.90073466 | Y58: =Y57+1 -> 45695 | Z58: =Z57+1 -> 45695 | AA58: 6 | AB58: Wed | AC58: =IFERROR(AVERAGEIFS(J172:J201,D172:D201,1,G172:G201,"wed"),0) -> 84250 | AD58: =COUNTIFS(D172:D201,1,G172:G201,"wed") -> 4 | AE58: =($I$12*[1]リトローボ_実績_2024R6!AI57)/AD58 -> 0 | AF58: =AD58*AE58 -> 0
C59: 39 | D59: 1 | E59: =MONTH(Y59) -> 2 | F59: =F58+1 -> 45696 | G59: =TEXT(Z59,"ddd") -> Sat | J59: 72500 | L59: =IF(D59=0,0,$K$8) -> 87628.866 | M59: =IF(D59=0,0,J59-L59) -> -15128.866 | N59: =IFERROR(J59/L59,"¥0") -> 0.82735294 | P59: =IF(D59=0,0,SUM($L$52:L59)) -> 613402.06 | Q59: =IF(D59=0,0,SUM($J$52:J59)) -> 498700 | R59: =IF(D59=0,0,Q59-P59) -> -114702.06 | S59: =IF(D59=0,0,Q59/P59) -> 0.81300672 | U59: =IF(D59=0,0,SUM($L$21:L59)) -> 2541237.1 | V59: =IF(D59=0,0,SUM($J$21:J59)) -> 2282550 | W59: =IF(D59=0,0,V59-U59) -> -258687.11 | X59: =IF(D59=0,0,V59/U59) -> 0.89820426 | Y59: =Y58+1 -> 45696 | Z59: =Z58+1 -> 45696 | AA59: 6 | AB59: Thu | AC59: =IFERROR(AVERAGEIFS(J172:J201,D172:D201,1,G172:G201,"thu"),0) -> 104375 | AD59: =COUNTIFS(D172:D201,1,G172:G201,"thu") -> 4 | AE59: =($I$12*[1]リトローボ_実績_2024R6!AI58)/AD59 -> 0 | AF59: =AD59*AE59 -> 0
C60: 40 | D60: 1 | E60: =MONTH(Y60) -> 2 | F60: =F59+1 -> 45697 | G60: =TEXT(Z60,"ddd") -> Sun | J60: 75650 | L60: =IF(D60=0,0,$K$8) -> 87628.866 | M60: =IF(D60=0,0,J60-L60) -> -11978.866 | N60: =IFERROR(J60/L60,"¥0") -> 0.8633 | P60: =IF(D60=0,0,SUM($L$52:L60)) -> 701030.93 | Q60: =IF(D60=0,0,SUM($J$52:J60)) -> 574350 | R60: =IF(D60=0,0,Q60-P60) -> -126680.93 | S60: =IF(D60=0,0,Q60/P60) -> 0.81929338 | U60: =IF(D60=0,0,SUM($L$21:L60)) -> 2628866 | V60: =IF(D60=0,0,SUM($J$21:J60)) -> 2358200 | W60: =IF(D60=0,0,V60-U60) -> -270665.98 | X60: =IF(D60=0,0,V60/U60) -> 0.89704078 | Y60: =Y59+1 -> 45697 | Z60: =Z59+1 -> 45697 | AA60: 6 | AB60: Fri | AC60: =IFERROR(AVERAGEIFS(J172:J201,D172:D201,1,G172:G201,"fri"),0) -> 142137.5 | AD60: =COUNTIFS(D172:D201,1,G172:G201,"fri") -> 4 | AE60: =($I$12*[1]リトローボ_実績_2024R6!AI59)/AD60 -> 0 | AF60: =AD60*AE60 -> 0
C61: 41 | D61: 0 | E61: =MONTH(Y61) -> 2 | F61: =F60+1 -> 45698 | G61: =TEXT(Z61,"ddd") -> Mon | L61: =IF(D61=0,0,$K$8) -> 0 | M61: =IF(D61=0,0,J61-L61) -> 0 | N61: =IFERROR(J61/L61,"¥0") -> ¥0 | P61: =IF(D61=0,0,SUM($L$52:L61)) -> 0 | Q61: =IF(D61=0,0,SUM($J$52:J61)) -> 0 | R61: =IF(D61=0,0,Q61-P61) -> 0 | S61: =IF(D61=0,0,Q61/P61) -> 0 | U61: =IF(D61=0,0,SUM($L$21:L61)) -> 0 | V61: =IF(D61=0,0,SUM($J$21:J61)) -> 0 | W61: =IF(D61=0,0,V61-U61) -> 0 | X61: =IF(D61=0,0,V61/U61) -> 0 | Y61: =Y60+1 -> 45698 | Z61: =Z60+1 -> 45698 | AA61: 6 | AB61: Sat | AC61: =IFERROR(AVERAGEIFS(J172:J201,D172:D201,1,G172:G201,"sat"),0) -> 100487.5 | AD61: =COUNTIFS(D172:D201,1,G172:G201,"sat") -> 4 | AE61: =($I$12*[1]リトローボ_実績_2024R6!AI60)/AD61 -> 0 | AF61: =AD61*AE61 -> 0 | AG61: 6月目標売り上げ
C62: 42 | D62: 0 | E62: =MONTH(Y62) -> 2 | F62: =F61+1 -> 45699 | G62: =TEXT(Z62,"ddd") -> Tue | L62: =IF(D62=0,0,$K$8) -> 0 | M62: =IF(D62=0,0,J62-L62) -> 0 | N62: =IFERROR(J62/L62,"¥0") -> ¥0 | P62: =IF(D62=0,0,SUM($L$52:L62)) -> 0 | Q62: =IF(D62=0,0,SUM($J$52:J62)) -> 0 | R62: =IF(D62=0,0,Q62-P62) -> 0 | S62: =IF(D62=0,0,Q62/P62) -> 0 | U62: =IF(D62=0,0,SUM($L$21:L62)) -> 0 | V62: =IF(D62=0,0,SUM($J$21:J62)) -> 0 | W62: =IF(D62=0,0,V62-U62) -> 0 | X62: =IF(D62=0,0,V62/U62) -> 0 | Y62: =Y61+1 -> 45699 | Z62: =Z61+1 -> 45699 | AA62: 6 | AB62: Sun | AC62: =IFERROR(AVERAGEIFS(J172:J201,D172:D201,1,G172:G201,"sun"),0) -> 79370 | AD62: =IFERROR(COUNTIFS(D172:D201,1,G172:G201,"sun"),0) -> 5 | AE62: =IFERROR(($I$12*[1]リトローボ_実績_2024R6!AI61)/AD62,0) -> 0 | AF62: =SUM(AF56:AF61) -> 0 | AG62: =I12 -> 2190721.6
C63: 43 | D63: 1 | E63: =MONTH(Y63) -> 2 | F63: =F62+1 -> 45700 | G63: =TEXT(Z63,"ddd") -> Wed | J63: 72400 | L63: =IF(D63=0,0,$K$8) -> 87628.866 | M63: =IF(D63=0,0,J63-L63) -> -15228.866 | N63: =IFERROR(J63/L63,"¥0") -> 0.82621176 | P63: =IF(D63=0,0,SUM($L$52:L63)) -> 788659.79 | Q63: =IF(D63=0,0,SUM($J$52:J63)) -> 646750 | R63: =IF(D63=0,0,Q63-P63) -> -141909.79 | S63: =IF(D63=0,0,Q63/P63) -> 0.82006209 | U63: =IF(D63=0,0,SUM($L$21:L63)) -> 2716494.8 | V63: =IF(D63=0,0,SUM($J$21:J63)) -> 2430600 | W63: =IF(D63=0,0,V63-U63) -> -285894.85 | X63: =IF(D63=0,0,V63/U63) -> 0.89475598 | Y63: =Y62+1 -> 45700 | Z63: =Z62+1 -> 45700 | AA63: 7 | AB63: Mon | AC63: =IFERROR(AVERAGEIFS(J202:J232,D202:D232,1,G202:G232,"mon"),0) -> 0 | AD63: =COUNTIFS(D202:D232,1,G202:G232,"Mon") -> 0 | AE63: =IFERROR(($I$13*[1]リトローボ_実績_2024R6!AI62)/AD63,0) -> 0 | AF63: =AD63*AE63 -> 0 | AG63: 202〜232
C64: 44 | D64: 1 | E64: =MONTH(Y64) -> 2 | F64: =F63+1 -> 45701 | G64: =TEXT(Z64,"ddd") -> Thu | J64: 106950 | L64: =IF(D64=0,0,$K$8) -> 87628.866 | M64: =IF(D64=0,0,J64-L64) -> 19321.134 | N64: =IFERROR(J64/L64,"¥0") -> 1.2204882 | P64: =IF(D64=0,0,SUM($L$52:L64)) -> 876288.66 | Q64: =IF(D64=0,0,SUM($J$52:J64)) -> 753700 | R64: =IF(D64=0,0,Q64-P64) -> -122588.66 | S64: =IF(D64=0,0,Q64/P64) -> 0.86010471 | U64: =IF(D64=0,0,SUM($L$21:L64)) -> 2804123.7 | V64: =IF(D64=0,0,SUM($J$21:J64)) -> 2537550 | W64: =IF(D64=0,0,V64-U64) -> -266573.71 | X64: =IF(D64=0,0,V64/U64) -> 0.90493511 | Y64: =Y63+1 -> 45701 | Z64: =Z63+1 -> 45701 | AA64: 7 | AB64: Tue | AC64: =IFERROR(AVERAGEIFS(J202:J232,D202:D232,1,G202:G232,"tue"),0) -> 91712.5 | AD64: =COUNTIFS(D202:D232,1,G202:G232,"tue") -> 4 | AE64: =($I$13*[1]リトローボ_実績_2024R6!AI63)/AD64 -> 0 | AF64: =AD64*AE64 -> 0
C65: 45 | D65: 1 | E65: =MONTH(Y65) -> 2 | F65: =F64+1 -> 45702 | G65: =TEXT(Z65,"ddd") -> Fri | J65: 103350 | L65: =IF(D65=0,0,$K$8) -> 87628.866 | M65: =IF(D65=0,0,J65-L65) -> 15721.134 | N65: =IFERROR(J65/L65,"¥0") -> 1.1794059 | P65: =IF(D65=0,0,SUM($L$52:L65)) -> 963917.53 | Q65: =IF(D65=0,0,SUM($J$52:J65)) -> 857050 | R65: =IF(D65=0,0,Q65-P65) -> -106867.53 | S65: =IF(D65=0,0,Q65/P65) -> 0.88913209 | U65: =IF(D65=0,0,SUM($L$21:L65)) -> 2891752.6 | V65: =IF(D65=0,0,SUM($J$21:J65)) -> 2640900 | W65: =IF(D65=0,0,V65-U65) -> -250852.58 | X65: =IF(D65=0,0,V65/U65) -> 0.91325241 | Y65: =Y64+1 -> 45702 | Z65: =Z64+1 -> 45702 | AA65: 7 | AB65: Wed | AC65: =IFERROR(AVERAGEIFS(J202:J232,D202:D232,1,G202:G232,"wed"),0) -> 94700 | AD65: =COUNTIFS(D202:D232,1,G202:G232,"wed") -> 4 | AE65: =($I$13*[1]リトローボ_実績_2024R6!AI64)/AD65 -> 0 | AF65: =AD65*AE65 -> 0
C66: 46 | D66: 1 | E66: =MONTH(Y66) -> 2 | F66: =F65+1 -> 45703 | G66: =TEXT(Z66,"ddd") -> Sat | J66: 68600 | L66: =IF(D66=0,0,$K$8) -> 87628.866 | M66: =IF(D66=0,0,J66-L66) -> -19028.866 | N66: =IFERROR(J66/L66,"¥0") -> 0.78284706 | P66: =IF(D66=0,0,SUM($L$52:L66)) -> 1051546.4 | Q66: =IF(D66=0,0,SUM($J$52:J66)) -> 925650 | R66: =IF(D66=0,0,Q66-P66) -> -125896.39 | S66: =IF(D66=0,0,Q66/P66) -> 0.880275 | U66: =IF(D66=0,0,SUM($L$21:L66)) -> 2979381.4 | V66: =IF(D66=0,0,SUM($J$21:J66)) -> 2709500 | W66: =IF(D66=0,0,V66-U66) -> -269881.44 | X66: =IF(D66=0,0,V66/U66) -> 0.90941696 | Y66: =Y65+1 -> 45703 | Z66: =Z65+1 -> 45703 | AA66: 7 | AB66: Thu | AC66: =IFERROR(AVERAGEIFS(J202:J232,D202:D232,1,G202:G232,"thu"),0) -> 96660 | AD66: =COUNTIFS(D202:D232,1,G202:G232,"thu") -> 5 | AE66: =($I$13*[1]リトローボ_実績_2024R6!AI65)/AD66 -> 0 | AF66: =AD66*AE66 -> 0
C67: 47 | D67: 1 | E67: =MONTH(Y67) -> 2 | F67: =F66+1 -> 45704 | G67: =TEXT(Z67,"ddd") -> Sun | J67: 74850 | L67: =IF(D67=0,0,$K$8) -> 87628.866 | M67: =IF(D67=0,0,J67-L67) -> -12778.866 | N67: =IFERROR(J67/L67,"¥0") -> 0.85417059 | P67: =IF(D67=0,0,SUM($L$52:L67)) -> 1139175.3 | Q67: =IF(D67=0,0,SUM($J$52:J67)) -> 1000500 | R67: =IF(D67=0,0,Q67-P67) -> -138675.26 | S67: =IF(D67=0,0,Q67/P67) -> 0.87826697 | U67: =IF(D67=0,0,SUM($L$21:L67)) -> 3067010.3 | V67: =IF(D67=0,0,SUM($J$21:J67)) -> 2784350 | W67: =IF(D67=0,0,V67-U67) -> -282660.31 | X67: =IF(D67=0,0,V67/U67) -> 0.90783849 | Y67: =Y66+1 -> 45704 | Z67: =Z66+1 -> 45704 | AA67: 7 | AB67: Fri | AC67: =IFERROR(AVERAGEIFS(J202:J232,D202:D232,1,G202:G232,"fri"),0) -> 124962.5 | AD67: =COUNTIFS(D202:D232,1,G202:G232,"fri") -> 4 | AE67: =($I$13*[1]リトローボ_実績_2024R6!AI66)/AD67 -> 0 | AF67: =AD67*AE67 -> 0
C68: 48 | D68: 0 | E68: =MONTH(Y68) -> 2 | F68: =F67+1 -> 45705 | G68: =TEXT(Z68,"ddd") -> Mon | L68: =IF(D68=0,0,$K$8) -> 0 | M68: =IF(D68=0,0,J68-L68) -> 0 | N68: =IFERROR(J68/L68,"¥0") -> ¥0 | P68: =IF(D68=0,0,SUM($L$52:L68)) -> 0 | Q68: =IF(D68=0,0,SUM($J$52:J68)) -> 0 | R68: =IF(D68=0,0,Q68-P68) -> 0 | S68: =IF(D68=0,0,Q68/P68) -> 0 | U68: =IF(D68=0,0,SUM($L$21:L68)) -> 0 | V68: =IF(D68=0,0,SUM($J$21:J68)) -> 0 | W68: =IF(D68=0,0,V68-U68) -> 0 | X68: =IF(D68=0,0,V68/U68) -> 0 | Y68: =Y67+1 -> 45705 | Z68: =Z67+1 -> 45705 | AA68: 7 | AB68: Sat | AC68: =IFERROR(AVERAGEIFS(J202:J232,D202:D232,1,G202:G232,"sat"),0) -> 55787.5 | AD68: =COUNTIFS(D202:D232,1,G202:G232,"sat") -> 4 | AE68: =($I$13*[1]リトローボ_実績_2024R6!AI67)/AD68 -> 0 | AF68: =AD68*AE68 -> 0 | AG68: 7月目標売り上げ
C69: 49 | D69: 1 | E69: =MONTH(Y69) -> 2 | F69: =F68+1 -> 45706 | G69: =TEXT(Z69,"ddd") -> Tue | J69: 34300 | L69: =IF(D69=0,0,$K$8) -> 87628.866 | M69: =IF(D69=0,0,J69-L69) -> -53328.866 | N69: =IFERROR(J69/L69,"¥0") -> 0.39142353 | P69: =IF(D69=0,0,SUM($L$52:L69)) -> 1226804.1 | Q69: =IF(D69=0,0,SUM($J$52:J69)) -> 1034800 | R69: =IF(D69=0,0,Q69-P69) -> -192004.12 | S69: =IF(D69=0,0,Q69/P69) -> 0.84349244 | U69: =IF(D69=0,0,SUM($L$21:L69)) -> 3154639.2 | V69: =IF(D69=0,0,SUM($J$21:J69)) -> 2818650 | W69: =IF(D69=0,0,V69-U69) -> -335989.18 | X69: =IF(D69=0,0,V69/U69) -> 0.89349363 | Y69: =Y68+1 -> 45706 | Z69: =Z68+1 -> 45706 | AA69: 7 | AB69: Sun | AC69: =IFERROR(AVERAGEIFS(J202:J232,D202:D232,1,G202:G232,"sun"),0) -> 88950 | AD69: =IFERROR(COUNTIFS(D202:D232,1,G202:G232,"sun"),0) -> 4 | AE69: =IFERROR(($I$13*[1]リトローボ_実績_2024R6!AI68)/AD69,0) -> 0 | AF69: =SUM(AF63:AF68) -> 0 | AG69: =I13 -> 2835051.5
C70: 50 | D70: 1 | E70: =MONTH(Y70) -> 2 | F70: =F69+1 -> 45707 | G70: =TEXT(Z70,"ddd") -> Wed | J70: 50550 | L70: =IF(D70=0,0,$K$8) -> 87628.866 | M70: =IF(D70=0,0,J70-L70) -> -37078.866 | N70: =IFERROR(J70/L70,"¥0") -> 0.57686471 | P70: =IF(D70=0,0,SUM($L$52:L70)) -> 1314433 | Q70: =IF(D70=0,0,SUM($J$52:J70)) -> 1085350 | R70: =IF(D70=0,0,Q70-P70) -> -229082.99 | S70: =IF(D70=0,0,Q70/P70) -> 0.82571725 | U70: =IF(D70=0,0,SUM($L$21:L70)) -> 3242268 | V70: =IF(D70=0,0,SUM($J$21:J70)) -> 2869200 | W70: =IF(D70=0,0,V70-U70) -> -373068.04 | X70: =IF(D70=0,0,V70/U70) -> 0.88493609 | Y70: =Y69+1 -> 45707 | Z70: =Z69+1 -> 45707 | AA70: 8 | AB70: Mon | AC70: =IFERROR(AVERAGEIFS(J233:J263,D233:D263,1,G233:G263,"mon"),0) -> 50400 | AD70: =COUNTIFS(D233:D263,1,G233:G263,"Mon") -> 1 | AE70: =IFERROR(($I$14*[1]リトローボ_実績_2024R6!AI69)/AD70,0) -> 0 | AF70: =AD70*AE70 -> 0 | AG70: 233〜263
C71: 51 | D71: 1 | E71: =MONTH(Y71) -> 2 | F71: =F70+1 -> 45708 | G71: =TEXT(Z71,"ddd") -> Thu | J71: 98050 | L71: =IF(D71=0,0,$K$8) -> 87628.866 | M71: =IF(D71=0,0,J71-L71) -> 10421.134 | N71: =IFERROR(J71/L71,"¥0") -> 1.1189235 | P71: =IF(D71=0,0,SUM($L$52:L71)) -> 1402061.9 | Q71: =IF(D71=0,0,SUM($J$52:J71)) -> 1183400 | R71: =IF(D71=0,0,Q71-P71) -> -218661.86 | S71: =IF(D71=0,0,Q71/P71) -> 0.84404265 | U71: =IF(D71=0,0,SUM($L$21:L71)) -> 3329896.9 | V71: =IF(D71=0,0,SUM($J$21:J71)) -> 2967250 | W71: =IF(D71=0,0,V71-U71) -> -362646.91 | X71: =IF(D71=0,0,V71/U71) -> 0.89109365 | Y71: =Y70+1 -> 45708 | Z71: =Z70+1 -> 45708 | AA71: 8 | AB71: Tue | AC71: =IFERROR(AVERAGEIFS(J233:J263,D233:D263,1,G233:G263,"tue"),0) -> 67400 | AD71: =COUNTIFS(D233:D263,1,G233:G263,"tue") -> 2 | AE71: =($I$14*[1]リトローボ_実績_2024R6!AI70)/AD71 -> 0 | AF71: =AD71*AE71 -> 0
C72: 52 | D72: 1 | E72: =MONTH(Y72) -> 2 | F72: =F71+1 -> 45709 | G72: =TEXT(Z72,"ddd") -> Fri | J72: 90500 | L72: =IF(D72=0,0,$K$8) -> 87628.866 | M72: =IF(D72=0,0,J72-L72) -> 2871.134 | N72: =IFERROR(J72/L72,"¥0") -> 1.0327647 | P72: =IF(D72=0,0,SUM($L$52:L72)) -> 1489690.7 | Q72: =IF(D72=0,0,SUM($J$52:J72)) -> 1273900 | R72: =IF(D72=0,0,Q72-P72) -> -215790.72 | S72: =IF(D72=0,0,Q72/P72) -> 0.85514394 | U72: =IF(D72=0,0,SUM($L$21:L72)) -> 3417525.8 | V72: =IF(D72=0,0,SUM($J$21:J72)) -> 3057750 | W72: =IF(D72=0,0,V72-U72) -> -359775.77 | X72: =IF(D72=0,0,V72/U72) -> 0.89472624 | Y72: =Y71+1 -> 45709 | Z72: =Z71+1 -> 45709 | AA72: 8 | AB72: Wed | AC72: =IFERROR(AVERAGEIFS(J233:J263,D233:D263,1,G233:G263,"wed"),0) -> 78250 | AD72: =COUNTIFS(D233:D263,1,G233:G263,"wed") -> 4 | AE72: =($I$14*[1]リトローボ_実績_2024R6!AI71)/AD72 -> 0 | AF72: =AD72*AE72 -> 0
C73: 53 | D73: 1 | E73: =MONTH(Y73) -> 2 | F73: =F72+1 -> 45710 | G73: =TEXT(Z73,"ddd") -> Sat | J73: 72250 | L73: =IF(D73=0,0,$K$8) -> 87628.866 | M73: =IF(D73=0,0,J73-L73) -> -15378.866 | N73: =IFERROR(J73/L73,"¥0") -> 0.8245 | P73: =IF(D73=0,0,SUM($L$52:L73)) -> 1577319.6 | Q73: =IF(D73=0,0,SUM($J$52:J73)) -> 1346150 | R73: =IF(D73=0,0,Q73-P73) -> -231169.59 | S73: =IF(D73=0,0,Q73/P73) -> 0.8534415 | U73: =IF(D73=0,0,SUM($L$21:L73)) -> 3505154.6 | V73: =IF(D73=0,0,SUM($J$21:J73)) -> 3130000 | W73: =IF(D73=0,0,V73-U73) -> -375154.64 | X73: =IF(D73=0,0,V73/U73) -> 0.89297059 | Y73: =Y72+1 -> 45710 | Z73: =Z72+1 -> 45710 | AA73: 8 | AB73: Thu | AC73: =IFERROR(AVERAGEIFS(J233:J263,D233:D263,1,G233:G263,"thu"),0) -> 114475 | AD73: =COUNTIFS(D233:D263,1,G233:G263,"thu") -> 4 | AE73: =($I$14*[1]リトローボ_実績_2024R6!AI72)/AD73 -> 0 | AF73: =AD73*AE73 -> 0
C74: 54 | D74: 1 | E74: =MONTH(Y74) -> 2 | F74: =F73+1 -> 45711 | G74: =TEXT(Z74,"ddd") -> Sun | J74: 103250 | L74: =IF(D74=0,0,$K$8) -> 87628.866 | M74: =IF(D74=0,0,J74-L74) -> 15621.134 | N74: =IFERROR(J74/L74,"¥0") -> 1.1782647 | P74: =IF(D74=0,0,SUM($L$52:L74)) -> 1664948.5 | Q74: =IF(D74=0,0,SUM($J$52:J74)) -> 1449400 | R74: =IF(D74=0,0,Q74-P74) -> -215548.45 | S74: =IF(D74=0,0,Q74/P74) -> 0.87053746 | U74: =IF(D74=0,0,SUM($L$21:L74)) -> 3592783.5 | V74: =IF(D74=0,0,SUM($J$21:J74)) -> 3233250 | W74: =IF(D74=0,0,V74-U74) -> -359533.51 | X74: =IF(D74=0,0,V74/U74) -> 0.89992898 | Y74: =Y73+1 -> 45711 | Z74: =Z73+1 -> 45711 | AA74: 8 | AB74: Fri | AC74: =IFERROR(AVERAGEIFS(J233:J263,D233:D263,1,G233:G263,"fri"),0) -> 107355 | AD74: =COUNTIFS(D233:D263,1,G233:G263,"fri") -> 5 | AE74: =($I$14*[1]リトローボ_実績_2024R6!AI73)/AD74 -> 0 | AF74: =AD74*AE74 -> 0
C75: 55 | D75: 0 | E75: =MONTH(Y75) -> 2 | F75: =F74+1 -> 45712 | G75: =TEXT(Z75,"ddd") -> Mon | L75: =IF(D75=0,0,$K$8) -> 0 | M75: =IF(D75=0,0,J75-L75) -> 0 | N75: =IFERROR(J75/L75,"¥0") -> ¥0 | P75: =IF(D75=0,0,SUM($L$52:L75)) -> 0 | Q75: =IF(D75=0,0,SUM($J$52:J75)) -> 0 | R75: =IF(D75=0,0,Q75-P75) -> 0 | S75: =IF(D75=0,0,Q75/P75) -> 0 | U75: =IF(D75=0,0,SUM($L$21:L75)) -> 0 | V75: =IF(D75=0,0,SUM($J$21:J75)) -> 0 | W75: =IF(D75=0,0,V75-U75) -> 0 | X75: =IF(D75=0,0,V75/U75) -> 0 | Y75: =Y74+1 -> 45712 | Z75: =Z74+1 -> 45712 | AA75: 8 | AB75: Sat | AC75: =IFERROR(AVERAGEIFS(J233:J263,D233:D263,1,G233:G263,"sat"),0) -> 46630 | AD75: =COUNTIFS(D233:D263,1,G233:G263,"sat") -> 5 | AE75: =($I$14*[1]リトローボ_実績_2024R6!AI74)/AD75 -> 0 | AF75: =AD75*AE75 -> 0 | AG75: 8月目標売り上げ
C76: 56 | D76: 1 | E76: =MONTH(Y76) -> 2 | F76: =F75+1 -> 45713 | G76: =TEXT(Z76,"ddd") -> Tue | J76: 82950 | L76: =IF(D76=0,0,$K$8) -> 87628.866 | M76: =IF(D76=0,0,J76-L76) -> -4678.866 | N76: =IFERROR(J76/L76,"¥0") -> 0.94660588 | P76: =IF(D76=0,0,SUM($L$52:L76)) -> 1752577.3 | Q76: =IF(D76=0,0,SUM($J$52:J76)) -> 1532350 | R76: =IF(D76=0,0,Q76-P76) -> -220227.32 | S76: =IF(D76=0,0,Q76/P76) -> 0.87434088 | U76: =IF(D76=0,0,SUM($L$21:L76)) -> 3680412.4 | V76: =IF(D76=0,0,SUM($J$21:J76)) -> 3316200 | W76: =IF(D76=0,0,V76-U76) -> -364212.37 | X76: =IF(D76=0,0,V76/U76) -> 0.90104034 | Y76: =Y75+1 -> 45713 | Z76: =Z75+1 -> 45713 | AA76: 8 | AB76: Sun | AC76: =IFERROR(AVERAGEIFS(J233:J263,D233:D263,1,G233:G263,"sun"),0) -> 84766.667 | AD76: =IFERROR(COUNTIFS(D233:D263,1,G233:G263,"sun"),0) -> 3 | AE76: =IFERROR(($I$14*[1]リトローボ_実績_2024R6!AI75)/AD76,0) -> 0 | AF76: =SUM(AF70:AF75) -> 0 | AG76: =I14 -> 2474226.8
C77: 57 | D77: 1 | E77: =MONTH(Y77) -> 2 | F77: =F76+1 -> 45714 | G77: =TEXT(Z77,"ddd") -> Wed | J77: 81700 | L77: =IF(D77=0,0,$K$8) -> 87628.866 | M77: =IF(D77=0,0,J77-L77) -> -5928.866 | N77: =IFERROR(J77/L77,"¥0") -> 0.93234118 | P77: =IF(D77=0,0,SUM($L$52:L77)) -> 1840206.2 | Q77: =IF(D77=0,0,SUM($J$52:J77)) -> 1614050 | R77: =IF(D77=0,0,Q77-P77) -> -226156.19 | S77: =IF(D77=0,0,Q77/P77) -> 0.8771028 | U77: =IF(D77=0,0,SUM($L$21:L77)) -> 3768041.2 | V77: =IF(D77=0,0,SUM($J$21:J77)) -> 3397900 | W77: =IF(D77=0,0,V77-U77) -> -370141.24 | X77: =IF(D77=0,0,V77/U77) -> 0.90176826 | Y77: =Y76+1 -> 45714 | Z77: =Z76+1 -> 45714 | AA77: 9 | AB77: Mon | AC77: =IFERROR(AVERAGEIFS(J264:J293,D264:D293,1,G264:G293,"mon"),0) -> 0 | AD77: =COUNTIFS(D264:D293,1,G264:G293,"Mon") -> 0 | AE77: =IFERROR(($I$15*[1]リトローボ_実績_2024R6!AI76)/AD77,0) -> 0 | AF77: =AD77*AE77 -> 0 | AG77: 264〜293
C78: 58 | D78: 1 | E78: =MONTH(Y78) -> 2 | F78: =F77+1 -> 45715 | G78: =TEXT(Z78,"ddd") -> Thu | J78: 108050 | L78: =IF(D78=0,0,$K$8) -> 87628.866 | M78: =IF(D78=0,0,J78-L78) -> 20421.134 | N78: =IFERROR(J78/L78,"¥0") -> 1.2330412 | P78: =IF(D78=0,0,SUM($L$52:L78)) -> 1927835.1 | Q78: =IF(D78=0,0,SUM($J$52:J78)) -> 1722100 | R78: =IF(D78=0,0,Q78-P78) -> -205735.05 | S78: =IF(D78=0,0,Q78/P78) -> 0.89328182 | U78: =IF(D78=0,0,SUM($L$21:L78)) -> 3855670.1 | V78: =IF(D78=0,0,SUM($J$21:J78)) -> 3505950 | W78: =IF(D78=0,0,V78-U78) -> -349720.1 | X78: =IF(D78=0,0,V78/U78) -> 0.90929719 | Y78: =Y77+1 -> 45715 | Z78: =Z77+1 -> 45715 | AA78: 9 | AB78: Tue | AC78: =IFERROR(AVERAGEIFS(J264:J293,D264:D293,1,G264:G293,"tue"),0) -> 69187.5 | AD78: =COUNTIFS(D264:D293,1,G264:G293,"tue") -> 4 | AE78: =($I$15*[1]リトローボ_実績_2024R6!AI77)/AD78 -> 0 | AF78: =AD78*AE78 -> 0
C79: 59 | D79: 1 | E79: =MONTH(Y79) -> 2 | F79: =F78+1 -> 45716 | G79: =TEXT(Z79,"ddd") -> Fri | J79: 100200 | L79: =IF(D79=0,0,$K$8) -> 87628.866 | M79: =IF(D79=0,0,J79-L79) -> 12571.134 | N79: =IFERROR(J79/L79,"¥0") -> 1.1434588 | P79: =IF(D79=0,0,SUM($L$52:L79)) -> 2015463.9 | Q79: =IF(D79=0,0,SUM($J$52:J79)) -> 1822300 | R79: =IF(D79=0,0,Q79-P79) -> -193163.92 | S79: =IF(D79=0,0,Q79/P79) -> 0.90415908 | U79: =IF(D79=0,0,SUM($L$21:L79)) -> 3943299 | V79: =IF(D79=0,0,SUM($J$21:J79)) -> 3606150 | W79: =IF(D79=0,0,V79-U79) -> -337148.97 | X79: =IF(D79=0,0,V79/U79) -> 0.91450078 | Y79: =Y78+1 -> 45716 | Z79: =Z78+1 -> 45716 | AA79: 9 | AB79: Wed | AC79: =IFERROR(AVERAGEIFS(J264:J293,D264:D293,1,G264:G293,"wed"),0) -> 44000 | AD79: =COUNTIFS(D264:D293,1,G264:G293,"wed") -> 4 | AE79: =($I$15*[1]リトローボ_実績_2024R6!AI78)/AD79 -> 0 | AF79: =AD79*AE79 -> 0
C80: 60 | D80: 1 | E80: =MONTH(Y80) -> 3 | F80: =F79+1 -> 45717 | G80: =TEXT(Z80,"ddd") -> Sat | J80: 78850 | L80: =IF(D80=0,0,$K$9) -> 103092.78 | M80: =IF(D80=0,0,J80-L80) -> -24242.784 | N80: =IFERROR(J80/L80,"¥0") -> 0.764845 | P80: =IF(D80=0,0,$L$80) -> 103092.78 | Q80: =IF(D80=0,0,$J$80) -> 78850 | R80: =IF(D80=0,0,Q80-P80) -> -24242.784 | S80: =IF(D80=0,0,Q80/P80) -> 0.764845 | U80: =IF(D80=0,0,SUM($L$21:L80)) -> 4046391.8 | V80: =IF(D80=0,0,SUM($J$21:J80)) -> 3685000 | W80: =IF(D80=0,0,V80-U80) -> -361391.75 | X80: =IF(D80=0,0,V80/U80) -> 0.9106879 | Y80: =Y79+1 -> 45717 | Z80: =Z79+1 -> 45717 | AA80: 9 | AB80: Thu | AC80: =IFERROR(AVERAGEIFS(J264:J293,D264:D293,1,G264:G293,"thu"),0) -> 107550 | AD80: =COUNTIFS(D264:D293,1,G264:G293,"thu") -> 4 | AE80: =($I$15*[1]リトローボ_実績_2024R6!AI79)/AD80 -> 0 | AF80: =AD80*AE80 -> 0
C81: 61 | D81: 1 | E81: =MONTH(Y81) -> 3 | F81: =F80+1 -> 45718 | G81: =TEXT(Z81,"ddd") -> Sun | J81: 79400 | L81: =IF(D81=0,0,$K$9) -> 103092.78 | M81: =IF(D81=0,0,J81-L81) -> -23692.784 | N81: =IFERROR(J81/L81,"¥0") -> 0.77018 | P81: =IF(D81=0,0,SUM($L$80:L81)) -> 206185.57 | Q81: =IF(D81=0,0,SUM($J$80:J81)) -> 158250 | R81: =IF(D81=0,0,Q81-P81) -> -47935.567 | S81: =IF(D81=0,0,Q81/P81) -> 0.7675125 | U81: =IF(D81=0,0,SUM($L$21:L81)) -> 4149484.5 | V81: =IF(D81=0,0,SUM($J$21:J81)) -> 3764400 | W81: =IF(D81=0,0,V81-U81) -> -385084.54 | X81: =IF(D81=0,0,V81/U81) -> 0.90719702 | Y81: =Y80+1 -> 45718 | Z81: =Z80+1 -> 45718 | AA81: 9 | AB81: Fri | AC81: =IFERROR(AVERAGEIFS(J264:J293,D264:D293,1,G264:G293,"fri"),0) -> 81487.5 | AD81: =COUNTIFS(D264:D293,1,G264:G293,"fri") -> 4 | AE81: =($I$15*[1]リトローボ_実績_2024R6!AI80)/AD81 -> 0 | AF81: =AD81*AE81 -> 0
C82: 62 | D82: 0 | E82: =MONTH(Y82) -> 3 | F82: =F81+1 -> 45719 | G82: =TEXT(Z82,"ddd") -> Mon | L82: =IF(D82=0,0,$K$9) -> 0 | M82: =IF(D82=0,0,J82-L82) -> 0 | N82: =IFERROR(J82/L82,"¥0") -> ¥0 | P82: =IF(D82=0,0,SUM($L$80:L82)) -> 0 | Q82: =IF(D82=0,0,SUM($J$80:J82)) -> 0 | R82: =IF(D82=0,0,Q82-P82) -> 0 | S82: =IF(D82=0,0,Q82/P82) -> 0 | U82: =IF(D82=0,0,SUM($L$21:L82)) -> 0 | V82: =IF(D82=0,0,SUM($J$21:J82)) -> 0 | W82: =IF(D82=0,0,V82-U82) -> 0 | X82: =IF(D82=0,0,V82/U82) -> 0 | Y82: =Y81+1 -> 45719 | Z82: =Z81+1 -> 45719 | AA82: 9 | AB82: Sat | AC82: =IFERROR(AVERAGEIFS(J264:J293,D264:D293,1,G264:G293,"sat"),0) -> 69675 | AD82: =COUNTIFS(D264:D293,1,G264:G293,"sat") -> 4 | AE82: =($I$15*[1]リトローボ_実績_2024R6!AI81)/AD82 -> 0 | AF82: =AD82*AE82 -> 0 | AG82: 9月目標売り上げ
C83: 63 | D83: 1 | E83: =MONTH(Y83) -> 3 | F83: =F82+1 -> 45720 | G83: =TEXT(Z83,"ddd") -> Tue | J83: 56950 | L83: =IF(D83=0,0,$K$9) -> 103092.78 | M83: =IF(D83=0,0,J83-L83) -> -46142.784 | N83: =IFERROR(J83/L83,"¥0") -> 0.552415 | P83: =IF(D83=0,0,SUM($L$80:L83)) -> 309278.35 | Q83: =IF(D83=0,0,SUM($J$80:J83)) -> 215200 | R83: =IF(D83=0,0,Q83-P83) -> -94078.351 | S83: =IF(D83=0,0,Q83/P83) -> 0.69581333 | U83: =IF(D83=0,0,SUM($L$21:L83)) -> 4252577.3 | V83: =IF(D83=0,0,SUM($J$21:J83)) -> 3821350 | W83: =IF(D83=0,0,V83-U83) -> -431227.32 | X83: =IF(D83=0,0,V83/U83) -> 0.89859624 | Y83: =Y82+1 -> 45720 | Z83: =Z82+1 -> 45720 | AA83: 9 | AB83: Sun | AC83: =IFERROR(AVERAGEIFS(J264:J293,D264:D293,1,G264:G293,"sun"),0) -> 104233.33 | AD83: =IFERROR(COUNTIFS(D264:D293,1,G264:G293,"sun"),0) -> 3 | AE83: =IFERROR(($I$15*[1]リトローボ_実績_2024R6!AI82)/AD83,0) -> 0 | AF83: =SUM(AF77:AF82) -> 0 | AG83: =I15 -> 2371134
C84: 64 | D84: 1 | E84: =MONTH(Y84) -> 3 | F84: =F83+1 -> 45721 | G84: =TEXT(Z84,"ddd") -> Wed | J84: 15550 | L84: =IF(D84=0,0,$K$9) -> 103092.78 | M84: =IF(D84=0,0,J84-L84) -> -87542.784 | N84: =IFERROR(J84/L84,"¥0") -> 0.150835 | P84: =IF(D84=0,0,SUM($L$80:L84)) -> 412371.13 | Q84: =IF(D84=0,0,SUM($J$80:J84)) -> 230750 | R84: =IF(D84=0,0,Q84-P84) -> -181621.13 | S84: =IF(D84=0,0,Q84/P84) -> 0.55956875 | U84: =IF(D84=0,0,SUM($L$21:L84)) -> 4355670.1 | V84: =IF(D84=0,0,SUM($J$21:J84)) -> 3836900 | W84: =IF(D84=0,0,V84-U84) -> -518770.1 | X84: =IF(D84=0,0,V84/U84) -> 0.88089775 | Y84: =Y83+1 -> 45721 | Z84: =Z83+1 -> 45721 | AA84: 10 | AB84: Mon | AC84: =IFERROR(AVERAGEIFS(J294:J324,D294:D324,1,G294:G324,"mon"),0) -> 0 | AD84: =COUNTIFS(D294:D324,1,G294:G324,"Mon") -> 0 | AE84: =IFERROR(($I$16*[1]リトローボ_実績_2024R6!AI83)/AD84,0) -> 0 | AF84: =AD84*AE84 -> 0 | AG84: 294〜324
C85: 65 | D85: 1 | E85: =MONTH(Y85) -> 3 | F85: =F84+1 -> 45722 | G85: =TEXT(Z85,"ddd") -> Thu | J85: 63400 | L85: =IF(D85=0,0,$K$9) -> 103092.78 | M85: =IF(D85=0,0,J85-L85) -> -39692.784 | N85: =IFERROR(J85/L85,"¥0") -> 0.61498 | P85: =IF(D85=0,0,SUM($L$80:L85)) -> 515463.92 | Q85: =IF(D85=0,0,SUM($J$80:J85)) -> 294150 | R85: =IF(D85=0,0,Q85-P85) -> -221313.92 | S85: =IF(D85=0,0,Q85/P85) -> 0.570651 | U85: =IF(D85=0,0,SUM($L$21:L85)) -> 4458762.9 | V85: =IF(D85=0,0,SUM($J$21:J85)) -> 3900300 | W85: =IF(D85=0,0,V85-U85) -> -558462.89 | X85: =IF(D85=0,0,V85/U85) -> 0.87474936 | Y85: =Y84+1 -> 45722 | Z85: =Z84+1 -> 45722 | AA85: 10 | AB85: Tue | AC85: =IFERROR(AVERAGEIFS(J294:J324,D294:D324,1,G294:G324,"tue"),0) -> 83933.333 | AD85: =COUNTIFS(D294:D324,1,G294:G324,"tue") -> 3 | AE85: =($I$16*[1]リトローボ_実績_2024R6!AI84)/AD85 -> 0 | AF85: =AD85*AE85 -> 0
C86: 66 | D86: 1 | E86: =MONTH(Y86) -> 3 | F86: =F85+1 -> 45723 | G86: =TEXT(Z86,"ddd") -> Fri | J86: 142700 | L86: =IF(D86=0,0,$K$9) -> 103092.78 | M86: =IF(D86=0,0,J86-L86) -> 39607.216 | N86: =IFERROR(J86/L86,"¥0") -> 1.38419 | P86: =IF(D86=0,0,SUM($L$80:L86)) -> 618556.7 | Q86: =IF(D86=0,0,SUM($J$80:J86)) -> 436850 | R86: =IF(D86=0,0,Q86-P86) -> -181706.7 | S86: =IF(D86=0,0,Q86/P86) -> 0.70624083 | U86: =IF(D86=0,0,SUM($L$21:L86)) -> 4561855.7 | V86: =IF(D86=0,0,SUM($J$21:J86)) -> 4043000 | W86: =IF(D86=0,0,V86-U86) -> -518855.67 | X86: =IF(D86=0,0,V86/U86) -> 0.88626215 | Y86: =Y85+1 -> 45723 | Z86: =Z85+1 -> 45723 | AA86: 10 | AB86: Wed | AC86: =IFERROR(AVERAGEIFS(J294:J324,D294:D324,1,G294:G324,"wed"),0) -> 75750 | AD86: =COUNTIFS(D294:D324,1,G294:G324,"wed") -> 5 | AE86: =($I$16*[1]リトローボ_実績_2024R6!AI85)/AD86 -> 0 | AF86: =AD86*AE86 -> 0
C87: 67 | D87: 1 | E87: =MONTH(Y87) -> 3 | F87: =F86+1 -> 45724 | G87: =TEXT(Z87,"ddd") -> Sat | J87: 36250 | L87: =IF(D87=0,0,$K$9) -> 103092.78 | M87: =IF(D87=0,0,J87-L87) -> -66842.784 | N87: =IFERROR(J87/L87,"¥0") -> 0.351625 | P87: =IF(D87=0,0,SUM($L$80:L87)) -> 721649.48 | Q87: =IF(D87=0,0,SUM($J$80:J87)) -> 473100 | R87: =IF(D87=0,0,Q87-P87) -> -248549.48 | S87: =IF(D87=0,0,Q87/P87) -> 0.65558143 | U87: =IF(D87=0,0,SUM($L$21:L87)) -> 4664948.5 | V87: =IF(D87=0,0,SUM($J$21:J87)) -> 4079250 | W87: =IF(D87=0,0,V87-U87) -> -585698.45 | X87: =IF(D87=0,0,V87/U87) -> 0.87444696 | Y87: =Y86+1 -> 45724 | Z87: =Z86+1 -> 45724 | AA87: 10 | AB87: Thu | AC87: =IFERROR(AVERAGEIFS(J294:J324,D294:D324,1,G294:G324,"thu"),0) -> 79480 | AD87: =COUNTIFS(D294:D324,1,G294:G324,"thu") -> 5 | AE87: =($I$16*[1]リトローボ_実績_2024R6!AI86)/AD87 -> 0 | AF87: =AD87*AE87 -> 0
C88: 68 | D88: 1 | E88: =MONTH(Y88) -> 3 | F88: =F87+1 -> 45725 | G88: =TEXT(Z88,"ddd") -> Sun | J88: 105700 | L88: =IF(D88=0,0,$K$9) -> 103092.78 | M88: =IF(D88=0,0,J88-L88) -> 2607.2165 | N88: =IFERROR(J88/L88,"¥0") -> 1.02529 | P88: =IF(D88=0,0,SUM($L$80:L88)) -> 824742.27 | Q88: =IF(D88=0,0,SUM($J$80:J88)) -> 578800 | R88: =IF(D88=0,0,Q88-P88) -> -245942.27 | S88: =IF(D88=0,0,Q88/P88) -> 0.701795 | U88: =IF(D88=0,0,SUM($L$21:L88)) -> 4768041.2 | V88: =IF(D88=0,0,SUM($J$21:J88)) -> 4184950 | W88: =IF(D88=0,0,V88-U88) -> -583091.24 | X88: =IF(D88=0,0,V88/U88) -> 0.87770843 | Y88: =Y87+1 -> 45725 | Z88: =Z87+1 -> 45725 | AA88: 10 | AB88: Fri | AC88: =IFERROR(AVERAGEIFS(J294:J324,D294:D324,1,G294:G324,"fri"),0) -> 125000 | AD88: =COUNTIFS(D294:D324,1,G294:G324,"fri") -> 5 | AE88: =($I$16*[1]リトローボ_実績_2024R6!AI87)/AD88 -> 0 | AF88: =AD88*AE88 -> 0
C89: 69 | D89: 0 | E89: =MONTH(Y89) -> 3 | F89: =F88+1 -> 45726 | G89: =TEXT(Z89,"ddd") -> Mon | L89: =IF(D89=0,0,$K$9) -> 0 | M89: =IF(D89=0,0,J89-L89) -> 0 | N89: =IFERROR(J89/L89,"¥0") -> ¥0 | P89: =IF(D89=0,0,SUM($L$80:L89)) -> 0 | Q89: =IF(D89=0,0,SUM($J$80:J89)) -> 0 | R89: =IF(D89=0,0,Q89-P89) -> 0 | S89: =IF(D89=0,0,Q89/P89) -> 0 | U89: =IF(D89=0,0,SUM($L$21:L89)) -> 0 | V89: =IF(D89=0,0,SUM($J$21:J89)) -> 0 | W89: =IF(D89=0,0,V89-U89) -> 0 | X89: =IF(D89=0,0,V89/U89) -> 0 | Y89: =Y88+1 -> 45726 | Z89: =Z88+1 -> 45726 | AA89: 10 | AB89: Sat | AC89: =IFERROR(AVERAGEIFS(J294:J324,D294:D324,1,G294:G324,"sat"),0) -> 48737.5 | AD89: =COUNTIFS(D294:D324,1,G294:G324,"sat") -> 4 | AE89: =($I$16*[1]リトローボ_実績_2024R6!AI88)/AD89 -> 0 | AF89: =AD89*AE89 -> 0 | AG89: 10月目標売り上げ
C90: 70 | D90: 1 | E90: =MONTH(Y90) -> 3 | F90: =F89+1 -> 45727 | G90: =TEXT(Z90,"ddd") -> Tue | J90: 62050 | L90: =IF(D90=0,0,$K$9) -> 103092.78 | M90: =IF(D90=0,0,J90-L90) -> -41042.784 | N90: =IFERROR(J90/L90,"¥0") -> 0.601885 | P90: =IF(D90=0,0,SUM($L$80:L90)) -> 927835.05 | Q90: =IF(D90=0,0,SUM($J$80:J90)) -> 640850 | R90: =IF(D90=0,0,Q90-P90) -> -286985.05 | S90: =IF(D90=0,0,Q90/P90) -> 0.69069389 | U90: =IF(D90=0,0,SUM($L$21:L90)) -> 4871134 | V90: =IF(D90=0,0,SUM($J$21:J90)) -> 4247000 | W90: =IF(D90=0,0,V90-U90) -> -624134.02 | X90: =IF(D90=0,0,V90/U90) -> 0.8718709 | Y90: =Y89+1 -> 45727 | Z90: =Z89+1 -> 45727 | AA90: 10 | AB90: Sun | AC90: =IFERROR(AVERAGEIFS(J294:J324,D294:D324,1,G294:G324,"sun"),0) -> 68962.5 | AD90: =IFERROR(COUNTIFS(D294:D324,1,G294:G324,"sun"),0) -> 4 | AE90: =IFERROR(($I$16*[1]リトローボ_実績_2024R6!AI89)/AD90,0) -> 0 | AF90: =SUM(AF84:AF89) -> 0 | AG90: =I16 -> 2948453.6
C91: 71 | D91: 1 | E91: =MONTH(Y91) -> 3 | F91: =F90+1 -> 45728 | G91: =TEXT(Z91,"ddd") -> Wed | J91: 67300 | L91: =IF(D91=0,0,$K$9) -> 103092.78 | M91: =IF(D91=0,0,J91-L91) -> -35792.784 | N91: =IFERROR(J91/L91,"¥0") -> 0.65281 | P91: =IF(D91=0,0,SUM($L$80:L91)) -> 1030927.8 | Q91: =IF(D91=0,0,SUM($J$80:J91)) -> 708150 | R91: =IF(D91=0,0,Q91-P91) -> -322777.84 | S91: =IF(D91=0,0,Q91/P91) -> 0.6869055 | U91: =IF(D91=0,0,SUM($L$21:L91)) -> 4974226.8 | V91: =IF(D91=0,0,SUM($J$21:J91)) -> 4314300 | W91: =IF(D91=0,0,V91-U91) -> -659926.8 | X91: =IF(D91=0,0,V91/U91) -> 0.86733078 | Y91: =Y90+1 -> 45728 | Z91: =Z90+1 -> 45728 | AA91: 11 | AB91: Mon | AC91: =IFERROR(AVERAGEIFS(J325:J354,D325:D354,1,G325:G354,"mon"),0) -> 0 | AD91: =COUNTIFS(D325:D354,1,G325:G354,"Mon") -> 0 | AE91: =IFERROR(($I$17*[1]リトローボ_実績_2024R6!AI90)/AD91,0) -> 0 | AF91: =AD91*AE91 -> 0 | AG91: 325〜354
C92: 72 | D92: 1 | E92: =MONTH(Y92) -> 3 | F92: =F91+1 -> 45729 | G92: =TEXT(Z92,"ddd") -> Thu | J92: 83950 | L92: =IF(D92=0,0,$K$9) -> 103092.78 | M92: =IF(D92=0,0,J92-L92) -> -19142.784 | N92: =IFERROR(J92/L92,"¥0") -> 0.814315 | P92: =IF(D92=0,0,SUM($L$80:L92)) -> 1134020.6 | Q92: =IF(D92=0,0,SUM($J$80:J92)) -> 792100 | R92: =IF(D92=0,0,Q92-P92) -> -341920.62 | S92: =IF(D92=0,0,Q92/P92) -> 0.69848818 | U92: =IF(D92=0,0,SUM($L$21:L92)) -> 5077319.6 | V92: =IF(D92=0,0,SUM($J$21:J92)) -> 4398250 | W92: =IF(D92=0,0,V92-U92) -> -679069.59 | X92: =IF(D92=0,0,V92/U92) -> 0.86625431 | Y92: =Y91+1 -> 45729 | Z92: =Z91+1 -> 45729 | AA92: 11 | AB92: Tue | AC92: =IFERROR(AVERAGEIFS(J325:J354,D325:D354,1,G325:G354,"tue"),0) -> 0 | AD92: =COUNTIFS(D325:D354,1,G325:G354,"tue") -> 2 | AE92: =($I$17*[1]リトローボ_実績_2024R6!AI91)/AD92 -> 0 | AF92: =AD92*AE92 -> 0
C93: 73 | D93: 1 | E93: =MONTH(Y93) -> 3 | F93: =F92+1 -> 45730 | G93: =TEXT(Z93,"ddd") -> Fri | J93: 127950 | L93: =IF(D93=0,0,$K$9) -> 103092.78 | M93: =IF(D93=0,0,J93-L93) -> 24857.216 | N93: =IFERROR(J93/L93,"¥0") -> 1.241115 | P93: =IF(D93=0,0,SUM($L$80:L93)) -> 1237113.4 | Q93: =IF(D93=0,0,SUM($J$80:J93)) -> 920050 | R93: =IF(D93=0,0,Q93-P93) -> -317063.4 | S93: =IF(D93=0,0,Q93/P93) -> 0.74370708 | U93: =IF(D93=0,0,SUM($L$21:L93)) -> 5180412.4 | V93: =IF(D93=0,0,SUM($J$21:J93)) -> 4526200 | W93: =IF(D93=0,0,V93-U93) -> -654212.37 | X93: =IF(D93=0,0,V93/U93) -> 0.87371423 | Y93: =Y92+1 -> 45730 | Z93: =Z92+1 -> 45730 | AA93: 11 | AB93: Wed | AC93: =IFERROR(AVERAGEIFS(J325:J354,D325:D354,1,G325:G354,"wed"),0) -> 119950 | AD93: =COUNTIFS(D325:D354,1,G325:G354,"wed") -> 3 | AE93: =($I$17*[1]リトローボ_実績_2024R6!AI92)/AD93 -> 0 | AF93: =AD93*AE93 -> 0
C94: 74 | D94: 1 | E94: =MONTH(Y94) -> 3 | F94: =F93+1 -> 45731 | G94: =TEXT(Z94,"ddd") -> Sat | J94: 43650 | L94: =IF(D94=0,0,$K$9) -> 103092.78 | M94: =IF(D94=0,0,J94-L94) -> -59442.784 | N94: =IFERROR(J94/L94,"¥0") -> 0.423405 | P94: =IF(D94=0,0,SUM($L$80:L94)) -> 1340206.2 | Q94: =IF(D94=0,0,SUM($J$80:J94)) -> 963700 | R94: =IF(D94=0,0,Q94-P94) -> -376506.19 | S94: =IF(D94=0,0,Q94/P94) -> 0.71906846 | U94: =IF(D94=0,0,SUM($L$21:L94)) -> 5283505.2 | V94: =IF(D94=0,0,SUM($J$21:J94)) -> 4569850 | W94: =IF(D94=0,0,V94-U94) -> -713655.15 | X94: =IF(D94=0,0,V94/U94) -> 0.86492771 | Y94: =Y93+1 -> 45731 | Z94: =Z93+1 -> 45731 | AA94: 11 | AB94: Thu | AC94: =IFERROR(AVERAGEIFS(J325:J354,D325:D354,1,G325:G354,"thu"),0) -> 75150 | AD94: =COUNTIFS(D325:D354,1,G325:G354,"thu") -> 4 | AE94: =($I$17*[1]リトローボ_実績_2024R6!AI93)/AD94 -> 0 | AF94: =AD94*AE94 -> 0
C95: 75 | D95: 1 | E95: =MONTH(Y95) -> 3 | F95: =F94+1 -> 45732 | G95: =TEXT(Z95,"ddd") -> Sun | J95: 88750 | L95: =IF(D95=0,0,$K$9) -> 103092.78 | M95: =IF(D95=0,0,J95-L95) -> -14342.784 | N95: =IFERROR(J95/L95,"¥0") -> 0.860875 | P95: =IF(D95=0,0,SUM($L$80:L95)) -> 1443299 | Q95: =IF(D95=0,0,SUM($J$80:J95)) -> 1052450 | R95: =IF(D95=0,0,Q95-P95) -> -390848.97 | S95: =IF(D95=0,0,Q95/P95) -> 0.7291975 | U95: =IF(D95=0,0,SUM($L$21:L95)) -> 5386597.9 | V95: =IF(D95=0,0,SUM($J$21:J95)) -> 4658600 | W95: =IF(D95=0,0,V95-U95) -> -727997.94 | X95: =IF(D95=0,0,V95/U95) -> 0.86485014 | Y95: =Y94+1 -> 45732 | Z95: =Z94+1 -> 45732 | AA95: 11 | AB95: Fri | AC95: =IFERROR(AVERAGEIFS(J325:J354,D325:D354,1,G325:G354,"fri"),0) -> 70300 | AD95: =COUNTIFS(D325:D354,1,G325:G354,"fri") -> 4 | AE95: =($I$17*[1]リトローボ_実績_2024R6!AI94)/AD95 -> 0 | AF95: =AD95*AE95 -> 0
C96: 76 | D96: 0 | E96: =MONTH(Y96) -> 3 | F96: =F95+1 -> 45733 | G96: =TEXT(Z96,"ddd") -> Mon | L96: =IF(D96=0,0,$K$9) -> 0 | M96: =IF(D96=0,0,J96-L96) -> 0 | N96: =IFERROR(J96/L96,"¥0") -> ¥0 | P96: =IF(D96=0,0,SUM($L$80:L96)) -> 0 | Q96: =IF(D96=0,0,SUM($J$80:J96)) -> 0 | R96: =IF(D96=0,0,Q96-P96) -> 0 | S96: =IF(D96=0,0,Q96/P96) -> 0 | U96: =IF(D96=0,0,SUM($L$21:L96)) -> 0 | V96: =IF(D96=0,0,SUM($J$21:J96)) -> 0 | W96: =IF(D96=0,0,V96-U96) -> 0 | X96: =IF(D96=0,0,V96/U96) -> 0 | Y96: =Y95+1 -> 45733 | Z96: =Z95+1 -> 45733 | AA96: 11 | AB96: Sat | AC96: =IFERROR(AVERAGEIFS(J325:J354,D325:D354,1,G325:G354,"sat"),0) -> 103450 | AD96: =COUNTIFS(D325:D354,1,G325:G354,"sat") -> 5 | AE96: =($I$17*[1]リトローボ_実績_2024R6!AI95)/AD96 -> 0 | AF96: =AD96*AE96 -> 0 | AG96: 11月目標売り上げ
C97: 77 | D97: 1 | E97: =MONTH(Y97) -> 3 | F97: =F96+1 -> 45734 | G97: =TEXT(Z97,"ddd") -> Tue | J97: 71400 | L97: =IF(D97=0,0,$K$9) -> 103092.78 | M97: =IF(D97=0,0,J97-L97) -> -31692.784 | N97: =IFERROR(J97/L97,"¥0") -> 0.69258 | P97: =IF(D97=0,0,SUM($L$80:L97)) -> 1546391.8 | Q97: =IF(D97=0,0,SUM($J$80:J97)) -> 1123850 | R97: =IF(D97=0,0,Q97-P97) -> -422541.75 | S97: =IF(D97=0,0,Q97/P97) -> 0.72675633 | U97: =IF(D97=0,0,SUM($L$21:L97)) -> 5489690.7 | V97: =IF(D97=0,0,SUM($J$21:J97)) -> 4730000 | W97: =IF(D97=0,0,V97-U97) -> -759690.72 | X97: =IF(D97=0,0,V97/U97) -> 0.86161502 | Y97: =Y96+1 -> 45734 | Z97: =Z96+1 -> 45734 | AA97: 11 | AB97: Sun | AC97: =IFERROR(AVERAGEIFS(J325:J354,D325:D354,1,G325:G354,"sun"),0) -> 67275 | AD97: =IFERROR(COUNTIFS(D325:D354,1,G325:G354,"sun"),0) -> 4 | AE97: =IFERROR(($I$17*[1]リトローボ_実績_2024R6!AI96)/AD97,0) -> 0 | AF97: =SUM(AF91:AF96) -> 0 | AG97: =I17 -> 2268041.2
C98: 78 | D98: 1 | E98: =MONTH(Y98) -> 3 | F98: =F97+1 -> 45735 | G98: =TEXT(Z98,"ddd") -> Wed | J98: 58150 | L98: =IF(D98=0,0,$K$9) -> 103092.78 | M98: =IF(D98=0,0,J98-L98) -> -44942.784 | N98: =IFERROR(J98/L98,"¥0") -> 0.564055 | P98: =IF(D98=0,0,SUM($L$80:L98)) -> 1649484.5 | Q98: =IF(D98=0,0,SUM($J$80:J98)) -> 1182000 | R98: =IF(D98=0,0,Q98-P98) -> -467484.54 | S98: =IF(D98=0,0,Q98/P98) -> 0.7165875 | U98: =IF(D98=0,0,SUM($L$21:L98)) -> 5592783.5 | V98: =IF(D98=0,0,SUM($J$21:J98)) -> 4788150 | W98: =IF(D98=0,0,V98-U98) -> -804633.51 | X98: =IF(D98=0,0,V98/U98) -> 0.85613005 | Y98: =Y97+1 -> 45735 | Z98: =Z97+1 -> 45735 | AA98: 12 | AB98: Mon | AC98: =IFERROR(AVERAGEIFS(J355:J385,D355:D385,1,G355:G385,"mon"),0) -> 0 | AD98: =COUNTIFS(D355:D385,1,G355:G385,"Mon") -> 0 | AE98: =IFERROR(($I$18*[1]リトローボ_実績_2024R6!AI97)/AD98,0) -> 0 | AF98: =AD98*AE98 -> 0 | AG98: 355〜385
C99: 79 | D99: 1 | E99: =MONTH(Y99) -> 3 | F99: =F98+1 -> 45736 | G99: =TEXT(Z99,"ddd") -> Thu | J99: 73100 | L99: =IF(D99=0,0,$K$9) -> 103092.78 | M99: =IF(D99=0,0,J99-L99) -> -29992.784 | N99: =IFERROR(J99/L99,"¥0") -> 0.70907 | P99: =IF(D99=0,0,SUM($L$80:L99)) -> 1752577.3 | Q99: =IF(D99=0,0,SUM($J$80:J99)) -> 1255100 | R99: =IF(D99=0,0,Q99-P99) -> -497477.32 | S99: =IF(D99=0,0,Q99/P99) -> 0.71614529 | U99: =IF(D99=0,0,SUM($L$21:L99)) -> 5695876.3 | V99: =IF(D99=0,0,SUM($J$21:J99)) -> 4861250 | W99: =IF(D99=0,0,V99-U99) -> -834626.29 | X99: =IF(D99=0,0,V99/U99) -> 0.85346833 | Y99: =Y98+1 -> 45736 | Z99: =Z98+1 -> 45736 | AA99: 12 | AB99: Tue | AC99: =IFERROR(AVERAGEIFS(J355:J385,D355:D385,1,G355:G385,"tue"),0) -> 0 | AD99: =COUNTIFS(D355:D385,1,G355:G385,"tue") -> 4 | AE99: =($I$18*[1]リトローボ_実績_2024R6!AI98)/AD99 -> 0 | AF99: =AD99*AE99 -> 0
C100: 80 | D100: 1 | E100: =MONTH(Y100) -> 3 | F100: =F99+1 -> 45737 | G100: =TEXT(Z100,"ddd") -> Fri | J100: 104250 | L100: =IF(D100=0,0,$K$9) -> 103092.78 | M100: =IF(D100=0,0,J100-L100) -> 1157.2165 | N100: =IFERROR(J100/L100,"¥0") -> 1.011225 | P100: =IF(D100=0,0,SUM($L$80:L100)) -> 1855670.1 | Q100: =IF(D100=0,0,SUM($J$80:J100)) -> 1359350 | R100: =IF(D100=0,0,Q100-P100) -> -496320.1 | S100: =IF(D100=0,0,Q100/P100) -> 0.73253861 | U100: =IF(D100=0,0,SUM($L$21:L100)) -> 5798969.1 | V100: =IF(D100=0,0,SUM($J$21:J100)) -> 4965500 | W100: =IF(D100=0,0,V100-U100) -> -833469.07 | X100: =IF(D100=0,0,V100/U100) -> 0.85627289 | Y100: =Y99+1 -> 45737 | Z100: =Z99+1 -> 45737 | AA100: 12 | AB100: Wed | AC100: =IFERROR(AVERAGEIFS(J355:J385,D355:D385,1,G355:G385,"wed"),0) -> 0 | AD100: =COUNTIFS(D355:D385,1,G355:G385,"wed") -> 4 | AE100: =($I$18*[1]リトローボ_実績_2024R6!AI99)/AD100 -> 0 | AF100: =AD100*AE100 -> 0
C101: 81 | D101: 1 | E101: =MONTH(Y101) -> 3 | F101: =F100+1 -> 45738 | G101: =TEXT(Z101,"ddd") -> Sat | J101: 103550 | L101: =IF(D101=0,0,$K$9) -> 103092.78 | M101: =IF(D101=0,0,J101-L101) -> 457.21649 | N101: =IFERROR(J101/L101,"¥0") -> 1.004435 | P101: =IF(D101=0,0,SUM($L$80:L101)) -> 1958762.9 | Q101: =IF(D101=0,0,SUM($J$80:J101)) -> 1462900 | R101: =IF(D101=0,0,Q101-P101) -> -495862.89 | S101: =IF(D101=0,0,Q101/P101) -> 0.74684895 | U101: =IF(D101=0,0,SUM($L$21:L101)) -> 5902061.9 | V101: =IF(D101=0,0,SUM($J$21:J101)) -> 5069050 | W101: =IF(D101=0,0,V101-U101) -> -833011.86 | X101: =IF(D101=0,0,V101/U101) -> 0.85886087 | Y101: =Y100+1 -> 45738 | Z101: =Z100+1 -> 45738 | AA101: 12 | AB101: Thu | AC101: =IFERROR(AVERAGEIFS(J355:J385,D355:D385,1,G355:G385,"thu"),0) -> 0 | AD101: =COUNTIFS(D355:D385,1,G355:G385,"thu") -> 4 | AE101: =($I$18*[1]リトローボ_実績_2024R6!AI100)/AD101 -> 0 | AF101: =AD101*AE101 -> 0
C102: 82 | D102: 1 | E102: =MONTH(Y102) -> 3 | F102: =F101+1 -> 45739 | G102: =TEXT(Z102,"ddd") -> Sun | J102: 117250 | L102: =IF(D102=0,0,$K$9) -> 103092.78 | M102: =IF(D102=0,0,J102-L102) -> 14157.216 | N102: =IFERROR(J102/L102,"¥0") -> 1.137325 | P102: =IF(D102=0,0,SUM($L$80:L102)) -> 2061855.7 | Q102: =IF(D102=0,0,SUM($J$80:J102)) -> 1580150 | R102: =IF(D102=0,0,Q102-P102) -> -481705.67 | S102: =IF(D102=0,0,Q102/P102) -> 0.76637275 | U102: =IF(D102=0,0,SUM($L$21:L102)) -> 6005154.6 | V102: =IF(D102=0,0,SUM($J$21:J102)) -> 5186300 | W102: =IF(D102=0,0,V102-U102) -> -818854.64 | X102: =IF(D102=0,0,V102/U102) -> 0.86364137 | Y102: =Y101+1 -> 45739 | Z102: =Z101+1 -> 45739 | AA102: 12 | AB102: Fri | AC102: =IFERROR(AVERAGEIFS(J355:J385,D355:D385,1,G355:G385,"fri"),0) -> 0 | AD102: =COUNTIFS(D355:D385,1,G355:G385,"fri") -> 4 | AE102: =($I$18*[1]リトローボ_実績_2024R6!AI101)/AD102 -> 0 | AF102: =AD102*AE102 -> 0
C103: 83 | D103: 0 | E103: =MONTH(Y103) -> 3 | F103: =F102+1 -> 45740 | G103: =TEXT(Z103,"ddd") -> Mon | L103: =IF(D103=0,0,$K$9) -> 0 | M103: =IF(D103=0,0,J103-L103) -> 0 | N103: =IFERROR(J103/L103,"¥0") -> ¥0 | P103: =IF(D103=0,0,SUM($L$80:L103)) -> 0 | Q103: =IF(D103=0,0,SUM($J$80:J103)) -> 0 | R103: =IF(D103=0,0,Q103-P103) -> 0 | S103: =IF(D103=0,0,Q103/P103) -> 0 | U103: =IF(D103=0,0,SUM($L$21:L103)) -> 0 | V103: =IF(D103=0,0,SUM($J$21:J103)) -> 0 | W103: =IF(D103=0,0,V103-U103) -> 0 | X103: =IF(D103=0,0,V103/U103) -> 0 | Y103: =Y102+1 -> 45740 | Z103: =Z102+1 -> 45740 | AA103: 12 | AB103: Sat | AC103: =IFERROR(AVERAGEIFS(J355:J385,D355:D385,1,G355:G385,"sat"),0) -> 0 | AD103: =COUNTIFS(D355:D385,1,G355:G385,"sat") -> 4 | AE103: =($I$18*[1]リトローボ_実績_2024R6!AI102)/AD103 -> 0 | AF103: =AD103*AE103 -> 0 | AG103: 12月目標売り上げ
...

Sheet 実績_2024R6
B2: 45292 | E2: ①年間営業日 | G2: ②年間目標売上 | I2: 年間売上％設定 | M2: 年間売上合計 | O2: 年間実質売上 | Q2: 年間利益率 | R2: 年間予想利益額
E3: =SUM(F6:F17) -> 291 | G3: =M3 -> 29397780 | I3: =SUM(AD6:AD17)*100 -> 0.9999996 | K3: =G3*I3 -> 29397768 | M3: =SUM(J20:J385) -> 29397780 | O3: =M3-G3 -> 0 | Q3: 0.21 | R3: =M3*Q3 -> 6173533.8
B5: 平均日次売上目標額 | E5: 月 | F5: 月次営業日数 | G5: 平均月間売上目標額 | H5: 月次繁閑期%設定 | J5: 月次目標売上 | K5: 日次目標売上 | M5: 月次売上 | N5: 月間差額 | P5: 月次実質% | R5: 1日の売上目標値 参考例 | AC5: =TEXT(K6,"¥0") -> ¥90921
B6: ② ÷ ① | E6: 1月 | F6: =COUNTIF(D20:D50,1) -> 21 | G6: =$B$7*F6 -> 2121489.3 | H6: 0.9 | J6: =G6*H6 -> 1909340.4 | K6: =J6/F6 -> 90920.969 | M6: =SUM(J20:J50) -> 1903700 | N6: =M6-J6 -> -5640.3505 | P6: =M6/G6 -> 0.89734132 | R6: 目標売上 | T6: ¥233564 | V6: 0.76 | AC6: =TEXT(K7,"¥0") -> ¥85870 | AD6: =(H6/100)*AE6 -> 0.0007499997 | AE6: 0.0833333
B7: =G3/E3 -> 101023.3 | E7: 2月 | F7: =COUNTIF(D51:D79,1) -> 25 | G7: =$B$7*F7 -> 2525582.5 | H7: 0.85 | J7: =G7*H7 -> 2146745.1 | K7: =J7/F7 -> 85869.804 | M7: =SUM(J51:J79) -> 2252350 | N7: =M7-J7 -> 105604.9 | P7: =M7/G7 -> 0.89181408 | T7: =T6*V6 -> 177508.64 | AC7: =TEXT(K8,"¥0") -> ¥101023 | AD7: =(H7/100)*AE7 -> 0.00070833305 | AE7: 0.0833333
E8: 3月 | F8: =COUNTIF(D80:D110,1) -> 25 | G8: =$B$7*F8 -> 2525582.5 | H8: 1 | J8: =G8*H8 -> 2525582.5 | K8: =J8/F8 -> 101023.3 | M8: =SUM(J80:J110) -> 2500050 | N8: =M8-J8 -> -25532.474 | P8: =M8/G8 -> 0.98989046 | R8: 差額 | T8: =T9-T6 -> 87436 | AC8: =TEXT(K9,"¥0") -> ¥106074 | AD8: =(H8/100)*AE8 -> 0.000833333 | AE8: 0.0833333
E9: 4月 | F9: =COUNTIF(D111:D140,1) -> 25 | G9: =$B$7*F9 -> 2525582.5 | H9: 1.05 | J9: =G9*H9 -> 2651861.6 | K9: =J9/F9 -> 106074.46 | M9: =SUM(J111:J140) -> 2732600 | N9: =M9-J9 -> 80738.402 | P9: =M9/G9 -> 1.0819682 | R9: 仮1日売上総合計 | T9: =SUM(V11:V16) -> 321000 | AC9: =TEXT(K10,"¥0") -> ¥101023 | AD9: =(H9/100)*AE9 -> 0.00087499965 | AE9: 0.0833333
E10: 5月 | F10: =COUNTIF(D141:D171,1) -> 25 | G10: =$B$7*F10 -> 2525582.5 | H10: 1 | J10: =G10*H10 -> 2525582.5 | K10: =J10/F10 -> 101023.3 | M10: =SUM(J141:J171) -> 2920150 | N10: =M10-J10 -> 394567.53 | P10: =M10/G10 -> 1.1562283 | R10: 項目 | S10: 仮客単価 | T10: 集客数 | V10: 仮1日の売上小計 | AC10: =TEXT(K11,"¥0") -> ¥90921 | AD10: =(H10/100)*AE10 -> 0.000833333 | AE10: 0.0833333
E11: 6月 | F11: =COUNTIF(D172:D201,1) -> 26 | G11: =$B$7*F11 -> 2626605.8 | H11: 0.9 | J11: =G11*H11 -> 2363945.2 | K11: =J11/F11 -> 90920.969 | M11: =SUM(J172:J201) -> 3064200 | N11: =M11-J11 -> 700254.8 | P11: =M11/G11 -> 1.1666006 | R11: ランチ | S11: 1100 | T11: 60 | V11: =S11*T11 -> 66000 | AC11: =TEXT(K12,"¥0") -> ¥95972 | AD11: =(H11/100)*AE11 -> 0.0007499997 | AE11: 0.0833333
E12: 7月 | F12: =COUNTIF(D202:D232,1) -> 25 | G12: =$B$7*F12 -> 2525582.5 | H12: 0.95 | J12: =G12*H12 -> 2399303.4 | K12: =J12/F12 -> 95972.134 | M12: =SUM(J202:J232) -> 2392050 | N12: =M12-J12 -> -7253.3505 | P12: =M12/G12 -> 0.94712805 | R12: ディナー | S12: 4500 | T12: 20 | V12: =S12*T12 -> 90000 | AC12: =TEXT(K13,"¥0") -> ¥80819 | AD12: =(H12/100)*AE12 -> 0.00079166635 | AE12: 0.0833333
E13: 8月 | F13: =COUNTIF(D233:D263,1) -> 22 | G13: =$B$7*F13 -> 2222512.6 | H13: 0.8 | J13: =G13*H13 -> 1778010.1 | K13: =J13/F13 -> 80818.639 | M13: =SUM(J233:J263) -> 2064530 | N13: =M13-J13 -> 286519.94 | P13: =M13/G13 -> 0.92891713 | R13: Party 5500 | S13: 5500 | T13: 30 | V13: =S13*T13 -> 165000 | AC13: =TEXT(K14,"¥0") -> ¥95972 | AD13: =(H13/100)*AE13 -> 0.0006666664 | AE13: 0.0833333
E14: 9 月 | F14: =COUNTIF(D264:D293,1) -> 23 | G14: =$B$7*F14 -> 2323535.9 | H14: 0.95 | J14: =G14*H14 -> 2207359.1 | K14: =J14/F14 -> 95972.134 | M14: =SUM(J264:J293) -> 2319650 | N14: =M14-J14 -> 112290.92 | P14: =M14/G14 -> 0.9983276 | T14: 0 | V14: =S14*T14 -> 0 | AC14: =TEXT(K15,"¥0") -> ¥126279 | AD14: =(H14/100)*AE14 -> 0.00079166635 | AE14: 0.0833333
E15: 10月 | F15: =COUNTIF(D294:D324,1) -> 26 | G15: =$B$7*F15 -> 2626605.8 | H15: 1.25 | J15: =G15*H15 -> 3283257.2 | K15: =J15/F15 -> 126279.12 | M15: =SUM(J294:J324) -> 2672000 | N15: =M15-J15 -> -611257.22 | P15: =M15/G15 -> 1.0172825 | T15: 0 | V15: =S15*T15 -> 0 | AC15: =TEXT(K16,"¥0") -> ¥106074 | AD15: =(H15/100)*AE15 -> 0.0010416662 | AE15: 0.0833333
E16: 11月 | F16: =COUNTIF(D325:D354,1) -> 24 | G16: =$B$7*F16 -> 2424559.2 | H16: 1.05 | J16: =G16*H16 -> 2545787.1 | K16: =J16/F16 -> 106074.46 | M16: =SUM(J325:J354) -> 2210250 | N16: =M16-J16 -> -335537.13 | P16: =M16/G16 -> 0.91160901 | T16: 0 | V16: =S16*T16 -> 0 | AC16: =TEXT(K17,"¥0") -> ¥131330 | AD16: =(H16/100)*AE16 -> 0.00087499965 | AE16: 0.0833333
E17: 12月 | F17: =COUNTIF(D355:D385,1) -> 24 | G17: =$B$7*F17 -> 2424559.2 | H17: 1.3 | J17: =G17*H17 -> 3151926.9 | K17: =J17/F17 -> 131330.29 | M17: =SUM(J355:J385) -> 2366250 | N17: =M17-J17 -> -785676.93 | P17: =M17/G17 -> 0.97595061 | AD17: =(H17/100)*AE17 -> 0.0010833329 | AE17: 0.0833333
E19: 月 | F19: 日程 | G19: 曜日 | H19: 休店日理由 | J19: Daily売上入力 | L19: 目標売上 KPI | M19: 日次実質売上 | N19: 実質% | P19: 月次目標売上 | Q19: 月次実質売上 | R19: 月次差額(勝率) | S19: 月次実質% | U19: 年次目標売上 | V19: 年次実質売上 | W19: 年次差額(勝率) | X19: 年次実質% | AC19: 月 | AD19: 曜日 | AE19: 平均売上 | AF19: 曜日回数 | AH19: 曜日合計額 | AI19: 加重比率
C20: 1 | D20: 0 | E20: =TEXT(AA20,"m") -> 1 | F20: =B2 -> 45292 | G20: =TEXT(Z20,"ddd") -> Mon | H20: 元旦 | J20: 0 | L20: =IF(D20=0,0,$K$6) -> 0 | M20: =IF(D20=0,0,J20-L20) -> 0 | N20: =IFERROR(J20/L20,"0%") -> 0% | P20: =IF(D20=0,0,$K$6) -> 0 | Q20: =IF(D20=0,0,$J$20) -> 0 | R20: =IF(D20=0,0,Q20-P20) -> 0 | S20: =IFERROR(Q20/P20,"0%") -> 0% | U20: =IF(D20=0,0,$L$20) -> 0 | V20: =IF(D20=0,0,$J$20) -> 0 | W20: =IF(D20=0,0,V20-U20) -> 0 | X20: =IFERROR(V20/U20,"0%") -> 0% | Z20: =B2 -> 45292 | AA20: =B2 -> 45292 | AB20: 45292 | AC20: 1 | AD20: 月 | AE20: =IFERROR(AVERAGEIFS(J20:J50,D20:D50,1,G20:G50,"mon"),0) -> 0 | AF20: =COUNTIFS(D20:D50,1,G20:G50,"Mon") -> 0 | AG20: =SUMIFS(J20:J50,D20:D50,1,G20:G50,"mon") -> 0 | AH20: =AE20*AF20 -> 0 | AI20: =AH20/$M$6 -> 0 | AJ20: =SUM(AI20:AI26) -> 1
C21: =C20+1 -> 2 | D21: 0 | E21: =TEXT(AA21,"m") -> 1 | F21: =F20+1 -> 45293 | G21: =TEXT(Z21,"ddd") -> Tue | H21: 休み | J21: 0 | L21: =IF(D21=0,0,$K$6) -> 0 | M21: =IF(D21=0,0,J21-L21) -> 0 | N21: =IFERROR(J21/L21,"0%") -> 0% | P21: =IF(D21=0,0,SUM($L$20:L21)) -> 0 | Q21: =IF(D21=0,0,SUM($J$20:J21)) -> 0 | R21: =IF(D21=0,0,Q21-P21) -> 0 | S21: =IFERROR(Q21/P21,"0%") -> 0% | U21: =IF(D21=0,0,SUM($L$20:L21)) -> 0 | V21: =IF(D21=0,0,SUM($J$20:J21)) -> 0 | W21: =IF(D21=0,0,V21-U21) -> 0 | X21: =IFERROR(V21/U21,"0%") -> 0% | Z21: =Z20+1 -> 45293 | AA21: =AA20+1 -> 45293 | AB21: 45293 | AC21: 1 | AD21: 火 | AE21: =IFERROR(AVERAGEIFS(J20:J50,D20:D50,1,G20:G50,"tue"),0) -> 88337.5 | AF21: =COUNTIFS(D20:D50,1,G20:G50,"Tue") -> 4 | AH21: =AE21*AF21 -> 353350 | AI21: =AH21/$M$6 -> 0.18561223
C22: =C21+1 -> 3 | D22: 0 | E22: =TEXT(AA22,"m") -> 1 | F22: =F21+1 -> 45294 | G22: =TEXT(Z22,"ddd") -> Wed | H22: 休み | J22: 0 | L22: =IF(D22=0,0,$K$6) -> 0 | M22: =IF(D22=0,0,J22-L22) -> 0 | N22: =IFERROR(J22/L22,"0%") -> 0% | P22: =IF(D22=0,0,SUM($L$20:L22)) -> 0 | Q22: =IF(D22=0,0,SUM($J$20:J22)) -> 0 | R22: =IF(D22=0,0,Q22-P22) -> 0 | S22: =IFERROR(Q22/P22,"0%") -> 0% | U22: =IF(D22=0,0,SUM($L$20:L22)) -> 0 | V22: =IF(D22=0,0,SUM($J$20:J22)) -> 0 | W22: =IF(D22=0,0,V22-U22) -> 0 | X22: =IFERROR(V22/U22,"0%") -> 0% | Z22: =Z21+1 -> 45294 | AA22: =AA21+1 -> 45294 | AB22: 45294 | AC22: 1 | AD22: 水 | AE22: =IFERROR(AVERAGEIFS(J20:J50,D20:D50,1,G20:G50,"wed"),0) -> 90283.333 | AF22: =COUNTIFS(D20:D50,1,G20:G50,"wed") -> 3 | AH22: =AE22*AF22 -> 270850 | AI22: =AH22/$M$6 -> 0.14227557
C23: =C22+1 -> 4 | D23: 0 | E23: =TEXT(AA23,"m") -> 1 | F23: =F22+1 -> 45295 | G23: =TEXT(Z23,"ddd") -> Thu | H23: 祝日 | J23: 0 | L23: =IF(D23=0,0,$K$6) -> 0 | M23: =IF(D23=0,0,J23-L23) -> 0 | N23: =IFERROR(J23/L23,"0%") -> 0% | P23: =IF(D23=0,0,SUM($L$20:L23)) -> 0 | Q23: =IF(D23=0,0,SUM($J$20:J23)) -> 0 | R23: =IF(D23=0,0,Q23-P23) -> 0 | S23: =IFERROR(Q23/P23,"0%") -> 0% | U23: =IF(D23=0,0,SUM($L$20:L23)) -> 0 | V23: =IF(D23=0,0,SUM($J$20:J23)) -> 0 | W23: =IF(D23=0,0,V23-U23) -> 0 | X23: =IFERROR(V23/U23,"0%") -> 0% | Z23: =Z22+1 -> 45295 | AA23: =AA22+1 -> 45295 | AB23: 45295 | AC23: 1 | AD23: 木 | AE23: =IFERROR(AVERAGEIFS(J20:J50,D20:D50,1,G20:G50,"thu"),0) -> 56700 | AF23: =COUNTIFS(D20:D50,1,G20:G50,"thu") -> 3 | AH23: =AE23*AF23 -> 170100 | AI23: =AH23/$M$6 -> 0.089352314
C24: =C23+1 -> 5 | D24: 1 | E24: =TEXT(AA24,"m") -> 1 | F24: =F23+1 -> 45296 | G24: =TEXT(Z24,"ddd") -> Fri | J24: 122350 | L24: =IF(D24=0,0,$K$6) -> 90920.969 | M24: =IF(D24=0,0,J24-L24) -> 31429.031 | N24: =IFERROR(J24/L24,"0%") -> 1.3456742 | P24: =IF(D24=0,0,SUM($L$20:L24)) -> 90920.969 | Q24: =IF(D24=0,0,SUM($J$20:J24)) -> 122350 | R24: =IF(D24=0,0,Q24-P24) -> 31429.031 | S24: =IFERROR(Q24/P24,"0%") -> 1.3456742 | U24: =IF(D24=0,0,SUM($L$20:L24)) -> 90920.969 | V24: =IF(D24=0,0,SUM($J$20:J24)) -> 122350 | W24: =IF(D24=0,0,V24-U24) -> 31429.031 | X24: =IFERROR(V24/U24,"0%") -> 1.3456742 | Z24: =Z23+1 -> 45296 | AA24: =AA23+1 -> 45296 | AB24: 45296 | AC24: 1 | AD24: 金 | AE24: =IFERROR(AVERAGEIFS(J20:J50,D20:D50,1,G20:G50,"fri"),0) -> 128412.5 | AF24: =COUNTIFS(D20:D50,1,G20:G50,"fri") -> 4 | AH24: =AE24*AF24 -> 513650 | AI24: =AH24/$M$6 -> 0.26981667
C25: =C24+1 -> 6 | D25: 0 | E25: =TEXT(AA25,"m") -> 1 | F25: =F24+1 -> 45297 | G25: =TEXT(Z25,"ddd") -> Sat | J25: 0 | L25: =IF(D25=0,0,$K$6) -> 0 | M25: =IF(D25=0,0,J25-L25) -> 0 | N25: =IFERROR(J25/L25,"0%") -> 0% | P25: =IF(D25=0,0,SUM($L$20:L25)) -> 0 | Q25: =IF(D25=0,0,SUM($J$20:J25)) -> 0 | R25: =IF(D25=0,0,Q25-P25) -> 0 | S25: =IFERROR(Q25/P25,"0%") -> 0% | U25: =IF(D25=0,0,SUM($L$20:L25)) -> 0 | V25: =IF(D25=0,0,SUM($J$20:J25)) -> 0 | W25: =IF(D25=0,0,V25-U25) -> 0 | X25: =IFERROR(V25/U25,"0%") -> 0% | Z25: =Z24+1 -> 45297 | AA25: =AA24+1 -> 45297 | AB25: 45297 | AC25: 1 | AD25: 土 | AE25: =IFERROR(AVERAGEIFS(J20:J50,D20:D50,1,G20:G50,"sat"),0) -> 80700 | AF25: =COUNTIFS(D20:D50,1,G20:G50,"sat") -> 3 | AH25: =AE25*AF25 -> 242100 | AI25: =AH25/$M$6 -> 0.1271734
C26: =C25+1 -> 7 | D26: 1 | E26: =TEXT(AA26,"m") -> 1 | F26: =F25+1 -> 45298 | G26: =TEXT(Z26,"ddd") -> Sun | H26: 日曜日 | J26: 63100 | L26: =IF(D26=0,0,$K$6) -> 90920.969 | M26: =IF(D26=0,0,J26-L26) -> -27820.969 | N26: =IFERROR(J26/L26,"0%") -> 0.69400932 | P26: =IF(D26=0,0,SUM($L$20:L26)) -> 181841.94 | Q26: =IF(D26=0,0,SUM($J$20:J26)) -> 185450 | R26: =IF(D26=0,0,Q26-P26) -> 3608.0619 | S26: =IFERROR(Q26/P26,"0%") -> 1.0198417 | U26: =IF(D26=0,0,SUM($L$20:L26)) -> 181841.94 | V26: =IF(D26=0,0,SUM($J$20:J26)) -> 185450 | W26: =IF(D26=0,0,V26-U26) -> 3608.0619 | X26: =IFERROR(V26/U26,"0%") -> 1.0198417 | Z26: =Z25+1 -> 45298 | AA26: =AA25+1 -> 45298 | AB26: 45298 | AC26: 1 | AD26: 日 | AE26: =IFERROR(AVERAGEIFS(J20:J50,D20:D50,1,G20:G50,"sun"),0) -> 88412.5 | AF26: =IFERROR(COUNTIFS(D20:D50,1,G20:G50,"sun"),0) -> 4 | AH26: =AE26*AF26 -> 353650 | AI26: =AH26/$M$6 -> 0.18576982
C27: =C26+1 -> 8 | D27: 0 | E27: =TEXT(AA27,"m") -> 1 | F27: =F26+1 -> 45299 | G27: =TEXT(Z27,"ddd") -> Mon | L27: =IF(D27=0,0,$K$6) -> 0 | M27: =IF(D27=0,0,J27-L27) -> 0 | N27: =IFERROR(J27/L27,"0%") -> 0% | P27: =IF(D27=0,0,SUM($L$20:L27)) -> 0 | Q27: =IF(D27=0,0,SUM($J$20:J27)) -> 0 | R27: =IF(D27=0,0,Q27-P27) -> 0 | S27: =IFERROR(Q27/P27,"0%") -> 0% | U27: =IF(D27=0,0,SUM($L$20:L27)) -> 0 | V27: =IF(D27=0,0,SUM($J$20:J27)) -> 0 | W27: =IF(D27=0,0,V27-U27) -> 0 | X27: =IFERROR(V27/U27,"0%") -> 0% | Z27: =Z26+1 -> 45299 | AA27: =AA26+1 -> 45299 | AB27: 45299 | AC27: 2 | AD27: 月 | AE27: =IFERROR(AVERAGEIFS(J51:J79,D51:D79,1,G51:G79,"mon"),0) -> 0 | AF27: =COUNTIFS(D51:D79,1,G51:G79,"Mon") -> 0 | AH27: =AE27*AF27 -> 0 | AI27: =AH27/$M$7 -> 0 | AJ27: =SUM(AI27:AI33) -> 1 | AK27: 51〜79
C28: =C27+1 -> 9 | D28: 1 | E28: =TEXT(AA28,"m") -> 1 | F28: =F27+1 -> 45300 | G28: =TEXT(Z28,"ddd") -> Tue | J28: 130500 | L28: =IF(D28=0,0,$K$6) -> 90920.969 | M28: =IF(D28=0,0,J28-L28) -> 39579.031 | N28: =IFERROR(J28/L28,"0%") -> 1.4353125 | P28: =IF(D28=0,0,SUM($L$20:L28)) -> 272762.91 | Q28: =IF(D28=0,0,SUM($J$20:J28)) -> 315950 | R28: =IF(D28=0,0,Q28-P28) -> 43187.093 | S28: =IFERROR(Q28/P28,"0%") -> 1.158332 | U28: =IF(D28=0,0,SUM($L$20:L28)) -> 272762.91 | V28: =IF(D28=0,0,SUM($J$20:J28)) -> 315950 | W28: =IF(D28=0,0,V28-U28) -> 43187.093 | X28: =IFERROR(V28/U28,"0%") -> 1.158332 | Z28: =Z27+1 -> 45300 | AA28: =AA27+1 -> 45300 | AB28: 45300 | AC28: 2 | AD28: 火 | AE28: =AVERAGEIFS(J51:J79,D51:D79,1,G51:G79,"tue") -> 66212.5 | AF28: =COUNTIFS(D51:D79,1,G51:G79,"tue") -> 4 | AH28: =AE28*AF28 -> 264850 | AI28: =AH28/$M$7 -> 0.1175883
C29: =C28+1 -> 10 | D29: 1 | E29: =TEXT(AA29,"m") -> 1 | F29: =F28+1 -> 45301 | G29: =TEXT(Z29,"ddd") -> Wed | J29: 106200 | L29: =IF(D29=0,0,$K$6) -> 90920.969 | M29: =IF(D29=0,0,J29-L29) -> 15279.031 | N29: =IFERROR(J29/L29,"0%") -> 1.1680474 | P29: =IF(D29=0,0,SUM($L$20:L29)) -> 363683.88 | Q29: =IF(D29=0,0,SUM($J$20:J29)) -> 422150 | R29: =IF(D29=0,0,Q29-P29) -> 58466.124 | S29: =IFERROR(Q29/P29,"0%") -> 1.1607608 | U29: =IF(D29=0,0,SUM($L$20:L29)) -> 363683.88 | V29: =IF(D29=0,0,SUM($J$20:J29)) -> 422150 | W29: =IF(D29=0,0,V29-U29) -> 58466.124 | X29: =IFERROR(V29/U29,"0%") -> 1.1607608 | Z29: =Z28+1 -> 45301 | AA29: =AA28+1 -> 45301 | AB29: 45301 | AC29: 2 | AD29: 水 | AE29: =AVERAGEIFS(J51:J79,D51:D79,1,G51:G79,"wed") -> 86962.5 | AF29: =COUNTIFS(D51:D79,1,G51:G79,"wed") -> 4 | AH29: =AE29*AF29 -> 347850 | AI29: =AH29/$M$7 -> 0.1544387
C30: =C29+1 -> 11 | D30: 1 | E30: =TEXT(AA30,"m") -> 1 | F30: =F29+1 -> 45302 | G30: =TEXT(Z30,"ddd") -> Thu | J30: 61950 | L30: =IF(D30=0,0,$K$6) -> 90920.969 | M30: =IF(D30=0,0,J30-L30) -> -28970.969 | N30: =IFERROR(J30/L30,"0%") -> 0.68136097 | P30: =IF(D30=0,0,SUM($L$20:L30)) -> 454604.85 | Q30: =IF(D30=0,0,SUM($J$20:J30)) -> 484100 | R30: =IF(D30=0,0,Q30-P30) -> 29495.155 | S30: =IFERROR(Q30/P30,"0%") -> 1.0648809 | U30: =IF(D30=0,0,SUM($L$20:L30)) -> 454604.85 | V30: =IF(D30=0,0,SUM($J$20:J30)) -> 484100 | W30: =IF(D30=0,0,V30-U30) -> 29495.155 | X30: =IFERROR(V30/U30,"0%") -> 1.0648809 | Z30: =Z29+1 -> 45302 | AA30: =AA29+1 -> 45302 | AB30: 45302 | AC30: 2 | AD30: 木 | AE30: =AVERAGEIFS(J51:J79,D51:D79,1,G51:G79,"thu") -> 95650 | AF30: =COUNTIFS(D51:D79,1,G51:G79,"thu") -> 5 | AH30: =AE30*AF30 -> 478250 | AI30: =AH30/$M$7 -> 0.21233378
C31: =C30+1 -> 12 | D31: 1 | E31: =TEXT(AA31,"m") -> 1 | F31: =F30+1 -> 45303 | G31: =TEXT(Z31,"ddd") -> Fri | J31: 132500 | L31: =IF(D31=0,0,$K$6) -> 90920.969 | M31: =IF(D31=0,0,J31-L31) -> 41579.031 | N31: =IFERROR(J31/L31,"0%") -> 1.4573096 | P31: =IF(D31=0,0,SUM($L$20:L31)) -> 545525.81 | Q31: =IF(D31=0,0,SUM($J$20:J31)) -> 616600 | R31: =IF(D31=0,0,Q31-P31) -> 71074.186 | S31: =IFERROR(Q31/P31,"0%") -> 1.1302857 | U31: =IF(D31=0,0,SUM($L$20:L31)) -> 545525.81 | V31: =IF(D31=0,0,SUM($J$20:J31)) -> 616600 | W31: =IF(D31=0,0,V31-U31) -> 71074.186 | X31: =IFERROR(V31/U31,"0%") -> 1.1302857 | Z31: =Z30+1 -> 45303 | AA31: =AA30+1 -> 45303 | AB31: 45303 | AC31: 2 | AD31: 金 | AE31: =AVERAGEIFS(J51:J79,D51:D79,1,G51:G79,"fri") -> 113575 | AF31: =COUNTIFS(D51:D79,1,G51:G79,"fri") -> 4 | AH31: =AE31*AF31 -> 454300 | AI31: =AH31/$M$7 -> 0.20170045
C32: =C31+1 -> 13 | D32: 1 | E32: =TEXT(AA32,"m") -> 1 | F32: =F31+1 -> 45304 | G32: =TEXT(Z32,"ddd") -> Sat | J32: 86150 | L32: =IF(D32=0,0,$K$6) -> 90920.969 | M32: =IF(D32=0,0,J32-L32) -> -4770.9691 | N32: =IFERROR(J32/L32,"0%") -> 0.9475262 | P32: =IF(D32=0,0,SUM($L$20:L32)) -> 636446.78 | Q32: =IF(D32=0,0,SUM($J$20:J32)) -> 702750 | R32: =IF(D32=0,0,Q32-P32) -> 66303.216 | S32: =IFERROR(Q32/P32,"0%") -> 1.1041772 | U32: =IF(D32=0,0,SUM($L$20:L32)) -> 636446.78 | V32: =IF(D32=0,0,SUM($J$20:J32)) -> 702750 | W32: =IF(D32=0,0,V32-U32) -> 66303.216 | X32: =IFERROR(V32/U32,"0%") -> 1.1041772 | Z32: =Z31+1 -> 45304 | AA32: =AA31+1 -> 45304 | AB32: 45304 | AC32: 2 | AD32: 土 | AE32: =AVERAGEIFS(J51:J79,D51:D79,1,G51:G79,"sat") -> 73337.5 | AF32: =COUNTIFS(D51:D79,1,G51:G79,"sat") -> 4 | AH32: =AE32*AF32 -> 293350 | AI32: =AH32/$M$7 -> 0.13024175
C33: =C32+1 -> 14 | D33: 1 | E33: =TEXT(AA33,"m") -> 1 | F33: =F32+1 -> 45305 | G33: =TEXT(Z33,"ddd") -> Sun | J33: 79100 | L33: =IF(D33=0,0,$K$6) -> 90920.969 | M33: =IF(D33=0,0,J33-L33) -> -11820.969 | N33: =IFERROR(J33/L33,"0%") -> 0.86998633 | P33: =IF(D33=0,0,SUM($L$20:L33)) -> 727367.75 | Q33: =IF(D33=0,0,SUM($J$20:J33)) -> 781850 | R33: =IF(D33=0,0,Q33-P33) -> 54482.247 | S33: =IFERROR(Q33/P33,"0%") -> 1.0749033 | U33: =IF(D33=0,0,SUM($L$20:L33)) -> 727367.75 | V33: =IF(D33=0,0,SUM($J$20:J33)) -> 781850 | W33: =IF(D33=0,0,V33-U33) -> 54482.247 | X33: =IFERROR(V33/U33,"0%") -> 1.0749033 | Z33: =Z32+1 -> 45305 | AA33: =AA32+1 -> 45305 | AB33: 45305 | AC33: 2 | AD33: 日 | AE33: =IFERROR(AVERAGEIFS(J51:J79,D51:D79,1,G51:G79,"sun"),0) -> 103437.5 | AF33: =IFERROR(COUNTIFS(D51:D79,1,G51:G79,"sun"),0) -> 4 | AH33: =AE33*AF33 -> 413750 | AI33: =AH33/$M$7 -> 0.18369703
C34: =C33+1 -> 15 | D34: 0 | E34: =TEXT(AA34,"m") -> 1 | F34: =F33+1 -> 45306 | G34: =TEXT(Z34,"ddd") -> Mon | L34: =IF(D34=0,0,$K$6) -> 0 | M34: =IF(D34=0,0,J34-L34) -> 0 | N34: =IFERROR(J34/L34,"0%") -> 0% | P34: =IF(D34=0,0,SUM($L$20:L34)) -> 0 | Q34: =IF(D34=0,0,SUM($J$20:J34)) -> 0 | R34: =IF(D34=0,0,Q34-P34) -> 0 | S34: =IFERROR(Q34/P34,"0%") -> 0% | U34: =IF(D34=0,0,SUM($L$20:L34)) -> 0 | V34: =IF(D34=0,0,SUM($J$20:J34)) -> 0 | W34: =IF(D34=0,0,V34-U34) -> 0 | X34: =IFERROR(V34/U34,"0%") -> 0% | Z34: =Z33+1 -> 45306 | AA34: =AA33+1 -> 45306 | AB34: 45306 | AC34: 3 | AD34: 月 | AE34: =IFERROR(AVERAGEIFS(J80:J110,D80:D110,1,G80:G110,"mon"),0) -> 0 | AF34: =COUNTIFS( D80:D110,1,G80:G110,"Mon") -> 0 | AH34: =AE34*AF34 -> 0 | AI34: =AH34/$M$8 -> 0 | AJ34: =SUM(AI34:AI40) -> 0.7752245 | AK34: 80〜110
C35: =C34+1 -> 16 | D35: 1 | E35: =TEXT(AA35,"m") -> 1 | F35: =F34+1 -> 45307 | G35: =TEXT(Z35,"ddd") -> Tue | J35: 62550 | L35: =IF(D35=0,0,$K$6) -> 90920.969 | M35: =IF(D35=0,0,J35-L35) -> -28370.969 | N35: =IFERROR(J35/L35,"0%") -> 0.68796011 | P35: =IF(D35=0,0,SUM($L$20:L35)) -> 818288.72 | Q35: =IF(D35=0,0,SUM($J$20:J35)) -> 844400 | R35: =IF(D35=0,0,Q35-P35) -> 26111.278 | S35: =IFERROR(Q35/P35,"0%") -> 1.0319096 | U35: =IF(D35=0,0,SUM($L$20:L35)) -> 818288.72 | V35: =IF(D35=0,0,SUM($J$20:J35)) -> 844400 | W35: =IF(D35=0,0,V35-U35) -> 26111.278 | X35: =IFERROR(V35/U35,"0%") -> 1.0319096 | Z35: =Z34+1 -> 45307 | AA35: =AA34+1 -> 45307 | AB35: 45307 | AC35: 3 | AD35: 火 | AE35: =AVERAGEIFS(J80:J110,D80:D110,1,G80:G110,"tue") -> 67850 | AF35: =COUNTIFS( D80:D110,1,G80:G110,"tue") -> 3 | AH35: =AE35*AF35 -> 203550 | AI35: =AH35/$M$8 -> 0.081418372
C36: =C35+1 -> 17 | D36: 1 | E36: =TEXT(AA36,"m") -> 1 | F36: =F35+1 -> 45308 | G36: =TEXT(Z36,"ddd") -> Wed | J36: 88700 | L36: =IF(D36=0,0,$K$6) -> 90920.969 | M36: =IF(D36=0,0,J36-L36) -> -2220.9691 | N36: =IFERROR(J36/L36,"0%") -> 0.97557253 | P36: =IF(D36=0,0,SUM($L$20:L36)) -> 909209.69 | Q36: =IF(D36=0,0,SUM($J$20:J36)) -> 933100 | R36: =IF(D36=0,0,Q36-P36) -> 23890.309 | S36: =IFERROR(Q36/P36,"0%") -> 1.0262759 | U36: =IF(D36=0,0,SUM($L$20:L36)) -> 909209.69 | V36: =IF(D36=0,0,SUM($J$20:J36)) -> 933100 | W36: =IF(D36=0,0,V36-U36) -> 23890.309 | X36: =IFERROR(V36/U36,"0%") -> 1.0262759 | Z36: =Z35+1 -> 45308 | AA36: =AA35+1 -> 45308 | AB36: 45308 | AC36: 3 | AD36: 水 | AE36: =AVERAGEIFS(J80:J110,D80:D110,1,G80:G110,"wed") -> 82283.333 | AF36: =COUNTIFS( D80:D110,1,G80:G110,"wed") -> 3 | AH36: =AE36*AF36 -> 246850 | AI36: =AH36/$M$8 -> 0.098738025
C37: =C36+1 -> 18 | D37: 1 | E37: =TEXT(AA37,"m") -> 1 | F37: =F36+1 -> 45309 | G37: =TEXT(Z37,"ddd") -> Thu | J37: 83850 | L37: =IF(D37=0,0,$K$6) -> 90920.969 | M37: =IF(D37=0,0,J37-L37) -> -7070.9691 | N37: =IFERROR(J37/L37,"0%") -> 0.9222295 | P37: =IF(D37=0,0,SUM($L$20:L37)) -> 1000130.7 | Q37: =IF(D37=0,0,SUM($J$20:J37)) -> 1016950 | R37: =IF(D37=0,0,Q37-P37) -> 16819.34 | S37: =IFERROR(Q37/P37,"0%") -> 1.0168171 | U37: =IF(D37=0,0,SUM($L$20:L37)) -> 1000130.7 | V37: =IF(D37=0,0,SUM($J$20:J37)) -> 1016950 | W37: =IF(D37=0,0,V37-U37) -> 16819.34 | X37: =IFERROR(V37/U37,"0%") -> 1.0168171 | Z37: =Z36+1 -> 45309 | AA37: =AA36+1 -> 45309 | AB37: 45309 | AC37: 3 | AD37: 木 | AE37: =AVERAGEIFS(J80:J110,D80:D110,1,G80:G110,"thu") -> 67162.5 | AF37: =COUNTIFS( D80:D110,1,G80:G110,"thu") -> 4 | AH37: =AE37*AF37 -> 268650 | AI37: =AH37/$M$8 -> 0.10745785
C38: =C37+1 -> 19 | D38: 1 | E38: =TEXT(AA38,"m") -> 1 | F38: =F37+1 -> 45310 | G38: =TEXT(Z38,"ddd") -> Fri | J38: 157100 | L38: =IF(D38=0,0,$K$6) -> 90920.969 | M38: =IF(D38=0,0,J38-L38) -> 66179.031 | N38: =IFERROR(J38/L38,"0%") -> 1.7278742 | P38: =IF(D38=0,0,SUM($L$20:L38)) -> 1091051.6 | Q38: =IF(D38=0,0,SUM($J$20:J38)) -> 1174050 | R38: =IF(D38=0,0,Q38-P38) -> 82998.371 | S38: =IFERROR(Q38/P38,"0%") -> 1.0760719 | U38: =IF(D38=0,0,SUM($L$20:L38)) -> 1091051.6 | V38: =IF(D38=0,0,SUM($J$20:J38)) -> 1174050 | W38: =IF(D38=0,0,V38-U38) -> 82998.371 | X38: =IFERROR(V38/U38,"0%") -> 1.0760719 | Z38: =Z37+1 -> 45310 | AA38: =AA37+1 -> 45310 | AB38: 45310 | AC38: 3 | AD38: 金 | AE38: =AVERAGEIFS(J80:J110,D80:D110,1,G80:G110,"fri") -> 144820 | AF38: =COUNTIFS( D80:D110,1,G80:G110,"fri") -> 5 | AH38: =AE38*AF38 -> 724100 | AI38: =AH38/$M$8 -> 0.28963421
C39: =C38+1 -> 20 | D39: 1 | E39: =TEXT(AA39,"m") -> 1 | F39: =F38+1 -> 45311 | G39: =TEXT(Z39,"ddd") -> Sat | J39: 76850 | L39: =IF(D39=0,0,$K$6) -> 90920.969 | M39: =IF(D39=0,0,J39-L39) -> -14070.969 | N39: =IFERROR(J39/L39,"0%") -> 0.84523956 | P39: =IF(D39=0,0,SUM($L$20:L39)) -> 1181972.6 | Q39: =IF(D39=0,0,SUM($J$20:J39)) -> 1250900 | R39: =IF(D39=0,0,Q39-P39) -> 68927.402 | S39: =IFERROR(Q39/P39,"0%") -> 1.0583156 | U39: =IF(D39=0,0,SUM($L$20:L39)) -> 1181972.6 | V39: =IF(D39=0,0,SUM($J$20:J39)) -> 1250900 | W39: =IF(D39=0,0,V39-U39) -> 68927.402 | X39: =IFERROR(V39/U39,"0%") -> 1.0583156 | Z39: =Z38+1 -> 45311 | AA39: =AA38+1 -> 45311 | AB39: 45311 | AC39: 3 | AD39: 土 | AE39: =AVERAGEIFS(J80:J110,D80:D110,1,G80:G110,"sat") -> 98990 | AF39: =COUNTIFS( D80:D110,1,G80:G110,"sat") -> 5 | AH39: =AE39*AF39 -> 494950 | AI39: =AH39/$M$8 -> 0.19797604
C40: =C39+1 -> 21 | D40: 1 | E40: =TEXT(AA40,"m") -> 1 | F40: =F39+1 -> 45312 | G40: =TEXT(Z40,"ddd") -> Sun | H40: 日曜日 | J40: 101650 | L40: =IF(D40=0,0,$K$6) -> 90920.969 | M40: =IF(D40=0,0,J40-L40) -> 10729.031 | N40: =IFERROR(J40/L40,"0%") -> 1.1180039 | P40: =IF(D40=0,0,SUM($L$20:L40)) -> 1272893.6 | Q40: =IF(D40=0,0,SUM($J$20:J40)) -> 1352550 | R40: =IF(D40=0,0,Q40-P40) -> 79656.433 | S40: =IFERROR(Q40/P40,"0%") -> 1.062579 | U40: =IF(D40=0,0,SUM($L$20:L40)) -> 1272893.6 | V40: =IF(D40=0,0,SUM($J$20:J40)) -> 1352550 | W40: =IF(D40=0,0,V40-U40) -> 79656.433 | X40: =IFERROR(V40/U40,"0%") -> 1.062579 | Z40: =Z39+1 -> 45312 | AA40: =AA39+1 -> 45312 | AB40: 45312 | AC40: 3 | AD40: 日 | AE40: =IFERROR(AVERAGEIFS(J80:J110,D80:D110,3,G80:G110,"sun"),0) -> 0 | AF40: =IFERROR(COUNTIFS( D80:D110,1,G80:G110,"sun"),0) -> 5 | AH40: =AE40*AF40 -> 0 | AI40: =AH40/$M$8 -> 0
C41: =C40+1 -> 22 | D41: 0 | E41: =TEXT(AA41,"m") -> 1 | F41: =F40+1 -> 45313 | G41: =TEXT(Z41,"ddd") -> Mon | L41: =IF(D41=0,0,$K$6) -> 0 | M41: =IF(D41=0,0,J41-L41) -> 0 | N41: =IFERROR(J41/L41,"0%") -> 0% | P41: =IF(D41=0,0,SUM($L$20:L41)) -> 0 | Q41: =IF(D41=0,0,SUM($J$20:J41)) -> 0 | R41: =IF(D41=0,0,Q41-P41) -> 0 | S41: =IFERROR(Q41/P41,"0%") -> 0% | U41: =IF(D41=0,0,SUM($L$20:L41)) -> 0 | V41: =IF(D41=0,0,SUM($J$20:J41)) -> 0 | W41: =IF(D41=0,0,V41-U41) -> 0 | X41: =IFERROR(V41/U41,"0%") -> 0% | Z41: =Z40+1 -> 45313 | AA41: =AA40+1 -> 45313 | AB41: 45313 | AC41: 4 | AD41: 月 | AE41: =IFERROR(AVERAGEIFS(J111:J140,D111:D140,1,G111:G140,"mon"),0) -> 0 | AF41: =COUNTIFS(D111:D140,1,G111:G140,"Mon") -> 0 | AH41: =AE41*AF41 -> 0 | AI41: =AH41/$M$9 -> 0 | AJ41: =SUM(AI41:AI47) -> 1 | AK41: 111〜140
C42: =C41+1 -> 23 | D42: 1 | E42: =TEXT(AA42,"m") -> 1 | F42: =F41+1 -> 45314 | G42: =TEXT(Z42,"ddd") -> Tue | J42: 122600 | L42: =IF(D42=0,0,$K$6) -> 90920.969 | M42: =IF(D42=0,0,J42-L42) -> 31679.031 | N42: =IFERROR(J42/L42,"0%") -> 1.3484238 | P42: =IF(D42=0,0,SUM($L$20:L42)) -> 1363814.5 | Q42: =IF(D42=0,0,SUM($J$20:J42)) -> 1475150 | R42: =IF(D42=0,0,Q42-P42) -> 111335.46 | S42: =IFERROR(Q42/P42,"0%") -> 1.0816353 | U42: =IF(D42=0,0,SUM($L$20:L42)) -> 1363814.5 | V42: =IF(D42=0,0,SUM($J$20:J42)) -> 1475150 | W42: =IF(D42=0,0,V42-U42) -> 111335.46 | X42: =IFERROR(V42/U42,"0%") -> 1.0816353 | Z42: =Z41+1 -> 45314 | AA42: =AA41+1 -> 45314 | AB42: 45314 | AC42: 4 | AD42: 火 | AE42: =AVERAGEIFS(J111:J140,D111:D140,1,G111:G140,"tue") -> 102760 | AF42: =COUNTIFS(D111:D140,1,G111:G140,"tue") -> 5 | AH42: =AE42*AF42 -> 513800 | AI42: =AH42/$M$9 -> 0.18802606
C43: =C42+1 -> 24 | D43: 0 | E43: =TEXT(AA43,"m") -> 1 | F43: =F42+1 -> 45315 | G43: =TEXT(Z43,"ddd") -> Wed | L43: =IF(D43=0,0,$K$6) -> 0 | M43: =IF(D43=0,0,J43-L43) -> 0 | N43: =IFERROR(J43/L43,"0%") -> 0% | P43: =IF(D43=0,0,SUM($L$20:L43)) -> 0 | Q43: =IF(D43=0,0,SUM($J$20:J43)) -> 0 | R43: =IF(D43=0,0,Q43-P43) -> 0 | S43: =IFERROR(Q43/P43,"0%") -> 0% | U43: =IF(D43=0,0,SUM($L$20:L43)) -> 0 | V43: =IF(D43=0,0,SUM($J$20:J43)) -> 0 | W43: =IF(D43=0,0,V43-U43) -> 0 | X43: =IFERROR(V43/U43,"0%") -> 0% | Z43: =Z42+1 -> 45315 | AA43: =AA42+1 -> 45315 | AB43: 45315 | AC43: 4 | AD43: 水 | AE43: =AVERAGEIFS(J111:J140,D111:D140,1,G111:G140,"wed") -> 80675 | AF43: =COUNTIFS(D111:D140,1,G111:G140,"wed") -> 4 | AH43: =AE43*AF43 -> 322700 | AI43: =AH43/$M$9 -> 0.11809266
C44: =C43+1 -> 25 | D44: 1 | E44: =TEXT(AA44,"m") -> 1 | F44: =F43+1 -> 45316 | G44: =TEXT(Z44,"ddd") -> Thu | J44: 24300 | L44: =IF(D44=0,0,$K$6) -> 90920.969 | M44: =IF(D44=0,0,J44-L44) -> -66620.969 | N44: =IFERROR(J44/L44,"0%") -> 0.26726508 | P44: =IF(D44=0,0,SUM($L$20:L44)) -> 1454735.5 | Q44: =IF(D44=0,0,SUM($J$20:J44)) -> 1499450 | R44: =IF(D44=0,0,Q44-P44) -> 44714.495 | S44: =IFERROR(Q44/P44,"0%") -> 1.0307372 | U44: =IF(D44=0,0,SUM($L$20:L44)) -> 1454735.5 | V44: =IF(D44=0,0,SUM($J$20:J44)) -> 1499450 | W44: =IF(D44=0,0,V44-U44) -> 44714.495 | X44: =IFERROR(V44/U44,"0%") -> 1.0307372 | Z44: =Z43+1 -> 45316 | AA44: =AA43+1 -> 45316 | AB44: 45316 | AC44: 4 | AD44: 木 | AE44: =AVERAGEIFS(J111:J140,D111:D140,1,G111:G140,"thu") -> 110900 | AF44: =COUNTIFS(D111:D140,1,G111:G140,"thu") -> 4 | AH44: =AE44*AF44 -> 443600 | AI44: =AH44/$M$9 -> 0.16233624
C45: =C44+1 -> 26 | D45: 1 | E45: =TEXT(AA45,"m") -> 1 | F45: =F44+1 -> 45317 | G45: =TEXT(Z45,"ddd") -> Fri | J45: 101700 | L45: =IF(D45=0,0,$K$6) -> 90920.969 | M45: =IF(D45=0,0,J45-L45) -> 10779.031 | N45: =IFERROR(J45/L45,"0%") -> 1.1185538 | P45: =IF(D45=0,0,SUM($L$20:L45)) -> 1545656.5 | Q45: =IF(D45=0,0,SUM($J$20:J45)) -> 1601150 | R45: =IF(D45=0,0,Q45-P45) -> 55493.526 | S45: =IFERROR(Q45/P45,"0%") -> 1.0359029 | U45: =IF(D45=0,0,SUM($L$20:L45)) -> 1545656.5 | V45: =IF(D45=0,0,SUM($J$20:J45)) -> 1601150 | W45: =IF(D45=0,0,V45-U45) -> 55493.526 | X45: =IFERROR(V45/U45,"0%") -> 1.0359029 | Z45: =Z44+1 -> 45317 | AA45: =AA44+1 -> 45317 | AB45: 45317 | AC45: 4 | AD45: 金 | AE45: =AVERAGEIFS(J111:J140,D111:D140,1,G111:G140,"fri") -> 148762.5 | AF45: =COUNTIFS(D111:D140,1,G111:G140,"fri") -> 4 | AH45: =AE45*AF45 -> 595050 | AI45: =AH45/$M$9 -> 0.21775964
C46: =C45+1 -> 27 | D46: 1 | E46: =TEXT(AA46,"m") -> 1 | F46: =F45+1 -> 45318 | G46: =TEXT(Z46,"ddd") -> Sat | J46: 79100 | L46: =IF(D46=0,0,$K$6) -> 90920.969 | M46: =IF(D46=0,0,J46-L46) -> -11820.969 | N46: =IFERROR(J46/L46,"0%") -> 0.86998633 | P46: =IF(D46=0,0,SUM($L$20:L46)) -> 1636577.4 | Q46: =IF(D46=0,0,SUM($J$20:J46)) -> 1680250 | R46: =IF(D46=0,0,Q46-P46) -> 43672.557 | S46: =IFERROR(Q46/P46,"0%") -> 1.0266853 | U46: =IF(D46=0,0,SUM($L$20:L46)) -> 1636577.4 | V46: =IF(D46=0,0,SUM($J$20:J46)) -> 1680250 | W46: =IF(D46=0,0,V46-U46) -> 43672.557 | X46: =IFERROR(V46/U46,"0%") -> 1.0266853 | Z46: =Z45+1 -> 45318 | AA46: =AA45+1 -> 45318 | AB46: 45318 | AC46: 4 | AD46: 土 | AE46: =AVERAGEIFS(J111:J140,D111:D140,1,G111:G140,"sat") -> 102537.5 | AF46: =COUNTIFS(D111:D140,1,G111:G140,"sat") -> 4 | AH46: =AE46*AF46 -> 410150 | AI46: =AH46/$M$9 -> 0.15009515
C47: =C46+1 -> 28 | D47: 1 | E47: =TEXT(AA47,"m") -> 1 | F47: =F46+1 -> 45319 | G47: =TEXT(Z47,"ddd") -> Sun | H47: 日曜日 | J47: 109800 | L47: =IF(D47=0,0,$K$6) -> 90920.969 | M47: =IF(D47=0,0,J47-L47) -> 18879.031 | N47: =IFERROR(J47/L47,"0%") -> 1.2076422 | P47: =IF(D47=0,0,SUM($L$20:L47)) -> 1727498.4 | Q47: =IF(D47=0,0,SUM($J$20:J47)) -> 1790050 | R47: =IF(D47=0,0,Q47-P47) -> 62551.588 | S47: =IFERROR(Q47/P47,"0%") -> 1.0362093 | U47: =IF(D47=0,0,SUM($L$20:L47)) -> 1727498.4 | V47: =IF(D47=0,0,SUM($J$20:J47)) -> 1790050 | W47: =IF(D47=0,0,V47-U47) -> 62551.588 | X47: =IFERROR(V47/U47,"0%") -> 1.0362093 | Z47: =Z46+1 -> 45319 | AA47: =AA46+1 -> 45319 | AB47: 45319 | AC47: 4 | AD47: 日 | AE47: =IFERROR(AVERAGEIFS(J111:J140,D111:D140,1,G111:G140,"sun"),0) -> 111825 | AF47: =IFERROR(COUNTIFS(D111:D140,1,G111:G140,"sun"),0) -> 4 | AH47: =AE47*AF47 -> 447300 | AI47: =AH47/$M$9 -> 0.16369026
C48: =C47+1 -> 29 | D48: 0 | E48: =TEXT(AA48,"m") -> 1 | F48: =F47+1 -> 45320 | G48: =TEXT(Z48,"ddd") -> Mon | L48: =IF(D48=0,0,$K$6) -> 0 | M48: =IF(D48=0,0,J48-L48) -> 0 | N48: =IFERROR(J48/L48,"0%") -> 0% | P48: =IF(D48=0,0,SUM($L$20:L48)) -> 0 | Q48: =IF(D48=0,0,SUM($J$20:J48)) -> 0 | R48: =IF(D48=0,0,Q48-P48) -> 0 | S48: =IFERROR(Q48/P48,"0%") -> 0% | U48: =IF(D48=0,0,SUM($L$20:L48)) -> 0 | V48: =IF(D48=0,0,SUM($J$20:J48)) -> 0 | W48: =IF(D48=0,0,V48-U48) -> 0 | X48: =IFERROR(V48/U48,"0%") -> 0% | Z48: =Z47+1 -> 45320 | AA48: =AA47+1 -> 45320 | AB48: 45320 | AC48: 5 | AD48: 月 | AE48: =IFERROR(AVERAGEIFS(J141:J171,D141:D171,1,G141:G171,"mon"),0) -> 0 | AF48: =COUNTIFS(D141:D171,1,G141:G171,"Mon") -> 0 | AH48: =AE48*AF48 -> 0 | AI48: =AH48/$M$10 -> 0 | AJ48: =SUM(AI48:AI54) -> 1 | AK48: 141〜171
C49: =C48+1 -> 30 | D49: 1 | E49: =TEXT(AA49,"m") -> 1 | F49: =F48+1 -> 45321 | G49: =TEXT(Z49,"ddd") -> Tue | J49: 37700 | L49: =IF(D49=0,0,$K$6) -> 90920.969 | M49: =IF(D49=0,0,J49-L49) -> -53220.969 | N49: =IFERROR(J49/L49,"0%") -> 0.41464582 | P49: =IF(D49=0,0,SUM($L$20:L49)) -> 1818419.4 | Q49: =IF(D49=0,0,SUM($J$20:J49)) -> 1827750 | R49: =IF(D49=0,0,Q49-P49) -> 9330.6186 | S49: =IFERROR(Q49/P49,"0%") -> 1.0051312 | U49: =IF(D49=0,0,SUM($L$20:L49)) -> 1818419.4 | V49: =IF(D49=0,0,SUM($J$20:J49)) -> 1827750 | W49: =IF(D49=0,0,V49-U49) -> 9330.6186 | X49: =IFERROR(V49/U49,"0%") -> 1.0051312 | Z49: =Z48+1 -> 45321 | AA49: =AA48+1 -> 45321 | AB49: 45321 | AC49: 5 | AD49: 火 | AE49: =AVERAGEIFS(J141:J171,D141:D171,1,G141:G171,"tue") -> 103950 | AF49: =COUNTIFS(D141:D171,1,G141:G171,"tue") -> 3 | AH49: =AE49*AF49 -> 311850 | AI49: =AH49/$M$10 -> 0.10679246
C50: =C49+1 -> 31 | D50: 1 | E50: =TEXT(AA50,"m") -> 1 | F50: =F49+1 -> 45322 | G50: =TEXT(Z50,"ddd") -> Wed | J50: 75950 | L50: =IF(D50=0,0,$K$6) -> 90920.969 | M50: =IF(D50=0,0,J50-L50) -> -14970.969 | N50: =IFERROR(J50/L50,"0%") -> 0.83534085 | P50: =IF(D50=0,0,SUM($L$20:L50)) -> 1909340.4 | Q50: =IF(D50=0,0,SUM($J$20:J50)) -> 1903700 | R50: =IF(D50=0,0,Q50-P50) -> -5640.3505 | S50: =IFERROR(Q50/P50,"0%") -> 0.99704592 | U50: =IF(D50=0,0,SUM($L$20:L50)) -> 1909340.4 | V50: =IF(D50=0,0,SUM($J$20:J50)) -> 1903700 | W50: =IF(D50=0,0,V50-U50) -> -5640.3505 | X50: =IFERROR(V50/U50,"0%") -> 0.99704592 | Z50: =Z49+1 -> 45322 | AA50: =AA49+1 -> 45322 | AB50: 45322 | AC50: 5 | AD50: 水 | AE50: =AVERAGEIFS(J141:J171,D141:D171,1,G141:G171,"wed") -> 103587.5 | AF50: =COUNTIFS(D141:D171,1,G141:G171,"wed") -> 4 | AH50: =AE50*AF50 -> 414350 | AI50: =AH50/$M$10 -> 0.1418934
C51: =C50+1 -> 32 | D51: 1 | E51: =TEXT(AA51,"m") -> 2 | F51: =F50+1 -> 45323 | G51: =TEXT(Z51,"ddd") -> Thu | J51: 59000 | L51: =IF(D51=0,0,$K$7) -> 85869.804 | M51: =IF(D51=0,0,J51-L51) -> -26869.804 | N51: =IFERROR(J51/L51,"0%") -> 0.6870867 | P51: =IF(D51=0,0,$L$51) -> 85869.804 | Q51: =IF(D51=0,0,$J$51) -> 59000 | R51: =IF(D51=0,0,Q51-P51) -> -26869.804 | S51: =IFERROR(Q51/P51,"0%") -> 0.6870867 | U51: =IF(D51=0,0,SUM($L$20:L51)) -> 1995210.2 | V51: =IF(D51=0,0,SUM($J$20:J51)) -> 1962700 | W51: =IF(D51=0,0,V51-U51) -> -32510.155 | X51: =IFERROR(V51/U51,"0%") -> 0.9837059 | Z51: =Z50+1 -> 45323 | AA51: =AA50+1 -> 45323 | AB51: 45323 | AC51: 5 | AD51: 木 | AE51: =AVERAGEIFS(J141:J171,D141:D171,1,G141:G171,"thu") -> 111270 | AF51: =COUNTIFS(D141:D171,1,G141:G171,"thu") -> 5 | AH51: =AE51*AF51 -> 556350 | AI51: =AH51/$M$10 -> 0.19052103
C52: =C51+1 -> 33 | D52: 1 | E52: =TEXT(AA52,"m") -> 2 | F52: =F51+1 -> 45324 | G52: =TEXT(Z52,"ddd") -> Fri | J52: 92400 | L52: =IF(D52=0,0,$K$7) -> 85869.804 | M52: =IF(D52=0,0,J52-L52) -> 6530.1959 | N52: =IFERROR(J52/L52,"0%") -> 1.0760476 | P52: =IF(D52=0,0,SUM($L$51:L52)) -> 171739.61 | Q52: =IF(D52=0,0,SUM($J$51:J52)) -> 151400 | R52: =IF(D52=0,0,Q52-P52) -> -20339.608 | S52: =IFERROR(Q52/P52,"0%") -> 0.88156717 | U52: =IF(D52=0,0,SUM($L$20:L52)) -> 2081080 | V52: =IF(D52=0,0,SUM($J$20:J52)) -> 2055100 | W52: =IF(D52=0,0,V52-U52) -> -25979.959 | X52: =IFERROR(V52/U52,"0%") -> 0.98751612 | Z52: =Z51+1 -> 45324 | AA52: =AA51+1 -> 45324 | AB52: 45324 | AC52: 5 | AD52: 金 | AE52: =AVERAGEIFS(J141:J171,D141:D171,1,G141:G171,"fri") -> 175940 | AF52: =COUNTIFS(D141:D171,1,G141:G171,"fri") -> 5 | AH52: =AE52*AF52 -> 879700 | AI52: =AH52/$M$10 -> 0.30125165
C53: =C52+1 -> 34 | D53: 1 | E53: =TEXT(AA53,"m") -> 2 | F53: =F52+1 -> 45325 | G53: =TEXT(Z53,"ddd") -> Sat | J53: 59300 | L53: =IF(D53=0,0,$K$7) -> 85869.804 | M53: =IF(D53=0,0,J53-L53) -> -26569.804 | N53: =IFERROR(J53/L53,"0%") -> 0.69058036 | P53: =IF(D53=0,0,SUM($L$51:L53)) -> 257609.41 | Q53: =IF(D53=0,0,SUM($J$51:J53)) -> 210700 | R53: =IF(D53=0,0,Q53-P53) -> -46909.412 | S53: =IFERROR(Q53/P53,"0%") -> 0.8179049 | U53: =IF(D53=0,0,SUM($L$20:L53)) -> 2166949.8 | V53: =IF(D53=0,0,SUM($J$20:J53)) -> 2114400 | W53: =IF(D53=0,0,V53-U53) -> -52549.763 | X53: =IFERROR(V53/U53,"0%") -> 0.97574943 | Z53: =Z52+1 -> 45325 | AA53: =AA52+1 -> 45325 | AB53: 45325 | AC53: 5 | AD53: 土 | AE53: =AVERAGEIFS(J141:J171,D141:D171,1,G141:G171,"sat") -> 77237.5 | AF53: =COUNTIFS(D141:D171,1,G141:G171,"sat") -> 4 | AH53: =AE53*AF53 -> 308950 | AI53: =AH53/$M$10 -> 0.10579936
C54: =C53+1 -> 35 | D54: 1 | E54: =TEXT(AA54,"m") -> 2 | F54: =F53+1 -> 45326 | G54: =TEXT(Z54,"ddd") -> Sun | H54: 日曜日 | J54: 86750 | L54: =IF(D54=0,0,$K$7) -> 85869.804 | M54: =IF(D54=0,0,J54-L54) -> 880.19588 | N54: =IFERROR(J54/L54,"0%") -> 1.0102504 | P54: =IF(D54=0,0,SUM($L$51:L54)) -> 343479.22 | Q54: =IF(D54=0,0,SUM($J$51:J54)) -> 297450 | R54: =IF(D54=0,0,Q54-P54) -> -46029.216 | S54: =IFERROR(Q54/P54,"0%") -> 0.86599126 | U54: =IF(D54=0,0,SUM($L$20:L54)) -> 2252819.6 | V54: =IF(D54=0,0,SUM($J$20:J54)) -> 2201150 | W54: =IF(D54=0,0,V54-U54) -> -51669.567 | X54: =IFERROR(V54/U54,"0%") -> 0.97706449 | Z54: =Z53+1 -> 45326 | AA54: =AA53+1 -> 45326 | AB54: 45326 | AC54: 5 | AD54: 日 | AE54: =IFERROR(AVERAGEIFS(J141:J171,D141:D171,1,G141:G171,"sun"),0) -> 112237.5 | AF54: =IFERROR(COUNTIFS(D141:D171,1,G141:G171,"sun"),0) -> 4 | AH54: =AE54*AF54 -> 448950 | AI54: =AH54/$M$10 -> 0.1537421
C55: =C54+1 -> 36 | D55: 0 | E55: =TEXT(AA55,"m") -> 2 | F55: =F54+1 -> 45327 | G55: =TEXT(Z55,"ddd") -> Mon | L55: =IF(D55=0,0,$K$7) -> 0 | M55: =IF(D55=0,0,J55-L55) -> 0 | N55: =IFERROR(J55/L55,"0%") -> 0% | P55: =IF(D55=0,0,SUM($L$51:L55)) -> 0 | Q55: =IF(D55=0,0,SUM($J$51:J55)) -> 0 | R55: =IF(D55=0,0,Q55-P55) -> 0 | S55: =IFERROR(Q55/P55,"0%") -> 0% | U55: =IF(D55=0,0,SUM($L$20:L55)) -> 0 | V55: =IF(D55=0,0,SUM($J$20:J55)) -> 0 | W55: =IF(D55=0,0,V55-U55) -> 0 | X55: =IFERROR(V55/U55,"0%") -> 0% | Z55: =Z54+1 -> 45327 | AA55: =AA54+1 -> 45327 | AB55: 45327 | AC55: 6 | AD55: 月 | AE55: =IFERROR(AVERAGEIFS(J172:J201,D172:D201,1,G172:G201,"mon"),0) -> 0 | AF55: =COUNTIFS(D172:D201,1,G172:G201,"Mon") -> 0 | AH55: =AE55*AF55 -> 0 | AI55: =AH55/$M$11 -> 0 | AJ55: =SUM(AI55:AI61) -> 1 | AK55: 172〜201
C56: =C55+1 -> 37 | D56: 1 | E56: =TEXT(AA56,"m") -> 2 | F56: =F55+1 -> 45328 | G56: =TEXT(Z56,"ddd") -> Tue | J56: 27050 | L56: =IF(D56=0,0,$K$7) -> 85869.804 | M56: =IF(D56=0,0,J56-L56) -> -58819.804 | N56: =IFERROR(J56/L56,"0%") -> 0.31501178 | P56: =IF(D56=0,0,SUM($L$51:L56)) -> 429349.02 | Q56: =IF(D56=0,0,SUM($J$51:J56)) -> 324500 | R56: =IF(D56=0,0,Q56-P56) -> -104849.02 | S56: =IFERROR(Q56/P56,"0%") -> 0.75579537 | U56: =IF(D56=0,0,SUM($L$20:L56)) -> 2338689.4 | V56: =IF(D56=0,0,SUM($J$20:J56)) -> 2228200 | W56: =IF(D56=0,0,V56-U56) -> -110489.37 | X56: =IFERROR(V56/U56,"0%") -> 0.95275586 | Z56: =Z55+1 -> 45328 | AA56: =AA55+1 -> 45328 | AB56: 45328 | AC56: 6 | AD56: 火 | AE56: =AVERAGEIFS(J172:J201,D172:D201,1,G172:G201,"tue") -> 88737.5 | AF56: =COUNTIFS(D172:D201,1,G172:G201,"tue") -> 4 | AH56: =AE56*AF56 -> 354950 | AI56: =AH56/$M$11 -> 0.11583774
C57: =C56+1 -> 38 | D57: 1 | E57: =TEXT(AA57,"m") -> 2 | F57: =F56+1 -> 45329 | G57: =TEXT(Z57,"ddd") -> Wed | J57: 115050 | L57: =IF(D57=0,0,$K$7) -> 85869.804 | M57: =IF(D57=0,0,J57-L57) -> 29180.196 | N57: =IFERROR(J57/L57,"0%") -> 1.3398191 | P57: =IF(D57=0,0,SUM($L$51:L57)) -> 515218.82 | Q57: =IF(D57=0,0,SUM($J$51:J57)) -> 439550 | R57: =IF(D57=0,0,Q57-P57) -> -75668.825 | S57: =IFERROR(Q57/P57,"0%") -> 0.85313265 | U57: =IF(D57=0,0,SUM($L$20:L57)) -> 2424559.2 | V57: =IF(D57=0,0,SUM($J$20:J57)) -> 2343250 | W57: =IF(D57=0,0,V57-U57) -> -81309.175 | X57: =IFERROR(V57/U57,"0%") -> 0.96646435 | Z57: =Z56+1 -> 45329 | AA57: =AA56+1 -> 45329 | AB57: 45329 | AC57: 6 | AD57: 水 | AE57: =AVERAGEIFS(J172:J201,D172:D201,1,G172:G201,"wed") -> 119062.5 | AF57: =COUNTIFS(D172:D201,1,G172:G201,"wed") -> 4 | AH57: =AE57*AF57 -> 476250 | AI57: =AH57/$M$11 -> 0.15542393
C58: =C57+1 -> 39 | D58: 1 | E58: =TEXT(AA58,"m") -> 2 | F58: =F57+1 -> 45330 | G58: =TEXT(Z58,"ddd") -> Thu | J58: 126450 | L58: =IF(D58=0,0,$K$7) -> 85869.804 | M58: =IF(D58=0,0,J58-L58) -> 40580.196 | N58: =IFERROR(J58/L58,"0%") -> 1.4725782 | P58: =IF(D58=0,0,SUM($L$51:L58)) -> 601088.63 | Q58: =IF(D58=0,0,SUM($J$51:J58)) -> 566000 | R58: =IF(D58=0,0,Q58-P58) -> -35088.629 | S58: =IFERROR(Q58/P58,"0%") -> 0.94162487 | U58: =IF(D58=0,0,SUM($L$20:L58)) -> 2510429 | V58: =IF(D58=0,0,SUM($J$20:J58)) -> 2469700 | W58: =IF(D58=0,0,V58-U58) -> -40728.979 | X58: =IFERROR(V58/U58,"0%") -> 0.98377609 | Z58: =Z57+1 -> 45330 | AA58: =AA57+1 -> 45330 | AB58: 45330 | AC58: 6 | AD58: 木 | AE58: =AVERAGEIFS(J172:J201,D172:D201,1,G172:G201,"thu") -> 135887.5 | AF58: =COUNTIFS(D172:D201,1,G172:G201,"thu") -> 4 | AH58: =AE58*AF58 -> 543550 | AI58: =AH58/$M$11 -> 0.17738725
C59: =C58+1 -> 40 | D59: 1 | E59: =TEXT(AA59,"m") -> 2 | F59: =F58+1 -> 45331 | G59: =TEXT(Z59,"ddd") -> Fri | J59: 121500 | L59: =IF(D59=0,0,$K$7) -> 85869.804 | M59: =IF(D59=0,0,J59-L59) -> 35630.196 | N59: =IFERROR(J59/L59,"0%") -> 1.4149328 | P59: =IF(D59=0,0,SUM($L$51:L59)) -> 686958.43 | Q59: =IF(D59=0,0,SUM($J$51:J59)) -> 687500 | R59: =IF(D59=0,0,Q59-P59) -> 541.56701 | S59: =IFERROR(Q59/P59,"0%") -> 1.0007884 | U59: =IF(D59=0,0,SUM($L$20:L59)) -> 2596298.8 | V59: =IF(D59=0,0,SUM($J$20:J59)) -> 2591200 | W59: =IF(D59=0,0,V59-U59) -> -5098.7835 | X59: =IFERROR(V59/U59,"0%") -> 0.99803613 | Z59: =Z58+1 -> 45331 | AA59: =AA58+1 -> 45331 | AB59: 45331 | AC59: 6 | AD59: 金 | AE59: =AVERAGEIFS(J172:J201,D172:D201,1,G172:G201,"fri") -> 156950 | AF59: =COUNTIFS(D172:D201,1,G172:G201,"fri") -> 4 | AH59: =AE59*AF59 -> 627800 | AI59: =AH59/$M$11 -> 0.20488219
C60: =C59+1 -> 41 | D60: 1 | E60: =TEXT(AA60,"m") -> 2 | F60: =F59+1 -> 45332 | G60: =TEXT(Z60,"ddd") -> Sat | J60: 51350 | L60: =IF(D60=0,0,$K$7) -> 85869.804 | M60: =IF(D60=0,0,J60-L60) -> -34519.804 | N60: =IFERROR(J60/L60,"0%") -> 0.59799834 | P60: =IF(D60=0,0,SUM($L$51:L60)) -> 772828.24 | Q60: =IF(D60=0,0,SUM($J$51:J60)) -> 738850 | R60: =IF(D60=0,0,Q60-P60) -> -33978.237 | S60: =IFERROR(Q60/P60,"0%") -> 0.95603391 | U60: =IF(D60=0,0,SUM($L$20:L60)) -> 2682168.6 | V60: =IF(D60=0,0,SUM($J$20:J60)) -> 2642550 | W60: =IF(D60=0,0,V60-U60) -> -39618.588 | X60: =IFERROR(V60/U60,"0%") -> 0.9852289 | Z60: =Z59+1 -> 45332 | AA60: =AA59+1 -> 45332 | AB60: 45332 | AC60: 6 | AD60: 土 | AE60: =AVERAGEIFS(J172:J201,D172:D201,1,G172:G201,"sat") -> 120950 | AF60: =COUNTIFS(D172:D201,1,G172:G201,"sat") -> 5 | AH60: =AE60*AF60 -> 604750 | AI60: =AH60/$M$11 -> 0.19735983
C61: =C60+1 -> 42 | D61: 1 | E61: =TEXT(AA61,"m") -> 2 | F61: =F60+1 -> 45333 | G61: =TEXT(Z61,"ddd") -> Sun | H61: 日曜日 | J61: 148600 | L61: =IF(D61=0,0,$K$7) -> 85869.804 | M61: =IF(D61=0,0,J61-L61) -> 62730.196 | N61: =IFERROR(J61/L61,"0%") -> 1.7305268 | P61: =IF(D61=0,0,SUM($L$51:L61)) -> 858698.04 | Q61: =IF(D61=0,0,SUM($J$51:J61)) -> 887450 | R61: =IF(D61=0,0,Q61-P61) -> 28751.959 | S61: =IFERROR(Q61/P61,"0%") -> 1.0334832 | U61: =IF(D61=0,0,SUM($L$20:L61)) -> 2768038.4 | V61: =IF(D61=0,0,SUM($J$20:J61)) -> 2791150 | W61: =IF(D61=0,0,V61-U61) -> 23111.608 | X61: =IFERROR(V61/U61,"0%") -> 1.0083495 | Z61: =Z60+1 -> 45333 | AA61: =AA60+1 -> 45333 | AB61: 45333 | AC61: 6 | AD61: 日 | AE61: =IFERROR(AVERAGEIFS(J172:J201,D172:D201,1,G172:G201,"sun"),0) -> 91380 | AF61: =IFERROR(COUNTIFS(D172:D201,1,G172:G201,"sun"),0) -> 5 | AH61: =AE61*AF61 -> 456900 | AI61: =AH61/$M$11 -> 0.14910907
C62: =C61+1 -> 43 | D62: 0 | E62: =TEXT(AA62,"m") -> 2 | F62: =F61+1 -> 45334 | G62: =TEXT(Z62,"ddd") -> Mon | H62: 祝日 | J62: 0 | L62: =IF(D62=0,0,$K$7) -> 0 | M62: =IF(D62=0,0,J62-L62) -> 0 | N62: =IFERROR(J62/L62,"0%") -> 0% | P62: =IF(D62=0,0,SUM($L$51:L62)) -> 0 | Q62: =IF(D62=0,0,SUM($J$51:J62)) -> 0 | R62: =IF(D62=0,0,Q62-P62) -> 0 | S62: =IFERROR(Q62/P62,"0%") -> 0% | U62: =IF(D62=0,0,SUM($L$20:L62)) -> 0 | V62: =IF(D62=0,0,SUM($J$20:J62)) -> 0 | W62: =IF(D62=0,0,V62-U62) -> 0 | X62: =IFERROR(V62/U62,"0%") -> 0% | Z62: =Z61+1 -> 45334 | AA62: =AA61+1 -> 45334 | AB62: 45334 | AC62: 7 | AD62: 月 | AE62: =IFERROR(AVERAGEIFS(J202:J232,D202:D232,1,G202:G232,"mon"),0) -> 0 | AF62: =COUNTIFS(D202:D232,1,G202:G232,"Mon") -> 0 | AH62: =AE62*AF62 -> 0 | AI62: =AH62/$M$12 -> 0 | AJ62: =SUM(AI62:AI68) -> 1 | AK62: 202〜232
C63: =C62+1 -> 44 | D63: 1 | E63: =TEXT(AA63,"m") -> 2 | F63: =F62+1 -> 45335 | G63: =TEXT(Z63,"ddd") -> Tue | J63: 62800 | L63: =IF(D63=0,0,$K$7) -> 85869.804 | M63: =IF(D63=0,0,J63-L63) -> -23069.804 | N63: =IFERROR(J63/L63,"0%") -> 0.73133974 | P63: =IF(D63=0,0,SUM($L$51:L63)) -> 944567.85 | Q63: =IF(D63=0,0,SUM($J$51:J63)) -> 950250 | R63: =IF(D63=0,0,Q63-P63) -> 5682.1546 | S63: =IFERROR(Q63/P63,"0%") -> 1.0060156 | U63: =IF(D63=0,0,SUM($L$20:L63)) -> 2853908.2 | V63: =IF(D63=0,0,SUM($J$20:J63)) -> 2853950 | W63: =IF(D63=0,0,V63-U63) -> 41.804124 | X63: =IFERROR(V63/U63,"0%") -> 1.0000146 | Z63: =Z62+1 -> 45335 | AA63: =AA62+1 -> 45335 | AB63: 45335 | AC63: 7 | AD63: 火 | AE63: =AVERAGEIFS(J202:J232,D202:D232,1,G202:G232,"tue") -> 82550 | AF63: =COUNTIFS(D202:D232,1,G202:G232,"tue") -> 5 | AH63: =AE63*AF63 -> 412750 | AI63: =AH63/$M$12 -> 0.17255074
C64: =C63+1 -> 45 | D64: 1 | E64: =TEXT(AA64,"m") -> 2 | F64: =F63+1 -> 45336 | G64: =TEXT(Z64,"ddd") -> Wed | J64: 99300 | L64: =IF(D64=0,0,$K$7) -> 85869.804 | M64: =IF(D64=0,0,J64-L64) -> 13430.196 | N64: =IFERROR(J64/L64,"0%") -> 1.1564018 | P64: =IF(D64=0,0,SUM($L$51:L64)) -> 1030437.6 | Q64: =IF(D64=0,0,SUM($J$51:J64)) -> 1049550 | R64: =IF(D64=0,0,Q64-P64) -> 19112.351 | S64: =IFERROR(Q64/P64,"0%") -> 1.0185478 | U64: =IF(D64=0,0,SUM($L$20:L64)) -> 2939778 | V64: =IF(D64=0,0,SUM($J$20:J64)) -> 2953250 | W64: =IF(D64=0,0,V64-U64) -> 13472 | X64: =IFERROR(V64/U64,"0%") -> 1.0045827 | Z64: =Z63+1 -> 45336 | AA64: =AA63+1 -> 45336 | AB64: 45336 | AC64: 7 | AD64: 水 | AE64: =AVERAGEIFS(J202:J232,D202:D232,1,G202:G232,"wed") -> 54350 | AF64: =COUNTIFS(D202:D232,1,G202:G232,"wed") -> 5 | AH64: =AE64*AF64 -> 271750 | AI64: =AH64/$M$12 -> 0.11360548
C65: =C64+1 -> 46 | D65: 1 | E65: =TEXT(AA65,"m") -> 2 | F65: =F64+1 -> 45337 | G65: =TEXT(Z65,"ddd") -> Thu | J65: 111000 | L65: =IF(D65=0,0,$K$7) -> 85869.804 | M65: =IF(D65=0,0,J65-L65) -> 25130.196 | N65: =IFERROR(J65/L65,"0%") -> 1.2926546 | P65: =IF(D65=0,0,SUM($L$51:L65)) -> 1116307.5 | Q65: =IF(D65=0,0,SUM($J$51:J65)) -> 1160550 | R65: =IF(D65=0,0,Q65-P65) -> 44242.546 | S65: =IFERROR(Q65/P65,"0%") -> 1.0396329 | U65: =IF(D65=0,0,SUM($L$20:L65)) -> 3025647.8 | V65: =IF(D65=0,0,SUM($J$20:J65)) -> 3064250 | W65: =IF(D65=0,0,V65-U65) -> 38602.196 | X65: =IFERROR(V65/U65,"0%") -> 1.0127583 | Z65: =Z64+1 -> 45337 | AA65: =AA64+1 -> 45337 | AB65: 45337 | AC65: 7 | AD65: 木 | AE65: =AVERAGEIFS(J202:J232,D202:D232,1,G202:G232,"thu") -> 82737.5 | AF65: =COUNTIFS(D202:D232,1,G202:G232,"thu") -> 4 | AH65: =AE65*AF65 -> 330950 | AI65: =AH65/$M$12 -> 0.13835413
C66: =C65+1 -> 47 | D66: 1 | E66: =TEXT(AA66,"m") -> 2 | F66: =F65+1 -> 45338 | G66: =TEXT(Z66,"ddd") -> Fri | J66: 149000 | L66: =IF(D66=0,0,$K$7) -> 85869.804 | M66: =IF(D66=0,0,J66-L66) -> 63130.196 | N66: =IFERROR(J66/L66,"0%") -> 1.735185 | P66: =IF(D66=0,0,SUM($L$51:L66)) -> 1202177.3 | Q66: =IF(D66=0,0,SUM($J$51:J66)) -> 1309550 | R66: =IF(D66=0,0,Q66-P66) -> 107372.74 | S66: =IFERROR(Q66/P66,"0%") -> 1.0893152 | U66: =IF(D66=0,0,SUM($L$20:L66)) -> 3111517.6 | V66: =IF(D66=0,0,SUM($J$20:J66)) -> 3213250 | W66: =IF(D66=0,0,V66-U66) -> 101732.39 | X66: =IFERROR(V66/U66,"0%") -> 1.0326954 | Z66: =Z65+1 -> 45338 | AA66: =AA65+1 -> 45338 | AB66: 45338 | AC66: 7 | AD66: 金 | AE66: =AVERAGEIFS(J202:J232,D202:D232,1,G202:G232,"fri") -> 124225 | AF66: =COUNTIFS(D202:D232,1,G202:G232,"fri") -> 4 | AH66: =AE66*AF66 -> 496900 | AI66: =AH66/$M$12 -> 0.20772977
C67: =C66+1 -> 48 | D67: 1 | E67: =TEXT(AA67,"m") -> 2 | F67: =F66+1 -> 45339 | G67: =TEXT(Z67,"ddd") -> Sat | J67: 109250 | L67: =IF(D67=0,0,$K$7) -> 85869.804 | M67: =IF(D67=0,0,J67-L67) -> 23380.196 | N67: =IFERROR(J67/L67,"0%") -> 1.2722749 | P67: =IF(D67=0,0,SUM($L$51:L67)) -> 1288047.1 | Q67: =IF(D67=0,0,SUM($J$51:J67)) -> 1418800 | R67: =IF(D67=0,0,Q67-P67) -> 130752.94 | S67: =IFERROR(Q67/P67,"0%") -> 1.1015125 | U67: =IF(D67=0,0,SUM($L$20:L67)) -> 3197387.4 | V67: =IF(D67=0,0,SUM($J$20:J67)) -> 3322500 | W67: =IF(D67=0,0,V67-U67) -> 125112.59 | X67: =IFERROR(V67/U67,"0%") -> 1.0391296 | Z67: =Z66+1 -> 45339 | AA67: =AA66+1 -> 45339 | AB67: 45339 | AC67: 7 | AD67: 土 | AE67: =AVERAGEIFS(J202:J232,D202:D232,1,G202:G232,"sat") -> 111762.5 | AF67: =COUNTIFS(D202:D232,1,G202:G232,"sat") -> 4 | AH67: =AE67*AF67 -> 447050 | AI67: =AH67/$M$12 -> 0.18688991
C68: =C67+1 -> 49 | D68: 1 | E68: =TEXT(AA68,"m") -> 2 | F68: =F67+1 -> 45340 | G68: =TEXT(Z68,"ddd") -> Sun | H68: 日曜日 | J68: 138100 | L68: =IF(D68=0,0,$K$7) -> 85869.804 | M68: =IF(D68=0,0,J68-L68) -> 52230.196 | N68: =IFERROR(J68/L68,"0%") -> 1.6082487 | P68: =IF(D68=0,0,SUM($L$51:L68)) -> 1373916.9 | Q68: =IF(D68=0,0,SUM($J$51:J68)) -> 1556900 | R68: =IF(D68=0,0,Q68-P68) -> 182983.13 | S68: =IFERROR(Q68/P68,"0%") -> 1.1331836 | U68: =IF(D68=0,0,SUM($L$20:L68)) -> 3283257.2 | V68: =IF(D68=0,0,SUM($J$20:J68)) -> 3460600 | W68: =IF(D68=0,0,V68-U68) -> 177342.78 | X68: =IFERROR(V68/U68,"0%") -> 1.0540143 | Z68: =Z67+1 -> 45340 | AA68: =AA67+1 -> 45340 | AB68: 45340 | AC68: 7 | AD68: 日 | AE68: =IFERROR(AVERAGEIFS(J202:J232,D202:D232,1,G202:G232,"sun"),0) -> 144216.67 | AF68: =IFERROR(COUNTIFS(D202:D232,1,G202:G232,"sun"),0) -> 3 | AH68: =AE68*AF68 -> 432650 | AI68: =AH68/$M$12 -> 0.18086997
C69: =C68+1 -> 50 | D69: 0 | E69: =TEXT(AA69,"m") -> 2 | F69: =F68+1 -> 45341 | G69: =TEXT(Z69,"ddd") -> Mon | L69: =IF(D69=0,0,$K$7) -> 0 | M69: =IF(D69=0,0,J69-L69) -> 0 | N69: =IFERROR(J69/L69,"0%") -> 0% | P69: =IF(D69=0,0,SUM($L$51:L69)) -> 0 | Q69: =IF(D69=0,0,SUM($J$51:J69)) -> 0 | R69: =IF(D69=0,0,Q69-P69) -> 0 | S69: =IFERROR(Q69/P69,"0%") -> 0% | U69: =IF(D69=0,0,SUM($L$20:L69)) -> 0 | V69: =IF(D69=0,0,SUM($J$20:J69)) -> 0 | W69: =IF(D69=0,0,V69-U69) -> 0 | X69: =IFERROR(V69/U69,"0%") -> 0% | Z69: =Z68+1 -> 45341 | AA69: =AA68+1 -> 45341 | AB69: 45341 | AC69: 8 | AD69: 月 | AE69: =IFERROR(AVERAGEIFS(J233:J263,D233:D263,1,G233:G263,"mon"),0) -> 0 | AF69: =COUNTIFS(D233:D263,1,G233:G263,"Mon") -> 0 | AH69: =AE69*AF69 -> 0 | AI69: =AH69/$M$13 -> 0 | AJ69: =SUM(AI69:AI75) -> 1 | AK69: 233〜263
C70: =C69+1 -> 51 | D70: 1 | E70: =TEXT(AA70,"m") -> 2 | F70: =F69+1 -> 45342 | G70: =TEXT(Z70,"ddd") -> Tue | J70: 108800 | L70: =IF(D70=0,0,$K$7) -> 85869.804 | M70: =IF(D70=0,0,J70-L70) -> 22930.196 | N70: =IFERROR(J70/L70,"0%") -> 1.2670344 | P70: =IF(D70=0,0,SUM($L$51:L70)) -> 1459786.7 | Q70: =IF(D70=0,0,SUM($J$51:J70)) -> 1665700 | R70: =IF(D70=0,0,Q70-P70) -> 205913.33 | S70: =IFERROR(Q70/P70,"0%") -> 1.1410571 | U70: =IF(D70=0,0,SUM($L$20:L70)) -> 3369127 | V70: =IF(D70=0,0,SUM($J$20:J70)) -> 3569400 | W70: =IF(D70=0,0,V70-U70) -> 200272.98 | X70: =IFERROR(V70/U70,"0%") -> 1.0594436 | Z70: =Z69+1 -> 45342 | AA70: =AA69+1 -> 45342 | AB70: 45342 | AC70: 8 | AD70: 火 | AE70: =AVERAGEIFS(J233:J263,D233:D263,1,G233:G263,"tue") -> 66726.667 | AF70: =COUNTIFS(D233:D263,1,G233:G263,"tue") -> 3 | AH70: =AE70*AF70 -> 200180 | AI70: =AH70/$M$13 -> 0.096961536
C71: =C70+1 -> 52 | D71: 1 | E71: =TEXT(AA71,"m") -> 2 | F71: =F70+1 -> 45343 | G71: =TEXT(Z71,"ddd") -> Wed | J71: 63950 | L71: =IF(D71=0,0,$K$7) -> 85869.804 | M71: =IF(D71=0,0,J71-L71) -> -21919.804 | N71: =IFERROR(J71/L71,"0%") -> 0.74473211 | P71: =IF(D71=0,0,SUM($L$51:L71)) -> 1545656.5 | Q71: =IF(D71=0,0,SUM($J$51:J71)) -> 1729650 | R71: =IF(D71=0,0,Q71-P71) -> 183993.53 | S71: =IFERROR(Q71/P71,"0%") -> 1.1190391 | U71: =IF(D71=0,0,SUM($L$20:L71)) -> 3454996.8 | V71: =IF(D71=0,0,SUM($J$20:J71)) -> 3633350 | W71: =IF(D71=0,0,V71-U71) -> 178353.18 | X71: =IFERROR(V71/U71,"0%") -> 1.0516218 | Z71: =Z70+1 -> 45343 | AA71: =AA70+1 -> 45343 | AB71: 45343 | AC71: 8 | AD71: 水 | AE71: =AVERAGEIFS(J233:J263,D233:D263,1,G233:G263,"wed") -> 96283.333 | AF71: =COUNTIFS(D233:D263,1,G233:G263,"wed") -> 3 | AH71: =AE71*AF71 -> 288850 | AI71: =AH71/$M$13 -> 0.13991078
C72: =C71+1 -> 53 | D72: 1 | E72: =TEXT(AA72,"m") -> 2 | F72: =F71+1 -> 45344 | G72: =TEXT(Z72,"ddd") -> Thu | J72: 139800 | L72: =IF(D72=0,0,$K$7) -> 85869.804 | M72: =IF(D72=0,0,J72-L72) -> 53930.196 | N72: =IFERROR(J72/L72,"0%") -> 1.6280461 | P72: =IF(D72=0,0,SUM($L$51:L72)) -> 1631526.3 | Q72: =IF(D72=0,0,SUM($J$51:J72)) -> 1869450 | R72: =IF(D72=0,0,Q72-P72) -> 237923.72 | S72: =IFERROR(Q72/P72,"0%") -> 1.1458289 | U72: =IF(D72=0,0,SUM($L$20:L72)) -> 3540866.6 | V72: =IF(D72=0,0,SUM($J$20:J72)) -> 3773150 | W72: =IF(D72=0,0,V72-U72) -> 232283.37 | X72: =IFERROR(V72/U72,"0%") -> 1.0656007 | Z72: =Z71+1 -> 45344 | AA72: =AA71+1 -> 45344 | AB72: 45344 | AC72: 8 | AD72: 木 | AE72: =AVERAGEIFS(J233:J263,D233:D263,1,G233:G263,"thu") -> 89637.5 | AF72: =COUNTIFS(D233:D263,1,G233:G263,"thu") -> 4 | AH72: =AE72*AF72 -> 358550 | AI72: =AH72/$M$13 -> 0.17367149
C73: =C72+1 -> 54 | D73: 1 | E73: =TEXT(AA73,"m") -> 2 | F73: =F72+1 -> 45345 | G73: =TEXT(Z73,"ddd") -> Fri | H73: 祝日 | J73: 91400 | L73: =IF(D73=0,0,$K$7) -> 85869.804 | M73: =IF(D73=0,0,J73-L73) -> 5530.1959 | N73: =IFERROR(J73/L73,"0%") -> 1.0644021 | P73: =IF(D73=0,0,SUM($L$51:L73)) -> 1717396.1 | Q73: =IF(D73=0,0,SUM($J$51:J73)) -> 1960850 | R73: =IF(D73=0,0,Q73-P73) -> 243453.92 | S73: =IFERROR(Q73/P73,"0%") -> 1.1417576 | U73: =IF(D73=0,0,SUM($L$20:L73)) -> 3626736.4 | V73: =IF(D73=0,0,SUM($J$20:J73)) -> 3864550 | W73: =IF(D73=0,0,V73-U73) -> 237813.57 | X73: =IFERROR(V73/U73,"0%") -> 1.0655723 | Z73: =Z72+1 -> 45345 | AA73: =AA72+1 -> 45345 | AB73: 45345 | AC73: 8 | AD73: 金 | AE73: =AVERAGEIFS(J233:J263,D233:D263,1,G233:G263,"fri") -> 144825 | AF73: =COUNTIFS(D233:D263,1,G233:G263,"fri") -> 4 | AH73: =AE73*AF73 -> 579300 | AI73: =AH73/$M$13 -> 0.28059655
C74: =C73+1 -> 55 | D74: 1 | E74: =TEXT(AA74,"m") -> 2 | F74: =F73+1 -> 45346 | G74: =TEXT(Z74,"ddd") -> Sat | J74: 73450 | L74: =IF(D74=0,0,$K$7) -> 85869.804 | M74: =IF(D74=0,0,J74-L74) -> -12419.804 | N74: =IFERROR(J74/L74,"0%") -> 0.85536471 | P74: =IF(D74=0,0,SUM($L$51:L74)) -> 1803265.9 | Q74: =IF(D74=0,0,SUM($J$51:J74)) -> 2034300 | R74: =IF(D74=0,0,Q74-P74) -> 231034.11 | S74: =IFERROR(Q74/P74,"0%") -> 1.1281198 | U74: =IF(D74=0,0,SUM($L$20:L74)) -> 3712606.2 | V74: =IF(D74=0,0,SUM($J$20:J74)) -> 3938000 | W74: =IF(D74=0,0,V74-U74) -> 225393.76 | X74: =IFERROR(V74/U74,"0%") -> 1.0607104 | Z74: =Z73+1 -> 45346 | AA74: =AA73+1 -> 45346 | AB74: 45346 | AC74: 8 | AD74: 土 | AE74: =AVERAGEIFS(J233:J263,D233:D263,1,G233:G263,"sat") -> 68750 | AF74: =COUNTIFS(D233:D263,1,G233:G263,"sat") -> 4 | AH74: =AE74*AF74 -> 275000 | AI74: =AH74/$M$13 -> 0.13320223
C75: =C74+1 -> 56 | D75: 1 | E75: =TEXT(AA75,"m") -> 2 | F75: =F74+1 -> 45347 | G75: =TEXT(Z75,"ddd") -> Sun | H75: 日曜日 | J75: 40300 | L75: =IF(D75=0,0,$K$7) -> 85869.804 | M75: =IF(D75=0,0,J75-L75) -> -45569.804 | N75: =IFERROR(J75/L75,"0%") -> 0.46931515 | P75: =IF(D75=0,0,SUM($L$51:L75)) -> 1889135.7 | Q75: =IF(D75=0,0,SUM($J$51:J75)) -> 2074600 | R75: =IF(D75=0,0,Q75-P75) -> 185464.31 | S75: =IFERROR(Q75/P75,"0%") -> 1.0981742 | U75: =IF(D75=0,0,SUM($L$20:L75)) -> 3798476 | V75: =IF(D75=0,0,SUM($J$20:J75)) -> 3978300 | W75: =IF(D75=0,0,V75-U75) -> 179823.96 | X75: =IFERROR(V75/U75,"0%") -> 1.0473411 | Z75: =Z74+1 -> 45347 | AA75: =AA74+1 -> 45347 | AB75: 45347 | AC75: 8 | AD75: 日 | AE75: =IFERROR(AVERAGEIFS(J233:J263,D233:D263,1,G233:G263,"sun"),0) -> 90662.5 | AF75: =IFERROR(COUNTIFS(D233:D263,1,G233:G263,"sun"),0) -> 4 | AH75: =AE75*AF75 -> 362650 | AI75: =AH75/$M$13 -> 0.17565741
C76: =C75+1 -> 57 | D76: 0 | E76: =TEXT(AA76,"m") -> 2 | F76: =F75+1 -> 45348 | G76: =TEXT(Z76,"ddd") -> Mon | L76: =IF(D76=0,0,$K$7) -> 0 | M76: =IF(D76=0,0,J76-L76) -> 0 | N76: =IFERROR(J76/L76,"0%") -> 0% | P76: =IF(D76=0,0,SUM($L$51:L76)) -> 0 | Q76: =IF(D76=0,0,SUM($J$51:J76)) -> 0 | R76: =IF(D76=0,0,Q76-P76) -> 0 | S76: =IFERROR(Q76/P76,"0%") -> 0% | U76: =IF(D76=0,0,SUM($L$20:L76)) -> 0 | V76: =IF(D76=0,0,SUM($J$20:J76)) -> 0 | W76: =IF(D76=0,0,V76-U76) -> 0 | X76: =IFERROR(V76/U76,"0%") -> 0% | Z76: =Z75+1 -> 45348 | AA76: =AA75+1 -> 45348 | AB76: 45348 | AC76: 9 | AD76: 月 | AE76: =IFERROR(AVERAGEIFS(J264:J293,D264:D293,1,G264:G293,"mon"),0) -> 0 | AF76: =COUNTIFS(D264:D293,1,G264:G293,"Mon") -> 0 | AH76: =AE76*AF76 -> 0 | AI76: =AH76/$M$14 -> 0 | AJ76: =SUM(AI76:AI82) -> 1 | AK76: 264〜293
C77: =C76+1 -> 58 | D77: 1 | E77: =TEXT(AA77,"m") -> 2 | F77: =F76+1 -> 45349 | G77: =TEXT(Z77,"ddd") -> Tue | J77: 66200 | L77: =IF(D77=0,0,$K$7) -> 85869.804 | M77: =IF(D77=0,0,J77-L77) -> -19669.804 | N77: =IFERROR(J77/L77,"0%") -> 0.77093456 | P77: =IF(D77=0,0,SUM($L$51:L77)) -> 1975005.5 | Q77: =IF(D77=0,0,SUM($J$51:J77)) -> 2140800 | R77: =IF(D77=0,0,Q77-P77) -> 165794.51 | S77: =IFERROR(Q77/P77,"0%") -> 1.0839464 | U77: =IF(D77=0,0,SUM($L$20:L77)) -> 3884345.8 | V77: =IF(D77=0,0,SUM($J$20:J77)) -> 4044500 | W77: =IF(D77=0,0,V77-U77) -> 160154.15 | X77: =IFERROR(V77/U77,"0%") -> 1.0412307 | Z77: =Z76+1 -> 45349 | AA77: =AA76+1 -> 45349 | AB77: 45349 | AC77: 9 | AD77: 火 | AE77: =AVERAGEIFS(J264:J293,D264:D293,1,G264:G293,"tue") -> 81987.5 | AF77: =COUNTIFS(D264:D293,1,G264:G293,"tue") -> 4 | AH77: =AE77*AF77 -> 327950 | AI77: =AH77/$M$14 -> 0.14137909
C78: =C77+1 -> 59 | D78: 1 | E78: =TEXT(AA78,"m") -> 2 | F78: =F77+1 -> 45350 | G78: =TEXT(Z78,"ddd") -> Wed | J78: 69550 | L78: =IF(D78=0,0,$K$7) -> 85869.804 | M78: =IF(D78=0,0,J78-L78) -> -16319.804 | N78: =IFERROR(J78/L78,"0%") -> 0.80994711 | P78: =IF(D78=0,0,SUM($L$51:L78)) -> 2060875.3 | Q78: =IF(D78=0,0,SUM($J$51:J78)) -> 2210350 | R78: =IF(D78=0,0,Q78-P78) -> 149474.7 | S78: =IFERROR(Q78/P78,"0%") -> 1.0725297 | U78: =IF(D78=0,0,SUM($L$20:L78)) -> 3970215.6 | V78: =IF(D78=0,0,SUM($J$20:J78)) -> 4114050 | W78: =IF(D78=0,0,V78-U78) -> 143834.35 | X78: =IFERROR(V78/U78,"0%") -> 1.0362283 | Z78: =Z77+1 -> 45350 | AA78: =AA77+1 -> 45350 | AB78: 45350 | AC78: 9 | AD78: 水 | AE78: =AVERAGEIFS(J264:J293,D264:D293,1,G264:G293,"wed") -> 86775 | AF78: =COUNTIFS(D264:D293,1,G264:G293,"wed") -> 4 | AH78: =AE78*AF78 -> 347100 | AI78: =AH78/$M$14 -> 0.14963464
C79: =C78+1 -> 60 | D79: 1 | E79: =TEXT(AA79,"m") -> 2 | F79: =F78+1 -> 45351 | G79: =TEXT(Z79,"ddd") -> Thu | J79: 42000 | L79: =IF(D79=0,0,$K$7) -> 85869.804 | M79: =IF(D79=0,0,J79-L79) -> -43869.804 | N79: =IFERROR(J79/L79,"0%") -> 0.48911256 | P79: =IF(D79=0,0,SUM($L$51:L79)) -> 2146745.1 | Q79: =IF(D79=0,0,SUM($J$51:J79)) -> 2252350 | R79: =IF(D79=0,0,Q79-P79) -> 105604.9 | S79: =IFERROR(Q79/P79,"0%") -> 1.049193 | U79: =IF(D79=0,0,SUM($L$20:L79)) -> 4056085.5 | V79: =IF(D79=0,0,SUM($J$20:J79)) -> 4156050 | W79: =IF(D79=0,0,V79-U79) -> 99964.546 | X79: =IFERROR(V79/U79,"0%") -> 1.0246456 | Z79: =Z78+1 -> 45351 | AA79: =AA78+1 -> 45351 | AB79: 45351 | AC79: 9 | AD79: 木 | AE79: =AVERAGEIFS(J264:J293,D264:D293,1,G264:G293,"thu") -> 103725 | AF79: =COUNTIFS(D264:D293,1,G264:G293,"thu") -> 4 | AH79: =AE79*AF79 -> 414900 | AI79: =AH79/$M$14 -> 0.17886319
C80: =C79+1 -> 61 | D80: 1 | E80: =TEXT(AA80,"m") -> 3 | F80: =F79+1 -> 45352 | G80: =TEXT(Z80,"ddd") -> Fri | J80: 108350 | L80: =IF(D80=0,0,$K$8) -> 101023.3 | M80: =IF(D80=0,0,J80-L80) -> 7326.701 | N80: =IFERROR(J80/L80,"0%") -> 1.0725249 | P80: =IF(D80=0,0,$L$80) -> 101023.3 | Q80: =IF(D80=0,0,$J$80) -> 108350 | R80: =IF(D80=0,0,Q80-P80) -> 7326.701 | S80: =IFERROR(Q80/P80,"0%") -> 1.0725249 | U80: =IF(D80=0,0,SUM($L$20:L80)) -> 4157108.8 | V80: =IF(D80=0,0,SUM($J$20:J80)) -> 4264400 | W80: =IF(D80=0,0,V80-U80) -> 107291.25 | X80: =IFERROR(V80/U80,"0%") -> 1.0258091 | Z80: =Z79+1 -> 45352 | AA80: =AA79+1 -> 45352 | AB80: 45352 | AC80: 9 | AD80: 金 | AE80: =AVERAGEIFS(J264:J293,D264:D293,1,G264:G293,"fri") -> 168625 | AF80: =COUNTIFS(D264:D293,1,G264:G293,"fri") -> 4 | AH80: =AE80*AF80 -> 674500 | AI80: =AH80/$M$14 -> 0.29077663
C81: =C80+1 -> 62 | D81: 1 | E81: =TEXT(AA81,"m") -> 3 | F81: =F80+1 -> 45353 | G81: =TEXT(Z81,"ddd") -> Sat | J81: 92250 | L81: =IF(D81=0,0,$K$8) -> 101023.3 | M81: =IF(D81=0,0,J81-L81) -> -8773.299 | N81: =IFERROR(J81/L81,"0%") -> 0.91315569 | P81: =IF(D81=0,0,SUM($L$80:L81)) -> 202046.6 | Q81: =IF(D81=0,0,SUM($J$80:J81)) -> 200600 | R81: =IF(D81=0,0,Q81-P81) -> -1446.5979 | S81: =IFERROR(Q81/P81,"0%") -> 0.99284028 | U81: =IF(D81=0,0,SUM($L$20:L81)) -> 4258132.1 | V81: =IF(D81=0,0,SUM($J$20:J81)) -> 4356650 | W81: =IF(D81=0,0,V81-U81) -> 98517.948 | X81: =IFERROR(V81/U81,"0%") -> 1.0231364 | Z81: =Z80+1 -> 45353 | AA81: =AA80+1 -> 45353 | AB81: 45353 | AC81: 9 | AD81: 土 | AE81: =AVERAGEIFS(J264:J293,D264:D293,1,G264:G293,"sat") -> 71775 | AF81: =COUNTIFS(D264:D293,1,G264:G293,"sat") -> 4 | AH81: =AE81*AF81 -> 287100 | AI81: =AH81/$M$14 -> 0.12376867
C82: =C81+1 -> 63 | D82: 1 | E82: =TEXT(AA82,"m") -> 3 | F82: =F81+1 -> 45354 | G82: =TEXT(Z82,"ddd") -> Sun | H82: 日曜日 | J82: 100950 | L82: =IF(D82=0,0,$K$8) -> 101023.3 | M82: =IF(D82=0,0,J82-L82) -> -73.298969 | N82: =IFERROR(J82/L82,"0%") -> 0.99927444 | P82: =IF(D82=0,0,SUM($L$80:L82)) -> 303069.9 | Q82: =IF(D82=0,0,SUM($J$80:J82)) -> 301550 | R82: =IF(D82=0,0,Q82-P82) -> -1519.8969 | S82: =IFERROR(Q82/P82,"0%") -> 0.994985 | U82: =IF(D82=0,0,SUM($L$20:L82)) -> 4359155.4 | V82: =IF(D82=0,0,SUM($J$20:J82)) -> 4457600 | W82: =IF(D82=0,0,V82-U82) -> 98444.649 | X82: =IFERROR(V82/U82,"0%") -> 1.0225834 | Z82: =Z81+1 -> 45354 | AA82: =AA81+1 -> 45354 | AB82: 45354 | AC82: 9 | AD82: 日 | AE82: =IFERROR(AVERAGEIFS(J264:J293,D264:D293,1,G264:G293,"sun"),0) -> 89366.667 | AF82: =IFERROR(COUNTIFS(D264:D293,1,G264:G293,"sun"),0) -> 3 | AH82: =AE82*AF82 -> 268100 | AI82: =AH82/$M$14 -> 0.11557778
C83: =C82+1 -> 64 | D83: 0 | E83: =TEXT(AA83,"m") -> 3 | F83: =F82+1 -> 45355 | G83: =TEXT(Z83,"ddd") -> Mon | L83: =IF(D83=0,0,$K$8) -> 0 | M83: =IF(D83=0,0,J83-L83) -> 0 | N83: =IFERROR(J83/L83,"0%") -> 0% | P83: =IF(D83=0,0,SUM($L$80:L83)) -> 0 | Q83: =IF(D83=0,0,SUM($J$80:J83)) -> 0 | R83: =IF(D83=0,0,Q83-P83) -> 0 | S83: =IFERROR(Q83/P83,"0%") -> 0% | U83: =IF(D83=0,0,SUM($L$20:L83)) -> 0 | V83: =IF(D83=0,0,SUM($J$20:J83)) -> 0 | W83: =IF(D83=0,0,V83-U83) -> 0 | X83: =IFERROR(V83/U83,"0%") -> 0% | Z83: =Z82+1 -> 45355 | AA83: =AA82+1 -> 45355 | AB83: 45355 | AC83: 10 | AD83: 月 | AE83: =IFERROR(AVERAGEIFS(J294:J324,D294:D324,1,G294:G324,"mon"),0) -> 0 | AF83: =COUNTIFS(D294:D324,1,G294:G324,"Mon") -> 0 | AH83: =AE83*AF83 -> 0 | AI83: =AH83/$M$15 -> 0 | AJ83: =SUM(AI83:AI89) -> 1 | AK83: 294〜324
C84: =C83+1 -> 65 | D84: 1 | E84: =TEXT(AA84,"m") -> 3 | F84: =F83+1 -> 45356 | G84: =TEXT(Z84,"ddd") -> Tue | J84: 37100 | L84: =IF(D84=0,0,$K$8) -> 101023.3 | M84: =IF(D84=0,0,J84-L84) -> -63923.299 | N84: =IFERROR(J84/L84,"0%") -> 0.36724202 | P84: =IF(D84=0,0,SUM($L$80:L84)) -> 404093.2 | Q84: =IF(D84=0,0,SUM($J$80:J84)) -> 338650 | R84: =IF(D84=0,0,Q84-P84) -> -65443.196 | S84: =IFERROR(Q84/P84,"0%") -> 0.83804925 | U84: =IF(D84=0,0,SUM($L$20:L84)) -> 4460178.6 | V84: =IF(D84=0,0,SUM($J$20:J84)) -> 4494700 | W84: =IF(D84=0,0,V84-U84) -> 34521.351 | X84: =IFERROR(V84/U84,"0%") -> 1.0077399 | Z84: =Z83+1 -> 45356 | AA84: =AA83+1 -> 45356 | AB84: 45356 | AC84: 10 | AD84: 火 | AE84: =AVERAGEIFS(J294:J324,D294:D324,1,G294:G324,"tue") -> 87800 | AF84: =COUNTIFS(D294:D324,1,G294:G324,"tue") -> 4 | AH84: =AE84*AF84 -> 351200 | AI84: =AH84/$M$15 -> 0.13143713
C85: =C84+1 -> 66 | D85: 1 | E85: =TEXT(AA85,"m") -> 3 | F85: =F84+1 -> 45357 | G85: =TEXT(Z85,"ddd") -> Wed | J85: 43400 | L85: =IF(D85=0,0,$K$8) -> 101023.3 | M85: =IF(D85=0,0,J85-L85) -> -57623.299 | N85: =IFERROR(J85/L85,"0%") -> 0.42960387 | P85: =IF(D85=0,0,SUM($L$80:L85)) -> 505116.49 | Q85: =IF(D85=0,0,SUM($J$80:J85)) -> 382050 | R85: =IF(D85=0,0,Q85-P85) -> -123066.49 | S85: =IFERROR(Q85/P85,"0%") -> 0.75636017 | U85: =IF(D85=0,0,SUM($L$20:L85)) -> 4561201.9 | V85: =IF(D85=0,0,SUM($J$20:J85)) -> 4538100 | W85: =IF(D85=0,0,V85-U85) -> -23101.948 | X85: =IFERROR(V85/U85,"0%") -> 0.99493512 | Z85: =Z84+1 -> 45357 | AA85: =AA84+1 -> 45357 | AB85: 45357 | AC85: 10 | AD85: 水 | AE85: =AVERAGEIFS(J294:J324,D294:D324,1,G294:G324,"wed") -> 90670 | AF85: =COUNTIFS(D294:D324,1,G294:G324,"wed") -> 5 | AH85: =AE85*AF85 -> 453350 | AI85: =AH85/$M$15 -> 0.16966692
C86: =C85+1 -> 67 | D86: 1 | E86: =TEXT(AA86,"m") -> 3 | F86: =F85+1 -> 45358 | G86: =TEXT(Z86,"ddd") -> Thu | J86: 34150 | L86: =IF(D86=0,0,$K$8) -> 101023.3 | M86: =IF(D86=0,0,J86-L86) -> -66873.299 | N86: =IFERROR(J86/L86,"0%") -> 0.33804083 | P86: =IF(D86=0,0,SUM($L$80:L86)) -> 606139.79 | Q86: =IF(D86=0,0,SUM($J$80:J86)) -> 416200 | R86: =IF(D86=0,0,Q86-P86) -> -189939.79 | S86: =IFERROR(Q86/P86,"0%") -> 0.68664028 | U86: =IF(D86=0,0,SUM($L$20:L86)) -> 4662225.2 | V86: =IF(D86=0,0,SUM($J$20:J86)) -> 4572250 | W86: =IF(D86=0,0,V86-U86) -> -89975.247 | X86: =IFERROR(V86/U86,"0%") -> 0.98070122 | Z86: =Z85+1 -> 45358 | AA86: =AA85+1 -> 45358 | AB86: 45358 | AC86: 10 | AD86: 木 | AE86: =AVERAGEIFS(J294:J324,D294:D324,1,G294:G324,"thu") -> 114050 | AF86: =COUNTIFS(D294:D324,1,G294:G324,"thu") -> 5 | AH86: =AE86*AF86 -> 570250 | AI86: =AH86/$M$15 -> 0.21341692
C87: =C86+1 -> 68 | D87: 1 | E87: =TEXT(AA87,"m") -> 3 | F87: =F86+1 -> 45359 | G87: =TEXT(Z87,"ddd") -> Fri | J87: 205100 | L87: =IF(D87=0,0,$K$8) -> 101023.3 | M87: =IF(D87=0,0,J87-L87) -> 104076.7 | N87: =IFERROR(J87/L87,"0%") -> 2.0302247 | P87: =IF(D87=0,0,SUM($L$80:L87)) -> 707163.09 | Q87: =IF(D87=0,0,SUM($J$80:J87)) -> 621300 | R87: =IF(D87=0,0,Q87-P87) -> -85863.093 | S87: =IFERROR(Q87/P87,"0%") -> 0.87858092 | U87: =IF(D87=0,0,SUM($L$20:L87)) -> 4763248.5 | V87: =IF(D87=0,0,SUM($J$20:J87)) -> 4777350 | W87: =IF(D87=0,0,V87-U87) -> 14101.454 | X87: =IFERROR(V87/U87,"0%") -> 1.0029605 | Z87: =Z86+1 -> 45359 | AA87: =AA86+1 -> 45359 | AB87: 45359 | AC87: 10 | AD87: 金 | AE87: =AVERAGEIFS(J294:J324,D294:D324,1,G294:G324,"fri") -> 137787.5 | AF87: =COUNTIFS(D294:D324,1,G294:G324,"fri") -> 4 | AH87: =AE87*AF87 -> 551150 | AI87: =AH87/$M$15 -> 0.20626871
C88: =C87+1 -> 69 | D88: 1 | E88: =TEXT(AA88,"m") -> 3 | F88: =F87+1 -> 45360 | G88: =TEXT(Z88,"ddd") -> Sat | J88: 88000 | L88: =IF(D88=0,0,$K$8) -> 101023.3 | M88: =IF(D88=0,0,J88-L88) -> -13023.299 | N88: =IFERROR(J88/L88,"0%") -> 0.87108618 | P88: =IF(D88=0,0,SUM($L$80:L88)) -> 808186.39 | Q88: =IF(D88=0,0,SUM($J$80:J88)) -> 709300 | R88: =IF(D88=0,0,Q88-P88) -> -98886.392 | S88: =IFERROR(Q88/P88,"0%") -> 0.87764408 | U88: =IF(D88=0,0,SUM($L$20:L88)) -> 4864271.8 | V88: =IF(D88=0,0,SUM($J$20:J88)) -> 4865350 | W88: =IF(D88=0,0,V88-U88) -> 1078.1546 | X88: =IFERROR(V88/U88,"0%") -> 1.0002216 | Z88: =Z87+1 -> 45360 | AA88: =AA87+1 -> 45360 | AB88: 45360 | AC88: 10 | AD88: 土 | AE88: =AVERAGEIFS(J294:J324,D294:D324,1,G294:G324,"sat") -> 90300 | AF88: =COUNTIFS(D294:D324,1,G294:G324,"sat") -> 4 | AH88: =AE88*AF88 -> 361200 | AI88: =AH88/$M$15 -> 0.13517964
C89: =C88+1 -> 70 | D89: 1 | E89: =TEXT(AA89,"m") -> 3 | F89: =F88+1 -> 45361 | G89: =TEXT(Z89,"ddd") -> Sun | H89: 日曜日 | J89: 110550 | L89: =IF(D89=0,0,$K$8) -> 101023.3 | M89: =IF(D89=0,0,J89-L89) -> 9526.701 | N89: =IFERROR(J89/L89,"0%") -> 1.094302 | P89: =IF(D89=0,0,SUM($L$80:L89)) -> 909209.69 | Q89: =IF(D89=0,0,SUM($J$80:J89)) -> 819850 | R89: =IF(D89=0,0,Q89-P89) -> -89359.691 | S89: =IFERROR(Q89/P89,"0%") -> 0.90171718 | U89: =IF(D89=0,0,SUM($L$20:L89)) -> 4965295.1 | V89: =IF(D89=0,0,SUM($J$20:J89)) -> 4975900 | W89: =IF(D89=0,0,V89-U89) -> 10604.856 | X89: =IFERROR(V89/U89,"0%") -> 1.0021358 | Z89: =Z88+1 -> 45361 | AA89: =AA88+1 -> 45361 | AB89: 45361 | AC89: 10 | AD89: 日 | AE89: =IFERROR(AVERAGEIFS(J294:J324,D294:D324,1,G294:G324,"sun"),0) -> 96212.5 | AF89: =IFERROR(COUNTIFS(D294:D324,1,G294:G324,"sun"),0) -> 4 | AH89: =AE89*AF89 -> 384850 | AI89: =AH89/$M$15 -> 0.14403069
C90: =C89+1 -> 71 | D90: 0 | E90: =TEXT(AA90,"m") -> 3 | F90: =F89+1 -> 45362 | G90: =TEXT(Z90,"ddd") -> Mon | L90: =IF(D90=0,0,$K$8) -> 0 | M90: =IF(D90=0,0,J90-L90) -> 0 | N90: =IFERROR(J90/L90,"0%") -> 0% | P90: =IF(D90=0,0,SUM($L$80:L90)) -> 0 | Q90: =IF(D90=0,0,SUM($J$80:J90)) -> 0 | R90: =IF(D90=0,0,Q90-P90) -> 0 | S90: =IFERROR(Q90/P90,"0%") -> 0% | U90: =IF(D90=0,0,SUM($L$20:L90)) -> 0 | V90: =IF(D90=0,0,SUM($J$20:J90)) -> 0 | W90: =IF(D90=0,0,V90-U90) -> 0 | X90: =IFERROR(V90/U90,"0%") -> 0% | Z90: =Z89+1 -> 45362 | AA90: =AA89+1 -> 45362 | AB90: 45362 | AC90: 11 | AD90: 月 | AE90: =IFERROR(AVERAGEIFS(J325:J354,D325:D354,1,G325:G354,"mon"),0) -> 0 | AF90: =COUNTIFS(D325:D354,1,G325:G354,"Mon") -> 0 | AH90: =AE90*AF90 -> 0 | AI90: =AH90/$M$16 -> 0 | AJ90: =SUM(AI90:AI96) -> 1 | AK90: 325〜354
C91: =C90+1 -> 72 | D91: 1 | E91: =TEXT(AA91,"m") -> 3 | F91: =F90+1 -> 45363 | G91: =TEXT(Z91,"ddd") -> Tue | J91: 41550 | L91: =IF(D91=0,0,$K$8) -> 101023.3 | M91: =IF(D91=0,0,J91-L91) -> -59473.299 | N91: =IFERROR(J91/L91,"0%") -> 0.41129126 | P91: =IF(D91=0,0,SUM($L$80:L91)) -> 1010233 | Q91: =IF(D91=0,0,SUM($J$80:J91)) -> 861400 | R91: =IF(D91=0,0,Q91-P91) -> -148832.99 | S91: =IFERROR(Q91/P91,"0%") -> 0.85267459 | U91: =IF(D91=0,0,SUM($L$20:L91)) -> 5066318.4 | V91: =IF(D91=0,0,SUM($J$20:J91)) -> 5017450 | W91: =IF(D91=0,0,V91-U91) -> -48868.443 | X91: =IFERROR(V91/U91,"0%") -> 0.99035425 | Z91: =Z90+1 -> 45363 | AA91: =AA90+1 -> 45363 | AB91: 45363 | AC91: 11 | AD91: 火 | AE91: =AVERAGEIFS(J325:J354,D325:D354,1,G325:G354,"tue") -> 107900 | AF91: =COUNTIFS(D325:D354,1,G325:G354,"tue") -> 2 | AH91: =AE91*AF91 -> 215800 | AI91: =AH91/$M$16 -> 0.097636014
C92: =C91+1 -> 73 | D92: 1 | E92: =TEXT(AA92,"m") -> 3 | F92: =F91+1 -> 45364 | G92: =TEXT(Z92,"ddd") -> Wed | J92: 75800 | L92: =IF(D92=0,0,$K$8) -> 101023.3 | M92: =IF(D92=0,0,J92-L92) -> -25223.299 | N92: =IFERROR(J92/L92,"0%") -> 0.75032196 | P92: =IF(D92=0,0,SUM($L$80:L92)) -> 1111256.3 | Q92: =IF(D92=0,0,SUM($J$80:J92)) -> 937200 | R92: =IF(D92=0,0,Q92-P92) -> -174056.29 | S92: =IFERROR(Q92/P92,"0%") -> 0.84336981 | U92: =IF(D92=0,0,SUM($L$20:L92)) -> 5167341.7 | V92: =IF(D92=0,0,SUM($J$20:J92)) -> 5093250 | W92: =IF(D92=0,0,V92-U92) -> -74091.742 | X92: =IFERROR(V92/U92,"0%") -> 0.98566154 | Z92: =Z91+1 -> 45364 | AA92: =AA91+1 -> 45364 | AB92: 45364 | AC92: 11 | AD92: 水 | AE92: =AVERAGEIFS(J325:J354,D325:D354,1,G325:G354,"wed") -> 59687.5 | AF92: =COUNTIFS(D325:D354,1,G325:G354,"wed") -> 4 | AH92: =AE92*AF92 -> 238750 | AI92: =AH92/$M$16 -> 0.10801945
C93: =C92+1 -> 74 | D93: 1 | E93: =TEXT(AA93,"m") -> 3 | F93: =F92+1 -> 45365 | G93: =TEXT(Z93,"ddd") -> Thu | J93: 53450 | L93: =IF(D93=0,0,$K$8) -> 101023.3 | M93: =IF(D93=0,0,J93-L93) -> -47573.299 | N93: =IFERROR(J93/L93,"0%") -> 0.52908587 | P93: =IF(D93=0,0,SUM($L$80:L93)) -> 1212279.6 | Q93: =IF(D93=0,0,SUM($J$80:J93)) -> 990650 | R93: =IF(D93=0,0,Q93-P93) -> -221629.59 | S93: =IFERROR(Q93/P93,"0%") -> 0.81717948 | U93: =IF(D93=0,0,SUM($L$20:L93)) -> 5268365 | V93: =IF(D93=0,0,SUM($J$20:J93)) -> 5146700 | W93: =IF(D93=0,0,V93-U93) -> -121665.04 | X93: =IFERROR(V93/U93,"0%") -> 0.97690649 | Z93: =Z92+1 -> 45365 | AA93: =AA92+1 -> 45365 | AB93: 45365 | AC93: 11 | AD93: 木 | AE93: =AVERAGEIFS(J325:J354,D325:D354,1,G325:G354,"thu") -> 71512.5 | AF93: =COUNTIFS(D325:D354,1,G325:G354,"thu") -> 4 | AH93: =AE93*AF93 -> 286050 | AI93: =AH93/$M$16 -> 0.12941975
C94: =C93+1 -> 75 | D94: 1 | E94: =TEXT(AA94,"m") -> 3 | F94: =F93+1 -> 45366 | G94: =TEXT(Z94,"ddd") -> Fri | J94: 144650 | L94: =IF(D94=0,0,$K$8) -> 101023.3 | M94: =IF(D94=0,0,J94-L94) -> 43626.701 | N94: =IFERROR(J94/L94,"0%") -> 1.4318479 | P94: =IF(D94=0,0,SUM($L$80:L94)) -> 1313302.9 | Q94: =IF(D94=0,0,SUM($J$80:J94)) -> 1135300 | R94: =IF(D94=0,0,Q94-P94) -> -178002.89 | S94: =IFERROR(Q94/P94,"0%") -> 0.86446167 | U94: =IF(D94=0,0,SUM($L$20:L94)) -> 5369388.3 | V94: =IF(D94=0,0,SUM($J$20:J94)) -> 5291350 | W94: =IF(D94=0,0,V94-U94) -> -78038.34 | X94: =IFERROR(V94/U94,"0%") -> 0.98546607 | Z94: =Z93+1 -> 45366 | AA94: =AA93+1 -> 45366 | AB94: 45366 | AC94: 11 | AD94: 金 | AE94: =AVERAGEIFS(J325:J354,D325:D354,1,G325:G354,"fri") -> 105520 | AF94: =COUNTIFS(D325:D354,1,G325:G354,"fri") -> 5 | AH94: =AE94*AF94 -> 527600 | AI94: =AH94/$M$16 -> 0.23870603
C95: =C94+1 -> 76 | D95: 1 | E95: =TEXT(AA95,"m") -> 3 | F95: =F94+1 -> 45367 | G95: =TEXT(Z95,"ddd") -> Sat | J95: 124600 | L95: =IF(D95=0,0,$K$8) -> 101023.3 | M95: =IF(D95=0,0,J95-L95) -> 23576.701 | N95: =IFERROR(J95/L95,"0%") -> 1.2333788 | P95: =IF(D95=0,0,SUM($L$80:L95)) -> 1414326.2 | Q95: =IF(D95=0,0,SUM($J$80:J95)) -> 1259900 | R95: =IF(D95=0,0,Q95-P95) -> -154426.19 | S95: =IFERROR(Q95/P95,"0%") -> 0.89081289 | U95: =IF(D95=0,0,SUM($L$20:L95)) -> 5470411.6 | V95: =IF(D95=0,0,SUM($J$20:J95)) -> 5415950 | W95: =IF(D95=0,0,V95-U95) -> -54461.639 | X95: =IFERROR(V95/U95,"0%") -> 0.99004433 | Z95: =Z94+1 -> 45367 | AA95: =AA94+1 -> 45367 | AB95: 45367 | AC95: 11 | AD95: 土 | AE95: =AVERAGEIFS(J325:J354,D325:D354,1,G325:G354,"sat") -> 88200 | AF95: =COUNTIFS(D325:D354,1,G325:G354,"sat") -> 5 | AH95: =AE95*AF95 -> 441000 | AI95: =AH95/$M$16 -> 0.19952494
C96: =C95+1 -> 77 | D96: 1 | E96: =TEXT(AA96,"m") -> 3 | F96: =F95+1 -> 45368 | G96: =TEXT(Z96,"ddd") -> Sun | H96: 日曜日 | J96: 105500 | L96: =IF(D96=0,0,$K$8) -> 101023.3 | M96: =IF(D96=0,0,J96-L96) -> 4476.701 | N96: =IFERROR(J96/L96,"0%") -> 1.0443136 | P96: =IF(D96=0,0,SUM($L$80:L96)) -> 1515349.5 | Q96: =IF(D96=0,0,SUM($J$80:J96)) -> 1365400 | R96: =IF(D96=0,0,Q96-P96) -> -149949.48 | S96: =IFERROR(Q96/P96,"0%") -> 0.90104627 | U96: =IF(D96=0,0,SUM($L$20:L96)) -> 5571434.9 | V96: =IF(D96=0,0,SUM($J$20:J96)) -> 5521450 | W96: =IF(D96=0,0,V96-U96) -> -49984.938 | X96: =IFERROR(V96/U96,"0%") -> 0.99102835 | Z96: =Z95+1 -> 45368 | AA96: =AA95+1 -> 45368 | AB96: 45368 | AC96: 11 | AD96: 日 | AE96: =IFERROR(AVERAGEIFS(J325:J354,D325:D354,1,G325:G354,"sun"),0) -> 125262.5 | AF96: =IFERROR(COUNTIFS(D325:D354,1,G325:G354,"sun"),0) -> 4 | AH96: =AE96*AF96 -> 501050 | AI96: =AH96/$M$16 -> 0.22669381
C97: =C96+1 -> 78 | D97: 0 | E97: =TEXT(AA97,"m") -> 3 | F97: =F96+1 -> 45369 | G97: =TEXT(Z97,"ddd") -> Mon | L97: =IF(D97=0,0,$K$8) -> 0 | M97: =IF(D97=0,0,J97-L97) -> 0 | N97: =IFERROR(J97/L97,"0%") -> 0% | P97: =IF(D97=0,0,SUM($L$80:L97)) -> 0 | Q97: =IF(D97=0,0,SUM($J$80:J97)) -> 0 | R97: =IF(D97=0,0,Q97-P97) -> 0 | S97: =IFERROR(Q97/P97,"0%") -> 0% | U97: =IF(D97=0,0,SUM($L$20:L97)) -> 0 | V97: =IF(D97=0,0,SUM($J$20:J97)) -> 0 | W97: =IF(D97=0,0,V97-U97) -> 0 | X97: =IFERROR(V97/U97,"0%") -> 0% | Z97: =Z96+1 -> 45369 | AA97: =AA96+1 -> 45369 | AB97: 45369 | AC97: 12 | AD97: 月 | AE97: =AVERAGEIFS(J355:J385,D355:D385,1,G355:G385,"mon") -> 76050 | AF97: =COUNTIFS(D355:D385,1,G355:G385,"Mon") -> 1 | AH97: =AE97*AF97 -> 76050 | AI97: =AH97/$M$17 -> 0.032139461 | AJ97: =SUM(AI97:AI103) -> 1 | AK97: 355〜385
C98: =C97+1 -> 79 | D98: 0 | E98: =TEXT(AA98,"m") -> 3 | F98: =F97+1 -> 45370 | G98: =TEXT(Z98,"ddd") -> Tue | L98: =IF(D98=0,0,$K$8) -> 0 | M98: =IF(D98=0,0,J98-L98) -> 0 | N98: =IFERROR(J98/L98,"0%") -> 0% | P98: =IF(D98=0,0,SUM($L$80:L98)) -> 0 | Q98: =IF(D98=0,0,SUM($J$80:J98)) -> 0 | R98: =IF(D98=0,0,Q98-P98) -> 0 | S98: =IFERROR(Q98/P98,"0%") -> 0% | U98: =IF(D98=0,0,SUM($L$20:L98)) -> 0 | V98: =IF(D98=0,0,SUM($J$20:J98)) -> 0 | W98: =IF(D98=0,0,V98-U98) -> 0 | X98: =IFERROR(V98/U98,"0%") -> 0% | Z98: =Z97+1 -> 45370 | AA98: =AA97+1 -> 45370 | AB98: 45370 | AC98: 12 | AD98: 火 | AE98: =AVERAGEIFS(J355:J385,D355:D385,1,G355:G385,"tue") -> 121350 | AF98: =COUNTIFS(D355:D385,1,G355:G385,"tue") -> 3 | AH98: =AE98*AF98 -> 364050 | AI98: =AH98/$M$17 -> 0.15385103
C99: =C98+1 -> 80 | D99: 0 | E99: =TEXT(AA99,"m") -> 3 | F99: =F98+1 -> 45371 | G99: =TEXT(Z99,"ddd") -> Wed | H99: 祝日 | L99: =IF(D99=0,0,$K$8) -> 0 | M99: =IF(D99=0,0,J99-L99) -> 0 | N99: =IFERROR(J99/L99,"0%") -> 0% | P99: =IF(D99=0,0,SUM($L$80:L99)) -> 0 | Q99: =IF(D99=0,0,SUM($J$80:J99)) -> 0 | R99: =IF(D99=0,0,Q99-P99) -> 0 | S99: =IFERROR(Q99/P99,"0%") -> 0% | U99: =IF(D99=0,0,SUM($L$20:L99)) -> 0 | V99: =IF(D99=0,0,SUM($J$20:J99)) -> 0 | W99: =IF(D99=0,0,V99-U99) -> 0 | X99: =IFERROR(V99/U99,"0%") -> 0% | Z99: =Z98+1 -> 45371 | AA99: =AA98+1 -> 45371 | AB99: 45371 | AC99: 12 | AD99: 水 | AE99: =AVERAGEIFS(J355:J385,D355:D385,1,G355:G385,"wed") -> 125700 | AF99: =COUNTIFS(D355:D385,1,G355:G385,"wed") -> 3 | AH99: =AE99*AF99 -> 377100 | AI99: =AH99/$M$17 -> 0.15936609
C100: =C99+1 -> 81 | D100: 1 | E100: =TEXT(AA100,"m") -> 3 | F100: =F99+1 -> 45372 | G100: =TEXT(Z100,"ddd") -> Thu | J100: 91750 | L100: =IF(D100=0,0,$K$8) -> 101023.3 | M100: =IF(D100=0,0,J100-L100) -> -9273.299 | N100: =IFERROR(J100/L100,"0%") -> 0.90820633 | P100: =IF(D100=0,0,SUM($L$80:L100)) -> 1616372.8 | Q100: =IF(D100=0,0,SUM($J$80:J100)) -> 1457150 | R100: =IF(D100=0,0,Q100-P100) -> -159222.78 | S100: =IFERROR(Q100/P100,"0%") -> 0.90149377 | U100: =IF(D100=0,0,SUM($L$20:L100)) -> 5672458.2 | V100: =IF(D100=0,0,SUM($J$20:J100)) -> 5613200 | W100: =IF(D100=0,0,V100-U100) -> -59258.237 | X100: =IFERROR(V100/U100,"0%") -> 0.98955334 | Z100: =Z99+1 -> 45372 | AA100: =AA99+1 -> 45372 | AB100: 45372 | AC100: 12 | AD100: 木 | AE100: =AVERAGEIFS(J355:J385,D355:D385,1,G355:G385,"thu") -> 97950 | AF100: =COUNTIFS(D355:D385,1,G355:G385,"thu") -> 4 | AH100: =AE100*AF100 -> 391800 | AI100: =AH100/$M$17 -> 0.16557845
C101: =C100+1 -> 82 | D101: 1 | E101: =TEXT(AA101,"m") -> 3 | F101: =F100+1 -> 45373 | G101: =TEXT(Z101,"ddd") -> Fri | J101: 88100 | L101: =IF(D101=0,0,$K$8) -> 101023.3 | M101: =IF(D101=0,0,J101-L101) -> -12923.299 | N101: =IFERROR(J101/L101,"0%") -> 0.87207605 | P101: =IF(D101=0,0,SUM($L$80:L101)) -> 1717396.1 | Q101: =IF(D101=0,0,SUM($J$80:J101)) -> 1545250 | R101: =IF(D101=0,0,Q101-P101) -> -172146.08 | S101: =IFERROR(Q101/P101,"0%") -> 0.89976332 | U101: =IF(D101=0,0,SUM($L$20:L101)) -> 5773481.5 | V101: =IF(D101=0,0,SUM($J$20:J101)) -> 5701300 | W101: =IF(D101=0,0,V101-U101) -> -72181.536 | X101: =IFERROR(V101/U101,"0%") -> 0.98749775 | Z101: =Z100+1 -> 45373 | AA101: =AA100+1 -> 45373 | AB101: 45373 | AC101: 12 | AD101: 金 | AE101: =AVERAGEIFS(J355:J385,D355:D385,1,G355:G385,"fri") -> 124712.5 | AF101: =COUNTIFS(D355:D385,1,G355:G385,"fri") -> 4 | AH101: =AE101*AF101 -> 498850 | AI101: =AH101/$M$17 -> 0.21081881
C102: =C101+1 -> 83 | D102: 1 | E102: =TEXT(AA102,"m") -> 3 | F102: =F101+1 -> 45374 | G102: =TEXT(Z102,"ddd") -> Sat | J102: 111100 | L102: =IF(D102=0,0,$K$8) -> 101023.3 | M102: =IF(D102=0,0,J102-L102) -> 10076.701 | N102: =IFERROR(J102/L102,"0%") -> 1.0997463 | P102: =IF(D102=0,0,SUM($L$80:L102)) -> 1818419.4 | Q102: =IF(D102=0,0,SUM($J$80:J102)) -> 1656350 | R102: =IF(D102=0,0,Q102-P102) -> -162069.38 | S102: =IFERROR(Q102/P102,"0%") -> 0.91087349 | U102: =IF(D102=0,0,SUM($L$20:L102)) -> 5874504.8 | V102: =IF(D102=0,0,SUM($J$20:J102)) -> 5812400 | W102: =IF(D102=0,0,V102-U102) -> -62104.835 | X102: =IFERROR(V102/U102,"0%") -> 0.98942807 | Z102: =Z101+1 -> 45374 | AA102: =AA101+1 -> 45374 | AB102: 45374 | AC102: 12 | AD102: 土 | AE102: =AVERAGEIFS(J355:J385,D355:D385,1,G355:G385,"sat") -> 82450 | AF102: =COUNTIFS(D355:D385,1,G355:G385,"sat") -> 4 | AH102: =AE102*AF102 -> 329800 | AI102: =AH102/$M$17 -> 0.13937665
C103: =C102+1 -> 84 | D103: 1 | E103: =TEXT(AA103,"m") -> 3 | F103: =F102+1 -> 45375 | G103: =TEXT(Z103,"ddd") -> Sun | H103: 日曜日 | J103: 114900 | L103: =IF(D103=0,0,$K$8) -> 101023.3 | M103: =IF(D103=0,0,J103-L103) -> 13876.701 | N103: =IFERROR(J103/L103,"0%") -> 1.1373614 | P103: =IF(D103=0,0,SUM($L$80:L103)) -> 1919442.7 | Q103: =IF(D103=0,0,SUM($J$80:J103)) -> 1771250 | R103: =IF(D103=0,0,Q103-P103) -> -148192.68 | S103: =IFERROR(Q103/P103,"0%") -> 0.9227939 | U103: =IF(D103=0,0,SUM($L$20:L103)) -> 5975528.1 | V103: =IF(D103=0,0,SUM($J$20:J103)) -> 5927300 | W103: =IF(D103=0,0,V103-U103) -> -48228.134 | X103: =IFERROR(V103/U103,"0%") -> 0.99192906 | Z103: =Z102+1 -> 45375 | AA103: =AA102+1 -> 45375 | AB103: 45375 | AC103: 12 | AD103: 日 | AE103: =IFERROR(AVERAGEIFS(J355:J385,D355:D385,1,G355:G385,"sun"),0) -> 65720 | AF103: =IFERROR(COUNTIFS(D355:D385,1,G355:G385,"sun"),0) -> 5 | AH103: =AE103*AF103 -> 328600 | AI103: =AH103/$M$17 -> 0.13886952
...

Sheet 適正原価＆人件費プリントアウト用
A1: =TODAY() -> 45975 | C1: 月 | H1: 営業日数 | I1: {=INDIRECT("'適正原価率表(仕入れお小遣い制度)'!C" & (2 * MONTH(A1) + 2))} -> 22
A2: 月次適正原価率表
B3: 月次 | F3: 日次
A4: フード | B4: {=INDEX('適正原価率表(仕入れお小遣い制度)'!I:I, MONTH(A1)*2+2)} -> 295576.49 | F4: {=INDEX('適正原価率表(仕入れお小遣い制度)'!J:J, MONTH(A1)*2+2)} -> 13435.295
A5: ドリンク | B5: {=INDEX('適正原価率表(仕入れお小遣い制度)'!I:I, MONTH(A1)*2+3)} -> 256557.25 | F5: {=INDEX('適正原価率表(仕入れお小遣い制度)'!J:J, MONTH(A1)*2+3)} -> 11661.693
A7: 月次適正人件費表
B8: 1日 | D8: フード | G8: ドリンク
A9: ランチ | B9: {=INDIRECT("'適正人件費表'!J" & (2 * MONTH(A1) + 2))} -> 3 | D9: =1 + IF(B9-4 >= 8, 1, 0) + IF(B9-4 >= 9, 1, 0) -> 1 | G9: =1 + IF(B9-4 >= 4, 1, 0) + IF(B9-4 >= 5, 1, 0) -> 1
A10: ディナー | D10: =1 + IF(B9-4 >= 6, 1, 0) + IF(B9-4 >= 7, 1, 0) -> 1 | G10: =1 + IF(B9-4 >= 1, 1, 0) + IF(B9-4 >= 2, 1, 0) + IF(B9-4 >= 3, 1, 0) -> 1

Sheet 月次累積原価率表
A1: 45658 | B1: 【食材費】フード適正早見表 | K1: 【食材費】ドリンク適正早見表
B3: 1月 | E3: フード目標日次 | F3: フード目標累計 | G3: フード実績 | H3: フード累積 | I3: 差額 | K3: =B3 -> 1月 | N3: ドリンク目標日次 | O3: ドリンク目標累計 | P3: ドリンク実績 | Q3: ドリンク累積 | R3: 差額
B4: =A1 -> 45658 | C4: =B4 -> 45658 | D4: =目標_2025R7!D21 -> 0 | E4: =IF(D4=1,'適正原価率表(仕入れお小遣い制度)'!$J$4,0) -> 0 | F4: =IF(D4=1,E4,0) -> 0 | H4: =IF(D4=1,G4,0) -> 0 | I4: =IF(D4=1,F4-H4,0) -> 0 | K4: =B4 -> 45658 | L4: =C4 -> 45658 | M4: =D4 -> 0 | N4: =IF(M4=1,'適正原価率表(仕入れお小遣い制度)'!$J$5,0) -> 0 | O4: =IF(M4=1,N4,0) -> 0 | Q4: =IF(M4=1,P4,0) -> 0 | R4: =IF(D4=1,O4-Q4,0) -> 0 | T4: =A1 -> 45658
B5: =B4+1 -> 45659 | C5: =B5 -> 45659 | D5: =目標_2025R7!D22 -> 0 | E5: =IF(D5=1,'適正原価率表(仕入れお小遣い制度)'!$J$4,0) -> 0 | F5: =IF(D5=1,SUM($E$4:E5),0) -> 0 | H5: =IF(D5=1,SUM($G$4:G5),0) -> 0 | I5: =IF(D5=1,F5-H5,0) -> 0 | K5: 45659 | L5: =C5 -> 45659 | M5: =D5 -> 0 | N5: =IF(M5=1,'適正原価率表(仕入れお小遣い制度)'!$J$5,0) -> 0 | O5: =IF(M5=1,SUM($N$4:N5),0) -> 0 | Q5: =IF(M5=1,SUM($P$4:P5),0) -> 0 | R5: =IF(D5=1,O5-Q5,0) -> 0 | T5: =T4+1 -> 45659
B6: =B5+1 -> 45660 | C6: =B6 -> 45660 | D6: =目標_2025R7!D23 -> 0 | E6: =IF(D6=1,'適正原価率表(仕入れお小遣い制度)'!$J$4,0) -> 0 | F6: =IF(D6=1,SUM($E$4:E6),0) -> 0 | H6: =IF(D6=1,SUM($G$4:G6),0) -> 0 | I6: =IF(D6=1,F6-H6,0) -> 0 | K6: 45660 | L6: =C6 -> 45660 | M6: =D6 -> 0 | N6: =IF(M6=1,'適正原価率表(仕入れお小遣い制度)'!$J$5,0) -> 0 | O6: =IF(M6=1,SUM($N$4:N6),0) -> 0 | Q6: =IF(M6=1,SUM($P$4:P6),0) -> 0 | R6: =IF(D6=1,O6-Q6,0) -> 0 | T6: =T5+1 -> 45660
B7: =B6+1 -> 45661 | C7: =B7 -> 45661 | D7: =目標_2025R7!D24 -> 0 | E7: =IF(D7=1,'適正原価率表(仕入れお小遣い制度)'!$J$4,0) -> 0 | F7: =IF(D7=1,SUM($E$4:E7),0) -> 0 | H7: =IF(D7=1,SUM($G$4:G7),0) -> 0 | I7: =IF(D7=1,F7-H7,0) -> 0 | K7: 45661 | L7: =C7 -> 45661 | M7: =D7 -> 0 | N7: =IF(M7=1,'適正原価率表(仕入れお小遣い制度)'!$J$5,0) -> 0 | O7: =IF(M7=1,SUM($N$4:N7),0) -> 0 | Q7: =IF(M7=1,SUM($P$4:P7),0) -> 0 | R7: =IF(D7=1,O7-Q7,0) -> 0 | T7: =T6+1 -> 45661
B8: =B7+1 -> 45662 | C8: =B8 -> 45662 | D8: =目標_2025R7!D25 -> 0 | E8: =IF(D8=1,'適正原価率表(仕入れお小遣い制度)'!$J$4,0) -> 0 | F8: =IF(D8=1,SUM($E$4:E8),0) -> 0 | H8: =IF(D8=1,SUM($G$4:G8),0) -> 0 | I8: =IF(D8=1,F8-H8,0) -> 0 | K8: 45662 | L8: =C8 -> 45662 | M8: =D8 -> 0 | N8: =IF(M8=1,'適正原価率表(仕入れお小遣い制度)'!$J$5,0) -> 0 | O8: =IF(M8=1,SUM($N$4:N8),0) -> 0 | Q8: =IF(M8=1,SUM($P$4:P8),0) -> 0 | R8: =IF(D8=1,O8-Q8,0) -> 0 | T8: =T7+1 -> 45662
B9: =B8+1 -> 45663 | C9: =B9 -> 45663 | D9: =目標_2025R7!D26 -> 0 | E9: =IF(D9=1,'適正原価率表(仕入れお小遣い制度)'!$J$4,0) -> 0 | F9: =IF(D9=1,SUM($E$4:E9),0) -> 0 | H9: =IF(D9=1,SUM($G$4:G9),0) -> 0 | I9: =IF(D9=1,F9-H9,0) -> 0 | K9: 45663 | L9: =C9 -> 45663 | M9: =D9 -> 0 | N9: =IF(M9=1,'適正原価率表(仕入れお小遣い制度)'!$J$5,0) -> 0 | O9: =IF(M9=1,SUM($N$4:N9),0) -> 0 | Q9: =IF(M9=1,SUM($P$4:P9),0) -> 0 | R9: =IF(D9=1,O9-Q9,0) -> 0 | T9: =T8+1 -> 45663
B10: =B9+1 -> 45664 | C10: =B10 -> 45664 | D10: =目標_2025R7!D27 -> 1 | E10: =IF(D10=1,'適正原価率表(仕入れお小遣い制度)'!$J$4,0) -> 11755.81 | F10: =IF(D10=1,SUM($E$4:E10),0) -> 11755.81 | H10: =IF(D10=1,SUM($G$4:G10),0) -> 0 | I10: =IF(D10=1,F10-H10,0) -> 11755.81 | K10: 45664 | L10: =C10 -> 45664 | M10: =D10 -> 1 | N10: =IF(M10=1,'適正原価率表(仕入れお小遣い制度)'!$J$5,0) -> 9688.5663 | O10: =IF(M10=1,SUM($N$4:N10),0) -> 9688.5663 | Q10: =IF(M10=1,SUM($P$4:P10),0) -> 0 | R10: =IF(D10=1,O10-Q10,0) -> 9688.5663 | T10: =T9+1 -> 45664
B11: =B10+1 -> 45665 | C11: =B11 -> 45665 | D11: =目標_2025R7!D28 -> 1 | E11: =IF(D11=1,'適正原価率表(仕入れお小遣い制度)'!$J$4,0) -> 11755.81 | F11: =IF(D11=1,SUM($E$4:E11),0) -> 23511.621 | H11: =IF(D11=1,SUM($G$4:G11),0) -> 0 | I11: =IF(D11=1,F11-H11,0) -> 23511.621 | K11: 45665 | L11: =C11 -> 45665 | M11: =D11 -> 1 | N11: =IF(M11=1,'適正原価率表(仕入れお小遣い制度)'!$J$5,0) -> 9688.5663 | O11: =IF(M11=1,SUM($N$4:N11),0) -> 19377.133 | Q11: =IF(M11=1,SUM($P$4:P11),0) -> 0 | R11: =IF(D11=1,O11-Q11,0) -> 19377.133 | T11: =T10+1 -> 45665
B12: =B11+1 -> 45666 | C12: =B12 -> 45666 | D12: =目標_2025R7!D29 -> 1 | E12: =IF(D12=1,'適正原価率表(仕入れお小遣い制度)'!$J$4,0) -> 11755.81 | F12: =IF(D12=1,SUM($E$4:E12),0) -> 35267.431 | H12: =IF(D12=1,SUM($G$4:G12),0) -> 0 | I12: =IF(D12=1,F12-H12,0) -> 35267.431 | K12: 45666 | L12: =C12 -> 45666 | M12: =D12 -> 1 | N12: =IF(M12=1,'適正原価率表(仕入れお小遣い制度)'!$J$5,0) -> 9688.5663 | O12: =IF(M12=1,SUM($N$4:N12),0) -> 29065.699 | Q12: =IF(M12=1,SUM($P$4:P12),0) -> 0 | R12: =IF(D12=1,O12-Q12,0) -> 29065.699 | T12: =T11+1 -> 45666
B13: =B12+1 -> 45667 | C13: =B13 -> 45667 | D13: =目標_2025R7!D30 -> 1 | E13: =IF(D13=1,'適正原価率表(仕入れお小遣い制度)'!$J$4,0) -> 11755.81 | F13: =IF(D13=1,SUM($E$4:E13),0) -> 47023.241 | H13: =IF(D13=1,SUM($G$4:G13),0) -> 0 | I13: =IF(D13=1,F13-H13,0) -> 47023.241 | K13: 45667 | L13: =C13 -> 45667 | M13: =D13 -> 1 | N13: =IF(M13=1,'適正原価率表(仕入れお小遣い制度)'!$J$5,0) -> 9688.5663 | O13: =IF(M13=1,SUM($N$4:N13),0) -> 38754.265 | Q13: =IF(M13=1,SUM($P$4:P13),0) -> 0 | R13: =IF(D13=1,O13-Q13,0) -> 38754.265 | T13: =T12+1 -> 45667
B14: =B13+1 -> 45668 | C14: =B14 -> 45668 | D14: =目標_2025R7!D31 -> 1 | E14: =IF(D14=1,'適正原価率表(仕入れお小遣い制度)'!$J$4,0) -> 11755.81 | F14: =IF(D14=1,SUM($E$4:E14),0) -> 58779.052 | H14: =IF(D14=1,SUM($G$4:G14),0) -> 0 | I14: =IF(D14=1,F14-H14,0) -> 58779.052 | K14: 45668 | L14: =C14 -> 45668 | M14: =D14 -> 1 | N14: =IF(M14=1,'適正原価率表(仕入れお小遣い制度)'!$J$5,0) -> 9688.5663 | O14: =IF(M14=1,SUM($N$4:N14),0) -> 48442.832 | Q14: =IF(M14=1,SUM($P$4:P14),0) -> 0 | R14: =IF(D14=1,O14-Q14,0) -> 48442.832 | T14: =T13+1 -> 45668
B15: =B14+1 -> 45669 | C15: =B15 -> 45669 | D15: =目標_2025R7!D32 -> 0 | E15: =IF(D15=1,'適正原価率表(仕入れお小遣い制度)'!$J$4,0) -> 0 | F15: =IF(D15=1,SUM($E$4:E15),0) -> 0 | H15: =IF(D15=1,SUM($G$4:G15),0) -> 0 | I15: =IF(D15=1,F15-H15,0) -> 0 | K15: 45669 | L15: =C15 -> 45669 | M15: =D15 -> 0 | N15: =IF(M15=1,'適正原価率表(仕入れお小遣い制度)'!$J$5,0) -> 0 | O15: =IF(M15=1,SUM($N$4:N15),0) -> 0 | Q15: =IF(M15=1,SUM($P$4:P15),0) -> 0 | R15: =IF(D15=1,O15-Q15,0) -> 0 | T15: =T14+1 -> 45669
B16: =B15+1 -> 45670 | C16: =B16 -> 45670 | D16: =目標_2025R7!D33 -> 0 | E16: =IF(D16=1,'適正原価率表(仕入れお小遣い制度)'!$J$4,0) -> 0 | F16: =IF(D16=1,SUM($E$4:E16),0) -> 0 | H16: =IF(D16=1,SUM($G$4:G16),0) -> 0 | I16: =IF(D16=1,F16-H16,0) -> 0 | K16: 45670 | L16: =C16 -> 45670 | M16: =D16 -> 0 | N16: =IF(M16=1,'適正原価率表(仕入れお小遣い制度)'!$J$5,0) -> 0 | O16: =IF(M16=1,SUM($N$4:N16),0) -> 0 | Q16: =IF(M16=1,SUM($P$4:P16),0) -> 0 | R16: =IF(D16=1,O16-Q16,0) -> 0 | T16: =T15+1 -> 45670
... B34: =B33+1 -> 45688 | C34: =B34 -> 45688 | D34: =目標_2025R7!D51 -> 1 | E34: =IF(D34=1,'適正原価率表(仕入れお小遣い制度)'!$J$4,0) -> 11755.81 | F34: =IF(D34=1,SUM($E$4:E34),0) -> 258627.83 | H34: =IF(D34=1,SUM($G$4:G34),0) -> 0 | I34: =IF(D34=1,F34-H34,0) -> 258627.83 | K34: 45688 | L34: =C34 -> 45688 | M34: =D34 -> 1 | N34: =IF(M34=1,'適正原価率表(仕入れお小遣い制度)'!$J$5,0) -> 9688.5663 | O34: =IF(M34=1,SUM($N$4:N34),0) -> 213148.46 | Q34: =IF(M34=1,SUM($P$4:P34),0) -> 0 | R34: =IF(D34=1,O34-Q34,0) -> 213148.46 | T34: =T33+1 -> 45688
B35: 合計 | E35: =SUM(E4:E34) -> 258627.83 | K35: 合計 | N35: =SUM(N4:N34) -> 213148.46
B37: 2月 | E37: フード目標日次 | F37: フード目標累計 | G37: フード実績 | H37: フード累積 | I37: 差額 | K37: =B37 -> 2月 | N37: ドリンク目標日次 | O37: ドリンク目標累計 | P37: ドリンク実績 | Q37: ドリンク累積 | R37: 差額
B38: =B34+1 -> 45689 | C38: =B38 -> 45689 | D38: =目標_2025R7!D52 -> 1 | E38: =IF(D38=1,'適正原価率表(仕入れお小遣い制度)'!$J$6,0) -> 11579.452 | F38: =IF(D38=1,E38,0) -> 11579.452 | H38: =IF(D38=1,G38,0) -> 0 | I38: =IF(D38=1,F38-H38,0) -> 11579.452 | K38: =B38 -> 45689 | L38: =C38 -> 45689 | M38: =D38 -> 1 | N38: =IF(M38=1,'適正原価率表(仕入れお小遣い制度)'!$J$7,0) -> 9806.1383 | O38: =IF(M38=1,N38,0) -> 9806.1383 | Q38: =IF(M38=1,P38,0) -> 0 | R38: =IF(D38=1,O38-Q38,0) -> 9806.1383 | T38: =T34+1 -> 45689
B39: =B38+1 -> 45690 | C39: =B39 -> 45690 | D39: =目標_2025R7!D53 -> 1 | E39: =IF(D39=1,'適正原価率表(仕入れお小遣い制度)'!$J$6,0) -> 11579.452 | F39: =IF(D39=1,SUM($E$38:E39),0) -> 23158.905 | H39: =IF(D39=1,SUM($G$38:G39),0) -> 0 | I39: =IF(D39=1,F39-H39,0) -> 23158.905 | K39: =B39 -> 45690 | L39: =C39 -> 45690 | M39: =D39 -> 1 | N39: =IF(M39=1,'適正原価率表(仕入れお小遣い制度)'!$J$7,0) -> 9806.1383 | O39: =IF(M39=1,SUM($N$38:N39),0) -> 19612.277 | Q39: =IF(M39=1,SUM($P$38:P39),0) -> 0 | R39: =IF(D39=1,O39-Q39,0) -> 19612.277 | T39: =T38+1 -> 45690
B40: =B39+1 -> 45691 | C40: =B40 -> 45691 | D40: =目標_2025R7!D54 -> 0 | E40: =IF(D40=1,'適正原価率表(仕入れお小遣い制度)'!$J$6,0) -> 0 | F40: =IF(D40=1,SUM($E$38:E40),0) -> 0 | H40: =IF(D40=1,SUM($G$38:G40),0) -> 0 | I40: =IF(D40=1,F40-H40,0) -> 0 | K40: =B40 -> 45691 | L40: =C40 -> 45691 | M40: =D40 -> 0 | N40: =IF(M40=1,'適正原価率表(仕入れお小遣い制度)'!$J$7,0) -> 0 | O40: =IF(M40=1,SUM($N$38:N40),0) -> 0 | Q40: =IF(M40=1,SUM($P$38:P40),0) -> 0 | R40: =IF(D40=1,O40-Q40,0) -> 0 | T40: =T39+1 -> 45691
B41: =B40+1 -> 45692 | C41: =B41 -> 45692 | D41: =目標_2025R7!D55 -> 1 | E41: =IF(D41=1,'適正原価率表(仕入れお小遣い制度)'!$J$6,0) -> 11579.452 | F41: =IF(D41=1,SUM($E$38:E41),0) -> 34738.357 | H41: =IF(D41=1,SUM($G$38:G41),0) -> 0 | I41: =IF(D41=1,F41-H41,0) -> 34738.357 | K41: =B41 -> 45692 | L41: =C41 -> 45692 | M41: =D41 -> 1 | N41: =IF(M41=1,'適正原価率表(仕入れお小遣い制度)'!$J$7,0) -> 9806.1383 | O41: =IF(M41=1,SUM($N$38:N41),0) -> 29418.415 | Q41: =IF(M41=1,SUM($P$38:P41),0) -> 0 | R41: =IF(D41=1,O41-Q41,0) -> 29418.415 | T41: =T40+1 -> 45692
B42: =B41+1 -> 45693 | C42: =B42 -> 45693 | D42: =目標_2025R7!D56 -> 1 | E42: =IF(D42=1,'適正原価率表(仕入れお小遣い制度)'!$J$6,0) -> 11579.452 | F42: =IF(D42=1,SUM($E$38:E42),0) -> 46317.809 | H42: =IF(D42=1,SUM($G$38:G42),0) -> 0 | I42: =IF(D42=1,F42-H42,0) -> 46317.809 | K42: =B42 -> 45693 | L42: =C42 -> 45693 | M42: =D42 -> 1 | N42: =IF(M42=1,'適正原価率表(仕入れお小遣い制度)'!$J$7,0) -> 9806.1383 | O42: =IF(M42=1,SUM($N$38:N42),0) -> 39224.553 | Q42: =IF(M42=1,SUM($P$38:P42),0) -> 0 | R42: =IF(D42=1,O42-Q42,0) -> 39224.553 | T42: =T41+1 -> 45693
B43: =B42+1 -> 45694 | C43: =B43 -> 45694 | D43: =目標_2025R7!D57 -> 1 | E43: =IF(D43=1,'適正原価率表(仕入れお小遣い制度)'!$J$6,0) -> 11579.452 | F43: =IF(D43=1,SUM($E$38:E43),0) -> 57897.261 | H43: =IF(D43=1,SUM($G$38:G43),0) -> 0 | I43: =IF(D43=1,F43-H43,0) -> 57897.261 | K43: =B43 -> 45694 | L43: =C43 -> 45694 | M43: =D43 -> 1 | N43: =IF(M43=1,'適正原価率表(仕入れお小遣い制度)'!$J$7,0) -> 9806.1383 | O43: =IF(M43=1,SUM($N$38:N43),0) -> 49030.692 | Q43: =IF(M43=1,SUM($P$38:P43),0) -> 0 | R43: =IF(D43=1,O43-Q43,0) -> 49030.692 | T43: =T42+1 -> 45694
B44: =B43+1 -> 45695 | C44: =B44 -> 45695 | D44: =目標_2025R7!D58 -> 1 | E44: =IF(D44=1,'適正原価率表(仕入れお小遣い制度)'!$J$6,0) -> 11579.452 | F44: =IF(D44=1,SUM($E$38:E44),0) -> 69476.714 | H44: =IF(D44=1,SUM($G$38:G44),0) -> 0 | I44: =IF(D44=1,F44-H44,0) -> 69476.714 | K44: =B44 -> 45695 | L44: =C44 -> 45695 | M44: =D44 -> 1 | N44: =IF(M44=1,'適正原価率表(仕入れお小遣い制度)'!$J$7,0) -> 9806.1383 | O44: =IF(M44=1,SUM($N$38:N44),0) -> 58836.83 | Q44: =IF(M44=1,SUM($P$38:P44),0) -> 0 | R44: =IF(D44=1,O44-Q44,0) -> 58836.83 | T44: =T43+1 -> 45695
B45: =B44+1 -> 45696 | C45: =B45 -> 45696 | D45: =目標_2025R7!D59 -> 1 | E45: =IF(D45=1,'適正原価率表(仕入れお小遣い制度)'!$J$6,0) -> 11579.452 | F45: =IF(D45=1,SUM($E$38:E45),0) -> 81056.166 | H45: =IF(D45=1,SUM($G$38:G45),0) -> 0 | I45: =IF(D45=1,F45-H45,0) -> 81056.166 | K45: =B45 -> 45696 | L45: =C45 -> 45696 | M45: =D45 -> 1 | N45: =IF(M45=1,'適正原価率表(仕入れお小遣い制度)'!$J$7,0) -> 9806.1383 | O45: =IF(M45=1,SUM($N$38:N45),0) -> 68642.968 | Q45: =IF(M45=1,SUM($P$38:P45),0) -> 0 | R45: =IF(D45=1,O45-Q45,0) -> 68642.968 | T45: =T44+1 -> 45696
B46: =B45+1 -> 45697 | C46: =B46 -> 45697 | D46: =目標_2025R7!D60 -> 1 | E46: =IF(D46=1,'適正原価率表(仕入れお小遣い制度)'!$J$6,0) -> 11579.452 | F46: =IF(D46=1,SUM($E$38:E46),0) -> 92635.618 | H46: =IF(D46=1,SUM($G$38:G46),0) -> 0 | I46: =IF(D46=1,F46-H46,0) -> 92635.618 | K46: =B46 -> 45697 | L46: =C46 -> 45697 | M46: =D46 -> 1 | N46: =IF(M46=1,'適正原価率表(仕入れお小遣い制度)'!$J$7,0) -> 9806.1383 | O46: =IF(M46=1,SUM($N$38:N46),0) -> 78449.107 | Q46: =IF(M46=1,SUM($P$38:P46),0) -> 0 | R46: =IF(D46=1,O46-Q46,0) -> 78449.107 | T46: =T45+1 -> 45697
B47: =B46+1 -> 45698 | C47: =B47 -> 45698 | D47: =目標_2025R7!D61 -> 0 | E47: =IF(D47=1,'適正原価率表(仕入れお小遣い制度)'!$J$6,0) -> 0 | F47: =IF(D47=1,SUM($E$38:E47),0) -> 0 | H47: =IF(D47=1,SUM($G$38:G47),0) -> 0 | I47: =IF(D47=1,F47-H47,0) -> 0 | K47: =B47 -> 45698 | L47: =C47 -> 45698 | M47: =D47 -> 0 | N47: =IF(M47=1,'適正原価率表(仕入れお小遣い制度)'!$J$7,0) -> 0 | O47: =IF(M47=1,SUM($N$38:N47),0) -> 0 | Q47: =IF(M47=1,SUM($P$38:P47),0) -> 0 | R47: =IF(D47=1,O47-Q47,0) -> 0 | T47: =T46+1 -> 45698
B48: =B47+1 -> 45699 | C48: =B48 -> 45699 | D48: =目標_2025R7!D62 -> 0 | E48: =IF(D48=1,'適正原価率表(仕入れお小遣い制度)'!$J$6,0) -> 0 | F48: =IF(D48=1,SUM($E$38:E48),0) -> 0 | H48: =IF(D48=1,SUM($G$38:G48),0) -> 0 | I48: =IF(D48=1,F48-H48,0) -> 0 | K48: =B48 -> 45699 | L48: =C48 -> 45699 | M48: =D48 -> 0 | N48: =IF(M48=1,'適正原価率表(仕入れお小遣い制度)'!$J$7,0) -> 0 | O48: =IF(M48=1,SUM($N$38:N48),0) -> 0 | Q48: =IF(M48=1,SUM($P$38:P48),0) -> 0 | R48: =IF(D48=1,O48-Q48,0) -> 0 | T48: =T47+1 -> 45699
B49: =B48+1 -> 45700 | C49: =B49 -> 45700 | D49: =目標_2025R7!D63 -> 1 | E49: =IF(D49=1,'適正原価率表(仕入れお小遣い制度)'!$J$6,0) -> 11579.452 | F49: =IF(D49=1,SUM($E$38:E49),0) -> 104215.07 | H49: =IF(D49=1,SUM($G$38:G49),0) -> 0 | I49: =IF(D49=1,F49-H49,0) -> 104215.07 | K49: =B49 -> 45700 | L49: =C49 -> 45700 | M49: =D49 -> 1 | N49: =IF(M49=1,'適正原価率表(仕入れお小遣い制度)'!$J$7,0) -> 9806.1383 | O49: =IF(M49=1,SUM($N$38:N49),0) -> 88255.245 | Q49: =IF(M49=1,SUM($P$38:P49),0) -> 0 | R49: =IF(D49=1,O49-Q49,0) -> 88255.245 | T49: =T48+1 -> 45700
B50: =B49+1 -> 45701 | C50: =B50 -> 45701 | D50: =目標_2025R7!D64 -> 1 | E50: =IF(D50=1,'適正原価率表(仕入れお小遣い制度)'!$J$6,0) -> 11579.452 | F50: =IF(D50=1,SUM($E$38:E50),0) -> 115794.52 | H50: =IF(D50=1,SUM($G$38:G50),0) -> 0 | I50: =IF(D50=1,F50-H50,0) -> 115794.52 | K50: =B50 -> 45701 | L50: =C50 -> 45701 | M50: =D50 -> 1 | N50: =IF(M50=1,'適正原価率表(仕入れお小遣い制度)'!$J$7,0) -> 9806.1383 | O50: =IF(M50=1,SUM($N$38:N50),0) -> 98061.383 | Q50: =IF(M50=1,SUM($P$38:P50),0) -> 0 | R50: =IF(D50=1,O50-Q50,0) -> 98061.383 | T50: =T49+1 -> 45701
... B65: =B64+1 -> 45716 | C65: =B65 -> 45716 | D65: =目標_2025R7!D79 -> 1 | E65: =IF(D65=1,'適正原価率表(仕入れお小遣い制度)'!$J$6,0) -> 11579.452 | F65: =IF(D65=1,SUM($E$38:E65),0) -> 266327.4 | H65: =IF(D65=1,SUM($G$38:G65),0) -> 0 | I65: =IF(D65=1,F65-H65,0) -> 266327.4 | K65: =B65 -> 45716 | L65: =C65 -> 45716 | M65: =D65 -> 1 | N65: =IF(M65=1,'適正原価率表(仕入れお小遣い制度)'!$J$7,0) -> 9806.1383 | O65: =IF(M65=1,SUM($N$38:N65),0) -> 225541.18 | Q65: =IF(M65=1,SUM($P$38:P65),0) -> 0 | R65: =IF(D65=1,O65-Q65,0) -> 225541.18 | T65: =T64+1 -> 45716
B66: 合計 | E66: =SUM(E38:E65) -> 266327.4 | K66: 合計 | N66: =SUM(N38:N65) -> 225541.18
B68: 3月 | E68: フード目標日次 | F68: フード目標累計 | G68: フード実績 | H68: フード累積 | I68: 差額 | K68: =B68 -> 3月 | N68: ドリンク目標日次 | O68: ドリンク目標累計 | P68: ドリンク実績 | Q68: ドリンク累積 | R68: 差額
B69: =B65+1 -> 45717 | C69: =B69 -> 45717 | D69: =目標_2025R7!D80 -> 1 | E69: =IF(D69=1,'適正原価率表(仕入れお小遣い制度)'!$J$8,0) -> 14371.259 | F69: =IF(D69=1,E69,0) -> 14371.259 | H69: =IF(D69=1,G69,0) -> 0 | I69: =IF(D69=1,F69-H69,0) -> 14371.259 | K69: =B69 -> 45717 | L69: =C69 -> 45717 | M69: =D69 -> 1 | N69: =IF(M69=1,'適正原価率表(仕入れお小遣い制度)'!$J$9,0) -> 11037.717 | O69: =IF(M69=1,N69,0) -> 11037.717 | Q69: =IF(M69=1,P69,0) -> 0 | R69: =IF(D69=1,O69-Q69,0) -> 11037.717 | T69: =T65+1 -> 45717
B70: =B69+1 -> 45718 | C70: =B70 -> 45718 | D70: =目標_2025R7!D81 -> 1 | E70: =IF(D70=1,'適正原価率表(仕入れお小遣い制度)'!$J$8,0) -> 14371.259 | F70: =IF(D70=1,SUM($E$69:E70),0) -> 28742.518 | H70: =IF(D70=1,SUM($G$69:G70),0) -> 0 | I70: =IF(D70=1,F70-H70,0) -> 28742.518 | K70: =B70 -> 45718 | L70: =C70 -> 45718 | M70: =D70 -> 1 | N70: =IF(M70=1,'適正原価率表(仕入れお小遣い制度)'!$J$9,0) -> 11037.717 | O70: =IF(M70=1,SUM($N$69:N70),0) -> 22075.435 | Q70: =IF(M70=1,SUM($P$69:P70),0) -> 0 | R70: =IF(D70=1,O70-Q70,0) -> 22075.435 | T70: =T69+1 -> 45718
B71: =B70+1 -> 45719 | C71: =B71 -> 45719 | D71: =目標_2025R7!D82 -> 0 | E71: =IF(D71=1,'適正原価率表(仕入れお小遣い制度)'!$J$8,0) -> 0 | F71: =IF(D71=1,SUM($E$69:E71),0) -> 0 | H71: =IF(D71=1,SUM($G$69:G71),0) -> 0 | I71: =IF(D71=1,F71-H71,0) -> 0 | K71: =B71 -> 45719 | L71: =C71 -> 45719 | M71: =D71 -> 0 | N71: =IF(M71=1,'適正原価率表(仕入れお小遣い制度)'!$J$9,0) -> 0 | O71: =IF(M71=1,SUM($N$69:N71),0) -> 0 | Q71: =IF(M71=1,SUM($P$69:P71),0) -> 0 | R71: =IF(D71=1,O71-Q71,0) -> 0 | T71: =T70+1 -> 45719
B72: =B71+1 -> 45720 | C72: =B72 -> 45720 | D72: =目標_2025R7!D83 -> 1 | E72: =IF(D72=1,'適正原価率表(仕入れお小遣い制度)'!$J$8,0) -> 14371.259 | F72: =IF(D72=1,SUM($E$69:E72),0) -> 43113.777 | H72: =IF(D72=1,SUM($G$69:G72),0) -> 0 | I72: =IF(D72=1,F72-H72,0) -> 43113.777 | K72: =B72 -> 45720 | L72: =C72 -> 45720 | M72: =D72 -> 1 | N72: =IF(M72=1,'適正原価率表(仕入れお小遣い制度)'!$J$9,0) -> 11037.717 | O72: =IF(M72=1,SUM($N$69:N72),0) -> 33113.152 | Q72: =IF(M72=1,SUM($P$69:P72),0) -> 0 | R72: =IF(D72=1,O72-Q72,0) -> 33113.152 | T72: =T71+1 -> 45720
B73: =B72+1 -> 45721 | C73: =B73 -> 45721 | D73: =目標_2025R7!D84 -> 1 | E73: =IF(D73=1,'適正原価率表(仕入れお小遣い制度)'!$J$8,0) -> 14371.259 | F73: =IF(D73=1,SUM($E$69:E73),0) -> 57485.036 | H73: =IF(D73=1,SUM($G$69:G73),0) -> 0 | I73: =IF(D73=1,F73-H73,0) -> 57485.036 | K73: =B73 -> 45721 | L73: =C73 -> 45721 | M73: =D73 -> 1 | N73: =IF(M73=1,'適正原価率表(仕入れお小遣い制度)'!$J$9,0) -> 11037.717 | O73: =IF(M73=1,SUM($N$69:N73),0) -> 44150.87 | Q73: =IF(M73=1,SUM($P$69:P73),0) -> 0 | R73: =IF(D73=1,O73-Q73,0) -> 44150.87 | T73: =T72+1 -> 45721
B74: =B73+1 -> 45722 | C74: =B74 -> 45722 | D74: =目標_2025R7!D85 -> 1 | E74: =IF(D74=1,'適正原価率表(仕入れお小遣い制度)'!$J$8,0) -> 14371.259 | F74: =IF(D74=1,SUM($E$69:E74),0) -> 71856.295 | H74: =IF(D74=1,SUM($G$69:G74),0) -> 0 | I74: =IF(D74=1,F74-H74,0) -> 71856.295 | K74: =B74 -> 45722 | L74: =C74 -> 45722 | M74: =D74 -> 1 | N74: =IF(M74=1,'適正原価率表(仕入れお小遣い制度)'!$J$9,0) -> 11037.717 | O74: =IF(M74=1,SUM($N$69:N74),0) -> 55188.587 | Q74: =IF(M74=1,SUM($P$69:P74),0) -> 0 | R74: =IF(D74=1,O74-Q74,0) -> 55188.587 | T74: =T73+1 -> 45722
B75: =B74+1 -> 45723 | C75: =B75 -> 45723 | D75: =目標_2025R7!D86 -> 1 | E75: =IF(D75=1,'適正原価率表(仕入れお小遣い制度)'!$J$8,0) -> 14371.259 | F75: =IF(D75=1,SUM($E$69:E75),0) -> 86227.554 | H75: =IF(D75=1,SUM($G$69:G75),0) -> 0 | I75: =IF(D75=1,F75-H75,0) -> 86227.554 | K75: =B75 -> 45723 | L75: =C75 -> 45723 | M75: =D75 -> 1 | N75: =IF(M75=1,'適正原価率表(仕入れお小遣い制度)'!$J$9,0) -> 11037.717 | O75: =IF(M75=1,SUM($N$69:N75),0) -> 66226.304 | Q75: =IF(M75=1,SUM($P$69:P75),0) -> 0 | R75: =IF(D75=1,O75-Q75,0) -> 66226.304 | T75: =T74+1 -> 45723
B76: =B75+1 -> 45724 | C76: =B76 -> 45724 | D76: =目標_2025R7!D87 -> 1 | E76: =IF(D76=1,'適正原価率表(仕入れお小遣い制度)'!$J$8,0) -> 14371.259 | F76: =IF(D76=1,SUM($E$69:E76),0) -> 100598.81 | H76: =IF(D76=1,SUM($G$69:G76),0) -> 0 | I76: =IF(D76=1,F76-H76,0) -> 100598.81 | K76: =B76 -> 45724 | L76: =C76 -> 45724 | M76: =D76 -> 1 | N76: =IF(M76=1,'適正原価率表(仕入れお小遣い制度)'!$J$9,0) -> 11037.717 | O76: =IF(M76=1,SUM($N$69:N76),0) -> 77264.022 | Q76: =IF(M76=1,SUM($P$69:P76),0) -> 0 | R76: =IF(D76=1,O76-Q76,0) -> 77264.022 | T76: =T75+1 -> 45724
B77: =B76+1 -> 45725 | C77: =B77 -> 45725 | D77: =目標_2025R7!D88 -> 1 | E77: =IF(D77=1,'適正原価率表(仕入れお小遣い制度)'!$J$8,0) -> 14371.259 | F77: =IF(D77=1,SUM($E$69:E77),0) -> 114970.07 | H77: =IF(D77=1,SUM($G$69:G77),0) -> 0 | I77: =IF(D77=1,F77-H77,0) -> 114970.07 | K77: =B77 -> 45725 | L77: =C77 -> 45725 | M77: =D77 -> 1 | N77: =IF(M77=1,'適正原価率表(仕入れお小遣い制度)'!$J$9,0) -> 11037.717 | O77: =IF(M77=1,SUM($N$69:N77),0) -> 88301.739 | Q77: =IF(M77=1,SUM($P$69:P77),0) -> 0 | R77: =IF(D77=1,O77-Q77,0) -> 88301.739 | T77: =T76+1 -> 45725
B78: =B77+1 -> 45726 | C78: =B78 -> 45726 | D78: =目標_2025R7!D89 -> 0 | E78: =IF(D78=1,'適正原価率表(仕入れお小遣い制度)'!$J$8,0) -> 0 | F78: =IF(D78=1,SUM($E$69:E78),0) -> 0 | H78: =IF(D78=1,SUM($G$69:G78),0) -> 0 | I78: =IF(D78=1,F78-H78,0) -> 0 | K78: =B78 -> 45726 | L78: =C78 -> 45726 | M78: =D78 -> 0 | N78: =IF(M78=1,'適正原価率表(仕入れお小遣い制度)'!$J$9,0) -> 0 | O78: =IF(M78=1,SUM($N$69:N78),0) -> 0 | Q78: =IF(M78=1,SUM($P$69:P78),0) -> 0 | R78: =IF(D78=1,O78-Q78,0) -> 0 | T78: =T77+1 -> 45726
B79: =B78+1 -> 45727 | C79: =B79 -> 45727 | D79: =目標_2025R7!D90 -> 1 | E79: =IF(D79=1,'適正原価率表(仕入れお小遣い制度)'!$J$8,0) -> 14371.259 | F79: =IF(D79=1,SUM($E$69:E79),0) -> 129341.33 | H79: =IF(D79=1,SUM($G$69:G79),0) -> 0 | I79: =IF(D79=1,F79-H79,0) -> 129341.33 | K79: =B79 -> 45727 | L79: =C79 -> 45727 | M79: =D79 -> 1 | N79: =IF(M79=1,'適正原価率表(仕入れお小遣い制度)'!$J$9,0) -> 11037.717 | O79: =IF(M79=1,SUM($N$69:N79),0) -> 99339.457 | Q79: =IF(M79=1,SUM($P$69:P79),0) -> 0 | R79: =IF(D79=1,O79-Q79,0) -> 99339.457 | T79: =T78+1 -> 45727
B80: =B79+1 -> 45728 | C80: =B80 -> 45728 | D80: =目標_2025R7!D91 -> 1 | E80: =IF(D80=1,'適正原価率表(仕入れお小遣い制度)'!$J$8,0) -> 14371.259 | F80: =IF(D80=1,SUM($E$69:E80),0) -> 143712.59 | H80: =IF(D80=1,SUM($G$69:G80),0) -> 0 | I80: =IF(D80=1,F80-H80,0) -> 143712.59 | K80: =B80 -> 45728 | L80: =C80 -> 45728 | M80: =D80 -> 1 | N80: =IF(M80=1,'適正原価率表(仕入れお小遣い制度)'!$J$9,0) -> 11037.717 | O80: =IF(M80=1,SUM($N$69:N80),0) -> 110377.17 | Q80: =IF(M80=1,SUM($P$69:P80),0) -> 0 | R80: =IF(D80=1,O80-Q80,0) -> 110377.17 | T80: =T79+1 -> 45728
B81: =B80+1 -> 45729 | C81: =B81 -> 45729 | D81: =目標_2025R7!D92 -> 1 | E81: =IF(D81=1,'適正原価率表(仕入れお小遣い制度)'!$J$8,0) -> 14371.259 | F81: =IF(D81=1,SUM($E$69:E81),0) -> 158083.85 | H81: =IF(D81=1,SUM($G$69:G81),0) -> 0 | I81: =IF(D81=1,F81-H81,0) -> 158083.85 | K81: =B81 -> 45729 | L81: =C81 -> 45729 | M81: =D81 -> 1 | N81: =IF(M81=1,'適正原価率表(仕入れお小遣い制度)'!$J$9,0) -> 11037.717 | O81: =IF(M81=1,SUM($N$69:N81),0) -> 121414.89 | Q81: =IF(M81=1,SUM($P$69:P81),0) -> 0 | R81: =IF(D81=1,O81-Q81,0) -> 121414.89 | T81: =T80+1 -> 45729
... B99: =B98+1 -> 45747 | C99: =B99 -> 45747 | D99: =目標_2025R7!D110 -> 0 | E99: =IF(D99=1,'適正原価率表(仕入れお小遣い制度)'!$J$8,0) -> 0 | F99: =IF(D99=1,SUM($E$69:E99),0) -> 0 | H99: =IF(D99=1,SUM($G$69:G99),0) -> 0 | I99: =IF(D99=1,F99-H99,0) -> 0 | K99: =B99 -> 45747 | L99: =C99 -> 45747 | M99: =D99 -> 0 | N99: =IF(M99=1,'適正原価率表(仕入れお小遣い制度)'!$J$9,0) -> 0 | O99: =IF(M99=1,SUM($N$69:N99),0) -> 0 | Q99: =IF(M99=1,SUM($P$69:P99),0) -> 0 | R99: =IF(D99=1,O99-Q99,0) -> 0 | T99: =T98+1 -> 45747
B100: 合計 | E100: =SUM(E69:E99) -> 373652.73 | K100: 合計 | N100: =SUM(N69:N99) -> 286980.65
B102: 4月 | E102: フード目標日次 | F102: フード目標累計 | G102: フード実績 | H102: フード累積 | I102: 差額 | K102: =B102 -> 4月 | N102: ドリンク目標日次 | O102: ドリンク目標累計 | P102: ドリンク実績 | Q102: ドリンク累積 | R102: 差額
B103: =B99+1 -> 45748 | C103: =B103 -> 45748 | D103: =目標_2025R7!D111 -> 1 | E103: =IF(D103=1,'適正原価率表(仕入れお小遣い制度)'!$J$10,0) -> 15534.995 | F103: =IF(D103=1,E103,0) -> 15534.995 | H103: =IF(D103=1,G103,0) -> 0 | I103: =IF(D103=1,F103-H103,0) -> 15534.995 | K103: =B103 -> 45748 | L103: =C103 -> 45748 | M103: =D103 -> 1 | N103: =IF(M103=1,'適正原価率表(仕入れお小遣い制度)'!$J$11,0) -> 12323.749 | O103: =IF(M103=1,N103,0) -> 12323.749 | Q103: =IF(M103=1,P103,0) -> 0 | R103: =IF(D103=1,O103-Q103,0) -> 12323.749 | T103: =T99+1 -> 45748
B104: =B103+1 -> 45749 | C104: =B104 -> 45749 | D104: =目標_2025R7!D112 -> 1 | E104: =IF(D104=1,'適正原価率表(仕入れお小遣い制度)'!$J$10,0) -> 15534.995 | F104: =IF(D104=1,SUM($E$103:E104),0) -> 31069.99 | H104: =IF(D104=1,SUM($G$103:G104),0) -> 0 | I104: =IF(D104=1,F104-H104,0) -> 31069.99 | K104: =B104 -> 45749 | L104: =C104 -> 45749 | M104: =D104 -> 1 | N104: =IF(M104=1,'適正原価率表(仕入れお小遣い制度)'!$J$11,0) -> 12323.749 | O104: =IF(M104=1,SUM($N$103:N104),0) -> 24647.498 | Q104: =IF(M104=1,SUM($P$103:P104),0) -> 0 | R104: =IF(D104=1,O104-Q104,0) -> 24647.498 | T104: =T103+1 -> 45749
B105: =B104+1 -> 45750 | C105: =B105 -> 45750 | D105: =目標_2025R7!D113 -> 1 | E105: =IF(D105=1,'適正原価率表(仕入れお小遣い制度)'!$J$10,0) -> 15534.995 | F105: =IF(D105=1,SUM($E$103:E105),0) -> 46604.986 | H105: =IF(D105=1,SUM($G$103:G105),0) -> 0 | I105: =IF(D105=1,F105-H105,0) -> 46604.986 | K105: =B105 -> 45750 | L105: =C105 -> 45750 | M105: =D105 -> 1 | N105: =IF(M105=1,'適正原価率表(仕入れお小遣い制度)'!$J$11,0) -> 12323.749 | O105: =IF(M105=1,SUM($N$103:N105),0) -> 36971.247 | Q105: =IF(M105=1,SUM($P$103:P105),0) -> 0 | R105: =IF(D105=1,O105-Q105,0) -> 36971.247 | T105: =T104+1 -> 45750
B106: =B105+1 -> 45751 | C106: =B106 -> 45751 | D106: =目標_2025R7!D114 -> 1 | E106: =IF(D106=1,'適正原価率表(仕入れお小遣い制度)'!$J$10,0) -> 15534.995 | F106: =IF(D106=1,SUM($E$103:E106),0) -> 62139.981 | H106: =IF(D106=1,SUM($G$103:G106),0) -> 0 | I106: =IF(D106=1,F106-H106,0) -> 62139.981 | K106: =B106 -> 45751 | L106: =C106 -> 45751 | M106: =D106 -> 1 | N106: =IF(M106=1,'適正原価率表(仕入れお小遣い制度)'!$J$11,0) -> 12323.749 | O106: =IF(M106=1,SUM($N$103:N106),0) -> 49294.996 | Q106: =IF(M106=1,SUM($P$103:P106),0) -> 0 | R106: =IF(D106=1,O106-Q106,0) -> 49294.996 | T106: =T105+1 -> 45751
B107: =B106+1 -> 45752 | C107: =B107 -> 45752 | D107: =目標_2025R7!D115 -> 1 | E107: =IF(D107=1,'適正原価率表(仕入れお小遣い制度)'!$J$10,0) -> 15534.995 | F107: =IF(D107=1,SUM($E$103:E107),0) -> 77674.976 | H107: =IF(D107=1,SUM($G$103:G107),0) -> 0 | I107: =IF(D107=1,F107-H107,0) -> 77674.976 | K107: =B107 -> 45752 | L107: =C107 -> 45752 | M107: =D107 -> 1 | N107: =IF(M107=1,'適正原価率表(仕入れお小遣い制度)'!$J$11,0) -> 12323.749 | O107: =IF(M107=1,SUM($N$103:N107),0) -> 61618.745 | Q107: =IF(M107=1,SUM($P$103:P107),0) -> 0 | R107: =IF(D107=1,O107-Q107,0) -> 61618.745 | T107: =T106+1 -> 45752
B108: =B107+1 -> 45753 | C108: =B108 -> 45753 | D108: =目標_2025R7!D116 -> 1 | E108: =IF(D108=1,'適正原価率表(仕入れお小遣い制度)'!$J$10,0) -> 15534.995 | F108: =IF(D108=1,SUM($E$103:E108),0) -> 93209.971 | H108: =IF(D108=1,SUM($G$103:G108),0) -> 0 | I108: =IF(D108=1,F108-H108,0) -> 93209.971 | K108: =B108 -> 45753 | L108: =C108 -> 45753 | M108: =D108 -> 1 | N108: =IF(M108=1,'適正原価率表(仕入れお小遣い制度)'!$J$11,0) -> 12323.749 | O108: =IF(M108=1,SUM($N$103:N108),0) -> 73942.493 | Q108: =IF(M108=1,SUM($P$103:P108),0) -> 0 | R108: =IF(D108=1,O108-Q108,0) -> 73942.493 | T108: =T107+1 -> 45753
B109: =B108+1 -> 45754 | C109: =B109 -> 45754 | D109: =目標_2025R7!D117 -> 0 | E109: =IF(D109=1,'適正原価率表(仕入れお小遣い制度)'!$J$10,0) -> 0 | F109: =IF(D109=1,SUM($E$103:E109),0) -> 0 | H109: =IF(D109=1,SUM($G$103:G109),0) -> 0 | I109: =IF(D109=1,F109-H109,0) -> 0 | K109: =B109 -> 45754 | L109: =C109 -> 45754 | M109: =D109 -> 0 | N109: =IF(M109=1,'適正原価率表(仕入れお小遣い制度)'!$J$11,0) -> 0 | O109: =IF(M109=1,SUM($N$103:N109),0) -> 0 | Q109: =IF(M109=1,SUM($P$103:P109),0) -> 0 | R109: =IF(D109=1,O109-Q109,0) -> 0 | T109: =T108+1 -> 45754
B110: =B109+1 -> 45755 | C110: =B110 -> 45755 | D110: =目標_2025R7!D118 -> 1 | E110: =IF(D110=1,'適正原価率表(仕入れお小遣い制度)'!$J$10,0) -> 15534.995 | F110: =IF(D110=1,SUM($E$103:E110),0) -> 108744.97 | H110: =IF(D110=1,SUM($G$103:G110),0) -> 0 | I110: =IF(D110=1,F110-H110,0) -> 108744.97 | K110: =B110 -> 45755 | L110: =C110 -> 45755 | M110: =D110 -> 1 | N110: =IF(M110=1,'適正原価率表(仕入れお小遣い制度)'!$J$11,0) -> 12323.749 | O110: =IF(M110=1,SUM($N$103:N110),0) -> 86266.242 | Q110: =IF(M110=1,SUM($P$103:P110),0) -> 0 | R110: =IF(D110=1,O110-Q110,0) -> 86266.242 | T110: =T109+1 -> 45755
B111: =B110+1 -> 45756 | C111: =B111 -> 45756 | D111: =目標_2025R7!D119 -> 1 | E111: =IF(D111=1,'適正原価率表(仕入れお小遣い制度)'!$J$10,0) -> 15534.995 | F111: =IF(D111=1,SUM($E$103:E111),0) -> 124279.96 | H111: =IF(D111=1,SUM($G$103:G111),0) -> 0 | I111: =IF(D111=1,F111-H111,0) -> 124279.96 | K111: =B111 -> 45756 | L111: =C111 -> 45756 | M111: =D111 -> 1 | N111: =IF(M111=1,'適正原価率表(仕入れお小遣い制度)'!$J$11,0) -> 12323.749 | O111: =IF(M111=1,SUM($N$103:N111),0) -> 98589.991 | Q111: =IF(M111=1,SUM($P$103:P111),0) -> 0 | R111: =IF(D111=1,O111-Q111,0) -> 98589.991 | T111: =T110+1 -> 45756
B112: =B111+1 -> 45757 | C112: =B112 -> 45757 | D112: =目標_2025R7!D120 -> 1 | E112: =IF(D112=1,'適正原価率表(仕入れお小遣い制度)'!$J$10,0) -> 15534.995 | F112: =IF(D112=1,SUM($E$103:E112),0) -> 139814.96 | H112: =IF(D112=1,SUM($G$103:G112),0) -> 0 | I112: =IF(D112=1,F112-H112,0) -> 139814.96 | K112: =B112 -> 45757 | L112: =C112 -> 45757 | M112: =D112 -> 1 | N112: =IF(M112=1,'適正原価率表(仕入れお小遣い制度)'!$J$11,0) -> 12323.749 | O112: =IF(M112=1,SUM($N$103:N112),0) -> 110913.74 | Q112: =IF(M112=1,SUM($P$103:P112),0) -> 0 | R112: =IF(D112=1,O112-Q112,0) -> 110913.74 | T112: =T111+1 -> 45757
B113: =B112+1 -> 45758 | C113: =B113 -> 45758 | D113: =目標_2025R7!D121 -> 1 | E113: =IF(D113=1,'適正原価率表(仕入れお小遣い制度)'!$J$10,0) -> 15534.995 | F113: =IF(D113=1,SUM($E$103:E113),0) -> 155349.95 | H113: =IF(D113=1,SUM($G$103:G113),0) -> 0 | I113: =IF(D113=1,F113-H113,0) -> 155349.95 | K113: =B113 -> 45758 | L113: =C113 -> 45758 | M113: =D113 -> 1 | N113: =IF(M113=1,'適正原価率表(仕入れお小遣い制度)'!$J$11,0) -> 12323.749 | O113: =IF(M113=1,SUM($N$103:N113),0) -> 123237.49 | Q113: =IF(M113=1,SUM($P$103:P113),0) -> 0 | R113: =IF(D113=1,O113-Q113,0) -> 123237.49 | T113: =T112+1 -> 45758
B114: =B113+1 -> 45759 | C114: =B114 -> 45759 | D114: =目標_2025R7!D122 -> 1 | E114: =IF(D114=1,'適正原価率表(仕入れお小遣い制度)'!$J$10,0) -> 15534.995 | F114: =IF(D114=1,SUM($E$103:E114),0) -> 170884.95 | H114: =IF(D114=1,SUM($G$103:G114),0) -> 0 | I114: =IF(D114=1,F114-H114,0) -> 170884.95 | K114: =B114 -> 45759 | L114: =C114 -> 45759 | M114: =D114 -> 1 | N114: =IF(M114=1,'適正原価率表(仕入れお小遣い制度)'!$J$11,0) -> 12323.749 | O114: =IF(M114=1,SUM($N$103:N114),0) -> 135561.24 | Q114: =IF(M114=1,SUM($P$103:P114),0) -> 0 | R114: =IF(D114=1,O114-Q114,0) -> 135561.24 | T114: =T113+1 -> 45759
B115: =B114+1 -> 45760 | C115: =B115 -> 45760 | D115: =目標_2025R7!D123 -> 1 | E115: =IF(D115=1,'適正原価率表(仕入れお小遣い制度)'!$J$10,0) -> 15534.995 | F115: =IF(D115=1,SUM($E$103:E115),0) -> 186419.94 | H115: =IF(D115=1,SUM($G$103:G115),0) -> 0 | I115: =IF(D115=1,F115-H115,0) -> 186419.94 | K115: =B115 -> 45760 | L115: =C115 -> 45760 | M115: =D115 -> 1 | N115: =IF(M115=1,'適正原価率表(仕入れお小遣い制度)'!$J$11,0) -> 12323.749 | O115: =IF(M115=1,SUM($N$103:N115),0) -> 147884.99 | Q115: =IF(M115=1,SUM($P$103:P115),0) -> 0 | R115: =IF(D115=1,O115-Q115,0) -> 147884.99 | T115: =T114+1 -> 45760
... B132: =B131+1 -> 45777 | C132: =B132 -> 45777 | D132: =目標_2025R7!D140 -> 1 | E132: =IF(D132=1,'適正原価率表(仕入れお小遣い制度)'!$J$10,0) -> 15534.995 | F132: =IF(D132=1,SUM($E$103:E132),0) -> 388374.88 | H132: =IF(D132=1,SUM($G$103:G132),0) -> 0 | I132: =IF(D132=1,F132-H132,0) -> 388374.88 | K132: =B132 -> 45777 | L132: =C132 -> 45777 | M132: =D132 -> 1 | N132: =IF(M132=1,'適正原価率表(仕入れお小遣い制度)'!$J$11,0) -> 12323.749 | O132: =IF(M132=1,SUM($N$103:N132),0) -> 308093.72 | Q132: =IF(M132=1,SUM($P$103:P132),0) -> 0 | R132: =IF(D132=1,O132-Q132,0) -> 308093.72 | T132: =T131+1 -> 45777
B133: 合計 | E133: =SUM(E103:E132) -> 388374.88 | K133: 合計 | N133: =SUM(N103:N132) -> 308093.72
B135: 5 | E135: フード目標日次 | F135: フード目標累計 | G135: フード実績 | H135: フード累積 | I135: 差額 | K135: =B135 -> 5 | N135: ドリンク目標日次 | O135: ドリンク目標累計 | P135: ドリンク実績 | Q135: ドリンク累積 | R135: 差額
B136: =B132+1 -> 45778 | C136: =B136 -> 45778 | D136: =目標_2025R7!D141 -> 1 | E136: =IF(D136=1,'適正原価率表(仕入れお小遣い制度)'!$J$12,0) -> 13486.809 | F136: =IF(D136=1,E136,0) -> 13486.809 | G136: 31875 | H136: =IF(D136=1,G136,0) -> 31875 | I136: =IF(D136=1,F136-H136,0) -> -18388.191 | K136: =B136 -> 45778 | L136: =C136 -> 45778 | M136: =D136 -> 1 | N136: =IF(M136=1,'適正原価率表(仕入れお小遣い制度)'!$J$13,0) -> 11627.351 | O136: =IF(M136=1,N136,0) -> 11627.351 | P136: 0 | Q136: =IF(M136=1,P136,0) -> 0 | R136: =IF(D136=1,O136-Q136,0) -> 11627.351 | T136: =T132+1 -> 45778
B137: =B136+1 -> 45779 | C137: =B137 -> 45779 | D137: =目標_2025R7!D142 -> 1 | E137: =IF(D137=1,'適正原価率表(仕入れお小遣い制度)'!$J$12,0) -> 13486.809 | F137: =IF(D137=1,SUM($E$136:E137),0) -> 26973.618 | G137: 14971 | H137: =IF(D137=1,SUM($G$136:G137),0) -> 46846 | I137: =IF(D137=1,F137-H137,0) -> -19872.382 | K137: =B137 -> 45779 | L137: =C137 -> 45779 | M137: =D137 -> 1 | N137: =IF(M137=1,'適正原価率表(仕入れお小遣い制度)'!$J$13,0) -> 11627.351 | O137: =IF(M137=1,SUM($N$136:N137),0) -> 23254.701 | P137: 0 | Q137: =IF(M137=1,SUM($P$136:P137),0) -> 0 | R137: =IF(D137=1,O137-Q137,0) -> 23254.701 | T137: =T136+1 -> 45779
B138: =B137+1 -> 45780 | C138: =B138 -> 45780 | D138: =目標_2025R7!D143 -> 1 | E138: =IF(D138=1,'適正原価率表(仕入れお小遣い制度)'!$J$12,0) -> 13486.809 | F138: =IF(D138=1,SUM($E$136:E138),0) -> 40460.427 | G138: 3404 | H138: =IF(D138=1,SUM($G$136:G138),0) -> 50250 | I138: =IF(D138=1,F138-H138,0) -> -9789.5732 | K138: =B138 -> 45780 | L138: =C138 -> 45780 | M138: =D138 -> 1 | N138: =IF(M138=1,'適正原価率表(仕入れお小遣い制度)'!$J$13,0) -> 11627.351 | O138: =IF(M138=1,SUM($N$136:N138),0) -> 34882.052 | P138: 0 | Q138: =IF(M138=1,SUM($P$136:P138),0) -> 0 | R138: =IF(D138=1,O138-Q138,0) -> 34882.052 | T138: =T137+1 -> 45780
B139: =B138+1 -> 45781 | C139: =B139 -> 45781 | D139: =目標_2025R7!D144 -> 1 | E139: =IF(D139=1,'適正原価率表(仕入れお小遣い制度)'!$J$12,0) -> 13486.809 | F139: =IF(D139=1,SUM($E$136:E139),0) -> 53947.236 | G139: 14848 | H139: =IF(D139=1,SUM($G$136:G139),0) -> 65098 | I139: =IF(D139=1,F139-H139,0) -> -11150.764 | K139: =B139 -> 45781 | L139: =C139 -> 45781 | M139: =D139 -> 1 | N139: =IF(M139=1,'適正原価率表(仕入れお小遣い制度)'!$J$13,0) -> 11627.351 | O139: =IF(M139=1,SUM($N$136:N139),0) -> 46509.403 | P139: 0 | Q139: =IF(M139=1,SUM($P$136:P139),0) -> 0 | R139: =IF(D139=1,O139-Q139,0) -> 46509.403 | T139: =T138+1 -> 45781
B140: =B139+1 -> 45782 | C140: =B140 -> 45782 | D140: =目標_2025R7!D145 -> 0 | E140: =IF(D140=1,'適正原価率表(仕入れお小遣い制度)'!$J$12,0) -> 0 | F140: =IF(D140=1,SUM($E$136:E140),0) -> 0 | G140: 0 | H140: =IF(D140=1,SUM($G$136:G140),0) -> 0 | I140: =IF(D140=1,F140-H140,0) -> 0 | K140: =B140 -> 45782 | L140: =C140 -> 45782 | M140: =D140 -> 0 | N140: =IF(M140=1,'適正原価率表(仕入れお小遣い制度)'!$J$13,0) -> 0 | O140: =IF(M140=1,SUM($N$136:N140),0) -> 0 | P140: 0 | Q140: =IF(M140=1,SUM($P$136:P140),0) -> 0 | R140: =IF(D140=1,O140-Q140,0) -> 0 | T140: =T139+1 -> 45782
B141: =B140+1 -> 45783 | C141: =B141 -> 45783 | D141: =目標_2025R7!D146 -> 0 | E141: =IF(D141=1,'適正原価率表(仕入れお小遣い制度)'!$J$12,0) -> 0 | F141: =IF(D141=1,SUM($E$136:E141),0) -> 0 | G141: 0 | H141: =IF(D141=1,SUM($G$136:G141),0) -> 0 | I141: =IF(D141=1,F141-H141,0) -> 0 | K141: =B141 -> 45783 | L141: =C141 -> 45783 | M141: =D141 -> 0 | N141: =IF(M141=1,'適正原価率表(仕入れお小遣い制度)'!$J$13,0) -> 0 | O141: =IF(M141=1,SUM($N$136:N141),0) -> 0 | P141: 0 | Q141: =IF(M141=1,SUM($P$136:P141),0) -> 0 | R141: =IF(D141=1,O141-Q141,0) -> 0 | T141: =T140+1 -> 45783
B142: =B141+1 -> 45784 | C142: =B142 -> 45784 | D142: =目標_2025R7!D147 -> 1 | E142: =IF(D142=1,'適正原価率表(仕入れお小遣い制度)'!$J$12,0) -> 13486.809 | F142: =IF(D142=1,SUM($E$136:E142),0) -> 67434.045 | G142: 3793 | H142: =IF(D142=1,SUM($G$136:G142),0) -> 68891 | I142: =IF(D142=1,F142-H142,0) -> -1456.9553 | K142: =B142 -> 45784 | L142: =C142 -> 45784 | M142: =D142 -> 1 | N142: =IF(M142=1,'適正原価率表(仕入れお小遣い制度)'!$J$13,0) -> 11627.351 | O142: =IF(M142=1,SUM($N$136:N142),0) -> 58136.754 | P142: 508 | Q142: =IF(M142=1,SUM($P$136:P142),0) -> 508 | R142: =IF(D142=1,O142-Q142,0) -> 57628.754 | T142: =T141+1 -> 45784
B143: =B142+1 -> 45785 | C143: =B143 -> 45785 | D143: =目標_2025R7!D148 -> 1 | E143: =IF(D143=1,'適正原価率表(仕入れお小遣い制度)'!$J$12,0) -> 13486.809 | F143: =IF(D143=1,SUM($E$136:E143),0) -> 80920.854 | G143: 23120 | H143: =IF(D143=1,SUM($G$136:G143),0) -> 92011 | I143: =IF(D143=1,F143-H143,0) -> -11090.146 | K143: =B143 -> 45785 | L143: =C143 -> 45785 | M143: =D143 -> 1 | N143: =IF(M143=1,'適正原価率表(仕入れお小遣い制度)'!$J$13,0) -> 11627.351 | O143: =IF(M143=1,SUM($N$136:N143),0) -> 69764.104 | P143: 0 | Q143: =IF(M143=1,SUM($P$136:P143),0) -> 508 | R143: =IF(D143=1,O143-Q143,0) -> 69256.104 | T143: =T142+1 -> 45785
B144: =B143+1 -> 45786 | C144: =B144 -> 45786 | D144: =目標_2025R7!D149 -> 1 | E144: =IF(D144=1,'適正原価率表(仕入れお小遣い制度)'!$J$12,0) -> 13486.809 | F144: =IF(D144=1,SUM($E$136:E144),0) -> 94407.663 | G144: 7561 | H144: =IF(D144=1,SUM($G$136:G144),0) -> 99572 | I144: =IF(D144=1,F144-H144,0) -> -5164.3374 | K144: =B144 -> 45786 | L144: =C144 -> 45786 | M144: =D144 -> 1 | N144: =IF(M144=1,'適正原価率表(仕入れお小遣い制度)'!$J$13,0) -> 11627.351 | O144: =IF(M144=1,SUM($N$136:N144),0) -> 81391.455 | P144: 0 | Q144: =IF(M144=1,SUM($P$136:P144),0) -> 508 | R144: =IF(D144=1,O144-Q144,0) -> 80883.455 | T144: =T143+1 -> 45786
